Workbook

Sheet MON
A1: B2 Daily Report
A2: 26-09-2022 | H2: WEATHER | J2: CLOUDY | L2: REPORT BY | O2: JOHN | R2: TOTAL STAFF | T2: 4 | X2: Merchant machine usage at B2 | AA2: Settle amount | AI2: Merchant machine usage at GA | AL2: Settle amount
A4: No | B4: Docket No | C4: Reg No | D4: Mobile | E4: Gender | F4: TIME | G4: Service | H4: CASH | I4: CARD | J4: RSL | K4: GV | L4: GV CASH | M4: GV CARD | N4: O/Taker | O4: Comment | R4: NAME | S4: Time In | T4: Time out | U4: Total Hours | Z4: B2 machine | AA4: BLH machine | AB4: Wongo | AE4: B2 machine | AF4: BLH machine | AG4: Wongo | AK4: GA machine | AL4: BLH machine | AM4: Wongo | AP4: GA machine | AQ4: BLH machine | AR4: Wongo
A5: 1 | B5: 11340 | C5: ETO68M | D5: 0431133102 | E5: M | F5: 930 | G5: X | I5: 95.95 | J5: =IF(G5="RSL","55","0") -> 0 | K5: =IF(G5="GVS","37.5",IF(G5="GVM","41.5",IF(G5="GVL","50",IF(G5="PCS","45.8",IF(G5="PCM","50",IF(G5="PCL","58.3","0")))))) -> 0 | N5: JOHN | R5: JOHN | S5: 0.35416667 | T5: 0.75 | U5: =(T5-S5)*24 -> 9.5 | X5: NOV | Y5: 1 | AD5: 16 | AI5: NOV | AJ5: 1 | AO5: 16
A6: 2 | B6: 11341 | C6: CKC333 | D6: 0411889693 | E6: M | F6: 925 | G6: RSL | J6: =IF(G6="RSL","55","0") -> 55 | K6: =IF(G6="GVS","37.5",IF(G6="GVM","41.5",IF(G6="GVL","50",IF(G6="PCS","45.8",IF(G6="PCM","50",IF(G6="PCL","58.3","0")))))) -> 0 | N6: JOHN | O6: 202208028(D) | R6: JUNIOR | S6: 0.33333333 | T6: 0.625 | U6: =(T6-S6)*24 -> 7 | W6: M | Y6: 2 | AD6: 17 | AJ6: 2 | AO6: 17
A7: 3 | B7: 11342 | C7: EQE97F | D7: 0455222481 | E7: M | F7: 950 | G7: X | I7: 95 | J7: =IF(G7="RSL","55","0") -> 0 | K7: =IF(G7="GVS","37.5",IF(G7="GVM","41.5",IF(G7="GVL","50",IF(G7="PCS","45.8",IF(G7="PCM","50",IF(G7="PCL","58.3","0")))))) -> 0 | N7: JOHN | R7: KUROSH | S7: 0.41666667 | T7: 0.75 | U7: =(T7-S7)*24 -> 8 | W7: F | Y7: 3 | AD7: 18 | AJ7: 3 | AO7: 18
A8: 4 | B8: 11343 | C8: NJC126 | D8: 0413570413 | E8: F | F8: 1005 | G8: X/ST | H8: 180 | J8: =IF(G8="RSL","55","0") -> 0 | K8: =IF(G8="GVS","37.5",IF(G8="GVM","41.5",IF(G8="GVL","50",IF(G8="PCS","45.8",IF(G8="PCM","50",IF(G8="PCL","58.3","0")))))) -> 0 | N8: JOHN | R8: VINNY | S8: 0.45833333 | T8: 0.71875 | U8: =(T8-S8)*24 -> 6.25 | Y8: 4 | AD8: 19 | AJ8: 4 | AO8: 19
A9: 5 | B9: 11344 | C9: ETJ04Y | D9: 0450603985 | E9: M | F9: 1030 | G9: RSL | H9: 20 | J9: =IF(G9="RSL","55","0") -> 55 | K9: =IF(G9="GVS","37.5",IF(G9="GVM","41.5",IF(G9="GVL","50",IF(G9="PCS","45.8",IF(G9="PCM","50",IF(G9="PCL","58.3","0")))))) -> 0 | N9: JOHN | O9: 202207033(D) | R9: ANDREW OCTEC | S9: 0.58333333 | T9: 0.70833333 | U9: =(T9-S9)*24 -> 3 | X9: EXCL RSL | Y9: 5 | AD9: 20 | AJ9: 5 | AO9: 20
A10: 6 | B10: 11345 | C10: EDW62A | D10: 0412928722 | E10: F | F10: 1045 | G10: X | H10: 75 | J10: =IF(G10="RSL","55","0") -> 0 | K10: =IF(G10="GVS","37.5",IF(G10="GVM","41.5",IF(G10="GVL","50",IF(G10="PCS","45.8",IF(G10="PCM","50",IF(G10="PCL","58.3","0")))))) -> 0 | N10: JOHN | R10: HEATHER | S10: 0.70833333 | T10: 0.72916667 | U10: =(T10-S10)*24 -> 0.5 | Y10: 6 | AD10: 21 | AJ10: 6 | AO10: 21
A11: 7 | B11: 11346 | C11: EJD71Q | D11: 0402545603 | E11: M | F11: 1050 | G11: H | H11: 130 | J11: =IF(G11="RSL","55","0") -> 0 | K11: =IF(G11="GVS","37.5",IF(G11="GVM","41.5",IF(G11="GVL","50",IF(G11="PCS","45.8",IF(G11="PCM","50",IF(G11="PCL","58.3","0")))))) -> 0 | N11: JOHN | R11: JAIKE | S11: 0.70833333 | T11: 0.72916667 | U11: =(T11-S11)*24 -> 0.5 | Y11: 7 | AD11: 22 | AJ11: 7 | AO11: 22
A12: 8 | B12: 11347 | C12: EQI04P | D12: 0432839662 | E12: F | F12: 1100 | G12: H | H12: 150 | J12: =IF(G12="RSL","55","0") -> 0 | K12: =IF(G12="GVS","37.5",IF(G12="GVM","41.5",IF(G12="GVL","50",IF(G12="PCS","45.8",IF(G12="PCM","50",IF(G12="PCL","58.3","0")))))) -> 0 | N12: JOHN | R12: KAMAL | S12: 0.70833333 | T12: 0.72916667 | U12: =(T12-S12)*24 -> 0.5 | Y12: 8 | AD12: 23 | AJ12: 8 | AO12: 23
A13: 9 | B13: 11348 | C13: EOW31B | D13: 0400902477 | E13: F | F13: 1130 | G13: H | I13: 150 | J13: =IF(G13="RSL","55","0") -> 0 | K13: =IF(G13="GVS","37.5",IF(G13="GVM","41.5",IF(G13="GVL","50",IF(G13="PCS","45.8",IF(G13="PCM","50",IF(G13="PCL","58.3","0")))))) -> 0 | N13: JOHN | U13: =(T13-S13)*24 -> 0 | Y13: 9 | AD13: 24 | AJ13: 9 | AO13: 24
A14: 10 | B14: 11349 | C14: EPN52F | D14: 0419716479 | E14: F | F14: 1200 | G14: X/LEATHER | I14: 180 | J14: =IF(G14="RSL","55","0") -> 0 | K14: =IF(G14="GVS","37.5",IF(G14="GVM","41.5",IF(G14="GVL","50",IF(G14="PCS","45.8",IF(G14="PCM","50",IF(G14="PCL","58.3","0")))))) -> 0 | N14: JOHN | O14: BACK SEAT LEATHER CLEAN | U14: =(T14-S14)*24 -> 0 | Y14: 10 | AD14: 25 | AJ14: 10 | AO14: 25
A15: 11 | B15: 11350 | C15: NRF289 | D15: 0416490500 | E15: M | F15: 1210 | G15: X | H15: 95 | J15: =IF(G15="RSL","55","0") -> 0 | K15: =IF(G15="GVS","37.5",IF(G15="GVM","41.5",IF(G15="GVL","50",IF(G15="PCS","45.8",IF(G15="PCM","50",IF(G15="PCL","58.3","0")))))) -> 0 | N15: JOHN | U15: =(T15-S15)*24 -> 0 | Y15: 11 | AD15: 26 | AJ15: 11 | AO15: 26
A16: 12 | B16: 11351 | C16: DGH46A | D16: 04306868 | E16: F | F16: 1315 | G16: D | I16: 75 | J16: 0 | K16: =IF(G16="GVS","37.5",IF(G16="GVM","41.5",IF(G16="GVL","50",IF(G16="PCS","45.8",IF(G16="PCM","50",IF(G16="PCL","58.3","0")))))) -> 0 | N16: JOHN | R16: =H32/U16 -> 0.5106383 | S16: =H32/(U16-U5) -> 0.69902913 | T16: =C32/U16 -> 68.281135 | U16: =SUM(U5:U15) -> 35.25 | Y16: 12 | AD16: 27 | AJ16: 12 | AO16: 27
A17: 13 | B17: 11352 | C17: WBB | D17: 0456043888 | E17: F | F17: 1400 | G17: RSL | H17: 20 | J17: =IF(G17="RSL","55","0") -> 55 | K17: =IF(G17="GVS","37.5",IF(G17="GVM","41.5",IF(G17="GVL","50",IF(G17="PCS","45.8",IF(G17="PCM","50",IF(G17="PCL","58.3","0")))))) -> 0 | N17: JOHN | O17: 202208009(D) | R17: Cars/T Hr ① | S17: Cars/T Hr ② | T17: Sales/T Hr | U17: Total Hours | Y17: 13 | AD17: 28 | AJ17: 13 | AO17: 28
A18: 14 | B18: 11353 | C18: CWB80V | D18: 0416163888 | E18: F | F18: 1400 | G18: RSL | J18: =IF(G18="RSL","55","0") -> 55 | K18: =IF(G18="GVS","37.5",IF(G18="GVM","41.5",IF(G18="GVL","50",IF(G18="PCS","45.8",IF(G18="PCM","50",IF(G18="PCL","58.3","0")))))) -> 0 | N18: JOHN | O18: 202208109(D) | R18: ITEM | S18: QTY | T18: AMT | U18: RMKS | Y18: 14 | AD18: 29 | AJ18: 14 | AO18: 29
A19: 15 | B19: 11354 | C19: B289XR | D19: 0425290116 | E19: F | F19: 1435 | G19: D | I19: 55 | J19: =IF(G19="RSL","55","0") -> 0 | K19: =IF(G19="GVS","37.5",IF(G19="GVM","41.5",IF(G19="GVL","50",IF(G19="PCS","45.8",IF(G19="PCM","50",IF(G19="PCL","58.3","0")))))) -> 0 | N19: JOHN | R19: GV | S19: =COUNT(L5:M29,L37:M61,L69:M93) -> 0 | T19: =SUM(L5:M29,L37:M61,L69:M93) -> 0 | Y19: 15 | AD19: 30 | AJ19: 15 | AO19: 30
A20: 16 | B20: 11355 | C20: HH030 | D20: 0421332492 | E20: M | F20: 1500 | G20: PCL | J20: =IF(G20="RSL","55","0") -> 0 | K20: 79.16 | N20: JOHN | O20: 22066(2/6) (X) | AD20: 31 | AO20: 31
A21: 17 | B21: 11356 | C21: LAU777 | D21: 0416462000 | E21: F | F21: 1500 | G21: PCS | J21: =IF(G21="RSL","55","0") -> 0 | K21: 100 | N21: JOHN | O21: 22037(3/6) (H)
A22: 18 | B22: 11357 | C22: SUNG | D22: 0428881889 | E22: F | F22: 1550 | G22: F/D | I22: 686.8 | J22: =IF(G22="RSL","55","0") -> 0 | K22: =IF(G22="GVS","37.5",IF(G22="GVM","41.5",IF(G22="GVL","50",IF(G22="PCS","45.8",IF(G22="PCM","50",IF(G22="PCL","58.3","0")))))) -> 0 | N22: JOHN | AD22: Total | AE22: =SUM(Z5:Z19,AE5:AE20) -> 0 | AF22: =SUM(AA5:AA19,AF5:AF20,) -> 0 | AG22: =SUM(AB5:AB19,AG5:AG20) -> 0 | AO22: Total | AP22: =SUM(AK5:AK19,AP5:AP20) -> 0 | AQ22: =SUM(AL5:AL19,AQ5:AQ20,) -> 0 | AR22: =SUM(AM5:AM19,AR5:AR20) -> 0
A23: 19 | J23: =IF(G23="RSL","55","0") -> 0 | K23: =IF(G23="GVS","37.5",IF(G23="GVM","41.5",IF(G23="GVL","50",IF(G23="PCS","45.8",IF(G23="PCM","50",IF(G23="PCL","58.3","0")))))) -> 0
A24: 20 | J24: =IF(G24="RSL","55","0") -> 0 | K24: =IF(G24="GVS","37.5",IF(G24="GVM","41.5",IF(G24="GVL","50",IF(G24="PCS","45.8",IF(G24="PCM","50",IF(G24="PCL","58.3","0")))))) -> 0 | R24: SMALL | S24: MEDIUM | T24: LARGE | U24: TOTAL | AD24: B2/GA TOTAL | AE24: B2 machine | AF24: GA machine | AG24: BLH machine | AH24: Wongo machine | AI24: Sub total
A25: 21 | J25: =IF(G25="RSL","55","0") -> 0 | K25: =IF(G25="GVS","37.5",IF(G25="GVM","41.5",IF(G25="GVL","50",IF(G25="PCS","45.8",IF(G25="PCM","50",IF(G25="PCL","58.3","0")))))) -> 0 | R25: =COUNTIF(G5:G29,"GV1")+COUNTIF(G37:G61,"GV1")+COUNTIF(G69:G93,"GV1") -> 0 | S25: =COUNTIF(G5:G29,"GV2")+COUNTIF(G37:G61,"GV2")+COUNTIF(G69:G93,"GV2") -> 0 | T25: =COUNTIF(G5:G29,"GV3")+COUNTIF(G37:G61,"GV3")+COUNTIF(G69:G93,"GV3") -> 0 | U25: =((C32+(R26+S26+T26)*0.5)) -> 2406.91 | AD25: =SUM(AE25:AF25) -> 0 | AE25: =SUM(AE22) -> 0 | AF25: =SUM(AP22) -> 0 | AG25: =SUM(AF22+AQ22) -> 0 | AH25: =AG22+AR22 -> 0 | AI25: =SUM(AE25:AH25) -> 0
A26: 22 | J26: =IF(G26="RSL","55","0") -> 0 | K26: =IF(G26="GVS","37.5",IF(G26="GVM","41.5",IF(G26="GVL","50",IF(G26="PCS","45.8",IF(G26="PCM","50",IF(G26="PCL","58.3","0")))))) -> 0 | R26: =R25*37.5 -> 0 | S26: =S25*41.5 -> 0 | T26: =T25*50 -> 0 | X26: Branch cards
A27: 23 | J27: =IF(G27="RSL","55","0") -> 0 | K27: =IF(G27="GVS","37.5",IF(G27="GVM","41.5",IF(G27="GVL","50",IF(G27="PCS","45.8",IF(G27="PCM","50",IF(G27="PCL","58.3","0")))))) -> 0 | R27: Expense | X27: 1 | Z27: -2745
A28: 24 | J28: =IF(G28="RSL","55","0") -> 0 | K28: =IF(G28="GVS","37.5",IF(G28="GVM","41.5",IF(G28="GVL","50",IF(G28="PCS","45.8",IF(G28="PCM","50",IF(G28="PCL","58.3","0")))))) -> 0 | X28: 2
A29: 25 | J29: =IF(G29="RSL","55","0") -> 0 | K29: =IF(G29="GVS","37.5",IF(G29="GVM","41.5",IF(G29="GVL","50",IF(G29="PCS","45.8",IF(G29="PCM","50",IF(G29="PCL","58.3","0")))))) -> 0 | X29: 3
A30: Page total | H30: =SUM(H5:H29) -> 670 | I30: =SUM(I5:I29) -> 1337.75 | J30: =J5+J6+J7+J8+J9+J10+J11+J12+J13+J14+J15+J16+J18+J19+J17+J20+J22+J23+J21+J24+J25+J26+J27+J28+J29 -> 220 | K30: =K5+K6+K7+K8+K9+K10+K11+K12+K13+K14+K15+K16+K18+K19+K17+K20+K22+K23+K21+K24+K25+K26+K27+K28+K29 -> 179.16 | L30: =SUM(L5:L29) -> 0 | M30: =SUM(M5:M29) -> 0 | N30: CASH | O30: CARD | P30: GV | Q30: RSL | X30: 4
A31: Daily Total | H31: =H30+H62+H94 -> 670 | I31: =I30+I62+I94 -> 1337.75 | J31: =J30+J62+J94 -> 220 | K31: =K30+K62+K94 -> 179.16 | L31: =L30+L62+L94 -> 0 | M31: =M30+M62+M94 -> 0 | N31: =COUNT(H5:H29,H37:H61,H69:H93) -> 7 | O31: =COUNT(I5:I29,I37:I61,I69:I93) -> 7 | P31: =COUNTIF(G5:G29,"G*")+COUNTIF(G37:G61,"G*")+COUNTIF(G69:G93,"G*")+COUNTIF(G5:G29,"P*")+COUNTIF(G37:G61,"P*")+COUNTIF(G69:G93,"P*") -> 2 | Q31: =COUNTIF(G5:G29,"RSL")+COUNTIF(G37:G61,"RSL")+COUNTIF(G69:G93,"RSL") -> 4 | R31: CASH CLOSING | S31: =H31+L31-U28-U29-U30 -> 670 | T31: =H31+I31+L31+M31 -> 2007.75 | X31: Subtotal | Z31: =SUM(Z27:Z30) -> -2745
A32: TOTAL SALES | C32: =H31+I31+J31+K31 -> 2406.91 | F32: No of Cars | H32: =COUNT(B5:B29,B37:B61,B69:B93) -> 18 | I32: Average | K32: =C32/H32 -> 133.71722 | N32: =H31/C32 -> 0.27836521 | O32: =I31/C32 -> 0.55579561 | P32: =K31/C32 -> 0.074435687 | Q32: =J31/C32 -> 0.091403501 | R32: CARD CLOSING | S32: =I31+M31 -> 1337.75 | X32: B2 card | Z32: =I31 -> 1337.75
A33: Daily Report | X33: Settlement | Z33: =SUM(Z31:Z32) -> -1407.25
A34: =A2 -> 26-09-2022 | H34: WEATHER | J34: =J2 -> CLOUDY | L34: REPORT by | O34: =O2 -> JOHN | R34: TOTAL STAFF | T34: =T2 -> 4
A36: No | B36: Docket No | C36: Reg No | D36: Mobile | E36: Gender | F36: TIME | G36: Service | H36: CASH | I36: CARD | J36: RSL | K36: GV | L36: GV CASH | M36: GV CARD | N36: O/Taker | O36: Comment | R36: NAME | S36: Time In | T36: Time out | U36: Total Hours
A37: =A29+1 -> 26 | J37: =IF(G37="RSL","55","0") -> 0 | K37: =IF(G37="GVS","37.5",IF(G37="GVM","41.5",IF(G37="GVL","50",IF(G37="PCS","45.8",IF(G37="PCM","50",IF(G37="PCL","58.3","0")))))) -> 0
A38: =A37+1 -> 27 | J38: =IF(G38="RSL","55","0") -> 0 | K38: =IF(G38="GVS","37.5",IF(G38="GVM","41.5",IF(G38="GVL","50",IF(G38="PCS","45.8",IF(G38="PCM","50",IF(G38="PCL","58.3","0")))))) -> 0
A39: =A38+1 -> 28 | J39: =IF(G39="RSL","55","0") -> 0 | K39: =IF(G39="GVS","37.5",IF(G39="GVM","41.5",IF(G39="GVL","50",IF(G39="PCS","45.8",IF(G39="PCM","50",IF(G39="PCL","58.3","0")))))) -> 0
A40: =A39+1 -> 29 | J40: =IF(G40="RSL","55","0") -> 0 | K40: =IF(G40="GVS","37.5",IF(G40="GVM","41.5",IF(G40="GVL","50",IF(G40="PCS","45.8",IF(G40="PCM","50",IF(G40="PCL","58.3","0")))))) -> 0
A41: =A40+1 -> 30 | J41: =IF(G41="RSL","55","0") -> 0 | K41: =IF(G41="GVS","37.5",IF(G41="GVM","41.5",IF(G41="GVL","50",IF(G41="PCS","45.8",IF(G41="PCM","50",IF(G41="PCL","58.3","0")))))) -> 0
A42: =A41+1 -> 31 | J42: =IF(G42="RSL","55","0") -> 0 | K42: =IF(G42="GVS","37.5",IF(G42="GVM","41.5",IF(G42="GVL","50",IF(G42="PCS","45.8",IF(G42="PCM","50",IF(G42="PCL","58.3","0")))))) -> 0
A43: =A42+1 -> 32 | J43: =IF(G43="RSL","55","0") -> 0 | K43: =IF(G43="GVS","37.5",IF(G43="GVM","41.5",IF(G43="GVL","50",IF(G43="PCS","45.8",IF(G43="PCM","50",IF(G43="PCL","58.3","0")))))) -> 0
A44: =A43+1 -> 33 | J44: =IF(G44="RSL","55","0") -> 0 | K44: =IF(G44="GVS","37.5",IF(G44="GVM","41.5",IF(G44="GVL","50",IF(G44="PCS","45.8",IF(G44="PCM","50",IF(G44="PCL","58.3","0")))))) -> 0
A45: =A44+1 -> 34 | J45: =IF(G45="RSL","55","0") -> 0 | K45: =IF(G45="GVS","37.5",IF(G45="GVM","41.5",IF(G45="GVL","50",IF(G45="PCS","45.8",IF(G45="PCM","50",IF(G45="PCL","58.3","0")))))) -> 0
A46: =A45+1 -> 35 | J46: =IF(G46="RSL","55","0") -> 0 | K46: =IF(G46="GVS","37.5",IF(G46="GVM","41.5",IF(G46="GVL","50",IF(G46="PCS","45.8",IF(G46="PCM","50",IF(G46="PCL","58.3","0")))))) -> 0
A47: =A46+1 -> 36 | J47: =IF(G47="RSL","55","0") -> 0 | K47: =IF(G47="GVS","37.5",IF(G47="GVM","41.5",IF(G47="GVL","50",IF(G47="PCS","45.8",IF(G47="PCM","50",IF(G47="PCL","58.3","0")))))) -> 0
A48: =A47+1 -> 37 | J48: =IF(G48="RSL","55","0") -> 0 | K48: =IF(G48="GVS","37.5",IF(G48="GVM","41.5",IF(G48="GVL","50",IF(G48="PCS","45.8",IF(G48="PCM","50",IF(G48="PCL","58.3","0")))))) -> 0
A49: =A48+1 -> 38 | J49: =IF(G49="RSL","55","0") -> 0 | K49: =IF(G49="GVS","37.5",IF(G49="GVM","41.5",IF(G49="GVL","50",IF(G49="PCS","45.8",IF(G49="PCM","50",IF(G49="PCL","58.3","0")))))) -> 0
... A61: =A60+1 -> 50 | J61: =IF(G61="RSL","55","0") -> 0 | K61: =IF(G61="GVS","37.5",IF(G61="GVM","41.5",IF(G61="GVL","50",IF(G61="PCS","45.8",IF(G61="PCM","50",IF(G61="PCL","58.3","0")))))) -> 0
A62: Page total | H62: =SUM(H37:H61) -> 0 | I62: =SUM(I37:I61) -> 0 | J62: =J61+J60+J59+J58+J57+J56+J55+J54+J53+J52+J51+J50+J49+J48+J47+J46+J45+J44+J43+J42+J41+J40+J39+J38+J37 -> 0 | K62: =K61+K60+K59+K58+K57+K56+K55+K54+K53+K52+K51+K50+K49+K48+K47+K46+K45+K44+K43+K42+K41+K40+K39+K38+K37 -> 0 | L62: =SUM(L37:L61) -> 0 | M62: =SUM(M37:M61) -> 0
R64: Page: 2
A65: Daily Report
A66: =A34 -> 26-09-2022 | H66: WEATHER | J66: =J34 -> CLOUDY | L66: REPORT by | O66: =O34 -> JOHN | R66: TOTAL STAFF | T66: =T34 -> 4
A68: No | B68: Docket No | C68: Reg No | D68: Mobile | E68: Gender | F68: TIME | G68: Service | H68: CASH | I68: CARD | J68: RSL | K68: GV | L68: GV CASH | M68: GV CARD | N68: O/Taker | O68: Comment | R68: NAME | S68: Time In | T68: Time out | U68: Total Hours
A69: =A61+1 -> 51 | J69: =IF(G69="RSL","55","0") -> 0 | K69: =IF(G69="GVS","37.5",IF(G69="GVM","41.5",IF(G69="GVL","50",IF(G69="PCS","45.8",IF(G69="PCM","50",IF(G69="PCL","58.3","0")))))) -> 0
A70: =A69+1 -> 52 | J70: =IF(G70="RSL","55","0") -> 0 | K70: =IF(G70="GVS","37.5",IF(G70="GVM","41.5",IF(G70="GVL","50",IF(G70="PCS","45.8",IF(G70="PCM","50",IF(G70="PCL","58.3","0")))))) -> 0
A71: =A70+1 -> 53 | J71: =IF(G71="RSL","55","0") -> 0 | K71: =IF(G71="GVS","37.5",IF(G71="GVM","41.5",IF(G71="GVL","50",IF(G71="PCS","45.8",IF(G71="PCM","50",IF(G71="PCL","58.3","0")))))) -> 0
A72: =A71+1 -> 54 | J72: =IF(G72="RSL","55","0") -> 0 | K72: =IF(G72="GVS","37.5",IF(G72="GVM","41.5",IF(G72="GVL","50",IF(G72="PCS","45.8",IF(G72="PCM","50",IF(G72="PCL","58.3","0")))))) -> 0
A73: =A72+1 -> 55 | J73: =IF(G73="RSL","55","0") -> 0 | K73: =IF(G73="GVS","37.5",IF(G73="GVM","41.5",IF(G73="GVL","50",IF(G73="PCS","45.8",IF(G73="PCM","50",IF(G73="PCL","58.3","0")))))) -> 0
A74: =A73+1 -> 56 | J74: =IF(G74="RSL","55","0") -> 0 | K74: =IF(G74="GVS","37.5",IF(G74="GVM","41.5",IF(G74="GVL","50",IF(G74="PCS","45.8",IF(G74="PCM","50",IF(G74="PCL","58.3","0")))))) -> 0
A75: =A74+1 -> 57 | J75: =IF(G75="RSL","55","0") -> 0 | K75: =IF(G75="GVS","37.5",IF(G75="GVM","41.5",IF(G75="GVL","50",IF(G75="PCS","45.8",IF(G75="PCM","50",IF(G75="PCL","58.3","0")))))) -> 0
A76: =A75+1 -> 58 | J76: =IF(G76="RSL","55","0") -> 0 | K76: =IF(G76="GVS","37.5",IF(G76="GVM","41.5",IF(G76="GVL","50",IF(G76="PCS","45.8",IF(G76="PCM","50",IF(G76="PCL","58.3","0")))))) -> 0
A77: =A76+1 -> 59 | J77: =IF(G77="RSL","55","0") -> 0 | K77: =IF(G77="GVS","37.5",IF(G77="GVM","41.5",IF(G77="GVL","50",IF(G77="PCS","45.8",IF(G77="PCM","50",IF(G77="PCL","58.3","0")))))) -> 0
A78: =A77+1 -> 60 | J78: =IF(G78="RSL","55","0") -> 0 | K78: =IF(G78="GVS","37.5",IF(G78="GVM","41.5",IF(G78="GVL","50",IF(G78="PCS","45.8",IF(G78="PCM","50",IF(G78="PCL","58.3","0")))))) -> 0
A79: =A78+1 -> 61 | J79: =IF(G79="RSL","55","0") -> 0 | K79: =IF(G79="GVS","37.5",IF(G79="GVM","41.5",IF(G79="GVL","50",IF(G79="PCS","45.8",IF(G79="PCM","50",IF(G79="PCL","58.3","0")))))) -> 0
A80: =A79+1 -> 62 | J80: =IF(G80="RSL","55","0") -> 0 | K80: =IF(G80="GVS","37.5",IF(G80="GVM","41.5",IF(G80="GVL","50",IF(G80="PCS","45.8",IF(G80="PCM","50",IF(G80="PCL","58.3","0")))))) -> 0
A81: =A80+1 -> 63 | J81: =IF(G81="RSL","55","0") -> 0 | K81: =IF(G81="GVS","37.5",IF(G81="GVM","41.5",IF(G81="GVL","50",IF(G81="PCS","45.8",IF(G81="PCM","50",IF(G81="PCL","58.3","0")))))) -> 0
... A93: =A92+1 -> 75 | J93: =IF(G93="RSL","55","0") -> 0 | K93: =IF(G93="GVS","37.5",IF(G93="GVM","41.5",IF(G93="GVL","50",IF(G93="PCS","45.8",IF(G93="PCM","50",IF(G93="PCL","58.3","0")))))) -> 0
A94: Page total | H94: =SUM(H69:H93) -> 0 | I94: =SUM(I69:I93) -> 0 | J94: =J93+J92+J91+J90+J89+J88+J87+J86+J85+J84+J83+J82+J81+J80+J79+J78+J77+J76+J75+J74+J73+J72+J71+J70+J69 -> 0 | K94: =K93+K92+K91+K90+K89+K88+K87+K86+K85+K84+K83+K82+K81+K80+K79+K78+K77+K76+K75+K74+K73+K72+K71+K70+K69 -> 0 | L94: =SUM(L69:L93) -> 0 | M94: =SUM(M69:M93) -> 0
R96: Page: 3

Sheet TUE
A1: B2 Daily Report
A2: 27 - 9 - 2022 | H2: WEATHER | J2: MIX | L2: REPORT BY | O2: HENDRA | R2: TOTAL STAFF | T2: 3 | X2: Merchant machine usage at B2 | AA2: Settle amount | AI2: Merchant machine usage at GA | AL2: Settle amount
A4: No | B4: Docket No | C4: Reg No | D4: Mobile | E4: Gender | F4: TIME | G4: Service | H4: CASH | I4: CARD | J4: RSL | K4: GV | L4: GV CASH | M4: GV CARD | N4: O/Taker | O4: Comment | R4: NAME | S4: Time In | T4: Time out | U4: Total Hours | Z4: B2 machine | AA4: BLH machine | AB4: Wongo | AE4: B2 machine | AF4: BLH machine | AG4: Wongo | AK4: GA machine | AL4: BLH machine | AM4: Wongo | AP4: GA machine | AQ4: BLH machine | AR4: Wongo
A5: 1 | B5: 11358 | C5: DGM062 | D5: 0411853091 | E5: M | F5: 950 | G5: D | H5: 75 | J5: =IF(G5="RSL","55","0") -> 0 | K5: =IF(G5="GVS","37.5",IF(G5="GVM","41.5",IF(G5="GVL","50",IF(G5="PCS","45.8",IF(G5="PCM","50",IF(G5="PCL","58.3","0")))))) -> 0 | N5: HENDRA | R5: HENDRA | S5: 0.33333333 | T5: 0.79166667 | U5: =(T5-S5)*24 -> 11 | X5: NOV | Y5: 1 | AD5: 16 | AI5: NOV | AJ5: 1 | AO5: 16
A6: 2 | B6: 11359 | C6: DXN78G | D6: 0412688684 | E6: F | F6: 1105 | G6: RSL | J6: =IF(G6="RSL","55","0") -> 55 | K6: =IF(G6="GVS","37.5",IF(G6="GVM","41.5",IF(G6="GVL","50",IF(G6="PCS","45.8",IF(G6="PCM","50",IF(G6="PCL","58.3","0")))))) -> 0 | N6: HENDRA | O6: 202207059(D) | R6: ARIANTO | S6: 0.39583333 | T6: 0.66666667 | U6: =(T6-S6)*24 -> 6.5 | W6: M | Y6: 2 | AD6: 17 | AJ6: 2 | AO6: 17
A7: 3 | B7: 11360 | C7: CXY11Y | D7: 0412411002 | E7: F | F7: 1115 | G7: D | H7: 55 | J7: =IF(G7="RSL","55","0") -> 0 | K7: =IF(G7="GVS","37.5",IF(G7="GVM","41.5",IF(G7="GVL","50",IF(G7="PCS","45.8",IF(G7="PCM","50",IF(G7="PCL","58.3","0")))))) -> 0 | N7: HENDRA | R7: VINNY | S7: 0.44791667 | T7: 0.71875 | U7: =(T7-S7)*24 -> 6.5 | W7: F | Y7: 3 | AD7: 18 | AJ7: 3 | AO7: 18
A8: 4 | B8: 11361 | C8: CRF59D | D8: 0415917725 | E8: F | F8: 1125 | G8: D | H8: 55 | J8: =IF(G8="RSL","55","0") -> 0 | K8: =IF(G8="GVS","37.5",IF(G8="GVM","41.5",IF(G8="GVL","50",IF(G8="PCS","45.8",IF(G8="PCM","50",IF(G8="PCL","58.3","0")))))) -> 0 | N8: VINNY | R8: JAMES | S8: 0.625 | T8: 0.79166667 | U8: =(T8-S8)*24 -> 4 | Y8: 4 | AD8: 19 | AJ8: 4 | AO8: 19
A9: 5 | B9: 11362 | C9: CV28KS | D9: 0404718880 | E9: F | F9: 1200 | G9: H | H9: 130 | J9: =IF(G9="RSL","55","0") -> 0 | K9: =IF(G9="GVS","37.5",IF(G9="GVM","41.5",IF(G9="GVL","50",IF(G9="PCS","45.8",IF(G9="PCM","50",IF(G9="PCL","58.3","0")))))) -> 0 | N9: HENDRA | O9: ST BABY SEAT | R9: KUROSH | S9: 0.66666667 | T9: 0.79166667 | U9: =(T9-S9)*24 -> 3 | X9: EXCL RSL | Y9: 5 | AD9: 20 | AJ9: 5 | AO9: 20
A10: 6 | B10: 11363 | C10: CW2222 | D10: 0414681613 | E10: M | F10: 1215 | G10: X | H10: 85 | J10: =IF(G10="RSL","55","0") -> 0 | K10: =IF(G10="GVS","37.5",IF(G10="GVM","41.5",IF(G10="GVL","50",IF(G10="PCS","45.8",IF(G10="PCM","50",IF(G10="PCL","58.3","0")))))) -> 0 | N10: HENDRA | R10: DARRYLAND OCTEC | S10: 0.6875 | T10: 0.75 | U10: =(T10-S10)*24 -> 1.5 | Y10: 6 | AD10: 21 | AJ10: 6 | AO10: 21
A11: 7 | B11: 11364 | C11: DQC84Z | D11: 0414311698 | E11: F | F11: 1245 | G11: D | H11: 75 | J11: =IF(G11="RSL","55","0") -> 0 | K11: =IF(G11="GVS","37.5",IF(G11="GVM","41.5",IF(G11="GVL","50",IF(G11="PCS","45.8",IF(G11="PCM","50",IF(G11="PCL","58.3","0")))))) -> 0 | N11: HENDRA | R11: JUN | S11: 0.75 | T11: 0.79166667 | U11: =(T11-S11)*24 -> 1 | Y11: 7 | AD11: 22 | AJ11: 7 | AO11: 22
A12: 8 | B12: 11365 | C12: DMW001 | D12: 0402488963 | E12: M | F12: 1245 | G12: X | I12: 95.95 | J12: =IF(G12="RSL","55","0") -> 0 | K12: =IF(G12="GVS","37.5",IF(G12="GVM","41.5",IF(G12="GVL","50",IF(G12="PCS","45.8",IF(G12="PCM","50",IF(G12="PCL","58.3","0")))))) -> 0 | N12: HENDRA | U12: =(T12-S12)*24 -> 0 | Y12: 8 | AD12: 23 | AJ12: 8 | AO12: 23
A13: 9 | B13: 11366 | C13: BZD29T | D13: 0412373911 | E13: F | F13: 1435 | G13: D | H13: 55 | J13: =IF(G13="RSL","55","0") -> 0 | K13: =IF(G13="GVS","37.5",IF(G13="GVM","41.5",IF(G13="GVL","50",IF(G13="PCS","45.8",IF(G13="PCM","50",IF(G13="PCL","58.3","0")))))) -> 0 | N13: VINNY | U13: =(T13-S13)*24 -> 0 | Y13: 9 | AD13: 24 | AJ13: 9 | AO13: 24
A14: 10 | B14: 11367 | C14: DYX73X | D14: 0403108842 | E14: F | F14: 1445 | G14: W/O | H14: 65 | J14: =IF(G14="RSL","55","0") -> 0 | K14: =IF(G14="GVS","37.5",IF(G14="GVM","41.5",IF(G14="GVL","50",IF(G14="PCS","45.8",IF(G14="PCM","50",IF(G14="PCL","58.3","0")))))) -> 0 | N14: VINNY | U14: =(T14-S14)*24 -> 0 | Y14: 10 | AD14: 25 | AJ14: 10 | AO14: 25
A15: 11 | B15: 11368 | C15: EHZ68U | D15: 0425310389 | E15: M | F15: 1445 | G15: D | I15: 75 | J15: =IF(G15="RSL","55","0") -> 0 | K15: =IF(G15="GVS","37.5",IF(G15="GVM","41.5",IF(G15="GVL","50",IF(G15="PCS","45.8",IF(G15="PCM","50",IF(G15="PCL","58.3","0")))))) -> 0 | N15: HENDRA | U15: =(T15-S15)*24 -> 0 | Y15: 11 | AD15: 26 | AJ15: 11 | AO15: 26
A16: 12 | B16: 11369 | C16: ETR15L | D16: 0412258130 | E16: F | F16: 1600 | G16: D | H16: 55 | J16: =IF(G16="RSL","55","0") -> 0 | K16: =IF(G16="GVS","37.5",IF(G16="GVM","41.5",IF(G16="GVL","50",IF(G16="PCS","45.8",IF(G16="PCM","50",IF(G16="PCL","58.3","0")))))) -> 0 | N16: HENDRA | R16: =H32/U16 -> 0.44776119 | S16: =H32/(U16-U5) -> 0.66666667 | T16: =C32/U16 -> 52.952239 | U16: =SUM(U5:U15) -> 33.5 | Y16: 12 | AD16: 27 | AJ16: 12 | AO16: 27
A17: 13 | B17: 11370 | C17: DHH46E | D17: 0448090824 | E17: F | F17: 1605 | G17: X | I17: 95 | J17: =IF(G17="RSL","55","0") -> 0 | K17: =IF(G17="GVS","37.5",IF(G17="GVM","41.5",IF(G17="GVL","50",IF(G17="PCS","45.8",IF(G17="PCM","50",IF(G17="PCL","58.3","0")))))) -> 0 | N17: VINNY | R17: Cars/T Hr ① | S17: Cars/T Hr ② | T17: Sales/T Hr | U17: Total Hours | Y17: 13 | AD17: 28 | AJ17: 13 | AO17: 28
A18: 14 | B18: 11371 | C18: EKB89T | D18: 0409705030 | E18: F | F18: 1615 | G18: X | I18: 95.95 | J18: =IF(G18="RSL","55","0") -> 0 | K18: =IF(G18="GVS","37.5",IF(G18="GVM","41.5",IF(G18="GVL","50",IF(G18="PCS","45.8",IF(G18="PCM","50",IF(G18="PCL","58.3","0")))))) -> 0 | N18: VINNY | R18: ITEM | S18: QTY | T18: AMT | U18: RMKS | Y18: 14 | AD18: 29 | AJ18: 14 | AO18: 29
A19: 15 | B19: 11372 | C19: HSING | D19: 0428881889 | E19: F | F19: 1615 | G19: FD | I19: 707 | J19: =IF(G19="RSL","55","0") -> 0 | K19: =IF(G19="GVS","37.5",IF(G19="GVM","41.5",IF(G19="GVL","50",IF(G19="PCS","45.8",IF(G19="PCM","50",IF(G19="PCL","58.3","0")))))) -> 0 | N19: HENDRA | R19: GV | S19: =COUNT(L5:M29,L37:M61,L69:M93) -> 0 | T19: =SUM(L5:M29,L37:M61,L69:M93) -> 0 | Y19: 15 | AD19: 30 | AJ19: 15 | AO19: 30
A20: 16 | J20: =IF(G20="RSL","55","0") -> 0 | K20: =IF(G20="GVS","37.5",IF(G20="GVM","41.5",IF(G20="GVL","50",IF(G20="PCS","45.8",IF(G20="PCM","50",IF(G20="PCL","58.3","0")))))) -> 0 | AD20: 31 | AO20: 31
A21: 17 | J21: =IF(G21="RSL","55","0") -> 0 | K21: =IF(G21="GVS","37.5",IF(G21="GVM","41.5",IF(G21="GVL","50",IF(G21="PCS","45.8",IF(G21="PCM","50",IF(G21="PCL","58.3","0")))))) -> 0
A22: 18 | J22: =IF(G22="RSL","55","0") -> 0 | K22: =IF(G22="GVS","37.5",IF(G22="GVM","41.5",IF(G22="GVL","50",IF(G22="PCS","45.8",IF(G22="PCM","50",IF(G22="PCL","58.3","0")))))) -> 0 | AD22: Total | AE22: =SUM(Z5:Z19,AE5:AE20) -> 0 | AF22: =SUM(AA5:AA19,AF5:AF20,) -> 0 | AG22: =SUM(AB5:AB19,AG5:AG20) -> 0 | AO22: Total | AP22: =SUM(AK5:AK19,AP5:AP20) -> 0 | AQ22: =SUM(AL5:AL19,AQ5:AQ20,) -> 0 | AR22: =SUM(AM5:AM19,AR5:AR20) -> 0
A23: 19 | J23: =IF(G23="RSL","55","0") -> 0 | K23: =IF(G23="GVS","37.5",IF(G23="GVM","41.5",IF(G23="GVL","50",IF(G23="PCS","45.8",IF(G23="PCM","50",IF(G23="PCL","58.3","0")))))) -> 0
A24: 20 | J24: =IF(G24="RSL","55","0") -> 0 | K24: =IF(G24="GVS","37.5",IF(G24="GVM","41.5",IF(G24="GVL","50",IF(G24="PCS","45.8",IF(G24="PCM","50",IF(G24="PCL","58.3","0")))))) -> 0 | R24: SMALL | S24: MEDIUM | T24: LARGE | U24: TOTAL | AD24: B2/GA TOTAL | AE24: B2 machine | AF24: GA machine | AG24: BLH machine | AH24: Wongo machine | AI24: Sub total
A25: 21 | J25: =IF(G25="RSL","55","0") -> 0 | K25: =IF(G25="GVS","37.5",IF(G25="GVM","41.5",IF(G25="GVL","50",IF(G25="PCS","45.8",IF(G25="PCM","50",IF(G25="PCL","58.3","0")))))) -> 0 | R25: =COUNTIF(G5:G29,"GV1")+COUNTIF(G37:G61,"GV1")+COUNTIF(G69:G93,"GV1") -> 0 | S25: =COUNTIF(G5:G29,"GV2")+COUNTIF(G37:G61,"GV2")+COUNTIF(G69:G93,"GV2") -> 0 | T25: =COUNTIF(G5:G29,"GV3")+COUNTIF(G37:G61,"GV3")+COUNTIF(G69:G93,"GV3") -> 0 | U25: =((C32+(R26+S26+T26)*0.5)) -> 1773.9 | AD25: =SUM(AE25:AF25) -> 0 | AE25: =SUM(AE22) -> 0 | AF25: =SUM(AP22) -> 0 | AG25: =SUM(AF22+AQ22) -> 0 | AH25: =AG22+AR22 -> 0 | AI25: =SUM(AE25:AH25) -> 0
A26: 22 | J26: =IF(G26="RSL","55","0") -> 0 | K26: =IF(G26="GVS","37.5",IF(G26="GVM","41.5",IF(G26="GVL","50",IF(G26="PCS","45.8",IF(G26="PCM","50",IF(G26="PCL","58.3","0")))))) -> 0 | R26: =R25*37.5 -> 0 | S26: =S25*41.5 -> 0 | T26: =T25*50 -> 0 | X26: Branch cards
A27: 23 | J27: =IF(G27="RSL","55","0") -> 0 | K27: =IF(G27="GVS","37.5",IF(G27="GVM","41.5",IF(G27="GVL","50",IF(G27="PCS","45.8",IF(G27="PCM","50",IF(G27="PCL","58.3","0")))))) -> 0 | R27: Expense | X27: 1 | Z27: -2745
A28: 24 | J28: =IF(G28="RSL","55","0") -> 0 | K28: =IF(G28="GVS","37.5",IF(G28="GVM","41.5",IF(G28="GVL","50",IF(G28="PCS","45.8",IF(G28="PCM","50",IF(G28="PCL","58.3","0")))))) -> 0 | X28: 2
A29: 25 | J29: =IF(G29="RSL","55","0") -> 0 | K29: =IF(G29="GVS","37.5",IF(G29="GVM","41.5",IF(G29="GVL","50",IF(G29="PCS","45.8",IF(G29="PCM","50",IF(G29="PCL","58.3","0")))))) -> 0 | X29: 3
A30: Page total | H30: =SUM(H5:H29) -> 650 | I30: =SUM(I5:I29) -> 1068.9 | J30: =J5+J6+J7+J8+J9+J10+J11+J12+J13+J14+J15+J16+J18+J19+J17+J20+J22+J23+J21+J24+J25+J26+J27+J28+J29 -> 55 | K30: =K5+K6+K7+K8+K9+K10+K11+K12+K13+K14+K15+K16+K18+K19+K17+K20+K22+K23+K21+K24+K25+K26+K27+K28+K29 -> 0 | L30: =SUM(L5:L29) -> 0 | M30: =SUM(M5:M29) -> 0 | N30: CASH | O30: CARD | P30: GV | Q30: RSL | X30: 4
A31: Daily Total | H31: =H30+H62+H94 -> 650 | I31: =I30+I62+I94 -> 1068.9 | J31: =J30+J62+J94 -> 55 | K31: =K30+K62+K94 -> 0 | L31: =L30+L62+L94 -> 0 | M31: =M30+M62+M94 -> 0 | N31: =COUNT(H5:H29,H37:H61,H69:H93) -> 9 | O31: =COUNT(I5:I29,I37:I61,I69:I93) -> 5 | P31: =COUNTIF(G5:G29,"G*")+COUNTIF(G37:G61,"G*")+COUNTIF(G69:G93,"G*")+COUNTIF(G5:G29,"P*")+COUNTIF(G37:G61,"P*")+COUNTIF(G69:G93,"P*") -> 0 | Q31: =COUNTIF(G5:G29,"RSL")+COUNTIF(G37:G61,"RSL")+COUNTIF(G69:G93,"RSL") -> 1 | R31: CASH CLOSING | S31: =H31+L31-U28-U29-U30 -> 650 | T31: =H31+I31+L31+M31 -> 1718.9 | X31: Subtotal | Z31: =SUM(Z27:Z30) -> -2745
A32: TOTAL SALES | C32: =H31+I31+J31+K31 -> 1773.9 | F32: No of Cars | H32: =COUNT(B5:B29,B37:B61,B69:B93) -> 15 | I32: Average | K32: =C32/H32 -> 118.26 | N32: =H31/C32 -> 0.36642426 | O32: =I31/C32 -> 0.60257061 | P32: =K31/C32 -> 0 | Q32: =J31/C32 -> 0.03100513 | R32: CARD CLOSING | S32: =I31+M31 -> 1068.9 | X32: B2 card | Z32: =I31 -> 1068.9
A33: Daily Report | X33: Settlement | Z33: =SUM(Z31:Z32) -> -1676.1
A34: =A2 -> 27 - 9 - 2022 | H34: WEATHER | J34: =J2 -> MIX | L34: REPORT by | O34: =O2 -> HENDRA | R34: TOTAL STAFF | T34: =T2 -> 3
A36: No | B36: Docket No | C36: Reg No | D36: Mobile | E36: Gender | F36: TIME | G36: Service | H36: CASH | I36: CARD | J36: RSL | K36: GV | L36: GV CASH | M36: GV CARD | N36: O/Taker | O36: Comment | R36: NAME | S36: Time In | T36: Time out | U36: Total Hours
A37: =A29+1 -> 26 | J37: =IF(G37="RSL","55","0") -> 0 | K37: =IF(G37="GVS","37.5",IF(G37="GVM","41.5",IF(G37="GVL","50",IF(G37="PCS","45.8",IF(G37="PCM","50",IF(G37="PCL","58.3","0")))))) -> 0
A38: =A37+1 -> 27 | J38: =IF(G38="RSL","55","0") -> 0 | K38: =IF(G38="GVS","37.5",IF(G38="GVM","41.5",IF(G38="GVL","50",IF(G38="PCS","45.8",IF(G38="PCM","50",IF(G38="PCL","58.3","0")))))) -> 0
A39: =A38+1 -> 28 | J39: =IF(G39="RSL","55","0") -> 0 | K39: =IF(G39="GVS","37.5",IF(G39="GVM","41.5",IF(G39="GVL","50",IF(G39="PCS","45.8",IF(G39="PCM","50",IF(G39="PCL","58.3","0")))))) -> 0
A40: =A39+1 -> 29 | J40: =IF(G40="RSL","55","0") -> 0 | K40: =IF(G40="GVS","37.5",IF(G40="GVM","41.5",IF(G40="GVL","50",IF(G40="PCS","45.8",IF(G40="PCM","50",IF(G40="PCL","58.3","0")))))) -> 0
A41: =A40+1 -> 30 | J41: =IF(G41="RSL","55","0") -> 0 | K41: =IF(G41="GVS","37.5",IF(G41="GVM","41.5",IF(G41="GVL","50",IF(G41="PCS","45.8",IF(G41="PCM","50",IF(G41="PCL","58.3","0")))))) -> 0
A42: =A41+1 -> 31 | J42: =IF(G42="RSL","55","0") -> 0 | K42: =IF(G42="GVS","37.5",IF(G42="GVM","41.5",IF(G42="GVL","50",IF(G42="PCS","45.8",IF(G42="PCM","50",IF(G42="PCL","58.3","0")))))) -> 0
A43: =A42+1 -> 32 | J43: =IF(G43="RSL","55","0") -> 0 | K43: =IF(G43="GVS","37.5",IF(G43="GVM","41.5",IF(G43="GVL","50",IF(G43="PCS","45.8",IF(G43="PCM","50",IF(G43="PCL","58.3","0")))))) -> 0
A44: =A43+1 -> 33 | J44: =IF(G44="RSL","55","0") -> 0 | K44: =IF(G44="GVS","37.5",IF(G44="GVM","41.5",IF(G44="GVL","50",IF(G44="PCS","45.8",IF(G44="PCM","50",IF(G44="PCL","58.3","0")))))) -> 0
A45: =A44+1 -> 34 | J45: =IF(G45="RSL","55","0") -> 0 | K45: =IF(G45="GVS","37.5",IF(G45="GVM","41.5",IF(G45="GVL","50",IF(G45="PCS","45.8",IF(G45="PCM","50",IF(G45="PCL","58.3","0")))))) -> 0
A46: =A45+1 -> 35 | J46: =IF(G46="RSL","55","0") -> 0 | K46: =IF(G46="GVS","37.5",IF(G46="GVM","41.5",IF(G46="GVL","50",IF(G46="PCS","45.8",IF(G46="PCM","50",IF(G46="PCL","58.3","0")))))) -> 0
A47: =A46+1 -> 36 | J47: =IF(G47="RSL","55","0") -> 0 | K47: =IF(G47="GVS","37.5",IF(G47="GVM","41.5",IF(G47="GVL","50",IF(G47="PCS","45.8",IF(G47="PCM","50",IF(G47="PCL","58.3","0")))))) -> 0
A48: =A47+1 -> 37 | J48: =IF(G48="RSL","55","0") -> 0 | K48: =IF(G48="GVS","37.5",IF(G48="GVM","41.5",IF(G48="GVL","50",IF(G48="PCS","45.8",IF(G48="PCM","50",IF(G48="PCL","58.3","0")))))) -> 0
A49: =A48+1 -> 38 | J49: =IF(G49="RSL","55","0") -> 0 | K49: =IF(G49="GVS","37.5",IF(G49="GVM","41.5",IF(G49="GVL","50",IF(G49="PCS","45.8",IF(G49="PCM","50",IF(G49="PCL","58.3","0")))))) -> 0
... A61: =A60+1 -> 50 | J61: =IF(G61="RSL","55","0") -> 0 | K61: =IF(G61="GVS","37.5",IF(G61="GVM","41.5",IF(G61="GVL","50",IF(G61="PCS","45.8",IF(G61="PCM","50",IF(G61="PCL","58.3","0")))))) -> 0
A62: Page total | H62: =SUM(H37:H61) -> 0 | I62: =SUM(I37:I61) -> 0 | J62: =J61+J60+J59+J58+J57+J56+J55+J54+J53+J52+J51+J50+J49+J48+J47+J46+J45+J44+J43+J42+J41+J40+J39+J38+J37 -> 0 | K62: =K61+K60+K59+K58+K57+K56+K55+K54+K53+K52+K51+K50+K49+K48+K47+K46+K45+K44+K43+K42+K41+K40+K39+K38+K37 -> 0 | L62: =SUM(L37:L61) -> 0 | M62: =SUM(M37:M61) -> 0
R64: Page: 2
A65: Daily Report
A66: =A34 -> 27 - 9 - 2022 | H66: WEATHER | J66: =J34 -> MIX | L66: REPORT by | O66: =O34 -> HENDRA | R66: TOTAL STAFF | T66: =T34 -> 3
A68: No | B68: Docket No | C68: Reg No | D68: Mobile | E68: Gender | F68: TIME | G68: Service | H68: CASH | I68: CARD | J68: RSL | K68: GV | L68: GV CASH | M68: GV CARD | N68: O/Taker | O68: Comment | R68: NAME | S68: Time In | T68: Time out | U68: Total Hours
A69: =A61+1 -> 51 | J69: =IF(G69="RSL","55","0") -> 0 | K69: =IF(G69="GVS","37.5",IF(G69="GVM","41.5",IF(G69="GVL","50",IF(G69="PCS","45.8",IF(G69="PCM","50",IF(G69="PCL","58.3","0")))))) -> 0
A70: =A69+1 -> 52 | J70: =IF(G70="RSL","55","0") -> 0 | K70: =IF(G70="GVS","37.5",IF(G70="GVM","41.5",IF(G70="GVL","50",IF(G70="PCS","45.8",IF(G70="PCM","50",IF(G70="PCL","58.3","0")))))) -> 0
A71: =A70+1 -> 53 | J71: =IF(G71="RSL","55","0") -> 0 | K71: =IF(G71="GVS","37.5",IF(G71="GVM","41.5",IF(G71="GVL","50",IF(G71="PCS","45.8",IF(G71="PCM","50",IF(G71="PCL","58.3","0")))))) -> 0
A72: =A71+1 -> 54 | J72: =IF(G72="RSL","55","0") -> 0 | K72: =IF(G72="GVS","37.5",IF(G72="GVM","41.5",IF(G72="GVL","50",IF(G72="PCS","45.8",IF(G72="PCM","50",IF(G72="PCL","58.3","0")))))) -> 0
A73: =A72+1 -> 55 | J73: =IF(G73="RSL","55","0") -> 0 | K73: =IF(G73="GVS","37.5",IF(G73="GVM","41.5",IF(G73="GVL","50",IF(G73="PCS","45.8",IF(G73="PCM","50",IF(G73="PCL","58.3","0")))))) -> 0
A74: =A73+1 -> 56 | J74: =IF(G74="RSL","55","0") -> 0 | K74: =IF(G74="GVS","37.5",IF(G74="GVM","41.5",IF(G74="GVL","50",IF(G74="PCS","45.8",IF(G74="PCM","50",IF(G74="PCL","58.3","0")))))) -> 0
A75: =A74+1 -> 57 | J75: =IF(G75="RSL","55","0") -> 0 | K75: =IF(G75="GVS","37.5",IF(G75="GVM","41.5",IF(G75="GVL","50",IF(G75="PCS","45.8",IF(G75="PCM","50",IF(G75="PCL","58.3","0")))))) -> 0
A76: =A75+1 -> 58 | J76: =IF(G76="RSL","55","0") -> 0 | K76: =IF(G76="GVS","37.5",IF(G76="GVM","41.5",IF(G76="GVL","50",IF(G76="PCS","45.8",IF(G76="PCM","50",IF(G76="PCL","58.3","0")))))) -> 0
A77: =A76+1 -> 59 | J77: =IF(G77="RSL","55","0") -> 0 | K77: =IF(G77="GVS","37.5",IF(G77="GVM","41.5",IF(G77="GVL","50",IF(G77="PCS","45.8",IF(G77="PCM","50",IF(G77="PCL","58.3","0")))))) -> 0
A78: =A77+1 -> 60 | J78: =IF(G78="RSL","55","0") -> 0 | K78: =IF(G78="GVS","37.5",IF(G78="GVM","41.5",IF(G78="GVL","50",IF(G78="PCS","45.8",IF(G78="PCM","50",IF(G78="PCL","58.3","0")))))) -> 0
A79: =A78+1 -> 61 | J79: =IF(G79="RSL","55","0") -> 0 | K79: =IF(G79="GVS","37.5",IF(G79="GVM","41.5",IF(G79="GVL","50",IF(G79="PCS","45.8",IF(G79="PCM","50",IF(G79="PCL","58.3","0")))))) -> 0
A80: =A79+1 -> 62 | J80: =IF(G80="RSL","55","0") -> 0 | K80: =IF(G80="GVS","37.5",IF(G80="GVM","41.5",IF(G80="GVL","50",IF(G80="PCS","45.8",IF(G80="PCM","50",IF(G80="PCL","58.3","0")))))) -> 0
A81: =A80+1 -> 63 | J81: =IF(G81="RSL","55","0") -> 0 | K81: =IF(G81="GVS","37.5",IF(G81="GVM","41.5",IF(G81="GVL","50",IF(G81="PCS","45.8",IF(G81="PCM","50",IF(G81="PCL","58.3","0")))))) -> 0
... A93: =A92+1 -> 75 | J93: =IF(G93="RSL","55","0") -> 0 | K93: =IF(G93="GVS","37.5",IF(G93="GVM","41.5",IF(G93="GVL","50",IF(G93="PCS","45.8",IF(G93="PCM","50",IF(G93="PCL","58.3","0")))))) -> 0
A94: Page total | H94: =SUM(H69:H93) -> 0 | I94: =SUM(I69:I93) -> 0 | J94: =J93+J92+J91+J90+J89+J88+J87+J86+J85+J84+J83+J82+J81+J80+J79+J78+J77+J76+J75+J74+J73+J72+J71+J70+J69 -> 0 | K94: =K93+K92+K91+K90+K89+K88+K87+K86+K85+K84+K83+K82+K81+K80+K79+K78+K77+K76+K75+K74+K73+K72+K71+K70+K69 -> 0 | L94: =SUM(L69:L93) -> 0 | M94: =SUM(M69:M93) -> 0
R96: Page: 3

Sheet WED
A1: B2 Daily Report
A2: 28 - 9 - 2022 | H2: WEATHER | J2: SUNNY | L2: REPORT BY | O2: HENDRA | R2: TOTAL STAFF | T2: 4 | X2: Merchant machine usage at B2 | AA2: Settle amount | AI2: Merchant machine usage at GA | AL2: Settle amount
A4: No | B4: Docket No | C4: Reg No | D4: Mobile | E4: Gender | F4: TIME | G4: Service | H4: CASH | I4: CARD | J4: RSL | K4: GV | L4: GV CASH | M4: GV CARD | N4: O/Taker | O4: Comment | R4: NAME | S4: Time In | T4: Time out | U4: Total Hours | Z4: B2 machine | AA4: BLH machine | AB4: Wongo | AE4: B2 machine | AF4: BLH machine | AG4: Wongo | AK4: GA machine | AL4: BLH machine | AM4: Wongo | AP4: GA machine | AQ4: BLH machine | AR4: Wongo
A5: 1 | B5: 11373 | C5: DND96D | D5: 0402833499 | E5: F | F5: 845 | G5: H | H5: 150 | J5: =IF(G5="RSL","55","0") -> 0 | K5: =IF(G5="GVS","37.5",IF(G5="GVM","41.5",IF(G5="GVL","50",IF(G5="PCS","45.8",IF(G5="PCM","50",IF(G5="PCL","58.3","0")))))) -> 0 | N5: HENDRA | R5: HENDRA | S5: 0.33333333 | T5: 0.66666667 | U5: =(T5-S5)*24 -> 8 | X5: NOV | Y5: 1 | AD5: 16 | AI5: NOV | AJ5: 1 | AO5: 16
A6: 2 | B6: 11374 | C6: DKI60J | D6: 0412062961 | E6: F | F6: 900 | G6: H | H6: 120 | J6: =IF(G6="RSL","55","0") -> 0 | K6: =IF(G6="GVS","37.5",IF(G6="GVM","41.5",IF(G6="GVL","50",IF(G6="PCS","45.8",IF(G6="PCM","50",IF(G6="PCL","58.3","0")))))) -> 0 | N6: HENDRA | R6: ARIANTO | S6: 0.37916667 | T6: 0.62916667 | U6: =(T6-S6)*24 -> 6 | W6: M | Y6: 2 | AD6: 17 | AJ6: 2 | AO6: 17
A7: 3 | B7: 11375 | C7: ETA54L | D7: 0438844667 | E7: M | F7: 920 | G7: D | I7: 55.55 | J7: =IF(G7="RSL","55","0") -> 0 | K7: =IF(G7="GVS","37.5",IF(G7="GVM","41.5",IF(G7="GVL","50",IF(G7="PCS","45.8",IF(G7="PCM","50",IF(G7="PCL","58.3","0")))))) -> 0 | N7: HENDRA | R7: KUROSH | S7: 0.41666667 | T7: 0.66666667 | U7: =(T7-S7)*24 -> 6 | W7: F | Y7: 3 | AD7: 18 | AJ7: 3 | AO7: 18
A8: 4 | B8: 11376 | C8: NCC58P | D8: 0418688707 | E8: F | F8: 930 | G8: X | I8: 95 | J8: =IF(G8="RSL","55","0") -> 0 | K8: =IF(G8="GVS","37.5",IF(G8="GVM","41.5",IF(G8="GVL","50",IF(G8="PCS","45.8",IF(G8="PCM","50",IF(G8="PCL","58.3","0")))))) -> 0 | N8: HENDRA | O8: TAX | R8: VINNY | S8: 0.45833333 | T8: 0.66666667 | U8: =(T8-S8)*24 -> 5 | Y8: 4 | AD8: 19 | AJ8: 4 | AO8: 19
A9: 5 | B9: 11377 | C9: GBI | D9: 0415888891 | E9: M | F9: 945 | G9: FD | I9: 295 | J9: =IF(G9="RSL","55","0") -> 0 | K9: =IF(G9="GVS","37.5",IF(G9="GVM","41.5",IF(G9="GVL","50",IF(G9="PCS","45.8",IF(G9="PCM","50",IF(G9="PCL","58.3","0")))))) -> 0 | N9: HENDRA | U9: =(T9-S9)*24 -> 0 | X9: EXCL RSL | Y9: 5 | AD9: 20 | AJ9: 5 | AO9: 20
A10: 6 | B10: 11378 | C10: CLV99 | D10: 0400778444 | E10: M | F10: 940 | G10: X | I10: 95.95 | J10: =IF(G10="RSL","55","0") -> 0 | K10: =IF(G10="GVS","37.5",IF(G10="GVM","41.5",IF(G10="GVL","50",IF(G10="PCS","45.8",IF(G10="PCM","50",IF(G10="PCL","58.3","0")))))) -> 0 | N10: SHIVAM | U10: =(T10-S10)*24 -> 0 | Y10: 6 | AD10: 21 | AJ10: 6 | AO10: 21
A11: 7 | B11: 11379 | C11: NBC88W | D11: 0416200300 | E11: F | F11: 1035 | G11: X | H11: 95 | J11: =IF(G11="RSL","55","0") -> 0 | K11: =IF(G11="GVS","37.5",IF(G11="GVM","41.5",IF(G11="GVL","50",IF(G11="PCS","45.8",IF(G11="PCM","50",IF(G11="PCL","58.3","0")))))) -> 0 | N11: HENDRA | U11: =(T11-S11)*24 -> 0 | Y11: 7 | AD11: 22 | AJ11: 7 | AO11: 22
A12: 8 | B12: 11380 | C12: CDK18 | D12: 0415999716 | E12: M | F12: 1130 | G12: X | I12: 100 | J12: =IF(G12="RSL","55","0") -> 0 | K12: =IF(G12="GVS","37.5",IF(G12="GVM","41.5",IF(G12="GVL","50",IF(G12="PCS","45.8",IF(G12="PCM","50",IF(G12="PCL","58.3","0")))))) -> 0 | N12: HENDRA | U12: =(T12-S12)*24 -> 0 | Y12: 8 | AD12: 23 | AJ12: 8 | AO12: 23
A13: 9 | B13: 11381 | C13: CMH45S | D13: 0415363387 | E13: F | F13: 1230 | G13: D | I13: 75.75 | J13: =IF(G13="RSL","55","0") -> 0 | K13: =IF(G13="GVS","37.5",IF(G13="GVM","41.5",IF(G13="GVL","50",IF(G13="PCS","45.8",IF(G13="PCM","50",IF(G13="PCL","58.3","0")))))) -> 0 | N13: HENDRA | U13: =(T13-S13)*24 -> 0 | Y13: 9 | AD13: 24 | AJ13: 9 | AO13: 24
A14: 10 | B14: 11382 | C14: BWL72K | D14: 0400129911 | E14: F | F14: 1230 | G14: H | I14: 101 | J14: =IF(G14="RSL","55","0") -> 0 | K14: =IF(G14="GVS","37.5",IF(G14="GVM","41.5",IF(G14="GVL","50",IF(G14="PCS","45.8",IF(G14="PCM","50",IF(G14="PCL","58.3","0")))))) -> 0 | N14: HENDRA | U14: =(T14-S14)*24 -> 0 | Y14: 10 | AD14: 25 | AJ14: 10 | AO14: 25
A15: 11 | B15: 11383 | C15: DVO83D | D15: 0412483824 | E15: M | F15: 1400 | G15: W/H | I15: 111.1 | J15: =IF(G15="RSL","55","0") -> 0 | K15: =IF(G15="GVS","37.5",IF(G15="GVM","41.5",IF(G15="GVL","50",IF(G15="PCS","45.8",IF(G15="PCM","50",IF(G15="PCL","58.3","0")))))) -> 0 | N15: HENDRA | U15: =(T15-S15)*24 -> 0 | Y15: 11 | AD15: 26 | AJ15: 11 | AO15: 26
A16: 12 | J16: =IF(G16="RSL","55","0") -> 0 | K16: =IF(G16="GVS","37.5",IF(G16="GVM","41.5",IF(G16="GVL","50",IF(G16="PCS","45.8",IF(G16="PCM","50",IF(G16="PCL","58.3","0")))))) -> 0 | R16: =H32/U16 -> 0.44 | S16: =H32/(U16-U5) -> 0.64705882 | T16: =C32/U16 -> 51.774 | U16: =SUM(U5:U15) -> 25 | Y16: 12 | AD16: 27 | AJ16: 12 | AO16: 27
A17: 13 | J17: =IF(G17="RSL","55","0") -> 0 | K17: =IF(G17="GVS","37.5",IF(G17="GVM","41.5",IF(G17="GVL","50",IF(G17="PCS","45.8",IF(G17="PCM","50",IF(G17="PCL","58.3","0")))))) -> 0 | R17: Cars/T Hr ① | S17: Cars/T Hr ② | T17: Sales/T Hr | U17: Total Hours | Y17: 13 | AD17: 28 | AJ17: 13 | AO17: 28
A18: 14 | J18: =IF(G18="RSL","55","0") -> 0 | K18: =IF(G18="GVS","37.5",IF(G18="GVM","41.5",IF(G18="GVL","50",IF(G18="PCS","45.8",IF(G18="PCM","50",IF(G18="PCL","58.3","0")))))) -> 0 | R18: ITEM | S18: QTY | T18: AMT | U18: RMKS | Y18: 14 | AD18: 29 | AJ18: 14 | AO18: 29
A19: 15 | J19: =IF(G19="RSL","55","0") -> 0 | K19: =IF(G19="GVS","37.5",IF(G19="GVM","41.5",IF(G19="GVL","50",IF(G19="PCS","45.8",IF(G19="PCM","50",IF(G19="PCL","58.3","0")))))) -> 0 | R19: GV | S19: =COUNT(L5:M29,L37:M61,L69:M93) -> 0 | T19: =SUM(L5:M29,L37:M61,L69:M93) -> 0 | Y19: 15 | AD19: 30 | AJ19: 15 | AO19: 30
A20: 16 | J20: =IF(G20="RSL","55","0") -> 0 | K20: =IF(G20="GVS","37.5",IF(G20="GVM","41.5",IF(G20="GVL","50",IF(G20="PCS","45.8",IF(G20="PCM","50",IF(G20="PCL","58.3","0")))))) -> 0 | AD20: 31 | AO20: 31
A21: 17 | J21: =IF(G21="RSL","55","0") -> 0 | K21: =IF(G21="GVS","37.5",IF(G21="GVM","41.5",IF(G21="GVL","50",IF(G21="PCS","45.8",IF(G21="PCM","50",IF(G21="PCL","58.3","0")))))) -> 0
A22: 18 | J22: =IF(G22="RSL","55","0") -> 0 | K22: =IF(G22="GVS","37.5",IF(G22="GVM","41.5",IF(G22="GVL","50",IF(G22="PCS","45.8",IF(G22="PCM","50",IF(G22="PCL","58.3","0")))))) -> 0 | AD22: Total | AE22: =SUM(Z5:Z19,AE5:AE20) -> 0 | AF22: =SUM(AA5:AA19,AF5:AF20,) -> 0 | AG22: =SUM(AB5:AB19,AG5:AG20) -> 0 | AO22: Total | AP22: =SUM(AK5:AK19,AP5:AP20) -> 0 | AQ22: =SUM(AL5:AL19,AQ5:AQ20,) -> 0 | AR22: =SUM(AM5:AM19,AR5:AR20) -> 0
A23: 19 | J23: =IF(G23="RSL","55","0") -> 0 | K23: =IF(G23="GVS","37.5",IF(G23="GVM","41.5",IF(G23="GVL","50",IF(G23="PCS","45.8",IF(G23="PCM","50",IF(G23="PCL","58.3","0")))))) -> 0
A24: 20 | J24: =IF(G24="RSL","55","0") -> 0 | K24: =IF(G24="GVS","37.5",IF(G24="GVM","41.5",IF(G24="GVL","50",IF(G24="PCS","45.8",IF(G24="PCM","50",IF(G24="PCL","58.3","0")))))) -> 0 | R24: SMALL | S24: MEDIUM | T24: LARGE | U24: TOTAL | AD24: B2/GA TOTAL | AE24: B2 machine | AF24: GA machine | AG24: BLH machine | AH24: Wongo machine | AI24: Sub total
A25: 21 | J25: =IF(G25="RSL","55","0") -> 0 | K25: =IF(G25="GVS","37.5",IF(G25="GVM","41.5",IF(G25="GVL","50",IF(G25="PCS","45.8",IF(G25="PCM","50",IF(G25="PCL","58.3","0")))))) -> 0 | R25: =COUNTIF(G5:G29,"GV1")+COUNTIF(G37:G61,"GV1")+COUNTIF(G69:G93,"GV1") -> 0 | S25: =COUNTIF(G5:G29,"GV2")+COUNTIF(G37:G61,"GV2")+COUNTIF(G69:G93,"GV2") -> 0 | T25: =COUNTIF(G5:G29,"GV3")+COUNTIF(G37:G61,"GV3")+COUNTIF(G69:G93,"GV3") -> 0 | U25: =((C32+(R26+S26+T26)*0.5)) -> 1294.35 | AD25: =SUM(AE25:AF25) -> 0 | AE25: =SUM(AE22) -> 0 | AF25: =SUM(AP22) -> 0 | AG25: =SUM(AF22+AQ22) -> 0 | AH25: =AG22+AR22 -> 0 | AI25: =SUM(AE25:AH25) -> 0
A26: 22 | J26: =IF(G26="RSL","55","0") -> 0 | K26: =IF(G26="GVS","37.5",IF(G26="GVM","41.5",IF(G26="GVL","50",IF(G26="PCS","45.8",IF(G26="PCM","50",IF(G26="PCL","58.3","0")))))) -> 0 | R26: =R25*37.5 -> 0 | S26: =S25*41.5 -> 0 | T26: =T25*50 -> 0 | X26: Branch cards
A27: 23 | J27: =IF(G27="RSL","55","0") -> 0 | K27: =IF(G27="GVS","37.5",IF(G27="GVM","41.5",IF(G27="GVL","50",IF(G27="PCS","45.8",IF(G27="PCM","50",IF(G27="PCL","58.3","0")))))) -> 0 | R27: Expense | X27: 1 | Z27: -2745
A28: 24 | J28: =IF(G28="RSL","55","0") -> 0 | K28: =IF(G28="GVS","37.5",IF(G28="GVM","41.5",IF(G28="GVL","50",IF(G28="PCS","45.8",IF(G28="PCM","50",IF(G28="PCL","58.3","0")))))) -> 0 | X28: 2
A29: 25 | J29: =IF(G29="RSL","55","0") -> 0 | K29: =IF(G29="GVS","37.5",IF(G29="GVM","41.5",IF(G29="GVL","50",IF(G29="PCS","45.8",IF(G29="PCM","50",IF(G29="PCL","58.3","0")))))) -> 0 | X29: 3
A30: Page total | H30: =SUM(H5:H29) -> 365 | I30: =SUM(I5:I29) -> 929.35 | J30: =J5+J6+J7+J8+J9+J10+J11+J12+J13+J14+J15+J16+J18+J19+J17+J20+J22+J23+J21+J24+J25+J26+J27+J28+J29 -> 0 | K30: =K5+K6+K7+K8+K9+K10+K11+K12+K13+K14+K15+K16+K18+K19+K17+K20+K22+K23+K21+K24+K25+K26+K27+K28+K29 -> 0 | L30: =SUM(L5:L29) -> 0 | M30: =SUM(M5:M29) -> 0 | N30: CASH | O30: CARD | P30: GV | Q30: RSL | X30: 4
A31: Daily Total | H31: =H30+H62+H94 -> 365 | I31: =I30+I62+I94 -> 929.35 | J31: =J30+J62+J94 -> 0 | K31: =K30+K62+K94 -> 0 | L31: =L30+L62+L94 -> 0 | M31: =M30+M62+M94 -> 0 | N31: =COUNT(H5:H29,H37:H61,H69:H93) -> 3 | O31: =COUNT(I5:I29,I37:I61,I69:I93) -> 8 | P31: =COUNTIF(G5:G29,"G*")+COUNTIF(G37:G61,"G*")+COUNTIF(G69:G93,"G*")+COUNTIF(G5:G29,"P*")+COUNTIF(G37:G61,"P*")+COUNTIF(G69:G93,"P*") -> 0 | Q31: =COUNTIF(G5:G29,"RSL")+COUNTIF(G37:G61,"RSL")+COUNTIF(G69:G93,"RSL") -> 0 | R31: CASH CLOSING | S31: =H31+L31-U28-U29-U30 -> 365 | T31: =H31+I31+L31+M31 -> 1294.35 | X31: Subtotal | Z31: =SUM(Z27:Z30) -> -2745
A32: TOTAL SALES | C32: =H31+I31+J31+K31 -> 1294.35 | F32: No of Cars | H32: =COUNT(B5:B29,B37:B61,B69:B93) -> 11 | I32: Average | K32: =C32/H32 -> 117.66818 | N32: =H31/C32 -> 0.28199482 | O32: =I31/C32 -> 0.71800518 | P32: =K31/C32 -> 0 | Q32: =J31/C32 -> 0 | R32: CARD CLOSING | S32: =I31+M31 -> 929.35 | X32: B2 card | Z32: =I31 -> 929.35
A33: Daily Report | X33: Settlement | Z33: =SUM(Z31:Z32) -> -1815.65
A34: =A2 -> 28 - 9 - 2022 | H34: WEATHER | J34: =J2 -> SUNNY | L34: REPORT by | O34: =O2 -> HENDRA | R34: TOTAL STAFF | T34: =T2 -> 4
A36: No | B36: Docket No | C36: Reg No | D36: Mobile | E36: Gender | F36: TIME | G36: Service | H36: CASH | I36: CARD | J36: RSL | K36: GV | L36: GV CASH | M36: GV CARD | N36: O/Taker | O36: Comment | R36: NAME | S36: Time In | T36: Time out | U36: Total Hours
A37: =A29+1 -> 26 | J37: =IF(G37="RSL","55","0") -> 0 | K37: =IF(G37="GVS","37.5",IF(G37="GVM","41.5",IF(G37="GVL","50",IF(G37="PCS","45.8",IF(G37="PCM","50",IF(G37="PCL","58.3","0")))))) -> 0
A38: =A37+1 -> 27 | J38: =IF(G38="RSL","55","0") -> 0 | K38: =IF(G38="GVS","37.5",IF(G38="GVM","41.5",IF(G38="GVL","50",IF(G38="PCS","45.8",IF(G38="PCM","50",IF(G38="PCL","58.3","0")))))) -> 0
A39: =A38+1 -> 28 | J39: =IF(G39="RSL","55","0") -> 0 | K39: =IF(G39="GVS","37.5",IF(G39="GVM","41.5",IF(G39="GVL","50",IF(G39="PCS","45.8",IF(G39="PCM","50",IF(G39="PCL","58.3","0")))))) -> 0
A40: =A39+1 -> 29 | J40: =IF(G40="RSL","55","0") -> 0 | K40: =IF(G40="GVS","37.5",IF(G40="GVM","41.5",IF(G40="GVL","50",IF(G40="PCS","45.8",IF(G40="PCM","50",IF(G40="PCL","58.3","0")))))) -> 0
A41: =A40+1 -> 30 | J41: =IF(G41="RSL","55","0") -> 0 | K41: =IF(G41="GVS","37.5",IF(G41="GVM","41.5",IF(G41="GVL","50",IF(G41="PCS","45.8",IF(G41="PCM","50",IF(G41="PCL","58.3","0")))))) -> 0
A42: =A41+1 -> 31 | J42: =IF(G42="RSL","55","0") -> 0 | K42: =IF(G42="GVS","37.5",IF(G42="GVM","41.5",IF(G42="GVL","50",IF(G42="PCS","45.8",IF(G42="PCM","50",IF(G42="PCL","58.3","0")))))) -> 0
A43: =A42+1 -> 32 | J43: =IF(G43="RSL","55","0") -> 0 | K43: =IF(G43="GVS","37.5",IF(G43="GVM","41.5",IF(G43="GVL","50",IF(G43="PCS","45.8",IF(G43="PCM","50",IF(G43="PCL","58.3","0")))))) -> 0
A44: =A43+1 -> 33 | J44: =IF(G44="RSL","55","0") -> 0 | K44: =IF(G44="GVS","37.5",IF(G44="GVM","41.5",IF(G44="GVL","50",IF(G44="PCS","45.8",IF(G44="PCM","50",IF(G44="PCL","58.3","0")))))) -> 0
A45: =A44+1 -> 34 | J45: =IF(G45="RSL","55","0") -> 0 | K45: =IF(G45="GVS","37.5",IF(G45="GVM","41.5",IF(G45="GVL","50",IF(G45="PCS","45.8",IF(G45="PCM","50",IF(G45="PCL","58.3","0")))))) -> 0
A46: =A45+1 -> 35 | J46: =IF(G46="RSL","55","0") -> 0 | K46: =IF(G46="GVS","37.5",IF(G46="GVM","41.5",IF(G46="GVL","50",IF(G46="PCS","45.8",IF(G46="PCM","50",IF(G46="PCL","58.3","0")))))) -> 0
A47: =A46+1 -> 36 | J47: =IF(G47="RSL","55","0") -> 0 | K47: =IF(G47="GVS","37.5",IF(G47="GVM","41.5",IF(G47="GVL","50",IF(G47="PCS","45.8",IF(G47="PCM","50",IF(G47="PCL","58.3","0")))))) -> 0
A48: =A47+1 -> 37 | J48: =IF(G48="RSL","55","0") -> 0 | K48: =IF(G48="GVS","37.5",IF(G48="GVM","41.5",IF(G48="GVL","50",IF(G48="PCS","45.8",IF(G48="PCM","50",IF(G48="PCL","58.3","0")))))) -> 0
A49: =A48+1 -> 38 | J49: =IF(G49="RSL","55","0") -> 0 | K49: =IF(G49="GVS","37.5",IF(G49="GVM","41.5",IF(G49="GVL","50",IF(G49="PCS","45.8",IF(G49="PCM","50",IF(G49="PCL","58.3","0")))))) -> 0
... A61: =A60+1 -> 50 | J61: =IF(G61="RSL","55","0") -> 0 | K61: =IF(G61="GVS","37.5",IF(G61="GVM","41.5",IF(G61="GVL","50",IF(G61="PCS","45.8",IF(G61="PCM","50",IF(G61="PCL","58.3","0")))))) -> 0
A62: Page total | H62: =SUM(H37:H61) -> 0 | I62: =SUM(I37:I61) -> 0 | J62: =J61+J60+J59+J58+J57+J56+J55+J54+J53+J52+J51+J50+J49+J48+J47+J46+J45+J44+J43+J42+J41+J40+J39+J38+J37 -> 0 | K62: =K61+K60+K59+K58+K57+K56+K55+K54+K53+K52+K51+K50+K49+K48+K47+K46+K45+K44+K43+K42+K41+K40+K39+K38+K37 -> 0 | L62: =SUM(L37:L61) -> 0 | M62: =SUM(M37:M61) -> 0
R64: Page: 2
A65: Daily Report
A66: =A34 -> 28 - 9 - 2022 | H66: WEATHER | J66: =J34 -> SUNNY | L66: REPORT by | O66: =O34 -> HENDRA | R66: TOTAL STAFF | T66: =T34 -> 4
A68: No | B68: Docket No | C68: Reg No | D68: Mobile | E68: Gender | F68: TIME | G68: Service | H68: CASH | I68: CARD | J68: RSL | K68: GV | L68: GV CASH | M68: GV CARD | N68: O/Taker | O68: Comment | R68: NAME | S68: Time In | T68: Time out | U68: Total Hours
A69: =A61+1 -> 51 | J69: =IF(G69="RSL","55","0") -> 0 | K69: =IF(G69="GVS","37.5",IF(G69="GVM","41.5",IF(G69="GVL","50",IF(G69="PCS","45.8",IF(G69="PCM","50",IF(G69="PCL","58.3","0")))))) -> 0
A70: =A69+1 -> 52 | J70: =IF(G70="RSL","55","0") -> 0 | K70: =IF(G70="GVS","37.5",IF(G70="GVM","41.5",IF(G70="GVL","50",IF(G70="PCS","45.8",IF(G70="PCM","50",IF(G70="PCL","58.3","0")))))) -> 0
A71: =A70+1 -> 53 | J71: =IF(G71="RSL","55","0") -> 0 | K71: =IF(G71="GVS","37.5",IF(G71="GVM","41.5",IF(G71="GVL","50",IF(G71="PCS","45.8",IF(G71="PCM","50",IF(G71="PCL","58.3","0")))))) -> 0
A72: =A71+1 -> 54 | J72: =IF(G72="RSL","55","0") -> 0 | K72: =IF(G72="GVS","37.5",IF(G72="GVM","41.5",IF(G72="GVL","50",IF(G72="PCS","45.8",IF(G72="PCM","50",IF(G72="PCL","58.3","0")))))) -> 0
A73: =A72+1 -> 55 | J73: =IF(G73="RSL","55","0") -> 0 | K73: =IF(G73="GVS","37.5",IF(G73="GVM","41.5",IF(G73="GVL","50",IF(G73="PCS","45.8",IF(G73="PCM","50",IF(G73="PCL","58.3","0")))))) -> 0
A74: =A73+1 -> 56 | J74: =IF(G74="RSL","55","0") -> 0 | K74: =IF(G74="GVS","37.5",IF(G74="GVM","41.5",IF(G74="GVL","50",IF(G74="PCS","45.8",IF(G74="PCM","50",IF(G74="PCL","58.3","0")))))) -> 0
A75: =A74+1 -> 57 | J75: =IF(G75="RSL","55","0") -> 0 | K75: =IF(G75="GVS","37.5",IF(G75="GVM","41.5",IF(G75="GVL","50",IF(G75="PCS","45.8",IF(G75="PCM","50",IF(G75="PCL","58.3","0")))))) -> 0
A76: =A75+1 -> 58 | J76: =IF(G76="RSL","55","0") -> 0 | K76: =IF(G76="GVS","37.5",IF(G76="GVM","41.5",IF(G76="GVL","50",IF(G76="PCS","45.8",IF(G76="PCM","50",IF(G76="PCL","58.3","0")))))) -> 0
A77: =A76+1 -> 59 | J77: =IF(G77="RSL","55","0") -> 0 | K77: =IF(G77="GVS","37.5",IF(G77="GVM","41.5",IF(G77="GVL","50",IF(G77="PCS","45.8",IF(G77="PCM","50",IF(G77="PCL","58.3","0")))))) -> 0
A78: =A77+1 -> 60 | J78: =IF(G78="RSL","55","0") -> 0 | K78: =IF(G78="GVS","37.5",IF(G78="GVM","41.5",IF(G78="GVL","50",IF(G78="PCS","45.8",IF(G78="PCM","50",IF(G78="PCL","58.3","0")))))) -> 0
A79: =A78+1 -> 61 | J79: =IF(G79="RSL","55","0") -> 0 | K79: =IF(G79="GVS","37.5",IF(G79="GVM","41.5",IF(G79="GVL","50",IF(G79="PCS","45.8",IF(G79="PCM","50",IF(G79="PCL","58.3","0")))))) -> 0
A80: =A79+1 -> 62 | J80: =IF(G80="RSL","55","0") -> 0 | K80: =IF(G80="GVS","37.5",IF(G80="GVM","41.5",IF(G80="GVL","50",IF(G80="PCS","45.8",IF(G80="PCM","50",IF(G80="PCL","58.3","0")))))) -> 0
A81: =A80+1 -> 63 | J81: =IF(G81="RSL","55","0") -> 0 | K81: =IF(G81="GVS","37.5",IF(G81="GVM","41.5",IF(G81="GVL","50",IF(G81="PCS","45.8",IF(G81="PCM","50",IF(G81="PCL","58.3","0")))))) -> 0
... A93: =A92+1 -> 75 | J93: =IF(G93="RSL","55","0") -> 0 | K93: =IF(G93="GVS","37.5",IF(G93="GVM","41.5",IF(G93="GVL","50",IF(G93="PCS","45.8",IF(G93="PCM","50",IF(G93="PCL","58.3","0")))))) -> 0
A94: Page total | H94: =SUM(H69:H93) -> 0 | I94: =SUM(I69:I93) -> 0 | J94: =J93+J92+J91+J90+J89+J88+J87+J86+J85+J84+J83+J82+J81+J80+J79+J78+J77+J76+J75+J74+J73+J72+J71+J70+J69 -> 0 | K94: =K93+K92+K91+K90+K89+K88+K87+K86+K85+K84+K83+K82+K81+K80+K79+K78+K77+K76+K75+K74+K73+K72+K71+K70+K69 -> 0 | L94: =SUM(L69:L93) -> 0 | M94: =SUM(M69:M93) -> 0
R96: Page: 3

Sheet THU
A1: B2 Daily Report
A2: 29-09-2022 | H2: WEATHER | J2: SUNNY | L2: REPORT BY | O2: JOHN | R2: TOTAL STAFF | T2: 5 | X2: Merchant machine usage at B2 | AA2: Settle amount | AI2: Merchant machine usage at GA | AL2: Settle amount
A4: No | B4: Docket No | C4: Reg No | D4: Mobile | E4: Gender | F4: TIME | G4: Service | H4: CASH | I4: CARD | J4: RSL | K4: GV | L4: GV CASH | M4: GV CARD | N4: O/Taker | O4: Comment | R4: NAME | S4: Time In | T4: Time out | U4: Total Hours | Z4: B2 machine | AA4: BLH machine | AB4: Wongo | AE4: B2 machine | AF4: BLH machine | AG4: Wongo | AK4: GA machine | AL4: BLH machine | AM4: Wongo | AP4: GA machine | AQ4: BLH machine | AR4: Wongo
A5: 1 | B5: 11384 | C5: X566 | D5: 0431875858 | E5: M | F5: 915 | G5: PCL | J5: =IF(G5="RSL","55","0") -> 0 | K5: 79.1 | N5: HENDRA | O5: 22013(5/6) | R5: JOHN | S5: 0.33333333 | T5: 0.69791667 | U5: =(T5-S5)*24 -> 8.75 | X5: NOV | Y5: 1 | AD5: 16 | AI5: NOV | AJ5: 1 | AO5: 16
A6: 2 | B6: 11385 | C6: EIA86L | D6: 0477204199 | E6: F | F6: 920 | G6: D | H6: 75 | J6: =IF(G6="RSL","55","0") -> 0 | K6: =IF(G6="GVS","37.5",IF(G6="GVM","41.5",IF(G6="GVL","50",IF(G6="PCS","45.8",IF(G6="PCM","50",IF(G6="PCL","58.3","0")))))) -> 0 | N6: HENDRA | R6: HENDRA | S6: 0.34375 | T6: 0.69791667 | U6: =(T6-S6)*24 -> 8.5 | W6: M | Y6: 2 | AD6: 17 | AJ6: 2 | AO6: 17
A7: 3 | B7: 11386 | C7: MSV333 | D7: 0447239698 | E7: F | F7: 925 | G7: X | H7: 95 | J7: =IF(G7="RSL","55","0") -> 0 | K7: =IF(G7="GVS","37.5",IF(G7="GVM","41.5",IF(G7="GVL","50",IF(G7="PCS","45.8",IF(G7="PCM","50",IF(G7="PCL","58.3","0")))))) -> 0 | N7: JOHN | R7: ARIANTO | S7: 0.41666667 | T7: 0.63541667 | U7: =(T7-S7)*24 -> 5.25 | W7: F | Y7: 3 | AD7: 18 | AJ7: 3 | AO7: 18
A8: 4 | B8: 11387 | C8: DVW72Q | D8: 0418881485 | E8: M | F8: 945 | G8: PCL | J8: =IF(G8="RSL","55","0") -> 0 | K8: 79.1 | N8: JOHN | O8: 22065(1/6) | R8: VINNY | S8: 0.4375 | T8: 0.69791667 | U8: =(T8-S8)*24 -> 6.25 | Y8: 4 | AD8: 19 | AJ8: 4 | AO8: 19
A9: 5 | B9: 11388 | C9: SKU881 | D9: 0404318904 | E9: M | F9: 945 | G9: RSL | J9: 110 | K9: =IF(G9="GVS","37.5",IF(G9="GVM","41.5",IF(G9="GVL","50",IF(G9="PCS","45.8",IF(G9="PCM","50",IF(G9="PCL","58.3","0")))))) -> 0 | N9: JOHN | O9: 202208034,202207024(X) | R9: CALAN OCTEC | S9: 0.45833333 | T9: 0.66666667 | U9: =(T9-S9)*24 -> 5 | X9: EXCL RSL | Y9: 5 | AD9: 20 | AJ9: 5 | AO9: 20
A10: 6 | B10: 11389 | C10: ECG68Q | D10: 0417230580 | E10: F | F10: 1025 | G10: X | I10: 75 | J10: =IF(G10="RSL","55","0") -> 0 | K10: =IF(G10="GVS","37.5",IF(G10="GVM","41.5",IF(G10="GVL","50",IF(G10="PCS","45.8",IF(G10="PCM","50",IF(G10="PCL","58.3","0")))))) -> 0 | N10: JOHN | R10: ANDREW OCTEC | S10: 0.5 | T10: 0.66666667 | U10: =(T10-S10)*24 -> 4 | Y10: 6 | AD10: 21 | AJ10: 6 | AO10: 21
A11: 7 | B11: 11390 | C11: DSJ13E | D11: 0408518552 | E11: F | F11: 1200 | G11: X | H11: 75 | J11: =IF(G11="RSL","55","0") -> 0 | K11: =IF(G11="GVS","37.5",IF(G11="GVM","41.5",IF(G11="GVL","50",IF(G11="PCS","45.8",IF(G11="PCM","50",IF(G11="PCL","58.3","0")))))) -> 0 | N11: JOHN | R11: JAIKE | S11: 0.39583333 | T11: 0.4375 | U11: =(T11-S11)*24 -> 1 | Y11: 7 | AD11: 22 | AJ11: 7 | AO11: 22
A12: 8 | B12: 11391 | C12: EPC29X | D12: 0403082345 | E12: F | F12: 1225 | G12: X | H12: 95 | J12: =IF(G12="RSL","55","0") -> 0 | K12: =IF(G12="GVS","37.5",IF(G12="GVM","41.5",IF(G12="GVL","50",IF(G12="PCS","45.8",IF(G12="PCM","50",IF(G12="PCL","58.3","0")))))) -> 0 | N12: JOHN | U12: =(T12-S12)*24 -> 0 | Y12: 8 | AD12: 23 | AJ12: 8 | AO12: 23
A13: 9 | B13: 11392 | C13: 2681 | D13: 0412413140 | E13: F | F13: 1300 | G13: X | I13: 95 | J13: =IF(G13="RSL","55","0") -> 0 | K13: =IF(G13="GVS","37.5",IF(G13="GVM","41.5",IF(G13="GVL","50",IF(G13="PCS","45.8",IF(G13="PCM","50",IF(G13="PCL","58.3","0")))))) -> 0 | N13: JOHN | U13: =(T13-S13)*24 -> 0 | Y13: 9 | AD13: 24 | AJ13: 9 | AO13: 24
A14: 10 | B14: 11393 | C14: DXK85G | D14: 0412413140 | E14: F | F14: 1300 | G14: X | I14: 76.7 | J14: =IF(G14="RSL","55","0") -> 0 | K14: =IF(G14="GVS","37.5",IF(G14="GVM","41.5",IF(G14="GVL","50",IF(G14="PCS","45.8",IF(G14="PCM","50",IF(G14="PCL","58.3","0")))))) -> 0 | N14: JOHN | U14: =(T14-S14)*24 -> 0 | Y14: 10 | AD14: 25 | AJ14: 10 | AO14: 25
A15: 11 | B15: 11394 | C15: ESN71P | D15: 0421630631 | E15: F | F15: 1320 | G15: X | H15: 95 | J15: =IF(G15="RSL","55","0") -> 0 | K15: =IF(G15="GVS","37.5",IF(G15="GVM","41.5",IF(G15="GVL","50",IF(G15="PCS","45.8",IF(G15="PCM","50",IF(G15="PCL","58.3","0")))))) -> 0 | N15: JOHN | U15: =(T15-S15)*24 -> 0 | Y15: 11 | AD15: 26 | AJ15: 11 | AO15: 26
A16: 12 | B16: 11395 | C16: DLLOX | D16: 0433017205 | E16: M | F16: 1330 | G16: PCL | J16: =IF(G16="RSL","55","0") -> 0 | K16: 79.1 | N16: JOHN | O16: 22077(2/6) | R16: =H32/U16 -> 0.33548387 | S16: =H32/(U16-U5) -> 0.43333333 | T16: =C32/U16 -> 29.006452 | U16: =SUM(U5:U15) -> 38.75 | Y16: 12 | AD16: 27 | AJ16: 12 | AO16: 27
A17: 13 | B17: 11396 | C17: EIM54Y | D17: 0409921951 | E17: M | F17: 1400 | G17: X | I17: 95 | J17: =IF(G17="RSL","55","0") -> 0 | K17: =IF(G17="GVS","37.5",IF(G17="GVM","41.5",IF(G17="GVL","50",IF(G17="PCS","45.8",IF(G17="PCM","50",IF(G17="PCL","58.3","0")))))) -> 0 | N17: JOHN | R17: Cars/T Hr ① | S17: Cars/T Hr ② | T17: Sales/T Hr | U17: Total Hours | Y17: 13 | AD17: 28 | AJ17: 13 | AO17: 28
A18: 14 | J18: =IF(G18="RSL","55","0") -> 0 | K18: =IF(G18="GVS","37.5",IF(G18="GVM","41.5",IF(G18="GVL","50",IF(G18="PCS","45.8",IF(G18="PCM","50",IF(G18="PCL","58.3","0")))))) -> 0 | R18: ITEM | S18: QTY | T18: AMT | U18: RMKS | Y18: 14 | AD18: 29 | AJ18: 14 | AO18: 29
A19: 15 | J19: =IF(G19="RSL","55","0") -> 0 | K19: =IF(G19="GVS","37.5",IF(G19="GVM","41.5",IF(G19="GVL","50",IF(G19="PCS","45.8",IF(G19="PCM","50",IF(G19="PCL","58.3","0")))))) -> 0 | R19: GV | S19: =COUNT(L5:M29,L37:M61,L69:M93) -> 0 | T19: =SUM(L5:M29,L37:M61,L69:M93) -> 0 | Y19: 15 | AD19: 30 | AJ19: 15 | AO19: 30
A20: 16 | J20: =IF(G20="RSL","55","0") -> 0 | K20: =IF(G20="GVS","37.5",IF(G20="GVM","41.5",IF(G20="GVL","50",IF(G20="PCS","45.8",IF(G20="PCM","50",IF(G20="PCL","58.3","0")))))) -> 0 | AD20: 31 | AO20: 31
A21: 17 | J21: =IF(G21="RSL","55","0") -> 0 | K21: =IF(G21="GVS","37.5",IF(G21="GVM","41.5",IF(G21="GVL","50",IF(G21="PCS","45.8",IF(G21="PCM","50",IF(G21="PCL","58.3","0")))))) -> 0
A22: 18 | J22: =IF(G22="RSL","55","0") -> 0 | K22: =IF(G22="GVS","37.5",IF(G22="GVM","41.5",IF(G22="GVL","50",IF(G22="PCS","45.8",IF(G22="PCM","50",IF(G22="PCL","58.3","0")))))) -> 0 | AD22: Total | AE22: =SUM(Z5:Z19,AE5:AE20) -> 0 | AF22: =SUM(AA5:AA19,AF5:AF20,) -> 0 | AG22: =SUM(AB5:AB19,AG5:AG20) -> 0 | AO22: Total | AP22: =SUM(AK5:AK19,AP5:AP20) -> 0 | AQ22: =SUM(AL5:AL19,AQ5:AQ20,) -> 0 | AR22: =SUM(AM5:AM19,AR5:AR20) -> 0
A23: 19 | J23: =IF(G23="RSL","55","0") -> 0 | K23: =IF(G23="GVS","37.5",IF(G23="GVM","41.5",IF(G23="GVL","50",IF(G23="PCS","45.8",IF(G23="PCM","50",IF(G23="PCL","58.3","0")))))) -> 0
A24: 20 | J24: =IF(G24="RSL","55","0") -> 0 | K24: =IF(G24="GVS","37.5",IF(G24="GVM","41.5",IF(G24="GVL","50",IF(G24="PCS","45.8",IF(G24="PCM","50",IF(G24="PCL","58.3","0")))))) -> 0 | R24: SMALL | S24: MEDIUM | T24: LARGE | U24: TOTAL | AD24: B2/GA TOTAL | AE24: B2 machine | AF24: GA machine | AG24: BLH machine | AH24: Wongo machine | AI24: Sub total
A25: 21 | J25: =IF(G25="RSL","55","0") -> 0 | K25: =IF(G25="GVS","37.5",IF(G25="GVM","41.5",IF(G25="GVL","50",IF(G25="PCS","45.8",IF(G25="PCM","50",IF(G25="PCL","58.3","0")))))) -> 0 | R25: =COUNTIF(G5:G29,"GV1")+COUNTIF(G37:G61,"GV1")+COUNTIF(G69:G93,"GV1") -> 0 | S25: =COUNTIF(G5:G29,"GV2")+COUNTIF(G37:G61,"GV2")+COUNTIF(G69:G93,"GV2") -> 0 | T25: =COUNTIF(G5:G29,"GV3")+COUNTIF(G37:G61,"GV3")+COUNTIF(G69:G93,"GV3") -> 0 | U25: =((C32+(R26+S26+T26)*0.5)) -> 1124 | AD25: =SUM(AE25:AF25) -> 0 | AE25: =SUM(AE22) -> 0 | AF25: =SUM(AP22) -> 0 | AG25: =SUM(AF22+AQ22) -> 0 | AH25: =AG22+AR22 -> 0 | AI25: =SUM(AE25:AH25) -> 0
A26: 22 | J26: =IF(G26="RSL","55","0") -> 0 | K26: =IF(G26="GVS","37.5",IF(G26="GVM","41.5",IF(G26="GVL","50",IF(G26="PCS","45.8",IF(G26="PCM","50",IF(G26="PCL","58.3","0")))))) -> 0 | R26: =R25*37.5 -> 0 | S26: =S25*41.5 -> 0 | T26: =T25*50 -> 0 | X26: Branch cards
A27: 23 | J27: =IF(G27="RSL","55","0") -> 0 | K27: =IF(G27="GVS","37.5",IF(G27="GVM","41.5",IF(G27="GVL","50",IF(G27="PCS","45.8",IF(G27="PCM","50",IF(G27="PCL","58.3","0")))))) -> 0 | R27: Expense | X27: 1 | Z27: -2745
A28: 24 | J28: =IF(G28="RSL","55","0") -> 0 | K28: =IF(G28="GVS","37.5",IF(G28="GVM","41.5",IF(G28="GVL","50",IF(G28="PCS","45.8",IF(G28="PCM","50",IF(G28="PCL","58.3","0")))))) -> 0 | X28: 2
A29: 25 | J29: =IF(G29="RSL","55","0") -> 0 | K29: =IF(G29="GVS","37.5",IF(G29="GVM","41.5",IF(G29="GVL","50",IF(G29="PCS","45.8",IF(G29="PCM","50",IF(G29="PCL","58.3","0")))))) -> 0 | X29: 3
A30: Page total | H30: =SUM(H5:H29) -> 435 | I30: =SUM(I5:I29) -> 341.7 | J30: =J5+J6+J7+J8+J9+J10+J11+J12+J13+J14+J15+J16+J18+J19+J17+J20+J22+J23+J21+J24+J25+J26+J27+J28+J29 -> 110 | K30: =K5+K6+K7+K8+K9+K10+K11+K12+K13+K14+K15+K16+K18+K19+K17+K20+K22+K23+K21+K24+K25+K26+K27+K28+K29 -> 237.3 | L30: =SUM(L5:L29) -> 0 | M30: =SUM(M5:M29) -> 0 | N30: CASH | O30: CARD | P30: GV | Q30: RSL | X30: 4
A31: Daily Total | H31: =H30+H62+H94 -> 435 | I31: =I30+I62+I94 -> 341.7 | J31: =J30+J62+J94 -> 110 | K31: =K30+K62+K94 -> 237.3 | L31: =L30+L62+L94 -> 0 | M31: =M30+M62+M94 -> 0 | N31: =COUNT(H5:H29,H37:H61,H69:H93) -> 5 | O31: =COUNT(I5:I29,I37:I61,I69:I93) -> 4 | P31: =COUNTIF(G5:G29,"G*")+COUNTIF(G37:G61,"G*")+COUNTIF(G69:G93,"G*")+COUNTIF(G5:G29,"P*")+COUNTIF(G37:G61,"P*")+COUNTIF(G69:G93,"P*") -> 3 | Q31: =COUNTIF(G5:G29,"RSL")+COUNTIF(G37:G61,"RSL")+COUNTIF(G69:G93,"RSL") -> 1 | R31: CASH CLOSING | S31: =H31+L31-U28-U29-U30 -> 435 | T31: =H31+I31+L31+M31 -> 776.7 | X31: Subtotal | Z31: =SUM(Z27:Z30) -> -2745
A32: TOTAL SALES | C32: =H31+I31+J31+K31 -> 1124 | F32: No of Cars | H32: =COUNT(B5:B29,B37:B61,B69:B93) -> 13 | I32: Average | K32: =C32/H32 -> 86.461538 | N32: =H31/C32 -> 0.38701068 | O32: =I31/C32 -> 0.30400356 | P32: =K31/C32 -> 0.211121 | Q32: =J31/C32 -> 0.097864769 | R32: CARD CLOSING | S32: =I31+M31 -> 341.7 | X32: B2 card | Z32: =I31 -> 341.7
A33: Daily Report | X33: Settlement | Z33: =SUM(Z31:Z32) -> -2403.3
A34: =A2 -> 29-09-2022 | H34: WEATHER | J34: =J2 -> SUNNY | L34: REPORT by | O34: =O2 -> JOHN | R34: TOTAL STAFF | T34: =T2 -> 5
A36: No | B36: Docket No | C36: Reg No | D36: Mobile | E36: Gender | F36: TIME | G36: Service | H36: CASH | I36: CARD | J36: RSL | K36: GV | L36: GV CASH | M36: GV CARD | N36: O/Taker | O36: Comment | R36: NAME | S36: Time In | T36: Time out | U36: Total Hours
A37: =A29+1 -> 26 | J37: =IF(G37="RSL","55","0") -> 0 | K37: =IF(G37="GVS","37.5",IF(G37="GVM","41.5",IF(G37="GVL","50",IF(G37="PCS","45.8",IF(G37="PCM","50",IF(G37="PCL","58.3","0")))))) -> 0
A38: =A37+1 -> 27 | J38: =IF(G38="RSL","55","0") -> 0 | K38: =IF(G38="GVS","37.5",IF(G38="GVM","41.5",IF(G38="GVL","50",IF(G38="PCS","45.8",IF(G38="PCM","50",IF(G38="PCL","58.3","0")))))) -> 0
A39: =A38+1 -> 28 | J39: =IF(G39="RSL","55","0") -> 0 | K39: =IF(G39="GVS","37.5",IF(G39="GVM","41.5",IF(G39="GVL","50",IF(G39="PCS","45.8",IF(G39="PCM","50",IF(G39="PCL","58.3","0")))))) -> 0
A40: =A39+1 -> 29 | J40: =IF(G40="RSL","55","0") -> 0 | K40: =IF(G40="GVS","37.5",IF(G40="GVM","41.5",IF(G40="GVL","50",IF(G40="PCS","45.8",IF(G40="PCM","50",IF(G40="PCL","58.3","0")))))) -> 0
A41: =A40+1 -> 30 | J41: =IF(G41="RSL","55","0") -> 0 | K41: =IF(G41="GVS","37.5",IF(G41="GVM","41.5",IF(G41="GVL","50",IF(G41="PCS","45.8",IF(G41="PCM","50",IF(G41="PCL","58.3","0")))))) -> 0
A42: =A41+1 -> 31 | J42: =IF(G42="RSL","55","0") -> 0 | K42: =IF(G42="GVS","37.5",IF(G42="GVM","41.5",IF(G42="GVL","50",IF(G42="PCS","45.8",IF(G42="PCM","50",IF(G42="PCL","58.3","0")))))) -> 0
A43: =A42+1 -> 32 | J43: =IF(G43="RSL","55","0") -> 0 | K43: =IF(G43="GVS","37.5",IF(G43="GVM","41.5",IF(G43="GVL","50",IF(G43="PCS","45.8",IF(G43="PCM","50",IF(G43="PCL","58.3","0")))))) -> 0
A44: =A43+1 -> 33 | J44: =IF(G44="RSL","55","0") -> 0 | K44: =IF(G44="GVS","37.5",IF(G44="GVM","41.5",IF(G44="GVL","50",IF(G44="PCS","45.8",IF(G44="PCM","50",IF(G44="PCL","58.3","0")))))) -> 0
A45: =A44+1 -> 34 | J45: =IF(G45="RSL","55","0") -> 0 | K45: =IF(G45="GVS","37.5",IF(G45="GVM","41.5",IF(G45="GVL","50",IF(G45="PCS","45.8",IF(G45="PCM","50",IF(G45="PCL","58.3","0")))))) -> 0
A46: =A45+1 -> 35 | J46: =IF(G46="RSL","55","0") -> 0 | K46: =IF(G46="GVS","37.5",IF(G46="GVM","41.5",IF(G46="GVL","50",IF(G46="PCS","45.8",IF(G46="PCM","50",IF(G46="PCL","58.3","0")))))) -> 0
A47: =A46+1 -> 36 | J47: =IF(G47="RSL","55","0") -> 0 | K47: =IF(G47="GVS","37.5",IF(G47="GVM","41.5",IF(G47="GVL","50",IF(G47="PCS","45.8",IF(G47="PCM","50",IF(G47="PCL","58.3","0")))))) -> 0
A48: =A47+1 -> 37 | J48: =IF(G48="RSL","55","0") -> 0 | K48: =IF(G48="GVS","37.5",IF(G48="GVM","41.5",IF(G48="GVL","50",IF(G48="PCS","45.8",IF(G48="PCM","50",IF(G48="PCL","58.3","0")))))) -> 0
A49: =A48+1 -> 38 | J49: =IF(G49="RSL","55","0") -> 0 | K49: =IF(G49="GVS","37.5",IF(G49="GVM","41.5",IF(G49="GVL","50",IF(G49="PCS","45.8",IF(G49="PCM","50",IF(G49="PCL","58.3","0")))))) -> 0
... A61: =A60+1 -> 50 | J61: =IF(G61="RSL","55","0") -> 0 | K61: =IF(G61="GVS","37.5",IF(G61="GVM","41.5",IF(G61="GVL","50",IF(G61="PCS","45.8",IF(G61="PCM","50",IF(G61="PCL","58.3","0")))))) -> 0
A62: Page total | H62: =SUM(H37:H61) -> 0 | I62: =SUM(I37:I61) -> 0 | J62: =J61+J60+J59+J58+J57+J56+J55+J54+J53+J52+J51+J50+J49+J48+J47+J46+J45+J44+J43+J42+J41+J40+J39+J38+J37 -> 0 | K62: =K61+K60+K59+K58+K57+K56+K55+K54+K53+K52+K51+K50+K49+K48+K47+K46+K45+K44+K43+K42+K41+K40+K39+K38+K37 -> 0 | L62: =SUM(L37:L61) -> 0 | M62: =SUM(M37:M61) -> 0
R64: Page: 2
A65: Daily Report
A66: =A34 -> 29-09-2022 | H66: WEATHER | J66: =J34 -> SUNNY | L66: REPORT by | O66: =O34 -> JOHN | R66: TOTAL STAFF | T66: =T34 -> 5
A68: No | B68: Docket No | C68: Reg No | D68: Mobile | E68: Gender | F68: TIME | G68: Service | H68: CASH | I68: CARD | J68: RSL | K68: GV | L68: GV CASH | M68: GV CARD | N68: O/Taker | O68: Comment | R68: NAME | S68: Time In | T68: Time out | U68: Total Hours
A69: =A61+1 -> 51 | J69: =IF(G69="RSL","55","0") -> 0 | K69: =IF(G69="GVS","37.5",IF(G69="GVM","41.5",IF(G69="GVL","50",IF(G69="PCS","45.8",IF(G69="PCM","50",IF(G69="PCL","58.3","0")))))) -> 0
A70: =A69+1 -> 52 | J70: =IF(G70="RSL","55","0") -> 0 | K70: =IF(G70="GVS","37.5",IF(G70="GVM","41.5",IF(G70="GVL","50",IF(G70="PCS","45.8",IF(G70="PCM","50",IF(G70="PCL","58.3","0")))))) -> 0
A71: =A70+1 -> 53 | J71: =IF(G71="RSL","55","0") -> 0 | K71: =IF(G71="GVS","37.5",IF(G71="GVM","41.5",IF(G71="GVL","50",IF(G71="PCS","45.8",IF(G71="PCM","50",IF(G71="PCL","58.3","0")))))) -> 0
A72: =A71+1 -> 54 | J72: =IF(G72="RSL","55","0") -> 0 | K72: =IF(G72="GVS","37.5",IF(G72="GVM","41.5",IF(G72="GVL","50",IF(G72="PCS","45.8",IF(G72="PCM","50",IF(G72="PCL","58.3","0")))))) -> 0
A73: =A72+1 -> 55 | J73: =IF(G73="RSL","55","0") -> 0 | K73: =IF(G73="GVS","37.5",IF(G73="GVM","41.5",IF(G73="GVL","50",IF(G73="PCS","45.8",IF(G73="PCM","50",IF(G73="PCL","58.3","0")))))) -> 0
A74: =A73+1 -> 56 | J74: =IF(G74="RSL","55","0") -> 0 | K74: =IF(G74="GVS","37.5",IF(G74="GVM","41.5",IF(G74="GVL","50",IF(G74="PCS","45.8",IF(G74="PCM","50",IF(G74="PCL","58.3","0")))))) -> 0
A75: =A74+1 -> 57 | J75: =IF(G75="RSL","55","0") -> 0 | K75: =IF(G75="GVS","37.5",IF(G75="GVM","41.5",IF(G75="GVL","50",IF(G75="PCS","45.8",IF(G75="PCM","50",IF(G75="PCL","58.3","0")))))) -> 0
A76: =A75+1 -> 58 | J76: =IF(G76="RSL","55","0") -> 0 | K76: =IF(G76="GVS","37.5",IF(G76="GVM","41.5",IF(G76="GVL","50",IF(G76="PCS","45.8",IF(G76="PCM","50",IF(G76="PCL","58.3","0")))))) -> 0
A77: =A76+1 -> 59 | J77: =IF(G77="RSL","55","0") -> 0 | K77: =IF(G77="GVS","37.5",IF(G77="GVM","41.5",IF(G77="GVL","50",IF(G77="PCS","45.8",IF(G77="PCM","50",IF(G77="PCL","58.3","0")))))) -> 0
A78: =A77+1 -> 60 | J78: =IF(G78="RSL","55","0") -> 0 | K78: =IF(G78="GVS","37.5",IF(G78="GVM","41.5",IF(G78="GVL","50",IF(G78="PCS","45.8",IF(G78="PCM","50",IF(G78="PCL","58.3","0")))))) -> 0
A79: =A78+1 -> 61 | J79: =IF(G79="RSL","55","0") -> 0 | K79: =IF(G79="GVS","37.5",IF(G79="GVM","41.5",IF(G79="GVL","50",IF(G79="PCS","45.8",IF(G79="PCM","50",IF(G79="PCL","58.3","0")))))) -> 0
A80: =A79+1 -> 62 | J80: =IF(G80="RSL","55","0") -> 0 | K80: =IF(G80="GVS","37.5",IF(G80="GVM","41.5",IF(G80="GVL","50",IF(G80="PCS","45.8",IF(G80="PCM","50",IF(G80="PCL","58.3","0")))))) -> 0
A81: =A80+1 -> 63 | J81: =IF(G81="RSL","55","0") -> 0 | K81: =IF(G81="GVS","37.5",IF(G81="GVM","41.5",IF(G81="GVL","50",IF(G81="PCS","45.8",IF(G81="PCM","50",IF(G81="PCL","58.3","0")))))) -> 0
... A93: =A92+1 -> 75 | J93: =IF(G93="RSL","55","0") -> 0 | K93: =IF(G93="GVS","37.5",IF(G93="GVM","41.5",IF(G93="GVL","50",IF(G93="PCS","45.8",IF(G93="PCM","50",IF(G93="PCL","58.3","0")))))) -> 0
A94: Page total | H94: =SUM(H69:H93) -> 0 | I94: =SUM(I69:I93) -> 0 | J94: =J93+J92+J91+J90+J89+J88+J87+J86+J85+J84+J83+J82+J81+J80+J79+J78+J77+J76+J75+J74+J73+J72+J71+J70+J69 -> 0 | K94: =K93+K92+K91+K90+K89+K88+K87+K86+K85+K84+K83+K82+K81+K80+K79+K78+K77+K76+K75+K74+K73+K72+K71+K70+K69 -> 0 | L94: =SUM(L69:L93) -> 0 | M94: =SUM(M69:M93) -> 0
R96: Page: 3

Sheet FRI
A1: B2 Daily Report
A2: 30 - 9 - 2022 | H2: WEATHER | J2: SHOWER | L2: REPORT BY | O2: HENDRA | R2: TOTAL STAFF | T2: 4 | X2: Merchant machine usage at B2 | AA2: Settle amount | AI2: Merchant machine usage at GA | AL2: Settle amount
A4: No | B4: Docket No | C4: Reg No | D4: Mobile | E4: Gender | F4: TIME | G4: Service | H4: CASH | I4: CARD | J4: RSL | K4: GV | L4: GV CASH | M4: GV CARD | N4: O/Taker | O4: Comment | R4: NAME | S4: Time In | T4: Time out | U4: Total Hours | Z4: B2 machine | AA4: BLH machine | AB4: Wongo | AE4: B2 machine | AF4: BLH machine | AG4: Wongo | AK4: GA machine | AL4: BLH machine | AM4: Wongo | AP4: GA machine | AQ4: BLH machine | AR4: Wongo
A5: 1 | B5: 11397 | C5: ENZ25L | D5: 0408244442 | E5: M | F5: 800 | G5: X | I5: 100 | J5: =IF(G5="RSL","55","0") -> 0 | K5: =IF(G5="GVS","37.5",IF(G5="GVM","41.5",IF(G5="GVL","50",IF(G5="PCS","45.8",IF(G5="PCM","50",IF(G5="PCL","58.3","0")))))) -> 0 | N5: HENDRA | R5: HENDRA | S5: 0.33333333 | T5: 0.66666667 | U5: =(T5-S5)*24 -> 8 | X5: NOV | Y5: 1 | AD5: 16 | AI5: NOV | AJ5: 1 | AO5: 16
A6: 2 | B6: 11398 | C6: JC5151 | D6: 0403102277 | E6: F | F6: 925 | G6: D | H6: 55 | J6: =IF(G6="RSL","55","0") -> 0 | K6: =IF(G6="GVS","37.5",IF(G6="GVM","41.5",IF(G6="GVL","50",IF(G6="PCS","45.8",IF(G6="PCM","50",IF(G6="PCL","58.3","0")))))) -> 0 | N6: HENDRA | R6: JAIKE | S6: 0.39583333 | T6: 0.66666667 | U6: =(T6-S6)*24 -> 6.5 | W6: M | Y6: 2 | AD6: 17 | AJ6: 2 | AO6: 17
A7: 3 | B7: 11399 | C7: EIZ58C | D7: 0401423486 | E7: F | F7: 1110 | G7: X | H7: 95 | J7: =IF(G7="RSL","55","0") -> 0 | K7: =IF(G7="GVS","37.5",IF(G7="GVM","41.5",IF(G7="GVL","50",IF(G7="PCS","45.8",IF(G7="PCM","50",IF(G7="PCL","58.3","0")))))) -> 0 | N7: VINNY | R7: VINNY | S7: 0.45833333 | T7: 0.66666667 | U7: =(T7-S7)*24 -> 5 | W7: F | Y7: 3 | AD7: 18 | AJ7: 3 | AO7: 18
A8: 4 | B8: 11400 | C8: DC66 | D8: 0431339618 | E8: M | F8: 1245 | G8: D | H8: 75 | J8: =IF(G8="RSL","55","0") -> 0 | K8: =IF(G8="GVS","37.5",IF(G8="GVM","41.5",IF(G8="GVL","50",IF(G8="PCS","45.8",IF(G8="PCM","50",IF(G8="PCL","58.3","0")))))) -> 0 | N8: HENDRA | R8: CALAN OCTEC | S8: 0.375 | T8: 0.66666667 | U8: =(T8-S8)*24 -> 7 | Y8: 4 | AD8: 19 | AJ8: 4 | AO8: 19
A9: 5 | B9: 11401 | C9: EDC28W | D9: 0411082981 | E9: M | F9: 1300 | G9: RSL | J9: 110 | K9: =IF(G9="GVS","37.5",IF(G9="GVM","41.5",IF(G9="GVL","50",IF(G9="PCS","45.8",IF(G9="PCM","50",IF(G9="PCL","58.3","0")))))) -> 0 | N9: HENDRA | O9: 202208116, 202207037(H) | R9: ANDREW OCTEC | S9: 0.54166667 | T9: 0.65625 | U9: =(T9-S9)*24 -> 2.75 | X9: EXCL RSL | Y9: 5 | AD9: 20 | AJ9: 5 | AO9: 20
A10: 6 | B10: 11402 | C10: NCF01C | D10: 0437494667 | E10: F | F10: 1330 | G10: X | I10: 75.75 | J10: =IF(G10="RSL","55","0") -> 0 | K10: =IF(G10="GVS","37.5",IF(G10="GVM","41.5",IF(G10="GVL","50",IF(G10="PCS","45.8",IF(G10="PCM","50",IF(G10="PCL","58.3","0")))))) -> 0 | N10: HENDRA | U10: =(T10-S10)*24 -> 0 | Y10: 6 | AD10: 21 | AJ10: 6 | AO10: 21
A11: 7 | B11: 11403 | C11: CPX73F | D11: 0404007918 | E11: M | F11: 1330 | G11: D | I11: 75.75 | J11: =IF(G11="RSL","55","0") -> 0 | K11: =IF(G11="GVS","37.5",IF(G11="GVM","41.5",IF(G11="GVL","50",IF(G11="PCS","45.8",IF(G11="PCM","50",IF(G11="PCL","58.3","0")))))) -> 0 | N11: HENDRA | U11: =(T11-S11)*24 -> 0 | Y11: 7 | AD11: 22 | AJ11: 7 | AO11: 22
A12: 8 | B12: 11404 | C12: BJF34A | D12: 0412255775 | E12: M | F12: 1345 | G12: X | I12: 95.95 | J12: =IF(G12="RSL","55","0") -> 0 | K12: =IF(G12="GVS","37.5",IF(G12="GVM","41.5",IF(G12="GVL","50",IF(G12="PCS","45.8",IF(G12="PCM","50",IF(G12="PCL","58.3","0")))))) -> 0 | N12: HENDRA | U12: =(T12-S12)*24 -> 0 | Y12: 8 | AD12: 23 | AJ12: 8 | AO12: 23
A13: 9 | B13: 11405 | C13: NCC89N | D13: 0405660278 | E13: F | F13: 1400 | G13: X | I13: 151.5 | J13: =IF(G13="RSL","55","0") -> 0 | K13: =IF(G13="GVS","37.5",IF(G13="GVM","41.5",IF(G13="GVL","50",IF(G13="PCS","45.8",IF(G13="PCM","50",IF(G13="PCL","58.3","0")))))) -> 0 | N13: HENDRA | O13: ST BABY SEAT | U13: =(T13-S13)*24 -> 0 | Y13: 9 | AD13: 24 | AJ13: 9 | AO13: 24
A14: 10 | B14: 11406 | C14: DWX12D | D14: 0438723655 | E14: F | F14: 1400 | G14: PCM | J14: =IF(G14="RSL","55","0") -> 0 | K14: 113.33 | N14: VINNY | O14: 22008(2/6) (H) | U14: =(T14-S14)*24 -> 0 | Y14: 10 | AD14: 25 | AJ14: 10 | AO14: 25
A15: 11 | B15: 11407 | C15: ESI54S | D15: 0414890999 | E15: M | F15: 1500 | G15: RSL | J15: 110 | K15: =IF(G15="GVS","37.5",IF(G15="GVM","41.5",IF(G15="GVL","50",IF(G15="PCS","45.8",IF(G15="PCM","50",IF(G15="PCL","58.3","0")))))) -> 0 | N15: HENDRA | O15: 202207049, 202207050(X) | U15: =(T15-S15)*24 -> 0 | Y15: 11 | AD15: 26 | AJ15: 11 | AO15: 26
A16: 12 | J16: =IF(G16="RSL","55","0") -> 0 | K16: =IF(G16="GVS","37.5",IF(G16="GVM","41.5",IF(G16="GVL","50",IF(G16="PCS","45.8",IF(G16="PCM","50",IF(G16="PCL","58.3","0")))))) -> 0 | R16: =H32/U16 -> 0.30769231 | S16: =H32/(U16-U5) -> 0.42352941 | T16: =C32/U16 -> 36.146325 | U16: =SUM(U5:U15) -> 29.25 | Y16: 12 | AD16: 27 | AJ16: 12 | AO16: 27
A17: 13 | J17: =IF(G17="RSL","55","0") -> 0 | K17: =IF(G17="GVS","37.5",IF(G17="GVM","41.5",IF(G17="GVL","50",IF(G17="PCS","45.8",IF(G17="PCM","50",IF(G17="PCL","58.3","0")))))) -> 0 | R17: Cars/T Hr ① | S17: Cars/T Hr ② | T17: Sales/T Hr | U17: Total Hours | Y17: 13 | AD17: 28 | AJ17: 13 | AO17: 28
A18: 14 | J18: =IF(G18="RSL","55","0") -> 0 | K18: =IF(G18="GVS","37.5",IF(G18="GVM","41.5",IF(G18="GVL","50",IF(G18="PCS","45.8",IF(G18="PCM","50",IF(G18="PCL","58.3","0")))))) -> 0 | R18: ITEM | S18: QTY | T18: AMT | U18: RMKS | Y18: 14 | AD18: 29 | AJ18: 14 | AO18: 29
A19: 15 | J19: =IF(G19="RSL","55","0") -> 0 | K19: =IF(G19="GVS","37.5",IF(G19="GVM","41.5",IF(G19="GVL","50",IF(G19="PCS","45.8",IF(G19="PCM","50",IF(G19="PCL","58.3","0")))))) -> 0 | R19: GV | S19: =COUNT(L5:M29,L37:M61,L69:M93) -> 0 | T19: =SUM(L5:M29,L37:M61,L69:M93) -> 0 | Y19: 15 | AD19: 30 | AJ19: 15 | AO19: 30
A20: 16 | J20: =IF(G20="RSL","55","0") -> 0 | K20: =IF(G20="GVS","37.5",IF(G20="GVM","41.5",IF(G20="GVL","50",IF(G20="PCS","45.8",IF(G20="PCM","50",IF(G20="PCL","58.3","0")))))) -> 0 | AD20: 31 | AO20: 31
A21: 17 | J21: =IF(G21="RSL","55","0") -> 0 | K21: =IF(G21="GVS","37.5",IF(G21="GVM","41.5",IF(G21="GVL","50",IF(G21="PCS","45.8",IF(G21="PCM","50",IF(G21="PCL","58.3","0")))))) -> 0
A22: 18 | J22: =IF(G22="RSL","55","0") -> 0 | K22: =IF(G22="GVS","37.5",IF(G22="GVM","41.5",IF(G22="GVL","50",IF(G22="PCS","45.8",IF(G22="PCM","50",IF(G22="PCL","58.3","0")))))) -> 0 | AD22: Total | AE22: =SUM(Z5:Z19,AE5:AE20) -> 0 | AF22: =SUM(AA5:AA19,AF5:AF20,) -> 0 | AG22: =SUM(AB5:AB19,AG5:AG20) -> 0 | AO22: Total | AP22: =SUM(AK5:AK19,AP5:AP20) -> 0 | AQ22: =SUM(AL5:AL19,AQ5:AQ20,) -> 0 | AR22: =SUM(AM5:AM19,AR5:AR20) -> 0
A23: 19 | J23: =IF(G23="RSL","55","0") -> 0 | K23: =IF(G23="GVS","37.5",IF(G23="GVM","41.5",IF(G23="GVL","50",IF(G23="PCS","45.8",IF(G23="PCM","50",IF(G23="PCL","58.3","0")))))) -> 0
A24: 20 | J24: =IF(G24="RSL","55","0") -> 0 | K24: =IF(G24="GVS","37.5",IF(G24="GVM","41.5",IF(G24="GVL","50",IF(G24="PCS","45.8",IF(G24="PCM","50",IF(G24="PCL","58.3","0")))))) -> 0 | R24: SMALL | S24: MEDIUM | T24: LARGE | U24: TOTAL | AD24: B2/GA TOTAL | AE24: B2 machine | AF24: GA machine | AG24: BLH machine | AH24: Wongo machine | AI24: Sub total
A25: 21 | J25: =IF(G25="RSL","55","0") -> 0 | K25: =IF(G25="GVS","37.5",IF(G25="GVM","41.5",IF(G25="GVL","50",IF(G25="PCS","45.8",IF(G25="PCM","50",IF(G25="PCL","58.3","0")))))) -> 0 | R25: =COUNTIF(G5:G29,"GV1")+COUNTIF(G37:G61,"GV1")+COUNTIF(G69:G93,"GV1") -> 0 | S25: =COUNTIF(G5:G29,"GV2")+COUNTIF(G37:G61,"GV2")+COUNTIF(G69:G93,"GV2") -> 0 | T25: =COUNTIF(G5:G29,"GV3")+COUNTIF(G37:G61,"GV3")+COUNTIF(G69:G93,"GV3") -> 0 | U25: =((C32+(R26+S26+T26)*0.5)) -> 1057.28 | AD25: =SUM(AE25:AF25) -> 0 | AE25: =SUM(AE22) -> 0 | AF25: =SUM(AP22) -> 0 | AG25: =SUM(AF22+AQ22) -> 0 | AH25: =AG22+AR22 -> 0 | AI25: =SUM(AE25:AH25) -> 0
A26: 22 | J26: =IF(G26="RSL","55","0") -> 0 | K26: =IF(G26="GVS","37.5",IF(G26="GVM","41.5",IF(G26="GVL","50",IF(G26="PCS","45.8",IF(G26="PCM","50",IF(G26="PCL","58.3","0")))))) -> 0 | R26: =R25*37.5 -> 0 | S26: =S25*41.5 -> 0 | T26: =T25*50 -> 0 | X26: Branch cards
A27: 23 | J27: =IF(G27="RSL","55","0") -> 0 | K27: =IF(G27="GVS","37.5",IF(G27="GVM","41.5",IF(G27="GVL","50",IF(G27="PCS","45.8",IF(G27="PCM","50",IF(G27="PCL","58.3","0")))))) -> 0 | R27: Expense | X27: 1 | Z27: -2745
A28: 24 | J28: =IF(G28="RSL","55","0") -> 0 | K28: =IF(G28="GVS","37.5",IF(G28="GVM","41.5",IF(G28="GVL","50",IF(G28="PCS","45.8",IF(G28="PCM","50",IF(G28="PCL","58.3","0")))))) -> 0 | X28: 2
A29: 25 | J29: =IF(G29="RSL","55","0") -> 0 | K29: =IF(G29="GVS","37.5",IF(G29="GVM","41.5",IF(G29="GVL","50",IF(G29="PCS","45.8",IF(G29="PCM","50",IF(G29="PCL","58.3","0")))))) -> 0 | X29: 3
A30: Page total | H30: =SUM(H5:H29) -> 225 | I30: =SUM(I5:I29) -> 498.95 | J30: =J5+J6+J7+J8+J9+J10+J11+J12+J13+J14+J15+J16+J18+J19+J17+J20+J22+J23+J21+J24+J25+J26+J27+J28+J29 -> 220 | K30: =K5+K6+K7+K8+K9+K10+K11+K12+K13+K14+K15+K16+K18+K19+K17+K20+K22+K23+K21+K24+K25+K26+K27+K28+K29 -> 113.33 | L30: =SUM(L5:L29) -> 0 | M30: =SUM(M5:M29) -> 0 | N30: CASH | O30: CARD | P30: GV | Q30: RSL | X30: 4
A31: Daily Total | H31: =H30+H62+H94 -> 225 | I31: =I30+I62+I94 -> 498.95 | J31: =J30+J62+J94 -> 220 | K31: =K30+K62+K94 -> 113.33 | L31: =L30+L62+L94 -> 0 | M31: =M30+M62+M94 -> 0 | N31: =COUNT(H5:H29,H37:H61,H69:H93) -> 3 | O31: =COUNT(I5:I29,I37:I61,I69:I93) -> 5 | P31: =COUNTIF(G5:G29,"G*")+COUNTIF(G37:G61,"G*")+COUNTIF(G69:G93,"G*")+COUNTIF(G5:G29,"P*")+COUNTIF(G37:G61,"P*")+COUNTIF(G69:G93,"P*") -> 1 | Q31: =COUNTIF(G5:G29,"RSL")+COUNTIF(G37:G61,"RSL")+COUNTIF(G69:G93,"RSL") -> 2 | R31: CASH CLOSING | S31: =H31+L31-U28-U29-U30 -> 225 | T31: =H31+I31+L31+M31 -> 723.95 | X31: Subtotal | Z31: =SUM(Z27:Z30) -> -2745
A32: TOTAL SALES | C32: =H31+I31+J31+K31 -> 1057.28 | F32: No of Cars | H32: =COUNT(B7:B29,B37:B61,B69:B93) -> 9 | I32: Average | K32: =C32/H32 -> 117.47556 | N32: =H31/C32 -> 0.21281023 | O32: =I31/C32 -> 0.47191851 | P32: =K31/C32 -> 0.10719015 | Q32: =J31/C32 -> 0.20808111 | R32: CARD CLOSING | S32: =I31+M31 -> 498.95 | X32: B2 card | Z32: =I31 -> 498.95
A33: Daily Report | X33: Settlement | Z33: =SUM(Z31:Z32) -> -2246.05
A34: =A2 -> 30 - 9 - 2022 | H34: WEATHER | J34: =J2 -> SHOWER | L34: REPORT by | O34: =O2 -> HENDRA | R34: TOTAL STAFF | T34: =T2 -> 4
A36: No | B36: Docket No | C36: Reg No | D36: Mobile | E36: Gender | F36: TIME | G36: Service | H36: CASH | I36: CARD | J36: RSL | K36: GV | L36: GV CASH | M36: GV CARD | N36: O/Taker | O36: Comment | R36: NAME | S36: Time In | T36: Time out | U36: Total Hours
A37: =A29+1 -> 26 | J37: =IF(G37="RSL","55","0") -> 0 | K37: =IF(G37="GVS","37.5",IF(G37="GVM","41.5",IF(G37="GVL","50",IF(G37="PCS","45.8",IF(G37="PCM","50",IF(G37="PCL","58.3","0")))))) -> 0
A38: =A37+1 -> 27 | J38: =IF(G38="RSL","55","0") -> 0 | K38: =IF(G38="GVS","37.5",IF(G38="GVM","41.5",IF(G38="GVL","50",IF(G38="PCS","45.8",IF(G38="PCM","50",IF(G38="PCL","58.3","0")))))) -> 0
A39: =A38+1 -> 28 | J39: =IF(G39="RSL","55","0") -> 0 | K39: =IF(G39="GVS","37.5",IF(G39="GVM","41.5",IF(G39="GVL","50",IF(G39="PCS","45.8",IF(G39="PCM","50",IF(G39="PCL","58.3","0")))))) -> 0
A40: =A39+1 -> 29 | J40: =IF(G40="RSL","55","0") -> 0 | K40: =IF(G40="GVS","37.5",IF(G40="GVM","41.5",IF(G40="GVL","50",IF(G40="PCS","45.8",IF(G40="PCM","50",IF(G40="PCL","58.3","0")))))) -> 0
A41: =A40+1 -> 30 | J41: =IF(G41="RSL","55","0") -> 0 | K41: =IF(G41="GVS","37.5",IF(G41="GVM","41.5",IF(G41="GVL","50",IF(G41="PCS","45.8",IF(G41="PCM","50",IF(G41="PCL","58.3","0")))))) -> 0
A42: =A41+1 -> 31 | J42: =IF(G42="RSL","55","0") -> 0 | K42: =IF(G42="GVS","37.5",IF(G42="GVM","41.5",IF(G42="GVL","50",IF(G42="PCS","45.8",IF(G42="PCM","50",IF(G42="PCL","58.3","0")))))) -> 0
A43: =A42+1 -> 32 | J43: =IF(G43="RSL","55","0") -> 0 | K43: =IF(G43="GVS","37.5",IF(G43="GVM","41.5",IF(G43="GVL","50",IF(G43="PCS","45.8",IF(G43="PCM","50",IF(G43="PCL","58.3","0")))))) -> 0
A44: =A43+1 -> 33 | J44: =IF(G44="RSL","55","0") -> 0 | K44: =IF(G44="GVS","37.5",IF(G44="GVM","41.5",IF(G44="GVL","50",IF(G44="PCS","45.8",IF(G44="PCM","50",IF(G44="PCL","58.3","0")))))) -> 0
A45: =A44+1 -> 34 | J45: =IF(G45="RSL","55","0") -> 0 | K45: =IF(G45="GVS","37.5",IF(G45="GVM","41.5",IF(G45="GVL","50",IF(G45="PCS","45.8",IF(G45="PCM","50",IF(G45="PCL","58.3","0")))))) -> 0
A46: =A45+1 -> 35 | J46: =IF(G46="RSL","55","0") -> 0 | K46: =IF(G46="GVS","37.5",IF(G46="GVM","41.5",IF(G46="GVL","50",IF(G46="PCS","45.8",IF(G46="PCM","50",IF(G46="PCL","58.3","0")))))) -> 0
A47: =A46+1 -> 36 | J47: =IF(G47="RSL","55","0") -> 0 | K47: =IF(G47="GVS","37.5",IF(G47="GVM","41.5",IF(G47="GVL","50",IF(G47="PCS","45.8",IF(G47="PCM","50",IF(G47="PCL","58.3","0")))))) -> 0
A48: =A47+1 -> 37 | J48: =IF(G48="RSL","55","0") -> 0 | K48: =IF(G48="GVS","37.5",IF(G48="GVM","41.5",IF(G48="GVL","50",IF(G48="PCS","45.8",IF(G48="PCM","50",IF(G48="PCL","58.3","0")))))) -> 0
A49: =A48+1 -> 38 | J49: =IF(G49="RSL","55","0") -> 0 | K49: =IF(G49="GVS","37.5",IF(G49="GVM","41.5",IF(G49="GVL","50",IF(G49="PCS","45.8",IF(G49="PCM","50",IF(G49="PCL","58.3","0")))))) -> 0
... A61: =A60+1 -> 50 | J61: =IF(G61="RSL","55","0") -> 0 | K61: =IF(G61="GVS","37.5",IF(G61="GVM","41.5",IF(G61="GVL","50",IF(G61="PCS","45.8",IF(G61="PCM","50",IF(G61="PCL","58.3","0")))))) -> 0
A62: Page total | H62: =SUM(H37:H61) -> 0 | I62: =SUM(I37:I61) -> 0 | J62: =J61+J60+J59+J58+J57+J56+J55+J54+J53+J52+J51+J50+J49+J48+J47+J46+J45+J44+J43+J42+J41+J40+J39+J38+J37 -> 0 | K62: =K61+K60+K59+K58+K57+K56+K55+K54+K53+K52+K51+K50+K49+K48+K47+K46+K45+K44+K43+K42+K41+K40+K39+K38+K37 -> 0 | L62: =SUM(L37:L61) -> 0 | M62: =SUM(M37:M61) -> 0
R64: Page: 2
A65: Daily Report
A66: =A34 -> 30 - 9 - 2022 | H66: WEATHER | J66: =J34 -> SHOWER | L66: REPORT by | O66: =O34 -> HENDRA | R66: TOTAL STAFF | T66: =T34 -> 4
A68: No | B68: Docket No | C68: Reg No | D68: Mobile | E68: Gender | F68: TIME | G68: Service | H68: CASH | I68: CARD | J68: RSL | K68: GV | L68: GV CASH | M68: GV CARD | N68: O/Taker | O68: Comment | R68: NAME | S68: Time In | T68: Time out | U68: Total Hours
A69: =A61+1 -> 51 | J69: =IF(G69="RSL","55","0") -> 0 | K69: =IF(G69="GVS","37.5",IF(G69="GVM","41.5",IF(G69="GVL","50",IF(G69="PCS","45.8",IF(G69="PCM","50",IF(G69="PCL","58.3","0")))))) -> 0
A70: =A69+1 -> 52 | J70: =IF(G70="RSL","55","0") -> 0 | K70: =IF(G70="GVS","37.5",IF(G70="GVM","41.5",IF(G70="GVL","50",IF(G70="PCS","45.8",IF(G70="PCM","50",IF(G70="PCL","58.3","0")))))) -> 0
A71: =A70+1 -> 53 | J71: =IF(G71="RSL","55","0") -> 0 | K71: =IF(G71="GVS","37.5",IF(G71="GVM","41.5",IF(G71="GVL","50",IF(G71="PCS","45.8",IF(G71="PCM","50",IF(G71="PCL","58.3","0")))))) -> 0
A72: =A71+1 -> 54 | J72: =IF(G72="RSL","55","0") -> 0 | K72: =IF(G72="GVS","37.5",IF(G72="GVM","41.5",IF(G72="GVL","50",IF(G72="PCS","45.8",IF(G72="PCM","50",IF(G72="PCL","58.3","0")))))) -> 0
A73: =A72+1 -> 55 | J73: =IF(G73="RSL","55","0") -> 0 | K73: =IF(G73="GVS","37.5",IF(G73="GVM","41.5",IF(G73="GVL","50",IF(G73="PCS","45.8",IF(G73="PCM","50",IF(G73="PCL","58.3","0")))))) -> 0
A74: =A73+1 -> 56 | J74: =IF(G74="RSL","55","0") -> 0 | K74: =IF(G74="GVS","37.5",IF(G74="GVM","41.5",IF(G74="GVL","50",IF(G74="PCS","45.8",IF(G74="PCM","50",IF(G74="PCL","58.3","0")))))) -> 0
A75: =A74+1 -> 57 | J75: =IF(G75="RSL","55","0") -> 0 | K75: =IF(G75="GVS","37.5",IF(G75="GVM","41.5",IF(G75="GVL","50",IF(G75="PCS","45.8",IF(G75="PCM","50",IF(G75="PCL","58.3","0")))))) -> 0
A76: =A75+1 -> 58 | J76: =IF(G76="RSL","55","0") -> 0 | K76: =IF(G76="GVS","37.5",IF(G76="GVM","41.5",IF(G76="GVL","50",IF(G76="PCS","45.8",IF(G76="PCM","50",IF(G76="PCL","58.3","0")))))) -> 0
A77: =A76+1 -> 59 | J77: =IF(G77="RSL","55","0") -> 0 | K77: =IF(G77="GVS","37.5",IF(G77="GVM","41.5",IF(G77="GVL","50",IF(G77="PCS","45.8",IF(G77="PCM","50",IF(G77="PCL","58.3","0")))))) -> 0
A78: =A77+1 -> 60 | J78: =IF(G78="RSL","55","0") -> 0 | K78: =IF(G78="GVS","37.5",IF(G78="GVM","41.5",IF(G78="GVL","50",IF(G78="PCS","45.8",IF(G78="PCM","50",IF(G78="PCL","58.3","0")))))) -> 0
A79: =A78+1 -> 61 | J79: =IF(G79="RSL","55","0") -> 0 | K79: =IF(G79="GVS","37.5",IF(G79="GVM","41.5",IF(G79="GVL","50",IF(G79="PCS","45.8",IF(G79="PCM","50",IF(G79="PCL","58.3","0")))))) -> 0
A80: =A79+1 -> 62 | J80: =IF(G80="RSL","55","0") -> 0 | K80: =IF(G80="GVS","37.5",IF(G80="GVM","41.5",IF(G80="GVL","50",IF(G80="PCS","45.8",IF(G80="PCM","50",IF(G80="PCL","58.3","0")))))) -> 0
A81: =A80+1 -> 63 | J81: =IF(G81="RSL","55","0") -> 0 | K81: =IF(G81="GVS","37.5",IF(G81="GVM","41.5",IF(G81="GVL","50",IF(G81="PCS","45.8",IF(G81="PCM","50",IF(G81="PCL","58.3","0")))))) -> 0
... A93: =A92+1 -> 75 | J93: =IF(G93="RSL","55","0") -> 0 | K93: =IF(G93="GVS","37.5",IF(G93="GVM","41.5",IF(G93="GVL","50",IF(G93="PCS","45.8",IF(G93="PCM","50",IF(G93="PCL","58.3","0")))))) -> 0
A94: Page total | H94: =SUM(H69:H93) -> 0 | I94: =SUM(I69:I93) -> 0 | J94: =J93+J92+J91+J90+J89+J88+J87+J86+J85+J84+J83+J82+J81+J80+J79+J78+J77+J76+J75+J74+J73+J72+J71+J70+J69 -> 0 | K94: =K93+K92+K91+K90+K89+K88+K87+K86+K85+K84+K83+K82+K81+K80+K79+K78+K77+K76+K75+K74+K73+K72+K71+K70+K69 -> 0 | L94: =SUM(L69:L93) -> 0 | M94: =SUM(M69:M93) -> 0
R96: Page: 3

Sheet SAT
A1: B2 Daily Report
A2: 1 - 10 - 2022 | H2: WEATHER | J2: SUNNY | L2: REPORT BY | O2: JOHN | R2: TOTAL STAFF | T2: 5 | X2: Merchant machine usage at B2 | AA2: Settle amount | AI2: Merchant machine usage at GA | AL2: Settle amount
A4: No | B4: Docket No | C4: Reg No | D4: Mobile | E4: Gender | F4: TIME | G4: Service | H4: CASH | I4: CARD | J4: RSL | K4: GV | L4: GV CASH | M4: GV CARD | N4: O/Taker | O4: Comment | R4: NAME | S4: Time In | T4: Time out | U4: Total Hours | Z4: B2 machine | AA4: BLH machine | AB4: Wongo | AE4: B2 machine | AF4: BLH machine | AG4: Wongo | AK4: GA machine | AL4: BLH machine | AM4: Wongo | AP4: GA machine | AQ4: BLH machine | AR4: Wongo
A5: 1 | B5: 11408 | C5: ETD70P | D5: 0438432621 | E5: M | F5: 815 | G5: X | I5: 95.95 | J5: =IF(G5="RSL","55","0") -> 0 | K5: =IF(G5="GVS","37.5",IF(G5="GVM","41.5",IF(G5="GVL","50",IF(G5="PCS","45.8",IF(G5="PCM","50",IF(G5="PCL","58.3","0")))))) -> 0 | N5: HENDRA | R5: JOHN | S5: 0.35416667 | T5: 0.71875 | U5: =(T5-S5)*24 -> 8.75 | X5: NOV | Y5: 1 | AD5: 16 | AI5: NOV | AJ5: 1 | AO5: 16
A6: 2 | B6: 11409 | C6: KDO100 | D6: 0478127117 | E6: M | F6: 820 | G6: X | H6: 100 | J6: =IF(G6="RSL","55","0") -> 0 | K6: =IF(G6="GVS","37.5",IF(G6="GVM","41.5",IF(G6="GVL","50",IF(G6="PCS","45.8",IF(G6="PCM","50",IF(G6="PCL","58.3","0")))))) -> 0 | N6: HENDRA | R6: HENDRA | S6: 0.33333333 | T6: 0.71875 | U6: =(T6-S6)*24 -> 9.25 | W6: M | Y6: 2 | AD6: 17 | AJ6: 2 | AO6: 17
A7: 3 | B7: 11410 | C7: AQA74J | D7: 0407424895 | E7: F | F7: 900 | G7: W/O | H7: 50 | J7: =IF(G7="RSL","55","0") -> 0 | K7: =IF(G7="GVS","37.5",IF(G7="GVM","41.5",IF(G7="GVL","50",IF(G7="PCS","45.8",IF(G7="PCM","50",IF(G7="PCL","58.3","0")))))) -> 0 | N7: JOHN | R7: ARIANTO | S7: 0.375 | T7: 0.54166667 | U7: =(T7-S7)*24 -> 4 | W7: F | Y7: 3 | AD7: 18 | AJ7: 3 | AO7: 18
A8: 4 | B8: 11411 | C8: EKT07G | D8: 0419615338 | E8: F | F8: 925 | G8: X | H8: 75 | J8: =IF(G8="RSL","55","0") -> 0 | K8: =IF(G8="GVS","37.5",IF(G8="GVM","41.5",IF(G8="GVL","50",IF(G8="PCS","45.8",IF(G8="PCM","50",IF(G8="PCL","58.3","0")))))) -> 0 | N8: JOHN | S8: 0.625 | T8: 0.71875 | U8: =(T8-S8)*24 -> 2.25 | Y8: 4 | AD8: 19 | AJ8: 4 | AO8: 19
A9: 5 | B9: 11412 | C9: YDF82L | D9: 0420909905 | E9: F | F9: 1000 | G9: X | I9: 75 | J9: =IF(G9="RSL","55","0") -> 0 | K9: =IF(G9="GVS","37.5",IF(G9="GVM","41.5",IF(G9="GVL","50",IF(G9="PCS","45.8",IF(G9="PCM","50",IF(G9="PCL","58.3","0")))))) -> 0 | N9: JOHN | R9: KUROSH | S9: 0.41666667 | T9: 0.53125 | U9: =(T9-S9)*24 -> 2.75 | X9: EXCL RSL | Y9: 5 | AD9: 20 | AJ9: 5 | AO9: 20
A10: 6 | B10: 11413 | C10: CTU62T | D10: 0400351671 | E10: F | F10: 1010 | G10: H | I10: 150 | J10: =IF(G10="RSL","55","0") -> 0 | K10: =IF(G10="GVS","37.5",IF(G10="GVM","41.5",IF(G10="GVL","50",IF(G10="PCS","45.8",IF(G10="PCM","50",IF(G10="PCL","58.3","0")))))) -> 0 | N10: JOHN | S10: 0.57291667 | T10: 0.71875 | U10: =(T10-S10)*24 -> 3.5 | Y10: 6 | AD10: 21 | AJ10: 6 | AO10: 21
A11: 7 | B11: 11414 | C11: CAJ28X | D11: 0413721179 | E11: F | F11: 1015 | G11: ID | I11: 195 | J11: =IF(G11="RSL","55","0") -> 0 | K11: =IF(G11="GVS","37.5",IF(G11="GVM","41.5",IF(G11="GVL","50",IF(G11="PCS","45.8",IF(G11="PCM","50",IF(G11="PCL","58.3","0")))))) -> 0 | N11: JOHN | R11: KADAM | S11: 0.45833333 | T11: 0.71875 | U11: =(T11-S11)*24 -> 6.25 | Y11: 7 | AD11: 22 | AJ11: 7 | AO11: 22
A12: 8 | B12: 11415 | C12: DCH66L | D12: 0449583573 | E12: M | F12: 1030 | G12: F/D | H12: 480 | J12: =IF(G12="RSL","55","0") -> 0 | K12: =IF(G12="GVS","37.5",IF(G12="GVM","41.5",IF(G12="GVL","50",IF(G12="PCS","45.8",IF(G12="PCM","50",IF(G12="PCL","58.3","0")))))) -> 0 | N12: JOHN | U12: =(T12-S12)*24 -> 0 | Y12: 8 | AD12: 23 | AJ12: 8 | AO12: 23
A13: 9 | B13: 11416 | C13: YIR28P | D13: 0431742688 | E13: M | F13: 1045 | G13: PCL | J13: =IF(G13="RSL","55","0") -> 0 | K13: 79.1 | M13: 479.75 | N13: JOHN | O13: 21122818(6/6),22085(NEW) | U13: =(T13-S13)*24 -> 0 | Y13: 9 | AD13: 24 | AJ13: 9 | AO13: 24
A14: 10 | B14: 11417 | C14: ESZ09V | D14: 0432273096 | E14: F | F14: 1100 | G14: X | H14: 75 | J14: =IF(G14="RSL","55","0") -> 0 | K14: =IF(G14="GVS","37.5",IF(G14="GVM","41.5",IF(G14="GVL","50",IF(G14="PCS","45.8",IF(G14="PCM","50",IF(G14="PCL","58.3","0")))))) -> 0 | N14: JOHN | U14: =(T14-S14)*24 -> 0 | Y14: 10 | AD14: 25 | AJ14: 10 | AO14: 25
A15: 11 | B15: 11418 | C15: ERB22T | D15: 0419809433 | E15: M | F15: 1220 | G15: H | H15: 120 | J15: =IF(G15="RSL","55","0") -> 0 | K15: =IF(G15="GVS","37.5",IF(G15="GVM","41.5",IF(G15="GVL","50",IF(G15="PCS","45.8",IF(G15="PCM","50",IF(G15="PCL","58.3","0")))))) -> 0 | N15: JOHN | U15: =(T15-S15)*24 -> 0 | Y15: 11 | AD15: 26 | AJ15: 11 | AO15: 26
A16: 12 | B16: 11419 | C16: DGIO00G | D16: 0404010880 | E16: F | F16: 1320 | G16: D | H16: 75 | J16: =IF(G16="RSL","55","0") -> 0 | K16: =IF(G16="GVS","37.5",IF(G16="GVM","41.5",IF(G16="GVL","50",IF(G16="PCS","45.8",IF(G16="PCM","50",IF(G16="PCL","58.3","0")))))) -> 0 | N16: JOHN | R16: =H32/U16 -> 0.46258503 | S16: =H32/(U16-U5) -> 0.60714286 | T16: =C32/U16 -> 70.639456 | U16: =SUM(U5:U15) -> 36.75 | Y16: 12 | AD16: 27 | AJ16: 12 | AO16: 27
A17: 13 | B17: 11420 | C17: EQC08K | D17: 0408017899 | E17: M | F17: 1330 | G17: X | I17: 95 | J17: =IF(G17="RSL","55","0") -> 0 | K17: =IF(G17="GVS","37.5",IF(G17="GVM","41.5",IF(G17="GVL","50",IF(G17="PCS","45.8",IF(G17="PCM","50",IF(G17="PCL","58.3","0")))))) -> 0 | N17: JOHN | R17: Cars/T Hr ① | S17: Cars/T Hr ② | T17: Sales/T Hr | U17: Total Hours | Y17: 13 | AD17: 28 | AJ17: 13 | AO17: 28
A18: 14 | B18: 11421 | C18: ESD87G | D18: 0428887158 | E18: F | F18: 1335 | G18: RSL | H18: 20 | J18: =IF(G18="RSL","55","0") -> 55 | K18: =IF(G18="GVS","37.5",IF(G18="GVM","41.5",IF(G18="GVL","50",IF(G18="PCS","45.8",IF(G18="PCM","50",IF(G18="PCL","58.3","0")))))) -> 0 | N18: JOHN | O18: 202208026 | R18: ITEM | S18: QTY | T18: AMT | U18: RMKS | Y18: 14 | AD18: 29 | AJ18: 14 | AO18: 29
A19: 15 | B19: 11422 | C19: EF076 | D19: 0418913425 | E19: M | F19: 1440 | G19: X | I19: 95.95 | J19: =IF(G19="RSL","55","0") -> 0 | K19: =IF(G19="GVS","37.5",IF(G19="GVM","41.5",IF(G19="GVL","50",IF(G19="PCS","45.8",IF(G19="PCM","50",IF(G19="PCL","58.3","0")))))) -> 0 | N19: JOHN | R19: GV | S19: =COUNT(L5:M29,L37:M61,L69:M93) -> 2 | T19: =SUM(L5:M29,L37:M61,L69:M93) -> 854.75 | Y19: 15 | AD19: 30 | AJ19: 15 | AO19: 30
A20: 16 | B20: 11423 | C20: NBW72B | D20: 0438002693 | E20: F | F20: 1455 | G20: H | H20: 150 | J20: =IF(G20="RSL","55","0") -> 0 | K20: =IF(G20="GVS","37.5",IF(G20="GVM","41.5",IF(G20="GVL","50",IF(G20="PCS","45.8",IF(G20="PCM","50",IF(G20="PCL","58.3","0")))))) -> 0 | N20: JOHN | AD20: 31 | AO20: 31
A21: 17 | B21: 11424 | C21: MG2077 | D21: 0416000655 | E21: F | F21: 1500 | G21: X | H21: 95 | J21: =IF(G21="RSL","55","0") -> 0 | K21: =IF(G21="GVS","37.5",IF(G21="GVM","41.5",IF(G21="GVL","50",IF(G21="PCS","45.8",IF(G21="PCM","50",IF(G21="PCL","58.3","0")))))) -> 0 | N21: JOHN
A22: 18 | B22: 11425 | C22: DYZ80J | D22: 0481215048 | E22: M | F22: 1520 | G22: BP/ID | I22: 420 | J22: =IF(G22="RSL","55","0") -> 0 | K22: =IF(G22="GVS","37.5",IF(G22="GVM","41.5",IF(G22="GVL","50",IF(G22="PCS","45.8",IF(G22="PCM","50",IF(G22="PCL","58.3","0")))))) -> 0 | M22: 375 | N22: JOHN | O22: 22056(NEW) | AD22: Total | AE22: =SUM(Z5:Z19,AE5:AE20) -> 0 | AF22: =SUM(AA5:AA19,AF5:AF20,) -> 0 | AG22: =SUM(AB5:AB19,AG5:AG20) -> 0 | AO22: Total | AP22: =SUM(AK5:AK19,AP5:AP20) -> 0 | AQ22: =SUM(AL5:AL19,AQ5:AQ20,) -> 0 | AR22: =SUM(AM5:AM19,AR5:AR20) -> 0
A23: 19 | B23: 11426 | C23: NCB62D | D23: 0452451336 | E23: M | F23: 1555 | G23: X | H23: 95 | J23: =IF(G23="RSL","55","0") -> 0 | K23: =IF(G23="GVS","37.5",IF(G23="GVM","41.5",IF(G23="GVL","50",IF(G23="PCS","45.8",IF(G23="PCM","50",IF(G23="PCL","58.3","0")))))) -> 0 | N23: JOHN
A24: 20 | J24: =IF(G24="RSL","55","0") -> 0 | K24: =IF(G24="GVS","37.5",IF(G24="GVM","41.5",IF(G24="GVL","50",IF(G24="PCS","45.8",IF(G24="PCM","50",IF(G24="PCL","58.3","0")))))) -> 0 | R24: SMALL | S24: MEDIUM | T24: LARGE | U24: TOTAL | AD24: B2/GA TOTAL | AE24: B2 machine | AF24: GA machine | AG24: BLH machine | AH24: Wongo machine | AI24: Sub total
A25: 21 | J25: =IF(G25="RSL","55","0") -> 0 | K25: =IF(G25="GVS","37.5",IF(G25="GVM","41.5",IF(G25="GVL","50",IF(G25="PCS","45.8",IF(G25="PCM","50",IF(G25="PCL","58.3","0")))))) -> 0 | R25: =COUNTIF(G5:G29,"GV1")+COUNTIF(G37:G61,"GV1")+COUNTIF(G69:G93,"GV1") -> 0 | S25: =COUNTIF(G5:G29,"GV2")+COUNTIF(G37:G61,"GV2")+COUNTIF(G69:G93,"GV2") -> 0 | T25: =COUNTIF(G5:G29,"GV3")+COUNTIF(G37:G61,"GV3")+COUNTIF(G69:G93,"GV3") -> 0 | U25: =((C32+(R26+S26+T26)*0.5)) -> 2596 | AD25: =SUM(AE25:AF25) -> 0 | AE25: =SUM(AE22) -> 0 | AF25: =SUM(AP22) -> 0 | AG25: =SUM(AF22+AQ22) -> 0 | AH25: =AG22+AR22 -> 0 | AI25: =SUM(AE25:AH25) -> 0
A26: 22 | J26: =IF(G26="RSL","55","0") -> 0 | K26: =IF(G26="GVS","37.5",IF(G26="GVM","41.5",IF(G26="GVL","50",IF(G26="PCS","45.8",IF(G26="PCM","50",IF(G26="PCL","58.3","0")))))) -> 0 | R26: =R25*37.5 -> 0 | S26: =S25*41.5 -> 0 | T26: =T25*50 -> 0 | X26: Branch cards
A27: 23 | J27: =IF(G27="RSL","55","0") -> 0 | K27: =IF(G27="GVS","37.5",IF(G27="GVM","41.5",IF(G27="GVL","50",IF(G27="PCS","45.8",IF(G27="PCM","50",IF(G27="PCL","58.3","0")))))) -> 0 | R27: Expense | X27: 1 | Z27: -2745
A28: 24 | J28: =IF(G28="RSL","55","0") -> 0 | K28: =IF(G28="GVS","37.5",IF(G28="GVM","41.5",IF(G28="GVL","50",IF(G28="PCS","45.8",IF(G28="PCM","50",IF(G28="PCL","58.3","0")))))) -> 0 | X28: 2
A29: 25 | J29: =IF(G29="RSL","55","0") -> 0 | K29: =IF(G29="GVS","37.5",IF(G29="GVM","41.5",IF(G29="GVL","50",IF(G29="PCS","45.8",IF(G29="PCM","50",IF(G29="PCL","58.3","0")))))) -> 0 | X29: 3
A30: Page total | H30: =SUM(H5:H29) -> 1335 | I30: =SUM(I5:I29) -> 1126.9 | J30: =J5+J6+J7+J8+J9+J10+J11+J12+J13+J14+J15+J16+J18+J19+J17+J20+J22+J23+J21+J24+J25+J26+J27+J28+J29 -> 55 | K30: =K5+K6+K7+K8+K9+K10+K11+K12+K13+K14+K15+K16+K18+K19+K17+K20+K22+K23+K21+K24+K25+K26+K27+K28+K29 -> 79.1 | L30: =SUM(L5:L29) -> 0 | M30: =SUM(M5:M29) -> 854.75 | N30: CASH | O30: CARD | P30: GV | Q30: RSL | X30: 4
A31: Daily Total | H31: =H30+H62+H94 -> 1335 | I31: =I30+I62+I94 -> 1126.9 | J31: =J30+J62+J94 -> 55 | K31: =K30+K62+K94 -> 79.1 | L31: =L30+L62+L94 -> 0 | M31: =M30+M62+M94 -> 854.75 | N31: =COUNT(H5:H29,H37:H61,H69:H93) -> 11 | O31: =COUNT(I5:I29,I37:I61,I69:I93) -> 7 | P31: =COUNTIF(G5:G29,"G*")+COUNTIF(G37:G61,"G*")+COUNTIF(G69:G93,"G*")+COUNTIF(G5:G29,"P*")+COUNTIF(G37:G61,"P*")+COUNTIF(G69:G93,"P*") -> 1 | Q31: =COUNTIF(G5:G29,"RSL")+COUNTIF(G37:G61,"RSL")+COUNTIF(G69:G93,"RSL") -> 1 | R31: CASH CLOSING | S31: =H31+L31-U28-U29-U30 -> 1335 | T31: =H31+I31+L31+M31 -> 3316.65 | X31: Subtotal | Z31: =SUM(Z27:Z30) -> -2745
A32: TOTAL SALES | C32: =H31+I31+J31+K31 -> 2596 | F32: No of Cars | H32: =COUNT(B7:B29,B37:B61,B69:B93) -> 17 | I32: Average | K32: =C32/H32 -> 152.70588 | N32: =H31/C32 -> 0.5142527 | O32: =I31/C32 -> 0.43409091 | P32: =K31/C32 -> 0.030469954 | Q32: =J31/C32 -> 0.021186441 | R32: CARD CLOSING | S32: =I31+M31 -> 1981.65 | X32: B2 card | Z32: =I31 -> 1126.9
A33: Daily Report | X33: Settlement | Z33: =SUM(Z31:Z32) -> -1618.1
A34: =A2 -> 1 - 10 - 2022 | H34: WEATHER | J34: =J2 -> SUNNY | L34: REPORT by | O34: =O2 -> JOHN | R34: TOTAL STAFF | T34: =T2 -> 5
A36: No | B36: Docket No | C36: Reg No | D36: Mobile | E36: Gender | F36: TIME | G36: Service | H36: CASH | I36: CARD | J36: RSL | K36: GV | L36: GV CASH | M36: GV CARD | N36: O/Taker | O36: Comment | R36: NAME | S36: Time In | T36: Time out | U36: Total Hours
A37: =A29+1 -> 26 | J37: =IF(G37="RSL","55","0") -> 0 | K37: =IF(G37="GVS","37.5",IF(G37="GVM","41.5",IF(G37="GVL","50",IF(G37="PCS","45.8",IF(G37="PCM","50",IF(G37="PCL","58.3","0")))))) -> 0
A38: =A37+1 -> 27 | J38: =IF(G38="RSL","55","0") -> 0 | K38: =IF(G38="GVS","37.5",IF(G38="GVM","41.5",IF(G38="GVL","50",IF(G38="PCS","45.8",IF(G38="PCM","50",IF(G38="PCL","58.3","0")))))) -> 0
A39: =A38+1 -> 28 | J39: =IF(G39="RSL","55","0") -> 0 | K39: =IF(G39="GVS","37.5",IF(G39="GVM","41.5",IF(G39="GVL","50",IF(G39="PCS","45.8",IF(G39="PCM","50",IF(G39="PCL","58.3","0")))))) -> 0
A40: =A39+1 -> 29 | J40: =IF(G40="RSL","55","0") -> 0 | K40: =IF(G40="GVS","37.5",IF(G40="GVM","41.5",IF(G40="GVL","50",IF(G40="PCS","45.8",IF(G40="PCM","50",IF(G40="PCL","58.3","0")))))) -> 0
A41: =A40+1 -> 30 | J41: =IF(G41="RSL","55","0") -> 0 | K41: =IF(G41="GVS","37.5",IF(G41="GVM","41.5",IF(G41="GVL","50",IF(G41="PCS","45.8",IF(G41="PCM","50",IF(G41="PCL","58.3","0")))))) -> 0
A42: =A41+1 -> 31 | J42: =IF(G42="RSL","55","0") -> 0 | K42: =IF(G42="GVS","37.5",IF(G42="GVM","41.5",IF(G42="GVL","50",IF(G42="PCS","45.8",IF(G42="PCM","50",IF(G42="PCL","58.3","0")))))) -> 0
A43: =A42+1 -> 32 | J43: =IF(G43="RSL","55","0") -> 0 | K43: =IF(G43="GVS","37.5",IF(G43="GVM","41.5",IF(G43="GVL","50",IF(G43="PCS","45.8",IF(G43="PCM","50",IF(G43="PCL","58.3","0")))))) -> 0
A44: =A43+1 -> 33 | J44: =IF(G44="RSL","55","0") -> 0 | K44: =IF(G44="GVS","37.5",IF(G44="GVM","41.5",IF(G44="GVL","50",IF(G44="PCS","45.8",IF(G44="PCM","50",IF(G44="PCL","58.3","0")))))) -> 0
A45: =A44+1 -> 34 | J45: =IF(G45="RSL","55","0") -> 0 | K45: =IF(G45="GVS","37.5",IF(G45="GVM","41.5",IF(G45="GVL","50",IF(G45="PCS","45.8",IF(G45="PCM","50",IF(G45="PCL","58.3","0")))))) -> 0
A46: =A45+1 -> 35 | J46: =IF(G46="RSL","55","0") -> 0 | K46: =IF(G46="GVS","37.5",IF(G46="GVM","41.5",IF(G46="GVL","50",IF(G46="PCS","45.8",IF(G46="PCM","50",IF(G46="PCL","58.3","0")))))) -> 0
A47: =A46+1 -> 36 | J47: =IF(G47="RSL","55","0") -> 0 | K47: =IF(G47="GVS","37.5",IF(G47="GVM","41.5",IF(G47="GVL","50",IF(G47="PCS","45.8",IF(G47="PCM","50",IF(G47="PCL","58.3","0")))))) -> 0
A48: =A47+1 -> 37 | J48: =IF(G48="RSL","55","0") -> 0 | K48: =IF(G48="GVS","37.5",IF(G48="GVM","41.5",IF(G48="GVL","50",IF(G48="PCS","45.8",IF(G48="PCM","50",IF(G48="PCL","58.3","0")))))) -> 0
A49: =A48+1 -> 38 | J49: =IF(G49="RSL","55","0") -> 0 | K49: =IF(G49="GVS","37.5",IF(G49="GVM","41.5",IF(G49="GVL","50",IF(G49="PCS","45.8",IF(G49="PCM","50",IF(G49="PCL","58.3","0")))))) -> 0
... A61: =A60+1 -> 50 | J61: =IF(G61="RSL","55","0") -> 0 | K61: =IF(G61="GVS","37.5",IF(G61="GVM","41.5",IF(G61="GVL","50",IF(G61="PCS","45.8",IF(G61="PCM","50",IF(G61="PCL","58.3","0")))))) -> 0
A62: Page total | H62: =SUM(H37:H61) -> 0 | I62: =SUM(I37:I61) -> 0 | J62: =J61+J60+J59+J58+J57+J56+J55+J54+J53+J52+J51+J50+J49+J48+J47+J46+J45+J44+J43+J42+J41+J40+J39+J38+J37 -> 0 | K62: =K61+K60+K59+K58+K57+K56+K55+K54+K53+K52+K51+K50+K49+K48+K47+K46+K45+K44+K43+K42+K41+K40+K39+K38+K37 -> 0 | L62: =SUM(L37:L61) -> 0 | M62: =SUM(M37:M61) -> 0
R64: Page: 2
A65: Daily Report
A66: =A34 -> 1 - 10 - 2022 | H66: WEATHER | J66: =J34 -> SUNNY | L66: REPORT by | O66: =O34 -> JOHN | R66: TOTAL STAFF | T66: =T34 -> 5
A68: No | B68: Docket No | C68: Reg No | D68: Mobile | E68: Gender | F68: TIME | G68: Service | H68: CASH | I68: CARD | J68: RSL | K68: GV | L68: GV CASH | M68: GV CARD | N68: O/Taker | O68: Comment | R68: NAME | S68: Time In | T68: Time out | U68: Total Hours
A69: =A61+1 -> 51 | J69: =IF(G69="RSL","55","0") -> 0 | K69: =IF(G69="GVS","37.5",IF(G69="GVM","41.5",IF(G69="GVL","50",IF(G69="PCS","45.8",IF(G69="PCM","50",IF(G69="PCL","58.3","0")))))) -> 0
A70: =A69+1 -> 52 | J70: =IF(G70="RSL","55","0") -> 0 | K70: =IF(G70="GVS","37.5",IF(G70="GVM","41.5",IF(G70="GVL","50",IF(G70="PCS","45.8",IF(G70="PCM","50",IF(G70="PCL","58.3","0")))))) -> 0
A71: =A70+1 -> 53 | J71: =IF(G71="RSL","55","0") -> 0 | K71: =IF(G71="GVS","37.5",IF(G71="GVM","41.5",IF(G71="GVL","50",IF(G71="PCS","45.8",IF(G71="PCM","50",IF(G71="PCL","58.3","0")))))) -> 0
A72: =A71+1 -> 54 | J72: =IF(G72="RSL","55","0") -> 0 | K72: =IF(G72="GVS","37.5",IF(G72="GVM","41.5",IF(G72="GVL","50",IF(G72="PCS","45.8",IF(G72="PCM","50",IF(G72="PCL","58.3","0")))))) -> 0
A73: =A72+1 -> 55 | J73: =IF(G73="RSL","55","0") -> 0 | K73: =IF(G73="GVS","37.5",IF(G73="GVM","41.5",IF(G73="GVL","50",IF(G73="PCS","45.8",IF(G73="PCM","50",IF(G73="PCL","58.3","0")))))) -> 0
A74: =A73+1 -> 56 | J74: =IF(G74="RSL","55","0") -> 0 | K74: =IF(G74="GVS","37.5",IF(G74="GVM","41.5",IF(G74="GVL","50",IF(G74="PCS","45.8",IF(G74="PCM","50",IF(G74="PCL","58.3","0")))))) -> 0
A75: =A74+1 -> 57 | J75: =IF(G75="RSL","55","0") -> 0 | K75: =IF(G75="GVS","37.5",IF(G75="GVM","41.5",IF(G75="GVL","50",IF(G75="PCS","45.8",IF(G75="PCM","50",IF(G75="PCL","58.3","0")))))) -> 0
A76: =A75+1 -> 58 | J76: =IF(G76="RSL","55","0") -> 0 | K76: =IF(G76="GVS","37.5",IF(G76="GVM","41.5",IF(G76="GVL","50",IF(G76="PCS","45.8",IF(G76="PCM","50",IF(G76="PCL","58.3","0")))))) -> 0
A77: =A76+1 -> 59 | J77: =IF(G77="RSL","55","0") -> 0 | K77: =IF(G77="GVS","37.5",IF(G77="GVM","41.5",IF(G77="GVL","50",IF(G77="PCS","45.8",IF(G77="PCM","50",IF(G77="PCL","58.3","0")))))) -> 0
A78: =A77+1 -> 60 | J78: =IF(G78="RSL","55","0") -> 0 | K78: =IF(G78="GVS","37.5",IF(G78="GVM","41.5",IF(G78="GVL","50",IF(G78="PCS","45.8",IF(G78="PCM","50",IF(G78="PCL","58.3","0")))))) -> 0
A79: =A78+1 -> 61 | J79: =IF(G79="RSL","55","0") -> 0 | K79: =IF(G79="GVS","37.5",IF(G79="GVM","41.5",IF(G79="GVL","50",IF(G79="PCS","45.8",IF(G79="PCM","50",IF(G79="PCL","58.3","0")))))) -> 0
A80: =A79+1 -> 62 | J80: =IF(G80="RSL","55","0") -> 0 | K80: =IF(G80="GVS","37.5",IF(G80="GVM","41.5",IF(G80="GVL","50",IF(G80="PCS","45.8",IF(G80="PCM","50",IF(G80="PCL","58.3","0")))))) -> 0
A81: =A80+1 -> 63 | J81: =IF(G81="RSL","55","0") -> 0 | K81: =IF(G81="GVS","37.5",IF(G81="GVM","41.5",IF(G81="GVL","50",IF(G81="PCS","45.8",IF(G81="PCM","50",IF(G81="PCL","58.3","0")))))) -> 0
... A93: =A92+1 -> 75 | J93: =IF(G93="RSL","55","0") -> 0 | K93: =IF(G93="GVS","37.5",IF(G93="GVM","41.5",IF(G93="GVL","50",IF(G93="PCS","45.8",IF(G93="PCM","50",IF(G93="PCL","58.3","0")))))) -> 0
A94: Page total | H94: =SUM(H69:H93) -> 0 | I94: =SUM(I69:I93) -> 0 | J94: =J93+J92+J91+J90+J89+J88+J87+J86+J85+J84+J83+J82+J81+J80+J79+J78+J77+J76+J75+J74+J73+J72+J71+J70+J69 -> 0 | K94: =K93+K92+K91+K90+K89+K88+K87+K86+K85+K84+K83+K82+K81+K80+K79+K78+K77+K76+K75+K74+K73+K72+K71+K70+K69 -> 0 | L94: =SUM(L69:L93) -> 0 | M94: =SUM(M69:M93) -> 0
R96: Page: 3

Sheet SUN
A1: B2 Daily Report
A2: 2-10-2022 | H2: WEATHER | J2: SUNNY | L2: REPORT BY | O2: JOHN | R2: TOTAL STAFF | T2: 5 | X2: Merchant machine usage at B2 | AA2: Settle amount | AI2: Merchant machine usage at GA | AL2: Settle amount
A4: No | B4: Docket No | C4: Reg No | D4: Mobile | E4: Gender | F4: TIME | G4: Service | H4: CASH | I4: CARD | J4: RSL | K4: GV | L4: GV CASH | M4: GV CARD | N4: O/Taker | O4: Comment | R4: NAME | S4: Time In | T4: Time out | U4: Total Hours | Z4: B2 machine | AA4: BLH machine | AB4: Wongo | AE4: B2 machine | AF4: BLH machine | AG4: Wongo | AK4: GA machine | AL4: BLH machine | AM4: Wongo | AP4: GA machine | AQ4: BLH machine | AR4: Wongo
A5: 1 | B5: 11427 | C5: DWH66Y | D5: 0418288233 | E5: F | F5: 1110 | G5: GV1 | J5: =IF(G5="RSL","55","0") -> 0 | K5: 50 | M5: 375 | N5: JOHN | O5: 192415(6/6), 22057(NEW)) | R5: JOHN | S5: 0.35416667 | T5: 0.70833333 | U5: =(T5-S5)*24 -> 8.5 | X5: NOV | Y5: 1 | AD5: 16 | AI5: NOV | AJ5: 1 | AO5: 16
A6: 2 | B6: 11428 | C6: EGX77A | D6: 0428116471 | E6: M | F6: 1110 | G6: X | H6: 95 | J6: =IF(G6="RSL","55","0") -> 0 | K6: =IF(G6="GVS","37.5",IF(G6="GVM","41.5",IF(G6="GVL","50",IF(G6="PCS","45.8",IF(G6="PCM","50",IF(G6="PCL","58.3","0")))))) -> 0 | N6: JOHN | R6: HENDRA | S6: 0.33333333 | T6: 0.70833333 | U6: =(T6-S6)*24 -> 9 | W6: M | Y6: 2 | AD6: 17 | AJ6: 2 | AO6: 17
A7: 3 | B7: 11429 | C7: DFW71R | D7: 0411443549 | E7: M | F7: 1130 | G7: W/O | H7: 300 | J7: =IF(G7="RSL","55","0") -> 0 | K7: =IF(G7="GVS","37.5",IF(G7="GVM","41.5",IF(G7="GVL","50",IF(G7="PCS","45.8",IF(G7="PCM","50",IF(G7="PCL","58.3","0")))))) -> 0 | N7: JOHN | R7: KUROSH | S7: 0.41666667 | T7: 0.59375 | U7: =(T7-S7)*24 -> 4.25 | W7: F | Y7: 3 | AD7: 18 | AJ7: 3 | AO7: 18
A8: 4 | B8: 11430 | C8: YDE08X | D8: 0403255310 | E8: M | F8: 1145 | G8: H | I8: 121.2 | J8: =IF(G8="RSL","55","0") -> 0 | K8: =IF(G8="GVS","37.5",IF(G8="GVM","41.5",IF(G8="GVL","50",IF(G8="PCS","45.8",IF(G8="PCM","50",IF(G8="PCL","58.3","0")))))) -> 0 | N8: JOHN | O8: TAX | S8: 0.63541667 | T8: 0.70833333 | U8: =(T8-S8)*24 -> 1.75 | Y8: 4 | AD8: 19 | AJ8: 4 | AO8: 19
A9: 5 | B9: 11431 | C9: EKD76Y | D9: 0450277473 | E9: M | F9: 1215 | G9: X | I9: 95.95 | J9: =IF(G9="RSL","55","0") -> 0 | K9: =IF(G9="GVS","37.5",IF(G9="GVM","41.5",IF(G9="GVL","50",IF(G9="PCS","45.8",IF(G9="PCM","50",IF(G9="PCL","58.3","0")))))) -> 0 | N9: JOHN | R9: VINNY | S9: 0.42708333 | T9: 0.70833333 | U9: =(T9-S9)*24 -> 6.75 | X9: EXCL RSL | Y9: 5 | AD9: 20 | AJ9: 5 | AO9: 20
A10: 6 | B10: 11432 | C10: DVW77C | D10: 0412621409 | E10: F | F10: 1240 | G10: D | I10: 75.75 | J10: =IF(G10="RSL","55","0") -> 0 | K10: =IF(G10="GVS","37.5",IF(G10="GVM","41.5",IF(G10="GVL","50",IF(G10="PCS","45.8",IF(G10="PCM","50",IF(G10="PCL","58.3","0")))))) -> 0 | N10: JOHN | R10: KADAM | S10: 0.44791667 | T10: 0.70833333 | U10: =(T10-S10)*24 -> 6.25 | Y10: 6 | AD10: 21 | AJ10: 6 | AO10: 21
A11: 7 | B11: 11433 | C11: CWB93E | D11: 0479167486 | E11: F | F11: 1245 | G11: H | I11: 131.3 | J11: =IF(G11="RSL","55","0") -> 0 | K11: =IF(G11="GVS","37.5",IF(G11="GVM","41.5",IF(G11="GVL","50",IF(G11="PCS","45.8",IF(G11="PCM","50",IF(G11="PCL","58.3","0")))))) -> 0 | N11: JOHN | U11: =(T11-S11)*24 -> 0 | Y11: 7 | AD11: 22 | AJ11: 7 | AO11: 22
A12: 8 | B12: 11434 | C12: DPE65K | D12: 0451990170 | E12: F | F12: 1250 | G12: X | H12: 95 | J12: =IF(G12="RSL","55","0") -> 0 | K12: =IF(G12="GVS","37.5",IF(G12="GVM","41.5",IF(G12="GVL","50",IF(G12="PCS","45.8",IF(G12="PCM","50",IF(G12="PCL","58.3","0")))))) -> 0 | N12: JOHN | U12: =(T12-S12)*24 -> 0 | Y12: 8 | AD12: 23 | AJ12: 8 | AO12: 23
A13: 9 | B13: 11435 | C13: NSZ899 | D13: 0422028291 | E13: F | F13: 1320 | G13: PCL | J13: =IF(G13="RSL","55","0") -> 0 | K13: 79.16 | M13: 475 | N13: JOHN | O13: 21048(6/6), 22087(NEW) | U13: =(T13-S13)*24 -> 0 | Y13: 9 | AD13: 24 | AJ13: 9 | AO13: 24
A14: 10 | B14: 11436 | C14: DAU95Y | D14: 0481370966 | E14: M | F14: 1330 | G14: D | I14: 55 | J14: =IF(G14="RSL","55","0") -> 0 | K14: =IF(G14="GVS","37.5",IF(G14="GVM","41.5",IF(G14="GVL","50",IF(G14="PCS","45.8",IF(G14="PCM","50",IF(G14="PCL","58.3","0")))))) -> 0 | N14: JOHN | U14: =(T14-S14)*24 -> 0 | Y14: 10 | AD14: 25 | AJ14: 10 | AO14: 25
A15: 11 | B15: 11437 | C15: DTM78K | D15: 0468814911 | E15: F | F15: 1505 | G15: X | I15: 95 | J15: =IF(G15="RSL","55","0") -> 0 | K15: =IF(G15="GVS","37.5",IF(G15="GVM","41.5",IF(G15="GVL","50",IF(G15="PCS","45.8",IF(G15="PCM","50",IF(G15="PCL","58.3","0")))))) -> 0 | N15: JOHN | U15: =(T15-S15)*24 -> 0 | Y15: 11 | AD15: 26 | AJ15: 11 | AO15: 26
A16: 12 | B16: 11438 | C16: EMB75G | D16: 0414973686 | E16: F | F16: 1515 | G16: X | H16: 95 | J16: =IF(G16="RSL","55","0") -> 0 | K16: =IF(G16="GVS","37.5",IF(G16="GVM","41.5",IF(G16="GVL","50",IF(G16="PCS","45.8",IF(G16="PCM","50",IF(G16="PCL","58.3","0")))))) -> 0 | N16: HENDRA | R16: =H32/U16 -> 0.38356164 | S16: =H32/(U16-U5) -> 0.5 | T16: =C32/U16 -> 38.859178 | U16: =SUM(U5:U15) -> 36.5 | Y16: 12 | AD16: 27 | AJ16: 12 | AO16: 27
A17: 13 | B17: 11439 | C17: 88BMWM | D17: 0479077545 | E17: M | F17: 1555 | G17: D | H17: 75 | J17: =IF(G17="RSL","55","0") -> 0 | K17: =IF(G17="GVS","37.5",IF(G17="GVM","41.5",IF(G17="GVL","50",IF(G17="PCS","45.8",IF(G17="PCM","50",IF(G17="PCL","58.3","0")))))) -> 0 | N17: JOHN | R17: Cars/T Hr ① | S17: Cars/T Hr ② | T17: Sales/T Hr | U17: Total Hours | Y17: 13 | AD17: 28 | AJ17: 13 | AO17: 28
A18: 14 | B18: 11440 | C18: DMS63Z | D18: 0434666669 | E18: M | F18: 1615 | G18: D | I18: 55 | J18: =IF(G18="RSL","55","0") -> 0 | K18: =IF(G18="GVS","37.5",IF(G18="GVM","41.5",IF(G18="GVL","50",IF(G18="PCS","45.8",IF(G18="PCM","50",IF(G18="PCL","58.3","0")))))) -> 0 | N18: JOHN | R18: ITEM | S18: QTY | T18: AMT | U18: RMKS | Y18: 14 | AD18: 29 | AJ18: 14 | AO18: 29
A19: 15 | J19: =IF(G19="RSL","55","0") -> 0 | K19: =IF(G19="GVS","37.5",IF(G19="GVM","41.5",IF(G19="GVL","50",IF(G19="PCS","45.8",IF(G19="PCM","50",IF(G19="PCL","58.3","0")))))) -> 0 | R19: GV | S19: =COUNT(L5:M29,L37:M61,L69:M93) -> 2 | T19: =SUM(L5:M29,L37:M61,L69:M93) -> 850 | Y19: 15 | AD19: 30 | AJ19: 15 | AO19: 30
A20: 16 | J20: =IF(G20="RSL","55","0") -> 0 | K20: =IF(G20="GVS","37.5",IF(G20="GVM","41.5",IF(G20="GVL","50",IF(G20="PCS","45.8",IF(G20="PCM","50",IF(G20="PCL","58.3","0")))))) -> 0 | AD20: 31 | AO20: 31
A21: 17 | J21: =IF(G21="RSL","55","0") -> 0 | K21: =IF(G21="GVS","37.5",IF(G21="GVM","41.5",IF(G21="GVL","50",IF(G21="PCS","45.8",IF(G21="PCM","50",IF(G21="PCL","58.3","0")))))) -> 0
A22: 18 | J22: =IF(G22="RSL","55","0") -> 0 | K22: =IF(G22="GVS","37.5",IF(G22="GVM","41.5",IF(G22="GVL","50",IF(G22="PCS","45.8",IF(G22="PCM","50",IF(G22="PCL","58.3","0")))))) -> 0 | AD22: Total | AE22: =SUM(Z5:Z19,AE5:AE20) -> 0 | AF22: =SUM(AA5:AA19,AF5:AF20,) -> 0 | AG22: =SUM(AB5:AB19,AG5:AG20) -> 0 | AO22: Total | AP22: =SUM(AK5:AK19,AP5:AP20) -> 0 | AQ22: =SUM(AL5:AL19,AQ5:AQ20,) -> 0 | AR22: =SUM(AM5:AM19,AR5:AR20) -> 0
A23: 19 | J23: =IF(G23="RSL","55","0") -> 0 | K23: =IF(G23="GVS","37.5",IF(G23="GVM","41.5",IF(G23="GVL","50",IF(G23="PCS","45.8",IF(G23="PCM","50",IF(G23="PCL","58.3","0")))))) -> 0
A24: 20 | J24: =IF(G24="RSL","55","0") -> 0 | K24: =IF(G24="GVS","37.5",IF(G24="GVM","41.5",IF(G24="GVL","50",IF(G24="PCS","45.8",IF(G24="PCM","50",IF(G24="PCL","58.3","0")))))) -> 0 | R24: SMALL | S24: MEDIUM | T24: LARGE | U24: TOTAL | AD24: B2/GA TOTAL | AE24: B2 machine | AF24: GA machine | AG24: BLH machine | AH24: Wongo machine | AI24: Sub total
A25: 21 | J25: =IF(G25="RSL","55","0") -> 0 | K25: =IF(G25="GVS","37.5",IF(G25="GVM","41.5",IF(G25="GVL","50",IF(G25="PCS","45.8",IF(G25="PCM","50",IF(G25="PCL","58.3","0")))))) -> 0 | R25: =COUNTIF(G5:G29,"GV1")+COUNTIF(G37:G61,"GV1")+COUNTIF(G69:G93,"GV1") -> 1 | S25: =COUNTIF(G5:G29,"GV2")+COUNTIF(G37:G61,"GV2")+COUNTIF(G69:G93,"GV2") -> 0 | T25: =COUNTIF(G5:G29,"GV3")+COUNTIF(G37:G61,"GV3")+COUNTIF(G69:G93,"GV3") -> 0 | U25: =((C32+(R26+S26+T26)*0.5)) -> 1437.11 | AD25: =SUM(AE25:AF25) -> 0 | AE25: =SUM(AE22) -> 0 | AF25: =SUM(AP22) -> 0 | AG25: =SUM(AF22+AQ22) -> 0 | AH25: =AG22+AR22 -> 0 | AI25: =SUM(AE25:AH25) -> 0
A26: 22 | J26: =IF(G26="RSL","55","0") -> 0 | K26: =IF(G26="GVS","37.5",IF(G26="GVM","41.5",IF(G26="GVL","50",IF(G26="PCS","45.8",IF(G26="PCM","50",IF(G26="PCL","58.3","0")))))) -> 0 | R26: =R25*37.5 -> 37.5 | S26: =S25*41.5 -> 0 | T26: =T25*50 -> 0 | X26: Branch cards
A27: 23 | J27: =IF(G27="RSL","55","0") -> 0 | K27: =IF(G27="GVS","37.5",IF(G27="GVM","41.5",IF(G27="GVL","50",IF(G27="PCS","45.8",IF(G27="PCM","50",IF(G27="PCL","58.3","0")))))) -> 0 | R27: Expense | X27: 1 | Z27: -2745
A28: 24 | J28: =IF(G28="RSL","55","0") -> 0 | K28: =IF(G28="GVS","37.5",IF(G28="GVM","41.5",IF(G28="GVL","50",IF(G28="PCS","45.8",IF(G28="PCM","50",IF(G28="PCL","58.3","0")))))) -> 0 | X28: 2
A29: 25 | J29: =IF(G29="RSL","55","0") -> 0 | K29: =IF(G29="GVS","37.5",IF(G29="GVM","41.5",IF(G29="GVL","50",IF(G29="PCS","45.8",IF(G29="PCM","50",IF(G29="PCL","58.3","0")))))) -> 0 | X29: 3
A30: Page total | H30: =SUM(H5:H29) -> 660 | I30: =SUM(I5:I29) -> 629.2 | J30: =J5+J6+J7+J8+J9+J10+J11+J12+J13+J14+J15+J16+J18+J19+J17+J20+J22+J23+J21+J24+J25+J26+J27+J28+J29 -> 0 | K30: =K5+K6+K7+K8+K9+K10+K11+K12+K13+K14+K15+K16+K18+K19+K17+K20+K22+K23+K21+K24+K25+K26+K27+K28+K29 -> 129.16 | L30: =SUM(L5:L29) -> 0 | M30: =SUM(M5:M29) -> 850 | N30: CASH | O30: CARD | P30: GV | Q30: RSL | X30: 4
A31: Daily Total | H31: =H30+H62+H94 -> 660 | I31: =I30+I62+I94 -> 629.2 | J31: =J30+J62+J94 -> 0 | K31: =K30+K62+K94 -> 129.16 | L31: =L30+L62+L94 -> 0 | M31: =M30+M62+M94 -> 850 | N31: =COUNT(H5:H29,H37:H61,H69:H93) -> 5 | O31: =COUNT(I5:I29,I37:I61,I69:I93) -> 7 | P31: =COUNTIF(G5:G29,"G*")+COUNTIF(G37:G61,"G*")+COUNTIF(G69:G93,"G*")+COUNTIF(G5:G29,"P*")+COUNTIF(G37:G61,"P*")+COUNTIF(G69:G93,"P*") -> 2 | Q31: =COUNTIF(G5:G29,"RSL")+COUNTIF(G37:G61,"RSL")+COUNTIF(G69:G93,"RSL") -> 0 | R31: CASH CLOSING | S31: =H31+L31-U28-U29-U30 -> 660 | T31: =H31+I31+L31+M31 -> 2139.2 | X31: Subtotal | Z31: =SUM(Z27:Z30) -> -2745
A32: TOTAL SALES | C32: =H31+I31+J31+K31 -> 1418.36 | F32: No of Cars | H32: =COUNT(B5:B29,B37:B61,B69:B93) -> 14 | I32: Average | K32: =C32/H32 -> 101.31143 | N32: =H31/C32 -> 0.46532615 | O32: =I31/C32 -> 0.44361093 | P32: =K31/C32 -> 0.091062918 | Q32: =J31/C32 -> 0 | R32: CARD CLOSING | S32: =I31+M31 -> 1479.2 | X32: B2 card | Z32: =I31 -> 629.2
A33: Daily Report | X33: Settlement | Z33: =SUM(Z31:Z32) -> -2115.8
A34: =A2 -> 2-10-2022 | H34: WEATHER | J34: =J2 -> SUNNY | L34: REPORT by | O34: =O2 -> JOHN | R34: TOTAL STAFF | T34: =T2 -> 5
A36: No | B36: Docket No | C36: Reg No | D36: Mobile | E36: Gender | F36: TIME | G36: Service | H36: CASH | I36: CARD | J36: RSL | K36: GV | L36: GV CASH | M36: GV CARD | N36: O/Taker | O36: Comment | R36: NAME | S36: Time In | T36: Time out | U36: Total Hours
A37: =A29+1 -> 26 | J37: =IF(G37="RSL","55","0") -> 0 | K37: =IF(G37="GVS","37.5",IF(G37="GVM","41.5",IF(G37="GVL","50",IF(G37="PCS","45.8",IF(G37="PCM","50",IF(G37="PCL","58.3","0")))))) -> 0
A38: =A37+1 -> 27 | J38: =IF(G38="RSL","55","0") -> 0 | K38: =IF(G38="GVS","37.5",IF(G38="GVM","41.5",IF(G38="GVL","50",IF(G38="PCS","45.8",IF(G38="PCM","50",IF(G38="PCL","58.3","0")))))) -> 0
A39: =A38+1 -> 28 | J39: =IF(G39="RSL","55","0") -> 0 | K39: =IF(G39="GVS","37.5",IF(G39="GVM","41.5",IF(G39="GVL","50",IF(G39="PCS","45.8",IF(G39="PCM","50",IF(G39="PCL","58.3","0")))))) -> 0
A40: =A39+1 -> 29 | J40: =IF(G40="RSL","55","0") -> 0 | K40: =IF(G40="GVS","37.5",IF(G40="GVM","41.5",IF(G40="GVL","50",IF(G40="PCS","45.8",IF(G40="PCM","50",IF(G40="PCL","58.3","0")))))) -> 0
A41: =A40+1 -> 30 | J41: =IF(G41="RSL","55","0") -> 0 | K41: =IF(G41="GVS","37.5",IF(G41="GVM","41.5",IF(G41="GVL","50",IF(G41="PCS","45.8",IF(G41="PCM","50",IF(G41="PCL","58.3","0")))))) -> 0
A42: =A41+1 -> 31 | J42: =IF(G42="RSL","55","0") -> 0 | K42: =IF(G42="GVS","37.5",IF(G42="GVM","41.5",IF(G42="GVL","50",IF(G42="PCS","45.8",IF(G42="PCM","50",IF(G42="PCL","58.3","0")))))) -> 0
A43: =A42+1 -> 32 | J43: =IF(G43="RSL","55","0") -> 0 | K43: =IF(G43="GVS","37.5",IF(G43="GVM","41.5",IF(G43="GVL","50",IF(G43="PCS","45.8",IF(G43="PCM","50",IF(G43="PCL","58.3","0")))))) -> 0
A44: =A43+1 -> 33 | J44: =IF(G44="RSL","55","0") -> 0 | K44: =IF(G44="GVS","37.5",IF(G44="GVM","41.5",IF(G44="GVL","50",IF(G44="PCS","45.8",IF(G44="PCM","50",IF(G44="PCL","58.3","0")))))) -> 0
A45: =A44+1 -> 34 | J45: =IF(G45="RSL","55","0") -> 0 | K45: =IF(G45="GVS","37.5",IF(G45="GVM","41.5",IF(G45="GVL","50",IF(G45="PCS","45.8",IF(G45="PCM","50",IF(G45="PCL","58.3","0")))))) -> 0
A46: =A45+1 -> 35 | J46: =IF(G46="RSL","55","0") -> 0 | K46: =IF(G46="GVS","37.5",IF(G46="GVM","41.5",IF(G46="GVL","50",IF(G46="PCS","45.8",IF(G46="PCM","50",IF(G46="PCL","58.3","0")))))) -> 0
A47: =A46+1 -> 36 | J47: =IF(G47="RSL","55","0") -> 0 | K47: =IF(G47="GVS","37.5",IF(G47="GVM","41.5",IF(G47="GVL","50",IF(G47="PCS","45.8",IF(G47="PCM","50",IF(G47="PCL","58.3","0")))))) -> 0
A48: =A47+1 -> 37 | J48: =IF(G48="RSL","55","0") -> 0 | K48: =IF(G48="GVS","37.5",IF(G48="GVM","41.5",IF(G48="GVL","50",IF(G48="PCS","45.8",IF(G48="PCM","50",IF(G48="PCL","58.3","0")))))) -> 0
A49: =A48+1 -> 38 | J49: =IF(G49="RSL","55","0") -> 0 | K49: =IF(G49="GVS","37.5",IF(G49="GVM","41.5",IF(G49="GVL","50",IF(G49="PCS","45.8",IF(G49="PCM","50",IF(G49="PCL","58.3","0")))))) -> 0
... A61: =A60+1 -> 50 | J61: =IF(G61="RSL","55","0") -> 0 | K61: =IF(G61="GVS","37.5",IF(G61="GVM","41.5",IF(G61="GVL","50",IF(G61="PCS","45.8",IF(G61="PCM","50",IF(G61="PCL","58.3","0")))))) -> 0
A62: Page total | H62: =SUM(H37:H61) -> 0 | I62: =SUM(I37:I61) -> 0 | J62: =J61+J60+J59+J58+J57+J56+J55+J54+J53+J52+J51+J50+J49+J48+J47+J46+J45+J44+J43+J42+J41+J40+J39+J38+J37 -> 0 | K62: =K61+K60+K59+K58+K57+K56+K55+K54+K53+K52+K51+K50+K49+K48+K47+K46+K45+K44+K43+K42+K41+K40+K39+K38+K37 -> 0 | L62: =SUM(L37:L61) -> 0 | M62: =SUM(M37:M61) -> 0
R64: Page: 2
A65: Daily Report
A66: =A34 -> 2-10-2022 | H66: WEATHER | J66: =J34 -> SUNNY | L66: REPORT by | O66: =O34 -> JOHN | R66: TOTAL STAFF | T66: =T34 -> 5
A68: No | B68: Docket No | C68: Reg No | D68: Mobile | E68: Gender | F68: TIME | G68: Service | H68: CASH | I68: CARD | J68: RSL | K68: GV | L68: GV CASH | M68: GV CARD | N68: O/Taker | O68: Comment | R68: NAME | S68: Time In | T68: Time out | U68: Total Hours
A69: =A61+1 -> 51 | J69: =IF(G69="RSL","55","0") -> 0 | K69: =IF(G69="GVS","37.5",IF(G69="GVM","41.5",IF(G69="GVL","50",IF(G69="PCS","45.8",IF(G69="PCM","50",IF(G69="PCL","58.3","0")))))) -> 0
A70: =A69+1 -> 52 | J70: =IF(G70="RSL","55","0") -> 0 | K70: =IF(G70="GVS","37.5",IF(G70="GVM","41.5",IF(G70="GVL","50",IF(G70="PCS","45.8",IF(G70="PCM","50",IF(G70="PCL","58.3","0")))))) -> 0
A71: =A70+1 -> 53 | J71: =IF(G71="RSL","55","0") -> 0 | K71: =IF(G71="GVS","37.5",IF(G71="GVM","41.5",IF(G71="GVL","50",IF(G71="PCS","45.8",IF(G71="PCM","50",IF(G71="PCL","58.3","0")))))) -> 0
A72: =A71+1 -> 54 | J72: =IF(G72="RSL","55","0") -> 0 | K72: =IF(G72="GVS","37.5",IF(G72="GVM","41.5",IF(G72="GVL","50",IF(G72="PCS","45.8",IF(G72="PCM","50",IF(G72="PCL","58.3","0")))))) -> 0
A73: =A72+1 -> 55 | J73: =IF(G73="RSL","55","0") -> 0 | K73: =IF(G73="GVS","37.5",IF(G73="GVM","41.5",IF(G73="GVL","50",IF(G73="PCS","45.8",IF(G73="PCM","50",IF(G73="PCL","58.3","0")))))) -> 0
A74: =A73+1 -> 56 | J74: =IF(G74="RSL","55","0") -> 0 | K74: =IF(G74="GVS","37.5",IF(G74="GVM","41.5",IF(G74="GVL","50",IF(G74="PCS","45.8",IF(G74="PCM","50",IF(G74="PCL","58.3","0")))))) -> 0
A75: =A74+1 -> 57 | J75: =IF(G75="RSL","55","0") -> 0 | K75: =IF(G75="GVS","37.5",IF(G75="GVM","41.5",IF(G75="GVL","50",IF(G75="PCS","45.8",IF(G75="PCM","50",IF(G75="PCL","58.3","0")))))) -> 0
A76: =A75+1 -> 58 | J76: =IF(G76="RSL","55","0") -> 0 | K76: =IF(G76="GVS","37.5",IF(G76="GVM","41.5",IF(G76="GVL","50",IF(G76="PCS","45.8",IF(G76="PCM","50",IF(G76="PCL","58.3","0")))))) -> 0
A77: =A76+1 -> 59 | J77: =IF(G77="RSL","55","0") -> 0 | K77: =IF(G77="GVS","37.5",IF(G77="GVM","41.5",IF(G77="GVL","50",IF(G77="PCS","45.8",IF(G77="PCM","50",IF(G77="PCL","58.3","0")))))) -> 0
A78: =A77+1 -> 60 | J78: =IF(G78="RSL","55","0") -> 0 | K78: =IF(G78="GVS","37.5",IF(G78="GVM","41.5",IF(G78="GVL","50",IF(G78="PCS","45.8",IF(G78="PCM","50",IF(G78="PCL","58.3","0")))))) -> 0
A79: =A78+1 -> 61 | J79: =IF(G79="RSL","55","0") -> 0 | K79: =IF(G79="GVS","37.5",IF(G79="GVM","41.5",IF(G79="GVL","50",IF(G79="PCS","45.8",IF(G79="PCM","50",IF(G79="PCL","58.3","0")))))) -> 0
A80: =A79+1 -> 62 | J80: =IF(G80="RSL","55","0") -> 0 | K80: =IF(G80="GVS","37.5",IF(G80="GVM","41.5",IF(G80="GVL","50",IF(G80="PCS","45.8",IF(G80="PCM","50",IF(G80="PCL","58.3","0")))))) -> 0
A81: =A80+1 -> 63 | J81: =IF(G81="RSL","55","0") -> 0 | K81: =IF(G81="GVS","37.5",IF(G81="GVM","41.5",IF(G81="GVL","50",IF(G81="PCS","45.8",IF(G81="PCM","50",IF(G81="PCL","58.3","0")))))) -> 0
... A93: =A92+1 -> 75 | J93: =IF(G93="RSL","55","0") -> 0 | K93: =IF(G93="GVS","37.5",IF(G93="GVM","41.5",IF(G93="GVL","50",IF(G93="PCS","45.8",IF(G93="PCM","50",IF(G93="PCL","58.3","0")))))) -> 0
A94: Page total | H94: =SUM(H69:H93) -> 0 | I94: =SUM(I69:I93) -> 0 | J94: =J93+J92+J91+J90+J89+J88+J87+J86+J85+J84+J83+J82+J81+J80+J79+J78+J77+J76+J75+J74+J73+J72+J71+J70+J69 -> 0 | K94: =K93+K92+K91+K90+K89+K88+K87+K86+K85+K84+K83+K82+K81+K80+K79+K78+K77+K76+K75+K74+K73+K72+K71+K70+K69 -> 0 | L94: =SUM(L69:L93) -> 0 | M94: =SUM(M69:M93) -> 0
R96: Page: 3

Sheet WEEKLY TOTAL
E1: CARS | H1: AMOUNT | L1: PERCENTAGE | Q1: TOTAL CARS | V1: TOTAL AMOUNT | AA1: AVERAGE
A2: MON | B2: Cash | E2: =MON!N31 -> 7 | H2: =MON!S31 -> 670 | L2: =MON!N32 -> 0.27836521 | Q2: =SUM(E2:G5) -> 20 | V2: =SUM(H2,H3,H5) -> 2227.75 | AA2: =V2/Q2 -> 111.3875
B3: Card | E3: =MON!O31 -> 7 | H3: =MON!S32 -> 1337.75 | L3: =MON!O32 -> 0.55579561
B4: GV | E4: =MON!P31 -> 2 | H4: =MON!K31 -> 179.16 | L4: =MON!P32 -> 0.074435687
B5: RSL | E5: =MON!Q31 -> 4 | H5: =MON!J31 -> 220 | L5: =MON!Q32 -> 0.091403501
B6: hrs | E6: =MON!U16 -> 35.25 | H6: no. staff | L6: =MON!T2 -> 4
A7: TUE | B7: Cash | E7: =TUE!N31 -> 9 | H7: =TUE!S31 -> 650 | L7: =TUE!N32 -> 0.36642426 | Q7: =SUM(E7:G10) -> 15 | V7: =SUM(H7,H8,H10) -> 1773.9 | AA7: =V7/Q7 -> 118.26
B8: Card | E8: =TUE!O31 -> 5 | H8: =TUE!S32 -> 1068.9 | L8: =TUE!O32 -> 0.60257061
B9: GV | E9: =TUE!P31 -> 0 | H9: =TUE!K31 -> 0 | L9: =TUE!P32 -> 0
B10: RSL | E10: =TUE!Q31 -> 1 | H10: =TUE!J31 -> 55 | L10: =TUE!Q32 -> 0.03100513
B11: hrs | E11: =TUE!U16 -> 33.5 | H11: no. staff | L11: =TUE!T2 -> 3
A12: WED | B12: Cash | E12: =WED!N31 -> 3 | H12: =WED!S31 -> 365 | L12: =WED!N32 -> 0.28199482 | Q12: =SUM(E12:G15) -> 11 | V12: =SUM(H12,H13,H15) -> 1294.35 | AA12: =V12/Q12 -> 117.66818
B13: Card | E13: =WED!O31 -> 8 | H13: =WED!S32 -> 929.35 | L13: =WED!O32 -> 0.71800518
B14: GV | E14: =WED!P31 -> 0 | H14: =WED!K31 -> 0 | L14: =WED!P32 -> 0
B15: RSL | E15: =WED!Q31 -> 0 | H15: =WED!J31 -> 0 | L15: =WED!Q32 -> 0
B16: hrs | E16: =WED!U16 -> 25 | H16: no. staff | L16: =WED!T2 -> 4
A17: THU | B17: Cash | E17: =THU!N31 -> 5 | H17: =THU!S31 -> 435 | L17: =THU!N32 -> 0.38701068 | Q17: =SUM(E17:G20) -> 13 | V17: =SUM(H17,H18,H20) -> 886.7 | AA17: =V17/Q17 -> 68.207692
B18: Card | E18: =THU!O31 -> 4 | H18: =THU!S32 -> 341.7 | L18: =THU!O32 -> 0.30400356
B19: GV | E19: =THU!P31 -> 3 | H19: =THU!K31 -> 237.3 | L19: =THU!P32 -> 0.211121
B20: RSL | E20: =THU!Q31 -> 1 | H20: =THU!J31 -> 110 | L20: =THU!Q32 -> 0.097864769
B21: hrs | E21: =THU!U16 -> 38.75 | H21: no. staff | L21: =THU!T2 -> 5
A22: FR I | B22: Cash | E22: =FRI!N31 -> 3 | H22: =FRI!S31 -> 225 | L22: =FRI!N32 -> 0.21281023 | Q22: =SUM(E22:G25) -> 11 | V22: =SUM(H22,H23,H25) -> 445 | AA22: =V22/Q22 -> 40.454545
B23: Card | E23: =FRI!O31 -> 5 | H23: =FRI!IS32 -> 0 | L23: =FRI!O32 -> 0.47191851
B24: GV | E24: =FRI!P31 -> 1 | H24: =FRI!K31 -> 113.33 | L24: =FRI!P32 -> 0.10719015
B25: RSL | E25: =FRI!Q31 -> 2 | H25: =FRI!J31 -> 220 | L25: =FRI!Q32 -> 0.20808111
B26: hrs | E26: =FRI!U16 -> 29.25 | H26: no. staff | L26: =FRI!T2 -> 4
A27: SAT | B27: Cash | E27: =SAT!N31 -> 11 | H27: =SAT!S31 -> 1335 | L27: =SAT!N32 -> 0.5142527 | Q27: =SUM(E27:G30) -> 20 | V27: =SUM(H27,H28,H30) -> 3371.65 | AA27: =V27/Q27 -> 168.5825
B28: Card | E28: =SAT!O31 -> 7 | H28: =SAT!S32 -> 1981.65 | L28: =SAT!O32 -> 0.43409091
B29: GV | E29: =SAT!P31 -> 1 | H29: =SAT!K31 -> 79.1 | L29: =SAT!P32 -> 0.030469954
B30: RSL | E30: =SAT!Q31 -> 1 | H30: =SAT!J31 -> 55 | L30: =SAT!Q32 -> 0.021186441
B31: hrs | E31: =SAT!U16 -> 36.75 | H31: no. staff | L31: =SAT!T2 -> 5
A32: SUN | B32: Cash | E32: =SUN!N31 -> 5 | H32: =SUN!S31 -> 660 | L32: =SUN!N32 -> 0.46532615 | Q32: =SUM(E32:G35) -> 14 | V32: =SUM(H32,H33,H35) -> 2139.2 | AA32: =V32/Q32 -> 152.8
B33: Card | E33: =SUN!O31 -> 7 | H33: =SUN!S32 -> 1479.2 | L33: =SUN!O32 -> 0.44361093
B34: GV | E34: =SUN!P31 -> 2 | H34: =SUN!K31 -> 129.16 | L34: =SUN!P32 -> 0.091062918
B35: RSL | E35: =SUN!Q31 -> 0 | H35: =SUN!J31 -> 0 | L35: =SUN!Q32 -> 0
B36: hrs | E36: =SUN!U16 -> 36.5 | H36: no. staff | L36: =SUN!T2 -> 5
A37: TOTAL CARS | E37: TOTAL SALES | K37: AVERAGE | O37: RSL | T37: GV | Y37: GV SOLD
A39: =SUM(Q2:U35) -> 104 | E39: =SUM(V2:Z35) -> 12138.55 | K39: =E39/A39 -> 116.71683 | O39: =SUM(MON:SUN!Q31) -> 9 | T39: =SUM(MON:SUN!P31) -> 9 | Y39: =SUM(MON:SUN!S19) -> 4
O41: =SUM(MON:SUN!J31) -> 660 | T41: =SUM(MON:SUN!K31) -> 738.05 | Y41: =SUM(MON:SUN!T19) -> 1704.75
A43: TOTAL CASH | F43: TOTAL CARD | K43: TOTAL RSL | P43: TOTAL GV | U43: STAFF HRS | Z43: no. staff
A45: =SUM(H2,H7,H12,H17,H22,H27,H32) -> 4340 | F45: =SUM(,H3,H8,H13,H18,H23,H28,H33) -> 7138.55 | K45: =SUM(H5,H10,H15,H20,H25,H30,H35) -> 660 | P45: =SUM(H4,H9,H14,H19,H24,H29,H34) -> 738.05 | U45: =SUM(E6,E11,E16,E21,E26,E31,E36) -> 235 | Z45: =SUM(L6,L11,L16,L21,L26,L31,L36) -> 30
A49: =A45/E39 -> 0.35753859 | F49: =F45/E39 -> 0.58808919 | K49: =K45/E39 -> 0.054372227 | P49: =P45/E39 -> 0.060802155 | U49: =U45/7 -> 33.571429 | Z49: =U45/Z45 -> 7.8333333
