Workbook

Sheet MON
A1: B2 Daily Report
A2: 16 - 5 - 2022 | H2: WEATHER | J2: SUNNY | L2: REPORT BY | O2: HENDRA | R2: TOTAL STAFF | T2: 5 | X2: Merchant machine usage at B2 | AA2: Settle amount | AI2: Merchant machine usage at GA | AL2: Settle amount
A4: No | B4: Docket No | C4: Reg No | D4: Mobile | E4: Gender | F4: TIME | G4: Service | H4: CASH | I4: CARD | J4: RSL | K4: GV | L4: GV CASH | M4: GV CARD | N4: O/Taker | O4: Comment | R4: NAME | S4: Time In | T4: Time out | U4: Total Hours | Z4: B2 machine | AA4: BLH machine | AB4: Wongo | AE4: B2 machine | AF4: BLH machine | AG4: Wongo | AK4: GA machine | AL4: BLH machine | AM4: Wongo | AP4: GA machine | AQ4: BLH machine | AR4: Wongo
A5: 1 | B5: 4162 | C5: GBI | D5: 0415888891 | E5: M | F5: 815 | G5: H | I5: 150 | J5: =IF(G5="RSL","55","0") -> 0 | K5: =IF(G5="GVS","37.5",IF(G5="GVM","41.5",IF(G5="GVL","50",IF(G5="PCS","45.8",IF(G5="PCM","50",IF(G5="PCL","58.3","0")))))) -> 0 | N5: HENDRA | O5: GEORGE CAR | R5: HENDRA | S5: 0.33333333 | T5: 0.72916667 | U5: =(T5-S5)*24 -> 9.5 | X5: NOV | Y5: 1 | AD5: 16 | AI5: NOV | AJ5: 1 | AO5: 16
A6: 2 | B6: 4163 | C6: JCL138 | D6: 0406120826 | E6: F | F6: 830 | G6: PCL | J6: =IF(G6="RSL","55","0") -> 0 | K6: =IF(G6="GVS","37.5",IF(G6="GVM","41.5",IF(G6="GVL","50",IF(G6="PCS","45.8",IF(G6="PCM","50",IF(G6="PCL","58.3","0")))))) -> 58.3 | N6: JUNIOR | O6: # 21122810 1/6 | R6: JUNIOR | S6: 0.33333333 | T6: 0.72916667 | U6: =(T6-S6)*24 -> 9.5 | W6: M | Y6: 2 | AD6: 17 | AJ6: 2 | AO6: 17
A7: 3 | B7: 4164 | C7: BWP56A | D7: 0432303166 | E7: F | F7: 835 | G7: D | I7: 75 | J7: =IF(G7="RSL","55","0") -> 0 | K7: =IF(G7="GVS","37.5",IF(G7="GVM","41.5",IF(G7="GVL","50",IF(G7="PCS","45.8",IF(G7="PCM","50",IF(G7="PCL","58.3","0")))))) -> 0 | N7: JUNIOR | R7: ARIANTO | S7: 0.375 | T7: 0.67708333 | U7: =(T7-S7)*24 -> 7.25 | W7: F | Y7: 3 | AD7: 18 | AJ7: 3 | AO7: 18
A8: 4 | B8: 4165 | C8: DJF90D | D8: 0450802929 | E8: M | F8: 845 | G8: H | H8: 120 | J8: =IF(G8="RSL","55","0") -> 0 | K8: =IF(G8="GVS","37.5",IF(G8="GVM","41.5",IF(G8="GVL","50",IF(G8="PCS","45.8",IF(G8="PCM","50",IF(G8="PCL","58.3","0")))))) -> 0 | N8: HENDRA | R8: KUROSH | S8: 0.38541667 | T8: 0.72916667 | U8: =(T8-S8)*24 -> 8.25 | Y8: 4 | AD8: 19 | AJ8: 4 | AO8: 19
A9: 5 | B9: 4166 | C9: DGA98Z | D9: 0413996557 | E9: F | F9: 900 | G9: X | I9: 85 | J9: =IF(G9="RSL","55","0") -> 0 | K9: =IF(G9="GVS","37.5",IF(G9="GVM","41.5",IF(G9="GVL","50",IF(G9="PCS","45.8",IF(G9="PCM","50",IF(G9="PCL","58.3","0")))))) -> 0 | N9: HENDRA | R9: VINNY | S9: 0.41666667 | T9: 0.70833333 | U9: =(T9-S9)*24 -> 7 | X9: EXCL RSL | Y9: 5 | AD9: 20 | AJ9: 5 | AO9: 20
A10: 6 | B10: 4167 | C10: ERB29F | D10: 0428080256 | E10: F | F10: 910 | G10: RSL | J10: 110 | K10: =IF(G10="GVS","37.5",IF(G10="GVM","41.5",IF(G10="GVL","50",IF(G10="PCS","45.8",IF(G10="PCM","50",IF(G10="PCL","58.3","0")))))) -> 0 | N10: HENDRA | O10: 2.0220401e+17 | R10: CHARLIE | S10: 0.66666667 | T10: 0.70833333 | U10: =(T10-S10)*24 -> 1 | Y10: 6 | AD10: 21 | AJ10: 6 | AO10: 21
A11: 7 | B11: 4168 | C11: EDN88M | D11: 0411883125 | E11: M | F11: 1035 | G11: RSL | J11: =IF(G11="RSL","55","0") -> 55 | K11: =IF(G11="GVS","37.5",IF(G11="GVM","41.5",IF(G11="GVL","50",IF(G11="PCS","45.8",IF(G11="PCM","50",IF(G11="PCL","58.3","0")))))) -> 0 | N11: HENDRA | O11: 202205033 | U11: =(T11-S11)*24 -> 0 | Y11: 7 | AD11: 22 | AJ11: 7 | AO11: 22
A12: 8 | B12: 4169 | C12: ECJ92N | D12: 0401801938 | E12: M | F12: 1040 | G12: H | I12: 120 | J12: =IF(G12="RSL","55","0") -> 0 | K12: =IF(G12="GVS","37.5",IF(G12="GVM","41.5",IF(G12="GVL","50",IF(G12="PCS","45.8",IF(G12="PCM","50",IF(G12="PCL","58.3","0")))))) -> 0 | N12: HENDRA | U12: =(T12-S12)*24 -> 0 | Y12: 8 | AD12: 23 | AJ12: 8 | AO12: 23
A13: 9 | B13: 4170 | C13: DXH43L | D13: 0410600470 | E13: M | F13: 1000 | G13: D | H13: 75 | J13: =IF(G13="RSL","55","0") -> 0 | K13: =IF(G13="GVS","37.5",IF(G13="GVM","41.5",IF(G13="GVL","50",IF(G13="PCS","45.8",IF(G13="PCM","50",IF(G13="PCL","58.3","0")))))) -> 0 | N13: HENDRA | U13: =(T13-S13)*24 -> 0 | Y13: 9 | AD13: 24 | AJ13: 9 | AO13: 24
A14: 10 | B14: 4171 | C14: CWP60M | D14: 0400230754 | E14: F | F14: 1045 | G14: H | I14: 120 | J14: =IF(G14="RSL","55","0") -> 0 | K14: =IF(G14="GVS","37.5",IF(G14="GVM","41.5",IF(G14="GVL","50",IF(G14="PCS","45.8",IF(G14="PCM","50",IF(G14="PCL","58.3","0")))))) -> 0 | N14: HENDRA | U14: =(T14-S14)*24 -> 0 | Y14: 10 | AD14: 25 | AJ14: 10 | AO14: 25
A15: 11 | B15: 4172 | C15: EMN94R | D15: 0422453824 | E15: F | F15: 1130 | G15: D | I15: 65 | J15: =IF(G15="RSL","55","0") -> 0 | K15: =IF(G15="GVS","37.5",IF(G15="GVM","41.5",IF(G15="GVL","50",IF(G15="PCS","45.8",IF(G15="PCM","50",IF(G15="PCL","58.3","0")))))) -> 0 | N15: HENDRA | U15: =(T15-S15)*24 -> 0 | Y15: 11 | AD15: 26 | AJ15: 11 | AO15: 26
A16: 12 | B16: 4173 | C16: 149SCN | D16: 0404838201 | E16: F | F16: 1200 | G16: PCS | J16: =IF(G16="RSL","55","0") -> 0 | K16: 62.5 | N16: HENDRA | O16: # 22010 2/6 | R16: =H32/U16 -> 0.61176471 | S16: =H32/(U16-U5) -> 0.78787879 | T16: =C32/U16 -> 63.430588 | U16: =SUM(U5:U15) -> 42.5 | Y16: 12 | AD16: 27 | AJ16: 12 | AO16: 27
A17: 13 | B17: 4174 | C17: CS22MW | D17: 0433830239 | E17: M | F17: 1215 | G17: D | I17: 80 | J17: =IF(G17="RSL","55","0") -> 0 | K17: =IF(G17="GVS","37.5",IF(G17="GVM","41.5",IF(G17="GVL","50",IF(G17="PCS","45.8",IF(G17="PCM","50",IF(G17="PCL","58.3","0")))))) -> 0 | N17: HENDRA | R17: Cars/T Hr ① | S17: Cars/T Hr ② | T17: Sales/T Hr | U17: Total Hours | Y17: 13 | AD17: 28 | AJ17: 13 | AO17: 28
A18: 14 | B18: 4175 | C18: AF889 | D18: 0416893888 | E18: M | F18: 1220 | G18: X | I18: 75 | J18: =IF(G18="RSL","55","0") -> 0 | K18: =IF(G18="GVS","37.5",IF(G18="GVM","41.5",IF(G18="GVL","50",IF(G18="PCS","45.8",IF(G18="PCM","50",IF(G18="PCL","58.3","0")))))) -> 0 | N18: JUNIOR | R18: ITEM | S18: QTY | T18: AMT | U18: RMKS | Y18: 14 | AD18: 29 | AJ18: 14 | AO18: 29
A19: 15 | B19: 4176 | C19: SIM81L | D19: 0408963629 | E19: F | F19: 1230 | G19: X | I19: 100 | J19: =IF(G19="RSL","55","0") -> 0 | K19: =IF(G19="GVS","37.5",IF(G19="GVM","41.5",IF(G19="GVL","50",IF(G19="PCS","45.8",IF(G19="PCM","50",IF(G19="PCL","58.3","0")))))) -> 0 | N19: HENDRA | R19: GV | S19: =COUNT(L5:M29,L37:M61,L69:M93) -> 1 | T19: =SUM(L5:M29,L37:M61,L69:M93) -> 475 | Y19: 15 | AD19: 30 | AJ19: 15 | AO19: 30
A20: 16 | B20: 4177 | C20: DD2222 | D20: 0409888822 | E20: M | F20: 1230 | G20: GV3 | J20: =IF(G20="RSL","55","0") -> 0 | K20: =IF(G20="GVS","37.5",IF(G20="GVM","41.5",IF(G20="GVL","50",IF(G20="PCS","45.8",IF(G20="PCM","50",IF(G20="PCL","58.3","0")))))) -> 0 | N20: HENDRA | O20: # 202778 6/6 | AD20: 31 | AO20: 31
A21: 17 | B21: 4178 | C21: BDR25W | D21: 0421356777 | E21: F | F21: 1230 | G21: H | I21: 120 | J21: =IF(G21="RSL","55","0") -> 0 | K21: =IF(G21="GVS","37.5",IF(G21="GVM","41.5",IF(G21="GVL","50",IF(G21="PCS","45.8",IF(G21="PCM","50",IF(G21="PCL","58.3","0")))))) -> 0 | N21: HENDRA
A22: 18 | B22: 4179 | C22: AJH79D | D22: 0414560884 | E22: M | F22: 1300 | G22: ID | I22: 350 | J22: =IF(G22="RSL","55","0") -> 0 | K22: =IF(G22="GVS","37.5",IF(G22="GVM","41.5",IF(G22="GVL","50",IF(G22="PCS","45.8",IF(G22="PCM","50",IF(G22="PCL","58.3","0")))))) -> 0 | N22: HENDRA | O22: SMALL | AD22: Total | AE22: =SUM(Z5:Z19,AE5:AE20) -> 0 | AF22: =SUM(AA5:AA19,AF5:AF20,) -> 0 | AG22: =SUM(AB5:AB19,AG5:AG20) -> 0 | AO22: Total | AP22: =SUM(AK5:AK19,AP5:AP20) -> 0 | AQ22: =SUM(AL5:AL19,AQ5:AQ20,) -> 0 | AR22: =SUM(AM5:AM19,AR5:AR20) -> 0
A23: 19 | B23: 4180 | C23: BFE86C | D23: 0435065659 | E23: F | F23: 1315 | G23: RSL | J23: =IF(G23="RSL","55","0") -> 55 | K23: =IF(G23="GVS","37.5",IF(G23="GVM","41.5",IF(G23="GVL","50",IF(G23="PCS","45.8",IF(G23="PCM","50",IF(G23="PCL","58.3","0")))))) -> 0 | N23: HENDRA | P23: 202203092
A24: 20 | B24: 4181 | C24: DST81Y | D24: 0402659320 | E24: F | F24: 1345 | G24: D | H24: 55 | J24: =IF(G24="RSL","55","0") -> 0 | K24: =IF(G24="GVS","37.5",IF(G24="GVM","41.5",IF(G24="GVL","50",IF(G24="PCS","45.8",IF(G24="PCM","50",IF(G24="PCL","58.3","0")))))) -> 0 | N24: HENDRA | R24: SMALL | S24: MEDIUM | T24: LARGE | U24: TOTAL | AD24: B2/GA TOTAL | AE24: B2 machine | AF24: GA machine | AG24: BLH machine | AH24: Wongo machine | AI24: Sub total
A25: 21 | B25: 4182 | C25: DZO86P | D25: 0413513528 | E25: M | F25: 1410 | G25: D | I25: 55 | J25: =IF(G25="RSL","55","0") -> 0 | K25: =IF(G25="GVS","37.5",IF(G25="GVM","41.5",IF(G25="GVL","50",IF(G25="PCS","45.8",IF(G25="PCM","50",IF(G25="PCL","58.3","0")))))) -> 0 | N25: HENDRA | R25: =COUNTIF(G5:G29,"GV1")+COUNTIF(G37:G61,"GV1")+COUNTIF(G69:G93,"GV1") -> 0 | S25: =COUNTIF(G5:G29,"GV2")+COUNTIF(G37:G61,"GV2")+COUNTIF(G69:G93,"GV2") -> 0 | T25: =COUNTIF(G5:G29,"GV3")+COUNTIF(G37:G61,"GV3")+COUNTIF(G69:G93,"GV3") -> 1 | U25: =((C32+(R26+S26+T26)*0.5)) -> 2720.8 | AD25: =SUM(AE25:AF25) -> 0 | AE25: =SUM(AE22) -> 0 | AF25: =SUM(AP22) -> 0 | AG25: =SUM(AF22+AQ22) -> 0 | AH25: =AG22+AR22 -> 0 | AI25: =SUM(AE25:AH25) -> 0
A26: 22 | B26: 4183 | C26: DLU27G | D26: 0440886933 | E26: M | F26: 1425 | G26: H | I26: 120 | J26: =IF(G26="RSL","55","0") -> 0 | K26: =IF(G26="GVS","37.5",IF(G26="GVM","41.5",IF(G26="GVL","50",IF(G26="PCS","45.8",IF(G26="PCM","50",IF(G26="PCL","58.3","0")))))) -> 0 | N26: HENDRA | R26: =R25*37.5 -> 0 | S26: =S25*41.5 -> 0 | T26: =T25*50 -> 50 | X26: Branch cards
A27: 23 | B27: 4184 | C27: CT51LJ | D27: 0410431911 | E27: F | F27: 1450 | G27: D/ST | I27: 200 | J27: =IF(G27="RSL","55","0") -> 0 | K27: =IF(G27="GVS","37.5",IF(G27="GVM","41.5",IF(G27="GVL","50",IF(G27="PCS","45.8",IF(G27="PCM","50",IF(G27="PCL","58.3","0")))))) -> 0 | N27: JUNIOR | R27: Expense | X27: 1 | Z27: -2745
A28: 24 | B28: 4185 | C28: CNG97K | D28: 0404827947 | E28: M | F28: 1520 | G28: RSL | J28: 165 | K28: =IF(G28="GVS","37.5",IF(G28="GVM","41.5",IF(G28="GVL","50",IF(G28="PCS","45.8",IF(G28="PCM","50",IF(G28="PCL","58.3","0")))))) -> 0 | N28: HENDRA | O28: 2.0211207e+18 | R28: NO 24 : 202204063 | X28: 2
A29: 25 | B29: 4186 | C29: EKO68R | D29: 0430312281 | E29: F | F29: 1530 | G29: H | H29: 150 | J29: =IF(G29="RSL","55","0") -> 0 | K29: =IF(G29="GVS","37.5",IF(G29="GVM","41.5",IF(G29="GVL","50",IF(G29="PCS","45.8",IF(G29="PCM","50",IF(G29="PCL","58.3","0")))))) -> 0 | L29: 475 | N29: HENDRA | O29: PCL 22027 | X29: 3
A30: Page total | H30: =SUM(H5:H29) -> 400 | I30: =SUM(I5:I29) -> 1715 | J30: =J5+J6+J7+J8+J9+J10+J11+J12+J13+J14+J15+J16+J18+J19+J17+J20+J22+J23+J21+J24+J25+J26+J27+J28+J29 -> 385 | K30: =K5+K6+K7+K8+K9+K10+K11+K12+K13+K14+K15+K16+K18+K19+K17+K20+K22+K23+K21+K24+K25+K26+K27+K28+K29 -> 120.8 | L30: =SUM(L5:L29) -> 475 | M30: =SUM(M5:M29) -> 0 | N30: CASH | O30: CARD | P30: GV | Q30: RSL | X30: 4
A31: Daily Total | H31: =H30+H62+H94 -> 400 | I31: =I30+I62+I94 -> 1790 | J31: =J30+J62+J94 -> 385 | K31: =K30+K62+K94 -> 120.8 | L31: =L30+L62+L94 -> 475 | M31: =M30+M62+M94 -> 0 | N31: =COUNT(H5:H29,H37:H61,H69:H93) -> 4 | O31: =COUNT(I5:I29,I37:I61,I69:I93) -> 15 | P31: =COUNTIF(G5:G29,"G*")+COUNTIF(G37:G61,"G*")+COUNTIF(G69:G93,"G*")+COUNTIF(G5:G29,"P*")+COUNTIF(G37:G61,"P*")+COUNTIF(G69:G93,"P*") -> 3 | Q31: =COUNTIF(G5:G29,"RSL")+COUNTIF(G37:G61,"RSL")+COUNTIF(G69:G93,"RSL") -> 4 | R31: CASH CLOSING | S31: =H31+L31-U28-U29-U30 -> 875 | T31: =H31+I31+L31+M31 -> 2665 | X31: Subtotal | Z31: =SUM(Z27:Z30) -> -2745
A32: TOTAL SALES | C32: =H31+I31+J31+K31 -> 2695.8 | F32: No of Cars | H32: =COUNT(B5:B29,B37:B61,B69:B93) -> 26 | I32: Average | K32: =C32/H32 -> 103.68462 | N32: =H31/C32 -> 0.14837896 | O32: =I31/C32 -> 0.66399585 | P32: =K31/C32 -> 0.044810446 | Q32: =J31/C32 -> 0.14281475 | R32: CARD CLOSING | S32: =I31+M31 -> 1790 | X32: B2 card | Z32: =I31 -> 1790
A33: Daily Report | X33: Settlement | Z33: =SUM(Z31:Z32) -> -955
A34: =A2 -> 16 - 5 - 2022 | H34: WEATHER | J34: =J2 -> SUNNY | L34: REPORT by | O34: =O2 -> HENDRA | R34: TOTAL STAFF | T34: =T2 -> 5
A36: No | B36: Docket No | C36: Reg No | D36: Mobile | E36: Gender | F36: TIME | G36: Service | H36: CASH | I36: CARD | J36: RSL | K36: GV | L36: GV CASH | M36: GV CARD | N36: O/Taker | O36: Comment | R36: NAME | S36: Time In | T36: Time out | U36: Total Hours
A37: =A29+1 -> 26 | B37: 4187 | C37: MS0007 | D37: 0422982196 | E37: F | F37: 1545 | G37: D | I37: 75 | J37: =IF(G37="RSL","55","0") -> 0 | K37: =IF(G37="GVS","37.5",IF(G37="GVM","41.5",IF(G37="GVL","50",IF(G37="PCS","45.8",IF(G37="PCM","50",IF(G37="PCL","58.3","0")))))) -> 0 | N37: HENDRA
A38: =A37+1 -> 27 | J38: =IF(G38="RSL","55","0") -> 0 | K38: =IF(G38="GVS","37.5",IF(G38="GVM","41.5",IF(G38="GVL","50",IF(G38="PCS","45.8",IF(G38="PCM","50",IF(G38="PCL","58.3","0")))))) -> 0
A39: =A38+1 -> 28 | J39: =IF(G39="RSL","55","0") -> 0 | K39: =IF(G39="GVS","37.5",IF(G39="GVM","41.5",IF(G39="GVL","50",IF(G39="PCS","45.8",IF(G39="PCM","50",IF(G39="PCL","58.3","0")))))) -> 0
A40: =A39+1 -> 29 | J40: =IF(G40="RSL","55","0") -> 0 | K40: =IF(G40="GVS","37.5",IF(G40="GVM","41.5",IF(G40="GVL","50",IF(G40="PCS","45.8",IF(G40="PCM","50",IF(G40="PCL","58.3","0")))))) -> 0
A41: =A40+1 -> 30 | J41: =IF(G41="RSL","55","0") -> 0 | K41: =IF(G41="GVS","37.5",IF(G41="GVM","41.5",IF(G41="GVL","50",IF(G41="PCS","45.8",IF(G41="PCM","50",IF(G41="PCL","58.3","0")))))) -> 0
A42: =A41+1 -> 31 | J42: =IF(G42="RSL","55","0") -> 0 | K42: =IF(G42="GVS","37.5",IF(G42="GVM","41.5",IF(G42="GVL","50",IF(G42="PCS","45.8",IF(G42="PCM","50",IF(G42="PCL","58.3","0")))))) -> 0
A43: =A42+1 -> 32 | J43: =IF(G43="RSL","55","0") -> 0 | K43: =IF(G43="GVS","37.5",IF(G43="GVM","41.5",IF(G43="GVL","50",IF(G43="PCS","45.8",IF(G43="PCM","50",IF(G43="PCL","58.3","0")))))) -> 0
A44: =A43+1 -> 33 | J44: =IF(G44="RSL","55","0") -> 0 | K44: =IF(G44="GVS","37.5",IF(G44="GVM","41.5",IF(G44="GVL","50",IF(G44="PCS","45.8",IF(G44="PCM","50",IF(G44="PCL","58.3","0")))))) -> 0
A45: =A44+1 -> 34 | J45: =IF(G45="RSL","55","0") -> 0 | K45: =IF(G45="GVS","37.5",IF(G45="GVM","41.5",IF(G45="GVL","50",IF(G45="PCS","45.8",IF(G45="PCM","50",IF(G45="PCL","58.3","0")))))) -> 0
A46: =A45+1 -> 35 | J46: =IF(G46="RSL","55","0") -> 0 | K46: =IF(G46="GVS","37.5",IF(G46="GVM","41.5",IF(G46="GVL","50",IF(G46="PCS","45.8",IF(G46="PCM","50",IF(G46="PCL","58.3","0")))))) -> 0
A47: =A46+1 -> 36 | J47: =IF(G47="RSL","55","0") -> 0 | K47: =IF(G47="GVS","37.5",IF(G47="GVM","41.5",IF(G47="GVL","50",IF(G47="PCS","45.8",IF(G47="PCM","50",IF(G47="PCL","58.3","0")))))) -> 0
A48: =A47+1 -> 37 | J48: =IF(G48="RSL","55","0") -> 0 | K48: =IF(G48="GVS","37.5",IF(G48="GVM","41.5",IF(G48="GVL","50",IF(G48="PCS","45.8",IF(G48="PCM","50",IF(G48="PCL","58.3","0")))))) -> 0
A49: =A48+1 -> 38 | J49: =IF(G49="RSL","55","0") -> 0 | K49: =IF(G49="GVS","37.5",IF(G49="GVM","41.5",IF(G49="GVL","50",IF(G49="PCS","45.8",IF(G49="PCM","50",IF(G49="PCL","58.3","0")))))) -> 0
... A61: =A60+1 -> 50 | J61: =IF(G61="RSL","55","0") -> 0 | K61: =IF(G61="GVS","37.5",IF(G61="GVM","41.5",IF(G61="GVL","50",IF(G61="PCS","45.8",IF(G61="PCM","50",IF(G61="PCL","58.3","0")))))) -> 0
A62: Page total | H62: =SUM(H37:H61) -> 0 | I62: =SUM(I37:I61) -> 75 | J62: =J61+J60+J59+J58+J57+J56+J55+J54+J53+J52+J51+J50+J49+J48+J47+J46+J45+J44+J43+J42+J41+J40+J39+J38+J37 -> 0 | K62: =K61+K60+K59+K58+K57+K56+K55+K54+K53+K52+K51+K50+K49+K48+K47+K46+K45+K44+K43+K42+K41+K40+K39+K38+K37 -> 0 | L62: =SUM(L37:L61) -> 0 | M62: =SUM(M37:M61) -> 0
R64: Page: 2
A65: Daily Report
A66: =A34 -> 16 - 5 - 2022 | H66: WEATHER | J66: =J34 -> SUNNY | L66: REPORT by | O66: =O34 -> HENDRA | R66: TOTAL STAFF | T66: =T34 -> 5
A68: No | B68: Docket No | C68: Reg No | D68: Mobile | E68: Gender | F68: TIME | G68: Service | H68: CASH | I68: CARD | J68: RSL | K68: GV | L68: GV CASH | M68: GV CARD | N68: O/Taker | O68: Comment | R68: NAME | S68: Time In | T68: Time out | U68: Total Hours
A69: =A61+1 -> 51 | J69: =IF(G69="RSL","55","0") -> 0 | K69: =IF(G69="GVS","37.5",IF(G69="GVM","41.5",IF(G69="GVL","50",IF(G69="PCS","45.8",IF(G69="PCM","50",IF(G69="PCL","58.3","0")))))) -> 0
A70: =A69+1 -> 52 | J70: =IF(G70="RSL","55","0") -> 0 | K70: =IF(G70="GVS","37.5",IF(G70="GVM","41.5",IF(G70="GVL","50",IF(G70="PCS","45.8",IF(G70="PCM","50",IF(G70="PCL","58.3","0")))))) -> 0
A71: =A70+1 -> 53 | J71: =IF(G71="RSL","55","0") -> 0 | K71: =IF(G71="GVS","37.5",IF(G71="GVM","41.5",IF(G71="GVL","50",IF(G71="PCS","45.8",IF(G71="PCM","50",IF(G71="PCL","58.3","0")))))) -> 0
A72: =A71+1 -> 54 | J72: =IF(G72="RSL","55","0") -> 0 | K72: =IF(G72="GVS","37.5",IF(G72="GVM","41.5",IF(G72="GVL","50",IF(G72="PCS","45.8",IF(G72="PCM","50",IF(G72="PCL","58.3","0")))))) -> 0
A73: =A72+1 -> 55 | J73: =IF(G73="RSL","55","0") -> 0 | K73: =IF(G73="GVS","37.5",IF(G73="GVM","41.5",IF(G73="GVL","50",IF(G73="PCS","45.8",IF(G73="PCM","50",IF(G73="PCL","58.3","0")))))) -> 0
A74: =A73+1 -> 56 | J74: =IF(G74="RSL","55","0") -> 0 | K74: =IF(G74="GVS","37.5",IF(G74="GVM","41.5",IF(G74="GVL","50",IF(G74="PCS","45.8",IF(G74="PCM","50",IF(G74="PCL","58.3","0")))))) -> 0
A75: =A74+1 -> 57 | J75: =IF(G75="RSL","55","0") -> 0 | K75: =IF(G75="GVS","37.5",IF(G75="GVM","41.5",IF(G75="GVL","50",IF(G75="PCS","45.8",IF(G75="PCM","50",IF(G75="PCL","58.3","0")))))) -> 0
A76: =A75+1 -> 58 | J76: =IF(G76="RSL","55","0") -> 0 | K76: =IF(G76="GVS","37.5",IF(G76="GVM","41.5",IF(G76="GVL","50",IF(G76="PCS","45.8",IF(G76="PCM","50",IF(G76="PCL","58.3","0")))))) -> 0
A77: =A76+1 -> 59 | J77: =IF(G77="RSL","55","0") -> 0 | K77: =IF(G77="GVS","37.5",IF(G77="GVM","41.5",IF(G77="GVL","50",IF(G77="PCS","45.8",IF(G77="PCM","50",IF(G77="PCL","58.3","0")))))) -> 0
A78: =A77+1 -> 60 | J78: =IF(G78="RSL","55","0") -> 0 | K78: =IF(G78="GVS","37.5",IF(G78="GVM","41.5",IF(G78="GVL","50",IF(G78="PCS","45.8",IF(G78="PCM","50",IF(G78="PCL","58.3","0")))))) -> 0
A79: =A78+1 -> 61 | J79: =IF(G79="RSL","55","0") -> 0 | K79: =IF(G79="GVS","37.5",IF(G79="GVM","41.5",IF(G79="GVL","50",IF(G79="PCS","45.8",IF(G79="PCM","50",IF(G79="PCL","58.3","0")))))) -> 0
A80: =A79+1 -> 62 | J80: =IF(G80="RSL","55","0") -> 0 | K80: =IF(G80="GVS","37.5",IF(G80="GVM","41.5",IF(G80="GVL","50",IF(G80="PCS","45.8",IF(G80="PCM","50",IF(G80="PCL","58.3","0")))))) -> 0
A81: =A80+1 -> 63 | J81: =IF(G81="RSL","55","0") -> 0 | K81: =IF(G81="GVS","37.5",IF(G81="GVM","41.5",IF(G81="GVL","50",IF(G81="PCS","45.8",IF(G81="PCM","50",IF(G81="PCL","58.3","0")))))) -> 0
... A93: =A92+1 -> 75 | J93: =IF(G93="RSL","55","0") -> 0 | K93: =IF(G93="GVS","37.5",IF(G93="GVM","41.5",IF(G93="GVL","50",IF(G93="PCS","45.8",IF(G93="PCM","50",IF(G93="PCL","58.3","0")))))) -> 0
A94: Page total | H94: =SUM(H69:H93) -> 0 | I94: =SUM(I69:I93) -> 0 | J94: =J93+J92+J91+J90+J89+J88+J87+J86+J85+J84+J83+J82+J81+J80+J79+J78+J77+J76+J75+J74+J73+J72+J71+J70+J69 -> 0 | K94: =K93+K92+K91+K90+K89+K88+K87+K86+K85+K84+K83+K82+K81+K80+K79+K78+K77+K76+K75+K74+K73+K72+K71+K70+K69 -> 0 | L94: =SUM(L69:L93) -> 0 | M94: =SUM(M69:M93) -> 0
R96: Page: 3

Sheet TUE
A1: B2 Daily Report
A2: 17 - 5 - 2022 | H2: WEATHER | J2: SUNNY | L2: REPORT BY | O2: HENDRA | R2: TOTAL STAFF | T2: 5 | X2: Merchant machine usage at B2 | AA2: Settle amount | AI2: Merchant machine usage at GA | AL2: Settle amount
A4: No | B4: Docket No | C4: Reg No | D4: Mobile | E4: Gender | F4: TIME | G4: Service | H4: CASH | I4: CARD | J4: RSL | K4: GV | L4: GV CASH | M4: GV CARD | N4: O/Taker | O4: Comment | R4: NAME | S4: Time In | T4: Time out | U4: Total Hours | Z4: B2 machine | AA4: BLH machine | AB4: Wongo | AE4: B2 machine | AF4: BLH machine | AG4: Wongo | AK4: GA machine | AL4: BLH machine | AM4: Wongo | AP4: GA machine | AQ4: BLH machine | AR4: Wongo
A5: 1 | B5: 4188 | C5: NBN68W | D5: 0432731177 | E5: M | F5: 755 | G5: RSL | J5: 110 | K5: =IF(G5="GVS","37.5",IF(G5="GVM","41.5",IF(G5="GVL","50",IF(G5="PCS","45.8",IF(G5="PCM","50",IF(G5="PCL","58.3","0")))))) -> 0 | N5: JUNIOR | O5: 2.0220302e+17 | R5: HENDRA | S5: 0.33333333 | T5: 0.70833333 | U5: =(T5-S5)*24 -> 9 | X5: NOV | Y5: 1 | AD5: 16 | AI5: NOV | AJ5: 1 | AO5: 16
A6: 2 | B6: 4189 | C6: DKR06B | D6: 0432303166 | E6: F | F6: 935 | G6: D | I6: 75 | J6: =IF(G6="RSL","55","0") -> 0 | K6: =IF(G6="GVS","37.5",IF(G6="GVM","41.5",IF(G6="GVL","50",IF(G6="PCS","45.8",IF(G6="PCM","50",IF(G6="PCL","58.3","0")))))) -> 0 | N6: HENDRA | R6: JUNIOR | S6: 0.33333333 | T6: 0.70833333 | U6: =(T6-S6)*24 -> 9 | W6: M | Y6: 2 | AD6: 17 | AJ6: 2 | AO6: 17
A7: 3 | B7: 4190 | C7: EBY17A | D7: 0425517888 | E7: M | F7: 935 | G7: GV2 | J7: =IF(G7="RSL","55","0") -> 0 | K7: =IF(G7="GVS","37.5",IF(G7="GVM","41.5",IF(G7="GVL","50",IF(G7="PCS","45.8",IF(G7="PCM","50",IF(G7="PCL","58.3","0")))))) -> 0 | N7: HENDRA | O7: # 202744 6/6 | R7: ARIANTO | S7: 0.375 | T7: 0.66666667 | U7: =(T7-S7)*24 -> 7 | W7: F | Y7: 3 | AD7: 18 | AJ7: 3 | AO7: 18
A8: 4 | B8: 4191 | C8: ERY51B | D8: 0407770517 | E8: F | F8: 945 | G8: H | I8: 130 | J8: =IF(G8="RSL","55","0") -> 0 | K8: =IF(G8="GVS","37.5",IF(G8="GVM","41.5",IF(G8="GVL","50",IF(G8="PCS","45.8",IF(G8="PCM","50",IF(G8="PCL","58.3","0")))))) -> 0 | N8: HENDRA | R8: KUROSH | S8: 0.36458333 | T8: 0.70833333 | U8: =(T8-S8)*24 -> 8.25 | Y8: 4 | AD8: 19 | AJ8: 4 | AO8: 19
A9: 5 | B9: 4192 | C9: ERE85D | D9: 0452286033 | E9: F | F9: 1045 | G9: X | J9: =IF(G9="RSL","55","0") -> 0 | K9: =IF(G9="GVS","37.5",IF(G9="GVM","41.5",IF(G9="GVL","50",IF(G9="PCS","45.8",IF(G9="PCM","50",IF(G9="PCL","58.3","0")))))) -> 0 | M9: 475 | N9: HENDRA | O9: PCL 22028 1/6 | R9: VINNY | S9: 0.45833333 | T9: 0.70833333 | U9: =(T9-S9)*24 -> 6 | X9: EXCL RSL | Y9: 5 | AD9: 20 | AJ9: 5 | AO9: 20
A10: 6 | B10: 4193 | C10: HOOPER | D10: 0418628429 | E10: M | F10: 1045 | G10: D | I10: 55 | J10: =IF(G10="RSL","55","0") -> 0 | K10: =IF(G10="GVS","37.5",IF(G10="GVM","41.5",IF(G10="GVL","50",IF(G10="PCS","45.8",IF(G10="PCM","50",IF(G10="PCL","58.3","0")))))) -> 0 | N10: HENDRA | U10: =(T10-S10)*24 -> 0 | Y10: 6 | AD10: 21 | AJ10: 6 | AO10: 21
A11: 7 | B11: 4194 | C11: DZY96P | D11: 0416162212 | E11: M | F11: 1100 | G11: H | I11: 160 | J11: =IF(G11="RSL","55","0") -> 0 | K11: =IF(G11="GVS","37.5",IF(G11="GVM","41.5",IF(G11="GVL","50",IF(G11="PCS","45.8",IF(G11="PCM","50",IF(G11="PCL","58.3","0")))))) -> 0 | N11: HENDRA | O11: TAX | U11: =(T11-S11)*24 -> 0 | Y11: 7 | AD11: 22 | AJ11: 7 | AO11: 22
A12: 8 | B12: 4195 | C12: CSR89J | D12: 0404868426 | E12: F | F12: 1130 | G12: W/O | I12: 65 | J12: =IF(G12="RSL","55","0") -> 0 | K12: =IF(G12="GVS","37.5",IF(G12="GVM","41.5",IF(G12="GVL","50",IF(G12="PCS","45.8",IF(G12="PCM","50",IF(G12="PCL","58.3","0")))))) -> 0 | N12: HENDRA | U12: =(T12-S12)*24 -> 0 | Y12: 8 | AD12: 23 | AJ12: 8 | AO12: 23
A13: 9 | B13: 4196 | C13: BER28W | D13: 0400194999 | E13: F | F13: 1145 | G13: RSL | H13: 20 | J13: =IF(G13="RSL","55","0") -> 55 | K13: =IF(G13="GVS","37.5",IF(G13="GVM","41.5",IF(G13="GVL","50",IF(G13="PCS","45.8",IF(G13="PCM","50",IF(G13="PCL","58.3","0")))))) -> 0 | N13: HENDRA | O13: 202203015 | U13: =(T13-S13)*24 -> 0 | Y13: 9 | AD13: 24 | AJ13: 9 | AO13: 24
A14: 10 | B14: 4197 | C14: DGF26E | D14: 0415991574 | E14: M | F14: 1145 | G14: H | I14: 150 | J14: =IF(G14="RSL","55","0") -> 0 | K14: =IF(G14="GVS","37.5",IF(G14="GVM","41.5",IF(G14="GVL","50",IF(G14="PCS","45.8",IF(G14="PCM","50",IF(G14="PCL","58.3","0")))))) -> 0 | N14: HENDRA | U14: =(T14-S14)*24 -> 0 | Y14: 10 | AD14: 25 | AJ14: 10 | AO14: 25
A15: 11 | B15: 4198 | C15: DVL10H | D15: 0413872431 | E15: F | F15: 1200 | G15: PCL | J15: =IF(G15="RSL","55","0") -> 0 | K15: 79.16 | N15: HENDRA | O15: 211206.4. 4/6 | U15: =(T15-S15)*24 -> 0 | Y15: 11 | AD15: 26 | AJ15: 11 | AO15: 26
A16: 12 | B16: 4199 | C16: EJA52G | D16: 0408228847 | E16: F | F16: 1205 | G16: D | I16: 75 | J16: =IF(G16="RSL","55","0") -> 0 | K16: =IF(G16="GVS","37.5",IF(G16="GVM","41.5",IF(G16="GVL","50",IF(G16="PCS","45.8",IF(G16="PCM","50",IF(G16="PCL","58.3","0")))))) -> 0 | N16: HENDRA | R16: =H32/U16 -> 0.50955414 | S16: =H32/(U16-U5) -> 0.66115702 | T16: =C32/U16 -> 43.163312 | U16: =SUM(U5:U15) -> 39.25 | Y16: 12 | AD16: 27 | AJ16: 12 | AO16: 27
A17: 13 | B17: 4200 | C17: CKDI8 | D17: 0431155888 | E17: F | F17: 1215 | G17: X | I17: 95 | J17: =IF(G17="RSL","55","0") -> 0 | K17: =IF(G17="GVS","37.5",IF(G17="GVM","41.5",IF(G17="GVL","50",IF(G17="PCS","45.8",IF(G17="PCM","50",IF(G17="PCL","58.3","0")))))) -> 0 | N17: HENDRA | R17: Cars/T Hr ① | S17: Cars/T Hr ② | T17: Sales/T Hr | U17: Total Hours | Y17: 13 | AD17: 28 | AJ17: 13 | AO17: 28
A18: 14 | B18: 4201 | C18: ERB65Q | D18: 0457336603 | E18: F | F18: 1230 | G18: H | I18: 150 | J18: =IF(G18="RSL","55","0") -> 0 | K18: =IF(G18="GVS","37.5",IF(G18="GVM","41.5",IF(G18="GVL","50",IF(G18="PCS","45.8",IF(G18="PCM","50",IF(G18="PCL","58.3","0")))))) -> 0 | N18: HENDRA | R18: ITEM | S18: QTY | T18: AMT | U18: RMKS | Y18: 14 | AD18: 29 | AJ18: 14 | AO18: 29
A19: 15 | B19: 4202 | C19: CXY11Y | D19: 0412411002 | E19: F | F19: 1245 | G19: D | I19: 55 | J19: =IF(G19="RSL","55","0") -> 0 | K19: =IF(G19="GVS","37.5",IF(G19="GVM","41.5",IF(G19="GVL","50",IF(G19="PCS","45.8",IF(G19="PCM","50",IF(G19="PCL","58.3","0")))))) -> 0 | N19: HENDRA | R19: GV | S19: =COUNT(L5:M29,L37:M61,L69:M93) -> 1 | T19: =SUM(L5:M29,L37:M61,L69:M93) -> 475 | Y19: 15 | AD19: 30 | AJ19: 15 | AO19: 30
A20: 16 | B20: 4203 | C20: CMF49L | D20: 0422400397 | E20: F | F20: 1310 | G20: D | I20: 65 | J20: =IF(G20="RSL","55","0") -> 0 | K20: =IF(G20="GVS","37.5",IF(G20="GVM","41.5",IF(G20="GVL","50",IF(G20="PCS","45.8",IF(G20="PCM","50",IF(G20="PCL","58.3","0")))))) -> 0 | N20: HENDRA | AD20: 31 | AO20: 31
A21: 17 | B21: 4204 | C21: DP469 | D21: 0419517672 | E21: M | F21: 1315 | G21: D | H21: 55 | J21: =IF(G21="RSL","55","0") -> 0 | K21: =IF(G21="GVS","37.5",IF(G21="GVM","41.5",IF(G21="GVL","50",IF(G21="PCS","45.8",IF(G21="PCM","50",IF(G21="PCL","58.3","0")))))) -> 0 | N21: HENDRA
A22: 18 | B22: 4205 | C22: DW088J | D22: 0487390063 | E22: M | F22: 1340 | G22: H | I22: 120 | J22: =IF(G22="RSL","55","0") -> 0 | K22: =IF(G22="GVS","37.5",IF(G22="GVM","41.5",IF(G22="GVL","50",IF(G22="PCS","45.8",IF(G22="PCM","50",IF(G22="PCL","58.3","0")))))) -> 0 | N22: HENDRA | AD22: Total | AE22: =SUM(Z5:Z19,AE5:AE20) -> 0 | AF22: =SUM(AA5:AA19,AF5:AF20,) -> 0 | AG22: =SUM(AB5:AB19,AG5:AG20) -> 0 | AO22: Total | AP22: =SUM(AK5:AK19,AP5:AP20) -> 0 | AQ22: =SUM(AL5:AL19,AQ5:AQ20,) -> 0 | AR22: =SUM(AM5:AM19,AR5:AR20) -> 0
A23: 19 | B23: 4206 | C23: EAH89D | D23: ???? | E23: F | F23: 1345 | G23: D | H23: 55 | J23: =IF(G23="RSL","55","0") -> 0 | K23: =IF(G23="GVS","37.5",IF(G23="GVM","41.5",IF(G23="GVL","50",IF(G23="PCS","45.8",IF(G23="PCM","50",IF(G23="PCL","58.3","0")))))) -> 0 | N23: HENDRA
A24: 20 | B24: 4207 | C24: DNK08Z | D24: 0426828096 | E24: F | F24: 1500 | G24: PCS | J24: =IF(G24="RSL","55","0") -> 0 | K24: 125 | N24: HENDRA | O24: #21036 5/6 6/6 | R24: SMALL | S24: MEDIUM | T24: LARGE | U24: TOTAL | AD24: B2/GA TOTAL | AE24: B2 machine | AF24: GA machine | AG24: BLH machine | AH24: Wongo machine | AI24: Sub total
A25: 21 | J25: =IF(G25="RSL","55","0") -> 0 | K25: =IF(G25="GVS","37.5",IF(G25="GVM","41.5",IF(G25="GVL","50",IF(G25="PCS","45.8",IF(G25="PCM","50",IF(G25="PCL","58.3","0")))))) -> 0 | R25: =COUNTIF(G5:G29,"GV1")+COUNTIF(G37:G61,"GV1")+COUNTIF(G69:G93,"GV1") -> 0 | S25: =COUNTIF(G5:G29,"GV2")+COUNTIF(G37:G61,"GV2")+COUNTIF(G69:G93,"GV2") -> 1 | T25: =COUNTIF(G5:G29,"GV3")+COUNTIF(G37:G61,"GV3")+COUNTIF(G69:G93,"GV3") -> 0 | U25: =((C32+(R26+S26+T26)*0.5)) -> 1714.91 | AD25: =SUM(AE25:AF25) -> 0 | AE25: =SUM(AE22) -> 0 | AF25: =SUM(AP22) -> 0 | AG25: =SUM(AF22+AQ22) -> 0 | AH25: =AG22+AR22 -> 0 | AI25: =SUM(AE25:AH25) -> 0
A26: 22 | J26: =IF(G26="RSL","55","0") -> 0 | K26: =IF(G26="GVS","37.5",IF(G26="GVM","41.5",IF(G26="GVL","50",IF(G26="PCS","45.8",IF(G26="PCM","50",IF(G26="PCL","58.3","0")))))) -> 0 | R26: =R25*37.5 -> 0 | S26: =S25*41.5 -> 41.5 | T26: =T25*50 -> 0 | X26: Branch cards
A27: 23 | J27: =IF(G27="RSL","55","0") -> 0 | K27: =IF(G27="GVS","37.5",IF(G27="GVM","41.5",IF(G27="GVL","50",IF(G27="PCS","45.8",IF(G27="PCM","50",IF(G27="PCL","58.3","0")))))) -> 0 | R27: Expense | X27: 1 | Z27: -2745
A28: 24 | J28: =IF(G28="RSL","55","0") -> 0 | K28: =IF(G28="GVS","37.5",IF(G28="GVM","41.5",IF(G28="GVL","50",IF(G28="PCS","45.8",IF(G28="PCM","50",IF(G28="PCL","58.3","0")))))) -> 0 | X28: 2
A29: 25 | J29: =IF(G29="RSL","55","0") -> 0 | K29: =IF(G29="GVS","37.5",IF(G29="GVM","41.5",IF(G29="GVL","50",IF(G29="PCS","45.8",IF(G29="PCM","50",IF(G29="PCL","58.3","0")))))) -> 0 | X29: 3
A30: Page total | H30: =SUM(H5:H29) -> 130 | I30: =SUM(I5:I29) -> 1195 | J30: =J5+J6+J7+J8+J9+J10+J11+J12+J13+J14+J15+J16+J18+J19+J17+J20+J22+J23+J21+J24+J25+J26+J27+J28+J29 -> 165 | K30: =K5+K6+K7+K8+K9+K10+K11+K12+K13+K14+K15+K16+K18+K19+K17+K20+K22+K23+K21+K24+K25+K26+K27+K28+K29 -> 204.16 | L30: =SUM(L5:L29) -> 0 | M30: =SUM(M5:M29) -> 475 | N30: CASH | O30: CARD | P30: GV | Q30: RSL | X30: 4
A31: Daily Total | H31: =H30+H62+H94 -> 130 | I31: =I30+I62+I94 -> 1195 | J31: =J30+J62+J94 -> 165 | K31: =K30+K62+K94 -> 204.16 | L31: =L30+L62+L94 -> 0 | M31: =M30+M62+M94 -> 475 | N31: =COUNT(H5:H29,H37:H61,H69:H93) -> 3 | O31: =COUNT(I5:I29,I37:I61,I69:I93) -> 12 | P31: =COUNTIF(G5:G29,"G*")+COUNTIF(G37:G61,"G*")+COUNTIF(G69:G93,"G*")+COUNTIF(G5:G29,"P*")+COUNTIF(G37:G61,"P*")+COUNTIF(G69:G93,"P*") -> 3 | Q31: =COUNTIF(G5:G29,"RSL")+COUNTIF(G37:G61,"RSL")+COUNTIF(G69:G93,"RSL") -> 2 | R31: CASH CLOSING | S31: =H31+L31-U28-U29-U30 -> 130 | T31: =H31+I31+L31+M31 -> 1800 | X31: Subtotal | Z31: =SUM(Z27:Z30) -> -2745
A32: TOTAL SALES | C32: =H31+I31+J31+K31 -> 1694.16 | F32: No of Cars | H32: =COUNT(B5:B29,B37:B61,B69:B93) -> 20 | I32: Average | K32: =C32/H32 -> 84.708 | N32: =H31/C32 -> 0.076734193 | O32: =I31/C32 -> 0.70536431 | P32: =K31/C32 -> 0.1205081 | Q32: =J31/C32 -> 0.097393398 | R32: CARD CLOSING | S32: =I31+M31 -> 1670 | X32: B2 card | Z32: =I31 -> 1195
A33: Daily Report | X33: Settlement | Z33: =SUM(Z31:Z32) -> -1550
A34: =A2 -> 17 - 5 - 2022 | H34: WEATHER | J34: =J2 -> SUNNY | L34: REPORT by | O34: =O2 -> HENDRA | R34: TOTAL STAFF | T34: =T2 -> 5
A36: No | B36: Docket No | C36: Reg No | D36: Mobile | E36: Gender | F36: TIME | G36: Service | H36: CASH | I36: CARD | J36: RSL | K36: GV | L36: GV CASH | M36: GV CARD | N36: O/Taker | O36: Comment | R36: NAME | S36: Time In | T36: Time out | U36: Total Hours
A37: =A29+1 -> 26 | J37: =IF(G37="RSL","55","0") -> 0 | K37: =IF(G37="GVS","37.5",IF(G37="GVM","41.5",IF(G37="GVL","50",IF(G37="PCS","45.8",IF(G37="PCM","50",IF(G37="PCL","58.3","0")))))) -> 0
A38: =A37+1 -> 27 | J38: =IF(G38="RSL","55","0") -> 0 | K38: =IF(G38="GVS","37.5",IF(G38="GVM","41.5",IF(G38="GVL","50",IF(G38="PCS","45.8",IF(G38="PCM","50",IF(G38="PCL","58.3","0")))))) -> 0
A39: =A38+1 -> 28 | J39: =IF(G39="RSL","55","0") -> 0 | K39: =IF(G39="GVS","37.5",IF(G39="GVM","41.5",IF(G39="GVL","50",IF(G39="PCS","45.8",IF(G39="PCM","50",IF(G39="PCL","58.3","0")))))) -> 0
A40: =A39+1 -> 29 | J40: =IF(G40="RSL","55","0") -> 0 | K40: =IF(G40="GVS","37.5",IF(G40="GVM","41.5",IF(G40="GVL","50",IF(G40="PCS","45.8",IF(G40="PCM","50",IF(G40="PCL","58.3","0")))))) -> 0
A41: =A40+1 -> 30 | J41: =IF(G41="RSL","55","0") -> 0 | K41: =IF(G41="GVS","37.5",IF(G41="GVM","41.5",IF(G41="GVL","50",IF(G41="PCS","45.8",IF(G41="PCM","50",IF(G41="PCL","58.3","0")))))) -> 0
A42: =A41+1 -> 31 | J42: =IF(G42="RSL","55","0") -> 0 | K42: =IF(G42="GVS","37.5",IF(G42="GVM","41.5",IF(G42="GVL","50",IF(G42="PCS","45.8",IF(G42="PCM","50",IF(G42="PCL","58.3","0")))))) -> 0
A43: =A42+1 -> 32 | J43: =IF(G43="RSL","55","0") -> 0 | K43: =IF(G43="GVS","37.5",IF(G43="GVM","41.5",IF(G43="GVL","50",IF(G43="PCS","45.8",IF(G43="PCM","50",IF(G43="PCL","58.3","0")))))) -> 0
A44: =A43+1 -> 33 | J44: =IF(G44="RSL","55","0") -> 0 | K44: =IF(G44="GVS","37.5",IF(G44="GVM","41.5",IF(G44="GVL","50",IF(G44="PCS","45.8",IF(G44="PCM","50",IF(G44="PCL","58.3","0")))))) -> 0
A45: =A44+1 -> 34 | J45: =IF(G45="RSL","55","0") -> 0 | K45: =IF(G45="GVS","37.5",IF(G45="GVM","41.5",IF(G45="GVL","50",IF(G45="PCS","45.8",IF(G45="PCM","50",IF(G45="PCL","58.3","0")))))) -> 0
A46: =A45+1 -> 35 | J46: =IF(G46="RSL","55","0") -> 0 | K46: =IF(G46="GVS","37.5",IF(G46="GVM","41.5",IF(G46="GVL","50",IF(G46="PCS","45.8",IF(G46="PCM","50",IF(G46="PCL","58.3","0")))))) -> 0
A47: =A46+1 -> 36 | J47: =IF(G47="RSL","55","0") -> 0 | K47: =IF(G47="GVS","37.5",IF(G47="GVM","41.5",IF(G47="GVL","50",IF(G47="PCS","45.8",IF(G47="PCM","50",IF(G47="PCL","58.3","0")))))) -> 0
A48: =A47+1 -> 37 | J48: =IF(G48="RSL","55","0") -> 0 | K48: =IF(G48="GVS","37.5",IF(G48="GVM","41.5",IF(G48="GVL","50",IF(G48="PCS","45.8",IF(G48="PCM","50",IF(G48="PCL","58.3","0")))))) -> 0
A49: =A48+1 -> 38 | J49: =IF(G49="RSL","55","0") -> 0 | K49: =IF(G49="GVS","37.5",IF(G49="GVM","41.5",IF(G49="GVL","50",IF(G49="PCS","45.8",IF(G49="PCM","50",IF(G49="PCL","58.3","0")))))) -> 0
... A61: =A60+1 -> 50 | J61: =IF(G61="RSL","55","0") -> 0 | K61: =IF(G61="GVS","37.5",IF(G61="GVM","41.5",IF(G61="GVL","50",IF(G61="PCS","45.8",IF(G61="PCM","50",IF(G61="PCL","58.3","0")))))) -> 0
A62: Page total | H62: =SUM(H37:H61) -> 0 | I62: =SUM(I37:I61) -> 0 | J62: =J61+J60+J59+J58+J57+J56+J55+J54+J53+J52+J51+J50+J49+J48+J47+J46+J45+J44+J43+J42+J41+J40+J39+J38+J37 -> 0 | K62: =K61+K60+K59+K58+K57+K56+K55+K54+K53+K52+K51+K50+K49+K48+K47+K46+K45+K44+K43+K42+K41+K40+K39+K38+K37 -> 0 | L62: =SUM(L37:L61) -> 0 | M62: =SUM(M37:M61) -> 0
R64: Page: 2
A65: Daily Report
A66: =A34 -> 17 - 5 - 2022 | H66: WEATHER | J66: =J34 -> SUNNY | L66: REPORT by | O66: =O34 -> HENDRA | R66: TOTAL STAFF | T66: =T34 -> 5
A68: No | B68: Docket No | C68: Reg No | D68: Mobile | E68: Gender | F68: TIME | G68: Service | H68: CASH | I68: CARD | J68: RSL | K68: GV | L68: GV CASH | M68: GV CARD | N68: O/Taker | O68: Comment | R68: NAME | S68: Time In | T68: Time out | U68: Total Hours
A69: =A61+1 -> 51 | J69: =IF(G69="RSL","55","0") -> 0 | K69: =IF(G69="GVS","37.5",IF(G69="GVM","41.5",IF(G69="GVL","50",IF(G69="PCS","45.8",IF(G69="PCM","50",IF(G69="PCL","58.3","0")))))) -> 0
A70: =A69+1 -> 52 | J70: =IF(G70="RSL","55","0") -> 0 | K70: =IF(G70="GVS","37.5",IF(G70="GVM","41.5",IF(G70="GVL","50",IF(G70="PCS","45.8",IF(G70="PCM","50",IF(G70="PCL","58.3","0")))))) -> 0
A71: =A70+1 -> 53 | J71: =IF(G71="RSL","55","0") -> 0 | K71: =IF(G71="GVS","37.5",IF(G71="GVM","41.5",IF(G71="GVL","50",IF(G71="PCS","45.8",IF(G71="PCM","50",IF(G71="PCL","58.3","0")))))) -> 0
A72: =A71+1 -> 54 | J72: =IF(G72="RSL","55","0") -> 0 | K72: =IF(G72="GVS","37.5",IF(G72="GVM","41.5",IF(G72="GVL","50",IF(G72="PCS","45.8",IF(G72="PCM","50",IF(G72="PCL","58.3","0")))))) -> 0
A73: =A72+1 -> 55 | J73: =IF(G73="RSL","55","0") -> 0 | K73: =IF(G73="GVS","37.5",IF(G73="GVM","41.5",IF(G73="GVL","50",IF(G73="PCS","45.8",IF(G73="PCM","50",IF(G73="PCL","58.3","0")))))) -> 0
A74: =A73+1 -> 56 | J74: =IF(G74="RSL","55","0") -> 0 | K74: =IF(G74="GVS","37.5",IF(G74="GVM","41.5",IF(G74="GVL","50",IF(G74="PCS","45.8",IF(G74="PCM","50",IF(G74="PCL","58.3","0")))))) -> 0
A75: =A74+1 -> 57 | J75: =IF(G75="RSL","55","0") -> 0 | K75: =IF(G75="GVS","37.5",IF(G75="GVM","41.5",IF(G75="GVL","50",IF(G75="PCS","45.8",IF(G75="PCM","50",IF(G75="PCL","58.3","0")))))) -> 0
A76: =A75+1 -> 58 | J76: =IF(G76="RSL","55","0") -> 0 | K76: =IF(G76="GVS","37.5",IF(G76="GVM","41.5",IF(G76="GVL","50",IF(G76="PCS","45.8",IF(G76="PCM","50",IF(G76="PCL","58.3","0")))))) -> 0
A77: =A76+1 -> 59 | J77: =IF(G77="RSL","55","0") -> 0 | K77: =IF(G77="GVS","37.5",IF(G77="GVM","41.5",IF(G77="GVL","50",IF(G77="PCS","45.8",IF(G77="PCM","50",IF(G77="PCL","58.3","0")))))) -> 0
A78: =A77+1 -> 60 | J78: =IF(G78="RSL","55","0") -> 0 | K78: =IF(G78="GVS","37.5",IF(G78="GVM","41.5",IF(G78="GVL","50",IF(G78="PCS","45.8",IF(G78="PCM","50",IF(G78="PCL","58.3","0")))))) -> 0
A79: =A78+1 -> 61 | J79: =IF(G79="RSL","55","0") -> 0 | K79: =IF(G79="GVS","37.5",IF(G79="GVM","41.5",IF(G79="GVL","50",IF(G79="PCS","45.8",IF(G79="PCM","50",IF(G79="PCL","58.3","0")))))) -> 0
A80: =A79+1 -> 62 | J80: =IF(G80="RSL","55","0") -> 0 | K80: =IF(G80="GVS","37.5",IF(G80="GVM","41.5",IF(G80="GVL","50",IF(G80="PCS","45.8",IF(G80="PCM","50",IF(G80="PCL","58.3","0")))))) -> 0
A81: =A80+1 -> 63 | J81: =IF(G81="RSL","55","0") -> 0 | K81: =IF(G81="GVS","37.5",IF(G81="GVM","41.5",IF(G81="GVL","50",IF(G81="PCS","45.8",IF(G81="PCM","50",IF(G81="PCL","58.3","0")))))) -> 0
... A93: =A92+1 -> 75 | J93: =IF(G93="RSL","55","0") -> 0 | K93: =IF(G93="GVS","37.5",IF(G93="GVM","41.5",IF(G93="GVL","50",IF(G93="PCS","45.8",IF(G93="PCM","50",IF(G93="PCL","58.3","0")))))) -> 0
A94: Page total | H94: =SUM(H69:H93) -> 0 | I94: =SUM(I69:I93) -> 0 | J94: =J93+J92+J91+J90+J89+J88+J87+J86+J85+J84+J83+J82+J81+J80+J79+J78+J77+J76+J75+J74+J73+J72+J71+J70+J69 -> 0 | K94: =K93+K92+K91+K90+K89+K88+K87+K86+K85+K84+K83+K82+K81+K80+K79+K78+K77+K76+K75+K74+K73+K72+K71+K70+K69 -> 0 | L94: =SUM(L69:L93) -> 0 | M94: =SUM(M69:M93) -> 0
R96: Page: 3

Sheet WED
A1: B2 Daily Report
A2: 18 - 5 - 2022 | H2: WEATHER | J2: SUNNY | L2: REPORT BY | O2: HENDRA | R2: TOTAL STAFF | T2: 6 | X2: Merchant machine usage at B2 | AA2: Settle amount | AI2: Merchant machine usage at GA | AL2: Settle amount
A4: No | B4: Docket No | C4: Reg No | D4: Mobile | E4: Gender | F4: TIME | G4: Service | H4: CASH | I4: CARD | J4: RSL | K4: GV | L4: GV CASH | M4: GV CARD | N4: O/Taker | O4: Comment | R4: NAME | S4: Time In | T4: Time out | U4: Total Hours | Z4: B2 machine | AA4: BLH machine | AB4: Wongo | AE4: B2 machine | AF4: BLH machine | AG4: Wongo | AK4: GA machine | AL4: BLH machine | AM4: Wongo | AP4: GA machine | AQ4: BLH machine | AR4: Wongo
A5: 1 | B5: 4208 | C5: DGC58G | D5: 0418888910 | E5: F | F5: 900 | G5: D | H5: 70 | J5: =IF(G5="RSL","55","0") -> 0 | K5: =IF(G5="GVS","37.5",IF(G5="GVM","41.5",IF(G5="GVL","50",IF(G5="PCS","45.8",IF(G5="PCM","50",IF(G5="PCL","58.3","0")))))) -> 0 | N5: HENDRA | R5: HENDRA | S5: 0.33333333 | T5: 0.70833333 | U5: =(T5-S5)*24 -> 9 | X5: NOV | Y5: 1 | AD5: 16 | AI5: NOV | AJ5: 1 | AO5: 16
A6: 2 | B6: 4209 | C6: DNK75K | D6: 0425421508 | E6: F | F6: 900 | G6: X | I6: 95 | J6: =IF(G6="RSL","55","0") -> 0 | K6: =IF(G6="GVS","37.5",IF(G6="GVM","41.5",IF(G6="GVL","50",IF(G6="PCS","45.8",IF(G6="PCM","50",IF(G6="PCL","58.3","0")))))) -> 0 | N6: HENDRA | R6: JUNIOR | S6: 0.33333333 | T6: 0.70833333 | U6: =(T6-S6)*24 -> 9 | W6: M | Y6: 2 | AD6: 17 | AJ6: 2 | AO6: 17
A7: 3 | B7: 4210 | C7: ELK07E | D7: 0403507267 | E7: F | F7: 915 | G7: D | I7: 75 | J7: =IF(G7="RSL","55","0") -> 0 | K7: =IF(G7="GVS","37.5",IF(G7="GVM","41.5",IF(G7="GVL","50",IF(G7="PCS","45.8",IF(G7="PCM","50",IF(G7="PCL","58.3","0")))))) -> 0 | N7: HENDRA | R7: ARIANTO | S7: 0.35416667 | T7: 0.66666667 | U7: =(T7-S7)*24 -> 7.5 | W7: F | Y7: 3 | AD7: 18 | AJ7: 3 | AO7: 18
A8: 4 | B8: 4211 | C8: EQJ49T | D8: 0449051688 | E8: F | F8: 920 | G8: H | J8: =IF(G8="RSL","55","0") -> 0 | K8: =IF(G8="GVS","37.5",IF(G8="GVM","41.5",IF(G8="GVL","50",IF(G8="PCS","45.8",IF(G8="PCM","50",IF(G8="PCL","58.3","0")))))) -> 0 | M8: 750 | N8: HENDRA | O8: PCL 22029 1/6 | R8: KUROSH | S8: 0.35416667 | T8: 0.70833333 | U8: =(T8-S8)*24 -> 8.5 | Y8: 4 | AD8: 19 | AJ8: 4 | AO8: 19
A9: 5 | B9: 4212 | C9: DVW72Q | D9: 0418881485 | E9: M | F9: 930 | G9: PCL | J9: =IF(G9="RSL","55","0") -> 0 | K9: 79.16 | N9: HENDRA | O9: # 21057 3/6 | R9: STEVE | S9: 0.375 | T9: 0.70833333 | U9: =(T9-S9)*24 -> 8 | X9: EXCL RSL | Y9: 5 | AD9: 20 | AJ9: 5 | AO9: 20
A10: 6 | B10: 4213 | C10: DQL85E | D10: 0418117824 | E10: F | F10: 945 | G10: D | I10: 55 | J10: =IF(G10="RSL","55","0") -> 0 | K10: =IF(G10="GVS","37.5",IF(G10="GVM","41.5",IF(G10="GVL","50",IF(G10="PCS","45.8",IF(G10="PCM","50",IF(G10="PCL","58.3","0")))))) -> 0 | N10: HENDRA | R10: VINNY | S10: 0.41666667 | T10: 0.70833333 | U10: =(T10-S10)*24 -> 7 | Y10: 6 | AD10: 21 | AJ10: 6 | AO10: 21
A11: 7 | B11: 4214 | C11: CEW82Y | D11: 0421218302 | E11: F | F11: 1000 | G11: X | I11: 95 | J11: =IF(G11="RSL","55","0") -> 0 | K11: =IF(G11="GVS","37.5",IF(G11="GVM","41.5",IF(G11="GVL","50",IF(G11="PCS","45.8",IF(G11="PCM","50",IF(G11="PCL","58.3","0")))))) -> 0 | N11: HENDRA | U11: =(T11-S11)*24 -> 0 | Y11: 7 | AD11: 22 | AJ11: 7 | AO11: 22
A12: 8 | B12: 4215 | C12: ERC80S | D12: 0414913058 | E12: F | F12: 1000 | G12: X | I12: 95 | J12: =IF(G12="RSL","55","0") -> 0 | K12: =IF(G12="GVS","37.5",IF(G12="GVM","41.5",IF(G12="GVL","50",IF(G12="PCS","45.8",IF(G12="PCM","50",IF(G12="PCL","58.3","0")))))) -> 0 | N12: HENDRA | U12: =(T12-S12)*24 -> 0 | Y12: 8 | AD12: 23 | AJ12: 8 | AO12: 23
A13: 9 | B13: 4216 | C13: CTI78H | D13: 0406816699 | E13: F | F13: 1005 | G13: D | I13: 75 | J13: =IF(G13="RSL","55","0") -> 0 | K13: =IF(G13="GVS","37.5",IF(G13="GVM","41.5",IF(G13="GVL","50",IF(G13="PCS","45.8",IF(G13="PCM","50",IF(G13="PCL","58.3","0")))))) -> 0 | N13: HENDRA | U13: =(T13-S13)*24 -> 0 | Y13: 9 | AD13: 24 | AJ13: 9 | AO13: 24
A14: 10 | B14: 4217 | C14: DNG33E | D14: 0414747668 | E14: F | F14: 1100 | G14: GV3 | J14: =IF(G14="RSL","55","0") -> 0 | K14: =IF(G14="GVS","37.5",IF(G14="GVM","41.5",IF(G14="GVL","50",IF(G14="PCS","45.8",IF(G14="PCM","50",IF(G14="PCL","58.3","0")))))) -> 0 | N14: HENDRA | O14: # 202761 5/6 6/6 | U14: =(T14-S14)*24 -> 0 | Y14: 10 | AD14: 25 | AJ14: 10 | AO14: 25
A15: 11 | B15: 4218 | C15: MY194 | D15: 0427040347 | E15: F | F15: 1105 | G15: FD | I15: 400 | J15: =IF(G15="RSL","55","0") -> 0 | K15: =IF(G15="GVS","37.5",IF(G15="GVM","41.5",IF(G15="GVL","50",IF(G15="PCS","45.8",IF(G15="PCM","50",IF(G15="PCL","58.3","0")))))) -> 0 | N15: HENDRA | O15: SMALL | U15: =(T15-S15)*24 -> 0 | Y15: 11 | AD15: 26 | AJ15: 11 | AO15: 26
A16: 12 | B16: 4219 | C16: EEQ91C | D16: 0405357559 | E16: F | F16: 1115 | G16: D | I16: 75 | J16: =IF(G16="RSL","55","0") -> 0 | K16: =IF(G16="GVS","37.5",IF(G16="GVM","41.5",IF(G16="GVL","50",IF(G16="PCS","45.8",IF(G16="PCM","50",IF(G16="PCL","58.3","0")))))) -> 0 | N16: HENDRA | O16: TAX | R16: =H32/U16 -> 0.40816327 | S16: =H32/(U16-U5) -> 0.5 | T16: =C32/U16 -> 47.822857 | U16: =SUM(U5:U15) -> 49 | Y16: 12 | AD16: 27 | AJ16: 12 | AO16: 27
A17: 13 | B17: 4220 | C17: EIM54Y | D17: 0409921951 | E17: M | F17: 1200 | G17: X | I17: 95 | J17: =IF(G17="RSL","55","0") -> 0 | K17: =IF(G17="GVS","37.5",IF(G17="GVM","41.5",IF(G17="GVL","50",IF(G17="PCS","45.8",IF(G17="PCM","50",IF(G17="PCL","58.3","0")))))) -> 0 | N17: HENDRA | R17: Cars/T Hr ① | S17: Cars/T Hr ② | T17: Sales/T Hr | U17: Total Hours | Y17: 13 | AD17: 28 | AJ17: 13 | AO17: 28
A18: 14 | B18: 4221 | C18: DFN84R | D18: 0450875092 | E18: M | F18: 1230 | G18: X | J18: =IF(G18="RSL","55","0") -> 0 | K18: =IF(G18="GVS","37.5",IF(G18="GVM","41.5",IF(G18="GVL","50",IF(G18="PCS","45.8",IF(G18="PCM","50",IF(G18="PCL","58.3","0")))))) -> 0 | N18: HENDRA | O18: CANCEL | R18: ITEM | S18: QTY | T18: AMT | U18: RMKS | Y18: 14 | AD18: 29 | AJ18: 14 | AO18: 29
A19: 15 | B19: 4222 | C19: BIHARI | D19: 0475979152 | E19: M | F19: 1315 | G19: FD | I19: 500 | J19: =IF(G19="RSL","55","0") -> 0 | K19: =IF(G19="GVS","37.5",IF(G19="GVM","41.5",IF(G19="GVL","50",IF(G19="PCS","45.8",IF(G19="PCM","50",IF(G19="PCL","58.3","0")))))) -> 0 | N19: HENDRA | O19: LARGE | R19: GV | S19: =COUNT(L5:M29,L37:M61,L69:M93) -> 1 | T19: =SUM(L5:M29,L37:M61,L69:M93) -> 750 | Y19: 15 | AD19: 30 | AJ19: 15 | AO19: 30
A20: 16 | B20: 4223 | C20: DBU53K | D20: 0410501852 | E20: M | F20: 1330 | G20: D/ST | I20: 300 | J20: =IF(G20="RSL","55","0") -> 0 | K20: =IF(G20="GVS","37.5",IF(G20="GVM","41.5",IF(G20="GVL","50",IF(G20="PCS","45.8",IF(G20="PCM","50",IF(G20="PCL","58.3","0")))))) -> 0 | N20: HENDRA | O20: MEDIUM | AD20: 31 | AO20: 31
A21: 17 | B21: 4224 | C21: OSMEN | D21: 0488181888 | E21: F | F21: 1330 | G21: PCL | J21: =IF(G21="RSL","55","0") -> 0 | K21: 79.16 | N21: HENDRA | O21: #21068 5/6
A22: 18 | B22: 4225 | C22: BNC63T | D22: 0425379428 | E22: F | F22: 1330 | G22: D | I22: 55 | J22: =IF(G22="RSL","55","0") -> 0 | K22: =IF(G22="GVS","37.5",IF(G22="GVM","41.5",IF(G22="GVL","50",IF(G22="PCS","45.8",IF(G22="PCM","50",IF(G22="PCL","58.3","0")))))) -> 0 | N22: HENDRA | AD22: Total | AE22: =SUM(Z5:Z19,AE5:AE20) -> 0 | AF22: =SUM(AA5:AA19,AF5:AF20,) -> 0 | AG22: =SUM(AB5:AB19,AG5:AG20) -> 0 | AO22: Total | AP22: =SUM(AK5:AK19,AP5:AP20) -> 0 | AQ22: =SUM(AL5:AL19,AQ5:AQ20,) -> 0 | AR22: =SUM(AM5:AM19,AR5:AR20) -> 0
A23: 19 | B23: 4226 | C23: DS036E | D23: 0407661607 | E23: F | F23: 1453 | G23: D | I23: 150 | J23: =IF(G23="RSL","55","0") -> 0 | K23: =IF(G23="GVS","37.5",IF(G23="GVM","41.5",IF(G23="GVL","50",IF(G23="PCS","45.8",IF(G23="PCM","50",IF(G23="PCL","58.3","0")))))) -> 0 | N23: VINNY | P23: TRICEPS
A24: 20 | B24: 4227 | C24: BK036S | D24: 0411757862 | E24: F | F24: 1620 | G24: W/O | I24: 50 | J24: =IF(G24="RSL","55","0") -> 0 | K24: =IF(G24="GVS","37.5",IF(G24="GVM","41.5",IF(G24="GVL","50",IF(G24="PCS","45.8",IF(G24="PCM","50",IF(G24="PCL","58.3","0")))))) -> 0 | N24: HENDRA | R24: SMALL | S24: MEDIUM | T24: LARGE | U24: TOTAL | AD24: B2/GA TOTAL | AE24: B2 machine | AF24: GA machine | AG24: BLH machine | AH24: Wongo machine | AI24: Sub total
A25: 21 | J25: =IF(G25="RSL","55","0") -> 0 | K25: =IF(G25="GVS","37.5",IF(G25="GVM","41.5",IF(G25="GVL","50",IF(G25="PCS","45.8",IF(G25="PCM","50",IF(G25="PCL","58.3","0")))))) -> 0 | R25: =COUNTIF(G5:G29,"GV1")+COUNTIF(G37:G61,"GV1")+COUNTIF(G69:G93,"GV1") -> 0 | S25: =COUNTIF(G5:G29,"GV2")+COUNTIF(G37:G61,"GV2")+COUNTIF(G69:G93,"GV2") -> 0 | T25: =COUNTIF(G5:G29,"GV3")+COUNTIF(G37:G61,"GV3")+COUNTIF(G69:G93,"GV3") -> 1 | U25: =((C32+(R26+S26+T26)*0.5)) -> 2368.32 | AD25: =SUM(AE25:AF25) -> 0 | AE25: =SUM(AE22) -> 0 | AF25: =SUM(AP22) -> 0 | AG25: =SUM(AF22+AQ22) -> 0 | AH25: =AG22+AR22 -> 0 | AI25: =SUM(AE25:AH25) -> 0
A26: 22 | J26: =IF(G26="RSL","55","0") -> 0 | K26: =IF(G26="GVS","37.5",IF(G26="GVM","41.5",IF(G26="GVL","50",IF(G26="PCS","45.8",IF(G26="PCM","50",IF(G26="PCL","58.3","0")))))) -> 0 | R26: =R25*37.5 -> 0 | S26: =S25*41.5 -> 0 | T26: =T25*50 -> 50 | X26: Branch cards
A27: 23 | J27: =IF(G27="RSL","55","0") -> 0 | K27: =IF(G27="GVS","37.5",IF(G27="GVM","41.5",IF(G27="GVL","50",IF(G27="PCS","45.8",IF(G27="PCM","50",IF(G27="PCL","58.3","0")))))) -> 0 | R27: Expense | X27: 1 | Z27: -2745
A28: 24 | J28: =IF(G28="RSL","55","0") -> 0 | K28: =IF(G28="GVS","37.5",IF(G28="GVM","41.5",IF(G28="GVL","50",IF(G28="PCS","45.8",IF(G28="PCM","50",IF(G28="PCL","58.3","0")))))) -> 0 | X28: 2
A29: 25 | J29: =IF(G29="RSL","55","0") -> 0 | K29: =IF(G29="GVS","37.5",IF(G29="GVM","41.5",IF(G29="GVL","50",IF(G29="PCS","45.8",IF(G29="PCM","50",IF(G29="PCL","58.3","0")))))) -> 0 | X29: 3
A30: Page total | H30: =SUM(H5:H29) -> 70 | I30: =SUM(I5:I29) -> 2115 | J30: =J5+J6+J7+J8+J9+J10+J11+J12+J13+J14+J15+J16+J18+J19+J17+J20+J22+J23+J21+J24+J25+J26+J27+J28+J29 -> 0 | K30: =K5+K6+K7+K8+K9+K10+K11+K12+K13+K14+K15+K16+K18+K19+K17+K20+K22+K23+K21+K24+K25+K26+K27+K28+K29 -> 158.32 | L30: =SUM(L5:L29) -> 0 | M30: =SUM(M5:M29) -> 750 | N30: CASH | O30: CARD | P30: GV | Q30: RSL | X30: 4
A31: Daily Total | H31: =H30+H62+H94 -> 70 | I31: =I30+I62+I94 -> 2115 | J31: =J30+J62+J94 -> 0 | K31: =K30+K62+K94 -> 158.32 | L31: =L30+L62+L94 -> 0 | M31: =M30+M62+M94 -> 750 | N31: =COUNT(H5:H29,H37:H61,H69:H93) -> 1 | O31: =COUNT(I5:I29,I37:I61,I69:I93) -> 14 | P31: =COUNTIF(G5:G29,"G*")+COUNTIF(G37:G61,"G*")+COUNTIF(G69:G93,"G*")+COUNTIF(G5:G29,"P*")+COUNTIF(G37:G61,"P*")+COUNTIF(G69:G93,"P*") -> 3 | Q31: =COUNTIF(G5:G29,"RSL")+COUNTIF(G37:G61,"RSL")+COUNTIF(G69:G93,"RSL") -> 0 | R31: CASH CLOSING | S31: =H31+L31-U28-U29-U30 -> 70 | T31: =H31+I31+L31+M31 -> 2935 | X31: Subtotal | Z31: =SUM(Z27:Z30) -> -2745
A32: TOTAL SALES | C32: =H31+I31+J31+K31 -> 2343.32 | F32: No of Cars | H32: =COUNT(B5:B29,B37:B61,B69:B93) -> 20 | I32: Average | K32: =C32/H32 -> 117.166 | N32: =H31/C32 -> 0.029872147 | O32: =I31/C32 -> 0.90256559 | P32: =K31/C32 -> 0.067562262 | Q32: =J31/C32 -> 0 | R32: CARD CLOSING | S32: =I31+M31 -> 2865 | X32: B2 card | Z32: =I31 -> 2115
A33: Daily Report | X33: Settlement | Z33: =SUM(Z31:Z32) -> -630
A34: =A2 -> 18 - 5 - 2022 | H34: WEATHER | J34: =J2 -> SUNNY | L34: REPORT by | O34: =O2 -> HENDRA | R34: TOTAL STAFF | T34: =T2 -> 6
A36: No | B36: Docket No | C36: Reg No | D36: Mobile | E36: Gender | F36: TIME | G36: Service | H36: CASH | I36: CARD | J36: RSL | K36: GV | L36: GV CASH | M36: GV CARD | N36: O/Taker | O36: Comment | R36: NAME | S36: Time In | T36: Time out | U36: Total Hours
A37: =A29+1 -> 26 | J37: =IF(G37="RSL","55","0") -> 0 | K37: =IF(G37="GVS","37.5",IF(G37="GVM","41.5",IF(G37="GVL","50",IF(G37="PCS","45.8",IF(G37="PCM","50",IF(G37="PCL","58.3","0")))))) -> 0
A38: =A37+1 -> 27 | J38: =IF(G38="RSL","55","0") -> 0 | K38: =IF(G38="GVS","37.5",IF(G38="GVM","41.5",IF(G38="GVL","50",IF(G38="PCS","45.8",IF(G38="PCM","50",IF(G38="PCL","58.3","0")))))) -> 0
A39: =A38+1 -> 28 | J39: =IF(G39="RSL","55","0") -> 0 | K39: =IF(G39="GVS","37.5",IF(G39="GVM","41.5",IF(G39="GVL","50",IF(G39="PCS","45.8",IF(G39="PCM","50",IF(G39="PCL","58.3","0")))))) -> 0
A40: =A39+1 -> 29 | J40: =IF(G40="RSL","55","0") -> 0 | K40: =IF(G40="GVS","37.5",IF(G40="GVM","41.5",IF(G40="GVL","50",IF(G40="PCS","45.8",IF(G40="PCM","50",IF(G40="PCL","58.3","0")))))) -> 0
A41: =A40+1 -> 30 | J41: =IF(G41="RSL","55","0") -> 0 | K41: =IF(G41="GVS","37.5",IF(G41="GVM","41.5",IF(G41="GVL","50",IF(G41="PCS","45.8",IF(G41="PCM","50",IF(G41="PCL","58.3","0")))))) -> 0
A42: =A41+1 -> 31 | J42: =IF(G42="RSL","55","0") -> 0 | K42: =IF(G42="GVS","37.5",IF(G42="GVM","41.5",IF(G42="GVL","50",IF(G42="PCS","45.8",IF(G42="PCM","50",IF(G42="PCL","58.3","0")))))) -> 0
A43: =A42+1 -> 32 | J43: =IF(G43="RSL","55","0") -> 0 | K43: =IF(G43="GVS","37.5",IF(G43="GVM","41.5",IF(G43="GVL","50",IF(G43="PCS","45.8",IF(G43="PCM","50",IF(G43="PCL","58.3","0")))))) -> 0
A44: =A43+1 -> 33 | J44: =IF(G44="RSL","55","0") -> 0 | K44: =IF(G44="GVS","37.5",IF(G44="GVM","41.5",IF(G44="GVL","50",IF(G44="PCS","45.8",IF(G44="PCM","50",IF(G44="PCL","58.3","0")))))) -> 0
A45: =A44+1 -> 34 | J45: =IF(G45="RSL","55","0") -> 0 | K45: =IF(G45="GVS","37.5",IF(G45="GVM","41.5",IF(G45="GVL","50",IF(G45="PCS","45.8",IF(G45="PCM","50",IF(G45="PCL","58.3","0")))))) -> 0
A46: =A45+1 -> 35 | J46: =IF(G46="RSL","55","0") -> 0 | K46: =IF(G46="GVS","37.5",IF(G46="GVM","41.5",IF(G46="GVL","50",IF(G46="PCS","45.8",IF(G46="PCM","50",IF(G46="PCL","58.3","0")))))) -> 0
A47: =A46+1 -> 36 | J47: =IF(G47="RSL","55","0") -> 0 | K47: =IF(G47="GVS","37.5",IF(G47="GVM","41.5",IF(G47="GVL","50",IF(G47="PCS","45.8",IF(G47="PCM","50",IF(G47="PCL","58.3","0")))))) -> 0
A48: =A47+1 -> 37 | J48: =IF(G48="RSL","55","0") -> 0 | K48: =IF(G48="GVS","37.5",IF(G48="GVM","41.5",IF(G48="GVL","50",IF(G48="PCS","45.8",IF(G48="PCM","50",IF(G48="PCL","58.3","0")))))) -> 0
A49: =A48+1 -> 38 | J49: =IF(G49="RSL","55","0") -> 0 | K49: =IF(G49="GVS","37.5",IF(G49="GVM","41.5",IF(G49="GVL","50",IF(G49="PCS","45.8",IF(G49="PCM","50",IF(G49="PCL","58.3","0")))))) -> 0
... A61: =A60+1 -> 50 | J61: =IF(G61="RSL","55","0") -> 0 | K61: =IF(G61="GVS","37.5",IF(G61="GVM","41.5",IF(G61="GVL","50",IF(G61="PCS","45.8",IF(G61="PCM","50",IF(G61="PCL","58.3","0")))))) -> 0
A62: Page total | H62: =SUM(H37:H61) -> 0 | I62: =SUM(I37:I61) -> 0 | J62: =J61+J60+J59+J58+J57+J56+J55+J54+J53+J52+J51+J50+J49+J48+J47+J46+J45+J44+J43+J42+J41+J40+J39+J38+J37 -> 0 | K62: =K61+K60+K59+K58+K57+K56+K55+K54+K53+K52+K51+K50+K49+K48+K47+K46+K45+K44+K43+K42+K41+K40+K39+K38+K37 -> 0 | L62: =SUM(L37:L61) -> 0 | M62: =SUM(M37:M61) -> 0
R64: Page: 2
A65: Daily Report
A66: =A34 -> 18 - 5 - 2022 | H66: WEATHER | J66: =J34 -> SUNNY | L66: REPORT by | O66: =O34 -> HENDRA | R66: TOTAL STAFF | T66: =T34 -> 6
A68: No | B68: Docket No | C68: Reg No | D68: Mobile | E68: Gender | F68: TIME | G68: Service | H68: CASH | I68: CARD | J68: RSL | K68: GV | L68: GV CASH | M68: GV CARD | N68: O/Taker | O68: Comment | R68: NAME | S68: Time In | T68: Time out | U68: Total Hours
A69: =A61+1 -> 51 | J69: =IF(G69="RSL","55","0") -> 0 | K69: =IF(G69="GVS","37.5",IF(G69="GVM","41.5",IF(G69="GVL","50",IF(G69="PCS","45.8",IF(G69="PCM","50",IF(G69="PCL","58.3","0")))))) -> 0
A70: =A69+1 -> 52 | J70: =IF(G70="RSL","55","0") -> 0 | K70: =IF(G70="GVS","37.5",IF(G70="GVM","41.5",IF(G70="GVL","50",IF(G70="PCS","45.8",IF(G70="PCM","50",IF(G70="PCL","58.3","0")))))) -> 0
A71: =A70+1 -> 53 | J71: =IF(G71="RSL","55","0") -> 0 | K71: =IF(G71="GVS","37.5",IF(G71="GVM","41.5",IF(G71="GVL","50",IF(G71="PCS","45.8",IF(G71="PCM","50",IF(G71="PCL","58.3","0")))))) -> 0
A72: =A71+1 -> 54 | J72: =IF(G72="RSL","55","0") -> 0 | K72: =IF(G72="GVS","37.5",IF(G72="GVM","41.5",IF(G72="GVL","50",IF(G72="PCS","45.8",IF(G72="PCM","50",IF(G72="PCL","58.3","0")))))) -> 0
A73: =A72+1 -> 55 | J73: =IF(G73="RSL","55","0") -> 0 | K73: =IF(G73="GVS","37.5",IF(G73="GVM","41.5",IF(G73="GVL","50",IF(G73="PCS","45.8",IF(G73="PCM","50",IF(G73="PCL","58.3","0")))))) -> 0
A74: =A73+1 -> 56 | J74: =IF(G74="RSL","55","0") -> 0 | K74: =IF(G74="GVS","37.5",IF(G74="GVM","41.5",IF(G74="GVL","50",IF(G74="PCS","45.8",IF(G74="PCM","50",IF(G74="PCL","58.3","0")))))) -> 0
A75: =A74+1 -> 57 | J75: =IF(G75="RSL","55","0") -> 0 | K75: =IF(G75="GVS","37.5",IF(G75="GVM","41.5",IF(G75="GVL","50",IF(G75="PCS","45.8",IF(G75="PCM","50",IF(G75="PCL","58.3","0")))))) -> 0
A76: =A75+1 -> 58 | J76: =IF(G76="RSL","55","0") -> 0 | K76: =IF(G76="GVS","37.5",IF(G76="GVM","41.5",IF(G76="GVL","50",IF(G76="PCS","45.8",IF(G76="PCM","50",IF(G76="PCL","58.3","0")))))) -> 0
A77: =A76+1 -> 59 | J77: =IF(G77="RSL","55","0") -> 0 | K77: =IF(G77="GVS","37.5",IF(G77="GVM","41.5",IF(G77="GVL","50",IF(G77="PCS","45.8",IF(G77="PCM","50",IF(G77="PCL","58.3","0")))))) -> 0
A78: =A77+1 -> 60 | J78: =IF(G78="RSL","55","0") -> 0 | K78: =IF(G78="GVS","37.5",IF(G78="GVM","41.5",IF(G78="GVL","50",IF(G78="PCS","45.8",IF(G78="PCM","50",IF(G78="PCL","58.3","0")))))) -> 0
A79: =A78+1 -> 61 | J79: =IF(G79="RSL","55","0") -> 0 | K79: =IF(G79="GVS","37.5",IF(G79="GVM","41.5",IF(G79="GVL","50",IF(G79="PCS","45.8",IF(G79="PCM","50",IF(G79="PCL","58.3","0")))))) -> 0
A80: =A79+1 -> 62 | J80: =IF(G80="RSL","55","0") -> 0 | K80: =IF(G80="GVS","37.5",IF(G80="GVM","41.5",IF(G80="GVL","50",IF(G80="PCS","45.8",IF(G80="PCM","50",IF(G80="PCL","58.3","0")))))) -> 0
A81: =A80+1 -> 63 | J81: =IF(G81="RSL","55","0") -> 0 | K81: =IF(G81="GVS","37.5",IF(G81="GVM","41.5",IF(G81="GVL","50",IF(G81="PCS","45.8",IF(G81="PCM","50",IF(G81="PCL","58.3","0")))))) -> 0
... A93: =A92+1 -> 75 | J93: =IF(G93="RSL","55","0") -> 0 | K93: =IF(G93="GVS","37.5",IF(G93="GVM","41.5",IF(G93="GVL","50",IF(G93="PCS","45.8",IF(G93="PCM","50",IF(G93="PCL","58.3","0")))))) -> 0
A94: Page total | H94: =SUM(H69:H93) -> 0 | I94: =SUM(I69:I93) -> 0 | J94: =J93+J92+J91+J90+J89+J88+J87+J86+J85+J84+J83+J82+J81+J80+J79+J78+J77+J76+J75+J74+J73+J72+J71+J70+J69 -> 0 | K94: =K93+K92+K91+K90+K89+K88+K87+K86+K85+K84+K83+K82+K81+K80+K79+K78+K77+K76+K75+K74+K73+K72+K71+K70+K69 -> 0 | L94: =SUM(L69:L93) -> 0 | M94: =SUM(M69:M93) -> 0
R96: Page: 3

Sheet THU
A1: B2 Daily Report
A2: 19 - 5 - 2022 | H2: WEATHER | J2: SUNNY | L2: REPORT BY | O2: HENDRA | R2: TOTAL STAFF | T2: 6 | X2: Merchant machine usage at B2 | AA2: Settle amount | AI2: Merchant machine usage at GA | AL2: Settle amount
A4: No | B4: Docket No | C4: Reg No | D4: Mobile | E4: Gender | F4: TIME | G4: Service | H4: CASH | I4: CARD | J4: RSL | K4: GV | L4: GV CASH | M4: GV CARD | N4: O/Taker | O4: Comment | R4: NAME | S4: Time In | T4: Time out | U4: Total Hours | Z4: B2 machine | AA4: BLH machine | AB4: Wongo | AE4: B2 machine | AF4: BLH machine | AG4: Wongo | AK4: GA machine | AL4: BLH machine | AM4: Wongo | AP4: GA machine | AQ4: BLH machine | AR4: Wongo
A5: 1 | B5: 4228 | C5: CKC333 | D5: 0411889693 | E5: M | F5: 850 | G5: RSL | J5: =IF(G5="RSL","55","0") -> 55 | K5: =IF(G5="GVS","37.5",IF(G5="GVM","41.5",IF(G5="GVL","50",IF(G5="PCS","45.8",IF(G5="PCM","50",IF(G5="PCL","58.3","0")))))) -> 0 | N5: HENDRA | O5: 202204037 | R5: HENDRA | S5: 0.33333333 | T5: 0.70833333 | U5: =(T5-S5)*24 -> 9 | X5: NOV | Y5: 1 | AD5: 16 | AI5: NOV | AJ5: 1 | AO5: 16
A6: 2 | B6: 4229 | C6: 88BMUM | D6: 0479077545 | E6: M | F6: 930 | G6: D | I6: 55 | J6: =IF(G6="RSL","55","0") -> 0 | K6: =IF(G6="GVS","37.5",IF(G6="GVM","41.5",IF(G6="GVL","50",IF(G6="PCS","45.8",IF(G6="PCM","50",IF(G6="PCL","58.3","0")))))) -> 0 | N6: HENDRA | R6: ARIANTO | S6: 0.35416667 | T6: 0.70833333 | U6: =(T6-S6)*24 -> 8.5 | W6: M | Y6: 2 | AD6: 17 | AJ6: 2 | AO6: 17
A7: 3 | B7: 4230 | C7: DKX87K | D7: 0410446389 | E7: F | F7: 930 | G7: PCS | J7: =IF(G7="RSL","55","0") -> 0 | K7: 62.5 | N7: HENDRA | O7: # 21122813 3/6 | R7: KUROSH | S7: 0.35416667 | T7: 0.5 | U7: =(T7-S7)*24 -> 3.5 | W7: F | Y7: 3 | AD7: 18 | AJ7: 3 | AO7: 18
A8: 4 | B8: 4231 | C8: EBR55B | D8: 0413519587 | E8: F | F8: 935 | G8: D | H8: 75 | J8: =IF(G8="RSL","55","0") -> 0 | K8: =IF(G8="GVS","37.5",IF(G8="GVM","41.5",IF(G8="GVL","50",IF(G8="PCS","45.8",IF(G8="PCM","50",IF(G8="PCL","58.3","0")))))) -> 0 | N8: HENDRA | R8: JUNIOR | S8: 0.375 | T8: 0.70833333 | U8: =(T8-S8)*24 -> 8 | Y8: 4 | AD8: 19 | AJ8: 4 | AO8: 19
A9: 5 | B9: 4232 | C9: DSB59R | D9: 0421284405 | E9: F | F9: 1000 | G9: X | I9: 95 | J9: =IF(G9="RSL","55","0") -> 0 | K9: =IF(G9="GVS","37.5",IF(G9="GVM","41.5",IF(G9="GVL","50",IF(G9="PCS","45.8",IF(G9="PCM","50",IF(G9="PCL","58.3","0")))))) -> 0 | N9: HENDRA | R9: STEVE | S9: 0.375 | T9: 0.70833333 | U9: =(T9-S9)*24 -> 8 | X9: EXCL RSL | Y9: 5 | AD9: 20 | AJ9: 5 | AO9: 20
A10: 6 | B10: 4233 | C10: OOOSAL | D10: 0414272218 | E10: F | F10: 1000 | G10: D | I10: 55 | J10: =IF(G10="RSL","55","0") -> 0 | K10: =IF(G10="GVS","37.5",IF(G10="GVM","41.5",IF(G10="GVL","50",IF(G10="PCS","45.8",IF(G10="PCM","50",IF(G10="PCL","58.3","0")))))) -> 0 | N10: HENDRA | R10: VINNY | S10: 0.45833333 | T10: 0.70833333 | U10: =(T10-S10)*24 -> 6 | Y10: 6 | AD10: 21 | AJ10: 6 | AO10: 21
A11: 7 | B11: 4234 | C11: DBI12C | D11: 0404479199 | E11: F | F11: 1025 | G11: H | I11: 120 | J11: =IF(G11="RSL","55","0") -> 0 | K11: =IF(G11="GVS","37.5",IF(G11="GVM","41.5",IF(G11="GVL","50",IF(G11="PCS","45.8",IF(G11="PCM","50",IF(G11="PCL","58.3","0")))))) -> 0 | N11: HENDRA | R11: AMAN | S11: 0.55208333 | T11: 0.59375 | U11: =(T11-S11)*24 -> 1 | Y11: 7 | AD11: 22 | AJ11: 7 | AO11: 22
A12: 8 | B12: 4235 | C12: CMR01C | D12: 0418963900 | E12: M | F12: 1025 | G12: D | I12: 55 | J12: =IF(G12="RSL","55","0") -> 0 | K12: =IF(G12="GVS","37.5",IF(G12="GVM","41.5",IF(G12="GVL","50",IF(G12="PCS","45.8",IF(G12="PCM","50",IF(G12="PCL","58.3","0")))))) -> 0 | N12: HENDRA | U12: =(T12-S12)*24 -> 0 | Y12: 8 | AD12: 23 | AJ12: 8 | AO12: 23
A13: 9 | B13: 4236 | C13: DQA16U | D13: ??? | E13: F | F13: 1130 | G13: D | I13: 65 | J13: =IF(G13="RSL","55","0") -> 0 | K13: =IF(G13="GVS","37.5",IF(G13="GVM","41.5",IF(G13="GVL","50",IF(G13="PCS","45.8",IF(G13="PCM","50",IF(G13="PCL","58.3","0")))))) -> 0 | N13: HENDRA | U13: =(T13-S13)*24 -> 0 | Y13: 9 | AD13: 24 | AJ13: 9 | AO13: 24
A14: 10 | B14: 4237 | C14: TS6888 | D14: 0417880888 | E14: M | F14: 1130 | G14: PCS | J14: =IF(G14="RSL","55","0") -> 0 | K14: 62.5 | N14: HENDRA | O14: # 22002 1/6 | U14: =(T14-S14)*24 -> 0 | Y14: 10 | AD14: 25 | AJ14: 10 | AO14: 25
A15: 11 | B15: 4238 | C15: NCE47E | D15: 0409980911 | E15: F | F15: 1140 | G15: D | I15: 75 | J15: =IF(G15="RSL","55","0") -> 0 | K15: =IF(G15="GVS","37.5",IF(G15="GVM","41.5",IF(G15="GVL","50",IF(G15="PCS","45.8",IF(G15="PCM","50",IF(G15="PCL","58.3","0")))))) -> 0 | N15: HENDRA | O15: TAX | U15: =(T15-S15)*24 -> 0 | Y15: 11 | AD15: 26 | AJ15: 11 | AO15: 26
A16: 12 | B16: 4239 | C16: ELR61W | D16: 0402092724 | E16: F | F16: 1200 | G16: X | I16: 95 | J16: =IF(G16="RSL","55","0") -> 0 | K16: =IF(G16="GVS","37.5",IF(G16="GVM","41.5",IF(G16="GVL","50",IF(G16="PCS","45.8",IF(G16="PCM","50",IF(G16="PCL","58.3","0")))))) -> 0 | N16: HENDRA | R16: =H32/U16 -> 0.45454545 | S16: =H32/(U16-U5) -> 0.57142857 | T16: =C32/U16 -> 40.227273 | U16: =SUM(U5:U15) -> 44 | Y16: 12 | AD16: 27 | AJ16: 12 | AO16: 27
A17: 13 | B17: 4240 | C17: ENV72Z | D17: 0409829032 | E17: M | F17: 1200 | G17: D | I17: 55 | J17: =IF(G17="RSL","55","0") -> 0 | K17: =IF(G17="GVS","37.5",IF(G17="GVM","41.5",IF(G17="GVL","50",IF(G17="PCS","45.8",IF(G17="PCM","50",IF(G17="PCL","58.3","0")))))) -> 0 | N17: HENDRA | R17: Cars/T Hr ① | S17: Cars/T Hr ② | T17: Sales/T Hr | U17: Total Hours | Y17: 13 | AD17: 28 | AJ17: 13 | AO17: 28
A18: 14 | B18: 4241 | C18: DVP26J | D18: 0433875588 | E18: F | F18: 1200 | G18: H | I18: 150 | J18: =IF(G18="RSL","55","0") -> 0 | K18: =IF(G18="GVS","37.5",IF(G18="GVM","41.5",IF(G18="GVL","50",IF(G18="PCS","45.8",IF(G18="PCM","50",IF(G18="PCL","58.3","0")))))) -> 0 | M18: 475 | N18: HENDRA | O18: PCL 22030 | R18: ITEM | S18: QTY | T18: AMT | U18: RMKS | Y18: 14 | AD18: 29 | AJ18: 14 | AO18: 29
A19: 15 | B19: 4242 | C19: GBI | D19: 0415888891 | E19: M | F19: 1210 | G19: H | I19: 150 | J19: =IF(G19="RSL","55","0") -> 0 | K19: =IF(G19="GVS","37.5",IF(G19="GVM","41.5",IF(G19="GVL","50",IF(G19="PCS","45.8",IF(G19="PCM","50",IF(G19="PCL","58.3","0")))))) -> 0 | N19: HENDRA | O19: GEORGE CAR | R19: GV | S19: =COUNT(L5:M29,L37:M61,L69:M93) -> 1 | T19: =SUM(L5:M29,L37:M61,L69:M93) -> 475 | Y19: 15 | AD19: 30 | AJ19: 15 | AO19: 30
A20: 16 | B20: 4243 | C20: DZC70W | D20: 0402919656 | E20: F | F20: 1245 | G20: D | I20: 90 | J20: =IF(G20="RSL","55","0") -> 0 | K20: =IF(G20="GVS","37.5",IF(G20="GVM","41.5",IF(G20="GVL","50",IF(G20="PCS","45.8",IF(G20="PCM","50",IF(G20="PCL","58.3","0")))))) -> 0 | N20: HENDRA | AD20: 31 | AO20: 31
A21: 17 | B21: 4244 | C21: ELL66R | D21: 0451788868 | E21: F | F21: 1245 | G21: D | I21: 55 | J21: =IF(G21="RSL","55","0") -> 0 | K21: =IF(G21="GVS","37.5",IF(G21="GVM","41.5",IF(G21="GVL","50",IF(G21="PCS","45.8",IF(G21="PCM","50",IF(G21="PCL","58.3","0")))))) -> 0 | N21: HENDRA
A22: 18 | B22: 4245 | C22: CVV55M | D22: 0422641661 | E22: F | F22: 1430 | G22: D/ST | I22: 250 | J22: =IF(G22="RSL","55","0") -> 0 | K22: =IF(G22="GVS","37.5",IF(G22="GVM","41.5",IF(G22="GVL","50",IF(G22="PCS","45.8",IF(G22="PCM","50",IF(G22="PCL","58.3","0")))))) -> 0 | N22: HENDRA | O22: SMALL | AD22: Total | AE22: =SUM(Z5:Z19,AE5:AE20) -> 0 | AF22: =SUM(AA5:AA19,AF5:AF20,) -> 0 | AG22: =SUM(AB5:AB19,AG5:AG20) -> 0 | AO22: Total | AP22: =SUM(AK5:AK19,AP5:AP20) -> 0 | AQ22: =SUM(AL5:AL19,AQ5:AQ20,) -> 0 | AR22: =SUM(AM5:AM19,AR5:AR20) -> 0
A23: 19 | B23: 4246 | C23: EMW16A | D23: 0430431137 | E23: F | F23: 1445 | G23: X | I23: 95 | J23: =IF(G23="RSL","55","0") -> 0 | K23: =IF(G23="GVS","37.5",IF(G23="GVM","41.5",IF(G23="GVL","50",IF(G23="PCS","45.8",IF(G23="PCM","50",IF(G23="PCL","58.3","0")))))) -> 0 | N23: HENDRA
A24: 20 | B24: 4247 | C24: EBZ970 | D24: ???? | E24: M | F24: 1530 | G24: W/O | I24: 55 | J24: =IF(G24="RSL","55","0") -> 0 | K24: =IF(G24="GVS","37.5",IF(G24="GVM","41.5",IF(G24="GVL","50",IF(G24="PCS","45.8",IF(G24="PCM","50",IF(G24="PCL","58.3","0")))))) -> 0 | N24: HENDRA | R24: SMALL | S24: MEDIUM | T24: LARGE | U24: TOTAL | AD24: B2/GA TOTAL | AE24: B2 machine | AF24: GA machine | AG24: BLH machine | AH24: Wongo machine | AI24: Sub total
A25: 21 | J25: =IF(G25="RSL","55","0") -> 0 | K25: =IF(G25="GVS","37.5",IF(G25="GVM","41.5",IF(G25="GVL","50",IF(G25="PCS","45.8",IF(G25="PCM","50",IF(G25="PCL","58.3","0")))))) -> 0 | R25: =COUNTIF(G5:G29,"GV1")+COUNTIF(G37:G61,"GV1")+COUNTIF(G69:G93,"GV1") -> 0 | S25: =COUNTIF(G5:G29,"GV2")+COUNTIF(G37:G61,"GV2")+COUNTIF(G69:G93,"GV2") -> 0 | T25: =COUNTIF(G5:G29,"GV3")+COUNTIF(G37:G61,"GV3")+COUNTIF(G69:G93,"GV3") -> 0 | U25: =((C32+(R26+S26+T26)*0.5)) -> 1770 | AD25: =SUM(AE25:AF25) -> 0 | AE25: =SUM(AE22) -> 0 | AF25: =SUM(AP22) -> 0 | AG25: =SUM(AF22+AQ22) -> 0 | AH25: =AG22+AR22 -> 0 | AI25: =SUM(AE25:AH25) -> 0
A26: 22 | J26: =IF(G26="RSL","55","0") -> 0 | K26: =IF(G26="GVS","37.5",IF(G26="GVM","41.5",IF(G26="GVL","50",IF(G26="PCS","45.8",IF(G26="PCM","50",IF(G26="PCL","58.3","0")))))) -> 0 | R26: =R25*37.5 -> 0 | S26: =S25*41.5 -> 0 | T26: =T25*50 -> 0 | X26: Branch cards
A27: 23 | J27: =IF(G27="RSL","55","0") -> 0 | K27: =IF(G27="GVS","37.5",IF(G27="GVM","41.5",IF(G27="GVL","50",IF(G27="PCS","45.8",IF(G27="PCM","50",IF(G27="PCL","58.3","0")))))) -> 0 | R27: Expense | X27: 1 | Z27: -2745
A28: 24 | J28: =IF(G28="RSL","55","0") -> 0 | K28: =IF(G28="GVS","37.5",IF(G28="GVM","41.5",IF(G28="GVL","50",IF(G28="PCS","45.8",IF(G28="PCM","50",IF(G28="PCL","58.3","0")))))) -> 0 | R28: KUROSH SICK GO HOME EARLY | X28: 2
A29: 25 | J29: =IF(G29="RSL","55","0") -> 0 | K29: =IF(G29="GVS","37.5",IF(G29="GVM","41.5",IF(G29="GVL","50",IF(G29="PCS","45.8",IF(G29="PCM","50",IF(G29="PCL","58.3","0")))))) -> 0 | X29: 3
A30: Page total | H30: =SUM(H5:H29) -> 75 | I30: =SUM(I5:I29) -> 1515 | J30: =J5+J6+J7+J8+J9+J10+J11+J12+J13+J14+J15+J16+J18+J19+J17+J20+J22+J23+J21+J24+J25+J26+J27+J28+J29 -> 55 | K30: =K5+K6+K7+K8+K9+K10+K11+K12+K13+K14+K15+K16+K18+K19+K17+K20+K22+K23+K21+K24+K25+K26+K27+K28+K29 -> 125 | L30: =SUM(L5:L29) -> 0 | M30: =SUM(M5:M29) -> 475 | N30: CASH | O30: CARD | P30: GV | Q30: RSL | X30: 4
A31: Daily Total | H31: =H30+H62+H94 -> 75 | I31: =I30+I62+I94 -> 1515 | J31: =J30+J62+J94 -> 55 | K31: =K30+K62+K94 -> 125 | L31: =L30+L62+L94 -> 0 | M31: =M30+M62+M94 -> 475 | N31: =COUNT(H5:H29,H37:H61,H69:H93) -> 1 | O31: =COUNT(I5:I29,I37:I61,I69:I93) -> 16 | P31: =COUNTIF(G5:G29,"G*")+COUNTIF(G37:G61,"G*")+COUNTIF(G69:G93,"G*")+COUNTIF(G5:G29,"P*")+COUNTIF(G37:G61,"P*")+COUNTIF(G69:G93,"P*") -> 2 | Q31: =COUNTIF(G5:G29,"RSL")+COUNTIF(G37:G61,"RSL")+COUNTIF(G69:G93,"RSL") -> 1 | R31: CASH CLOSING | S31: =H31+L31-U28-U29-U30 -> 75 | T31: =H31+I31+L31+M31 -> 2065 | X31: Subtotal | Z31: =SUM(Z27:Z30) -> -2745
A32: TOTAL SALES | C32: =H31+I31+J31+K31 -> 1770 | F32: No of Cars | H32: =COUNT(B5:B29,B37:B61,B69:B93) -> 20 | I32: Average | K32: =C32/H32 -> 88.5 | N32: =H31/C32 -> 0.042372881 | O32: =I31/C32 -> 0.8559322 | P32: =K31/C32 -> 0.070621469 | Q32: =J31/C32 -> 0.031073446 | R32: CARD CLOSING | S32: =I31+M31 -> 1990 | X32: B2 card | Z32: =I31 -> 1515
A33: Daily Report | X33: Settlement | Z33: =SUM(Z31:Z32) -> -1230
A34: =A2 -> 19 - 5 - 2022 | H34: WEATHER | J34: =J2 -> SUNNY | L34: REPORT by | O34: =O2 -> HENDRA | R34: TOTAL STAFF | T34: =T2 -> 6
A36: No | B36: Docket No | C36: Reg No | D36: Mobile | E36: Gender | F36: TIME | G36: Service | H36: CASH | I36: CARD | J36: RSL | K36: GV | L36: GV CASH | M36: GV CARD | N36: O/Taker | O36: Comment | R36: NAME | S36: Time In | T36: Time out | U36: Total Hours
A37: =A29+1 -> 26 | J37: =IF(G37="RSL","55","0") -> 0 | K37: =IF(G37="GVS","37.5",IF(G37="GVM","41.5",IF(G37="GVL","50",IF(G37="PCS","45.8",IF(G37="PCM","50",IF(G37="PCL","58.3","0")))))) -> 0
A38: =A37+1 -> 27 | J38: =IF(G38="RSL","55","0") -> 0 | K38: =IF(G38="GVS","37.5",IF(G38="GVM","41.5",IF(G38="GVL","50",IF(G38="PCS","45.8",IF(G38="PCM","50",IF(G38="PCL","58.3","0")))))) -> 0
A39: =A38+1 -> 28 | J39: =IF(G39="RSL","55","0") -> 0 | K39: =IF(G39="GVS","37.5",IF(G39="GVM","41.5",IF(G39="GVL","50",IF(G39="PCS","45.8",IF(G39="PCM","50",IF(G39="PCL","58.3","0")))))) -> 0
A40: =A39+1 -> 29 | J40: =IF(G40="RSL","55","0") -> 0 | K40: =IF(G40="GVS","37.5",IF(G40="GVM","41.5",IF(G40="GVL","50",IF(G40="PCS","45.8",IF(G40="PCM","50",IF(G40="PCL","58.3","0")))))) -> 0
A41: =A40+1 -> 30 | J41: =IF(G41="RSL","55","0") -> 0 | K41: =IF(G41="GVS","37.5",IF(G41="GVM","41.5",IF(G41="GVL","50",IF(G41="PCS","45.8",IF(G41="PCM","50",IF(G41="PCL","58.3","0")))))) -> 0
A42: =A41+1 -> 31 | J42: =IF(G42="RSL","55","0") -> 0 | K42: =IF(G42="GVS","37.5",IF(G42="GVM","41.5",IF(G42="GVL","50",IF(G42="PCS","45.8",IF(G42="PCM","50",IF(G42="PCL","58.3","0")))))) -> 0
A43: =A42+1 -> 32 | J43: =IF(G43="RSL","55","0") -> 0 | K43: =IF(G43="GVS","37.5",IF(G43="GVM","41.5",IF(G43="GVL","50",IF(G43="PCS","45.8",IF(G43="PCM","50",IF(G43="PCL","58.3","0")))))) -> 0
A44: =A43+1 -> 33 | J44: =IF(G44="RSL","55","0") -> 0 | K44: =IF(G44="GVS","37.5",IF(G44="GVM","41.5",IF(G44="GVL","50",IF(G44="PCS","45.8",IF(G44="PCM","50",IF(G44="PCL","58.3","0")))))) -> 0
A45: =A44+1 -> 34 | J45: =IF(G45="RSL","55","0") -> 0 | K45: =IF(G45="GVS","37.5",IF(G45="GVM","41.5",IF(G45="GVL","50",IF(G45="PCS","45.8",IF(G45="PCM","50",IF(G45="PCL","58.3","0")))))) -> 0
A46: =A45+1 -> 35 | J46: =IF(G46="RSL","55","0") -> 0 | K46: =IF(G46="GVS","37.5",IF(G46="GVM","41.5",IF(G46="GVL","50",IF(G46="PCS","45.8",IF(G46="PCM","50",IF(G46="PCL","58.3","0")))))) -> 0
A47: =A46+1 -> 36 | J47: =IF(G47="RSL","55","0") -> 0 | K47: =IF(G47="GVS","37.5",IF(G47="GVM","41.5",IF(G47="GVL","50",IF(G47="PCS","45.8",IF(G47="PCM","50",IF(G47="PCL","58.3","0")))))) -> 0
A48: =A47+1 -> 37 | J48: =IF(G48="RSL","55","0") -> 0 | K48: =IF(G48="GVS","37.5",IF(G48="GVM","41.5",IF(G48="GVL","50",IF(G48="PCS","45.8",IF(G48="PCM","50",IF(G48="PCL","58.3","0")))))) -> 0
A49: =A48+1 -> 38 | J49: =IF(G49="RSL","55","0") -> 0 | K49: =IF(G49="GVS","37.5",IF(G49="GVM","41.5",IF(G49="GVL","50",IF(G49="PCS","45.8",IF(G49="PCM","50",IF(G49="PCL","58.3","0")))))) -> 0
... A61: =A60+1 -> 50 | J61: =IF(G61="RSL","55","0") -> 0 | K61: =IF(G61="GVS","37.5",IF(G61="GVM","41.5",IF(G61="GVL","50",IF(G61="PCS","45.8",IF(G61="PCM","50",IF(G61="PCL","58.3","0")))))) -> 0
A62: Page total | H62: =SUM(H37:H61) -> 0 | I62: =SUM(I37:I61) -> 0 | J62: =J61+J60+J59+J58+J57+J56+J55+J54+J53+J52+J51+J50+J49+J48+J47+J46+J45+J44+J43+J42+J41+J40+J39+J38+J37 -> 0 | K62: =K61+K60+K59+K58+K57+K56+K55+K54+K53+K52+K51+K50+K49+K48+K47+K46+K45+K44+K43+K42+K41+K40+K39+K38+K37 -> 0 | L62: =SUM(L37:L61) -> 0 | M62: =SUM(M37:M61) -> 0
R64: Page: 2
A65: Daily Report
A66: =A34 -> 19 - 5 - 2022 | H66: WEATHER | J66: =J34 -> SUNNY | L66: REPORT by | O66: =O34 -> HENDRA | R66: TOTAL STAFF | T66: =T34 -> 6
A68: No | B68: Docket No | C68: Reg No | D68: Mobile | E68: Gender | F68: TIME | G68: Service | H68: CASH | I68: CARD | J68: RSL | K68: GV | L68: GV CASH | M68: GV CARD | N68: O/Taker | O68: Comment | R68: NAME | S68: Time In | T68: Time out | U68: Total Hours
A69: =A61+1 -> 51 | J69: =IF(G69="RSL","55","0") -> 0 | K69: =IF(G69="GVS","37.5",IF(G69="GVM","41.5",IF(G69="GVL","50",IF(G69="PCS","45.8",IF(G69="PCM","50",IF(G69="PCL","58.3","0")))))) -> 0
A70: =A69+1 -> 52 | J70: =IF(G70="RSL","55","0") -> 0 | K70: =IF(G70="GVS","37.5",IF(G70="GVM","41.5",IF(G70="GVL","50",IF(G70="PCS","45.8",IF(G70="PCM","50",IF(G70="PCL","58.3","0")))))) -> 0
A71: =A70+1 -> 53 | J71: =IF(G71="RSL","55","0") -> 0 | K71: =IF(G71="GVS","37.5",IF(G71="GVM","41.5",IF(G71="GVL","50",IF(G71="PCS","45.8",IF(G71="PCM","50",IF(G71="PCL","58.3","0")))))) -> 0
A72: =A71+1 -> 54 | J72: =IF(G72="RSL","55","0") -> 0 | K72: =IF(G72="GVS","37.5",IF(G72="GVM","41.5",IF(G72="GVL","50",IF(G72="PCS","45.8",IF(G72="PCM","50",IF(G72="PCL","58.3","0")))))) -> 0
A73: =A72+1 -> 55 | J73: =IF(G73="RSL","55","0") -> 0 | K73: =IF(G73="GVS","37.5",IF(G73="GVM","41.5",IF(G73="GVL","50",IF(G73="PCS","45.8",IF(G73="PCM","50",IF(G73="PCL","58.3","0")))))) -> 0
A74: =A73+1 -> 56 | J74: =IF(G74="RSL","55","0") -> 0 | K74: =IF(G74="GVS","37.5",IF(G74="GVM","41.5",IF(G74="GVL","50",IF(G74="PCS","45.8",IF(G74="PCM","50",IF(G74="PCL","58.3","0")))))) -> 0
A75: =A74+1 -> 57 | J75: =IF(G75="RSL","55","0") -> 0 | K75: =IF(G75="GVS","37.5",IF(G75="GVM","41.5",IF(G75="GVL","50",IF(G75="PCS","45.8",IF(G75="PCM","50",IF(G75="PCL","58.3","0")))))) -> 0
A76: =A75+1 -> 58 | J76: =IF(G76="RSL","55","0") -> 0 | K76: =IF(G76="GVS","37.5",IF(G76="GVM","41.5",IF(G76="GVL","50",IF(G76="PCS","45.8",IF(G76="PCM","50",IF(G76="PCL","58.3","0")))))) -> 0
A77: =A76+1 -> 59 | J77: =IF(G77="RSL","55","0") -> 0 | K77: =IF(G77="GVS","37.5",IF(G77="GVM","41.5",IF(G77="GVL","50",IF(G77="PCS","45.8",IF(G77="PCM","50",IF(G77="PCL","58.3","0")))))) -> 0
A78: =A77+1 -> 60 | J78: =IF(G78="RSL","55","0") -> 0 | K78: =IF(G78="GVS","37.5",IF(G78="GVM","41.5",IF(G78="GVL","50",IF(G78="PCS","45.8",IF(G78="PCM","50",IF(G78="PCL","58.3","0")))))) -> 0
A79: =A78+1 -> 61 | J79: =IF(G79="RSL","55","0") -> 0 | K79: =IF(G79="GVS","37.5",IF(G79="GVM","41.5",IF(G79="GVL","50",IF(G79="PCS","45.8",IF(G79="PCM","50",IF(G79="PCL","58.3","0")))))) -> 0
A80: =A79+1 -> 62 | J80: =IF(G80="RSL","55","0") -> 0 | K80: =IF(G80="GVS","37.5",IF(G80="GVM","41.5",IF(G80="GVL","50",IF(G80="PCS","45.8",IF(G80="PCM","50",IF(G80="PCL","58.3","0")))))) -> 0
A81: =A80+1 -> 63 | J81: =IF(G81="RSL","55","0") -> 0 | K81: =IF(G81="GVS","37.5",IF(G81="GVM","41.5",IF(G81="GVL","50",IF(G81="PCS","45.8",IF(G81="PCM","50",IF(G81="PCL","58.3","0")))))) -> 0
... A93: =A92+1 -> 75 | J93: =IF(G93="RSL","55","0") -> 0 | K93: =IF(G93="GVS","37.5",IF(G93="GVM","41.5",IF(G93="GVL","50",IF(G93="PCS","45.8",IF(G93="PCM","50",IF(G93="PCL","58.3","0")))))) -> 0
A94: Page total | H94: =SUM(H69:H93) -> 0 | I94: =SUM(I69:I93) -> 0 | J94: =J93+J92+J91+J90+J89+J88+J87+J86+J85+J84+J83+J82+J81+J80+J79+J78+J77+J76+J75+J74+J73+J72+J71+J70+J69 -> 0 | K94: =K93+K92+K91+K90+K89+K88+K87+K86+K85+K84+K83+K82+K81+K80+K79+K78+K77+K76+K75+K74+K73+K72+K71+K70+K69 -> 0 | L94: =SUM(L69:L93) -> 0 | M94: =SUM(M69:M93) -> 0
R96: Page: 3

Sheet FRI
A1: B2 Daily Report
A2: 20/05 / 2022 | H2: WEATHER | J2: RAIN | L2: REPORT BY | O2: HENDRA | R2: TOTAL STAFF | T2: 4 | X2: Merchant machine usage at B2 | AA2: Settle amount | AI2: Merchant machine usage at GA | AL2: Settle amount
A4: No | B4: Docket No | C4: Reg No | D4: Mobile | E4: Gender | F4: TIME | G4: Service | H4: CASH | I4: CARD | J4: RSL | K4: GV | L4: GV CASH | M4: GV CARD | N4: O/Taker | O4: Comment | R4: NAME | S4: Time In | T4: Time out | U4: Total Hours | Z4: B2 machine | AA4: BLH machine | AB4: Wongo | AE4: B2 machine | AF4: BLH machine | AG4: Wongo | AK4: GA machine | AL4: BLH machine | AM4: Wongo | AP4: GA machine | AQ4: BLH machine | AR4: Wongo
A5: 1 | B5: 4248 | C5: EOG19M | D5: 0499630535 | E5: F | F5: 1030 | G5: D | I5: 75 | J5: =IF(G5="RSL","55","0") -> 0 | K5: =IF(G5="GVS","37.5",IF(G5="GVM","41.5",IF(G5="GVL","50",IF(G5="PCS","45.8",IF(G5="PCM","50",IF(G5="PCL","58.3","0")))))) -> 0 | N5: HENDRA | R5: HENDRA | S5: 0.33333333 | T5: 0.67708333 | U5: =(T5-S5)*24 -> 8.25 | X5: NOV | Y5: 1 | AD5: 16 | AI5: NOV | AJ5: 1 | AO5: 16
A6: 2 | B6: 4249 | C6: DQR27A | D6: 0419487797 | E6: F | F6: 1040 | G6: X | I6: 95 | J6: =IF(G6="RSL","55","0") -> 0 | K6: =IF(G6="GVS","37.5",IF(G6="GVM","41.5",IF(G6="GVL","50",IF(G6="PCS","45.8",IF(G6="PCM","50",IF(G6="PCL","58.3","0")))))) -> 0 | N6: HENDRA | R6: JUNIOR | S6: 0.33333333 | T6: 0.67708333 | U6: =(T6-S6)*24 -> 8.25 | W6: M | Y6: 2 | AD6: 17 | AJ6: 2 | AO6: 17
A7: 3 | B7: 4250 | C7: CXT85G | D7: 0434688628 | E7: F | F7: 1305 | G7: X | H7: 75 | J7: =IF(G7="RSL","55","0") -> 0 | K7: =IF(G7="GVS","37.5",IF(G7="GVM","41.5",IF(G7="GVL","50",IF(G7="PCS","45.8",IF(G7="PCM","50",IF(G7="PCL","58.3","0")))))) -> 0 | N7: VINNY | R7: VINNY | S7: 0.42708333 | T7: 0.67708333 | U7: =(T7-S7)*24 -> 6 | W7: F | Y7: 3 | AD7: 18 | AJ7: 3 | AO7: 18
A8: 4 | B8: 4251 | C8: NBO33G | D8: 0419498299 | E8: M | F8: 1315 | G8: D | I8: 75 | J8: =IF(G8="RSL","55","0") -> 0 | K8: =IF(G8="GVS","37.5",IF(G8="GVM","41.5",IF(G8="GVL","50",IF(G8="PCS","45.8",IF(G8="PCM","50",IF(G8="PCL","58.3","0")))))) -> 0 | N8: HENDRA | R8: STEVE | S8: 0.375 | T8: 0.54166667 | U8: =(T8-S8)*24 -> 4 | Y8: 4 | AD8: 19 | AJ8: 4 | AO8: 19
A9: 5 | B9: 4252 | C9: EPV24R | D9: 0424962456 | E9: F | F9: 1430 | G9: X | I9: 75 | J9: =IF(G9="RSL","55","0") -> 0 | K9: =IF(G9="GVS","37.5",IF(G9="GVM","41.5",IF(G9="GVL","50",IF(G9="PCS","45.8",IF(G9="PCM","50",IF(G9="PCL","58.3","0")))))) -> 0 | N9: HENDRA | R9: CHARLIE | S9: 0.625 | T9: 0.66666667 | U9: =(T9-S9)*24 -> 1 | X9: EXCL RSL | Y9: 5 | AD9: 20 | AJ9: 5 | AO9: 20
A10: 6 | B10: 4253 | C10: ENI58P | D10: 0418263227 | E10: F | F10: 1500 | G10: D | I10: 70 | J10: =IF(G10="RSL","55","0") -> 0 | K10: =IF(G10="GVS","37.5",IF(G10="GVM","41.5",IF(G10="GVL","50",IF(G10="PCS","45.8",IF(G10="PCM","50",IF(G10="PCL","58.3","0")))))) -> 0 | N10: HENDRA | U10: =(T10-S10)*24 -> 0 | Y10: 6 | AD10: 21 | AJ10: 6 | AO10: 21
A11: 7 | J11: =IF(G11="RSL","55","0") -> 0 | K11: =IF(G11="GVS","37.5",IF(G11="GVM","41.5",IF(G11="GVL","50",IF(G11="PCS","45.8",IF(G11="PCM","50",IF(G11="PCL","58.3","0")))))) -> 0 | U11: =(T11-S11)*24 -> 0 | Y11: 7 | AD11: 22 | AJ11: 7 | AO11: 22
A12: 8 | J12: =IF(G12="RSL","55","0") -> 0 | K12: =IF(G12="GVS","37.5",IF(G12="GVM","41.5",IF(G12="GVL","50",IF(G12="PCS","45.8",IF(G12="PCM","50",IF(G12="PCL","58.3","0")))))) -> 0 | U12: =(T12-S12)*24 -> 0 | Y12: 8 | AD12: 23 | AJ12: 8 | AO12: 23
A13: 9 | J13: =IF(G13="RSL","55","0") -> 0 | K13: =IF(G13="GVS","37.5",IF(G13="GVM","41.5",IF(G13="GVL","50",IF(G13="PCS","45.8",IF(G13="PCM","50",IF(G13="PCL","58.3","0")))))) -> 0 | U13: =(T13-S13)*24 -> 0 | Y13: 9 | AD13: 24 | AJ13: 9 | AO13: 24
A14: 10 | J14: =IF(G14="RSL","55","0") -> 0 | K14: =IF(G14="GVS","37.5",IF(G14="GVM","41.5",IF(G14="GVL","50",IF(G14="PCS","45.8",IF(G14="PCM","50",IF(G14="PCL","58.3","0")))))) -> 0 | U14: =(T14-S14)*24 -> 0 | Y14: 10 | AD14: 25 | AJ14: 10 | AO14: 25
A15: 11 | J15: =IF(G15="RSL","55","0") -> 0 | K15: =IF(G15="GVS","37.5",IF(G15="GVM","41.5",IF(G15="GVL","50",IF(G15="PCS","45.8",IF(G15="PCM","50",IF(G15="PCL","58.3","0")))))) -> 0 | U15: =(T15-S15)*24 -> 0 | Y15: 11 | AD15: 26 | AJ15: 11 | AO15: 26
A16: 12 | J16: =IF(G16="RSL","55","0") -> 0 | K16: =IF(G16="GVS","37.5",IF(G16="GVM","41.5",IF(G16="GVL","50",IF(G16="PCS","45.8",IF(G16="PCM","50",IF(G16="PCL","58.3","0")))))) -> 0 | R16: =H32/U16 -> 0.21818182 | S16: =H32/(U16-U5) -> 0.31168831 | T16: =C32/U16 -> 16.909091 | U16: =SUM(U5:U15) -> 27.5 | Y16: 12 | AD16: 27 | AJ16: 12 | AO16: 27
A17: 13 | J17: =IF(G17="RSL","55","0") -> 0 | K17: =IF(G17="GVS","37.5",IF(G17="GVM","41.5",IF(G17="GVL","50",IF(G17="PCS","45.8",IF(G17="PCM","50",IF(G17="PCL","58.3","0")))))) -> 0 | R17: Cars/T Hr ① | S17: Cars/T Hr ② | T17: Sales/T Hr | U17: Total Hours | Y17: 13 | AD17: 28 | AJ17: 13 | AO17: 28
A18: 14 | J18: =IF(G18="RSL","55","0") -> 0 | K18: =IF(G18="GVS","37.5",IF(G18="GVM","41.5",IF(G18="GVL","50",IF(G18="PCS","45.8",IF(G18="PCM","50",IF(G18="PCL","58.3","0")))))) -> 0 | R18: ITEM | S18: QTY | T18: AMT | U18: RMKS | Y18: 14 | AD18: 29 | AJ18: 14 | AO18: 29
A19: 15 | J19: =IF(G19="RSL","55","0") -> 0 | K19: =IF(G19="GVS","37.5",IF(G19="GVM","41.5",IF(G19="GVL","50",IF(G19="PCS","45.8",IF(G19="PCM","50",IF(G19="PCL","58.3","0")))))) -> 0 | R19: GV | S19: =COUNT(L5:M29,L37:M61,L69:M93) -> 0 | T19: =SUM(L5:M29,L37:M61,L69:M93) -> 0 | Y19: 15 | AD19: 30 | AJ19: 15 | AO19: 30
A20: 16 | J20: =IF(G20="RSL","55","0") -> 0 | K20: =IF(G20="GVS","37.5",IF(G20="GVM","41.5",IF(G20="GVL","50",IF(G20="PCS","45.8",IF(G20="PCM","50",IF(G20="PCL","58.3","0")))))) -> 0 | AD20: 31 | AO20: 31
A21: 17 | J21: =IF(G21="RSL","55","0") -> 0 | K21: =IF(G21="GVS","37.5",IF(G21="GVM","41.5",IF(G21="GVL","50",IF(G21="PCS","45.8",IF(G21="PCM","50",IF(G21="PCL","58.3","0")))))) -> 0
A22: 18 | J22: =IF(G22="RSL","55","0") -> 0 | K22: =IF(G22="GVS","37.5",IF(G22="GVM","41.5",IF(G22="GVL","50",IF(G22="PCS","45.8",IF(G22="PCM","50",IF(G22="PCL","58.3","0")))))) -> 0 | AD22: Total | AE22: =SUM(Z5:Z19,AE5:AE20) -> 0 | AF22: =SUM(AA5:AA19,AF5:AF20,) -> 0 | AG22: =SUM(AB5:AB19,AG5:AG20) -> 0 | AO22: Total | AP22: =SUM(AK5:AK19,AP5:AP20) -> 0 | AQ22: =SUM(AL5:AL19,AQ5:AQ20,) -> 0 | AR22: =SUM(AM5:AM19,AR5:AR20) -> 0
A23: 19 | J23: =IF(G23="RSL","55","0") -> 0 | K23: =IF(G23="GVS","37.5",IF(G23="GVM","41.5",IF(G23="GVL","50",IF(G23="PCS","45.8",IF(G23="PCM","50",IF(G23="PCL","58.3","0")))))) -> 0
A24: 20 | J24: =IF(G24="RSL","55","0") -> 0 | K24: =IF(G24="GVS","37.5",IF(G24="GVM","41.5",IF(G24="GVL","50",IF(G24="PCS","45.8",IF(G24="PCM","50",IF(G24="PCL","58.3","0")))))) -> 0 | R24: SMALL | S24: MEDIUM | T24: LARGE | U24: TOTAL | AD24: B2/GA TOTAL | AE24: B2 machine | AF24: GA machine | AG24: BLH machine | AH24: Wongo machine | AI24: Sub total
A25: 21 | J25: =IF(G25="RSL","55","0") -> 0 | K25: =IF(G25="GVS","37.5",IF(G25="GVM","41.5",IF(G25="GVL","50",IF(G25="PCS","45.8",IF(G25="PCM","50",IF(G25="PCL","58.3","0")))))) -> 0 | R25: =COUNTIF(G5:G29,"GV1")+COUNTIF(G37:G61,"GV1")+COUNTIF(G69:G93,"GV1") -> 0 | S25: =COUNTIF(G5:G29,"GV2")+COUNTIF(G37:G61,"GV2")+COUNTIF(G69:G93,"GV2") -> 0 | T25: =COUNTIF(G5:G29,"GV3")+COUNTIF(G37:G61,"GV3")+COUNTIF(G69:G93,"GV3") -> 0 | U25: =((C32+(R26+S26+T26)*0.5)) -> 465 | AD25: =SUM(AE25:AF25) -> 0 | AE25: =SUM(AE22) -> 0 | AF25: =SUM(AP22) -> 0 | AG25: =SUM(AF22+AQ22) -> 0 | AH25: =AG22+AR22 -> 0 | AI25: =SUM(AE25:AH25) -> 0
A26: 22 | J26: =IF(G26="RSL","55","0") -> 0 | K26: =IF(G26="GVS","37.5",IF(G26="GVM","41.5",IF(G26="GVL","50",IF(G26="PCS","45.8",IF(G26="PCM","50",IF(G26="PCL","58.3","0")))))) -> 0 | R26: =R25*37.5 -> 0 | S26: =S25*41.5 -> 0 | T26: =T25*50 -> 0 | X26: Branch cards
A27: 23 | J27: =IF(G27="RSL","55","0") -> 0 | K27: =IF(G27="GVS","37.5",IF(G27="GVM","41.5",IF(G27="GVL","50",IF(G27="PCS","45.8",IF(G27="PCM","50",IF(G27="PCL","58.3","0")))))) -> 0 | R27: Expense | X27: 1 | Z27: -2745
A28: 24 | J28: =IF(G28="RSL","55","0") -> 0 | K28: =IF(G28="GVS","37.5",IF(G28="GVM","41.5",IF(G28="GVL","50",IF(G28="PCS","45.8",IF(G28="PCM","50",IF(G28="PCL","58.3","0")))))) -> 0 | X28: 2
A29: 25 | J29: =IF(G29="RSL","55","0") -> 0 | K29: =IF(G29="GVS","37.5",IF(G29="GVM","41.5",IF(G29="GVL","50",IF(G29="PCS","45.8",IF(G29="PCM","50",IF(G29="PCL","58.3","0")))))) -> 0 | X29: 3
A30: Page total | H30: =SUM(H5:H29) -> 75 | I30: =SUM(I5:I29) -> 390 | J30: =J5+J6+J7+J8+J9+J10+J11+J12+J13+J14+J15+J16+J18+J19+J17+J20+J22+J23+J21+J24+J25+J26+J27+J28+J29 -> 0 | K30: =K5+K6+K7+K8+K9+K10+K11+K12+K13+K14+K15+K16+K18+K19+K17+K20+K22+K23+K21+K24+K25+K26+K27+K28+K29 -> 0 | L30: =SUM(L5:L29) -> 0 | M30: =SUM(M5:M29) -> 0 | N30: CASH | O30: CARD | P30: GV | Q30: RSL | X30: 4
A31: Daily Total | H31: =H30+H62+H94 -> 75 | I31: =I30+I62+I94 -> 390 | J31: =J30+J62+J94 -> 0 | K31: =K30+K62+K94 -> 0 | L31: =L30+L62+L94 -> 0 | M31: =M30+M62+M94 -> 0 | N31: =COUNT(H5:H29,H37:H61,H69:H93) -> 1 | O31: =COUNT(I5:I29,I37:I61,I69:I93) -> 5 | P31: =COUNTIF(G5:G29,"G*")+COUNTIF(G37:G61,"G*")+COUNTIF(G69:G93,"G*")+COUNTIF(G5:G29,"P*")+COUNTIF(G37:G61,"P*")+COUNTIF(G69:G93,"P*") -> 0 | Q31: =COUNTIF(G5:G29,"RSL")+COUNTIF(G37:G61,"RSL")+COUNTIF(G69:G93,"RSL") -> 0 | R31: CASH CLOSING | S31: =H31+L31-U28-U29-U30 -> 75 | T31: =H31+I31+L31+M31 -> 465 | X31: Subtotal | Z31: =SUM(Z27:Z30) -> -2745
A32: TOTAL SALES | C32: =H31+I31+J31+K31 -> 465 | F32: No of Cars | H32: =COUNT(B5:B29,B37:B61,B69:B93) -> 6 | I32: Average | K32: =C32/H32 -> 77.5 | N32: =H31/C32 -> 0.16129032 | O32: =I31/C32 -> 0.83870968 | P32: =K31/C32 -> 0 | Q32: =J31/C32 -> 0 | R32: CARD CLOSING | S32: =I31+M31 -> 390 | X32: B2 card | Z32: =I31 -> 390
A33: Daily Report | X33: Settlement | Z33: =SUM(Z31:Z32) -> -2355
A34: =A2 -> 20/05 / 2022 | H34: WEATHER | J34: =J2 -> RAIN | L34: REPORT by | O34: =O2 -> HENDRA | R34: TOTAL STAFF | T34: =T2 -> 4
A36: No | B36: Docket No | C36: Reg No | D36: Mobile | E36: Gender | F36: TIME | G36: Service | H36: CASH | I36: CARD | J36: RSL | K36: GV | L36: GV CASH | M36: GV CARD | N36: O/Taker | O36: Comment | R36: NAME | S36: Time In | T36: Time out | U36: Total Hours
A37: =A29+1 -> 26 | J37: =IF(G37="RSL","55","0") -> 0 | K37: =IF(G37="GVS","37.5",IF(G37="GVM","41.5",IF(G37="GVL","50",IF(G37="PCS","45.8",IF(G37="PCM","50",IF(G37="PCL","58.3","0")))))) -> 0
A38: =A37+1 -> 27 | J38: =IF(G38="RSL","55","0") -> 0 | K38: =IF(G38="GVS","37.5",IF(G38="GVM","41.5",IF(G38="GVL","50",IF(G38="PCS","45.8",IF(G38="PCM","50",IF(G38="PCL","58.3","0")))))) -> 0
A39: =A38+1 -> 28 | J39: =IF(G39="RSL","55","0") -> 0 | K39: =IF(G39="GVS","37.5",IF(G39="GVM","41.5",IF(G39="GVL","50",IF(G39="PCS","45.8",IF(G39="PCM","50",IF(G39="PCL","58.3","0")))))) -> 0
A40: =A39+1 -> 29 | J40: =IF(G40="RSL","55","0") -> 0 | K40: =IF(G40="GVS","37.5",IF(G40="GVM","41.5",IF(G40="GVL","50",IF(G40="PCS","45.8",IF(G40="PCM","50",IF(G40="PCL","58.3","0")))))) -> 0
A41: =A40+1 -> 30 | J41: =IF(G41="RSL","55","0") -> 0 | K41: =IF(G41="GVS","37.5",IF(G41="GVM","41.5",IF(G41="GVL","50",IF(G41="PCS","45.8",IF(G41="PCM","50",IF(G41="PCL","58.3","0")))))) -> 0
A42: =A41+1 -> 31 | J42: =IF(G42="RSL","55","0") -> 0 | K42: =IF(G42="GVS","37.5",IF(G42="GVM","41.5",IF(G42="GVL","50",IF(G42="PCS","45.8",IF(G42="PCM","50",IF(G42="PCL","58.3","0")))))) -> 0
A43: =A42+1 -> 32 | J43: =IF(G43="RSL","55","0") -> 0 | K43: =IF(G43="GVS","37.5",IF(G43="GVM","41.5",IF(G43="GVL","50",IF(G43="PCS","45.8",IF(G43="PCM","50",IF(G43="PCL","58.3","0")))))) -> 0
A44: =A43+1 -> 33 | J44: =IF(G44="RSL","55","0") -> 0 | K44: =IF(G44="GVS","37.5",IF(G44="GVM","41.5",IF(G44="GVL","50",IF(G44="PCS","45.8",IF(G44="PCM","50",IF(G44="PCL","58.3","0")))))) -> 0
A45: =A44+1 -> 34 | J45: =IF(G45="RSL","55","0") -> 0 | K45: =IF(G45="GVS","37.5",IF(G45="GVM","41.5",IF(G45="GVL","50",IF(G45="PCS","45.8",IF(G45="PCM","50",IF(G45="PCL","58.3","0")))))) -> 0
A46: =A45+1 -> 35 | J46: =IF(G46="RSL","55","0") -> 0 | K46: =IF(G46="GVS","37.5",IF(G46="GVM","41.5",IF(G46="GVL","50",IF(G46="PCS","45.8",IF(G46="PCM","50",IF(G46="PCL","58.3","0")))))) -> 0
A47: =A46+1 -> 36 | J47: =IF(G47="RSL","55","0") -> 0 | K47: =IF(G47="GVS","37.5",IF(G47="GVM","41.5",IF(G47="GVL","50",IF(G47="PCS","45.8",IF(G47="PCM","50",IF(G47="PCL","58.3","0")))))) -> 0
A48: =A47+1 -> 37 | J48: =IF(G48="RSL","55","0") -> 0 | K48: =IF(G48="GVS","37.5",IF(G48="GVM","41.5",IF(G48="GVL","50",IF(G48="PCS","45.8",IF(G48="PCM","50",IF(G48="PCL","58.3","0")))))) -> 0
A49: =A48+1 -> 38 | J49: =IF(G49="RSL","55","0") -> 0 | K49: =IF(G49="GVS","37.5",IF(G49="GVM","41.5",IF(G49="GVL","50",IF(G49="PCS","45.8",IF(G49="PCM","50",IF(G49="PCL","58.3","0")))))) -> 0
... A61: =A60+1 -> 50 | J61: =IF(G61="RSL","55","0") -> 0 | K61: =IF(G61="GVS","37.5",IF(G61="GVM","41.5",IF(G61="GVL","50",IF(G61="PCS","45.8",IF(G61="PCM","50",IF(G61="PCL","58.3","0")))))) -> 0
A62: Page total | H62: =SUM(H37:H61) -> 0 | I62: =SUM(I37:I61) -> 0 | J62: =J61+J60+J59+J58+J57+J56+J55+J54+J53+J52+J51+J50+J49+J48+J47+J46+J45+J44+J43+J42+J41+J40+J39+J38+J37 -> 0 | K62: =K61+K60+K59+K58+K57+K56+K55+K54+K53+K52+K51+K50+K49+K48+K47+K46+K45+K44+K43+K42+K41+K40+K39+K38+K37 -> 0 | L62: =SUM(L37:L61) -> 0 | M62: =SUM(M37:M61) -> 0
R64: Page: 2
A65: Daily Report
A66: =A34 -> 20/05 / 2022 | H66: WEATHER | J66: =J34 -> RAIN | L66: REPORT by | O66: =O34 -> HENDRA | R66: TOTAL STAFF | T66: =T34 -> 4
A68: No | B68: Docket No | C68: Reg No | D68: Mobile | E68: Gender | F68: TIME | G68: Service | H68: CASH | I68: CARD | J68: RSL | K68: GV | L68: GV CASH | M68: GV CARD | N68: O/Taker | O68: Comment | R68: NAME | S68: Time In | T68: Time out | U68: Total Hours
A69: =A61+1 -> 51 | J69: =IF(G69="RSL","55","0") -> 0 | K69: =IF(G69="GVS","37.5",IF(G69="GVM","41.5",IF(G69="GVL","50",IF(G69="PCS","45.8",IF(G69="PCM","50",IF(G69="PCL","58.3","0")))))) -> 0
A70: =A69+1 -> 52 | J70: =IF(G70="RSL","55","0") -> 0 | K70: =IF(G70="GVS","37.5",IF(G70="GVM","41.5",IF(G70="GVL","50",IF(G70="PCS","45.8",IF(G70="PCM","50",IF(G70="PCL","58.3","0")))))) -> 0
A71: =A70+1 -> 53 | J71: =IF(G71="RSL","55","0") -> 0 | K71: =IF(G71="GVS","37.5",IF(G71="GVM","41.5",IF(G71="GVL","50",IF(G71="PCS","45.8",IF(G71="PCM","50",IF(G71="PCL","58.3","0")))))) -> 0
A72: =A71+1 -> 54 | J72: =IF(G72="RSL","55","0") -> 0 | K72: =IF(G72="GVS","37.5",IF(G72="GVM","41.5",IF(G72="GVL","50",IF(G72="PCS","45.8",IF(G72="PCM","50",IF(G72="PCL","58.3","0")))))) -> 0
A73: =A72+1 -> 55 | J73: =IF(G73="RSL","55","0") -> 0 | K73: =IF(G73="GVS","37.5",IF(G73="GVM","41.5",IF(G73="GVL","50",IF(G73="PCS","45.8",IF(G73="PCM","50",IF(G73="PCL","58.3","0")))))) -> 0
A74: =A73+1 -> 56 | J74: =IF(G74="RSL","55","0") -> 0 | K74: =IF(G74="GVS","37.5",IF(G74="GVM","41.5",IF(G74="GVL","50",IF(G74="PCS","45.8",IF(G74="PCM","50",IF(G74="PCL","58.3","0")))))) -> 0
A75: =A74+1 -> 57 | J75: =IF(G75="RSL","55","0") -> 0 | K75: =IF(G75="GVS","37.5",IF(G75="GVM","41.5",IF(G75="GVL","50",IF(G75="PCS","45.8",IF(G75="PCM","50",IF(G75="PCL","58.3","0")))))) -> 0
A76: =A75+1 -> 58 | J76: =IF(G76="RSL","55","0") -> 0 | K76: =IF(G76="GVS","37.5",IF(G76="GVM","41.5",IF(G76="GVL","50",IF(G76="PCS","45.8",IF(G76="PCM","50",IF(G76="PCL","58.3","0")))))) -> 0
A77: =A76+1 -> 59 | J77: =IF(G77="RSL","55","0") -> 0 | K77: =IF(G77="GVS","37.5",IF(G77="GVM","41.5",IF(G77="GVL","50",IF(G77="PCS","45.8",IF(G77="PCM","50",IF(G77="PCL","58.3","0")))))) -> 0
A78: =A77+1 -> 60 | J78: =IF(G78="RSL","55","0") -> 0 | K78: =IF(G78="GVS","37.5",IF(G78="GVM","41.5",IF(G78="GVL","50",IF(G78="PCS","45.8",IF(G78="PCM","50",IF(G78="PCL","58.3","0")))))) -> 0
A79: =A78+1 -> 61 | J79: =IF(G79="RSL","55","0") -> 0 | K79: =IF(G79="GVS","37.5",IF(G79="GVM","41.5",IF(G79="GVL","50",IF(G79="PCS","45.8",IF(G79="PCM","50",IF(G79="PCL","58.3","0")))))) -> 0
A80: =A79+1 -> 62 | J80: =IF(G80="RSL","55","0") -> 0 | K80: =IF(G80="GVS","37.5",IF(G80="GVM","41.5",IF(G80="GVL","50",IF(G80="PCS","45.8",IF(G80="PCM","50",IF(G80="PCL","58.3","0")))))) -> 0
A81: =A80+1 -> 63 | J81: =IF(G81="RSL","55","0") -> 0 | K81: =IF(G81="GVS","37.5",IF(G81="GVM","41.5",IF(G81="GVL","50",IF(G81="PCS","45.8",IF(G81="PCM","50",IF(G81="PCL","58.3","0")))))) -> 0
... A93: =A92+1 -> 75 | J93: =IF(G93="RSL","55","0") -> 0 | K93: =IF(G93="GVS","37.5",IF(G93="GVM","41.5",IF(G93="GVL","50",IF(G93="PCS","45.8",IF(G93="PCM","50",IF(G93="PCL","58.3","0")))))) -> 0
A94: Page total | H94: =SUM(H69:H93) -> 0 | I94: =SUM(I69:I93) -> 0 | J94: =J93+J92+J91+J90+J89+J88+J87+J86+J85+J84+J83+J82+J81+J80+J79+J78+J77+J76+J75+J74+J73+J72+J71+J70+J69 -> 0 | K94: =K93+K92+K91+K90+K89+K88+K87+K86+K85+K84+K83+K82+K81+K80+K79+K78+K77+K76+K75+K74+K73+K72+K71+K70+K69 -> 0 | L94: =SUM(L69:L93) -> 0 | M94: =SUM(M69:M93) -> 0
R96: Page: 3

Sheet SAT
A1: B2 Daily Report
A2: 21 - 5 - 2022 | H2: WEATHER | J2: SHOWER | L2: REPORT BY | O2: HENDRA | R2: TOTAL STAFF | T2: 5 | X2: Merchant machine usage at B2 | AA2: Settle amount | AI2: Merchant machine usage at GA | AL2: Settle amount
A4: No | B4: Docket No | C4: Reg No | D4: Mobile | E4: Gender | F4: TIME | G4: Service | H4: CASH | I4: CARD | J4: RSL | K4: GV | L4: GV CASH | M4: GV CARD | N4: O/Taker | O4: Comment | R4: NAME | S4: Time In | T4: Time out | U4: Total Hours | Z4: B2 machine | AA4: BLH machine | AB4: Wongo | AE4: B2 machine | AF4: BLH machine | AG4: Wongo | AK4: GA machine | AL4: BLH machine | AM4: Wongo | AP4: GA machine | AQ4: BLH machine | AR4: Wongo
A5: 1 | B5: 4254 | C5: DSY26Z | D5: 0452212543 | E5: F | F5: 845 | G5: PCL | J5: =IF(G5="RSL","55","0") -> 0 | K5: 79.16 | N5: HENDRA | O5: # 21066 3/6 | R5: HENDRA | S5: 0.33333333 | T5: 0.72916667 | U5: =(T5-S5)*24 -> 9.5 | X5: NOV | Y5: 1 | AD5: 16 | AI5: NOV | AJ5: 1 | AO5: 16
A6: 2 | B6: 4255 | C6: DHS111 | D6: 0412255630 | E6: F | F6: 900 | G6: PCL | J6: =IF(G6="RSL","55","0") -> 0 | K6: 79.16 | N6: HENDRA | O6: # 21060 4/6 | R6: JUNIOR | S6: 0.33333333 | T6: 0.55208333 | U6: =(T6-S6)*24 -> 5.25 | W6: M | Y6: 2 | AD6: 17 | AJ6: 2 | AO6: 17
A7: 3 | B7: 4256 | C7: DBW83M | D7: 0413842371 | E7: F | F7: 1100 | G7: X | I7: 95 | J7: =IF(G7="RSL","55","0") -> 0 | K7: =IF(G7="GVS","37.5",IF(G7="GVM","41.5",IF(G7="GVL","50",IF(G7="PCS","45.8",IF(G7="PCM","50",IF(G7="PCL","58.3","0")))))) -> 0 | N7: HENDRA | R7: ARIANTO | S7: 0.39583333 | T7: 0.70833333 | U7: =(T7-S7)*24 -> 7.5 | W7: F | Y7: 3 | AD7: 18 | AJ7: 3 | AO7: 18
A8: 4 | B8: 4257 | C8: ELY12W | D8: 0426464093 | E8: M | F8: 920 | G8: X | I8: 75 | J8: =IF(G8="RSL","55","0") -> 0 | K8: =IF(G8="GVS","37.5",IF(G8="GVM","41.5",IF(G8="GVL","50",IF(G8="PCS","45.8",IF(G8="PCM","50",IF(G8="PCL","58.3","0")))))) -> 0 | N8: HENDRA | R8: KUROSH | S8: 0.375 | T8: 0.72916667 | U8: =(T8-S8)*24 -> 8.5 | Y8: 4 | AD8: 19 | AJ8: 4 | AO8: 19
A9: 5 | B9: 4258 | C9: CEC64E | D9: 0430166888 | E9: M | F9: 1020 | G9: H | I9: 120 | J9: =IF(G9="RSL","55","0") -> 0 | K9: =IF(G9="GVS","37.5",IF(G9="GVM","41.5",IF(G9="GVL","50",IF(G9="PCS","45.8",IF(G9="PCM","50",IF(G9="PCL","58.3","0")))))) -> 0 | N9: HENDRA | O9: TAX | R9: KEVIN | S9: 0.375 | T9: 0.72916667 | U9: =(T9-S9)*24 -> 8.5 | X9: EXCL RSL | Y9: 5 | AD9: 20 | AJ9: 5 | AO9: 20
A10: 6 | B10: 4259 | C10: ENJ116 | D10: 0433966747 | E10: M | F10: 1025 | G10: x | I10: 95 | J10: =IF(G10="RSL","55","0") -> 0 | K10: =IF(G10="GVS","37.5",IF(G10="GVM","41.5",IF(G10="GVL","50",IF(G10="PCS","45.8",IF(G10="PCM","50",IF(G10="PCL","58.3","0")))))) -> 0 | N10: HENDRA | R10: CHRIS | S10: 0.5625 | T10: 0.70833333 | U10: =(T10-S10)*24 -> 3.5 | Y10: 6 | AD10: 21 | AJ10: 6 | AO10: 21
A11: 7 | B11: 4260 | C11: 84EKB | D11: 0452198401 | E11: F | F11: 1115 | G11: H | I11: 150 | J11: =IF(G11="RSL","55","0") -> 0 | K11: =IF(G11="GVS","37.5",IF(G11="GVM","41.5",IF(G11="GVL","50",IF(G11="PCS","45.8",IF(G11="PCM","50",IF(G11="PCL","58.3","0")))))) -> 0 | N11: HENDRA | U11: =(T11-S11)*24 -> 0 | Y11: 7 | AD11: 22 | AJ11: 7 | AO11: 22
A12: 8 | B12: 4261 | C12: EGQ58G | D12: 0467792693 | E12: M | F12: 1130 | G12: D | I12: 65 | J12: =IF(G12="RSL","55","0") -> 0 | K12: =IF(G12="GVS","37.5",IF(G12="GVM","41.5",IF(G12="GVL","50",IF(G12="PCS","45.8",IF(G12="PCM","50",IF(G12="PCL","58.3","0")))))) -> 0 | N12: HENDRA | U12: =(T12-S12)*24 -> 0 | Y12: 8 | AD12: 23 | AJ12: 8 | AO12: 23
A13: 9 | B13: 4262 | C13: EGM52V | D13: 0415832282 | E13: F | F13: 1200 | G13: D | I13: 75 | J13: =IF(G13="RSL","55","0") -> 0 | K13: =IF(G13="GVS","37.5",IF(G13="GVM","41.5",IF(G13="GVL","50",IF(G13="PCS","45.8",IF(G13="PCM","50",IF(G13="PCL","58.3","0")))))) -> 0 | N13: HENDRA | U13: =(T13-S13)*24 -> 0 | Y13: 9 | AD13: 24 | AJ13: 9 | AO13: 24
A14: 10 | B14: 4263 | C14: CJK30U | D14: 0406939929 | E14: M | F14: 1155 | G14: X | I14: 75 | J14: =IF(G14="RSL","55","0") -> 0 | K14: =IF(G14="GVS","37.5",IF(G14="GVM","41.5",IF(G14="GVL","50",IF(G14="PCS","45.8",IF(G14="PCM","50",IF(G14="PCL","58.3","0")))))) -> 0 | N14: HENDRA | U14: =(T14-S14)*24 -> 0 | Y14: 10 | AD14: 25 | AJ14: 10 | AO14: 25
A15: 11 | B15: 4264 | C15: EDH10W | D15: 0407525804 | E15: M | F15: 1200 | G15: D | I15: 55 | J15: =IF(G15="RSL","55","0") -> 0 | K15: =IF(G15="GVS","37.5",IF(G15="GVM","41.5",IF(G15="GVL","50",IF(G15="PCS","45.8",IF(G15="PCM","50",IF(G15="PCL","58.3","0")))))) -> 0 | N15: HENDRA | U15: =(T15-S15)*24 -> 0 | Y15: 11 | AD15: 26 | AJ15: 11 | AO15: 26
A16: 12 | B16: 4265 | C16: DDM87V | D16: 0404010990 | E16: F | F16: 1220 | G16: D/ST | I16: 250 | J16: =IF(G16="RSL","55","0") -> 0 | K16: =IF(G16="GVS","37.5",IF(G16="GVM","41.5",IF(G16="GVL","50",IF(G16="PCS","45.8",IF(G16="PCM","50",IF(G16="PCL","58.3","0")))))) -> 0 | N16: HENDRA | O16: SMALL | R16: =H32/U16 -> 0.46783626 | S16: =H32/(U16-U5) -> 0.60150376 | T16: =C32/U16 -> 45.867135 | U16: =SUM(U5:U15) -> 42.75 | Y16: 12 | AD16: 27 | AJ16: 12 | AO16: 27
A17: 13 | B17: 4266 | C17: DPR39N | D17: o449981171 | E17: M | F17: 1230 | G17: X | I17: 75 | J17: =IF(G17="RSL","55","0") -> 0 | K17: =IF(G17="GVS","37.5",IF(G17="GVM","41.5",IF(G17="GVL","50",IF(G17="PCS","45.8",IF(G17="PCM","50",IF(G17="PCL","58.3","0")))))) -> 0 | N17: HENDRA | R17: Cars/T Hr ① | S17: Cars/T Hr ② | T17: Sales/T Hr | U17: Total Hours | Y17: 13 | AD17: 28 | AJ17: 13 | AO17: 28
A18: 14 | B18: 4267 | C18: DKZ64J | D18: 0466271535 | E18: M | F18: 1315 | G18: X | I18: 95 | J18: =IF(G18="RSL","55","0") -> 0 | K18: =IF(G18="GVS","37.5",IF(G18="GVM","41.5",IF(G18="GVL","50",IF(G18="PCS","45.8",IF(G18="PCM","50",IF(G18="PCL","58.3","0")))))) -> 0 | N18: HENDRA | R18: ITEM | S18: QTY | T18: AMT | U18: RMKS | Y18: 14 | AD18: 29 | AJ18: 14 | AO18: 29
A19: 15 | B19: 4268 | C19: SGF30B | D19: 0433319117 | E19: F | F19: 1330 | G19: D | H19: 75 | J19: =IF(G19="RSL","55","0") -> 0 | K19: =IF(G19="GVS","37.5",IF(G19="GVM","41.5",IF(G19="GVL","50",IF(G19="PCS","45.8",IF(G19="PCM","50",IF(G19="PCL","58.3","0")))))) -> 0 | N19: HENDRA | R19: GV | S19: =COUNT(L5:M29,L37:M61,L69:M93) -> 1 | T19: =SUM(L5:M29,L37:M61,L69:M93) -> 375 | Y19: 15 | AD19: 30 | AJ19: 15 | AO19: 30
A20: 16 | B20: 4269 | C20: AKA47G | D20: 0411558686 | E20: F | F20: 1400 | G20: I/ST | I20: 200 | J20: =IF(G20="RSL","55","0") -> 0 | K20: =IF(G20="GVS","37.5",IF(G20="GVM","41.5",IF(G20="GVL","50",IF(G20="PCS","45.8",IF(G20="PCM","50",IF(G20="PCL","58.3","0")))))) -> 0 | N20: HENDRA | O20: SMALL | AD20: 31 | AO20: 31
A21: 17 | B21: 4270 | C21: CIO83P | D21: 0401714252 | E21: M | F21: 1500 | G21: PCS | J21: =IF(G21="RSL","55","0") -> 0 | K21: 62.5 | M21: 375 | N21: HENDRA | O21: # 22018 1/6
A22: 18 | B22: 4271 | C22: AR41MF | D22: 0411702399 | E22: F | F22: 1530 | G22: RSL | J22: =IF(G22="RSL","55","0") -> 55 | K22: =IF(G22="GVS","37.5",IF(G22="GVM","41.5",IF(G22="GVL","50",IF(G22="PCS","45.8",IF(G22="PCM","50",IF(G22="PCL","58.3","0")))))) -> 0 | N22: HENDRA | O22: 202203084 | AD22: Total | AE22: =SUM(Z5:Z19,AE5:AE20) -> 0 | AF22: =SUM(AA5:AA19,AF5:AF20,) -> 0 | AG22: =SUM(AB5:AB19,AG5:AG20) -> 0 | AO22: Total | AP22: =SUM(AK5:AK19,AP5:AP20) -> 0 | AQ22: =SUM(AL5:AL19,AQ5:AQ20,) -> 0 | AR22: =SUM(AM5:AM19,AR5:AR20) -> 0
A23: 19 | B23: 4272 | C23: EPK68N | D23: 0401754320 | E23: F | F23: 1530 | G23: X | I23: 85 | J23: =IF(G23="RSL","55","0") -> 0 | K23: =IF(G23="GVS","37.5",IF(G23="GVM","41.5",IF(G23="GVL","50",IF(G23="PCS","45.8",IF(G23="PCM","50",IF(G23="PCL","58.3","0")))))) -> 0 | N23: HENDRA
A24: 20 | B24: 4273 | C24: EMF53P | D24: 0401665168 | E24: F | F24: 1550 | G24: X | I24: 100 | J24: =IF(G24="RSL","55","0") -> 0 | K24: =IF(G24="GVS","37.5",IF(G24="GVM","41.5",IF(G24="GVL","50",IF(G24="PCS","45.8",IF(G24="PCM","50",IF(G24="PCL","58.3","0")))))) -> 0 | N24: HENDRA | R24: SMALL | S24: MEDIUM | T24: LARGE | U24: TOTAL | AD24: B2/GA TOTAL | AE24: B2 machine | AF24: GA machine | AG24: BLH machine | AH24: Wongo machine | AI24: Sub total
A25: 21 | J25: =IF(G25="RSL","55","0") -> 0 | K25: =IF(G25="GVS","37.5",IF(G25="GVM","41.5",IF(G25="GVL","50",IF(G25="PCS","45.8",IF(G25="PCM","50",IF(G25="PCL","58.3","0")))))) -> 0 | R25: =COUNTIF(G5:G29,"GV1")+COUNTIF(G37:G61,"GV1")+COUNTIF(G69:G93,"GV1") -> 0 | S25: =COUNTIF(G5:G29,"GV2")+COUNTIF(G37:G61,"GV2")+COUNTIF(G69:G93,"GV2") -> 0 | T25: =COUNTIF(G5:G29,"GV3")+COUNTIF(G37:G61,"GV3")+COUNTIF(G69:G93,"GV3") -> 0 | U25: =((C32+(R26+S26+T26)*0.5)) -> 1960.82 | AD25: =SUM(AE25:AF25) -> 0 | AE25: =SUM(AE22) -> 0 | AF25: =SUM(AP22) -> 0 | AG25: =SUM(AF22+AQ22) -> 0 | AH25: =AG22+AR22 -> 0 | AI25: =SUM(AE25:AH25) -> 0
A26: 22 | J26: =IF(G26="RSL","55","0") -> 0 | K26: =IF(G26="GVS","37.5",IF(G26="GVM","41.5",IF(G26="GVL","50",IF(G26="PCS","45.8",IF(G26="PCM","50",IF(G26="PCL","58.3","0")))))) -> 0 | R26: =R25*37.5 -> 0 | S26: =S25*41.5 -> 0 | T26: =T25*50 -> 0 | X26: Branch cards
A27: 23 | J27: =IF(G27="RSL","55","0") -> 0 | K27: =IF(G27="GVS","37.5",IF(G27="GVM","41.5",IF(G27="GVL","50",IF(G27="PCS","45.8",IF(G27="PCM","50",IF(G27="PCL","58.3","0")))))) -> 0 | R27: Expense | X27: 1 | Z27: -2745
A28: 24 | J28: =IF(G28="RSL","55","0") -> 0 | K28: =IF(G28="GVS","37.5",IF(G28="GVM","41.5",IF(G28="GVL","50",IF(G28="PCS","45.8",IF(G28="PCM","50",IF(G28="PCL","58.3","0")))))) -> 0 | X28: 2
A29: 25 | J29: =IF(G29="RSL","55","0") -> 0 | K29: =IF(G29="GVS","37.5",IF(G29="GVM","41.5",IF(G29="GVL","50",IF(G29="PCS","45.8",IF(G29="PCM","50",IF(G29="PCL","58.3","0")))))) -> 0 | X29: 3
A30: Page total | H30: =SUM(H5:H29) -> 75 | I30: =SUM(I5:I29) -> 1610 | J30: =J5+J6+J7+J8+J9+J10+J11+J12+J13+J14+J15+J16+J18+J19+J17+J20+J22+J23+J21+J24+J25+J26+J27+J28+J29 -> 55 | K30: =K5+K6+K7+K8+K9+K10+K11+K12+K13+K14+K15+K16+K18+K19+K17+K20+K22+K23+K21+K24+K25+K26+K27+K28+K29 -> 220.82 | L30: =SUM(L5:L29) -> 0 | M30: =SUM(M5:M29) -> 375 | N30: CASH | O30: CARD | P30: GV | Q30: RSL | X30: 4
A31: Daily Total | H31: =H30+H62+H94 -> 75 | I31: =I30+I62+I94 -> 1610 | J31: =J30+J62+J94 -> 55 | K31: =K30+K62+K94 -> 220.82 | L31: =L30+L62+L94 -> 0 | M31: =M30+M62+M94 -> 375 | N31: =COUNT(H5:H29,H37:H61,H69:H93) -> 1 | O31: =COUNT(I5:I29,I37:I61,I69:I93) -> 15 | P31: =COUNTIF(G5:G29,"G*")+COUNTIF(G37:G61,"G*")+COUNTIF(G69:G93,"G*")+COUNTIF(G5:G29,"P*")+COUNTIF(G37:G61,"P*")+COUNTIF(G69:G93,"P*") -> 3 | Q31: =COUNTIF(G5:G29,"RSL")+COUNTIF(G37:G61,"RSL")+COUNTIF(G69:G93,"RSL") -> 1 | R31: CASH CLOSING | S31: =H31+L31-U28-U29-U30 -> 75 | T31: =H31+I31+L31+M31 -> 2060 | X31: Subtotal | Z31: =SUM(Z27:Z30) -> -2745
A32: TOTAL SALES | C32: =H31+I31+J31+K31 -> 1960.82 | F32: No of Cars | H32: =COUNT(B5:B29,B37:B61,B69:B93) -> 20 | I32: Average | K32: =C32/H32 -> 98.041 | N32: =H31/C32 -> 0.038249304 | O32: =I31/C32 -> 0.82108506 | P32: =K31/C32 -> 0.11261615 | Q32: =J31/C32 -> 0.028049489 | R32: CARD CLOSING | S32: =I31+M31 -> 1985 | X32: B2 card | Z32: =I31 -> 1610
A33: Daily Report | X33: Settlement | Z33: =SUM(Z31:Z32) -> -1135
A34: =A2 -> 21 - 5 - 2022 | H34: WEATHER | J34: =J2 -> SHOWER | L34: REPORT by | O34: =O2 -> HENDRA | R34: TOTAL STAFF | T34: =T2 -> 5
A36: No | B36: Docket No | C36: Reg No | D36: Mobile | E36: Gender | F36: TIME | G36: Service | H36: CASH | I36: CARD | J36: RSL | K36: GV | L36: GV CASH | M36: GV CARD | N36: O/Taker | O36: Comment | R36: NAME | S36: Time In | T36: Time out | U36: Total Hours
A37: =A29+1 -> 26 | J37: =IF(G37="RSL","55","0") -> 0 | K37: =IF(G37="GVS","37.5",IF(G37="GVM","41.5",IF(G37="GVL","50",IF(G37="PCS","45.8",IF(G37="PCM","50",IF(G37="PCL","58.3","0")))))) -> 0
A38: =A37+1 -> 27 | J38: =IF(G38="RSL","55","0") -> 0 | K38: =IF(G38="GVS","37.5",IF(G38="GVM","41.5",IF(G38="GVL","50",IF(G38="PCS","45.8",IF(G38="PCM","50",IF(G38="PCL","58.3","0")))))) -> 0
A39: =A38+1 -> 28 | J39: =IF(G39="RSL","55","0") -> 0 | K39: =IF(G39="GVS","37.5",IF(G39="GVM","41.5",IF(G39="GVL","50",IF(G39="PCS","45.8",IF(G39="PCM","50",IF(G39="PCL","58.3","0")))))) -> 0
A40: =A39+1 -> 29 | J40: =IF(G40="RSL","55","0") -> 0 | K40: =IF(G40="GVS","37.5",IF(G40="GVM","41.5",IF(G40="GVL","50",IF(G40="PCS","45.8",IF(G40="PCM","50",IF(G40="PCL","58.3","0")))))) -> 0
A41: =A40+1 -> 30 | J41: =IF(G41="RSL","55","0") -> 0 | K41: =IF(G41="GVS","37.5",IF(G41="GVM","41.5",IF(G41="GVL","50",IF(G41="PCS","45.8",IF(G41="PCM","50",IF(G41="PCL","58.3","0")))))) -> 0
A42: =A41+1 -> 31 | J42: =IF(G42="RSL","55","0") -> 0 | K42: =IF(G42="GVS","37.5",IF(G42="GVM","41.5",IF(G42="GVL","50",IF(G42="PCS","45.8",IF(G42="PCM","50",IF(G42="PCL","58.3","0")))))) -> 0
A43: =A42+1 -> 32 | J43: =IF(G43="RSL","55","0") -> 0 | K43: =IF(G43="GVS","37.5",IF(G43="GVM","41.5",IF(G43="GVL","50",IF(G43="PCS","45.8",IF(G43="PCM","50",IF(G43="PCL","58.3","0")))))) -> 0
A44: =A43+1 -> 33 | J44: =IF(G44="RSL","55","0") -> 0 | K44: =IF(G44="GVS","37.5",IF(G44="GVM","41.5",IF(G44="GVL","50",IF(G44="PCS","45.8",IF(G44="PCM","50",IF(G44="PCL","58.3","0")))))) -> 0
A45: =A44+1 -> 34 | J45: =IF(G45="RSL","55","0") -> 0 | K45: =IF(G45="GVS","37.5",IF(G45="GVM","41.5",IF(G45="GVL","50",IF(G45="PCS","45.8",IF(G45="PCM","50",IF(G45="PCL","58.3","0")))))) -> 0
A46: =A45+1 -> 35 | J46: =IF(G46="RSL","55","0") -> 0 | K46: =IF(G46="GVS","37.5",IF(G46="GVM","41.5",IF(G46="GVL","50",IF(G46="PCS","45.8",IF(G46="PCM","50",IF(G46="PCL","58.3","0")))))) -> 0
A47: =A46+1 -> 36 | J47: =IF(G47="RSL","55","0") -> 0 | K47: =IF(G47="GVS","37.5",IF(G47="GVM","41.5",IF(G47="GVL","50",IF(G47="PCS","45.8",IF(G47="PCM","50",IF(G47="PCL","58.3","0")))))) -> 0
A48: =A47+1 -> 37 | J48: =IF(G48="RSL","55","0") -> 0 | K48: =IF(G48="GVS","37.5",IF(G48="GVM","41.5",IF(G48="GVL","50",IF(G48="PCS","45.8",IF(G48="PCM","50",IF(G48="PCL","58.3","0")))))) -> 0
A49: =A48+1 -> 38 | J49: =IF(G49="RSL","55","0") -> 0 | K49: =IF(G49="GVS","37.5",IF(G49="GVM","41.5",IF(G49="GVL","50",IF(G49="PCS","45.8",IF(G49="PCM","50",IF(G49="PCL","58.3","0")))))) -> 0
... A61: =A60+1 -> 50 | J61: =IF(G61="RSL","55","0") -> 0 | K61: =IF(G61="GVS","37.5",IF(G61="GVM","41.5",IF(G61="GVL","50",IF(G61="PCS","45.8",IF(G61="PCM","50",IF(G61="PCL","58.3","0")))))) -> 0
A62: Page total | H62: =SUM(H37:H61) -> 0 | I62: =SUM(I37:I61) -> 0 | J62: =J61+J60+J59+J58+J57+J56+J55+J54+J53+J52+J51+J50+J49+J48+J47+J46+J45+J44+J43+J42+J41+J40+J39+J38+J37 -> 0 | K62: =K61+K60+K59+K58+K57+K56+K55+K54+K53+K52+K51+K50+K49+K48+K47+K46+K45+K44+K43+K42+K41+K40+K39+K38+K37 -> 0 | L62: =SUM(L37:L61) -> 0 | M62: =SUM(M37:M61) -> 0
R64: Page: 2
A65: Daily Report
A66: =A34 -> 21 - 5 - 2022 | H66: WEATHER | J66: =J34 -> SHOWER | L66: REPORT by | O66: =O34 -> HENDRA | R66: TOTAL STAFF | T66: =T34 -> 5
A68: No | B68: Docket No | C68: Reg No | D68: Mobile | E68: Gender | F68: TIME | G68: Service | H68: CASH | I68: CARD | J68: RSL | K68: GV | L68: GV CASH | M68: GV CARD | N68: O/Taker | O68: Comment | R68: NAME | S68: Time In | T68: Time out | U68: Total Hours
A69: =A61+1 -> 51 | J69: =IF(G69="RSL","55","0") -> 0 | K69: =IF(G69="GVS","37.5",IF(G69="GVM","41.5",IF(G69="GVL","50",IF(G69="PCS","45.8",IF(G69="PCM","50",IF(G69="PCL","58.3","0")))))) -> 0
A70: =A69+1 -> 52 | J70: =IF(G70="RSL","55","0") -> 0 | K70: =IF(G70="GVS","37.5",IF(G70="GVM","41.5",IF(G70="GVL","50",IF(G70="PCS","45.8",IF(G70="PCM","50",IF(G70="PCL","58.3","0")))))) -> 0
A71: =A70+1 -> 53 | J71: =IF(G71="RSL","55","0") -> 0 | K71: =IF(G71="GVS","37.5",IF(G71="GVM","41.5",IF(G71="GVL","50",IF(G71="PCS","45.8",IF(G71="PCM","50",IF(G71="PCL","58.3","0")))))) -> 0
A72: =A71+1 -> 54 | J72: =IF(G72="RSL","55","0") -> 0 | K72: =IF(G72="GVS","37.5",IF(G72="GVM","41.5",IF(G72="GVL","50",IF(G72="PCS","45.8",IF(G72="PCM","50",IF(G72="PCL","58.3","0")))))) -> 0
A73: =A72+1 -> 55 | J73: =IF(G73="RSL","55","0") -> 0 | K73: =IF(G73="GVS","37.5",IF(G73="GVM","41.5",IF(G73="GVL","50",IF(G73="PCS","45.8",IF(G73="PCM","50",IF(G73="PCL","58.3","0")))))) -> 0
A74: =A73+1 -> 56 | J74: =IF(G74="RSL","55","0") -> 0 | K74: =IF(G74="GVS","37.5",IF(G74="GVM","41.5",IF(G74="GVL","50",IF(G74="PCS","45.8",IF(G74="PCM","50",IF(G74="PCL","58.3","0")))))) -> 0
A75: =A74+1 -> 57 | J75: =IF(G75="RSL","55","0") -> 0 | K75: =IF(G75="GVS","37.5",IF(G75="GVM","41.5",IF(G75="GVL","50",IF(G75="PCS","45.8",IF(G75="PCM","50",IF(G75="PCL","58.3","0")))))) -> 0
A76: =A75+1 -> 58 | J76: =IF(G76="RSL","55","0") -> 0 | K76: =IF(G76="GVS","37.5",IF(G76="GVM","41.5",IF(G76="GVL","50",IF(G76="PCS","45.8",IF(G76="PCM","50",IF(G76="PCL","58.3","0")))))) -> 0
A77: =A76+1 -> 59 | J77: =IF(G77="RSL","55","0") -> 0 | K77: =IF(G77="GVS","37.5",IF(G77="GVM","41.5",IF(G77="GVL","50",IF(G77="PCS","45.8",IF(G77="PCM","50",IF(G77="PCL","58.3","0")))))) -> 0
A78: =A77+1 -> 60 | J78: =IF(G78="RSL","55","0") -> 0 | K78: =IF(G78="GVS","37.5",IF(G78="GVM","41.5",IF(G78="GVL","50",IF(G78="PCS","45.8",IF(G78="PCM","50",IF(G78="PCL","58.3","0")))))) -> 0
A79: =A78+1 -> 61 | J79: =IF(G79="RSL","55","0") -> 0 | K79: =IF(G79="GVS","37.5",IF(G79="GVM","41.5",IF(G79="GVL","50",IF(G79="PCS","45.8",IF(G79="PCM","50",IF(G79="PCL","58.3","0")))))) -> 0
A80: =A79+1 -> 62 | J80: =IF(G80="RSL","55","0") -> 0 | K80: =IF(G80="GVS","37.5",IF(G80="GVM","41.5",IF(G80="GVL","50",IF(G80="PCS","45.8",IF(G80="PCM","50",IF(G80="PCL","58.3","0")))))) -> 0
A81: =A80+1 -> 63 | J81: =IF(G81="RSL","55","0") -> 0 | K81: =IF(G81="GVS","37.5",IF(G81="GVM","41.5",IF(G81="GVL","50",IF(G81="PCS","45.8",IF(G81="PCM","50",IF(G81="PCL","58.3","0")))))) -> 0
... A93: =A92+1 -> 75 | J93: =IF(G93="RSL","55","0") -> 0 | K93: =IF(G93="GVS","37.5",IF(G93="GVM","41.5",IF(G93="GVL","50",IF(G93="PCS","45.8",IF(G93="PCM","50",IF(G93="PCL","58.3","0")))))) -> 0
A94: Page total | H94: =SUM(H69:H93) -> 0 | I94: =SUM(I69:I93) -> 0 | J94: =J93+J92+J91+J90+J89+J88+J87+J86+J85+J84+J83+J82+J81+J80+J79+J78+J77+J76+J75+J74+J73+J72+J71+J70+J69 -> 0 | K94: =K93+K92+K91+K90+K89+K88+K87+K86+K85+K84+K83+K82+K81+K80+K79+K78+K77+K76+K75+K74+K73+K72+K71+K70+K69 -> 0 | L94: =SUM(L69:L93) -> 0 | M94: =SUM(M69:M93) -> 0
R96: Page: 3

Sheet SUN
A1: B2 Daily Report
A2: 22 - 5 - 2022 | H2: WEATHER | J2: SHOWER | L2: REPORT BY | O2: HENDRA | R2: TOTAL STAFF | T2: 5 | X2: Merchant machine usage at B2 | AA2: Settle amount | AI2: Merchant machine usage at GA | AL2: Settle amount
A4: No | B4: Docket No | C4: Reg No | D4: Mobile | E4: Gender | F4: TIME | G4: Service | H4: CASH | I4: CARD | J4: RSL | K4: GV | L4: GV CASH | M4: GV CARD | N4: O/Taker | O4: Comment | R4: NAME | S4: Time In | T4: Time out | U4: Total Hours | Z4: B2 machine | AA4: BLH machine | AB4: Wongo | AE4: B2 machine | AF4: BLH machine | AG4: Wongo | AK4: GA machine | AL4: BLH machine | AM4: Wongo | AP4: GA machine | AQ4: BLH machine | AR4: Wongo
A5: 1 | B5: 4274 | C5: BNP94F | D5: 0412435299 | E5: F | F5: 950 | G5: H | I5: 120 | J5: =IF(G5="RSL","55","0") -> 0 | K5: =IF(G5="GVS","37.5",IF(G5="GVM","41.5",IF(G5="GVL","50",IF(G5="PCS","45.8",IF(G5="PCM","50",IF(G5="PCL","58.3","0")))))) -> 0 | N5: HENDRA | R5: HENDRA | S5: 0.33333333 | T5: 0.66666667 | U5: =(T5-S5)*24 -> 8 | X5: NOV | Y5: 1 | AD5: 16 | AI5: NOV | AJ5: 1 | AO5: 16
A6: 2 | B6: 4275 | C6: NBS89E | D6: 0417550172 | E6: F | F6: 1015 | G6: X | I6: 95 | J6: =IF(G6="RSL","55","0") -> 0 | K6: =IF(G6="GVS","37.5",IF(G6="GVM","41.5",IF(G6="GVL","50",IF(G6="PCS","45.8",IF(G6="PCM","50",IF(G6="PCL","58.3","0")))))) -> 0 | N6: HENDRA | R6: ERIC | S6: 0.33333333 | T6: 0.58333333 | U6: =(T6-S6)*24 -> 6 | W6: M | Y6: 2 | AD6: 17 | AJ6: 2 | AO6: 17
A7: 3 | B7: 4276 | C7: GBI | D7: 0415888891 | E7: M | F7: 1030 | G7: H | I7: 150 | J7: =IF(G7="RSL","55","0") -> 0 | K7: =IF(G7="GVS","37.5",IF(G7="GVM","41.5",IF(G7="GVL","50",IF(G7="PCS","45.8",IF(G7="PCM","50",IF(G7="PCL","58.3","0")))))) -> 0 | N7: HENDRA | O7: GEORGE CAR | R7: KEVIN | S7: 0.35416667 | T7: 0.58333333 | U7: =(T7-S7)*24 -> 5.5 | W7: F | Y7: 3 | AD7: 18 | AJ7: 3 | AO7: 18
A8: 4 | B8: 4277 | C8: EGY78F | D8: 0421257396 | E8: M | F8: 1045 | G8: D | I8: 75 | J8: =IF(G8="RSL","55","0") -> 0 | K8: =IF(G8="GVS","37.5",IF(G8="GVM","41.5",IF(G8="GVL","50",IF(G8="PCS","45.8",IF(G8="PCM","50",IF(G8="PCL","58.3","0")))))) -> 0 | N8: HENDRA | R8: KUROSH | S8: 0.375 | T8: 0.66666667 | U8: =(T8-S8)*24 -> 7 | Y8: 4 | AD8: 19 | AJ8: 4 | AO8: 19
A9: 5 | B9: 4278 | C9: DYI60E | D9: 0405303318 | E9: F | F9: 1115 | G9: H | I9: 150 | J9: =IF(G9="RSL","55","0") -> 0 | K9: =IF(G9="GVS","37.5",IF(G9="GVM","41.5",IF(G9="GVL","50",IF(G9="PCS","45.8",IF(G9="PCM","50",IF(G9="PCL","58.3","0")))))) -> 0 | N9: HENDRA | R9: VINNY | S9: 0.44791667 | T9: 0.66666667 | U9: =(T9-S9)*24 -> 5.25 | X9: EXCL RSL | Y9: 5 | AD9: 20 | AJ9: 5 | AO9: 20
A10: 6 | B10: 4279 | C10: DQF88H | D10: 0429263156 | E10: M | F10: 1130 | G10: D | I10: 55 | J10: =IF(G10="RSL","55","0") -> 0 | K10: =IF(G10="GVS","37.5",IF(G10="GVM","41.5",IF(G10="GVL","50",IF(G10="PCS","45.8",IF(G10="PCM","50",IF(G10="PCL","58.3","0")))))) -> 0 | N10: HENDRA | U10: =(T10-S10)*24 -> 0 | Y10: 6 | AD10: 21 | AJ10: 6 | AO10: 21
A11: 7 | B11: 4280 | C11: EMB53M | D11: 0419879786 | E11: F | F11: 1245 | G11: H | I11: 150 | J11: =IF(G11="RSL","55","0") -> 0 | K11: =IF(G11="GVS","37.5",IF(G11="GVM","41.5",IF(G11="GVL","50",IF(G11="PCS","45.8",IF(G11="PCM","50",IF(G11="PCL","58.3","0")))))) -> 0 | N11: HENDRA | U11: =(T11-S11)*24 -> 0 | Y11: 7 | AD11: 22 | AJ11: 7 | AO11: 22
A12: 8 | B12: 4281 | C12: SLW94A | D12: 0412925531 | E12: F | F12: 1310 | G12: X | I12: 75 | J12: =IF(G12="RSL","55","0") -> 0 | K12: =IF(G12="GVS","37.5",IF(G12="GVM","41.5",IF(G12="GVL","50",IF(G12="PCS","45.8",IF(G12="PCM","50",IF(G12="PCL","58.3","0")))))) -> 0 | N12: HENDRA | U12: =(T12-S12)*24 -> 0 | Y12: 8 | AD12: 23 | AJ12: 8 | AO12: 23
A13: 9 | B13: 4282 | C13: YYY789 | D13: 0412115425 | E13: M | F13: 1410 | G13: D | H13: 75 | J13: =IF(G13="RSL","55","0") -> 0 | K13: =IF(G13="GVS","37.5",IF(G13="GVM","41.5",IF(G13="GVL","50",IF(G13="PCS","45.8",IF(G13="PCM","50",IF(G13="PCL","58.3","0")))))) -> 0 | N13: HENDRA | U13: =(T13-S13)*24 -> 0 | Y13: 9 | AD13: 24 | AJ13: 9 | AO13: 24
A14: 10 | B14: 4283 | C14: NCD89V | D14: 0411895199 | E14: M | F14: 1445 | G14: X | I14: 95 | J14: =IF(G14="RSL","55","0") -> 0 | K14: =IF(G14="GVS","37.5",IF(G14="GVM","41.5",IF(G14="GVL","50",IF(G14="PCS","45.8",IF(G14="PCM","50",IF(G14="PCL","58.3","0")))))) -> 0 | N14: HENDRA | U14: =(T14-S14)*24 -> 0 | Y14: 10 | AD14: 25 | AJ14: 10 | AO14: 25
A15: 11 | J15: =IF(G15="RSL","55","0") -> 0 | K15: =IF(G15="GVS","37.5",IF(G15="GVM","41.5",IF(G15="GVL","50",IF(G15="PCS","45.8",IF(G15="PCM","50",IF(G15="PCL","58.3","0")))))) -> 0 | U15: =(T15-S15)*24 -> 0 | Y15: 11 | AD15: 26 | AJ15: 11 | AO15: 26
A16: 12 | J16: =IF(G16="RSL","55","0") -> 0 | K16: =IF(G16="GVS","37.5",IF(G16="GVM","41.5",IF(G16="GVL","50",IF(G16="PCS","45.8",IF(G16="PCM","50",IF(G16="PCL","58.3","0")))))) -> 0 | R16: =H32/U16 -> 0.31496063 | S16: =H32/(U16-U5) -> 0.42105263 | T16: =C32/U16 -> 32.755906 | U16: =SUM(U5:U15) -> 31.75 | Y16: 12 | AD16: 27 | AJ16: 12 | AO16: 27
A17: 13 | J17: =IF(G17="RSL","55","0") -> 0 | K17: =IF(G17="GVS","37.5",IF(G17="GVM","41.5",IF(G17="GVL","50",IF(G17="PCS","45.8",IF(G17="PCM","50",IF(G17="PCL","58.3","0")))))) -> 0 | R17: Cars/T Hr ① | S17: Cars/T Hr ② | T17: Sales/T Hr | U17: Total Hours | Y17: 13 | AD17: 28 | AJ17: 13 | AO17: 28
A18: 14 | J18: =IF(G18="RSL","55","0") -> 0 | K18: =IF(G18="GVS","37.5",IF(G18="GVM","41.5",IF(G18="GVL","50",IF(G18="PCS","45.8",IF(G18="PCM","50",IF(G18="PCL","58.3","0")))))) -> 0 | R18: ITEM | S18: QTY | T18: AMT | U18: RMKS | Y18: 14 | AD18: 29 | AJ18: 14 | AO18: 29
A19: 15 | J19: =IF(G19="RSL","55","0") -> 0 | K19: =IF(G19="GVS","37.5",IF(G19="GVM","41.5",IF(G19="GVL","50",IF(G19="PCS","45.8",IF(G19="PCM","50",IF(G19="PCL","58.3","0")))))) -> 0 | R19: GV | S19: =COUNT(L5:M29,L37:M61,L69:M93) -> 0 | T19: =SUM(L5:M29,L37:M61,L69:M93) -> 0 | Y19: 15 | AD19: 30 | AJ19: 15 | AO19: 30
A20: 16 | J20: =IF(G20="RSL","55","0") -> 0 | K20: =IF(G20="GVS","37.5",IF(G20="GVM","41.5",IF(G20="GVL","50",IF(G20="PCS","45.8",IF(G20="PCM","50",IF(G20="PCL","58.3","0")))))) -> 0 | AD20: 31 | AO20: 31
A21: 17 | J21: =IF(G21="RSL","55","0") -> 0 | K21: =IF(G21="GVS","37.5",IF(G21="GVM","41.5",IF(G21="GVL","50",IF(G21="PCS","45.8",IF(G21="PCM","50",IF(G21="PCL","58.3","0")))))) -> 0
A22: 18 | J22: =IF(G22="RSL","55","0") -> 0 | K22: =IF(G22="GVS","37.5",IF(G22="GVM","41.5",IF(G22="GVL","50",IF(G22="PCS","45.8",IF(G22="PCM","50",IF(G22="PCL","58.3","0")))))) -> 0 | AD22: Total | AE22: =SUM(Z5:Z19,AE5:AE20) -> 0 | AF22: =SUM(AA5:AA19,AF5:AF20,) -> 0 | AG22: =SUM(AB5:AB19,AG5:AG20) -> 0 | AO22: Total | AP22: =SUM(AK5:AK19,AP5:AP20) -> 0 | AQ22: =SUM(AL5:AL19,AQ5:AQ20,) -> 0 | AR22: =SUM(AM5:AM19,AR5:AR20) -> 0
A23: 19 | J23: =IF(G23="RSL","55","0") -> 0 | K23: =IF(G23="GVS","37.5",IF(G23="GVM","41.5",IF(G23="GVL","50",IF(G23="PCS","45.8",IF(G23="PCM","50",IF(G23="PCL","58.3","0")))))) -> 0
A24: 20 | J24: =IF(G24="RSL","55","0") -> 0 | K24: =IF(G24="GVS","37.5",IF(G24="GVM","41.5",IF(G24="GVL","50",IF(G24="PCS","45.8",IF(G24="PCM","50",IF(G24="PCL","58.3","0")))))) -> 0 | R24: SMALL | S24: MEDIUM | T24: LARGE | U24: TOTAL | AD24: B2/GA TOTAL | AE24: B2 machine | AF24: GA machine | AG24: BLH machine | AH24: Wongo machine | AI24: Sub total
A25: 21 | J25: =IF(G25="RSL","55","0") -> 0 | K25: =IF(G25="GVS","37.5",IF(G25="GVM","41.5",IF(G25="GVL","50",IF(G25="PCS","45.8",IF(G25="PCM","50",IF(G25="PCL","58.3","0")))))) -> 0 | R25: =COUNTIF(G5:G29,"GV1")+COUNTIF(G37:G61,"GV1")+COUNTIF(G69:G93,"GV1") -> 0 | S25: =COUNTIF(G5:G29,"GV2")+COUNTIF(G37:G61,"GV2")+COUNTIF(G69:G93,"GV2") -> 0 | T25: =COUNTIF(G5:G29,"GV3")+COUNTIF(G37:G61,"GV3")+COUNTIF(G69:G93,"GV3") -> 0 | U25: =((C32+(R26+S26+T26)*0.5)) -> 1040 | AD25: =SUM(AE25:AF25) -> 0 | AE25: =SUM(AE22) -> 0 | AF25: =SUM(AP22) -> 0 | AG25: =SUM(AF22+AQ22) -> 0 | AH25: =AG22+AR22 -> 0 | AI25: =SUM(AE25:AH25) -> 0
A26: 22 | J26: =IF(G26="RSL","55","0") -> 0 | K26: =IF(G26="GVS","37.5",IF(G26="GVM","41.5",IF(G26="GVL","50",IF(G26="PCS","45.8",IF(G26="PCM","50",IF(G26="PCL","58.3","0")))))) -> 0 | R26: =R25*37.5 -> 0 | S26: =S25*41.5 -> 0 | T26: =T25*50 -> 0 | X26: Branch cards
A27: 23 | J27: =IF(G27="RSL","55","0") -> 0 | K27: =IF(G27="GVS","37.5",IF(G27="GVM","41.5",IF(G27="GVL","50",IF(G27="PCS","45.8",IF(G27="PCM","50",IF(G27="PCL","58.3","0")))))) -> 0 | R27: Expense | X27: 1 | Z27: -2745
A28: 24 | J28: =IF(G28="RSL","55","0") -> 0 | K28: =IF(G28="GVS","37.5",IF(G28="GVM","41.5",IF(G28="GVL","50",IF(G28="PCS","45.8",IF(G28="PCM","50",IF(G28="PCL","58.3","0")))))) -> 0 | X28: 2
A29: 25 | J29: =IF(G29="RSL","55","0") -> 0 | K29: =IF(G29="GVS","37.5",IF(G29="GVM","41.5",IF(G29="GVL","50",IF(G29="PCS","45.8",IF(G29="PCM","50",IF(G29="PCL","58.3","0")))))) -> 0 | X29: 3
A30: Page total | H30: =SUM(H5:H29) -> 75 | I30: =SUM(I5:I29) -> 965 | J30: =J5+J6+J7+J8+J9+J10+J11+J12+J13+J14+J15+J16+J18+J19+J17+J20+J22+J23+J21+J24+J25+J26+J27+J28+J29 -> 0 | K30: =K5+K6+K7+K8+K9+K10+K11+K12+K13+K14+K15+K16+K18+K19+K17+K20+K22+K23+K21+K24+K25+K26+K27+K28+K29 -> 0 | L30: =SUM(L5:L29) -> 0 | M30: =SUM(M5:M29) -> 0 | N30: CASH | O30: CARD | P30: GV | Q30: RSL | X30: 4
A31: Daily Total | H31: =H30+H62+H94 -> 75 | I31: =I30+I62+I94 -> 965 | J31: =J30+J62+J94 -> 0 | K31: =K30+K62+K94 -> 0 | L31: =L30+L62+L94 -> 0 | M31: =M30+M62+M94 -> 0 | N31: =COUNT(H5:H29,H37:H61,H69:H93) -> 1 | O31: =COUNT(I5:I29,I37:I61,I69:I93) -> 9 | P31: =COUNTIF(G5:G29,"G*")+COUNTIF(G37:G61,"G*")+COUNTIF(G69:G93,"G*")+COUNTIF(G5:G29,"P*")+COUNTIF(G37:G61,"P*")+COUNTIF(G69:G93,"P*") -> 0 | Q31: =COUNTIF(G5:G29,"RSL")+COUNTIF(G37:G61,"RSL")+COUNTIF(G69:G93,"RSL") -> 0 | R31: CASH CLOSING | S31: =H31+L31-U28-U29-U30 -> 75 | T31: =H31+I31+L31+M31 -> 1040 | X31: Subtotal | Z31: =SUM(Z27:Z30) -> -2745
A32: TOTAL SALES | C32: =H31+I31+J31+K31 -> 1040 | F32: No of Cars | H32: =COUNT(B5:B29,B37:B61,B69:B93) -> 10 | I32: Average | K32: =C32/H32 -> 104 | N32: =H31/C32 -> 0.072115385 | O32: =I31/C32 -> 0.92788462 | P32: =K31/C32 -> 0 | Q32: =J31/C32 -> 0 | R32: CARD CLOSING | S32: =I31+M31 -> 965 | X32: B2 card | Z32: =I31 -> 965
A33: Daily Report | X33: Settlement | Z33: =SUM(Z31:Z32) -> -1780
A34: =A2 -> 22 - 5 - 2022 | H34: WEATHER | J34: =J2 -> SHOWER | L34: REPORT by | O34: =O2 -> HENDRA | R34: TOTAL STAFF | T34: =T2 -> 5
A36: No | B36: Docket No | C36: Reg No | D36: Mobile | E36: Gender | F36: TIME | G36: Service | H36: CASH | I36: CARD | J36: RSL | K36: GV | L36: GV CASH | M36: GV CARD | N36: O/Taker | O36: Comment | R36: NAME | S36: Time In | T36: Time out | U36: Total Hours
A37: =A29+1 -> 26 | J37: =IF(G37="RSL","55","0") -> 0 | K37: =IF(G37="GVS","37.5",IF(G37="GVM","41.5",IF(G37="GVL","50",IF(G37="PCS","45.8",IF(G37="PCM","50",IF(G37="PCL","58.3","0")))))) -> 0
A38: =A37+1 -> 27 | J38: =IF(G38="RSL","55","0") -> 0 | K38: =IF(G38="GVS","37.5",IF(G38="GVM","41.5",IF(G38="GVL","50",IF(G38="PCS","45.8",IF(G38="PCM","50",IF(G38="PCL","58.3","0")))))) -> 0
A39: =A38+1 -> 28 | J39: =IF(G39="RSL","55","0") -> 0 | K39: =IF(G39="GVS","37.5",IF(G39="GVM","41.5",IF(G39="GVL","50",IF(G39="PCS","45.8",IF(G39="PCM","50",IF(G39="PCL","58.3","0")))))) -> 0
A40: =A39+1 -> 29 | J40: =IF(G40="RSL","55","0") -> 0 | K40: =IF(G40="GVS","37.5",IF(G40="GVM","41.5",IF(G40="GVL","50",IF(G40="PCS","45.8",IF(G40="PCM","50",IF(G40="PCL","58.3","0")))))) -> 0
A41: =A40+1 -> 30 | J41: =IF(G41="RSL","55","0") -> 0 | K41: =IF(G41="GVS","37.5",IF(G41="GVM","41.5",IF(G41="GVL","50",IF(G41="PCS","45.8",IF(G41="PCM","50",IF(G41="PCL","58.3","0")))))) -> 0
A42: =A41+1 -> 31 | J42: =IF(G42="RSL","55","0") -> 0 | K42: =IF(G42="GVS","37.5",IF(G42="GVM","41.5",IF(G42="GVL","50",IF(G42="PCS","45.8",IF(G42="PCM","50",IF(G42="PCL","58.3","0")))))) -> 0
A43: =A42+1 -> 32 | J43: =IF(G43="RSL","55","0") -> 0 | K43: =IF(G43="GVS","37.5",IF(G43="GVM","41.5",IF(G43="GVL","50",IF(G43="PCS","45.8",IF(G43="PCM","50",IF(G43="PCL","58.3","0")))))) -> 0
A44: =A43+1 -> 33 | J44: =IF(G44="RSL","55","0") -> 0 | K44: =IF(G44="GVS","37.5",IF(G44="GVM","41.5",IF(G44="GVL","50",IF(G44="PCS","45.8",IF(G44="PCM","50",IF(G44="PCL","58.3","0")))))) -> 0
A45: =A44+1 -> 34 | J45: =IF(G45="RSL","55","0") -> 0 | K45: =IF(G45="GVS","37.5",IF(G45="GVM","41.5",IF(G45="GVL","50",IF(G45="PCS","45.8",IF(G45="PCM","50",IF(G45="PCL","58.3","0")))))) -> 0
A46: =A45+1 -> 35 | J46: =IF(G46="RSL","55","0") -> 0 | K46: =IF(G46="GVS","37.5",IF(G46="GVM","41.5",IF(G46="GVL","50",IF(G46="PCS","45.8",IF(G46="PCM","50",IF(G46="PCL","58.3","0")))))) -> 0
A47: =A46+1 -> 36 | J47: =IF(G47="RSL","55","0") -> 0 | K47: =IF(G47="GVS","37.5",IF(G47="GVM","41.5",IF(G47="GVL","50",IF(G47="PCS","45.8",IF(G47="PCM","50",IF(G47="PCL","58.3","0")))))) -> 0
A48: =A47+1 -> 37 | J48: =IF(G48="RSL","55","0") -> 0 | K48: =IF(G48="GVS","37.5",IF(G48="GVM","41.5",IF(G48="GVL","50",IF(G48="PCS","45.8",IF(G48="PCM","50",IF(G48="PCL","58.3","0")))))) -> 0
A49: =A48+1 -> 38 | J49: =IF(G49="RSL","55","0") -> 0 | K49: =IF(G49="GVS","37.5",IF(G49="GVM","41.5",IF(G49="GVL","50",IF(G49="PCS","45.8",IF(G49="PCM","50",IF(G49="PCL","58.3","0")))))) -> 0
... A61: =A60+1 -> 50 | J61: =IF(G61="RSL","55","0") -> 0 | K61: =IF(G61="GVS","37.5",IF(G61="GVM","41.5",IF(G61="GVL","50",IF(G61="PCS","45.8",IF(G61="PCM","50",IF(G61="PCL","58.3","0")))))) -> 0
A62: Page total | H62: =SUM(H37:H61) -> 0 | I62: =SUM(I37:I61) -> 0 | J62: =J61+J60+J59+J58+J57+J56+J55+J54+J53+J52+J51+J50+J49+J48+J47+J46+J45+J44+J43+J42+J41+J40+J39+J38+J37 -> 0 | K62: =K61+K60+K59+K58+K57+K56+K55+K54+K53+K52+K51+K50+K49+K48+K47+K46+K45+K44+K43+K42+K41+K40+K39+K38+K37 -> 0 | L62: =SUM(L37:L61) -> 0 | M62: =SUM(M37:M61) -> 0
R64: Page: 2
A65: Daily Report
A66: =A34 -> 22 - 5 - 2022 | H66: WEATHER | J66: =J34 -> SHOWER | L66: REPORT by | O66: =O34 -> HENDRA | R66: TOTAL STAFF | T66: =T34 -> 5
A68: No | B68: Docket No | C68: Reg No | D68: Mobile | E68: Gender | F68: TIME | G68: Service | H68: CASH | I68: CARD | J68: RSL | K68: GV | L68: GV CASH | M68: GV CARD | N68: O/Taker | O68: Comment | R68: NAME | S68: Time In | T68: Time out | U68: Total Hours
A69: =A61+1 -> 51 | J69: =IF(G69="RSL","55","0") -> 0 | K69: =IF(G69="GVS","37.5",IF(G69="GVM","41.5",IF(G69="GVL","50",IF(G69="PCS","45.8",IF(G69="PCM","50",IF(G69="PCL","58.3","0")))))) -> 0
A70: =A69+1 -> 52 | J70: =IF(G70="RSL","55","0") -> 0 | K70: =IF(G70="GVS","37.5",IF(G70="GVM","41.5",IF(G70="GVL","50",IF(G70="PCS","45.8",IF(G70="PCM","50",IF(G70="PCL","58.3","0")))))) -> 0
A71: =A70+1 -> 53 | J71: =IF(G71="RSL","55","0") -> 0 | K71: =IF(G71="GVS","37.5",IF(G71="GVM","41.5",IF(G71="GVL","50",IF(G71="PCS","45.8",IF(G71="PCM","50",IF(G71="PCL","58.3","0")))))) -> 0
A72: =A71+1 -> 54 | J72: =IF(G72="RSL","55","0") -> 0 | K72: =IF(G72="GVS","37.5",IF(G72="GVM","41.5",IF(G72="GVL","50",IF(G72="PCS","45.8",IF(G72="PCM","50",IF(G72="PCL","58.3","0")))))) -> 0
A73: =A72+1 -> 55 | J73: =IF(G73="RSL","55","0") -> 0 | K73: =IF(G73="GVS","37.5",IF(G73="GVM","41.5",IF(G73="GVL","50",IF(G73="PCS","45.8",IF(G73="PCM","50",IF(G73="PCL","58.3","0")))))) -> 0
A74: =A73+1 -> 56 | J74: =IF(G74="RSL","55","0") -> 0 | K74: =IF(G74="GVS","37.5",IF(G74="GVM","41.5",IF(G74="GVL","50",IF(G74="PCS","45.8",IF(G74="PCM","50",IF(G74="PCL","58.3","0")))))) -> 0
A75: =A74+1 -> 57 | J75: =IF(G75="RSL","55","0") -> 0 | K75: =IF(G75="GVS","37.5",IF(G75="GVM","41.5",IF(G75="GVL","50",IF(G75="PCS","45.8",IF(G75="PCM","50",IF(G75="PCL","58.3","0")))))) -> 0
A76: =A75+1 -> 58 | J76: =IF(G76="RSL","55","0") -> 0 | K76: =IF(G76="GVS","37.5",IF(G76="GVM","41.5",IF(G76="GVL","50",IF(G76="PCS","45.8",IF(G76="PCM","50",IF(G76="PCL","58.3","0")))))) -> 0
A77: =A76+1 -> 59 | J77: =IF(G77="RSL","55","0") -> 0 | K77: =IF(G77="GVS","37.5",IF(G77="GVM","41.5",IF(G77="GVL","50",IF(G77="PCS","45.8",IF(G77="PCM","50",IF(G77="PCL","58.3","0")))))) -> 0
A78: =A77+1 -> 60 | J78: =IF(G78="RSL","55","0") -> 0 | K78: =IF(G78="GVS","37.5",IF(G78="GVM","41.5",IF(G78="GVL","50",IF(G78="PCS","45.8",IF(G78="PCM","50",IF(G78="PCL","58.3","0")))))) -> 0
A79: =A78+1 -> 61 | J79: =IF(G79="RSL","55","0") -> 0 | K79: =IF(G79="GVS","37.5",IF(G79="GVM","41.5",IF(G79="GVL","50",IF(G79="PCS","45.8",IF(G79="PCM","50",IF(G79="PCL","58.3","0")))))) -> 0
A80: =A79+1 -> 62 | J80: =IF(G80="RSL","55","0") -> 0 | K80: =IF(G80="GVS","37.5",IF(G80="GVM","41.5",IF(G80="GVL","50",IF(G80="PCS","45.8",IF(G80="PCM","50",IF(G80="PCL","58.3","0")))))) -> 0
A81: =A80+1 -> 63 | J81: =IF(G81="RSL","55","0") -> 0 | K81: =IF(G81="GVS","37.5",IF(G81="GVM","41.5",IF(G81="GVL","50",IF(G81="PCS","45.8",IF(G81="PCM","50",IF(G81="PCL","58.3","0")))))) -> 0
... A93: =A92+1 -> 75 | J93: =IF(G93="RSL","55","0") -> 0 | K93: =IF(G93="GVS","37.5",IF(G93="GVM","41.5",IF(G93="GVL","50",IF(G93="PCS","45.8",IF(G93="PCM","50",IF(G93="PCL","58.3","0")))))) -> 0
A94: Page total | H94: =SUM(H69:H93) -> 0 | I94: =SUM(I69:I93) -> 0 | J94: =J93+J92+J91+J90+J89+J88+J87+J86+J85+J84+J83+J82+J81+J80+J79+J78+J77+J76+J75+J74+J73+J72+J71+J70+J69 -> 0 | K94: =K93+K92+K91+K90+K89+K88+K87+K86+K85+K84+K83+K82+K81+K80+K79+K78+K77+K76+K75+K74+K73+K72+K71+K70+K69 -> 0 | L94: =SUM(L69:L93) -> 0 | M94: =SUM(M69:M93) -> 0
R96: Page: 3

Sheet WEEKLY TOTAL
E1: CARS | H1: AMOUNT | L1: PERCENTAGE | Q1: TOTAL CARS | V1: TOTAL AMOUNT | AA1: AVERAGE
A2: MON | B2: Cash | E2: =MON!N31 -> 4 | H2: =MON!S31 -> 875 | L2: =MON!N32 -> 0.14837896 | Q2: =SUM(E2:G5) -> 26 | V2: =SUM(H2,H3,H5) -> 3050 | AA2: =V2/Q2 -> 117.30769
B3: Card | E3: =MON!O31 -> 15 | H3: =MON!S32 -> 1790 | L3: =MON!O32 -> 0.66399585
B4: GV | E4: =MON!P31 -> 3 | H4: =MON!K31 -> 120.8 | L4: =MON!P32 -> 0.044810446
B5: RSL | E5: =MON!Q31 -> 4 | H5: =MON!J31 -> 385 | L5: =MON!Q32 -> 0.14281475
B6: hrs | E6: =MON!U16 -> 42.5 | H6: no. staff | L6: =MON!T2 -> 5
A7: TUE | B7: Cash | E7: =TUE!N31 -> 3 | H7: =TUE!S31 -> 130 | L7: =TUE!N32 -> 0.076734193 | Q7: =SUM(E7:G10) -> 20 | V7: =SUM(H7,H8,H10) -> 1965 | AA7: =V7/Q7 -> 98.25
B8: Card | E8: =TUE!O31 -> 12 | H8: =TUE!S32 -> 1670 | L8: =TUE!O32 -> 0.70536431
B9: GV | E9: =TUE!P31 -> 3 | H9: =TUE!K31 -> 204.16 | L9: =TUE!P32 -> 0.1205081
B10: RSL | E10: =TUE!Q31 -> 2 | H10: =TUE!J31 -> 165 | L10: =TUE!Q32 -> 0.097393398
B11: hrs | E11: =TUE!U16 -> 39.25 | H11: no. staff | L11: =TUE!T2 -> 5
A12: WED | B12: Cash | E12: =WED!N31 -> 1 | H12: =WED!S31 -> 70 | L12: =WED!N32 -> 0.029872147 | Q12: =SUM(E12:G15) -> 18 | V12: =SUM(H12,H13,H15) -> 2935 | AA12: =V12/Q12 -> 163.05556
B13: Card | E13: =WED!O31 -> 14 | H13: =WED!S32 -> 2865 | L13: =WED!O32 -> 0.90256559
B14: GV | E14: =WED!P31 -> 3 | H14: =WED!K31 -> 158.32 | L14: =WED!P32 -> 0.067562262
B15: RSL | E15: =WED!Q31 -> 0 | H15: =WED!J31 -> 0 | L15: =WED!Q32 -> 0
B16: hrs | E16: =WED!U16 -> 49 | H16: no. staff | L16: =WED!T2 -> 6
A17: THU | B17: Cash | E17: =THU!N31 -> 1 | H17: =THU!S31 -> 75 | L17: =THU!N32 -> 0.042372881 | Q17: =SUM(E17:G20) -> 20 | V17: =SUM(H17,H18,H20) -> 2120 | AA17: =V17/Q17 -> 106
B18: Card | E18: =THU!O31 -> 16 | H18: =THU!S32 -> 1990 | L18: =THU!O32 -> 0.8559322
B19: GV | E19: =THU!P31 -> 2 | H19: =THU!K31 -> 125 | L19: =THU!P32 -> 0.070621469
B20: RSL | E20: =THU!Q31 -> 1 | H20: =THU!J31 -> 55 | L20: =THU!Q32 -> 0.031073446
B21: hrs | E21: =THU!U16 -> 44 | H21: no. staff | L21: =THU!T2 -> 6
A22: FR I | B22: Cash | E22: =FRI!N31 -> 1 | H22: =FRI!S31 -> 75 | L22: =FRI!N32 -> 0.16129032 | Q22: =SUM(E22:G25) -> 6 | V22: =SUM(H22,H23,H25) -> 465 | AA22: =V22/Q22 -> 77.5
B23: Card | E23: =FRI!O31 -> 5 | H23: =FRI!S32 -> 390 | L23: =FRI!O32 -> 0.83870968
B24: GV | E24: =FRI!P31 -> 0 | H24: =FRI!K31 -> 0 | L24: =FRI!P32 -> 0
B25: RSL | E25: =FRI!Q31 -> 0 | H25: =FRI!J31 -> 0 | L25: =FRI!Q32 -> 0
B26: hrs | E26: =FRI!U16 -> 27.5 | H26: no. staff | L26: =FRI!T2 -> 4
A27: SAT | B27: Cash | E27: =SAT!N31 -> 1 | H27: =SAT!S31 -> 75 | L27: =SAT!N32 -> 0.038249304 | Q27: =SUM(E27:G30) -> 20 | V27: =SUM(H27,H28,H30) -> 2115 | AA27: =V27/Q27 -> 105.75
B28: Card | E28: =SAT!O31 -> 15 | H28: =SAT!S32 -> 1985 | L28: =SAT!O32 -> 0.82108506
B29: GV | E29: =SAT!P31 -> 3 | H29: =SAT!K31 -> 220.82 | L29: =SAT!P32 -> 0.11261615
B30: RSL | E30: =SAT!Q31 -> 1 | H30: =SAT!J31 -> 55 | L30: =SAT!Q32 -> 0.028049489
B31: hrs | E31: =SAT!U16 -> 42.75 | H31: no. staff | L31: =SAT!T2 -> 5
A32: SUN | B32: Cash | E32: =SUN!N31 -> 1 | H32: =SUN!S31 -> 75 | L32: =SUN!N32 -> 0.072115385 | Q32: =SUM(E32:G35) -> 10 | V32: =SUM(H32,H33,H35) -> 1040 | AA32: =V32/Q32 -> 104
B33: Card | E33: =SUN!O31 -> 9 | H33: =SUN!S32 -> 965 | L33: =SUN!O32 -> 0.92788462
B34: GV | E34: =SUN!P31 -> 0 | H34: =SUN!K31 -> 0 | L34: =SUN!P32 -> 0
B35: RSL | E35: =SUN!Q31 -> 0 | H35: =SUN!J31 -> 0 | L35: =SUN!Q32 -> 0
B36: hrs | E36: =SUN!U16 -> 31.75 | H36: no. staff | L36: =SUN!T2 -> 5
A37: TOTAL CARS | E37: TOTAL SALES | K37: AVERAGE | O37: RSL | T37: GV | Y37: GV SOLD
A39: =SUM(Q2:U35) -> 120 | E39: =SUM(V2:Z35) -> 13690 | K39: =E39/A39 -> 114.08333 | O39: =SUM(MON:SUN!Q31) -> 8 | T39: =SUM(MON:SUN!P31) -> 14 | Y39: =SUM(MON:SUN!S19) -> 5
O41: =SUM(MON:SUN!J31) -> 660 | T41: =SUM(MON:SUN!K31) -> 829.1 | Y41: =SUM(MON:SUN!T19) -> 2550
A43: TOTAL CASH | F43: TOTAL CARD | K43: TOTAL RSL | P43: TOTAL GV | U43: STAFF HRS | Z43: no. staff
A45: =SUM(H2,H7,H12,H17,H22,H27,H32) -> 1375 | F45: =SUM(,H3,H8,H13,H18,H23,H28,H33) -> 11655 | K45: =SUM(H5,H10,H15,H20,H25,H30,H35) -> 660 | P45: =SUM(H4,H9,H14,H19,H24,H29,H34) -> 829.1 | U45: =SUM(E6,E11,E16,E21,E26,E31,E36) -> 276.75 | Z45: =SUM(L6,L11,L16,L21,L26,L31,L36) -> 36
A49: =A45/E39 -> 0.10043828 | F49: =F45/E39 -> 0.85135135 | K49: =K45/E39 -> 0.048210373 | P49: =P45/E39 -> 0.060562454 | U49: =U45/7 -> 39.535714 | Z49: =U45/Z45 -> 7.6875
