Workbook

Sheet MON
A1: B2 Daily Report
A2: 25 - 4 - 2022 | H2: WEATHER | J2: CLOUDY | L2: REPORT BY | O2: JOHN | R2: TOTAL STAFF | T2: 4 | X2: Merchant machine usage at B2 | AA2: Settle amount | AI2: Merchant machine usage at GA | AL2: Settle amount
A4: No | B4: Docket No | C4: Reg No | D4: Mobile | E4: Gender | F4: TIME | G4: Service | H4: CASH | I4: CARD | J4: RSL | K4: GV | L4: GV CASH | M4: GV CARD | N4: O/Taker | O4: Comment | R4: NAME | S4: Time In | T4: Time out | U4: Total Hours | Z4: B2 machine | AA4: BLH machine | AB4: Wongo | AE4: B2 machine | AF4: BLH machine | AG4: Wongo | AK4: GA machine | AL4: BLH machine | AM4: Wongo | AP4: GA machine | AQ4: BLH machine | AR4: Wongo
A5: 1 | B5: 3098 | C5: CTK90W | D5: 0418285867 | E5: F | F5: 1245 | G5: H/AMR | H5: 200 | J5: =IF(G5="RSL","55","0") -> 0 | K5: =IF(G5="GVS","37.5",IF(G5="GVM","41.5",IF(G5="GVL","50",IF(G5="PCS","45.8",IF(G5="PCM","50",IF(G5="PCL","58.3","0")))))) -> 0 | N5: JOHN | R5: JOHN | S5: 0.5 | T5: 0.71875 | U5: =(T5-S5)*24 -> 5.25 | X5: NOV | Y5: 1 | AD5: 16 | AI5: NOV | AJ5: 1 | AO5: 16
A6: 2 | B6: 3099 | C6: DHV71G | D6: 0427677472 | E6: F | F6: 1250 | G6: GV2 | J6: =IF(G6="RSL","55","0") -> 0 | K6: =IF(G6="GVS","37.5",IF(G6="GVM","41.5",IF(G6="GVL","50",IF(G6="PCS","45.8",IF(G6="PCM","50",IF(G6="PCL","58.3","0")))))) -> 0 | N6: JOHN | O6: 202749.62 | R6: ARIANTO | S6: 0.5 | T6: 0.66666667 | U6: =(T6-S6)*24 -> 4 | W6: M | Y6: 2 | AD6: 17 | AJ6: 2 | AO6: 17
A7: 3 | B7: 3100 | C7: QU11ET | D7: 0400004755 | E7: M | F7: 1300 | G7: H | I7: 140 | J7: =IF(G7="RSL","55","0") -> 0 | K7: =IF(G7="GVS","37.5",IF(G7="GVM","41.5",IF(G7="GVL","50",IF(G7="PCS","45.8",IF(G7="PCM","50",IF(G7="PCL","58.3","0")))))) -> 0 | N7: JOHN | O7: TAX | R7: KUROSH | S7: 0.45833333 | T7: 0.71875 | U7: =(T7-S7)*24 -> 6.25 | W7: F | Y7: 3 | AD7: 18 | AJ7: 3 | AO7: 18
A8: 4 | B8: 3101 | C8: EEE905 | D8: 0418392801 | E8: F | F8: 1320 | G8: X | I8: 95 | J8: =IF(G8="RSL","55","0") -> 0 | K8: =IF(G8="GVS","37.5",IF(G8="GVM","41.5",IF(G8="GVL","50",IF(G8="PCS","45.8",IF(G8="PCM","50",IF(G8="PCL","58.3","0")))))) -> 0 | N8: JOHN | R8: KEVIN | S8: 0.5 | T8: 0.71875 | U8: =(T8-S8)*24 -> 5.25 | Y8: 4 | AD8: 19 | AJ8: 4 | AO8: 19
A9: 5 | B9: 3102 | C9: DHR56G | D9: 0421787989 | E9: M | F9: 1430 | G9: X | I9: 95 | J9: =IF(G9="RSL","55","0") -> 0 | K9: =IF(G9="GVS","37.5",IF(G9="GVM","41.5",IF(G9="GVL","50",IF(G9="PCS","45.8",IF(G9="PCM","50",IF(G9="PCL","58.3","0")))))) -> 0 | N9: JOHN | R9: JUNIOR | S9: 0.65625 | T9: 0.71875 | U9: =(T9-S9)*24 -> 1.5 | X9: EXCL RSL | Y9: 5 | AD9: 20 | AJ9: 5 | AO9: 20
A10: 6 | B10: 3103 | C10: CC26XO | D10: 0431978611 | E10: F | F10: 1450 | G10: W/O | I10: 130 | J10: =IF(G10="RSL","55","0") -> 0 | K10: =IF(G10="GVS","37.5",IF(G10="GVM","41.5",IF(G10="GVL","50",IF(G10="PCS","45.8",IF(G10="PCM","50",IF(G10="PCL","58.3","0")))))) -> 0 | N10: JOHN | R10: VINNY | S10: 0.65625 | T10: 0.69791667 | U10: =(T10-S10)*24 -> 1 | Y10: 6 | AD10: 21 | AJ10: 6 | AO10: 21
A11: 7 | B11: 3104 | C11: BNE03Q | D11: 0447266193 | E11: M | F11: 1510 | G11: W/O | I11: 75 | J11: =IF(G11="RSL","55","0") -> 0 | K11: =IF(G11="GVS","37.5",IF(G11="GVM","41.5",IF(G11="GVL","50",IF(G11="PCS","45.8",IF(G11="PCM","50",IF(G11="PCL","58.3","0")))))) -> 0 | N11: JOHN | U11: =(T11-S11)*24 -> 0 | Y11: 7 | AD11: 22 | AJ11: 7 | AO11: 22
A12: 8 | B12: 3105 | C12: NBX94X | D12: 0412322656 | E12: M | F12: 1510 | G12: X/ST | I12: 280 | J12: =IF(G12="RSL","55","0") -> 0 | K12: =IF(G12="GVS","37.5",IF(G12="GVM","41.5",IF(G12="GVL","50",IF(G12="PCS","45.8",IF(G12="PCM","50",IF(G12="PCL","58.3","0")))))) -> 0 | N12: JOHN | U12: =(T12-S12)*24 -> 0 | Y12: 8 | AD12: 23 | AJ12: 8 | AO12: 23
A13: 9 | B13: 3106 | C13: MARY | D13: 0410445403 | E13: M | F13: 1530 | G13: X | I13: 95 | J13: =IF(G13="RSL","55","0") -> 0 | K13: =IF(G13="GVS","37.5",IF(G13="GVM","41.5",IF(G13="GVL","50",IF(G13="PCS","45.8",IF(G13="PCM","50",IF(G13="PCL","58.3","0")))))) -> 0 | N13: JOHN | O13: TAX | U13: =(T13-S13)*24 -> 0 | Y13: 9 | AD13: 24 | AJ13: 9 | AO13: 24
A14: 10 | B14: 3107 | C14: SC6221 | D14: 0418249876 | E14: F | F14: 1550 | G14: X | I14: 95 | J14: =IF(G14="RSL","55","0") -> 0 | K14: =IF(G14="GVS","37.5",IF(G14="GVM","41.5",IF(G14="GVL","50",IF(G14="PCS","45.8",IF(G14="PCM","50",IF(G14="PCL","58.3","0")))))) -> 0 | N14: JOHN | U14: =(T14-S14)*24 -> 0 | Y14: 10 | AD14: 25 | AJ14: 10 | AO14: 25
A15: 11 | J15: =IF(G15="RSL","55","0") -> 0 | K15: =IF(G15="GVS","37.5",IF(G15="GVM","41.5",IF(G15="GVL","50",IF(G15="PCS","45.8",IF(G15="PCM","50",IF(G15="PCL","58.3","0")))))) -> 0 | U15: =(T15-S15)*24 -> 0 | Y15: 11 | AD15: 26 | AJ15: 11 | AO15: 26
A16: 12 | J16: =IF(G16="RSL","55","0") -> 0 | K16: =IF(G16="GVS","37.5",IF(G16="GVM","41.5",IF(G16="GVL","50",IF(G16="PCS","45.8",IF(G16="PCM","50",IF(G16="PCL","58.3","0")))))) -> 0 | R16: =H32/U16 -> 0.43010753 | S16: =H32/(U16-U5) -> 0.55555556 | T16: =C32/U16 -> 51.827957 | U16: =SUM(U5:U15) -> 23.25 | Y16: 12 | AD16: 27 | AJ16: 12 | AO16: 27
A17: 13 | J17: =IF(G17="RSL","55","0") -> 0 | K17: =IF(G17="GVS","37.5",IF(G17="GVM","41.5",IF(G17="GVL","50",IF(G17="PCS","45.8",IF(G17="PCM","50",IF(G17="PCL","58.3","0")))))) -> 0 | R17: Cars/T Hr ① | S17: Cars/T Hr ② | T17: Sales/T Hr | U17: Total Hours | Y17: 13 | AD17: 28 | AJ17: 13 | AO17: 28
A18: 14 | J18: =IF(G18="RSL","55","0") -> 0 | K18: =IF(G18="GVS","37.5",IF(G18="GVM","41.5",IF(G18="GVL","50",IF(G18="PCS","45.8",IF(G18="PCM","50",IF(G18="PCL","58.3","0")))))) -> 0 | R18: ITEM | S18: QTY | T18: AMT | U18: RMKS | Y18: 14 | AD18: 29 | AJ18: 14 | AO18: 29
A19: 15 | J19: =IF(G19="RSL","55","0") -> 0 | K19: =IF(G19="GVS","37.5",IF(G19="GVM","41.5",IF(G19="GVL","50",IF(G19="PCS","45.8",IF(G19="PCM","50",IF(G19="PCL","58.3","0")))))) -> 0 | R19: GV | S19: =COUNT(L5:M29,L37:M61,L69:M93) -> 0 | T19: =SUM(L5:M29,L37:M61,L69:M93) -> 0 | Y19: 15 | AD19: 30 | AJ19: 15 | AO19: 30
A20: 16 | J20: =IF(G20="RSL","55","0") -> 0 | K20: =IF(G20="GVS","37.5",IF(G20="GVM","41.5",IF(G20="GVL","50",IF(G20="PCS","45.8",IF(G20="PCM","50",IF(G20="PCL","58.3","0")))))) -> 0 | AD20: 31 | AO20: 31
A21: 17 | J21: =IF(G21="RSL","55","0") -> 0 | K21: =IF(G21="GVS","37.5",IF(G21="GVM","41.5",IF(G21="GVL","50",IF(G21="PCS","45.8",IF(G21="PCM","50",IF(G21="PCL","58.3","0")))))) -> 0
A22: 18 | J22: =IF(G22="RSL","55","0") -> 0 | K22: =IF(G22="GVS","37.5",IF(G22="GVM","41.5",IF(G22="GVL","50",IF(G22="PCS","45.8",IF(G22="PCM","50",IF(G22="PCL","58.3","0")))))) -> 0 | AD22: Total | AE22: =SUM(Z5:Z19,AE5:AE20) -> 0 | AF22: =SUM(AA5:AA19,AF5:AF20,) -> 0 | AG22: =SUM(AB5:AB19,AG5:AG20) -> 0 | AO22: Total | AP22: =SUM(AK5:AK19,AP5:AP20) -> 0 | AQ22: =SUM(AL5:AL19,AQ5:AQ20,) -> 0 | AR22: =SUM(AM5:AM19,AR5:AR20) -> 0
A23: 19 | J23: =IF(G23="RSL","55","0") -> 0 | K23: =IF(G23="GVS","37.5",IF(G23="GVM","41.5",IF(G23="GVL","50",IF(G23="PCS","45.8",IF(G23="PCM","50",IF(G23="PCL","58.3","0")))))) -> 0
A24: 20 | J24: =IF(G24="RSL","55","0") -> 0 | K24: =IF(G24="GVS","37.5",IF(G24="GVM","41.5",IF(G24="GVL","50",IF(G24="PCS","45.8",IF(G24="PCM","50",IF(G24="PCL","58.3","0")))))) -> 0 | R24: SMALL | S24: MEDIUM | T24: LARGE | U24: TOTAL | AD24: B2/GA TOTAL | AE24: B2 machine | AF24: GA machine | AG24: BLH machine | AH24: Wongo machine | AI24: Sub total
A25: 21 | J25: =IF(G25="RSL","55","0") -> 0 | K25: =IF(G25="GVS","37.5",IF(G25="GVM","41.5",IF(G25="GVL","50",IF(G25="PCS","45.8",IF(G25="PCM","50",IF(G25="PCL","58.3","0")))))) -> 0 | R25: =COUNTIF(G5:G29,"GV1")+COUNTIF(G37:G61,"GV1")+COUNTIF(G69:G93,"GV1") -> 0 | S25: =COUNTIF(G5:G29,"GV2")+COUNTIF(G37:G61,"GV2")+COUNTIF(G69:G93,"GV2") -> 1 | T25: =COUNTIF(G5:G29,"GV3")+COUNTIF(G37:G61,"GV3")+COUNTIF(G69:G93,"GV3") -> 0 | U25: =((C32+(R26+S26+T26)*0.5)) -> 1225.75 | AD25: =SUM(AE25:AF25) -> 0 | AE25: =SUM(AE22) -> 0 | AF25: =SUM(AP22) -> 0 | AG25: =SUM(AF22+AQ22) -> 0 | AH25: =AG22+AR22 -> 0 | AI25: =SUM(AE25:AH25) -> 0
A26: 22 | J26: =IF(G26="RSL","55","0") -> 0 | K26: =IF(G26="GVS","37.5",IF(G26="GVM","41.5",IF(G26="GVL","50",IF(G26="PCS","45.8",IF(G26="PCM","50",IF(G26="PCL","58.3","0")))))) -> 0 | R26: =R25*37.5 -> 0 | S26: =S25*41.5 -> 41.5 | T26: =T25*50 -> 0 | X26: Branch cards
A27: 23 | J27: =IF(G27="RSL","55","0") -> 0 | K27: =IF(G27="GVS","37.5",IF(G27="GVM","41.5",IF(G27="GVL","50",IF(G27="PCS","45.8",IF(G27="PCM","50",IF(G27="PCL","58.3","0")))))) -> 0 | R27: Expense | X27: 1 | Z27: -2745
A28: 24 | J28: =IF(G28="RSL","55","0") -> 0 | K28: =IF(G28="GVS","37.5",IF(G28="GVM","41.5",IF(G28="GVL","50",IF(G28="PCS","45.8",IF(G28="PCM","50",IF(G28="PCL","58.3","0")))))) -> 0 | X28: 2
A29: 25 | J29: =IF(G29="RSL","55","0") -> 0 | K29: =IF(G29="GVS","37.5",IF(G29="GVM","41.5",IF(G29="GVL","50",IF(G29="PCS","45.8",IF(G29="PCM","50",IF(G29="PCL","58.3","0")))))) -> 0 | X29: 3
A30: Page total | H30: =SUM(H5:H29) -> 200 | I30: =SUM(I5:I29) -> 1005 | J30: =J5+J6+J7+J8+J9+J10+J11+J12+J13+J14+J15+J16+J18+J19+J17+J20+J22+J23+J21+J24+J25+J26+J27+J28+J29 -> 0 | K30: =K5+K6+K7+K8+K9+K10+K11+K12+K13+K14+K15+K16+K18+K19+K17+K20+K22+K23+K21+K24+K25+K26+K27+K28+K29 -> 0 | L30: =SUM(L5:L29) -> 0 | M30: =SUM(M5:M29) -> 0 | N30: CASH | O30: CARD | P30: GV | Q30: RSL | X30: 4
A31: Daily Total | H31: =H30+H62+H94 -> 200 | I31: =I30+I62+I94 -> 1005 | J31: =J30+J62+J94 -> 0 | K31: =K30+K62+K94 -> 0 | L31: =L30+L62+L94 -> 0 | M31: =M30+M62+M94 -> 0 | N31: =COUNT(H5:H29,H37:H61,H69:H93) -> 1 | O31: =COUNT(I5:I29,I37:I61,I69:I93) -> 8 | P31: =COUNTIF(G5:G29,"G*")+COUNTIF(G37:G61,"G*")+COUNTIF(G69:G93,"G*")+COUNTIF(G5:G29,"P*")+COUNTIF(G37:G61,"P*")+COUNTIF(G69:G93,"P*") -> 1 | Q31: =COUNTIF(G5:G29,"RSL")+COUNTIF(G37:G61,"RSL")+COUNTIF(G69:G93,"RSL") -> 0 | R31: CASH CLOSING | S31: =H31+L31-U28-U29-U30 -> 200 | T31: =H31+I31+L31+M31 -> 1205 | X31: Subtotal | Z31: =SUM(Z27:Z30) -> -2745
A32: TOTAL SALES | C32: =H31+I31+J31+K31 -> 1205 | F32: No of Cars | H32: =COUNT(B5:B29,B37:B61,B69:B93) -> 10 | I32: Average | K32: =C32/H32 -> 120.5 | N32: =H31/C32 -> 0.1659751 | O32: =I31/C32 -> 0.8340249 | P32: =K31/C32 -> 0 | Q32: =J31/C32 -> 0 | R32: CARD CLOSING | S32: =I31+M31 -> 1005 | X32: B2 card | Z32: =I31 -> 1005
A33: Daily Report | X33: Settlement | Z33: =SUM(Z31:Z32) -> -1740
A34: =A2 -> 25 - 4 - 2022 | H34: WEATHER | J34: =J2 -> CLOUDY | L34: REPORT by | O34: =O2 -> JOHN | R34: TOTAL STAFF | T34: =T2 -> 4
A36: No | B36: Docket No | C36: Reg No | D36: Mobile | E36: Gender | F36: TIME | G36: Service | H36: CASH | I36: CARD | J36: RSL | K36: GV | L36: GV CASH | M36: GV CARD | N36: O/Taker | O36: Comment | R36: NAME | S36: Time In | T36: Time out | U36: Total Hours
A37: =A29+1 -> 26 | J37: =IF(G37="RSL","55","0") -> 0 | K37: =IF(G37="GVS","37.5",IF(G37="GVM","41.5",IF(G37="GVL","50",IF(G37="PCS","45.8",IF(G37="PCM","50",IF(G37="PCL","58.3","0")))))) -> 0
A38: =A37+1 -> 27 | J38: =IF(G38="RSL","55","0") -> 0 | K38: =IF(G38="GVS","37.5",IF(G38="GVM","41.5",IF(G38="GVL","50",IF(G38="PCS","45.8",IF(G38="PCM","50",IF(G38="PCL","58.3","0")))))) -> 0
A39: =A38+1 -> 28 | J39: =IF(G39="RSL","55","0") -> 0 | K39: =IF(G39="GVS","37.5",IF(G39="GVM","41.5",IF(G39="GVL","50",IF(G39="PCS","45.8",IF(G39="PCM","50",IF(G39="PCL","58.3","0")))))) -> 0
A40: =A39+1 -> 29 | J40: =IF(G40="RSL","55","0") -> 0 | K40: =IF(G40="GVS","37.5",IF(G40="GVM","41.5",IF(G40="GVL","50",IF(G40="PCS","45.8",IF(G40="PCM","50",IF(G40="PCL","58.3","0")))))) -> 0
A41: =A40+1 -> 30 | J41: =IF(G41="RSL","55","0") -> 0 | K41: =IF(G41="GVS","37.5",IF(G41="GVM","41.5",IF(G41="GVL","50",IF(G41="PCS","45.8",IF(G41="PCM","50",IF(G41="PCL","58.3","0")))))) -> 0
A42: =A41+1 -> 31 | J42: =IF(G42="RSL","55","0") -> 0 | K42: =IF(G42="GVS","37.5",IF(G42="GVM","41.5",IF(G42="GVL","50",IF(G42="PCS","45.8",IF(G42="PCM","50",IF(G42="PCL","58.3","0")))))) -> 0
A43: =A42+1 -> 32 | J43: =IF(G43="RSL","55","0") -> 0 | K43: =IF(G43="GVS","37.5",IF(G43="GVM","41.5",IF(G43="GVL","50",IF(G43="PCS","45.8",IF(G43="PCM","50",IF(G43="PCL","58.3","0")))))) -> 0
A44: =A43+1 -> 33 | J44: =IF(G44="RSL","55","0") -> 0 | K44: =IF(G44="GVS","37.5",IF(G44="GVM","41.5",IF(G44="GVL","50",IF(G44="PCS","45.8",IF(G44="PCM","50",IF(G44="PCL","58.3","0")))))) -> 0
A45: =A44+1 -> 34 | J45: =IF(G45="RSL","55","0") -> 0 | K45: =IF(G45="GVS","37.5",IF(G45="GVM","41.5",IF(G45="GVL","50",IF(G45="PCS","45.8",IF(G45="PCM","50",IF(G45="PCL","58.3","0")))))) -> 0
A46: =A45+1 -> 35 | J46: =IF(G46="RSL","55","0") -> 0 | K46: =IF(G46="GVS","37.5",IF(G46="GVM","41.5",IF(G46="GVL","50",IF(G46="PCS","45.8",IF(G46="PCM","50",IF(G46="PCL","58.3","0")))))) -> 0
A47: =A46+1 -> 36 | J47: =IF(G47="RSL","55","0") -> 0 | K47: =IF(G47="GVS","37.5",IF(G47="GVM","41.5",IF(G47="GVL","50",IF(G47="PCS","45.8",IF(G47="PCM","50",IF(G47="PCL","58.3","0")))))) -> 0
A48: =A47+1 -> 37 | J48: =IF(G48="RSL","55","0") -> 0 | K48: =IF(G48="GVS","37.5",IF(G48="GVM","41.5",IF(G48="GVL","50",IF(G48="PCS","45.8",IF(G48="PCM","50",IF(G48="PCL","58.3","0")))))) -> 0
A49: =A48+1 -> 38 | J49: =IF(G49="RSL","55","0") -> 0 | K49: =IF(G49="GVS","37.5",IF(G49="GVM","41.5",IF(G49="GVL","50",IF(G49="PCS","45.8",IF(G49="PCM","50",IF(G49="PCL","58.3","0")))))) -> 0
... A61: =A60+1 -> 50 | J61: =IF(G61="RSL","55","0") -> 0 | K61: =IF(G61="GVS","37.5",IF(G61="GVM","41.5",IF(G61="GVL","50",IF(G61="PCS","45.8",IF(G61="PCM","50",IF(G61="PCL","58.3","0")))))) -> 0
A62: Page total | H62: =SUM(H37:H61) -> 0 | I62: =SUM(I37:I61) -> 0 | J62: =J61+J60+J59+J58+J57+J56+J55+J54+J53+J52+J51+J50+J49+J48+J47+J46+J45+J44+J43+J42+J41+J40+J39+J38+J37 -> 0 | K62: =K61+K60+K59+K58+K57+K56+K55+K54+K53+K52+K51+K50+K49+K48+K47+K46+K45+K44+K43+K42+K41+K40+K39+K38+K37 -> 0 | L62: =SUM(L37:L61) -> 0 | M62: =SUM(M37:M61) -> 0
R64: Page: 2
A65: Daily Report
A66: =A34 -> 25 - 4 - 2022 | H66: WEATHER | J66: =J34 -> CLOUDY | L66: REPORT by | O66: =O34 -> JOHN | R66: TOTAL STAFF | T66: =T34 -> 4
A68: No | B68: Docket No | C68: Reg No | D68: Mobile | E68: Gender | F68: TIME | G68: Service | H68: CASH | I68: CARD | J68: RSL | K68: GV | L68: GV CASH | M68: GV CARD | N68: O/Taker | O68: Comment | R68: NAME | S68: Time In | T68: Time out | U68: Total Hours
A69: =A61+1 -> 51 | J69: =IF(G69="RSL","55","0") -> 0 | K69: =IF(G69="GVS","37.5",IF(G69="GVM","41.5",IF(G69="GVL","50",IF(G69="PCS","45.8",IF(G69="PCM","50",IF(G69="PCL","58.3","0")))))) -> 0
A70: =A69+1 -> 52 | J70: =IF(G70="RSL","55","0") -> 0 | K70: =IF(G70="GVS","37.5",IF(G70="GVM","41.5",IF(G70="GVL","50",IF(G70="PCS","45.8",IF(G70="PCM","50",IF(G70="PCL","58.3","0")))))) -> 0
A71: =A70+1 -> 53 | J71: =IF(G71="RSL","55","0") -> 0 | K71: =IF(G71="GVS","37.5",IF(G71="GVM","41.5",IF(G71="GVL","50",IF(G71="PCS","45.8",IF(G71="PCM","50",IF(G71="PCL","58.3","0")))))) -> 0
A72: =A71+1 -> 54 | J72: =IF(G72="RSL","55","0") -> 0 | K72: =IF(G72="GVS","37.5",IF(G72="GVM","41.5",IF(G72="GVL","50",IF(G72="PCS","45.8",IF(G72="PCM","50",IF(G72="PCL","58.3","0")))))) -> 0
A73: =A72+1 -> 55 | J73: =IF(G73="RSL","55","0") -> 0 | K73: =IF(G73="GVS","37.5",IF(G73="GVM","41.5",IF(G73="GVL","50",IF(G73="PCS","45.8",IF(G73="PCM","50",IF(G73="PCL","58.3","0")))))) -> 0
A74: =A73+1 -> 56 | J74: =IF(G74="RSL","55","0") -> 0 | K74: =IF(G74="GVS","37.5",IF(G74="GVM","41.5",IF(G74="GVL","50",IF(G74="PCS","45.8",IF(G74="PCM","50",IF(G74="PCL","58.3","0")))))) -> 0
A75: =A74+1 -> 57 | J75: =IF(G75="RSL","55","0") -> 0 | K75: =IF(G75="GVS","37.5",IF(G75="GVM","41.5",IF(G75="GVL","50",IF(G75="PCS","45.8",IF(G75="PCM","50",IF(G75="PCL","58.3","0")))))) -> 0
A76: =A75+1 -> 58 | J76: =IF(G76="RSL","55","0") -> 0 | K76: =IF(G76="GVS","37.5",IF(G76="GVM","41.5",IF(G76="GVL","50",IF(G76="PCS","45.8",IF(G76="PCM","50",IF(G76="PCL","58.3","0")))))) -> 0
A77: =A76+1 -> 59 | J77: =IF(G77="RSL","55","0") -> 0 | K77: =IF(G77="GVS","37.5",IF(G77="GVM","41.5",IF(G77="GVL","50",IF(G77="PCS","45.8",IF(G77="PCM","50",IF(G77="PCL","58.3","0")))))) -> 0
A78: =A77+1 -> 60 | J78: =IF(G78="RSL","55","0") -> 0 | K78: =IF(G78="GVS","37.5",IF(G78="GVM","41.5",IF(G78="GVL","50",IF(G78="PCS","45.8",IF(G78="PCM","50",IF(G78="PCL","58.3","0")))))) -> 0
A79: =A78+1 -> 61 | J79: =IF(G79="RSL","55","0") -> 0 | K79: =IF(G79="GVS","37.5",IF(G79="GVM","41.5",IF(G79="GVL","50",IF(G79="PCS","45.8",IF(G79="PCM","50",IF(G79="PCL","58.3","0")))))) -> 0
A80: =A79+1 -> 62 | J80: =IF(G80="RSL","55","0") -> 0 | K80: =IF(G80="GVS","37.5",IF(G80="GVM","41.5",IF(G80="GVL","50",IF(G80="PCS","45.8",IF(G80="PCM","50",IF(G80="PCL","58.3","0")))))) -> 0
A81: =A80+1 -> 63 | J81: =IF(G81="RSL","55","0") -> 0 | K81: =IF(G81="GVS","37.5",IF(G81="GVM","41.5",IF(G81="GVL","50",IF(G81="PCS","45.8",IF(G81="PCM","50",IF(G81="PCL","58.3","0")))))) -> 0
... A93: =A92+1 -> 75 | J93: =IF(G93="RSL","55","0") -> 0 | K93: =IF(G93="GVS","37.5",IF(G93="GVM","41.5",IF(G93="GVL","50",IF(G93="PCS","45.8",IF(G93="PCM","50",IF(G93="PCL","58.3","0")))))) -> 0
A94: Page total | H94: =SUM(H69:H93) -> 0 | I94: =SUM(I69:I93) -> 0 | J94: =J93+J92+J91+J90+J89+J88+J87+J86+J85+J84+J83+J82+J81+J80+J79+J78+J77+J76+J75+J74+J73+J72+J71+J70+J69 -> 0 | K94: =K93+K92+K91+K90+K89+K88+K87+K86+K85+K84+K83+K82+K81+K80+K79+K78+K77+K76+K75+K74+K73+K72+K71+K70+K69 -> 0 | L94: =SUM(L69:L93) -> 0 | M94: =SUM(M69:M93) -> 0
R96: Page: 3

Sheet TUE
A1: B2 Daily Report
A2: 26 - 4 - 2022 | H2: WEATHER | J2: SHOWER | L2: REPORT BY | O2: HENDRA | R2: TOTAL STAFF | T2: 4 | X2: Merchant machine usage at B2 | AA2: Settle amount | AI2: Merchant machine usage at GA | AL2: Settle amount
A4: No | B4: Docket No | C4: Reg No | D4: Mobile | E4: Gender | F4: TIME | G4: Service | H4: CASH | I4: CARD | J4: RSL | K4: GV | L4: GV CASH | M4: GV CARD | N4: O/Taker | O4: Comment | R4: NAME | S4: Time In | T4: Time out | U4: Total Hours | Z4: B2 machine | AA4: BLH machine | AB4: Wongo | AE4: B2 machine | AF4: BLH machine | AG4: Wongo | AK4: GA machine | AL4: BLH machine | AM4: Wongo | AP4: GA machine | AQ4: BLH machine | AR4: Wongo
A5: 1 | B5: 3108 | C5: DLK18K | D5: 0410194666 | E5: M | F5: 1015 | G5: X | I5: 75 | J5: =IF(G5="RSL","55","0") -> 0 | K5: =IF(G5="GVS","37.5",IF(G5="GVM","41.5",IF(G5="GVL","50",IF(G5="PCS","45.8",IF(G5="PCM","50",IF(G5="PCL","58.3","0")))))) -> 0 | N5: JUNIOR | R5: HENDRA | S5: 0.33333333 | T5: 0.70833333 | U5: =(T5-S5)*24 -> 9 | X5: NOV | Y5: 1 | AD5: 16 | AI5: NOV | AJ5: 1 | AO5: 16
A6: 2 | B6: 3109 | C6: CKL001 | D6: 0400892000 | E6: F | F6: 1100 | G6: D | I6: 55 | J6: =IF(G6="RSL","55","0") -> 0 | K6: =IF(G6="GVS","37.5",IF(G6="GVM","41.5",IF(G6="GVL","50",IF(G6="PCS","45.8",IF(G6="PCM","50",IF(G6="PCL","58.3","0")))))) -> 0 | N6: HENDRA | R6: JUNIOR | S6: 0.33333333 | T6: 0.70833333 | U6: =(T6-S6)*24 -> 9 | W6: M | Y6: 2 | AD6: 17 | AJ6: 2 | AO6: 17
A7: 3 | B7: 3110 | C7: BCI71Z | D7: 0415366717 | E7: F | F7: 1120 | G7: D/ST | I7: 280 | J7: =IF(G7="RSL","55","0") -> 0 | K7: =IF(G7="GVS","37.5",IF(G7="GVM","41.5",IF(G7="GVL","50",IF(G7="PCS","45.8",IF(G7="PCM","50",IF(G7="PCL","58.3","0")))))) -> 0 | N7: HENDRA | R7: ARIANTO | S7: 0.375 | T7: 0.66666667 | U7: =(T7-S7)*24 -> 7 | W7: F | Y7: 3 | AD7: 18 | AJ7: 3 | AO7: 18
A8: 4 | B8: 3111 | C8: CLC26L | D8: 0403029383 | E8: F | F8: 1245 | G8: PCL | J8: =IF(G8="RSL","55","0") -> 0 | K8: =IF(G8="GVS","37.5",IF(G8="GVM","41.5",IF(G8="GVL","50",IF(G8="PCS","45.8",IF(G8="PCM","50",IF(G8="PCL","58.3","0")))))) -> 58.3 | N8: HENDRA | O8: 202869.83 | R8: VINNY | S8: 0.45833333 | T8: 0.70833333 | U8: =(T8-S8)*24 -> 6 | Y8: 4 | AD8: 19 | AJ8: 4 | AO8: 19
A9: 5 | B9: 3112 | C9: GBI | D9: 0415888891 | E9: M | F9: 1245 | G9: H | I9: 150 | J9: =IF(G9="RSL","55","0") -> 0 | K9: =IF(G9="GVS","37.5",IF(G9="GVM","41.5",IF(G9="GVL","50",IF(G9="PCS","45.8",IF(G9="PCM","50",IF(G9="PCL","58.3","0")))))) -> 0 | N9: HENDRA | O9: GEORGE CAR | U9: =(T9-S9)*24 -> 0 | X9: EXCL RSL | Y9: 5 | AD9: 20 | AJ9: 5 | AO9: 20
A10: 6 | B10: 3113 | C10: EQO59B | D10: 0402243008 | E10: F | F10: 1250 | G10: X | I10: 75 | J10: =IF(G10="RSL","55","0") -> 0 | K10: =IF(G10="GVS","37.5",IF(G10="GVM","41.5",IF(G10="GVL","50",IF(G10="PCS","45.8",IF(G10="PCM","50",IF(G10="PCL","58.3","0")))))) -> 0 | N10: HENDRA | U10: =(T10-S10)*24 -> 0 | Y10: 6 | AD10: 21 | AJ10: 6 | AO10: 21
A11: 7 | B11: 3114 | C11: DFM62L | D11: 0402690837 | E11: F | F11: 1315 | G11: D | H11: 95 | J11: =IF(G11="RSL","55","0") -> 0 | K11: =IF(G11="GVS","37.5",IF(G11="GVM","41.5",IF(G11="GVL","50",IF(G11="PCS","45.8",IF(G11="PCM","50",IF(G11="PCL","58.3","0")))))) -> 0 | N11: HENDRA | U11: =(T11-S11)*24 -> 0 | Y11: 7 | AD11: 22 | AJ11: 7 | AO11: 22
A12: 8 | B12: 3115 | C12: DTS62P | D12: 0449886933 | E12: M | F12: 1320 | G12: H | I12: 120 | J12: =IF(G12="RSL","55","0") -> 0 | K12: =IF(G12="GVS","37.5",IF(G12="GVM","41.5",IF(G12="GVL","50",IF(G12="PCS","45.8",IF(G12="PCM","50",IF(G12="PCL","58.3","0")))))) -> 0 | N12: HENDRA | U12: =(T12-S12)*24 -> 0 | Y12: 8 | AD12: 23 | AJ12: 8 | AO12: 23
A13: 9 | B13: 3116 | C13: EAH89D | D13: 94498870 | E13: F | F13: 1345 | G13: D | H13: 55 | J13: =IF(G13="RSL","55","0") -> 0 | K13: =IF(G13="GVS","37.5",IF(G13="GVM","41.5",IF(G13="GVL","50",IF(G13="PCS","45.8",IF(G13="PCM","50",IF(G13="PCL","58.3","0")))))) -> 0 | N13: HENDRA | U13: =(T13-S13)*24 -> 0 | Y13: 9 | AD13: 24 | AJ13: 9 | AO13: 24
A14: 10 | B14: 3117 | C14: DXF86Q | D14: 0425889988 | E14: F | F14: 1415 | G14: PCL | J14: =IF(G14="RSL","55","0") -> 0 | K14: 158.33 | N14: HENDRA | O14: 21051 4/6 5/6 | U14: =(T14-S14)*24 -> 0 | Y14: 10 | AD14: 25 | AJ14: 10 | AO14: 25
A15: 11 | B15: 3118 | C15: DJL54R | D15: 0408752956 | E15: M | F15: 1445 | G15: PCL | J15: =IF(G15="RSL","55","0") -> 0 | K15: =IF(G15="GVS","37.5",IF(G15="GVM","41.5",IF(G15="GVL","50",IF(G15="PCS","45.8",IF(G15="PCM","50",IF(G15="PCL","58.3","0")))))) -> 58.3 | N15: HENDRA | O15: # 2112062 3/6 | U15: =(T15-S15)*24 -> 0 | Y15: 11 | AD15: 26 | AJ15: 11 | AO15: 26
A16: 12 | B16: 3119 | C16: NBO55A | D16: 0416196666 | E16: M | F16: 1500 | G16: RSL | I16: 20 | J16: =IF(G16="RSL","55","0") -> 55 | K16: =IF(G16="GVS","37.5",IF(G16="GVM","41.5",IF(G16="GVL","50",IF(G16="PCS","45.8",IF(G16="PCM","50",IF(G16="PCL","58.3","0")))))) -> 0 | N16: HENDRA | O16: 202203049 | R16: =H32/U16 -> 0.41935484 | S16: =H32/(U16-U5) -> 0.59090909 | T16: =C32/U16 -> 41.959032 | U16: =SUM(U5:U15) -> 31 | Y16: 12 | AD16: 27 | AJ16: 12 | AO16: 27
A17: 13 | B17: 3120 | C17: LAU777 | D17: 0416462000 | E17: F | F17: 1510 | G17: PCS | J17: =IF(G17="RSL","55","0") -> 0 | K17: =IF(G17="GVS","37.5",IF(G17="GVM","41.5",IF(G17="GVL","50",IF(G17="PCS","45.8",IF(G17="PCM","50",IF(G17="PCL","58.3","0")))))) -> 45.8 | N17: HENDRA | O17: # 22012 1/6 | R17: Cars/T Hr ① | S17: Cars/T Hr ② | T17: Sales/T Hr | U17: Total Hours | Y17: 13 | AD17: 28 | AJ17: 13 | AO17: 28
A18: 14 | J18: =IF(G18="RSL","55","0") -> 0 | K18: =IF(G18="GVS","37.5",IF(G18="GVM","41.5",IF(G18="GVL","50",IF(G18="PCS","45.8",IF(G18="PCM","50",IF(G18="PCL","58.3","0")))))) -> 0 | R18: ITEM | S18: QTY | T18: AMT | U18: RMKS | Y18: 14 | AD18: 29 | AJ18: 14 | AO18: 29
A19: 15 | J19: =IF(G19="RSL","55","0") -> 0 | K19: =IF(G19="GVS","37.5",IF(G19="GVM","41.5",IF(G19="GVL","50",IF(G19="PCS","45.8",IF(G19="PCM","50",IF(G19="PCL","58.3","0")))))) -> 0 | R19: GV | S19: =COUNT(L5:M29,L37:M61,L69:M93) -> 0 | T19: =SUM(L5:M29,L37:M61,L69:M93) -> 0 | Y19: 15 | AD19: 30 | AJ19: 15 | AO19: 30
A20: 16 | J20: =IF(G20="RSL","55","0") -> 0 | K20: =IF(G20="GVS","37.5",IF(G20="GVM","41.5",IF(G20="GVL","50",IF(G20="PCS","45.8",IF(G20="PCM","50",IF(G20="PCL","58.3","0")))))) -> 0 | AD20: 31 | AO20: 31
A21: 17 | J21: =IF(G21="RSL","55","0") -> 0 | K21: =IF(G21="GVS","37.5",IF(G21="GVM","41.5",IF(G21="GVL","50",IF(G21="PCS","45.8",IF(G21="PCM","50",IF(G21="PCL","58.3","0")))))) -> 0
A22: 18 | J22: =IF(G22="RSL","55","0") -> 0 | K22: =IF(G22="GVS","37.5",IF(G22="GVM","41.5",IF(G22="GVL","50",IF(G22="PCS","45.8",IF(G22="PCM","50",IF(G22="PCL","58.3","0")))))) -> 0 | AD22: Total | AE22: =SUM(Z5:Z19,AE5:AE20) -> 0 | AF22: =SUM(AA5:AA19,AF5:AF20,) -> 0 | AG22: =SUM(AB5:AB19,AG5:AG20) -> 0 | AO22: Total | AP22: =SUM(AK5:AK19,AP5:AP20) -> 0 | AQ22: =SUM(AL5:AL19,AQ5:AQ20,) -> 0 | AR22: =SUM(AM5:AM19,AR5:AR20) -> 0
A23: 19 | J23: =IF(G23="RSL","55","0") -> 0 | K23: =IF(G23="GVS","37.5",IF(G23="GVM","41.5",IF(G23="GVL","50",IF(G23="PCS","45.8",IF(G23="PCM","50",IF(G23="PCL","58.3","0")))))) -> 0
A24: 20 | J24: =IF(G24="RSL","55","0") -> 0 | K24: =IF(G24="GVS","37.5",IF(G24="GVM","41.5",IF(G24="GVL","50",IF(G24="PCS","45.8",IF(G24="PCM","50",IF(G24="PCL","58.3","0")))))) -> 0 | R24: SMALL | S24: MEDIUM | T24: LARGE | U24: TOTAL | AD24: B2/GA TOTAL | AE24: B2 machine | AF24: GA machine | AG24: BLH machine | AH24: Wongo machine | AI24: Sub total
A25: 21 | J25: =IF(G25="RSL","55","0") -> 0 | K25: =IF(G25="GVS","37.5",IF(G25="GVM","41.5",IF(G25="GVL","50",IF(G25="PCS","45.8",IF(G25="PCM","50",IF(G25="PCL","58.3","0")))))) -> 0 | R25: =COUNTIF(G5:G29,"GV1")+COUNTIF(G37:G61,"GV1")+COUNTIF(G69:G93,"GV1") -> 0 | S25: =COUNTIF(G5:G29,"GV2")+COUNTIF(G37:G61,"GV2")+COUNTIF(G69:G93,"GV2") -> 0 | T25: =COUNTIF(G5:G29,"GV3")+COUNTIF(G37:G61,"GV3")+COUNTIF(G69:G93,"GV3") -> 0 | U25: =((C32+(R26+S26+T26)*0.5)) -> 1300.73 | AD25: =SUM(AE25:AF25) -> 0 | AE25: =SUM(AE22) -> 0 | AF25: =SUM(AP22) -> 0 | AG25: =SUM(AF22+AQ22) -> 0 | AH25: =AG22+AR22 -> 0 | AI25: =SUM(AE25:AH25) -> 0
A26: 22 | J26: =IF(G26="RSL","55","0") -> 0 | K26: =IF(G26="GVS","37.5",IF(G26="GVM","41.5",IF(G26="GVL","50",IF(G26="PCS","45.8",IF(G26="PCM","50",IF(G26="PCL","58.3","0")))))) -> 0 | R26: =R25*37.5 -> 0 | S26: =S25*41.5 -> 0 | T26: =T25*50 -> 0 | X26: Branch cards
A27: 23 | J27: =IF(G27="RSL","55","0") -> 0 | K27: =IF(G27="GVS","37.5",IF(G27="GVM","41.5",IF(G27="GVL","50",IF(G27="PCS","45.8",IF(G27="PCM","50",IF(G27="PCL","58.3","0")))))) -> 0 | R27: Expense | X27: 1 | Z27: -2745
A28: 24 | J28: =IF(G28="RSL","55","0") -> 0 | K28: =IF(G28="GVS","37.5",IF(G28="GVM","41.5",IF(G28="GVL","50",IF(G28="PCS","45.8",IF(G28="PCM","50",IF(G28="PCL","58.3","0")))))) -> 0 | X28: 2
A29: 25 | J29: =IF(G29="RSL","55","0") -> 0 | K29: =IF(G29="GVS","37.5",IF(G29="GVM","41.5",IF(G29="GVL","50",IF(G29="PCS","45.8",IF(G29="PCM","50",IF(G29="PCL","58.3","0")))))) -> 0 | X29: 3
A30: Page total | H30: =SUM(H5:H29) -> 150 | I30: =SUM(I5:I29) -> 775 | J30: =J5+J6+J7+J8+J9+J10+J11+J12+J13+J14+J15+J16+J18+J19+J17+J20+J22+J23+J21+J24+J25+J26+J27+J28+J29 -> 55 | K30: =K5+K6+K7+K8+K9+K10+K11+K12+K13+K14+K15+K16+K18+K19+K17+K20+K22+K23+K21+K24+K25+K26+K27+K28+K29 -> 320.73 | L30: =SUM(L5:L29) -> 0 | M30: =SUM(M5:M29) -> 0 | N30: CASH | O30: CARD | P30: GV | Q30: RSL | X30: 4
A31: Daily Total | H31: =H30+H62+H94 -> 150 | I31: =I30+I62+I94 -> 775 | J31: =J30+J62+J94 -> 55 | K31: =K30+K62+K94 -> 320.73 | L31: =L30+L62+L94 -> 0 | M31: =M30+M62+M94 -> 0 | N31: =COUNT(H5:H29,H37:H61,H69:H93) -> 2 | O31: =COUNT(I5:I29,I37:I61,I69:I93) -> 7 | P31: =COUNTIF(G5:G29,"G*")+COUNTIF(G37:G61,"G*")+COUNTIF(G69:G93,"G*")+COUNTIF(G5:G29,"P*")+COUNTIF(G37:G61,"P*")+COUNTIF(G69:G93,"P*") -> 4 | Q31: =COUNTIF(G5:G29,"RSL")+COUNTIF(G37:G61,"RSL")+COUNTIF(G69:G93,"RSL") -> 1 | R31: CASH CLOSING | S31: =H31+L31-U28-U29-U30 -> 150 | T31: =H31+I31+L31+M31 -> 925 | X31: Subtotal | Z31: =SUM(Z27:Z30) -> -2745
A32: TOTAL SALES | C32: =H31+I31+J31+K31 -> 1300.73 | F32: No of Cars | H32: =COUNT(B5:B29,B37:B61,B69:B93) -> 13 | I32: Average | K32: =C32/H32 -> 100.05615 | N32: =H31/C32 -> 0.11531986 | O32: =I31/C32 -> 0.59581927 | P32: =K31/C32 -> 0.24657692 | Q32: =J31/C32 -> 0.042283948 | R32: CARD CLOSING | S32: =I31+M31 -> 775 | X32: B2 card | Z32: =I31 -> 775
A33: Daily Report | X33: Settlement | Z33: =SUM(Z31:Z32) -> -1970
A34: =A2 -> 26 - 4 - 2022 | H34: WEATHER | J34: =J2 -> SHOWER | L34: REPORT by | O34: =O2 -> HENDRA | R34: TOTAL STAFF | T34: =T2 -> 4
A36: No | B36: Docket No | C36: Reg No | D36: Mobile | E36: Gender | F36: TIME | G36: Service | H36: CASH | I36: CARD | J36: RSL | K36: GV | L36: GV CASH | M36: GV CARD | N36: O/Taker | O36: Comment | R36: NAME | S36: Time In | T36: Time out | U36: Total Hours
A37: =A29+1 -> 26 | J37: =IF(G37="RSL","55","0") -> 0 | K37: =IF(G37="GVS","37.5",IF(G37="GVM","41.5",IF(G37="GVL","50",IF(G37="PCS","45.8",IF(G37="PCM","50",IF(G37="PCL","58.3","0")))))) -> 0
A38: =A37+1 -> 27 | J38: =IF(G38="RSL","55","0") -> 0 | K38: =IF(G38="GVS","37.5",IF(G38="GVM","41.5",IF(G38="GVL","50",IF(G38="PCS","45.8",IF(G38="PCM","50",IF(G38="PCL","58.3","0")))))) -> 0
A39: =A38+1 -> 28 | J39: =IF(G39="RSL","55","0") -> 0 | K39: =IF(G39="GVS","37.5",IF(G39="GVM","41.5",IF(G39="GVL","50",IF(G39="PCS","45.8",IF(G39="PCM","50",IF(G39="PCL","58.3","0")))))) -> 0
A40: =A39+1 -> 29 | J40: =IF(G40="RSL","55","0") -> 0 | K40: =IF(G40="GVS","37.5",IF(G40="GVM","41.5",IF(G40="GVL","50",IF(G40="PCS","45.8",IF(G40="PCM","50",IF(G40="PCL","58.3","0")))))) -> 0
A41: =A40+1 -> 30 | J41: =IF(G41="RSL","55","0") -> 0 | K41: =IF(G41="GVS","37.5",IF(G41="GVM","41.5",IF(G41="GVL","50",IF(G41="PCS","45.8",IF(G41="PCM","50",IF(G41="PCL","58.3","0")))))) -> 0
A42: =A41+1 -> 31 | J42: =IF(G42="RSL","55","0") -> 0 | K42: =IF(G42="GVS","37.5",IF(G42="GVM","41.5",IF(G42="GVL","50",IF(G42="PCS","45.8",IF(G42="PCM","50",IF(G42="PCL","58.3","0")))))) -> 0
A43: =A42+1 -> 32 | J43: =IF(G43="RSL","55","0") -> 0 | K43: =IF(G43="GVS","37.5",IF(G43="GVM","41.5",IF(G43="GVL","50",IF(G43="PCS","45.8",IF(G43="PCM","50",IF(G43="PCL","58.3","0")))))) -> 0
A44: =A43+1 -> 33 | J44: =IF(G44="RSL","55","0") -> 0 | K44: =IF(G44="GVS","37.5",IF(G44="GVM","41.5",IF(G44="GVL","50",IF(G44="PCS","45.8",IF(G44="PCM","50",IF(G44="PCL","58.3","0")))))) -> 0
A45: =A44+1 -> 34 | J45: =IF(G45="RSL","55","0") -> 0 | K45: =IF(G45="GVS","37.5",IF(G45="GVM","41.5",IF(G45="GVL","50",IF(G45="PCS","45.8",IF(G45="PCM","50",IF(G45="PCL","58.3","0")))))) -> 0
A46: =A45+1 -> 35 | J46: =IF(G46="RSL","55","0") -> 0 | K46: =IF(G46="GVS","37.5",IF(G46="GVM","41.5",IF(G46="GVL","50",IF(G46="PCS","45.8",IF(G46="PCM","50",IF(G46="PCL","58.3","0")))))) -> 0
A47: =A46+1 -> 36 | J47: =IF(G47="RSL","55","0") -> 0 | K47: =IF(G47="GVS","37.5",IF(G47="GVM","41.5",IF(G47="GVL","50",IF(G47="PCS","45.8",IF(G47="PCM","50",IF(G47="PCL","58.3","0")))))) -> 0
A48: =A47+1 -> 37 | J48: =IF(G48="RSL","55","0") -> 0 | K48: =IF(G48="GVS","37.5",IF(G48="GVM","41.5",IF(G48="GVL","50",IF(G48="PCS","45.8",IF(G48="PCM","50",IF(G48="PCL","58.3","0")))))) -> 0
A49: =A48+1 -> 38 | J49: =IF(G49="RSL","55","0") -> 0 | K49: =IF(G49="GVS","37.5",IF(G49="GVM","41.5",IF(G49="GVL","50",IF(G49="PCS","45.8",IF(G49="PCM","50",IF(G49="PCL","58.3","0")))))) -> 0
... A61: =A60+1 -> 50 | J61: =IF(G61="RSL","55","0") -> 0 | K61: =IF(G61="GVS","37.5",IF(G61="GVM","41.5",IF(G61="GVL","50",IF(G61="PCS","45.8",IF(G61="PCM","50",IF(G61="PCL","58.3","0")))))) -> 0
A62: Page total | H62: =SUM(H37:H61) -> 0 | I62: =SUM(I37:I61) -> 0 | J62: =J61+J60+J59+J58+J57+J56+J55+J54+J53+J52+J51+J50+J49+J48+J47+J46+J45+J44+J43+J42+J41+J40+J39+J38+J37 -> 0 | K62: =K61+K60+K59+K58+K57+K56+K55+K54+K53+K52+K51+K50+K49+K48+K47+K46+K45+K44+K43+K42+K41+K40+K39+K38+K37 -> 0 | L62: =SUM(L37:L61) -> 0 | M62: =SUM(M37:M61) -> 0
R64: Page: 2
A65: Daily Report
A66: =A34 -> 26 - 4 - 2022 | H66: WEATHER | J66: =J34 -> SHOWER | L66: REPORT by | O66: =O34 -> HENDRA | R66: TOTAL STAFF | T66: =T34 -> 4
A68: No | B68: Docket No | C68: Reg No | D68: Mobile | E68: Gender | F68: TIME | G68: Service | H68: CASH | I68: CARD | J68: RSL | K68: GV | L68: GV CASH | M68: GV CARD | N68: O/Taker | O68: Comment | R68: NAME | S68: Time In | T68: Time out | U68: Total Hours
A69: =A61+1 -> 51 | J69: =IF(G69="RSL","55","0") -> 0 | K69: =IF(G69="GVS","37.5",IF(G69="GVM","41.5",IF(G69="GVL","50",IF(G69="PCS","45.8",IF(G69="PCM","50",IF(G69="PCL","58.3","0")))))) -> 0
A70: =A69+1 -> 52 | J70: =IF(G70="RSL","55","0") -> 0 | K70: =IF(G70="GVS","37.5",IF(G70="GVM","41.5",IF(G70="GVL","50",IF(G70="PCS","45.8",IF(G70="PCM","50",IF(G70="PCL","58.3","0")))))) -> 0
A71: =A70+1 -> 53 | J71: =IF(G71="RSL","55","0") -> 0 | K71: =IF(G71="GVS","37.5",IF(G71="GVM","41.5",IF(G71="GVL","50",IF(G71="PCS","45.8",IF(G71="PCM","50",IF(G71="PCL","58.3","0")))))) -> 0
A72: =A71+1 -> 54 | J72: =IF(G72="RSL","55","0") -> 0 | K72: =IF(G72="GVS","37.5",IF(G72="GVM","41.5",IF(G72="GVL","50",IF(G72="PCS","45.8",IF(G72="PCM","50",IF(G72="PCL","58.3","0")))))) -> 0
A73: =A72+1 -> 55 | J73: =IF(G73="RSL","55","0") -> 0 | K73: =IF(G73="GVS","37.5",IF(G73="GVM","41.5",IF(G73="GVL","50",IF(G73="PCS","45.8",IF(G73="PCM","50",IF(G73="PCL","58.3","0")))))) -> 0
A74: =A73+1 -> 56 | J74: =IF(G74="RSL","55","0") -> 0 | K74: =IF(G74="GVS","37.5",IF(G74="GVM","41.5",IF(G74="GVL","50",IF(G74="PCS","45.8",IF(G74="PCM","50",IF(G74="PCL","58.3","0")))))) -> 0
A75: =A74+1 -> 57 | J75: =IF(G75="RSL","55","0") -> 0 | K75: =IF(G75="GVS","37.5",IF(G75="GVM","41.5",IF(G75="GVL","50",IF(G75="PCS","45.8",IF(G75="PCM","50",IF(G75="PCL","58.3","0")))))) -> 0
A76: =A75+1 -> 58 | J76: =IF(G76="RSL","55","0") -> 0 | K76: =IF(G76="GVS","37.5",IF(G76="GVM","41.5",IF(G76="GVL","50",IF(G76="PCS","45.8",IF(G76="PCM","50",IF(G76="PCL","58.3","0")))))) -> 0
A77: =A76+1 -> 59 | J77: =IF(G77="RSL","55","0") -> 0 | K77: =IF(G77="GVS","37.5",IF(G77="GVM","41.5",IF(G77="GVL","50",IF(G77="PCS","45.8",IF(G77="PCM","50",IF(G77="PCL","58.3","0")))))) -> 0
A78: =A77+1 -> 60 | J78: =IF(G78="RSL","55","0") -> 0 | K78: =IF(G78="GVS","37.5",IF(G78="GVM","41.5",IF(G78="GVL","50",IF(G78="PCS","45.8",IF(G78="PCM","50",IF(G78="PCL","58.3","0")))))) -> 0
A79: =A78+1 -> 61 | J79: =IF(G79="RSL","55","0") -> 0 | K79: =IF(G79="GVS","37.5",IF(G79="GVM","41.5",IF(G79="GVL","50",IF(G79="PCS","45.8",IF(G79="PCM","50",IF(G79="PCL","58.3","0")))))) -> 0
A80: =A79+1 -> 62 | J80: =IF(G80="RSL","55","0") -> 0 | K80: =IF(G80="GVS","37.5",IF(G80="GVM","41.5",IF(G80="GVL","50",IF(G80="PCS","45.8",IF(G80="PCM","50",IF(G80="PCL","58.3","0")))))) -> 0
A81: =A80+1 -> 63 | J81: =IF(G81="RSL","55","0") -> 0 | K81: =IF(G81="GVS","37.5",IF(G81="GVM","41.5",IF(G81="GVL","50",IF(G81="PCS","45.8",IF(G81="PCM","50",IF(G81="PCL","58.3","0")))))) -> 0
... A93: =A92+1 -> 75 | J93: =IF(G93="RSL","55","0") -> 0 | K93: =IF(G93="GVS","37.5",IF(G93="GVM","41.5",IF(G93="GVL","50",IF(G93="PCS","45.8",IF(G93="PCM","50",IF(G93="PCL","58.3","0")))))) -> 0
A94: Page total | H94: =SUM(H69:H93) -> 0 | I94: =SUM(I69:I93) -> 0 | J94: =J93+J92+J91+J90+J89+J88+J87+J86+J85+J84+J83+J82+J81+J80+J79+J78+J77+J76+J75+J74+J73+J72+J71+J70+J69 -> 0 | K94: =K93+K92+K91+K90+K89+K88+K87+K86+K85+K84+K83+K82+K81+K80+K79+K78+K77+K76+K75+K74+K73+K72+K71+K70+K69 -> 0 | L94: =SUM(L69:L93) -> 0 | M94: =SUM(M69:M93) -> 0
R96: Page: 3

Sheet WED
A1: B2 Daily Report
A2: 27 - 4 - 2022 | H2: WEATHER | J2: MIX | L2: REPORT BY | O2: HENDRA | R2: TOTAL STAFF | T2: 6 | X2: Merchant machine usage at B2 | AA2: Settle amount | AI2: Merchant machine usage at GA | AL2: Settle amount
A4: No | B4: Docket No | C4: Reg No | D4: Mobile | E4: Gender | F4: TIME | G4: Service | H4: CASH | I4: CARD | J4: RSL | K4: GV | L4: GV CASH | M4: GV CARD | N4: O/Taker | O4: Comment | R4: NAME | S4: Time In | T4: Time out | U4: Total Hours | Z4: B2 machine | AA4: BLH machine | AB4: Wongo | AE4: B2 machine | AF4: BLH machine | AG4: Wongo | AK4: GA machine | AL4: BLH machine | AM4: Wongo | AP4: GA machine | AQ4: BLH machine | AR4: Wongo
A5: 1 | B5: 3121 | C5: AJL661 | D5: 0427242374 | E5: M | F5: 840 | G5: H | H5: 150 | J5: =IF(G5="RSL","55","0") -> 0 | K5: =IF(G5="GVS","37.5",IF(G5="GVM","41.5",IF(G5="GVL","50",IF(G5="PCS","45.8",IF(G5="PCM","50",IF(G5="PCL","58.3","0")))))) -> 0 | N5: HENDRA | R5: HENDRA | S5: 0.33333333 | T5: 0.69791667 | U5: =(T5-S5)*24 -> 8.75 | X5: NOV | Y5: 1 | AD5: 16 | AI5: NOV | AJ5: 1 | AO5: 16
A6: 2 | B6: 3122 | C6: CLB30E | D6: 0434022699 | E6: M | F6: 900 | G6: PCS | J6: =IF(G6="RSL","55","0") -> 0 | K6: =IF(G6="GVS","37.5",IF(G6="GVM","41.5",IF(G6="GVL","50",IF(G6="PCS","45.8",IF(G6="PCM","50",IF(G6="PCL","58.3","0")))))) -> 45.8 | N6: HENDRA | O6: # 21020 6/6 | R6: JUNIOR | S6: 0.33333333 | T6: 0.66666667 | U6: =(T6-S6)*24 -> 8 | W6: M | Y6: 2 | AD6: 17 | AJ6: 2 | AO6: 17
A7: 3 | B7: 3123 | C7: CKC333 | D7: 0411889693 | E7: M | F7: 920 | G7: RSL | J7: =IF(G7="RSL","55","0") -> 55 | K7: =IF(G7="GVS","37.5",IF(G7="GVM","41.5",IF(G7="GVL","50",IF(G7="PCS","45.8",IF(G7="PCM","50",IF(G7="PCL","58.3","0")))))) -> 0 | N7: HENDRA | O7: 202202002 | R7: ARIANTO | S7: 0.40625 | T7: 0.66666667 | U7: =(T7-S7)*24 -> 6.25 | W7: F | Y7: 3 | AD7: 18 | AJ7: 3 | AO7: 18
A8: 4 | B8: 3124 | C8: BMT040 | D8: 0401928669 | E8: F | F8: 925 | G8: X | I8: 95 | J8: =IF(G8="RSL","55","0") -> 0 | K8: =IF(G8="GVS","37.5",IF(G8="GVM","41.5",IF(G8="GVL","50",IF(G8="PCS","45.8",IF(G8="PCM","50",IF(G8="PCL","58.3","0")))))) -> 0 | N8: HENDRA | R8: KUROSH | S8: 0.38541667 | T8: 0.66666667 | U8: =(T8-S8)*24 -> 6.75 | Y8: 4 | AD8: 19 | AJ8: 4 | AO8: 19
A9: 5 | B9: 3125 | C9: DSU09D | D9: 0473204828 | E9: F | F9: 945 | G9: D | H9: 100 | J9: =IF(G9="RSL","55","0") -> 0 | K9: =IF(G9="GVS","37.5",IF(G9="GVM","41.5",IF(G9="GVL","50",IF(G9="PCS","45.8",IF(G9="PCM","50",IF(G9="PCL","58.3","0")))))) -> 0 | N9: HENDRA | O9: TRICEPS | R9: VINNY | S9: 0.42708333 | T9: 0.66666667 | U9: =(T9-S9)*24 -> 5.75 | X9: EXCL RSL | Y9: 5 | AD9: 20 | AJ9: 5 | AO9: 20
A10: 6 | B10: 3126 | C10: EAE28E | D10: 0406816699 | E10: F | F10: 1000 | G10: H | I10: 150 | J10: =IF(G10="RSL","55","0") -> 0 | K10: =IF(G10="GVS","37.5",IF(G10="GVM","41.5",IF(G10="GVL","50",IF(G10="PCS","45.8",IF(G10="PCM","50",IF(G10="PCL","58.3","0")))))) -> 0 | N10: HENDRA | R10: SRI | S10: 0.45833333 | T10: 0.66666667 | U10: =(T10-S10)*24 -> 5 | Y10: 6 | AD10: 21 | AJ10: 6 | AO10: 21
A11: 7 | B11: 3127 | C11: DYK68U | D11: 0424651162 | E11: M | F11: 1015 | G11: X | I11: 95 | J11: =IF(G11="RSL","55","0") -> 0 | K11: =IF(G11="GVS","37.5",IF(G11="GVM","41.5",IF(G11="GVL","50",IF(G11="PCS","45.8",IF(G11="PCM","50",IF(G11="PCL","58.3","0")))))) -> 0 | N11: HENDRA | U11: =(T11-S11)*24 -> 0 | Y11: 7 | AD11: 22 | AJ11: 7 | AO11: 22
A12: 8 | B12: 3128 | C12: DSR98T | D12: ??? | E12: F | F12: 1100 | G12: GV3 | J12: =IF(G12="RSL","55","0") -> 0 | K12: =IF(G12="GVS","37.5",IF(G12="GVM","41.5",IF(G12="GVL","50",IF(G12="PCS","45.8",IF(G12="PCM","50",IF(G12="PCL","58.3","0")))))) -> 0 | N12: HENDRA | O12: # 202887 5/6 | U12: =(T12-S12)*24 -> 0 | Y12: 8 | AD12: 23 | AJ12: 8 | AO12: 23
A13: 9 | B13: 3129 | C13: CC77CP | D13: 0405547715 | E13: F | F13: 1115 | G13: W/O | H13: 100 | J13: =IF(G13="RSL","55","0") -> 0 | K13: =IF(G13="GVS","37.5",IF(G13="GVM","41.5",IF(G13="GVL","50",IF(G13="PCS","45.8",IF(G13="PCM","50",IF(G13="PCL","58.3","0")))))) -> 0 | N13: HENDRA | O13: TRICEPS | U13: =(T13-S13)*24 -> 0 | Y13: 9 | AD13: 24 | AJ13: 9 | AO13: 24
A14: 10 | B14: 3130 | C14: DCS80J | D14: 0401521360 | E14: F | F14: 1130 | G14: X | H14: 95 | J14: =IF(G14="RSL","55","0") -> 0 | K14: =IF(G14="GVS","37.5",IF(G14="GVM","41.5",IF(G14="GVL","50",IF(G14="PCS","45.8",IF(G14="PCM","50",IF(G14="PCL","58.3","0")))))) -> 0 | N14: VINNY | U14: =(T14-S14)*24 -> 0 | Y14: 10 | AD14: 25 | AJ14: 10 | AO14: 25
A15: 11 | B15: 3131 | C15: EOD56V | D15: 0478104783 | E15: F | F15: 1145 | G15: RSL | H15: 15 | J15: =IF(G15="RSL","55","0") -> 55 | K15: =IF(G15="GVS","37.5",IF(G15="GVM","41.5",IF(G15="GVL","50",IF(G15="PCS","45.8",IF(G15="PCM","50",IF(G15="PCL","58.3","0")))))) -> 0 | N15: HENDRA | O15: 202202026 | U15: =(T15-S15)*24 -> 0 | Y15: 11 | AD15: 26 | AJ15: 11 | AO15: 26
A16: 12 | B16: 3132 | C16: S551BDL | D16: ???? | E16: F | F16: 1215 | G16: GV3 | J16: =IF(G16="RSL","55","0") -> 0 | K16: =IF(G16="GVS","37.5",IF(G16="GVM","41.5",IF(G16="GVL","50",IF(G16="PCS","45.8",IF(G16="PCM","50",IF(G16="PCL","58.3","0")))))) -> 0 | N16: HENDRA | O16: # 202887 6/6 | R16: =H32/U16 -> 0.39506173 | S16: =H32/(U16-U5) -> 0.50393701 | T16: =C32/U16 -> 32.2 | U16: =SUM(U5:U15) -> 40.5 | Y16: 12 | AD16: 27 | AJ16: 12 | AO16: 27
A17: 13 | B17: 3133 | C17: JB0212 | D17: 0401604628 | E17: F | F17: 1215 | G17: D | H17: 75 | J17: =IF(G17="RSL","55","0") -> 0 | K17: =IF(G17="GVS","37.5",IF(G17="GVM","41.5",IF(G17="GVL","50",IF(G17="PCS","45.8",IF(G17="PCM","50",IF(G17="PCL","58.3","0")))))) -> 0 | N17: HENDRA | R17: Cars/T Hr ① | S17: Cars/T Hr ② | T17: Sales/T Hr | U17: Total Hours | Y17: 13 | AD17: 28 | AJ17: 13 | AO17: 28
A18: 14 | B18: 3134 | C18: DLX57A | D18: 0421051276 | E18: F | F18: 1230 | G18: PCL | J18: =IF(G18="RSL","55","0") -> 0 | K18: =IF(G18="GVS","37.5",IF(G18="GVM","41.5",IF(G18="GVL","50",IF(G18="PCS","45.8",IF(G18="PCM","50",IF(G18="PCL","58.3","0")))))) -> 58.3 | N18: HENDRA | O18: # 21028 4/6 | R18: ITEM | S18: QTY | T18: AMT | U18: RMKS | Y18: 14 | AD18: 29 | AJ18: 14 | AO18: 29
A19: 15 | B19: 3135 | C19: EHR64E | D19: 0414867180 | E19: F | F19: 1300 | G19: D | I19: 55 | J19: =IF(G19="RSL","55","0") -> 0 | K19: =IF(G19="GVS","37.5",IF(G19="GVM","41.5",IF(G19="GVL","50",IF(G19="PCS","45.8",IF(G19="PCM","50",IF(G19="PCL","58.3","0")))))) -> 0 | N19: HENDRA | R19: GV | S19: =COUNT(L5:M29,L37:M61,L69:M93) -> 0 | T19: =SUM(L5:M29,L37:M61,L69:M93) -> 0 | Y19: 15 | AD19: 30 | AJ19: 15 | AO19: 30
A20: 16 | B20: 3136 | C20: EJX89L | D20: 0432180139 | E20: F | F20: 1410 | G20: D/ST | H20: 160 | J20: =IF(G20="RSL","55","0") -> 0 | K20: =IF(G20="GVS","37.5",IF(G20="GVM","41.5",IF(G20="GVL","50",IF(G20="PCS","45.8",IF(G20="PCM","50",IF(G20="PCL","58.3","0")))))) -> 0 | N20: HENDRA | O20: SMALL | AD20: 31 | AO20: 31
A21: 17 | J21: =IF(G21="RSL","55","0") -> 0 | K21: =IF(G21="GVS","37.5",IF(G21="GVM","41.5",IF(G21="GVL","50",IF(G21="PCS","45.8",IF(G21="PCM","50",IF(G21="PCL","58.3","0")))))) -> 0
A22: 18 | J22: =IF(G22="RSL","55","0") -> 0 | K22: =IF(G22="GVS","37.5",IF(G22="GVM","41.5",IF(G22="GVL","50",IF(G22="PCS","45.8",IF(G22="PCM","50",IF(G22="PCL","58.3","0")))))) -> 0 | AD22: Total | AE22: =SUM(Z5:Z19,AE5:AE20) -> 0 | AF22: =SUM(AA5:AA19,AF5:AF20,) -> 0 | AG22: =SUM(AB5:AB19,AG5:AG20) -> 0 | AO22: Total | AP22: =SUM(AK5:AK19,AP5:AP20) -> 0 | AQ22: =SUM(AL5:AL19,AQ5:AQ20,) -> 0 | AR22: =SUM(AM5:AM19,AR5:AR20) -> 0
A23: 19 | J23: =IF(G23="RSL","55","0") -> 0 | K23: =IF(G23="GVS","37.5",IF(G23="GVM","41.5",IF(G23="GVL","50",IF(G23="PCS","45.8",IF(G23="PCM","50",IF(G23="PCL","58.3","0")))))) -> 0
A24: 20 | J24: =IF(G24="RSL","55","0") -> 0 | K24: =IF(G24="GVS","37.5",IF(G24="GVM","41.5",IF(G24="GVL","50",IF(G24="PCS","45.8",IF(G24="PCM","50",IF(G24="PCL","58.3","0")))))) -> 0 | R24: SMALL | S24: MEDIUM | T24: LARGE | U24: TOTAL | AD24: B2/GA TOTAL | AE24: B2 machine | AF24: GA machine | AG24: BLH machine | AH24: Wongo machine | AI24: Sub total
A25: 21 | J25: =IF(G25="RSL","55","0") -> 0 | K25: =IF(G25="GVS","37.5",IF(G25="GVM","41.5",IF(G25="GVL","50",IF(G25="PCS","45.8",IF(G25="PCM","50",IF(G25="PCL","58.3","0")))))) -> 0 | R25: =COUNTIF(G5:G29,"GV1")+COUNTIF(G37:G61,"GV1")+COUNTIF(G69:G93,"GV1") -> 0 | S25: =COUNTIF(G5:G29,"GV2")+COUNTIF(G37:G61,"GV2")+COUNTIF(G69:G93,"GV2") -> 0 | T25: =COUNTIF(G5:G29,"GV3")+COUNTIF(G37:G61,"GV3")+COUNTIF(G69:G93,"GV3") -> 2 | U25: =((C32+(R26+S26+T26)*0.5)) -> 1354.1 | AD25: =SUM(AE25:AF25) -> 0 | AE25: =SUM(AE22) -> 0 | AF25: =SUM(AP22) -> 0 | AG25: =SUM(AF22+AQ22) -> 0 | AH25: =AG22+AR22 -> 0 | AI25: =SUM(AE25:AH25) -> 0
A26: 22 | J26: =IF(G26="RSL","55","0") -> 0 | K26: =IF(G26="GVS","37.5",IF(G26="GVM","41.5",IF(G26="GVL","50",IF(G26="PCS","45.8",IF(G26="PCM","50",IF(G26="PCL","58.3","0")))))) -> 0 | R26: =R25*37.5 -> 0 | S26: =S25*41.5 -> 0 | T26: =T25*50 -> 100 | X26: Branch cards
A27: 23 | J27: =IF(G27="RSL","55","0") -> 0 | K27: =IF(G27="GVS","37.5",IF(G27="GVM","41.5",IF(G27="GVL","50",IF(G27="PCS","45.8",IF(G27="PCM","50",IF(G27="PCL","58.3","0")))))) -> 0 | R27: Expense | X27: 1 | Z27: -2745
A28: 24 | J28: =IF(G28="RSL","55","0") -> 0 | K28: =IF(G28="GVS","37.5",IF(G28="GVM","41.5",IF(G28="GVL","50",IF(G28="PCS","45.8",IF(G28="PCM","50",IF(G28="PCL","58.3","0")))))) -> 0 | R28: JUNIOR TAKEN $30 | X28: 2
A29: 25 | J29: =IF(G29="RSL","55","0") -> 0 | K29: =IF(G29="GVS","37.5",IF(G29="GVM","41.5",IF(G29="GVL","50",IF(G29="PCS","45.8",IF(G29="PCM","50",IF(G29="PCL","58.3","0")))))) -> 0 | X29: 3
A30: Page total | H30: =SUM(H5:H29) -> 695 | I30: =SUM(I5:I29) -> 395 | J30: =J5+J6+J7+J8+J9+J10+J11+J12+J13+J14+J15+J16+J18+J19+J17+J20+J22+J23+J21+J24+J25+J26+J27+J28+J29 -> 110 | K30: =K5+K6+K7+K8+K9+K10+K11+K12+K13+K14+K15+K16+K18+K19+K17+K20+K22+K23+K21+K24+K25+K26+K27+K28+K29 -> 104.1 | L30: =SUM(L5:L29) -> 0 | M30: =SUM(M5:M29) -> 0 | N30: CASH | O30: CARD | P30: GV | Q30: RSL | X30: 4
A31: Daily Total | H31: =H30+H62+H94 -> 695 | I31: =I30+I62+I94 -> 395 | J31: =J30+J62+J94 -> 110 | K31: =K30+K62+K94 -> 104.1 | L31: =L30+L62+L94 -> 0 | M31: =M30+M62+M94 -> 0 | N31: =COUNT(H5:H29,H37:H61,H69:H93) -> 7 | O31: =COUNT(I5:I29,I37:I61,I69:I93) -> 4 | P31: =COUNTIF(G5:G29,"G*")+COUNTIF(G37:G61,"G*")+COUNTIF(G69:G93,"G*")+COUNTIF(G5:G29,"P*")+COUNTIF(G37:G61,"P*")+COUNTIF(G69:G93,"P*") -> 4 | Q31: =COUNTIF(G5:G29,"RSL")+COUNTIF(G37:G61,"RSL")+COUNTIF(G69:G93,"RSL") -> 2 | R31: CASH CLOSING | S31: =H31+L31-U28-U29-U30 -> 695 | T31: =H31+I31+L31+M31 -> 1090 | X31: Subtotal | Z31: =SUM(Z27:Z30) -> -2745
A32: TOTAL SALES | C32: =H31+I31+J31+K31 -> 1304.1 | F32: No of Cars | H32: =COUNT(B5:B29,B37:B61,B69:B93) -> 16 | I32: Average | K32: =C32/H32 -> 81.50625 | N32: =H31/C32 -> 0.53293459 | O32: =I31/C32 -> 0.30289088 | P32: =K31/C32 -> 0.079825167 | Q32: =J31/C32 -> 0.08434936 | R32: CARD CLOSING | S32: =I31+M31 -> 395 | X32: B2 card | Z32: =I31 -> 395
A33: Daily Report | X33: Settlement | Z33: =SUM(Z31:Z32) -> -2350
A34: =A2 -> 27 - 4 - 2022 | H34: WEATHER | J34: =J2 -> MIX | L34: REPORT by | O34: =O2 -> HENDRA | R34: TOTAL STAFF | T34: =T2 -> 6
A36: No | B36: Docket No | C36: Reg No | D36: Mobile | E36: Gender | F36: TIME | G36: Service | H36: CASH | I36: CARD | J36: RSL | K36: GV | L36: GV CASH | M36: GV CARD | N36: O/Taker | O36: Comment | R36: NAME | S36: Time In | T36: Time out | U36: Total Hours
A37: =A29+1 -> 26 | J37: =IF(G37="RSL","55","0") -> 0 | K37: =IF(G37="GVS","37.5",IF(G37="GVM","41.5",IF(G37="GVL","50",IF(G37="PCS","45.8",IF(G37="PCM","50",IF(G37="PCL","58.3","0")))))) -> 0
A38: =A37+1 -> 27 | J38: =IF(G38="RSL","55","0") -> 0 | K38: =IF(G38="GVS","37.5",IF(G38="GVM","41.5",IF(G38="GVL","50",IF(G38="PCS","45.8",IF(G38="PCM","50",IF(G38="PCL","58.3","0")))))) -> 0
A39: =A38+1 -> 28 | J39: =IF(G39="RSL","55","0") -> 0 | K39: =IF(G39="GVS","37.5",IF(G39="GVM","41.5",IF(G39="GVL","50",IF(G39="PCS","45.8",IF(G39="PCM","50",IF(G39="PCL","58.3","0")))))) -> 0
A40: =A39+1 -> 29 | J40: =IF(G40="RSL","55","0") -> 0 | K40: =IF(G40="GVS","37.5",IF(G40="GVM","41.5",IF(G40="GVL","50",IF(G40="PCS","45.8",IF(G40="PCM","50",IF(G40="PCL","58.3","0")))))) -> 0
A41: =A40+1 -> 30 | J41: =IF(G41="RSL","55","0") -> 0 | K41: =IF(G41="GVS","37.5",IF(G41="GVM","41.5",IF(G41="GVL","50",IF(G41="PCS","45.8",IF(G41="PCM","50",IF(G41="PCL","58.3","0")))))) -> 0
A42: =A41+1 -> 31 | J42: =IF(G42="RSL","55","0") -> 0 | K42: =IF(G42="GVS","37.5",IF(G42="GVM","41.5",IF(G42="GVL","50",IF(G42="PCS","45.8",IF(G42="PCM","50",IF(G42="PCL","58.3","0")))))) -> 0
A43: =A42+1 -> 32 | J43: =IF(G43="RSL","55","0") -> 0 | K43: =IF(G43="GVS","37.5",IF(G43="GVM","41.5",IF(G43="GVL","50",IF(G43="PCS","45.8",IF(G43="PCM","50",IF(G43="PCL","58.3","0")))))) -> 0
A44: =A43+1 -> 33 | J44: =IF(G44="RSL","55","0") -> 0 | K44: =IF(G44="GVS","37.5",IF(G44="GVM","41.5",IF(G44="GVL","50",IF(G44="PCS","45.8",IF(G44="PCM","50",IF(G44="PCL","58.3","0")))))) -> 0
A45: =A44+1 -> 34 | J45: =IF(G45="RSL","55","0") -> 0 | K45: =IF(G45="GVS","37.5",IF(G45="GVM","41.5",IF(G45="GVL","50",IF(G45="PCS","45.8",IF(G45="PCM","50",IF(G45="PCL","58.3","0")))))) -> 0
A46: =A45+1 -> 35 | J46: =IF(G46="RSL","55","0") -> 0 | K46: =IF(G46="GVS","37.5",IF(G46="GVM","41.5",IF(G46="GVL","50",IF(G46="PCS","45.8",IF(G46="PCM","50",IF(G46="PCL","58.3","0")))))) -> 0
A47: =A46+1 -> 36 | J47: =IF(G47="RSL","55","0") -> 0 | K47: =IF(G47="GVS","37.5",IF(G47="GVM","41.5",IF(G47="GVL","50",IF(G47="PCS","45.8",IF(G47="PCM","50",IF(G47="PCL","58.3","0")))))) -> 0
A48: =A47+1 -> 37 | J48: =IF(G48="RSL","55","0") -> 0 | K48: =IF(G48="GVS","37.5",IF(G48="GVM","41.5",IF(G48="GVL","50",IF(G48="PCS","45.8",IF(G48="PCM","50",IF(G48="PCL","58.3","0")))))) -> 0
A49: =A48+1 -> 38 | J49: =IF(G49="RSL","55","0") -> 0 | K49: =IF(G49="GVS","37.5",IF(G49="GVM","41.5",IF(G49="GVL","50",IF(G49="PCS","45.8",IF(G49="PCM","50",IF(G49="PCL","58.3","0")))))) -> 0
... A61: =A60+1 -> 50 | J61: =IF(G61="RSL","55","0") -> 0 | K61: =IF(G61="GVS","37.5",IF(G61="GVM","41.5",IF(G61="GVL","50",IF(G61="PCS","45.8",IF(G61="PCM","50",IF(G61="PCL","58.3","0")))))) -> 0
A62: Page total | H62: =SUM(H37:H61) -> 0 | I62: =SUM(I37:I61) -> 0 | J62: =J61+J60+J59+J58+J57+J56+J55+J54+J53+J52+J51+J50+J49+J48+J47+J46+J45+J44+J43+J42+J41+J40+J39+J38+J37 -> 0 | K62: =K61+K60+K59+K58+K57+K56+K55+K54+K53+K52+K51+K50+K49+K48+K47+K46+K45+K44+K43+K42+K41+K40+K39+K38+K37 -> 0 | L62: =SUM(L37:L61) -> 0 | M62: =SUM(M37:M61) -> 0
R64: Page: 2
A65: Daily Report
A66: =A34 -> 27 - 4 - 2022 | H66: WEATHER | J66: =J34 -> MIX | L66: REPORT by | O66: =O34 -> HENDRA | R66: TOTAL STAFF | T66: =T34 -> 6
A68: No | B68: Docket No | C68: Reg No | D68: Mobile | E68: Gender | F68: TIME | G68: Service | H68: CASH | I68: CARD | J68: RSL | K68: GV | L68: GV CASH | M68: GV CARD | N68: O/Taker | O68: Comment | R68: NAME | S68: Time In | T68: Time out | U68: Total Hours
A69: =A61+1 -> 51 | J69: =IF(G69="RSL","55","0") -> 0 | K69: =IF(G69="GVS","37.5",IF(G69="GVM","41.5",IF(G69="GVL","50",IF(G69="PCS","45.8",IF(G69="PCM","50",IF(G69="PCL","58.3","0")))))) -> 0
A70: =A69+1 -> 52 | J70: =IF(G70="RSL","55","0") -> 0 | K70: =IF(G70="GVS","37.5",IF(G70="GVM","41.5",IF(G70="GVL","50",IF(G70="PCS","45.8",IF(G70="PCM","50",IF(G70="PCL","58.3","0")))))) -> 0
A71: =A70+1 -> 53 | J71: =IF(G71="RSL","55","0") -> 0 | K71: =IF(G71="GVS","37.5",IF(G71="GVM","41.5",IF(G71="GVL","50",IF(G71="PCS","45.8",IF(G71="PCM","50",IF(G71="PCL","58.3","0")))))) -> 0
A72: =A71+1 -> 54 | J72: =IF(G72="RSL","55","0") -> 0 | K72: =IF(G72="GVS","37.5",IF(G72="GVM","41.5",IF(G72="GVL","50",IF(G72="PCS","45.8",IF(G72="PCM","50",IF(G72="PCL","58.3","0")))))) -> 0
A73: =A72+1 -> 55 | J73: =IF(G73="RSL","55","0") -> 0 | K73: =IF(G73="GVS","37.5",IF(G73="GVM","41.5",IF(G73="GVL","50",IF(G73="PCS","45.8",IF(G73="PCM","50",IF(G73="PCL","58.3","0")))))) -> 0
A74: =A73+1 -> 56 | J74: =IF(G74="RSL","55","0") -> 0 | K74: =IF(G74="GVS","37.5",IF(G74="GVM","41.5",IF(G74="GVL","50",IF(G74="PCS","45.8",IF(G74="PCM","50",IF(G74="PCL","58.3","0")))))) -> 0
A75: =A74+1 -> 57 | J75: =IF(G75="RSL","55","0") -> 0 | K75: =IF(G75="GVS","37.5",IF(G75="GVM","41.5",IF(G75="GVL","50",IF(G75="PCS","45.8",IF(G75="PCM","50",IF(G75="PCL","58.3","0")))))) -> 0
A76: =A75+1 -> 58 | J76: =IF(G76="RSL","55","0") -> 0 | K76: =IF(G76="GVS","37.5",IF(G76="GVM","41.5",IF(G76="GVL","50",IF(G76="PCS","45.8",IF(G76="PCM","50",IF(G76="PCL","58.3","0")))))) -> 0
A77: =A76+1 -> 59 | J77: =IF(G77="RSL","55","0") -> 0 | K77: =IF(G77="GVS","37.5",IF(G77="GVM","41.5",IF(G77="GVL","50",IF(G77="PCS","45.8",IF(G77="PCM","50",IF(G77="PCL","58.3","0")))))) -> 0
A78: =A77+1 -> 60 | J78: =IF(G78="RSL","55","0") -> 0 | K78: =IF(G78="GVS","37.5",IF(G78="GVM","41.5",IF(G78="GVL","50",IF(G78="PCS","45.8",IF(G78="PCM","50",IF(G78="PCL","58.3","0")))))) -> 0
A79: =A78+1 -> 61 | J79: =IF(G79="RSL","55","0") -> 0 | K79: =IF(G79="GVS","37.5",IF(G79="GVM","41.5",IF(G79="GVL","50",IF(G79="PCS","45.8",IF(G79="PCM","50",IF(G79="PCL","58.3","0")))))) -> 0
A80: =A79+1 -> 62 | J80: =IF(G80="RSL","55","0") -> 0 | K80: =IF(G80="GVS","37.5",IF(G80="GVM","41.5",IF(G80="GVL","50",IF(G80="PCS","45.8",IF(G80="PCM","50",IF(G80="PCL","58.3","0")))))) -> 0
A81: =A80+1 -> 63 | J81: =IF(G81="RSL","55","0") -> 0 | K81: =IF(G81="GVS","37.5",IF(G81="GVM","41.5",IF(G81="GVL","50",IF(G81="PCS","45.8",IF(G81="PCM","50",IF(G81="PCL","58.3","0")))))) -> 0
... A93: =A92+1 -> 75 | J93: =IF(G93="RSL","55","0") -> 0 | K93: =IF(G93="GVS","37.5",IF(G93="GVM","41.5",IF(G93="GVL","50",IF(G93="PCS","45.8",IF(G93="PCM","50",IF(G93="PCL","58.3","0")))))) -> 0
A94: Page total | H94: =SUM(H69:H93) -> 0 | I94: =SUM(I69:I93) -> 0 | J94: =J93+J92+J91+J90+J89+J88+J87+J86+J85+J84+J83+J82+J81+J80+J79+J78+J77+J76+J75+J74+J73+J72+J71+J70+J69 -> 0 | K94: =K93+K92+K91+K90+K89+K88+K87+K86+K85+K84+K83+K82+K81+K80+K79+K78+K77+K76+K75+K74+K73+K72+K71+K70+K69 -> 0 | L94: =SUM(L69:L93) -> 0 | M94: =SUM(M69:M93) -> 0
R96: Page: 3

Sheet THU
A1: B2 Daily Report
A2: 28 - 4 - 2022 | H2: WEATHER | J2: MIX | L2: REPORT BY | O2: HENDRA | R2: TOTAL STAFF | T2: 6 | X2: Merchant machine usage at B2 | AA2: Settle amount | AI2: Merchant machine usage at GA | AL2: Settle amount
A4: No | B4: Docket No | C4: Reg No | D4: Mobile | E4: Gender | F4: TIME | G4: Service | H4: CASH | I4: CARD | J4: RSL | K4: GV | L4: GV CASH | M4: GV CARD | N4: O/Taker | O4: Comment | R4: NAME | S4: Time In | T4: Time out | U4: Total Hours | Z4: B2 machine | AA4: BLH machine | AB4: Wongo | AE4: B2 machine | AF4: BLH machine | AG4: Wongo | AK4: GA machine | AL4: BLH machine | AM4: Wongo | AP4: GA machine | AQ4: BLH machine | AR4: Wongo
A5: 1 | B5: 3137 | C5: EBP42L | D5: 0408062082 | E5: F | F5: 925 | G5: D | H5: 55 | J5: =IF(G5="RSL","55","0") -> 0 | K5: =IF(G5="GVS","37.5",IF(G5="GVM","41.5",IF(G5="GVL","50",IF(G5="PCS","45.8",IF(G5="PCM","50",IF(G5="PCL","58.3","0")))))) -> 0 | N5: HENDRA | R5: HENDRA | S5: 0.33333333 | T5: 0.69791667 | U5: =(T5-S5)*24 -> 8.75 | X5: NOV | Y5: 1 | AD5: 16 | AI5: NOV | AJ5: 1 | AO5: 16
A6: 2 | B6: 3138 | C6: COM84M | D6: 0405232880 | E6: F | F6: 945 | G6: GV3 | J6: =IF(G6="RSL","55","0") -> 0 | K6: =IF(G6="GVS","37.5",IF(G6="GVM","41.5",IF(G6="GVL","50",IF(G6="PCS","45.8",IF(G6="PCM","50",IF(G6="PCL","58.3","0")))))) -> 0 | M6: 475 | N6: HENDRA | O6: #192657 6/6,PCL22022 | R6: JUNIOR | S6: 0.33333333 | T6: 0.69791667 | U6: =(T6-S6)*24 -> 8.75 | W6: M | Y6: 2 | AD6: 17 | AJ6: 2 | AO6: 17
A7: 3 | B7: 3139 | C7: MHC100 | D7: 0401719195 | E7: M | F7: 1000 | G7: X | I7: 95 | J7: =IF(G7="RSL","55","0") -> 0 | K7: =IF(G7="GVS","37.5",IF(G7="GVM","41.5",IF(G7="GVL","50",IF(G7="PCS","45.8",IF(G7="PCM","50",IF(G7="PCL","58.3","0")))))) -> 0 | N7: HENDRA | R7: ARIANTO | S7: 0.375 | T7: 0.58333333 | U7: =(T7-S7)*24 -> 5 | W7: F | Y7: 3 | AD7: 18 | AJ7: 3 | AO7: 18
A8: 4 | B8: 3140 | C8: DZN84H | D8: 0409124145 | E8: F | F8: 1000 | G8: X | I8: 75 | J8: =IF(G8="RSL","55","0") -> 0 | K8: =IF(G8="GVS","37.5",IF(G8="GVM","41.5",IF(G8="GVL","50",IF(G8="PCS","45.8",IF(G8="PCM","50",IF(G8="PCL","58.3","0")))))) -> 0 | N8: HENDRA | R8: KUROSH | S8: 0.39583333 | T8: 0.69791667 | U8: =(T8-S8)*24 -> 7.25 | Y8: 4 | AD8: 19 | AJ8: 4 | AO8: 19
A9: 5 | B9: 3141 | C9: DCA86H | D9: 0488888890 | E9: F | F9: 1130 | G9: D/LTH | H9: 280 | J9: =IF(G9="RSL","55","0") -> 0 | K9: =IF(G9="GVS","37.5",IF(G9="GVM","41.5",IF(G9="GVL","50",IF(G9="PCS","45.8",IF(G9="PCM","50",IF(G9="PCL","58.3","0")))))) -> 0 | N9: HENDRA | O9: MEDIUM | R9: VINNY | S9: 0.45833333 | T9: 0.69791667 | U9: =(T9-S9)*24 -> 5.75 | X9: EXCL RSL | Y9: 5 | AD9: 20 | AJ9: 5 | AO9: 20
A10: 6 | B10: 3142 | C10: CPG22Z | D10: 0431128123 | E10: F | F10: 1145 | G10: W/O | I10: 50 | J10: =IF(G10="RSL","55","0") -> 0 | K10: =IF(G10="GVS","37.5",IF(G10="GVM","41.5",IF(G10="GVL","50",IF(G10="PCS","45.8",IF(G10="PCM","50",IF(G10="PCL","58.3","0")))))) -> 0 | N10: HENDRA | R10: AMAN | S10: 0.41666667 | T10: 0.625 | U10: =(T10-S10)*24 -> 5 | Y10: 6 | AD10: 21 | AJ10: 6 | AO10: 21
A11: 7 | B11: 3143 | C11: CCWWW | D11: 0406531188 | E11: F | F11: 1145 | G11: PCS | J11: =IF(G11="RSL","55","0") -> 0 | K11: 183.2 | L11: 375 | N11: HENDRA | O11: #21012 3-6/6, 22015 | U11: =(T11-S11)*24 -> 0 | Y11: 7 | AD11: 22 | AJ11: 7 | AO11: 22
A12: 8 | B12: 3144 | C12: ELL66R | D12: 0451788868 | E12: F | F12: 1230 | G12: X | I12: 75 | J12: =IF(G12="RSL","55","0") -> 0 | K12: =IF(G12="GVS","37.5",IF(G12="GVM","41.5",IF(G12="GVL","50",IF(G12="PCS","45.8",IF(G12="PCM","50",IF(G12="PCL","58.3","0")))))) -> 0 | N12: HENDRA | U12: =(T12-S12)*24 -> 0 | Y12: 8 | AD12: 23 | AJ12: 8 | AO12: 23
A13: 9 | B13: 3145 | C13: ELD06Q | D13: 0468939163 | E13: M | F13: 1230 | G13: RSL | J13: =IF(G13="RSL","55","0") -> 55 | K13: =IF(G13="GVS","37.5",IF(G13="GVM","41.5",IF(G13="GVL","50",IF(G13="PCS","45.8",IF(G13="PCM","50",IF(G13="PCL","58.3","0")))))) -> 0 | N13: HENDRA | O13: 202112050 | U13: =(T13-S13)*24 -> 0 | Y13: 9 | AD13: 24 | AJ13: 9 | AO13: 24
A14: 10 | B14: 3146 | C14: DKM59V | D14: 0425227128 | E14: F | F14: 1330 | G14: D | I14: 75 | J14: =IF(G14="RSL","55","0") -> 0 | K14: =IF(G14="GVS","37.5",IF(G14="GVM","41.5",IF(G14="GVL","50",IF(G14="PCS","45.8",IF(G14="PCM","50",IF(G14="PCL","58.3","0")))))) -> 0 | N14: HENDRA | U14: =(T14-S14)*24 -> 0 | Y14: 10 | AD14: 25 | AJ14: 10 | AO14: 25
A15: 11 | B15: 3147 | C15: EOK70F | D15: 0419236787 | E15: F | F15: 1545 | G15: X | H15: 95 | J15: =IF(G15="RSL","55","0") -> 0 | K15: =IF(G15="GVS","37.5",IF(G15="GVM","41.5",IF(G15="GVL","50",IF(G15="PCS","45.8",IF(G15="PCM","50",IF(G15="PCL","58.3","0")))))) -> 0 | N15: HENDRA | U15: =(T15-S15)*24 -> 0 | Y15: 11 | AD15: 26 | AJ15: 11 | AO15: 26
A16: 12 | J16: =IF(G16="RSL","55","0") -> 0 | K16: =IF(G16="GVS","37.5",IF(G16="GVM","41.5",IF(G16="GVL","50",IF(G16="PCS","45.8",IF(G16="PCM","50",IF(G16="PCL","58.3","0")))))) -> 0 | R16: =H32/U16 -> 0.27160494 | S16: =H32/(U16-U5) -> 0.34645669 | T16: =C32/U16 -> 25.634568 | U16: =SUM(U5:U15) -> 40.5 | Y16: 12 | AD16: 27 | AJ16: 12 | AO16: 27
A17: 13 | J17: =IF(G17="RSL","55","0") -> 0 | K17: =IF(G17="GVS","37.5",IF(G17="GVM","41.5",IF(G17="GVL","50",IF(G17="PCS","45.8",IF(G17="PCM","50",IF(G17="PCL","58.3","0")))))) -> 0 | R17: Cars/T Hr ① | S17: Cars/T Hr ② | T17: Sales/T Hr | U17: Total Hours | Y17: 13 | AD17: 28 | AJ17: 13 | AO17: 28
A18: 14 | J18: =IF(G18="RSL","55","0") -> 0 | K18: =IF(G18="GVS","37.5",IF(G18="GVM","41.5",IF(G18="GVL","50",IF(G18="PCS","45.8",IF(G18="PCM","50",IF(G18="PCL","58.3","0")))))) -> 0 | R18: ITEM | S18: QTY | T18: AMT | U18: RMKS | Y18: 14 | AD18: 29 | AJ18: 14 | AO18: 29
A19: 15 | J19: =IF(G19="RSL","55","0") -> 0 | K19: =IF(G19="GVS","37.5",IF(G19="GVM","41.5",IF(G19="GVL","50",IF(G19="PCS","45.8",IF(G19="PCM","50",IF(G19="PCL","58.3","0")))))) -> 0 | R19: GV | S19: =COUNT(L5:M29,L37:M61,L69:M93) -> 2 | T19: =SUM(L5:M29,L37:M61,L69:M93) -> 850 | Y19: 15 | AD19: 30 | AJ19: 15 | AO19: 30
A20: 16 | J20: =IF(G20="RSL","55","0") -> 0 | K20: =IF(G20="GVS","37.5",IF(G20="GVM","41.5",IF(G20="GVL","50",IF(G20="PCS","45.8",IF(G20="PCM","50",IF(G20="PCL","58.3","0")))))) -> 0 | AD20: 31 | AO20: 31
A21: 17 | J21: =IF(G21="RSL","55","0") -> 0 | K21: =IF(G21="GVS","37.5",IF(G21="GVM","41.5",IF(G21="GVL","50",IF(G21="PCS","45.8",IF(G21="PCM","50",IF(G21="PCL","58.3","0")))))) -> 0
A22: 18 | J22: =IF(G22="RSL","55","0") -> 0 | K22: =IF(G22="GVS","37.5",IF(G22="GVM","41.5",IF(G22="GVL","50",IF(G22="PCS","45.8",IF(G22="PCM","50",IF(G22="PCL","58.3","0")))))) -> 0 | AD22: Total | AE22: =SUM(Z5:Z19,AE5:AE20) -> 0 | AF22: =SUM(AA5:AA19,AF5:AF20,) -> 0 | AG22: =SUM(AB5:AB19,AG5:AG20) -> 0 | AO22: Total | AP22: =SUM(AK5:AK19,AP5:AP20) -> 0 | AQ22: =SUM(AL5:AL19,AQ5:AQ20,) -> 0 | AR22: =SUM(AM5:AM19,AR5:AR20) -> 0
A23: 19 | J23: =IF(G23="RSL","55","0") -> 0 | K23: =IF(G23="GVS","37.5",IF(G23="GVM","41.5",IF(G23="GVL","50",IF(G23="PCS","45.8",IF(G23="PCM","50",IF(G23="PCL","58.3","0")))))) -> 0
A24: 20 | J24: =IF(G24="RSL","55","0") -> 0 | K24: =IF(G24="GVS","37.5",IF(G24="GVM","41.5",IF(G24="GVL","50",IF(G24="PCS","45.8",IF(G24="PCM","50",IF(G24="PCL","58.3","0")))))) -> 0 | R24: SMALL | S24: MEDIUM | T24: LARGE | U24: TOTAL | AD24: B2/GA TOTAL | AE24: B2 machine | AF24: GA machine | AG24: BLH machine | AH24: Wongo machine | AI24: Sub total
A25: 21 | J25: =IF(G25="RSL","55","0") -> 0 | K25: =IF(G25="GVS","37.5",IF(G25="GVM","41.5",IF(G25="GVL","50",IF(G25="PCS","45.8",IF(G25="PCM","50",IF(G25="PCL","58.3","0")))))) -> 0 | R25: =COUNTIF(G5:G29,"GV1")+COUNTIF(G37:G61,"GV1")+COUNTIF(G69:G93,"GV1") -> 0 | S25: =COUNTIF(G5:G29,"GV2")+COUNTIF(G37:G61,"GV2")+COUNTIF(G69:G93,"GV2") -> 0 | T25: =COUNTIF(G5:G29,"GV3")+COUNTIF(G37:G61,"GV3")+COUNTIF(G69:G93,"GV3") -> 1 | U25: =((C32+(R26+S26+T26)*0.5)) -> 1063.2 | AD25: =SUM(AE25:AF25) -> 0 | AE25: =SUM(AE22) -> 0 | AF25: =SUM(AP22) -> 0 | AG25: =SUM(AF22+AQ22) -> 0 | AH25: =AG22+AR22 -> 0 | AI25: =SUM(AE25:AH25) -> 0
A26: 22 | J26: =IF(G26="RSL","55","0") -> 0 | K26: =IF(G26="GVS","37.5",IF(G26="GVM","41.5",IF(G26="GVL","50",IF(G26="PCS","45.8",IF(G26="PCM","50",IF(G26="PCL","58.3","0")))))) -> 0 | R26: =R25*37.5 -> 0 | S26: =S25*41.5 -> 0 | T26: =T25*50 -> 50 | X26: Branch cards
A27: 23 | J27: =IF(G27="RSL","55","0") -> 0 | K27: =IF(G27="GVS","37.5",IF(G27="GVM","41.5",IF(G27="GVL","50",IF(G27="PCS","45.8",IF(G27="PCM","50",IF(G27="PCL","58.3","0")))))) -> 0 | R27: Expense | X27: 1 | Z27: -2745
A28: 24 | J28: =IF(G28="RSL","55","0") -> 0 | K28: =IF(G28="GVS","37.5",IF(G28="GVM","41.5",IF(G28="GVL","50",IF(G28="PCS","45.8",IF(G28="PCM","50",IF(G28="PCL","58.3","0")))))) -> 0 | X28: 2
A29: 25 | J29: =IF(G29="RSL","55","0") -> 0 | K29: =IF(G29="GVS","37.5",IF(G29="GVM","41.5",IF(G29="GVL","50",IF(G29="PCS","45.8",IF(G29="PCM","50",IF(G29="PCL","58.3","0")))))) -> 0 | X29: 3
A30: Page total | H30: =SUM(H5:H29) -> 430 | I30: =SUM(I5:I29) -> 370 | J30: =J5+J6+J7+J8+J9+J10+J11+J12+J13+J14+J15+J16+J18+J19+J17+J20+J22+J23+J21+J24+J25+J26+J27+J28+J29 -> 55 | K30: =K5+K6+K7+K8+K9+K10+K11+K12+K13+K14+K15+K16+K18+K19+K17+K20+K22+K23+K21+K24+K25+K26+K27+K28+K29 -> 183.2 | L30: =SUM(L5:L29) -> 375 | M30: =SUM(M5:M29) -> 475 | N30: CASH | O30: CARD | P30: GV | Q30: RSL | X30: 4
A31: Daily Total | H31: =H30+H62+H94 -> 430 | I31: =I30+I62+I94 -> 370 | J31: =J30+J62+J94 -> 55 | K31: =K30+K62+K94 -> 183.2 | L31: =L30+L62+L94 -> 375 | M31: =M30+M62+M94 -> 475 | N31: =COUNT(H5:H29,H37:H61,H69:H93) -> 3 | O31: =COUNT(I5:I29,I37:I61,I69:I93) -> 5 | P31: =COUNTIF(G5:G29,"G*")+COUNTIF(G37:G61,"G*")+COUNTIF(G69:G93,"G*")+COUNTIF(G5:G29,"P*")+COUNTIF(G37:G61,"P*")+COUNTIF(G69:G93,"P*") -> 2 | Q31: =COUNTIF(G5:G29,"RSL")+COUNTIF(G37:G61,"RSL")+COUNTIF(G69:G93,"RSL") -> 1 | R31: CASH CLOSING | S31: =H31+L31-U28-U29-U30 -> 805 | T31: =H31+I31+L31+M31 -> 1650 | X31: Subtotal | Z31: =SUM(Z27:Z30) -> -2745
A32: TOTAL SALES | C32: =H31+I31+J31+K31 -> 1038.2 | F32: No of Cars | H32: =COUNT(B5:B29,B37:B61,B69:B93) -> 11 | I32: Average | K32: =C32/H32 -> 94.381818 | N32: =H31/C32 -> 0.41417839 | O32: =I31/C32 -> 0.35638605 | P32: =K31/C32 -> 0.17645926 | Q32: =J31/C32 -> 0.052976305 | R32: CARD CLOSING | S32: =I31+M31 -> 845 | X32: B2 card | Z32: =I31 -> 370
A33: Daily Report | X33: Settlement | Z33: =SUM(Z31:Z32) -> -2375
A34: =A2 -> 28 - 4 - 2022 | H34: WEATHER | J34: =J2 -> MIX | L34: REPORT by | O34: =O2 -> HENDRA | R34: TOTAL STAFF | T34: =T2 -> 6
A36: No | B36: Docket No | C36: Reg No | D36: Mobile | E36: Gender | F36: TIME | G36: Service | H36: CASH | I36: CARD | J36: RSL | K36: GV | L36: GV CASH | M36: GV CARD | N36: O/Taker | O36: Comment | R36: NAME | S36: Time In | T36: Time out | U36: Total Hours
A37: =A29+1 -> 26 | J37: =IF(G37="RSL","55","0") -> 0 | K37: =IF(G37="GVS","37.5",IF(G37="GVM","41.5",IF(G37="GVL","50",IF(G37="PCS","45.8",IF(G37="PCM","50",IF(G37="PCL","58.3","0")))))) -> 0
A38: =A37+1 -> 27 | J38: =IF(G38="RSL","55","0") -> 0 | K38: =IF(G38="GVS","37.5",IF(G38="GVM","41.5",IF(G38="GVL","50",IF(G38="PCS","45.8",IF(G38="PCM","50",IF(G38="PCL","58.3","0")))))) -> 0
A39: =A38+1 -> 28 | J39: =IF(G39="RSL","55","0") -> 0 | K39: =IF(G39="GVS","37.5",IF(G39="GVM","41.5",IF(G39="GVL","50",IF(G39="PCS","45.8",IF(G39="PCM","50",IF(G39="PCL","58.3","0")))))) -> 0
A40: =A39+1 -> 29 | J40: =IF(G40="RSL","55","0") -> 0 | K40: =IF(G40="GVS","37.5",IF(G40="GVM","41.5",IF(G40="GVL","50",IF(G40="PCS","45.8",IF(G40="PCM","50",IF(G40="PCL","58.3","0")))))) -> 0
A41: =A40+1 -> 30 | J41: =IF(G41="RSL","55","0") -> 0 | K41: =IF(G41="GVS","37.5",IF(G41="GVM","41.5",IF(G41="GVL","50",IF(G41="PCS","45.8",IF(G41="PCM","50",IF(G41="PCL","58.3","0")))))) -> 0
A42: =A41+1 -> 31 | J42: =IF(G42="RSL","55","0") -> 0 | K42: =IF(G42="GVS","37.5",IF(G42="GVM","41.5",IF(G42="GVL","50",IF(G42="PCS","45.8",IF(G42="PCM","50",IF(G42="PCL","58.3","0")))))) -> 0
A43: =A42+1 -> 32 | J43: =IF(G43="RSL","55","0") -> 0 | K43: =IF(G43="GVS","37.5",IF(G43="GVM","41.5",IF(G43="GVL","50",IF(G43="PCS","45.8",IF(G43="PCM","50",IF(G43="PCL","58.3","0")))))) -> 0
A44: =A43+1 -> 33 | J44: =IF(G44="RSL","55","0") -> 0 | K44: =IF(G44="GVS","37.5",IF(G44="GVM","41.5",IF(G44="GVL","50",IF(G44="PCS","45.8",IF(G44="PCM","50",IF(G44="PCL","58.3","0")))))) -> 0
A45: =A44+1 -> 34 | J45: =IF(G45="RSL","55","0") -> 0 | K45: =IF(G45="GVS","37.5",IF(G45="GVM","41.5",IF(G45="GVL","50",IF(G45="PCS","45.8",IF(G45="PCM","50",IF(G45="PCL","58.3","0")))))) -> 0
A46: =A45+1 -> 35 | J46: =IF(G46="RSL","55","0") -> 0 | K46: =IF(G46="GVS","37.5",IF(G46="GVM","41.5",IF(G46="GVL","50",IF(G46="PCS","45.8",IF(G46="PCM","50",IF(G46="PCL","58.3","0")))))) -> 0
A47: =A46+1 -> 36 | J47: =IF(G47="RSL","55","0") -> 0 | K47: =IF(G47="GVS","37.5",IF(G47="GVM","41.5",IF(G47="GVL","50",IF(G47="PCS","45.8",IF(G47="PCM","50",IF(G47="PCL","58.3","0")))))) -> 0
A48: =A47+1 -> 37 | J48: =IF(G48="RSL","55","0") -> 0 | K48: =IF(G48="GVS","37.5",IF(G48="GVM","41.5",IF(G48="GVL","50",IF(G48="PCS","45.8",IF(G48="PCM","50",IF(G48="PCL","58.3","0")))))) -> 0
A49: =A48+1 -> 38 | J49: =IF(G49="RSL","55","0") -> 0 | K49: =IF(G49="GVS","37.5",IF(G49="GVM","41.5",IF(G49="GVL","50",IF(G49="PCS","45.8",IF(G49="PCM","50",IF(G49="PCL","58.3","0")))))) -> 0
... A61: =A60+1 -> 50 | J61: =IF(G61="RSL","55","0") -> 0 | K61: =IF(G61="GVS","37.5",IF(G61="GVM","41.5",IF(G61="GVL","50",IF(G61="PCS","45.8",IF(G61="PCM","50",IF(G61="PCL","58.3","0")))))) -> 0
A62: Page total | H62: =SUM(H37:H61) -> 0 | I62: =SUM(I37:I61) -> 0 | J62: =J61+J60+J59+J58+J57+J56+J55+J54+J53+J52+J51+J50+J49+J48+J47+J46+J45+J44+J43+J42+J41+J40+J39+J38+J37 -> 0 | K62: =K61+K60+K59+K58+K57+K56+K55+K54+K53+K52+K51+K50+K49+K48+K47+K46+K45+K44+K43+K42+K41+K40+K39+K38+K37 -> 0 | L62: =SUM(L37:L61) -> 0 | M62: =SUM(M37:M61) -> 0
R64: Page: 2
A65: Daily Report
A66: =A34 -> 28 - 4 - 2022 | H66: WEATHER | J66: =J34 -> MIX | L66: REPORT by | O66: =O34 -> HENDRA | R66: TOTAL STAFF | T66: =T34 -> 6
A68: No | B68: Docket No | C68: Reg No | D68: Mobile | E68: Gender | F68: TIME | G68: Service | H68: CASH | I68: CARD | J68: RSL | K68: GV | L68: GV CASH | M68: GV CARD | N68: O/Taker | O68: Comment | R68: NAME | S68: Time In | T68: Time out | U68: Total Hours
A69: =A61+1 -> 51 | J69: =IF(G69="RSL","55","0") -> 0 | K69: =IF(G69="GVS","37.5",IF(G69="GVM","41.5",IF(G69="GVL","50",IF(G69="PCS","45.8",IF(G69="PCM","50",IF(G69="PCL","58.3","0")))))) -> 0
A70: =A69+1 -> 52 | J70: =IF(G70="RSL","55","0") -> 0 | K70: =IF(G70="GVS","37.5",IF(G70="GVM","41.5",IF(G70="GVL","50",IF(G70="PCS","45.8",IF(G70="PCM","50",IF(G70="PCL","58.3","0")))))) -> 0
A71: =A70+1 -> 53 | J71: =IF(G71="RSL","55","0") -> 0 | K71: =IF(G71="GVS","37.5",IF(G71="GVM","41.5",IF(G71="GVL","50",IF(G71="PCS","45.8",IF(G71="PCM","50",IF(G71="PCL","58.3","0")))))) -> 0
A72: =A71+1 -> 54 | J72: =IF(G72="RSL","55","0") -> 0 | K72: =IF(G72="GVS","37.5",IF(G72="GVM","41.5",IF(G72="GVL","50",IF(G72="PCS","45.8",IF(G72="PCM","50",IF(G72="PCL","58.3","0")))))) -> 0
A73: =A72+1 -> 55 | J73: =IF(G73="RSL","55","0") -> 0 | K73: =IF(G73="GVS","37.5",IF(G73="GVM","41.5",IF(G73="GVL","50",IF(G73="PCS","45.8",IF(G73="PCM","50",IF(G73="PCL","58.3","0")))))) -> 0
A74: =A73+1 -> 56 | J74: =IF(G74="RSL","55","0") -> 0 | K74: =IF(G74="GVS","37.5",IF(G74="GVM","41.5",IF(G74="GVL","50",IF(G74="PCS","45.8",IF(G74="PCM","50",IF(G74="PCL","58.3","0")))))) -> 0
A75: =A74+1 -> 57 | J75: =IF(G75="RSL","55","0") -> 0 | K75: =IF(G75="GVS","37.5",IF(G75="GVM","41.5",IF(G75="GVL","50",IF(G75="PCS","45.8",IF(G75="PCM","50",IF(G75="PCL","58.3","0")))))) -> 0
A76: =A75+1 -> 58 | J76: =IF(G76="RSL","55","0") -> 0 | K76: =IF(G76="GVS","37.5",IF(G76="GVM","41.5",IF(G76="GVL","50",IF(G76="PCS","45.8",IF(G76="PCM","50",IF(G76="PCL","58.3","0")))))) -> 0
A77: =A76+1 -> 59 | J77: =IF(G77="RSL","55","0") -> 0 | K77: =IF(G77="GVS","37.5",IF(G77="GVM","41.5",IF(G77="GVL","50",IF(G77="PCS","45.8",IF(G77="PCM","50",IF(G77="PCL","58.3","0")))))) -> 0
A78: =A77+1 -> 60 | J78: =IF(G78="RSL","55","0") -> 0 | K78: =IF(G78="GVS","37.5",IF(G78="GVM","41.5",IF(G78="GVL","50",IF(G78="PCS","45.8",IF(G78="PCM","50",IF(G78="PCL","58.3","0")))))) -> 0
A79: =A78+1 -> 61 | J79: =IF(G79="RSL","55","0") -> 0 | K79: =IF(G79="GVS","37.5",IF(G79="GVM","41.5",IF(G79="GVL","50",IF(G79="PCS","45.8",IF(G79="PCM","50",IF(G79="PCL","58.3","0")))))) -> 0
A80: =A79+1 -> 62 | J80: =IF(G80="RSL","55","0") -> 0 | K80: =IF(G80="GVS","37.5",IF(G80="GVM","41.5",IF(G80="GVL","50",IF(G80="PCS","45.8",IF(G80="PCM","50",IF(G80="PCL","58.3","0")))))) -> 0
A81: =A80+1 -> 63 | J81: =IF(G81="RSL","55","0") -> 0 | K81: =IF(G81="GVS","37.5",IF(G81="GVM","41.5",IF(G81="GVL","50",IF(G81="PCS","45.8",IF(G81="PCM","50",IF(G81="PCL","58.3","0")))))) -> 0
... A93: =A92+1 -> 75 | J93: =IF(G93="RSL","55","0") -> 0 | K93: =IF(G93="GVS","37.5",IF(G93="GVM","41.5",IF(G93="GVL","50",IF(G93="PCS","45.8",IF(G93="PCM","50",IF(G93="PCL","58.3","0")))))) -> 0
A94: Page total | H94: =SUM(H69:H93) -> 0 | I94: =SUM(I69:I93) -> 0 | J94: =J93+J92+J91+J90+J89+J88+J87+J86+J85+J84+J83+J82+J81+J80+J79+J78+J77+J76+J75+J74+J73+J72+J71+J70+J69 -> 0 | K94: =K93+K92+K91+K90+K89+K88+K87+K86+K85+K84+K83+K82+K81+K80+K79+K78+K77+K76+K75+K74+K73+K72+K71+K70+K69 -> 0 | L94: =SUM(L69:L93) -> 0 | M94: =SUM(M69:M93) -> 0
R96: Page: 3

Sheet FRI
A1: B2 Daily Report
A2: 29 - 4 - 2022 | H2: WEATHER | J2: SUNNY | L2: REPORT BY | O2: HENDRA | R2: TOTAL STAFF | T2: 6 | X2: Merchant machine usage at B2 | AA2: Settle amount | AI2: Merchant machine usage at GA | AL2: Settle amount
A4: No | B4: Docket No | C4: Reg No | D4: Mobile | E4: Gender | F4: TIME | G4: Service | H4: CASH | I4: CARD | J4: RSL | K4: GV | L4: GV CASH | M4: GV CARD | N4: O/Taker | O4: Comment | R4: NAME | S4: Time In | T4: Time out | U4: Total Hours | Z4: B2 machine | AA4: BLH machine | AB4: Wongo | AE4: B2 machine | AF4: BLH machine | AG4: Wongo | AK4: GA machine | AL4: BLH machine | AM4: Wongo | AP4: GA machine | AQ4: BLH machine | AR4: Wongo
A5: 1 | B5: 3148 | C5: YKB60A | D5: 0450603985 | E5: M | F5: 840 | G5: RSL | H5: 10 | J5: =IF(G5="RSL","55","0") -> 55 | K5: =IF(G5="GVS","37.5",IF(G5="GVM","41.5",IF(G5="GVL","50",IF(G5="PCS","45.8",IF(G5="PCM","50",IF(G5="PCL","58.3","0")))))) -> 0 | N5: HENDRA | O5: 202202012 | R5: HENDRA | S5: 0.33333333 | T5: 0.70833333 | U5: =(T5-S5)*24 -> 9 | X5: NOV | Y5: 1 | AD5: 16 | AI5: NOV | AJ5: 1 | AO5: 16
A6: 2 | B6: 3149 | C6: GBI | D6: 0415888891 | E6: M | F6: 840 | G6: X | J6: =IF(G6="RSL","55","0") -> 0 | K6: =IF(G6="GVS","37.5",IF(G6="GVM","41.5",IF(G6="GVL","50",IF(G6="PCS","45.8",IF(G6="PCM","50",IF(G6="PCL","58.3","0")))))) -> 0 | N6: HENDRA | O6: CANCEL | R6: JUNIOR | S6: 0.33333333 | T6: 0.70833333 | U6: =(T6-S6)*24 -> 9 | W6: M | Y6: 2 | AD6: 17 | AJ6: 2 | AO6: 17
A7: 3 | B7: 3150 | C7: KEN838 | D7: ???? | E7: M | F7: 900 | G7: PCL | J7: =IF(G7="RSL","55","0") -> 0 | K7: 79.16 | N7: HENDRA | O7: # 22012 2/6 | R7: KUROSH | S7: 0.375 | T7: 0.70833333 | U7: =(T7-S7)*24 -> 8 | W7: F | Y7: 3 | AD7: 18 | AJ7: 3 | AO7: 18
A8: 4 | B8: 3151 | C8: YGH08Q | D8: ??? | E8: M | F8: 930 | G8: RSL | H8: 10 | J8: =IF(G8="RSL","55","0") -> 55 | K8: =IF(G8="GVS","37.5",IF(G8="GVM","41.5",IF(G8="GVL","50",IF(G8="PCS","45.8",IF(G8="PCM","50",IF(G8="PCL","58.3","0")))))) -> 0 | N8: HENDRA | O8: 202202054 | R8: ERIC | S8: 0.375 | T8: 0.70833333 | U8: =(T8-S8)*24 -> 8 | Y8: 4 | AD8: 19 | AJ8: 4 | AO8: 19
A9: 5 | B9: 3152 | C9: 84415R | D9: 0419551753 | E9: M | F9: 930 | G9: X | I9: 95 | J9: =IF(G9="RSL","55","0") -> 0 | K9: =IF(G9="GVS","37.5",IF(G9="GVM","41.5",IF(G9="GVL","50",IF(G9="PCS","45.8",IF(G9="PCM","50",IF(G9="PCL","58.3","0")))))) -> 0 | N9: HENDRA | R9: VINNY | S9: 0.41666667 | T9: 0.70833333 | U9: =(T9-S9)*24 -> 7 | X9: EXCL RSL | Y9: 5 | AD9: 20 | AJ9: 5 | AO9: 20
A10: 6 | B10: 3153 | C10: CIK51X | D10: 0412777581 | E10: F | F10: 1020 | G10: X | I10: 95 | J10: =IF(G10="RSL","55","0") -> 0 | K10: =IF(G10="GVS","37.5",IF(G10="GVM","41.5",IF(G10="GVL","50",IF(G10="PCS","45.8",IF(G10="PCM","50",IF(G10="PCL","58.3","0")))))) -> 0 | N10: HENDRA | R10: AMAN | S10: 0.40625 | T10: 0.70833333 | U10: =(T10-S10)*24 -> 7.25 | Y10: 6 | AD10: 21 | AJ10: 6 | AO10: 21
A11: 7 | B11: 3154 | C11: NBO53E | D11: 0414369004 | E11: F | F11: 1135 | G11: X | I11: 95 | J11: =IF(G11="RSL","55","0") -> 0 | K11: =IF(G11="GVS","37.5",IF(G11="GVM","41.5",IF(G11="GVL","50",IF(G11="PCS","45.8",IF(G11="PCM","50",IF(G11="PCL","58.3","0")))))) -> 0 | N11: JUNIOR | U11: =(T11-S11)*24 -> 0 | Y11: 7 | AD11: 22 | AJ11: 7 | AO11: 22
A12: 8 | B12: 3155 | C12: EMP51Y | D12: 0493119547 | E12: M | F12: 1145 | G12: X | I12: 95 | J12: =IF(G12="RSL","55","0") -> 0 | K12: =IF(G12="GVS","37.5",IF(G12="GVM","41.5",IF(G12="GVL","50",IF(G12="PCS","45.8",IF(G12="PCM","50",IF(G12="PCL","58.3","0")))))) -> 0 | N12: HENDRA | U12: =(T12-S12)*24 -> 0 | Y12: 8 | AD12: 23 | AJ12: 8 | AO12: 23
A13: 9 | B13: 3156 | C13: DHT87X | D13: 0411822032 | E13: F | F13: 1200 | G13: X | I13: 95 | J13: =IF(G13="RSL","55","0") -> 0 | K13: =IF(G13="GVS","37.5",IF(G13="GVM","41.5",IF(G13="GVL","50",IF(G13="PCS","45.8",IF(G13="PCM","50",IF(G13="PCL","58.3","0")))))) -> 0 | N13: HENDRA | U13: =(T13-S13)*24 -> 0 | Y13: 9 | AD13: 24 | AJ13: 9 | AO13: 24
A14: 10 | B14: 3157 | C14: BFI56T | D14: 0406340211 | E14: F | F14: 1210 | G14: D | I14: 55 | J14: =IF(G14="RSL","55","0") -> 0 | K14: =IF(G14="GVS","37.5",IF(G14="GVM","41.5",IF(G14="GVL","50",IF(G14="PCS","45.8",IF(G14="PCM","50",IF(G14="PCL","58.3","0")))))) -> 0 | N14: HENDRA | U14: =(T14-S14)*24 -> 0 | Y14: 10 | AD14: 25 | AJ14: 10 | AO14: 25
A15: 11 | B15: 3158 | C15: ZAP687 | D15: 0418144417 | E15: F | F15: 1215 | G15: D | I15: 65 | J15: =IF(G15="RSL","55","0") -> 0 | K15: =IF(G15="GVS","37.5",IF(G15="GVM","41.5",IF(G15="GVL","50",IF(G15="PCS","45.8",IF(G15="PCM","50",IF(G15="PCL","58.3","0")))))) -> 0 | N15: HENDRA | U15: =(T15-S15)*24 -> 0 | Y15: 11 | AD15: 26 | AJ15: 11 | AO15: 26
A16: 12 | B16: 3159 | C16: BGX82C | D16: 0401256951 | E16: M | F16: 1220 | G16: I/ST | I16: 200 | J16: =IF(G16="RSL","55","0") -> 0 | K16: =IF(G16="GVS","37.5",IF(G16="GVM","41.5",IF(G16="GVL","50",IF(G16="PCS","45.8",IF(G16="PCM","50",IF(G16="PCL","58.3","0")))))) -> 0 | N16: HENDRA | O16: MEDIUM | R16: =H32/U16 -> 0.41450777 | S16: =H32/(U16-U5) -> 0.50955414 | T16: =C32/U16 -> 31.174093 | U16: =SUM(U5:U15) -> 48.25 | Y16: 12 | AD16: 27 | AJ16: 12 | AO16: 27
A17: 13 | B17: 3160 | C17: DBI12C | D17: 0404479199 | E17: F | F17: 1300 | G17: D | I17: 55 | J17: =IF(G17="RSL","55","0") -> 0 | K17: =IF(G17="GVS","37.5",IF(G17="GVM","41.5",IF(G17="GVL","50",IF(G17="PCS","45.8",IF(G17="PCM","50",IF(G17="PCL","58.3","0")))))) -> 0 | N17: HENDRA | R17: Cars/T Hr ① | S17: Cars/T Hr ② | T17: Sales/T Hr | U17: Total Hours | Y17: 13 | AD17: 28 | AJ17: 13 | AO17: 28
A18: 14 | B18: 3161 | C18: CTC79Q | D18: 0407662843 | E18: F | F18: 1255 | G18: D | I18: 55 | J18: =IF(G18="RSL","55","0") -> 0 | K18: =IF(G18="GVS","37.5",IF(G18="GVM","41.5",IF(G18="GVL","50",IF(G18="PCS","45.8",IF(G18="PCM","50",IF(G18="PCL","58.3","0")))))) -> 0 | N18: HENDRA | R18: ITEM | S18: QTY | T18: AMT | U18: RMKS | Y18: 14 | AD18: 29 | AJ18: 14 | AO18: 29
A19: 15 | B19: 3162 | C19: BT28JS | D19: 0416107668 | E19: F | F19: 1320 | G19: RSL | J19: 110 | K19: =IF(G19="GVS","37.5",IF(G19="GVM","41.5",IF(G19="GVL","50",IF(G19="PCS","45.8",IF(G19="PCM","50",IF(G19="PCL","58.3","0")))))) -> 0 | N19: JUNIOR | O19: 202201065 , 202202046 | R19: GV | S19: =COUNT(L5:M29,L37:M61,L69:M93) -> 0 | T19: =SUM(L5:M29,L37:M61,L69:M93) -> 0 | Y19: 15 | AD19: 30 | AJ19: 15 | AO19: 30
A20: 16 | B20: 3163 | C20: CSB82P | D20: 0423229968 | E20: F | F20: 1400 | G20: GV3 | J20: =IF(G20="RSL","55","0") -> 0 | K20: =IF(G20="GVS","37.5",IF(G20="GVM","41.5",IF(G20="GVL","50",IF(G20="PCS","45.8",IF(G20="PCM","50",IF(G20="PCL","58.3","0")))))) -> 0 | N20: HENDRA | O20: #202810 3/6 4/6 | AD20: 31 | AO20: 31
A21: 17 | B21: 3164 | C21: DTI10V | D21: 0413181450 | E21: F | F21: 1400 | G21: PCS | J21: =IF(G21="RSL","55","0") -> 0 | K21: 70.83 | N21: HENDRA | O21: # 22011 2/6
A22: 18 | B22: 3165 | C22: XS66 | D22: 0431875858 | E22: M | F22: 1400 | G22: PCL | J22: =IF(G22="RSL","55","0") -> 0 | K22: 79.16 | N22: HENDRA | O22: # 22013 1/6 | AD22: Total | AE22: =SUM(Z5:Z19,AE5:AE20) -> 0 | AF22: =SUM(AA5:AA19,AF5:AF20,) -> 0 | AG22: =SUM(AB5:AB19,AG5:AG20) -> 0 | AO22: Total | AP22: =SUM(AK5:AK19,AP5:AP20) -> 0 | AQ22: =SUM(AL5:AL19,AQ5:AQ20,) -> 0 | AR22: =SUM(AM5:AM19,AR5:AR20) -> 0
A23: 19 | B23: 3166 | C23: APC88A | D23: 0410062241 | E23: F | F23: 1520 | G23: RSL | J23: =IF(G23="RSL","55","0") -> 55 | K23: =IF(G23="GVS","37.5",IF(G23="GVM","41.5",IF(G23="GVL","50",IF(G23="PCS","45.8",IF(G23="PCM","50",IF(G23="PCL","58.3","0")))))) -> 0 | N23: HENDRA | P23: 202202081
A24: 20 | B24: 3167 | C24: DGG70Q | D24: 0431155888 | E24: M | F24: 1615 | G24: X | I24: 75 | J24: =IF(G24="RSL","55","0") -> 0 | K24: =IF(G24="GVS","37.5",IF(G24="GVM","41.5",IF(G24="GVL","50",IF(G24="PCS","45.8",IF(G24="PCM","50",IF(G24="PCL","58.3","0")))))) -> 0 | N24: VINNY | R24: SMALL | S24: MEDIUM | T24: LARGE | U24: TOTAL | AD24: B2/GA TOTAL | AE24: B2 machine | AF24: GA machine | AG24: BLH machine | AH24: Wongo machine | AI24: Sub total
A25: 21 | J25: =IF(G25="RSL","55","0") -> 0 | K25: =IF(G25="GVS","37.5",IF(G25="GVM","41.5",IF(G25="GVL","50",IF(G25="PCS","45.8",IF(G25="PCM","50",IF(G25="PCL","58.3","0")))))) -> 0 | R25: =COUNTIF(G5:G29,"GV1")+COUNTIF(G37:G61,"GV1")+COUNTIF(G69:G93,"GV1") -> 0 | S25: =COUNTIF(G5:G29,"GV2")+COUNTIF(G37:G61,"GV2")+COUNTIF(G69:G93,"GV2") -> 0 | T25: =COUNTIF(G5:G29,"GV3")+COUNTIF(G37:G61,"GV3")+COUNTIF(G69:G93,"GV3") -> 1 | U25: =((C32+(R26+S26+T26)*0.5)) -> 1554.15 | AD25: =SUM(AE25:AF25) -> 0 | AE25: =SUM(AE22) -> 0 | AF25: =SUM(AP22) -> 0 | AG25: =SUM(AF22+AQ22) -> 0 | AH25: =AG22+AR22 -> 0 | AI25: =SUM(AE25:AH25) -> 0
A26: 22 | J26: =IF(G26="RSL","55","0") -> 0 | K26: =IF(G26="GVS","37.5",IF(G26="GVM","41.5",IF(G26="GVL","50",IF(G26="PCS","45.8",IF(G26="PCM","50",IF(G26="PCL","58.3","0")))))) -> 0 | R26: =R25*37.5 -> 0 | S26: =S25*41.5 -> 0 | T26: 100 | X26: Branch cards
A27: 23 | J27: =IF(G27="RSL","55","0") -> 0 | K27: =IF(G27="GVS","37.5",IF(G27="GVM","41.5",IF(G27="GVL","50",IF(G27="PCS","45.8",IF(G27="PCM","50",IF(G27="PCL","58.3","0")))))) -> 0 | R27: Expense | X27: 1 | Z27: -2745
A28: 24 | J28: =IF(G28="RSL","55","0") -> 0 | K28: =IF(G28="GVS","37.5",IF(G28="GVM","41.5",IF(G28="GVL","50",IF(G28="PCS","45.8",IF(G28="PCM","50",IF(G28="PCL","58.3","0")))))) -> 0 | X28: 2
A29: 25 | J29: =IF(G29="RSL","55","0") -> 0 | K29: =IF(G29="GVS","37.5",IF(G29="GVM","41.5",IF(G29="GVL","50",IF(G29="PCS","45.8",IF(G29="PCM","50",IF(G29="PCL","58.3","0")))))) -> 0 | X29: 3
A30: Page total | H30: =SUM(H5:H29) -> 20 | I30: =SUM(I5:I29) -> 980 | J30: =J5+J6+J7+J8+J9+J10+J11+J12+J13+J14+J15+J16+J18+J19+J17+J20+J22+J23+J21+J24+J25+J26+J27+J28+J29 -> 275 | K30: =K5+K6+K7+K8+K9+K10+K11+K12+K13+K14+K15+K16+K18+K19+K17+K20+K22+K23+K21+K24+K25+K26+K27+K28+K29 -> 229.15 | L30: =SUM(L5:L29) -> 0 | M30: =SUM(M5:M29) -> 0 | N30: CASH | O30: CARD | P30: GV | Q30: RSL | X30: 4
A31: Daily Total | H31: =H30+H62+H94 -> 20 | I31: =I30+I62+I94 -> 980 | J31: =J30+J62+J94 -> 275 | K31: =K30+K62+K94 -> 229.15 | L31: =L30+L62+L94 -> 0 | M31: =M30+M62+M94 -> 0 | N31: =COUNT(H5:H29,H37:H61,H69:H93) -> 2 | O31: =COUNT(I5:I29,I37:I61,I69:I93) -> 11 | P31: =COUNTIF(G5:G29,"G*")+COUNTIF(G37:G61,"G*")+COUNTIF(G69:G93,"G*")+COUNTIF(G5:G29,"P*")+COUNTIF(G37:G61,"P*")+COUNTIF(G69:G93,"P*") -> 4 | Q31: =COUNTIF(G5:G29,"RSL")+COUNTIF(G37:G61,"RSL")+COUNTIF(G69:G93,"RSL") -> 4 | R31: CASH CLOSING | S31: =H31+L31-U28-U29-U30 -> 20 | T31: =H31+I31+L31+M31 -> 1000 | X31: Subtotal | Z31: =SUM(Z27:Z30) -> -2745
A32: TOTAL SALES | C32: =H31+I31+J31+K31 -> 1504.15 | F32: No of Cars | H32: =COUNT(B5:B29,B37:B61,B69:B93) -> 20 | I32: Average | K32: =C32/H32 -> 75.2075 | N32: =H31/C32 -> 0.013296546 | O32: =I31/C32 -> 0.65153076 | P32: =K31/C32 -> 0.15234518 | Q32: =J31/C32 -> 0.18282751 | R32: CARD CLOSING | S32: =I31+M31 -> 980 | X32: B2 card | Z32: =I31 -> 980
A33: Daily Report | X33: Settlement | Z33: =SUM(Z31:Z32) -> -1765
A34: =A2 -> 29 - 4 - 2022 | H34: WEATHER | J34: =J2 -> SUNNY | L34: REPORT by | O34: =O2 -> HENDRA | R34: TOTAL STAFF | T34: =T2 -> 6
A36: No | B36: Docket No | C36: Reg No | D36: Mobile | E36: Gender | F36: TIME | G36: Service | H36: CASH | I36: CARD | J36: RSL | K36: GV | L36: GV CASH | M36: GV CARD | N36: O/Taker | O36: Comment | R36: NAME | S36: Time In | T36: Time out | U36: Total Hours
A37: =A29+1 -> 26 | J37: =IF(G37="RSL","55","0") -> 0 | K37: =IF(G37="GVS","37.5",IF(G37="GVM","41.5",IF(G37="GVL","50",IF(G37="PCS","45.8",IF(G37="PCM","50",IF(G37="PCL","58.3","0")))))) -> 0
A38: =A37+1 -> 27 | J38: =IF(G38="RSL","55","0") -> 0 | K38: =IF(G38="GVS","37.5",IF(G38="GVM","41.5",IF(G38="GVL","50",IF(G38="PCS","45.8",IF(G38="PCM","50",IF(G38="PCL","58.3","0")))))) -> 0
A39: =A38+1 -> 28 | J39: =IF(G39="RSL","55","0") -> 0 | K39: =IF(G39="GVS","37.5",IF(G39="GVM","41.5",IF(G39="GVL","50",IF(G39="PCS","45.8",IF(G39="PCM","50",IF(G39="PCL","58.3","0")))))) -> 0
A40: =A39+1 -> 29 | J40: =IF(G40="RSL","55","0") -> 0 | K40: =IF(G40="GVS","37.5",IF(G40="GVM","41.5",IF(G40="GVL","50",IF(G40="PCS","45.8",IF(G40="PCM","50",IF(G40="PCL","58.3","0")))))) -> 0
A41: =A40+1 -> 30 | J41: =IF(G41="RSL","55","0") -> 0 | K41: =IF(G41="GVS","37.5",IF(G41="GVM","41.5",IF(G41="GVL","50",IF(G41="PCS","45.8",IF(G41="PCM","50",IF(G41="PCL","58.3","0")))))) -> 0
A42: =A41+1 -> 31 | J42: =IF(G42="RSL","55","0") -> 0 | K42: =IF(G42="GVS","37.5",IF(G42="GVM","41.5",IF(G42="GVL","50",IF(G42="PCS","45.8",IF(G42="PCM","50",IF(G42="PCL","58.3","0")))))) -> 0
A43: =A42+1 -> 32 | J43: =IF(G43="RSL","55","0") -> 0 | K43: =IF(G43="GVS","37.5",IF(G43="GVM","41.5",IF(G43="GVL","50",IF(G43="PCS","45.8",IF(G43="PCM","50",IF(G43="PCL","58.3","0")))))) -> 0
A44: =A43+1 -> 33 | J44: =IF(G44="RSL","55","0") -> 0 | K44: =IF(G44="GVS","37.5",IF(G44="GVM","41.5",IF(G44="GVL","50",IF(G44="PCS","45.8",IF(G44="PCM","50",IF(G44="PCL","58.3","0")))))) -> 0
A45: =A44+1 -> 34 | J45: =IF(G45="RSL","55","0") -> 0 | K45: =IF(G45="GVS","37.5",IF(G45="GVM","41.5",IF(G45="GVL","50",IF(G45="PCS","45.8",IF(G45="PCM","50",IF(G45="PCL","58.3","0")))))) -> 0
A46: =A45+1 -> 35 | J46: =IF(G46="RSL","55","0") -> 0 | K46: =IF(G46="GVS","37.5",IF(G46="GVM","41.5",IF(G46="GVL","50",IF(G46="PCS","45.8",IF(G46="PCM","50",IF(G46="PCL","58.3","0")))))) -> 0
A47: =A46+1 -> 36 | J47: =IF(G47="RSL","55","0") -> 0 | K47: =IF(G47="GVS","37.5",IF(G47="GVM","41.5",IF(G47="GVL","50",IF(G47="PCS","45.8",IF(G47="PCM","50",IF(G47="PCL","58.3","0")))))) -> 0
A48: =A47+1 -> 37 | J48: =IF(G48="RSL","55","0") -> 0 | K48: =IF(G48="GVS","37.5",IF(G48="GVM","41.5",IF(G48="GVL","50",IF(G48="PCS","45.8",IF(G48="PCM","50",IF(G48="PCL","58.3","0")))))) -> 0
A49: =A48+1 -> 38 | J49: =IF(G49="RSL","55","0") -> 0 | K49: =IF(G49="GVS","37.5",IF(G49="GVM","41.5",IF(G49="GVL","50",IF(G49="PCS","45.8",IF(G49="PCM","50",IF(G49="PCL","58.3","0")))))) -> 0
... A61: =A60+1 -> 50 | J61: =IF(G61="RSL","55","0") -> 0 | K61: =IF(G61="GVS","37.5",IF(G61="GVM","41.5",IF(G61="GVL","50",IF(G61="PCS","45.8",IF(G61="PCM","50",IF(G61="PCL","58.3","0")))))) -> 0
A62: Page total | H62: =SUM(H37:H61) -> 0 | I62: =SUM(I37:I61) -> 0 | J62: =J61+J60+J59+J58+J57+J56+J55+J54+J53+J52+J51+J50+J49+J48+J47+J46+J45+J44+J43+J42+J41+J40+J39+J38+J37 -> 0 | K62: =K61+K60+K59+K58+K57+K56+K55+K54+K53+K52+K51+K50+K49+K48+K47+K46+K45+K44+K43+K42+K41+K40+K39+K38+K37 -> 0 | L62: =SUM(L37:L61) -> 0 | M62: =SUM(M37:M61) -> 0
R64: Page: 2
A65: Daily Report
A66: =A34 -> 29 - 4 - 2022 | H66: WEATHER | J66: =J34 -> SUNNY | L66: REPORT by | O66: =O34 -> HENDRA | R66: TOTAL STAFF | T66: =T34 -> 6
A68: No | B68: Docket No | C68: Reg No | D68: Mobile | E68: Gender | F68: TIME | G68: Service | H68: CASH | I68: CARD | J68: RSL | K68: GV | L68: GV CASH | M68: GV CARD | N68: O/Taker | O68: Comment | R68: NAME | S68: Time In | T68: Time out | U68: Total Hours
A69: =A61+1 -> 51 | J69: =IF(G69="RSL","55","0") -> 0 | K69: =IF(G69="GVS","37.5",IF(G69="GVM","41.5",IF(G69="GVL","50",IF(G69="PCS","45.8",IF(G69="PCM","50",IF(G69="PCL","58.3","0")))))) -> 0
A70: =A69+1 -> 52 | J70: =IF(G70="RSL","55","0") -> 0 | K70: =IF(G70="GVS","37.5",IF(G70="GVM","41.5",IF(G70="GVL","50",IF(G70="PCS","45.8",IF(G70="PCM","50",IF(G70="PCL","58.3","0")))))) -> 0
A71: =A70+1 -> 53 | J71: =IF(G71="RSL","55","0") -> 0 | K71: =IF(G71="GVS","37.5",IF(G71="GVM","41.5",IF(G71="GVL","50",IF(G71="PCS","45.8",IF(G71="PCM","50",IF(G71="PCL","58.3","0")))))) -> 0
A72: =A71+1 -> 54 | J72: =IF(G72="RSL","55","0") -> 0 | K72: =IF(G72="GVS","37.5",IF(G72="GVM","41.5",IF(G72="GVL","50",IF(G72="PCS","45.8",IF(G72="PCM","50",IF(G72="PCL","58.3","0")))))) -> 0
A73: =A72+1 -> 55 | J73: =IF(G73="RSL","55","0") -> 0 | K73: =IF(G73="GVS","37.5",IF(G73="GVM","41.5",IF(G73="GVL","50",IF(G73="PCS","45.8",IF(G73="PCM","50",IF(G73="PCL","58.3","0")))))) -> 0
A74: =A73+1 -> 56 | J74: =IF(G74="RSL","55","0") -> 0 | K74: =IF(G74="GVS","37.5",IF(G74="GVM","41.5",IF(G74="GVL","50",IF(G74="PCS","45.8",IF(G74="PCM","50",IF(G74="PCL","58.3","0")))))) -> 0
A75: =A74+1 -> 57 | J75: =IF(G75="RSL","55","0") -> 0 | K75: =IF(G75="GVS","37.5",IF(G75="GVM","41.5",IF(G75="GVL","50",IF(G75="PCS","45.8",IF(G75="PCM","50",IF(G75="PCL","58.3","0")))))) -> 0
A76: =A75+1 -> 58 | J76: =IF(G76="RSL","55","0") -> 0 | K76: =IF(G76="GVS","37.5",IF(G76="GVM","41.5",IF(G76="GVL","50",IF(G76="PCS","45.8",IF(G76="PCM","50",IF(G76="PCL","58.3","0")))))) -> 0
A77: =A76+1 -> 59 | J77: =IF(G77="RSL","55","0") -> 0 | K77: =IF(G77="GVS","37.5",IF(G77="GVM","41.5",IF(G77="GVL","50",IF(G77="PCS","45.8",IF(G77="PCM","50",IF(G77="PCL","58.3","0")))))) -> 0
A78: =A77+1 -> 60 | J78: =IF(G78="RSL","55","0") -> 0 | K78: =IF(G78="GVS","37.5",IF(G78="GVM","41.5",IF(G78="GVL","50",IF(G78="PCS","45.8",IF(G78="PCM","50",IF(G78="PCL","58.3","0")))))) -> 0
A79: =A78+1 -> 61 | J79: =IF(G79="RSL","55","0") -> 0 | K79: =IF(G79="GVS","37.5",IF(G79="GVM","41.5",IF(G79="GVL","50",IF(G79="PCS","45.8",IF(G79="PCM","50",IF(G79="PCL","58.3","0")))))) -> 0
A80: =A79+1 -> 62 | J80: =IF(G80="RSL","55","0") -> 0 | K80: =IF(G80="GVS","37.5",IF(G80="GVM","41.5",IF(G80="GVL","50",IF(G80="PCS","45.8",IF(G80="PCM","50",IF(G80="PCL","58.3","0")))))) -> 0
A81: =A80+1 -> 63 | J81: =IF(G81="RSL","55","0") -> 0 | K81: =IF(G81="GVS","37.5",IF(G81="GVM","41.5",IF(G81="GVL","50",IF(G81="PCS","45.8",IF(G81="PCM","50",IF(G81="PCL","58.3","0")))))) -> 0
... A93: =A92+1 -> 75 | J93: =IF(G93="RSL","55","0") -> 0 | K93: =IF(G93="GVS","37.5",IF(G93="GVM","41.5",IF(G93="GVL","50",IF(G93="PCS","45.8",IF(G93="PCM","50",IF(G93="PCL","58.3","0")))))) -> 0
A94: Page total | H94: =SUM(H69:H93) -> 0 | I94: =SUM(I69:I93) -> 0 | J94: =J93+J92+J91+J90+J89+J88+J87+J86+J85+J84+J83+J82+J81+J80+J79+J78+J77+J76+J75+J74+J73+J72+J71+J70+J69 -> 0 | K94: =K93+K92+K91+K90+K89+K88+K87+K86+K85+K84+K83+K82+K81+K80+K79+K78+K77+K76+K75+K74+K73+K72+K71+K70+K69 -> 0 | L94: =SUM(L69:L93) -> 0 | M94: =SUM(M69:M93) -> 0
R96: Page: 3

Sheet SAT
A1: B2 Daily Report
A2: 30-04-2022 | H2: WEATHER | J2: MIX | L2: REPORT BY | O2: JOHN | R2: TOTAL STAFF | T2: 7 | X2: Merchant machine usage at B2 | AA2: Settle amount | AI2: Merchant machine usage at GA | AL2: Settle amount
A4: No | B4: Docket No | C4: Reg No | D4: Mobile | E4: Gender | F4: TIME | G4: Service | H4: CASH | I4: CARD | J4: RSL | K4: GV | L4: GV CASH | M4: GV CARD | N4: O/Taker | O4: Comment | R4: NAME | S4: Time In | T4: Time out | U4: Total Hours | Z4: B2 machine | AA4: BLH machine | AB4: Wongo | AE4: B2 machine | AF4: BLH machine | AG4: Wongo | AK4: GA machine | AL4: BLH machine | AM4: Wongo | AP4: GA machine | AQ4: BLH machine | AR4: Wongo
A5: 1 | B5: 3168 | C5: DSK36Z | D5: 0450687838 | E5: M | F5: 800 | G5: RSL | J5: 110 | K5: =IF(G5="GVS","37.5",IF(G5="GVM","41.5",IF(G5="GVL","50",IF(G5="PCS","45.8",IF(G5="PCM","50",IF(G5="PCL","58.3","0")))))) -> 0 | N5: JUNIOR | O5: 202202025,28(X) | R5: JOHN | S5: 0.34375 | T5: 0.71875 | U5: =(T5-S5)*24 -> 9 | X5: NOV | Y5: 1 | AD5: 16 | AI5: NOV | AJ5: 1 | AO5: 16
A6: 2 | B6: 3169 | C6: EOJ30W | D6: 0418432402 | E6: F | F6: 800 | G6: RSL | J6: 110 | K6: =IF(G6="GVS","37.5",IF(G6="GVM","41.5",IF(G6="GVL","50",IF(G6="PCS","45.8",IF(G6="PCM","50",IF(G6="PCL","58.3","0")))))) -> 0 | N6: JUNIOR | O6: 202202051-52(X) | R6: JUNIOR | S6: 0.33333333 | T6: 0.70833333 | U6: =(T6-S6)*24 -> 9 | W6: M | Y6: 2 | AD6: 17 | AJ6: 2 | AO6: 17
A7: 3 | B7: 3170 | C7: DAE37Y | D7: 0425774597 | E7: F | F7: 820 | G7: H | I7: 100 | J7: =IF(G7="RSL","55","0") -> 0 | K7: =IF(G7="GVS","37.5",IF(G7="GVM","41.5",IF(G7="GVL","50",IF(G7="PCS","45.8",IF(G7="PCM","50",IF(G7="PCL","58.3","0")))))) -> 0 | N7: JUNIOR | R7: ARIANTO | S7: 0.39583333 | T7: 0.70833333 | U7: =(T7-S7)*24 -> 7.5 | W7: F | Y7: 3 | AD7: 18 | AJ7: 3 | AO7: 18
A8: 4 | B8: 3171 | C8: CSI78N | D8: 0421493870 | E8: F | F8: 845 | G8: D | I8: 55 | J8: =IF(G8="RSL","55","0") -> 0 | K8: =IF(G8="GVS","37.5",IF(G8="GVM","41.5",IF(G8="GVL","50",IF(G8="PCS","45.8",IF(G8="PCM","50",IF(G8="PCL","58.3","0")))))) -> 0 | N8: JOHN | R8: KUROSH | S8: 0.38541667 | T8: 0.71875 | U8: =(T8-S8)*24 -> 8 | Y8: 4 | AD8: 19 | AJ8: 4 | AO8: 19
A9: 5 | B9: 3172 | C9: PS699 | D9: 0412256630 | E9: M | F9: 915 | G9: PCL | J9: =IF(G9="RSL","55","0") -> 0 | K9: 79.1 | N9: JOHN | O9: 210760(3/6) | R9: KEVIN | S9: 0.375 | T9: 0.71875 | U9: =(T9-S9)*24 -> 8.25 | X9: EXCL RSL | Y9: 5 | AD9: 20 | AJ9: 5 | AO9: 20
A10: 6 | B10: 3173 | C10: CVL96X | D10: 0432358067 | E10: M | F10: 940 | G10: X | I10: 95 | J10: =IF(G10="RSL","55","0") -> 0 | K10: =IF(G10="GVS","37.5",IF(G10="GVM","41.5",IF(G10="GVL","50",IF(G10="PCS","45.8",IF(G10="PCM","50",IF(G10="PCL","58.3","0")))))) -> 0 | N10: JOHN | R10: BIVEK | S10: 0.41666667 | T10: 0.70833333 | U10: =(T10-S10)*24 -> 7 | Y10: 6 | AD10: 21 | AJ10: 6 | AO10: 21
A11: 7 | B11: 3174 | C11: CDR89K | D11: 0457336600 | E11: F | F11: 950 | G11: D/ST | H11: 180 | J11: =IF(G11="RSL","55","0") -> 0 | K11: =IF(G11="GVS","37.5",IF(G11="GVM","41.5",IF(G11="GVL","50",IF(G11="PCS","45.8",IF(G11="PCM","50",IF(G11="PCL","58.3","0")))))) -> 0 | N11: JOHN | R11: AMAN | S11: 0.41666667 | T11: 0.70833333 | U11: =(T11-S11)*24 -> 7 | Y11: 7 | AD11: 22 | AJ11: 7 | AO11: 22
A12: 8 | B12: 3175 | C12: ENT76V | D12: 0416037429 | E12: F | F12: 1015 | G12: RSL | J12: =IF(G12="RSL","55","0") -> 55 | K12: =IF(G12="GVS","37.5",IF(G12="GVM","41.5",IF(G12="GVL","50",IF(G12="PCS","45.8",IF(G12="PCM","50",IF(G12="PCL","58.3","0")))))) -> 0 | N12: JOHN | O12: 202202080(D) | U12: =(T12-S12)*24 -> 0 | Y12: 8 | AD12: 23 | AJ12: 8 | AO12: 23
A13: 9 | B13: 3176 | C13: BUN414 | D13: 0401704348 | E13: F | F13: 1045 | G13: X/ST | I13: 280 | J13: =IF(G13="RSL","55","0") -> 0 | K13: =IF(G13="GVS","37.5",IF(G13="GVM","41.5",IF(G13="GVL","50",IF(G13="PCS","45.8",IF(G13="PCM","50",IF(G13="PCL","58.3","0")))))) -> 0 | N13: JOHN | U13: =(T13-S13)*24 -> 0 | Y13: 9 | AD13: 24 | AJ13: 9 | AO13: 24
A14: 10 | B14: 3177 | C14: EJV52G | D14: 0409203967 | E14: F | F14: 1110 | G14: X | I14: 150 | J14: =IF(G14="RSL","55","0") -> 0 | K14: =IF(G14="GVS","37.5",IF(G14="GVM","41.5",IF(G14="GVL","50",IF(G14="PCS","45.8",IF(G14="PCM","50",IF(G14="PCL","58.3","0")))))) -> 0 | N14: JOHN | U14: =(T14-S14)*24 -> 0 | Y14: 10 | AD14: 25 | AJ14: 10 | AO14: 25
A15: 11 | B15: 3178 | C15: B4TM4N | D15: 0480144733 | E15: M | F15: 1110 | G15: D/DT | I15: 250 | J15: =IF(G15="RSL","55","0") -> 0 | K15: =IF(G15="GVS","37.5",IF(G15="GVM","41.5",IF(G15="GVL","50",IF(G15="PCS","45.8",IF(G15="PCM","50",IF(G15="PCL","58.3","0")))))) -> 0 | N15: JOHN | U15: =(T15-S15)*24 -> 0 | Y15: 11 | AD15: 26 | AJ15: 11 | AO15: 26
A16: 12 | B16: 3179 | C16: F9F | D16: 0488891999 | E16: M | F16: 1110 | G16: PCL | J16: =IF(G16="RSL","55","0") -> 0 | K16: 79.1 | M16: 475 | N16: JOHN | O16: 22023(1/6) | R16: =H32/U16 -> 0.32286996 | S16: =H32/(U16-U5) -> 0.38502674 | T16: =C32/U16 -> 51.447534 | U16: =SUM(U5:U15) -> 55.75 | Y16: 12 | AD16: 27 | AJ16: 12 | AO16: 27
A17: 13 | B17: 3180 | C17: WWQ862 | D17: 0488134554 | E17: M | F17: 1230 | G17: X/ID | H17: 300 | J17: =IF(G17="RSL","55","0") -> 0 | K17: =IF(G17="GVS","37.5",IF(G17="GVM","41.5",IF(G17="GVL","50",IF(G17="PCS","45.8",IF(G17="PCM","50",IF(G17="PCL","58.3","0")))))) -> 0 | N17: JOHN | R17: Cars/T Hr ① | S17: Cars/T Hr ② | T17: Sales/T Hr | U17: Total Hours | Y17: 13 | AD17: 28 | AJ17: 13 | AO17: 28
A18: 14 | B18: 3181 | C18: DFG91A | D18: 0450603998 | E18: F | F18: 1315 | G18: RSL | H18: 25 | J18: =IF(G18="RSL","55","0") -> 55 | K18: =IF(G18="GVS","37.5",IF(G18="GVM","41.5",IF(G18="GVL","50",IF(G18="PCS","45.8",IF(G18="PCM","50",IF(G18="PCL","58.3","0")))))) -> 0 | N18: JOHN | O18: 202202021(D) | R18: ITEM | S18: QTY | T18: AMT | U18: RMKS | Y18: 14 | AD18: 29 | AJ18: 14 | AO18: 29
A19: 15 | B19: 3182 | C19: BTT79A | D19: 0404861166 | E19: M | F19: 1250 | G19: D/ST | I19: 180 | J19: =IF(G19="RSL","55","0") -> 0 | K19: =IF(G19="GVS","37.5",IF(G19="GVM","41.5",IF(G19="GVL","50",IF(G19="PCS","45.8",IF(G19="PCM","50",IF(G19="PCL","58.3","0")))))) -> 0 | N19: JOHN | R19: GV | S19: =COUNT(L5:M29,L37:M61,L69:M93) -> 1 | T19: =SUM(L5:M29,L37:M61,L69:M93) -> 475 | Y19: 15 | AD19: 30 | AJ19: 15 | AO19: 30
A20: 16 | B20: 3183 | C20: ENZ25L | D20: 0408244442 | E20: M | F20: 1500 | G20: X/ST | I20: 320 | J20: =IF(G20="RSL","55","0") -> 0 | K20: =IF(G20="GVS","37.5",IF(G20="GVM","41.5",IF(G20="GVL","50",IF(G20="PCS","45.8",IF(G20="PCM","50",IF(G20="PCL","58.3","0")))))) -> 0 | N20: JOHN | O20: TAX | AD20: 31 | AO20: 31
A21: 17 | B21: 3184 | C21: EHW53Q | D21: 0404066946 | E21: F | F21: 1505 | G21: D | I21: 55 | J21: =IF(G21="RSL","55","0") -> 0 | K21: =IF(G21="GVS","37.5",IF(G21="GVM","41.5",IF(G21="GVL","50",IF(G21="PCS","45.8",IF(G21="PCM","50",IF(G21="PCL","58.3","0")))))) -> 0 | N21: JOHN
A22: 18 | B22: 3185 | C22: EMG49M | D22: 0401588000 | E22: M | F22: 1545 | G22: X/ID | I22: 390 | J22: =IF(G22="RSL","55","0") -> 0 | K22: =IF(G22="GVS","37.5",IF(G22="GVM","41.5",IF(G22="GVL","50",IF(G22="PCS","45.8",IF(G22="PCM","50",IF(G22="PCL","58.3","0")))))) -> 0 | N22: JOHN | AD22: Total | AE22: =SUM(Z5:Z19,AE5:AE20) -> 0 | AF22: =SUM(AA5:AA19,AF5:AF20,) -> 0 | AG22: =SUM(AB5:AB19,AG5:AG20) -> 0 | AO22: Total | AP22: =SUM(AK5:AK19,AP5:AP20) -> 0 | AQ22: =SUM(AL5:AL19,AQ5:AQ20,) -> 0 | AR22: =SUM(AM5:AM19,AR5:AR20) -> 0
A23: 19 | J23: =IF(G23="RSL","55","0") -> 0 | K23: =IF(G23="GVS","37.5",IF(G23="GVM","41.5",IF(G23="GVL","50",IF(G23="PCS","45.8",IF(G23="PCM","50",IF(G23="PCL","58.3","0")))))) -> 0
A24: 20 | J24: =IF(G24="RSL","55","0") -> 0 | K24: =IF(G24="GVS","37.5",IF(G24="GVM","41.5",IF(G24="GVL","50",IF(G24="PCS","45.8",IF(G24="PCM","50",IF(G24="PCL","58.3","0")))))) -> 0 | R24: SMALL | S24: MEDIUM | T24: LARGE | U24: TOTAL | AD24: B2/GA TOTAL | AE24: B2 machine | AF24: GA machine | AG24: BLH machine | AH24: Wongo machine | AI24: Sub total
A25: 21 | J25: =IF(G25="RSL","55","0") -> 0 | K25: =IF(G25="GVS","37.5",IF(G25="GVM","41.5",IF(G25="GVL","50",IF(G25="PCS","45.8",IF(G25="PCM","50",IF(G25="PCL","58.3","0")))))) -> 0 | R25: =COUNTIF(G5:G29,"GV1")+COUNTIF(G37:G61,"GV1")+COUNTIF(G69:G93,"GV1") -> 0 | S25: =COUNTIF(G5:G29,"GV2")+COUNTIF(G37:G61,"GV2")+COUNTIF(G69:G93,"GV2") -> 0 | T25: =COUNTIF(G5:G29,"GV3")+COUNTIF(G37:G61,"GV3")+COUNTIF(G69:G93,"GV3") -> 0 | U25: =((C32+(R26+S26+T26)*0.5)) -> 2868.2 | AD25: =SUM(AE25:AF25) -> 0 | AE25: =SUM(AE22) -> 0 | AF25: =SUM(AP22) -> 0 | AG25: =SUM(AF22+AQ22) -> 0 | AH25: =AG22+AR22 -> 0 | AI25: =SUM(AE25:AH25) -> 0
A26: 22 | J26: =IF(G26="RSL","55","0") -> 0 | K26: =IF(G26="GVS","37.5",IF(G26="GVM","41.5",IF(G26="GVL","50",IF(G26="PCS","45.8",IF(G26="PCM","50",IF(G26="PCL","58.3","0")))))) -> 0 | R26: =R25*37.5 -> 0 | S26: =S25*41.5 -> 0 | T26: =T25*50 -> 0 | X26: Branch cards
A27: 23 | J27: =IF(G27="RSL","55","0") -> 0 | K27: =IF(G27="GVS","37.5",IF(G27="GVM","41.5",IF(G27="GVL","50",IF(G27="PCS","45.8",IF(G27="PCM","50",IF(G27="PCL","58.3","0")))))) -> 0 | R27: Expense | X27: 1 | Z27: -2745
A28: 24 | J28: =IF(G28="RSL","55","0") -> 0 | K28: =IF(G28="GVS","37.5",IF(G28="GVM","41.5",IF(G28="GVL","50",IF(G28="PCS","45.8",IF(G28="PCM","50",IF(G28="PCL","58.3","0")))))) -> 0 | X28: 2
A29: 25 | J29: =IF(G29="RSL","55","0") -> 0 | K29: =IF(G29="GVS","37.5",IF(G29="GVM","41.5",IF(G29="GVL","50",IF(G29="PCS","45.8",IF(G29="PCM","50",IF(G29="PCL","58.3","0")))))) -> 0 | X29: 3
A30: Page total | H30: =SUM(H5:H29) -> 505 | I30: =SUM(I5:I29) -> 1875 | J30: =J5+J6+J7+J8+J9+J10+J11+J12+J13+J14+J15+J16+J18+J19+J17+J20+J22+J23+J21+J24+J25+J26+J27+J28+J29 -> 330 | K30: =K5+K6+K7+K8+K9+K10+K11+K12+K13+K14+K15+K16+K18+K19+K17+K20+K22+K23+K21+K24+K25+K26+K27+K28+K29 -> 158.2 | L30: =SUM(L5:L29) -> 0 | M30: =SUM(M5:M29) -> 475 | N30: CASH | O30: CARD | P30: GV | Q30: RSL | X30: 4
A31: Daily Total | H31: =H30+H62+H94 -> 505 | I31: =I30+I62+I94 -> 1875 | J31: =J30+J62+J94 -> 330 | K31: =K30+K62+K94 -> 158.2 | L31: =L30+L62+L94 -> 0 | M31: =M30+M62+M94 -> 475 | N31: =COUNT(H5:H29,H37:H61,H69:H93) -> 3 | O31: =COUNT(I5:I29,I37:I61,I69:I93) -> 10 | P31: =COUNTIF(G5:G29,"G*")+COUNTIF(G37:G61,"G*")+COUNTIF(G69:G93,"G*")+COUNTIF(G5:G29,"P*")+COUNTIF(G37:G61,"P*")+COUNTIF(G69:G93,"P*") -> 2 | Q31: =COUNTIF(G5:G29,"RSL")+COUNTIF(G37:G61,"RSL")+COUNTIF(G69:G93,"RSL") -> 4 | R31: CASH CLOSING | S31: =H31+L31-U28-U29-U30 -> 505 | T31: =H31+I31+L31+M31 -> 2855 | X31: Subtotal | Z31: =SUM(Z27:Z30) -> -2745
A32: TOTAL SALES | C32: =H31+I31+J31+K31 -> 2868.2 | F32: No of Cars | H32: =COUNT(B5:B29,B37:B61,B69:B93) -> 18 | I32: Average | K32: =C32/H32 -> 159.34444 | N32: =H31/C32 -> 0.17606861 | O32: =I31/C32 -> 0.6537201 | P32: =K31/C32 -> 0.055156544 | Q32: =J31/C32 -> 0.11505474 | R32: CARD CLOSING | S32: =I31+M31 -> 2350 | X32: B2 card | Z32: =I31 -> 1875
A33: Daily Report | X33: Settlement | Z33: =SUM(Z31:Z32) -> -870
A34: =A2 -> 30-04-2022 | H34: WEATHER | J34: =J2 -> MIX | L34: REPORT by | O34: =O2 -> JOHN | R34: TOTAL STAFF | T34: =T2 -> 7
A36: No | B36: Docket No | C36: Reg No | D36: Mobile | E36: Gender | F36: TIME | G36: Service | H36: CASH | I36: CARD | J36: RSL | K36: GV | L36: GV CASH | M36: GV CARD | N36: O/Taker | O36: Comment | R36: NAME | S36: Time In | T36: Time out | U36: Total Hours
A37: =A29+1 -> 26 | J37: =IF(G37="RSL","55","0") -> 0 | K37: =IF(G37="GVS","37.5",IF(G37="GVM","41.5",IF(G37="GVL","50",IF(G37="PCS","45.8",IF(G37="PCM","50",IF(G37="PCL","58.3","0")))))) -> 0
A38: =A37+1 -> 27 | J38: =IF(G38="RSL","55","0") -> 0 | K38: =IF(G38="GVS","37.5",IF(G38="GVM","41.5",IF(G38="GVL","50",IF(G38="PCS","45.8",IF(G38="PCM","50",IF(G38="PCL","58.3","0")))))) -> 0
A39: =A38+1 -> 28 | J39: =IF(G39="RSL","55","0") -> 0 | K39: =IF(G39="GVS","37.5",IF(G39="GVM","41.5",IF(G39="GVL","50",IF(G39="PCS","45.8",IF(G39="PCM","50",IF(G39="PCL","58.3","0")))))) -> 0
A40: =A39+1 -> 29 | J40: =IF(G40="RSL","55","0") -> 0 | K40: =IF(G40="GVS","37.5",IF(G40="GVM","41.5",IF(G40="GVL","50",IF(G40="PCS","45.8",IF(G40="PCM","50",IF(G40="PCL","58.3","0")))))) -> 0
A41: =A40+1 -> 30 | J41: =IF(G41="RSL","55","0") -> 0 | K41: =IF(G41="GVS","37.5",IF(G41="GVM","41.5",IF(G41="GVL","50",IF(G41="PCS","45.8",IF(G41="PCM","50",IF(G41="PCL","58.3","0")))))) -> 0
A42: =A41+1 -> 31 | J42: =IF(G42="RSL","55","0") -> 0 | K42: =IF(G42="GVS","37.5",IF(G42="GVM","41.5",IF(G42="GVL","50",IF(G42="PCS","45.8",IF(G42="PCM","50",IF(G42="PCL","58.3","0")))))) -> 0
A43: =A42+1 -> 32 | J43: =IF(G43="RSL","55","0") -> 0 | K43: =IF(G43="GVS","37.5",IF(G43="GVM","41.5",IF(G43="GVL","50",IF(G43="PCS","45.8",IF(G43="PCM","50",IF(G43="PCL","58.3","0")))))) -> 0
A44: =A43+1 -> 33 | J44: =IF(G44="RSL","55","0") -> 0 | K44: =IF(G44="GVS","37.5",IF(G44="GVM","41.5",IF(G44="GVL","50",IF(G44="PCS","45.8",IF(G44="PCM","50",IF(G44="PCL","58.3","0")))))) -> 0
A45: =A44+1 -> 34 | J45: =IF(G45="RSL","55","0") -> 0 | K45: =IF(G45="GVS","37.5",IF(G45="GVM","41.5",IF(G45="GVL","50",IF(G45="PCS","45.8",IF(G45="PCM","50",IF(G45="PCL","58.3","0")))))) -> 0
A46: =A45+1 -> 35 | J46: =IF(G46="RSL","55","0") -> 0 | K46: =IF(G46="GVS","37.5",IF(G46="GVM","41.5",IF(G46="GVL","50",IF(G46="PCS","45.8",IF(G46="PCM","50",IF(G46="PCL","58.3","0")))))) -> 0
A47: =A46+1 -> 36 | J47: =IF(G47="RSL","55","0") -> 0 | K47: =IF(G47="GVS","37.5",IF(G47="GVM","41.5",IF(G47="GVL","50",IF(G47="PCS","45.8",IF(G47="PCM","50",IF(G47="PCL","58.3","0")))))) -> 0
A48: =A47+1 -> 37 | J48: =IF(G48="RSL","55","0") -> 0 | K48: =IF(G48="GVS","37.5",IF(G48="GVM","41.5",IF(G48="GVL","50",IF(G48="PCS","45.8",IF(G48="PCM","50",IF(G48="PCL","58.3","0")))))) -> 0
A49: =A48+1 -> 38 | J49: =IF(G49="RSL","55","0") -> 0 | K49: =IF(G49="GVS","37.5",IF(G49="GVM","41.5",IF(G49="GVL","50",IF(G49="PCS","45.8",IF(G49="PCM","50",IF(G49="PCL","58.3","0")))))) -> 0
... A61: =A60+1 -> 50 | J61: =IF(G61="RSL","55","0") -> 0 | K61: =IF(G61="GVS","37.5",IF(G61="GVM","41.5",IF(G61="GVL","50",IF(G61="PCS","45.8",IF(G61="PCM","50",IF(G61="PCL","58.3","0")))))) -> 0
A62: Page total | H62: =SUM(H37:H61) -> 0 | I62: =SUM(I37:I61) -> 0 | J62: =J61+J60+J59+J58+J57+J56+J55+J54+J53+J52+J51+J50+J49+J48+J47+J46+J45+J44+J43+J42+J41+J40+J39+J38+J37 -> 0 | K62: =K61+K60+K59+K58+K57+K56+K55+K54+K53+K52+K51+K50+K49+K48+K47+K46+K45+K44+K43+K42+K41+K40+K39+K38+K37 -> 0 | L62: =SUM(L37:L61) -> 0 | M62: =SUM(M37:M61) -> 0
R64: Page: 2
A65: Daily Report
A66: =A34 -> 30-04-2022 | H66: WEATHER | J66: =J34 -> MIX | L66: REPORT by | O66: =O34 -> JOHN | R66: TOTAL STAFF | T66: =T34 -> 7
A68: No | B68: Docket No | C68: Reg No | D68: Mobile | E68: Gender | F68: TIME | G68: Service | H68: CASH | I68: CARD | J68: RSL | K68: GV | L68: GV CASH | M68: GV CARD | N68: O/Taker | O68: Comment | R68: NAME | S68: Time In | T68: Time out | U68: Total Hours
A69: =A61+1 -> 51 | J69: =IF(G69="RSL","55","0") -> 0 | K69: =IF(G69="GVS","37.5",IF(G69="GVM","41.5",IF(G69="GVL","50",IF(G69="PCS","45.8",IF(G69="PCM","50",IF(G69="PCL","58.3","0")))))) -> 0
A70: =A69+1 -> 52 | J70: =IF(G70="RSL","55","0") -> 0 | K70: =IF(G70="GVS","37.5",IF(G70="GVM","41.5",IF(G70="GVL","50",IF(G70="PCS","45.8",IF(G70="PCM","50",IF(G70="PCL","58.3","0")))))) -> 0
A71: =A70+1 -> 53 | J71: =IF(G71="RSL","55","0") -> 0 | K71: =IF(G71="GVS","37.5",IF(G71="GVM","41.5",IF(G71="GVL","50",IF(G71="PCS","45.8",IF(G71="PCM","50",IF(G71="PCL","58.3","0")))))) -> 0
A72: =A71+1 -> 54 | J72: =IF(G72="RSL","55","0") -> 0 | K72: =IF(G72="GVS","37.5",IF(G72="GVM","41.5",IF(G72="GVL","50",IF(G72="PCS","45.8",IF(G72="PCM","50",IF(G72="PCL","58.3","0")))))) -> 0
A73: =A72+1 -> 55 | J73: =IF(G73="RSL","55","0") -> 0 | K73: =IF(G73="GVS","37.5",IF(G73="GVM","41.5",IF(G73="GVL","50",IF(G73="PCS","45.8",IF(G73="PCM","50",IF(G73="PCL","58.3","0")))))) -> 0
A74: =A73+1 -> 56 | J74: =IF(G74="RSL","55","0") -> 0 | K74: =IF(G74="GVS","37.5",IF(G74="GVM","41.5",IF(G74="GVL","50",IF(G74="PCS","45.8",IF(G74="PCM","50",IF(G74="PCL","58.3","0")))))) -> 0
A75: =A74+1 -> 57 | J75: =IF(G75="RSL","55","0") -> 0 | K75: =IF(G75="GVS","37.5",IF(G75="GVM","41.5",IF(G75="GVL","50",IF(G75="PCS","45.8",IF(G75="PCM","50",IF(G75="PCL","58.3","0")))))) -> 0
A76: =A75+1 -> 58 | J76: =IF(G76="RSL","55","0") -> 0 | K76: =IF(G76="GVS","37.5",IF(G76="GVM","41.5",IF(G76="GVL","50",IF(G76="PCS","45.8",IF(G76="PCM","50",IF(G76="PCL","58.3","0")))))) -> 0
A77: =A76+1 -> 59 | J77: =IF(G77="RSL","55","0") -> 0 | K77: =IF(G77="GVS","37.5",IF(G77="GVM","41.5",IF(G77="GVL","50",IF(G77="PCS","45.8",IF(G77="PCM","50",IF(G77="PCL","58.3","0")))))) -> 0
A78: =A77+1 -> 60 | J78: =IF(G78="RSL","55","0") -> 0 | K78: =IF(G78="GVS","37.5",IF(G78="GVM","41.5",IF(G78="GVL","50",IF(G78="PCS","45.8",IF(G78="PCM","50",IF(G78="PCL","58.3","0")))))) -> 0
A79: =A78+1 -> 61 | J79: =IF(G79="RSL","55","0") -> 0 | K79: =IF(G79="GVS","37.5",IF(G79="GVM","41.5",IF(G79="GVL","50",IF(G79="PCS","45.8",IF(G79="PCM","50",IF(G79="PCL","58.3","0")))))) -> 0
A80: =A79+1 -> 62 | J80: =IF(G80="RSL","55","0") -> 0 | K80: =IF(G80="GVS","37.5",IF(G80="GVM","41.5",IF(G80="GVL","50",IF(G80="PCS","45.8",IF(G80="PCM","50",IF(G80="PCL","58.3","0")))))) -> 0
A81: =A80+1 -> 63 | J81: =IF(G81="RSL","55","0") -> 0 | K81: =IF(G81="GVS","37.5",IF(G81="GVM","41.5",IF(G81="GVL","50",IF(G81="PCS","45.8",IF(G81="PCM","50",IF(G81="PCL","58.3","0")))))) -> 0
... A93: =A92+1 -> 75 | J93: =IF(G93="RSL","55","0") -> 0 | K93: =IF(G93="GVS","37.5",IF(G93="GVM","41.5",IF(G93="GVL","50",IF(G93="PCS","45.8",IF(G93="PCM","50",IF(G93="PCL","58.3","0")))))) -> 0
A94: Page total | H94: =SUM(H69:H93) -> 0 | I94: =SUM(I69:I93) -> 0 | J94: =J93+J92+J91+J90+J89+J88+J87+J86+J85+J84+J83+J82+J81+J80+J79+J78+J77+J76+J75+J74+J73+J72+J71+J70+J69 -> 0 | K94: =K93+K92+K91+K90+K89+K88+K87+K86+K85+K84+K83+K82+K81+K80+K79+K78+K77+K76+K75+K74+K73+K72+K71+K70+K69 -> 0 | L94: =SUM(L69:L93) -> 0 | M94: =SUM(M69:M93) -> 0
R96: Page: 3

Sheet SUN
A1: B2 Daily Report
A2: 01-05-2022 | H2: WEATHER | J2: SUNNY | L2: REPORT BY | O2: JOHN | R2: TOTAL STAFF | T2: 8 | X2: Merchant machine usage at B2 | AA2: Settle amount | AI2: Merchant machine usage at GA | AL2: Settle amount
A4: No | B4: Docket No | C4: Reg No | D4: Mobile | E4: Gender | F4: TIME | G4: Service | H4: CASH | I4: CARD | J4: RSL | K4: GV | L4: GV CASH | M4: GV CARD | N4: O/Taker | O4: Comment | R4: NAME | S4: Time In | T4: Time out | U4: Total Hours | Z4: B2 machine | AA4: BLH machine | AB4: Wongo | AE4: B2 machine | AF4: BLH machine | AG4: Wongo | AK4: GA machine | AL4: BLH machine | AM4: Wongo | AP4: GA machine | AQ4: BLH machine | AR4: Wongo
A5: 1 | B5: 3186 | C5: CNK76Q | D5: 0405223889 | E5: F | F5: 800 | G5: D/ST | I5: 100 | J5: =IF(G5="RSL","55","0") -> 0 | K5: =IF(G5="GVS","37.5",IF(G5="GVM","41.5",IF(G5="GVL","50",IF(G5="PCS","45.8",IF(G5="PCM","50",IF(G5="PCL","58.3","0")))))) -> 0 | N5: JOHN | R5: JOHN | S5: 0.34375 | T5: 0.72916667 | U5: =(T5-S5)*24 -> 9.25 | X5: NOV | Y5: 1 | AD5: 16 | AI5: NOV | AJ5: 1 | AO5: 16
A6: 2 | B6: 3187 | E6: M | F6: 800 | G6: RSL | H6: 20 | J6: =IF(G6="RSL","55","0") -> 55 | K6: =IF(G6="GVS","37.5",IF(G6="GVM","41.5",IF(G6="GVL","50",IF(G6="PCS","45.8",IF(G6="PCM","50",IF(G6="PCL","58.3","0")))))) -> 0 | N6: JOHN | O6: 202202070(D) | R6: JUNIOR | S6: 0.33333333 | T6: 0.72916667 | U6: =(T6-S6)*24 -> 9.5 | W6: M | Y6: 2 | AD6: 17 | AJ6: 2 | AO6: 17
A7: 3 | B7: 3188 | C7: NBS90G | D7: 0411439769 | E7: M | F7: 850 | G7: H | I7: 90 | J7: =IF(G7="RSL","55","0") -> 0 | K7: =IF(G7="GVS","37.5",IF(G7="GVM","41.5",IF(G7="GVL","50",IF(G7="PCS","45.8",IF(G7="PCM","50",IF(G7="PCL","58.3","0")))))) -> 0 | N7: JOHN | R7: KUROSH | S7: 0.36458333 | T7: 0.72916667 | U7: =(T7-S7)*24 -> 8.75 | W7: F | Y7: 3 | AD7: 18 | AJ7: 3 | AO7: 18
A8: 4 | B8: 3189 | C8: BZ63SD | D8: 0401093636 | E8: F | F8: 855 | G8: X | I8: 70 | J8: =IF(G8="RSL","55","0") -> 0 | K8: =IF(G8="GVS","37.5",IF(G8="GVM","41.5",IF(G8="GVL","50",IF(G8="PCS","45.8",IF(G8="PCM","50",IF(G8="PCL","58.3","0")))))) -> 0 | N8: JOHN | R8: KEVIN | S8: 0.36458333 | T8: 0.72916667 | U8: =(T8-S8)*24 -> 8.75 | Y8: 4 | AD8: 19 | AJ8: 4 | AO8: 19
A9: 5 | B9: 3190 | C9: 98CHUD | D9: 0403552027 | E9: M | F9: 930 | G9: H | I9: 120 | J9: =IF(G9="RSL","55","0") -> 0 | K9: =IF(G9="GVS","37.5",IF(G9="GVM","41.5",IF(G9="GVL","50",IF(G9="PCS","45.8",IF(G9="PCM","50",IF(G9="PCL","58.3","0")))))) -> 0 | N9: ```````` | R9: BIVEK | S9: 0.375 | T9: 0.70833333 | U9: =(T9-S9)*24 -> 8 | X9: EXCL RSL | Y9: 5 | AD9: 20 | AJ9: 5 | AO9: 20
A10: 6 | B10: 3191 | C10: NBZ30L | D10: 0419413007 | E10: M | F10: 945 | G10: H | I10: 120 | J10: =IF(G10="RSL","55","0") -> 0 | K10: =IF(G10="GVS","37.5",IF(G10="GVM","41.5",IF(G10="GVL","50",IF(G10="PCS","45.8",IF(G10="PCM","50",IF(G10="PCL","58.3","0")))))) -> 0 | N10: JOHN | R10: AMAN | S10: 0.375 | T10: 0.70833333 | U10: =(T10-S10)*24 -> 8 | Y10: 6 | AD10: 21 | AJ10: 6 | AO10: 21
A11: 7 | B11: 3192 | C11: DYB76T | D11: 0416130135 | E11: M | F11: 100 | G11: D | I11: 55 | J11: =IF(G11="RSL","55","0") -> 0 | K11: =IF(G11="GVS","37.5",IF(G11="GVM","41.5",IF(G11="GVL","50",IF(G11="PCS","45.8",IF(G11="PCM","50",IF(G11="PCL","58.3","0")))))) -> 0 | N11: JOHN | R11: SOVID | S11: 0.4375 | T11: 0.66666667 | U11: =(T11-S11)*24 -> 5.5 | Y11: 7 | AD11: 22 | AJ11: 7 | AO11: 22
A12: 8 | B12: 3193 | C12: ERN94L | D12: 0412384897 | E12: M | F12: 1020 | G12: X | I12: 85 | J12: =IF(G12="RSL","55","0") -> 0 | K12: =IF(G12="GVS","37.5",IF(G12="GVM","41.5",IF(G12="GVL","50",IF(G12="PCS","45.8",IF(G12="PCM","50",IF(G12="PCL","58.3","0")))))) -> 0 | N12: JOHN | R12: PRAGATI | S12: 0.39583333 | T12: 0.70833333 | U12: =(T12-S12)*24 -> 7.5 | Y12: 8 | AD12: 23 | AJ12: 8 | AO12: 23
A13: 9 | B13: 3194 | C13: SZ520 | D13: 0488027777 | E13: M | F13: 1025 | G13: X | H13: 95 | J13: =IF(G13="RSL","55","0") -> 0 | K13: =IF(G13="GVS","37.5",IF(G13="GVM","41.5",IF(G13="GVL","50",IF(G13="PCS","45.8",IF(G13="PCM","50",IF(G13="PCL","58.3","0")))))) -> 0 | N13: JOHN | U13: =(T13-S13)*24 -> 0 | Y13: 9 | AD13: 24 | AJ13: 9 | AO13: 24
A14: 10 | B14: 3195 | C14: CSV94D | D14: 0402213906 | E14: M | F14: 1030 | G14: X | H14: 75 | J14: =IF(G14="RSL","55","0") -> 0 | K14: =IF(G14="GVS","37.5",IF(G14="GVM","41.5",IF(G14="GVL","50",IF(G14="PCS","45.8",IF(G14="PCM","50",IF(G14="PCL","58.3","0")))))) -> 0 | N14: JOHN | U14: =(T14-S14)*24 -> 0 | Y14: 10 | AD14: 25 | AJ14: 10 | AO14: 25
A15: 11 | B15: 3196 | C15: DDQ71L | D15: 0400116979 | E15: F | F15: 1050 | G15: X | I15: 95 | J15: =IF(G15="RSL","55","0") -> 0 | K15: =IF(G15="GVS","37.5",IF(G15="GVM","41.5",IF(G15="GVL","50",IF(G15="PCS","45.8",IF(G15="PCM","50",IF(G15="PCL","58.3","0")))))) -> 0 | N15: JOHN | U15: =(T15-S15)*24 -> 0 | Y15: 11 | AD15: 26 | AJ15: 11 | AO15: 26
A16: 12 | B16: 3197 | C16: DVN59W | D16: 0410760274 | E16: F | F16: 1115 | G16: X | I16: 75 | J16: =IF(G16="RSL","55","0") -> 0 | K16: =IF(G16="GVS","37.5",IF(G16="GVM","41.5",IF(G16="GVL","50",IF(G16="PCS","45.8",IF(G16="PCM","50",IF(G16="PCL","58.3","0")))))) -> 0 | N16: JOHN | R16: =H32/U16 -> 0.47509579 | S16: =H32/(U16-U5) -> 0.55357143 | T16: =C32/U16 -> 51.684291 | U16: =SUM(U5:U15) -> 65.25 | Y16: 12 | AD16: 27 | AJ16: 12 | AO16: 27
A17: 13 | B17: 3198 | C17: LI6888 | D17: 0433286059 | E17: F | F17: 1115 | G17: H | I17: 140 | J17: =IF(G17="RSL","55","0") -> 0 | K17: =IF(G17="GVS","37.5",IF(G17="GVM","41.5",IF(G17="GVL","50",IF(G17="PCS","45.8",IF(G17="PCM","50",IF(G17="PCL","58.3","0")))))) -> 0 | N17: JOHN | R17: Cars/T Hr ① | S17: Cars/T Hr ② | T17: Sales/T Hr | U17: Total Hours | Y17: 13 | AD17: 28 | AJ17: 13 | AO17: 28
A18: 14 | B18: 3199 | C18: EAK86U | D18: 0411577377 | E18: F | F18: 1140 | G18: X | I18: 95 | J18: =IF(G18="RSL","55","0") -> 0 | K18: =IF(G18="GVS","37.5",IF(G18="GVM","41.5",IF(G18="GVL","50",IF(G18="PCS","45.8",IF(G18="PCM","50",IF(G18="PCL","58.3","0")))))) -> 0 | N18: JOHN | R18: ITEM | S18: QTY | T18: AMT | U18: RMKS | Y18: 14 | AD18: 29 | AJ18: 14 | AO18: 29
A19: 15 | B19: 3200 | C19: DZV96M | D19: 0400707487 | E19: F | F19: 1150 | G19: X | I19: 125 | J19: =IF(G19="RSL","55","0") -> 0 | K19: =IF(G19="GVS","37.5",IF(G19="GVM","41.5",IF(G19="GVL","50",IF(G19="PCS","45.8",IF(G19="PCM","50",IF(G19="PCL","58.3","0")))))) -> 0 | N19: JOHN | R19: GV | S19: =COUNT(L5:M29,L37:M61,L69:M93) -> 0 | T19: =SUM(L5:M29,L37:M61,L69:M93) -> 0 | Y19: 15 | AD19: 30 | AJ19: 15 | AO19: 30
A20: 16 | B20: 3201 | C20: CXO57N | D20: 0409782436 | E20: F | F20: 1150 | G20: X | I20: 75 | J20: =IF(G20="RSL","55","0") -> 0 | K20: =IF(G20="GVS","37.5",IF(G20="GVM","41.5",IF(G20="GVL","50",IF(G20="PCS","45.8",IF(G20="PCM","50",IF(G20="PCL","58.3","0")))))) -> 0 | N20: JOHN | AD20: 31 | AO20: 31
A21: 17 | B21: 3202 | C21: YHN50Q | D21: 0456656661 | E21: F | F21: 1200 | G21: W/O | I21: 50 | J21: =IF(G21="RSL","55","0") -> 0 | K21: =IF(G21="GVS","37.5",IF(G21="GVM","41.5",IF(G21="GVL","50",IF(G21="PCS","45.8",IF(G21="PCM","50",IF(G21="PCL","58.3","0")))))) -> 0 | N21: JOHN
A22: 18 | B22: 3203 | C22: DAJ78X | D22: 0434668842 | E22: M | F22: 1200 | G22: H | I22: 150 | J22: =IF(G22="RSL","55","0") -> 0 | K22: =IF(G22="GVS","37.5",IF(G22="GVM","41.5",IF(G22="GVL","50",IF(G22="PCS","45.8",IF(G22="PCM","50",IF(G22="PCL","58.3","0")))))) -> 0 | N22: JOHN | AD22: Total | AE22: =SUM(Z5:Z19,AE5:AE20) -> 0 | AF22: =SUM(AA5:AA19,AF5:AF20,) -> 0 | AG22: =SUM(AB5:AB19,AG5:AG20) -> 0 | AO22: Total | AP22: =SUM(AK5:AK19,AP5:AP20) -> 0 | AQ22: =SUM(AL5:AL19,AQ5:AQ20,) -> 0 | AR22: =SUM(AM5:AM19,AR5:AR20) -> 0
A23: 19 | B23: 3204 | C23: EBG85Z | D23: 0478659198 | E23: M | F23: 1210 | G23: F/D | I23: 480 | J23: =IF(G23="RSL","55","0") -> 0 | K23: =IF(G23="GVS","37.5",IF(G23="GVM","41.5",IF(G23="GVL","50",IF(G23="PCS","45.8",IF(G23="PCM","50",IF(G23="PCL","58.3","0")))))) -> 0 | N23: JOHN
A24: 20 | B24: 3205 | C24: CAD07Y | D24: 0416135899 | E24: F | F24: 1245 | G24: X | I24: 80 | J24: =IF(G24="RSL","55","0") -> 0 | K24: =IF(G24="GVS","37.5",IF(G24="GVM","41.5",IF(G24="GVL","50",IF(G24="PCS","45.8",IF(G24="PCM","50",IF(G24="PCL","58.3","0")))))) -> 0 | N24: JOHN | R24: SMALL | S24: MEDIUM | T24: LARGE | U24: TOTAL | AD24: B2/GA TOTAL | AE24: B2 machine | AF24: GA machine | AG24: BLH machine | AH24: Wongo machine | AI24: Sub total
A25: 21 | B25: 3206 | C25: OOSHA | D25: 0450928298 | E25: F | F25: 1330 | G25: D | I25: 55 | J25: =IF(G25="RSL","55","0") -> 0 | K25: =IF(G25="GVS","37.5",IF(G25="GVM","41.5",IF(G25="GVL","50",IF(G25="PCS","45.8",IF(G25="PCM","50",IF(G25="PCL","58.3","0")))))) -> 0 | N25: JOHN | R25: =COUNTIF(G5:G29,"GV1")+COUNTIF(G37:G61,"GV1")+COUNTIF(G69:G93,"GV1") -> 0 | S25: =COUNTIF(G5:G29,"GV2")+COUNTIF(G37:G61,"GV2")+COUNTIF(G69:G93,"GV2") -> 0 | T25: =COUNTIF(G5:G29,"GV3")+COUNTIF(G37:G61,"GV3")+COUNTIF(G69:G93,"GV3") -> 0 | U25: =((C32+(R26+S26+T26)*0.5)) -> 3372.4 | AD25: =SUM(AE25:AF25) -> 0 | AE25: =SUM(AE22) -> 0 | AF25: =SUM(AP22) -> 0 | AG25: =SUM(AF22+AQ22) -> 0 | AH25: =AG22+AR22 -> 0 | AI25: =SUM(AE25:AH25) -> 0
A26: 22 | B26: 3207 | C26: PF888 | D26: 0400167996 | E26: F | F26: 1330 | G26: PCS | J26: =IF(G26="RSL","55","0") -> 0 | K26: 58.3 | N26: JOHN | O26: 22004(3/6) | R26: =R25*37.5 -> 0 | S26: =S25*41.5 -> 0 | T26: =T25*50 -> 0 | X26: Branch cards
A27: 23 | B27: 3208 | C27: EF076 | D27: 0418913425 | E27: M | F27: 1345 | G27: H | I27: 150 | J27: =IF(G27="RSL","55","0") -> 0 | K27: =IF(G27="GVS","37.5",IF(G27="GVM","41.5",IF(G27="GVL","50",IF(G27="PCS","45.8",IF(G27="PCM","50",IF(G27="PCL","58.3","0")))))) -> 0 | N27: JOHN | R27: Expense | X27: 1 | Z27: -2745
A28: 24 | B28: 3209 | C28: DD33BW | D28: 0480261729 | E28: M | F28: 1410 | G28: IN/ID | I28: 300 | J28: =IF(G28="RSL","55","0") -> 0 | K28: =IF(G28="GVS","37.5",IF(G28="GVM","41.5",IF(G28="GVL","50",IF(G28="PCS","45.8",IF(G28="PCM","50",IF(G28="PCL","58.3","0")))))) -> 0 | N28: JOHN | X28: 2
A29: 25 | B29: 3210 | C29: CHUYI | D29: 0401573480 | E29: F | F29: 1415 | G29: X | I29: 95 | J29: =IF(G29="RSL","55","0") -> 0 | K29: =IF(G29="GVS","37.5",IF(G29="GVM","41.5",IF(G29="GVL","50",IF(G29="PCS","45.8",IF(G29="PCM","50",IF(G29="PCL","58.3","0")))))) -> 0 | N29: JOHN | X29: 3
A30: Page total | H30: =SUM(H5:H29) -> 190 | I30: =SUM(I5:I29) -> 2605 | J30: =J5+J6+J7+J8+J9+J10+J11+J12+J13+J14+J15+J16+J18+J19+J17+J20+J22+J23+J21+J24+J25+J26+J27+J28+J29 -> 55 | K30: =K5+K6+K7+K8+K9+K10+K11+K12+K13+K14+K15+K16+K18+K19+K17+K20+K22+K23+K21+K24+K25+K26+K27+K28+K29 -> 58.3 | L30: =SUM(L5:L29) -> 0 | M30: =SUM(M5:M29) -> 0 | N30: CASH | O30: CARD | P30: GV | Q30: RSL | X30: 4
A31: Daily Total | H31: =H30+H62+H94 -> 190 | I31: =I30+I62+I94 -> 2990 | J31: =J30+J62+J94 -> 55 | K31: =K30+K62+K94 -> 137.4 | L31: =L30+L62+L94 -> 0 | M31: =M30+M62+M94 -> 0 | N31: =COUNT(H5:H29,H37:H61,H69:H93) -> 3 | O31: =COUNT(I5:I29,I37:I61,I69:I93) -> 26 | P31: =COUNTIF(G5:G29,"G*")+COUNTIF(G37:G61,"G*")+COUNTIF(G69:G93,"G*")+COUNTIF(G5:G29,"P*")+COUNTIF(G37:G61,"P*")+COUNTIF(G69:G93,"P*") -> 2 | Q31: =COUNTIF(G5:G29,"RSL")+COUNTIF(G37:G61,"RSL")+COUNTIF(G69:G93,"RSL") -> 1 | R31: CASH CLOSING | S31: =H31+L31-U28-U29-U30 -> 190 | T31: =H31+I31+L31+M31 -> 3180 | X31: Subtotal | Z31: =SUM(Z27:Z30) -> -2745
A32: TOTAL SALES | C32: =H31+I31+J31+K31 -> 3372.4 | F32: No of Cars | H32: =COUNT(B5:B29,B37:B61,B69:B93) -> 31 | I32: Average | K32: =C32/H32 -> 108.7871 | N32: =H31/C32 -> 0.056339699 | O32: =I31/C32 -> 0.88660894 | P32: =K31/C32 -> 0.040742498 | Q32: =J31/C32 -> 0.01630886 | R32: CARD CLOSING | S32: =I31+M31 -> 2990 | X32: B2 card | Z32: =I31 -> 2990
A33: Daily Report | X33: Settlement | Z33: =SUM(Z31:Z32) -> 245
A34: =A2 -> 01-05-2022 | H34: WEATHER | J34: =J2 -> SUNNY | L34: REPORT by | O34: =O2 -> JOHN | R34: TOTAL STAFF | T34: =T2 -> 8
A36: No | B36: Docket No | C36: Reg No | D36: Mobile | E36: Gender | F36: TIME | G36: Service | H36: CASH | I36: CARD | J36: RSL | K36: GV | L36: GV CASH | M36: GV CARD | N36: O/Taker | O36: Comment | R36: NAME | S36: Time In | T36: Time out | U36: Total Hours
A37: =A29+1 -> 26 | B37: 3211 | C37: CZN61D | D37: 0410255587 | E37: M | F37: 1415 | G37: X | I37: 75 | J37: =IF(G37="RSL","55","0") -> 0 | K37: =IF(G37="GVS","37.5",IF(G37="GVM","41.5",IF(G37="GVL","50",IF(G37="PCS","45.8",IF(G37="PCM","50",IF(G37="PCL","58.3","0")))))) -> 0 | N37: JOHN
A38: =A37+1 -> 27 | B38: 3212 | C38: DVA51P | D38: 0400447345 | E38: F | F38: 1430 | G38: D | I38: 75 | J38: =IF(G38="RSL","55","0") -> 0 | K38: =IF(G38="GVS","37.5",IF(G38="GVM","41.5",IF(G38="GVL","50",IF(G38="PCS","45.8",IF(G38="PCM","50",IF(G38="PCL","58.3","0")))))) -> 0 | N38: JOHN
A39: =A38+1 -> 28 | B39: 3213 | C39: EOA01Y | D39: 0416270608 | E39: F | F39: 1430 | G39: X | I39: 75 | J39: =IF(G39="RSL","55","0") -> 0 | K39: =IF(G39="GVS","37.5",IF(G39="GVM","41.5",IF(G39="GVL","50",IF(G39="PCS","45.8",IF(G39="PCM","50",IF(G39="PCL","58.3","0")))))) -> 0 | N39: JOHN
A40: =A39+1 -> 29 | B40: 3214 | C40: NSZ8S9 | D40: 0422028291 | E40: F | F40: 1515 | G40: PCL | J40: =IF(G40="RSL","55","0") -> 0 | K40: 79.1 | N40: JOHN | O40: 21048(4/6)
A41: =A40+1 -> 30 | B41: 3215 | C41: DFR03K | D41: 0450959723 | E41: M | F41: 1525 | G41: X | I41: 75 | J41: =IF(G41="RSL","55","0") -> 0 | K41: =IF(G41="GVS","37.5",IF(G41="GVM","41.5",IF(G41="GVL","50",IF(G41="PCS","45.8",IF(G41="PCM","50",IF(G41="PCL","58.3","0")))))) -> 0 | N41: JOHN
A42: =A41+1 -> 31 | B42: 3216 | C42: DMW26A | D42: 0412921206 | E42: M | F42: 1550 | G42: X | I42: 85 | J42: =IF(G42="RSL","55","0") -> 0 | K42: =IF(G42="GVS","37.5",IF(G42="GVM","41.5",IF(G42="GVL","50",IF(G42="PCS","45.8",IF(G42="PCM","50",IF(G42="PCL","58.3","0")))))) -> 0 | N42: JOHN | O42: TAX
A43: =A42+1 -> 32 | J43: =IF(G43="RSL","55","0") -> 0 | K43: =IF(G43="GVS","37.5",IF(G43="GVM","41.5",IF(G43="GVL","50",IF(G43="PCS","45.8",IF(G43="PCM","50",IF(G43="PCL","58.3","0")))))) -> 0
A44: =A43+1 -> 33 | J44: =IF(G44="RSL","55","0") -> 0 | K44: =IF(G44="GVS","37.5",IF(G44="GVM","41.5",IF(G44="GVL","50",IF(G44="PCS","45.8",IF(G44="PCM","50",IF(G44="PCL","58.3","0")))))) -> 0
A45: =A44+1 -> 34 | J45: =IF(G45="RSL","55","0") -> 0 | K45: =IF(G45="GVS","37.5",IF(G45="GVM","41.5",IF(G45="GVL","50",IF(G45="PCS","45.8",IF(G45="PCM","50",IF(G45="PCL","58.3","0")))))) -> 0
A46: =A45+1 -> 35 | J46: =IF(G46="RSL","55","0") -> 0 | K46: =IF(G46="GVS","37.5",IF(G46="GVM","41.5",IF(G46="GVL","50",IF(G46="PCS","45.8",IF(G46="PCM","50",IF(G46="PCL","58.3","0")))))) -> 0
A47: =A46+1 -> 36 | J47: =IF(G47="RSL","55","0") -> 0 | K47: =IF(G47="GVS","37.5",IF(G47="GVM","41.5",IF(G47="GVL","50",IF(G47="PCS","45.8",IF(G47="PCM","50",IF(G47="PCL","58.3","0")))))) -> 0
A48: =A47+1 -> 37 | J48: =IF(G48="RSL","55","0") -> 0 | K48: =IF(G48="GVS","37.5",IF(G48="GVM","41.5",IF(G48="GVL","50",IF(G48="PCS","45.8",IF(G48="PCM","50",IF(G48="PCL","58.3","0")))))) -> 0
A49: =A48+1 -> 38 | J49: =IF(G49="RSL","55","0") -> 0 | K49: =IF(G49="GVS","37.5",IF(G49="GVM","41.5",IF(G49="GVL","50",IF(G49="PCS","45.8",IF(G49="PCM","50",IF(G49="PCL","58.3","0")))))) -> 0
A50: =A49+1 -> 39 | J50: =IF(G50="RSL","55","0") -> 0 | K50: =IF(G50="GVS","37.5",IF(G50="GVM","41.5",IF(G50="GVL","50",IF(G50="PCS","45.8",IF(G50="PCM","50",IF(G50="PCL","58.3","0")))))) -> 0
A51: =A50+1 -> 40 | J51: =IF(G51="RSL","55","0") -> 0 | K51: =IF(G51="GVS","37.5",IF(G51="GVM","41.5",IF(G51="GVL","50",IF(G51="PCS","45.8",IF(G51="PCM","50",IF(G51="PCL","58.3","0")))))) -> 0
A52: =A51+1 -> 41 | J52: =IF(G52="RSL","55","0") -> 0 | K52: =IF(G52="GVS","37.5",IF(G52="GVM","41.5",IF(G52="GVL","50",IF(G52="PCS","45.8",IF(G52="PCM","50",IF(G52="PCL","58.3","0")))))) -> 0
A53: =A52+1 -> 42 | J53: =IF(G53="RSL","55","0") -> 0 | K53: =IF(G53="GVS","37.5",IF(G53="GVM","41.5",IF(G53="GVL","50",IF(G53="PCS","45.8",IF(G53="PCM","50",IF(G53="PCL","58.3","0")))))) -> 0
A54: =A53+1 -> 43 | J54: =IF(G54="RSL","55","0") -> 0 | K54: =IF(G54="GVS","37.5",IF(G54="GVM","41.5",IF(G54="GVL","50",IF(G54="PCS","45.8",IF(G54="PCM","50",IF(G54="PCL","58.3","0")))))) -> 0
... A61: =A60+1 -> 50 | J61: =IF(G61="RSL","55","0") -> 0 | K61: =IF(G61="GVS","37.5",IF(G61="GVM","41.5",IF(G61="GVL","50",IF(G61="PCS","45.8",IF(G61="PCM","50",IF(G61="PCL","58.3","0")))))) -> 0
A62: Page total | H62: =SUM(H37:H61) -> 0 | I62: =SUM(I37:I61) -> 385 | J62: =J61+J60+J59+J58+J57+J56+J55+J54+J53+J52+J51+J50+J49+J48+J47+J46+J45+J44+J43+J42+J41+J40+J39+J38+J37 -> 0 | K62: =K61+K60+K59+K58+K57+K56+K55+K54+K53+K52+K51+K50+K49+K48+K47+K46+K45+K44+K43+K42+K41+K40+K39+K38+K37 -> 79.1 | L62: =SUM(L37:L61) -> 0 | M62: =SUM(M37:M61) -> 0
R64: Page: 2
A65: Daily Report
A66: =A34 -> 01-05-2022 | H66: WEATHER | J66: =J34 -> SUNNY | L66: REPORT by | O66: =O34 -> JOHN | R66: TOTAL STAFF | T66: =T34 -> 8
A68: No | B68: Docket No | C68: Reg No | D68: Mobile | E68: Gender | F68: TIME | G68: Service | H68: CASH | I68: CARD | J68: RSL | K68: GV | L68: GV CASH | M68: GV CARD | N68: O/Taker | O68: Comment | R68: NAME | S68: Time In | T68: Time out | U68: Total Hours
A69: =A61+1 -> 51 | J69: =IF(G69="RSL","55","0") -> 0 | K69: =IF(G69="GVS","37.5",IF(G69="GVM","41.5",IF(G69="GVL","50",IF(G69="PCS","45.8",IF(G69="PCM","50",IF(G69="PCL","58.3","0")))))) -> 0
A70: =A69+1 -> 52 | J70: =IF(G70="RSL","55","0") -> 0 | K70: =IF(G70="GVS","37.5",IF(G70="GVM","41.5",IF(G70="GVL","50",IF(G70="PCS","45.8",IF(G70="PCM","50",IF(G70="PCL","58.3","0")))))) -> 0
A71: =A70+1 -> 53 | J71: =IF(G71="RSL","55","0") -> 0 | K71: =IF(G71="GVS","37.5",IF(G71="GVM","41.5",IF(G71="GVL","50",IF(G71="PCS","45.8",IF(G71="PCM","50",IF(G71="PCL","58.3","0")))))) -> 0
A72: =A71+1 -> 54 | J72: =IF(G72="RSL","55","0") -> 0 | K72: =IF(G72="GVS","37.5",IF(G72="GVM","41.5",IF(G72="GVL","50",IF(G72="PCS","45.8",IF(G72="PCM","50",IF(G72="PCL","58.3","0")))))) -> 0
A73: =A72+1 -> 55 | J73: =IF(G73="RSL","55","0") -> 0 | K73: =IF(G73="GVS","37.5",IF(G73="GVM","41.5",IF(G73="GVL","50",IF(G73="PCS","45.8",IF(G73="PCM","50",IF(G73="PCL","58.3","0")))))) -> 0
A74: =A73+1 -> 56 | J74: =IF(G74="RSL","55","0") -> 0 | K74: =IF(G74="GVS","37.5",IF(G74="GVM","41.5",IF(G74="GVL","50",IF(G74="PCS","45.8",IF(G74="PCM","50",IF(G74="PCL","58.3","0")))))) -> 0
A75: =A74+1 -> 57 | J75: =IF(G75="RSL","55","0") -> 0 | K75: =IF(G75="GVS","37.5",IF(G75="GVM","41.5",IF(G75="GVL","50",IF(G75="PCS","45.8",IF(G75="PCM","50",IF(G75="PCL","58.3","0")))))) -> 0
A76: =A75+1 -> 58 | J76: =IF(G76="RSL","55","0") -> 0 | K76: =IF(G76="GVS","37.5",IF(G76="GVM","41.5",IF(G76="GVL","50",IF(G76="PCS","45.8",IF(G76="PCM","50",IF(G76="PCL","58.3","0")))))) -> 0
A77: =A76+1 -> 59 | J77: =IF(G77="RSL","55","0") -> 0 | K77: =IF(G77="GVS","37.5",IF(G77="GVM","41.5",IF(G77="GVL","50",IF(G77="PCS","45.8",IF(G77="PCM","50",IF(G77="PCL","58.3","0")))))) -> 0
A78: =A77+1 -> 60 | J78: =IF(G78="RSL","55","0") -> 0 | K78: =IF(G78="GVS","37.5",IF(G78="GVM","41.5",IF(G78="GVL","50",IF(G78="PCS","45.8",IF(G78="PCM","50",IF(G78="PCL","58.3","0")))))) -> 0
A79: =A78+1 -> 61 | J79: =IF(G79="RSL","55","0") -> 0 | K79: =IF(G79="GVS","37.5",IF(G79="GVM","41.5",IF(G79="GVL","50",IF(G79="PCS","45.8",IF(G79="PCM","50",IF(G79="PCL","58.3","0")))))) -> 0
A80: =A79+1 -> 62 | J80: =IF(G80="RSL","55","0") -> 0 | K80: =IF(G80="GVS","37.5",IF(G80="GVM","41.5",IF(G80="GVL","50",IF(G80="PCS","45.8",IF(G80="PCM","50",IF(G80="PCL","58.3","0")))))) -> 0
A81: =A80+1 -> 63 | J81: =IF(G81="RSL","55","0") -> 0 | K81: =IF(G81="GVS","37.5",IF(G81="GVM","41.5",IF(G81="GVL","50",IF(G81="PCS","45.8",IF(G81="PCM","50",IF(G81="PCL","58.3","0")))))) -> 0
... A93: =A92+1 -> 75 | J93: =IF(G93="RSL","55","0") -> 0 | K93: =IF(G93="GVS","37.5",IF(G93="GVM","41.5",IF(G93="GVL","50",IF(G93="PCS","45.8",IF(G93="PCM","50",IF(G93="PCL","58.3","0")))))) -> 0
A94: Page total | H94: =SUM(H69:H93) -> 0 | I94: =SUM(I69:I93) -> 0 | J94: =J93+J92+J91+J90+J89+J88+J87+J86+J85+J84+J83+J82+J81+J80+J79+J78+J77+J76+J75+J74+J73+J72+J71+J70+J69 -> 0 | K94: =K93+K92+K91+K90+K89+K88+K87+K86+K85+K84+K83+K82+K81+K80+K79+K78+K77+K76+K75+K74+K73+K72+K71+K70+K69 -> 0 | L94: =SUM(L69:L93) -> 0 | M94: =SUM(M69:M93) -> 0
R96: Page: 3

Sheet WEEKLY TOTAL
E1: CARS | H1: AMOUNT | L1: PERCENTAGE | Q1: TOTAL CARS | V1: TOTAL AMOUNT | AA1: AVERAGE
A2: MON | B2: Cash | E2: =MON!N31 -> 1 | H2: =MON!S31 -> 200 | L2: =MON!N32 -> 0.1659751 | Q2: =SUM(E2:G5) -> 10 | V2: =SUM(H2,H3,H5) -> 1205 | AA2: =V2/Q2 -> 120.5
B3: Card | E3: =MON!O31 -> 8 | H3: =MON!S32 -> 1005 | L3: =MON!O32 -> 0.8340249
B4: GV | E4: =MON!P31 -> 1 | H4: =MON!K31 -> 0 | L4: =MON!P32 -> 0
B5: RSL | E5: =MON!Q31 -> 0 | H5: =MON!J31 -> 0 | L5: =MON!Q32 -> 0
B6: hrs | E6: =MON!U16 -> 23.25 | H6: no. staff | L6: =MON!T2 -> 4
A7: TUE | B7: Cash | E7: =TUE!N31 -> 2 | H7: =TUE!S31 -> 150 | L7: =TUE!N32 -> 0.11531986 | Q7: =SUM(E7:G10) -> 14 | V7: =SUM(H7,H8,H10) -> 980 | AA7: =V7/Q7 -> 70
B8: Card | E8: =TUE!O31 -> 7 | H8: =TUE!S32 -> 775 | L8: =TUE!O32 -> 0.59581927
B9: GV | E9: =TUE!P31 -> 4 | H9: =TUE!K31 -> 320.73 | L9: =TUE!P32 -> 0.24657692
B10: RSL | E10: =TUE!Q31 -> 1 | H10: =TUE!J31 -> 55 | L10: =TUE!Q32 -> 0.042283948
B11: hrs | E11: =TUE!U16 -> 31 | H11: no. staff | L11: =TUE!T2 -> 4
A12: WED | B12: Cash | E12: =WED!N31 -> 7 | H12: =WED!S31 -> 695 | L12: =WED!N32 -> 0.53293459 | Q12: =SUM(E12:G15) -> 17 | V12: =SUM(H12,H13,H15) -> 1200 | AA12: =V12/Q12 -> 70.588235
B13: Card | E13: =WED!O31 -> 4 | H13: =WED!S32 -> 395 | L13: =WED!O32 -> 0.30289088
B14: GV | E14: =WED!P31 -> 4 | H14: =WED!K31 -> 104.1 | L14: =WED!P32 -> 0.079825167
B15: RSL | E15: =WED!Q31 -> 2 | H15: =WED!J31 -> 110 | L15: =WED!Q32 -> 0.08434936
B16: hrs | E16: =WED!U16 -> 40.5 | H16: no. staff | L16: =WED!T2 -> 6
A17: THU | B17: Cash | E17: =THU!N31 -> 3 | H17: =THU!S31 -> 805 | L17: =THU!N32 -> 0.41417839 | Q17: =SUM(E17:G20) -> 11 | V17: =SUM(H17,H18,H20) -> 1705 | AA17: =V17/Q17 -> 155
B18: Card | E18: =THU!O31 -> 5 | H18: =THU!S32 -> 845 | L18: =THU!O32 -> 0.35638605
B19: GV | E19: =THU!P31 -> 2 | H19: =THU!K31 -> 183.2 | L19: =THU!P32 -> 0.17645926
B20: RSL | E20: =THU!Q31 -> 1 | H20: =THU!J31 -> 55 | L20: =THU!Q32 -> 0.052976305
B21: hrs | E21: =THU!U16 -> 40.5 | H21: no. staff | L21: =THU!T2 -> 6
A22: FR I | B22: Cash | E22: =FRI!N31 -> 2 | H22: =FRI!S31 -> 20 | L22: =FRI!N32 -> 0.013296546 | Q22: =SUM(E22:G25) -> 21 | V22: =SUM(H22,H23,H25) -> 1275 | AA22: =V22/Q22 -> 60.714286
B23: Card | E23: =FRI!O31 -> 11 | H23: =FRI!S32 -> 980 | L23: =FRI!O32 -> 0.65153076
B24: GV | E24: =FRI!P31 -> 4 | H24: =FRI!K31 -> 229.15 | L24: =FRI!P32 -> 0.15234518
B25: RSL | E25: =FRI!Q31 -> 4 | H25: =FRI!J31 -> 275 | L25: =FRI!Q32 -> 0.18282751
B26: hrs | E26: =FRI!U16 -> 48.25 | H26: no. staff | L26: =FRI!T2 -> 6
A27: SAT | B27: Cash | E27: =SAT!N31 -> 3 | H27: =SAT!S31 -> 505 | L27: =SAT!N32 -> 0.17606861 | Q27: =SUM(E27:G30) -> 19 | V27: =SUM(H27,H28,H30) -> 3185 | AA27: =V27/Q27 -> 167.63158
B28: Card | E28: =SAT!O31 -> 10 | H28: =SAT!S32 -> 2350 | L28: =SAT!O32 -> 0.6537201
B29: GV | E29: =SAT!P31 -> 2 | H29: =SAT!K31 -> 158.2 | L29: =SAT!P32 -> 0.055156544
B30: RSL | E30: =SAT!Q31 -> 4 | H30: =SAT!J31 -> 330 | L30: =SAT!Q32 -> 0.11505474
B31: hrs | E31: =SAT!U16 -> 55.75 | H31: no. staff | L31: =SAT!T2 -> 7
A32: SUN | B32: Cash | E32: =SUN!N31 -> 3 | H32: =SUN!S31 -> 190 | L32: =SUN!N32 -> 0.056339699 | Q32: =SUM(E32:G35) -> 32 | V32: =SUM(H32,H33,H35) -> 3235 | AA32: =V32/Q32 -> 101.09375
B33: Card | E33: =SUN!O31 -> 26 | H33: =SUN!S32 -> 2990 | L33: =SUN!O32 -> 0.88660894
B34: GV | E34: =SUN!P31 -> 2 | H34: =SUN!K31 -> 137.4 | L34: =SUN!P32 -> 0.040742498
B35: RSL | E35: =SUN!Q31 -> 1 | H35: =SUN!J31 -> 55 | L35: =SUN!Q32 -> 0.01630886
B36: hrs | E36: =SUN!U16 -> 65.25 | H36: no. staff | L36: =SUN!T2 -> 8
A37: TOTAL CARS | E37: TOTAL SALES | K37: AVERAGE | O37: RSL | T37: GV | Y37: GV SOLD
A39: =SUM(Q2:U35) -> 124 | E39: =SUM(V2:Z35) -> 12785 | K39: =E39/A39 -> 103.10484 | O39: =SUM(MON:SUN!Q31) -> 13 | T39: =SUM(MON:SUN!P31) -> 19 | Y39: =SUM(MON:SUN!S19) -> 3
O41: =SUM(MON:SUN!J31) -> 880 | T41: =SUM(MON:SUN!K31) -> 1132.78 | Y41: =SUM(MON:SUN!T19) -> 1325
A43: TOTAL CASH | F43: TOTAL CARD | K43: TOTAL RSL | P43: TOTAL GV | U43: STAFF HRS | Z43: no. staff
A45: =SUM(H2,H7,H12,H17,H22,H27,H32) -> 2565 | F45: =SUM(,H3,H8,H13,H18,H23,H28,H33) -> 9340 | K45: =SUM(H5,H10,H15,H20,H25,H30,H35) -> 880 | P45: =SUM(H4,H9,H14,H19,H24,H29,H34) -> 1132.78 | U45: =SUM(E6,E11,E16,E21,E26,E31,E36) -> 304.5 | Z45: =SUM(L6,L11,L16,L21,L26,L31,L36) -> 41
A49: =A45/E39 -> 0.20062573 | F49: =F45/E39 -> 0.73054361 | K49: =K45/E39 -> 0.068830661 | P49: =P45/E39 -> 0.088602268 | U49: =U45/7 -> 43.5 | Z49: =U45/Z45 -> 7.4268293

Sheet Sheet1

Sheet Sheet2
