Workbook

Sheet MON
A1: B2 Daily Report
A2: 44991 | H2: WEATHER | J2: SUNNY | L2: REPORT BY | O2: HENDRA | R2: TOTAL STAFF | T2: 5 | X2: Merchant machine usage at B2 | AA2: Settle amount | AI2: Merchant machine usage at GA | AL2: Settle amount
A4: No | B4: Docket No | C4: Reg No | D4: Mobile | E4: Gender | F4: TIME | G4: Service | H4: CASH | I4: CARD | J4: RSL | K4: GV | L4: GV CASH | M4: GV CARD | N4: O/Taker | O4: Comment | R4: NAME | S4: Time In | T4: Time out | U4: Total Hours | Z4: B2 machine | AA4: BLH machine | AB4: Wongo | AE4: B2 machine | AF4: BLH machine | AG4: Wongo | AK4: GA machine | AL4: BLH machine | AM4: Wongo | AP4: GA machine | AQ4: BLH machine | AR4: Wongo
A5: 1 | B5: 14125 | C5: KEN838 | D5: 0412038383 | E5: M | F5: 905 | G5: PCL | J5: =IF(G5="RSL","55","0") -> 0 | K5: 79 | N5: HENDRA | O5: 22012 (6/6) | R5: HENDRA | S5: 0.33333333 | T5: 0.70833333 | U5: =(T5-S5)*24 -> 9 | X5: NOV | Y5: 1 | AD5: 16 | AI5: NOV | AJ5: 1 | AO5: 16
A6: 2 | B6: 14126 | C6: ENA66S | D6: 0416951959 | E6: F | F6: 915 | G6: PCL | J6: =IF(G6="RSL","55","0") -> 0 | K6: 79 | M6: 475 | N6: HENDRA | O6: 23225 (1/6) | R6: SHIVAM | S6: 0.33333333 | T6: 0.70833333 | U6: =(T6-S6)*24 -> 9 | W6: M | Y6: 2 | AD6: 17 | AJ6: 2 | AO6: 17
A7: 3 | B7: 14127 | C7: EEY61G | D7: 0401995714 | E7: F | F7: 930 | G7: X | H7: 95 | J7: =IF(G7="RSL","55","0") -> 0 | K7: =IF(G7="GVS","37.5",IF(G7="GVM","41.5",IF(G7="GVL","50",IF(G7="PCS","45.8",IF(G7="PCM","50",IF(G7="PCL","58.3","0")))))) -> 0 | N7: HENDRA | R7: JAMES | S7: 0.35416667 | T7: 0.70833333 | U7: =(T7-S7)*24 -> 8.5 | W7: F | Y7: 3 | AD7: 18 | AJ7: 3 | AO7: 18
A8: 4 | B8: 14128 | C8: CN800 | D8: 0418882000 | E8: F | F8: 935 | G8: D | I8: 75 | J8: =IF(G8="RSL","55","0") -> 0 | K8: =IF(G8="GVS","37.5",IF(G8="GVM","41.5",IF(G8="GVL","50",IF(G8="PCS","45.8",IF(G8="PCM","50",IF(G8="PCL","58.3","0")))))) -> 0 | N8: HENDRA | R8: ARIANTO | S8: 0.375 | T8: 0.625 | U8: =(T8-S8)*24 -> 6 | Y8: 4 | AD8: 19 | AJ8: 4 | AO8: 19
A9: 5 | B9: 14129 | C9: JH2211 | D9: 0412771876 | E9: F | F9: 945 | G9: X | I9: 95 | J9: =IF(G9="RSL","55","0") -> 0 | K9: =IF(G9="GVS","37.5",IF(G9="GVM","41.5",IF(G9="GVL","50",IF(G9="PCS","45.8",IF(G9="PCM","50",IF(G9="PCL","58.3","0")))))) -> 0 | N9: HENDRA | R9: VINNY | S9: 0.45833333 | T9: 0.70833333 | U9: =(T9-S9)*24 -> 6 | X9: EXCL RSL | Y9: 5 | AD9: 20 | AJ9: 5 | AO9: 20
A10: 6 | B10: 14130 | C10: CE32DD | D10: 0416155783 | E10: F | F10: 1010 | G10: D | I10: 75 | J10: =IF(G10="RSL","55","0") -> 0 | K10: =IF(G10="GVS","37.5",IF(G10="GVM","41.5",IF(G10="GVL","50",IF(G10="PCS","45.8",IF(G10="PCM","50",IF(G10="PCL","58.3","0")))))) -> 0 | N10: SHIVAM | U10: =(T10-S10)*24 -> 0 | Y10: 6 | AD10: 21 | AJ10: 6 | AO10: 21
A11: 7 | B11: 14131 | C11: EVU18U | D11: 0499080777 | E11: F | F11: 1030 | G11: GV | J11: =IF(G11="RSL","55","0") -> 0 | K11: 0 | L11: 300 | N11: SHIVAM | O11: XD-50-176 TO 181 | U11: =(T11-S11)*24 -> 0 | Y11: 7 | AD11: 22 | AJ11: 7 | AO11: 22
A12: 8 | B12: 14132 | C12: EXD61Y | D12: 0407213067 | E12: F | F12: 1050 | G12: D | I12: 75 | J12: =IF(G12="RSL","55","0") -> 0 | K12: =IF(G12="GVS","37.5",IF(G12="GVM","41.5",IF(G12="GVL","50",IF(G12="PCS","45.8",IF(G12="PCM","50",IF(G12="PCL","58.3","0")))))) -> 0 | N12: SHIVAM | U12: =(T12-S12)*24 -> 0 | V12: + | Y12: 8 | AD12: 23 | AJ12: 8 | AO12: 23
A13: 9 | B13: 14133 | C13: DTY90V | D13: 0439592230 | E13: M | F13: 1100 | G13: H | I13: 100 | J13: =IF(G13="RSL","55","0") -> 0 | K13: =IF(G13="GVS","37.5",IF(G13="GVM","41.5",IF(G13="GVL","50",IF(G13="PCS","45.8",IF(G13="PCM","50",IF(G13="PCL","58.3","0")))))) -> 0 | N13: SHIVAM | U13: =(T13-S13)*24 -> 0 | Y13: 9 | AD13: 24 | AJ13: 9 | AO13: 24
A14: 10 | B14: 14134 | C14: NXQ74D | D14: 0408518552 | E14: F | F14: 1100 | G14: X | H14: 75 | J14: =IF(G14="RSL","55","0") -> 0 | K14: =IF(G14="GVS","37.5",IF(G14="GVM","41.5",IF(G14="GVL","50",IF(G14="PCS","45.8",IF(G14="PCM","50",IF(G14="PCL","58.3","0")))))) -> 0 | N14: SHIVAM | U14: =(T14-S14)*24 -> 0 | Y14: 10 | AD14: 25 | AJ14: 10 | AO14: 25
A15: 11 | B15: 14135 | C15: ERF78A | D15: 0432015255 | E15: F | F15: 1100 | G15: PCL | J15: =IF(G15="RSL","55","0") -> 0 | K15: 125 | N15: SHIVAM | O15: 22044 (4/6) H | U15: =(T15-S15)*24 -> 0 | Y15: 11 | AD15: 26 | AJ15: 11 | AO15: 26
A16: 12 | B16: 14136 | C16: EUP53B | D16: 0410043981 | E16: F | F16: 1115 | G16: X | I16: 75 | J16: =IF(G16="RSL","55","0") -> 0 | K16: =IF(G16="GVS","37.5",IF(G16="GVM","41.5",IF(G16="GVL","50",IF(G16="PCS","45.8",IF(G16="PCM","50",IF(G16="PCL","58.3","0")))))) -> 0 | N16: SHIVAM | R16: =H32/U16 -> 0.54545455 | S16: =H32/(U16-U5) -> 0.71186441 | T16: =C32/U16 -> 43.116883 | U16: =SUM(U5:U15) -> 38.5 | Y16: 12 | AD16: 27 | AJ16: 12 | AO16: 27
A17: 13 | B17: 14137 | C17: EKR80D | D17: 0414337002 | E17: M | F17: 1145 | G17: W/O | I17: 65 | J17: =IF(G17="RSL","55","0") -> 0 | K17: =IF(G17="GVS","37.5",IF(G17="GVM","41.5",IF(G17="GVL","50",IF(G17="PCS","45.8",IF(G17="PCM","50",IF(G17="PCL","58.3","0")))))) -> 0 | N17: SHIVAM | R17: Cars/T Hr ① | S17: Cars/T Hr ② | T17: Sales/T Hr | U17: Total Hours | Y17: 13 | AD17: 28 | AJ17: 13 | AO17: 28
A18: 14 | B18: 14138 | C18: EBT61V | D18: 0416281895 | E18: F | F18: 1145 | G18: D | I18: 55 | J18: =IF(G18="RSL","55","0") -> 0 | K18: =IF(G18="GVS","37.5",IF(G18="GVM","41.5",IF(G18="GVL","50",IF(G18="PCS","45.8",IF(G18="PCM","50",IF(G18="PCL","58.3","0")))))) -> 0 | N18: SHIVAM | R18: ITEM | S18: QTY | T18: AMT | U18: RMKS | Y18: 14 | AD18: 29 | AJ18: 14 | AO18: 29
A19: 15 | B19: 14139 | C19: VW278 | D19: 0417674600 | E19: F | F19: 1205 | G19: H | H19: 115 | J19: =IF(G19="RSL","55","0") -> 0 | K19: =IF(G19="GVS","37.5",IF(G19="GVM","41.5",IF(G19="GVL","50",IF(G19="PCS","45.8",IF(G19="PCM","50",IF(G19="PCL","58.3","0")))))) -> 0 | N19: HENDRA | O19: $5 OFF | R19: GV | S19: =COUNT(L5:M29,L37:M61,L69:M93) -> 2 | T19: =SUM(L5:M29,L37:M61,L69:M93) -> 775 | Y19: 15 | AD19: 30 | AJ19: 15 | AO19: 30
A20: 16 | B20: 14140 | C20: C1092M | D20: 0423229668 | E20: F | F20: 1325 | G20: X | I20: 120 | J20: =IF(G20="RSL","55","0") -> 0 | K20: =IF(G20="GVS","37.5",IF(G20="GVM","41.5",IF(G20="GVL","50",IF(G20="PCS","45.8",IF(G20="PCM","50",IF(G20="PCL","58.3","0")))))) -> 0 | N20: HENDRA | O20: DUST | AD20: 31 | AO20: 31
A21: 17 | B21: 14141 | C21: JKD988 | D21: 0412822216 | E21: M | F21: 1330 | G21: PCL | J21: =IF(G21="RSL","55","0") -> 0 | K21: 79 | N21: SHIVAM | O21: 22186(2/6)
A22: 18 | B22: 14142 | C22: DLY25Y | D22: 0421050164 | E22: M | F22: 1400 | G22: W/O | I22: 65 | J22: =IF(G22="RSL","55","0") -> 0 | K22: =IF(G22="GVS","37.5",IF(G22="GVM","41.5",IF(G22="GVL","50",IF(G22="PCS","45.8",IF(G22="PCM","50",IF(G22="PCL","58.3","0")))))) -> 0 | N22: SHIVAM | AD22: Total | AE22: =SUM(Z5:Z19,AE5:AE20) -> 0 | AF22: =SUM(AA5:AA19,AF5:AF20,) -> 0 | AG22: =SUM(AB5:AB19,AG5:AG20) -> 0 | AO22: Total | AP22: =SUM(AK5:AK19,AP5:AP20) -> 0 | AQ22: =SUM(AL5:AL19,AQ5:AQ20,) -> 0 | AR22: =SUM(AM5:AM19,AR5:AR20) -> 0
A23: 19 | B23: 14143 | C23: CV57AO | D23: 0435117046 | E23: F | F23: 1415 | G23: D | I23: 55 | J23: =IF(G23="RSL","55","0") -> 0 | K23: =IF(G23="GVS","37.5",IF(G23="GVM","41.5",IF(G23="GVL","50",IF(G23="PCS","45.8",IF(G23="PCM","50",IF(G23="PCL","58.3","0")))))) -> 0 | N23: HENDRA
A24: 20 | B24: 14144 | C24: DYZ80J | D24: 0481215048 | E24: F | F24: 1420 | G24: PCS | J24: =IF(G24="RSL","55","0") -> 0 | K24: 63 | N24: HENDRA | O24: 22056(1/6) | R24: SMALL | S24: MEDIUM | T24: LARGE | U24: TOTAL | AD24: B2/GA TOTAL | AE24: B2 machine | AF24: GA machine | AG24: BLH machine | AH24: Wongo machine | AI24: Sub total
A25: 21 | B25: 14145 | C25: DWR91W | D25: 0411724816 | E25: M | F25: 1500 | G25: X | I25: 95 | J25: =IF(G25="RSL","55","0") -> 0 | K25: =IF(G25="GVS","37.5",IF(G25="GVM","41.5",IF(G25="GVL","50",IF(G25="PCS","45.8",IF(G25="PCM","50",IF(G25="PCL","58.3","0")))))) -> 0 | N25: VINNY | R25: =COUNTIF(G5:G29,"GV1")+COUNTIF(G37:G61,"GV1")+COUNTIF(G69:G93,"GV1") -> 0 | S25: =COUNTIF(G5:G29,"GV2")+COUNTIF(G37:G61,"GV2")+COUNTIF(G69:G93,"GV2") -> 0 | T25: =COUNTIF(G5:G29,"GV3")+COUNTIF(G37:G61,"GV3")+COUNTIF(G69:G93,"GV3") -> 0 | U25: =((C32+(R26+S26+T26)*0.5)) -> 1660 | AD25: =SUM(AE25:AF25) -> 0 | AE25: =SUM(AE22) -> 0 | AF25: =SUM(AP22) -> 0 | AG25: =SUM(AF22+AQ22) -> 0 | AH25: =AG22+AR22 -> 0 | AI25: =SUM(AE25:AH25) -> 0
A26: 22 | J26: =IF(G26="RSL","55","0") -> 0 | K26: =IF(G26="GVS","37.5",IF(G26="GVM","41.5",IF(G26="GVL","50",IF(G26="PCS","45.8",IF(G26="PCM","50",IF(G26="PCL","58.3","0")))))) -> 0 | R26: =R25*37.5 -> 0 | S26: =S25*41.5 -> 0 | T26: =T25*50 -> 0 | X26: Branch cards
A27: 23 | J27: =IF(G27="RSL","55","0") -> 0 | K27: =IF(G27="GVS","37.5",IF(G27="GVM","41.5",IF(G27="GVL","50",IF(G27="PCS","45.8",IF(G27="PCM","50",IF(G27="PCL","58.3","0")))))) -> 0 | R27: Expense | X27: 1 | Z27: -2745
A28: 24 | J28: =IF(G28="RSL","55","0") -> 0 | K28: =IF(G28="GVS","37.5",IF(G28="GVM","41.5",IF(G28="GVL","50",IF(G28="PCS","45.8",IF(G28="PCM","50",IF(G28="PCL","58.3","0")))))) -> 0 | X28: 2
A29: 25 | J29: =IF(G29="RSL","55","0") -> 0 | K29: =IF(G29="GVS","37.5",IF(G29="GVM","41.5",IF(G29="GVL","50",IF(G29="PCS","45.8",IF(G29="PCM","50",IF(G29="PCL","58.3","0")))))) -> 0 | X29: 3
A30: Page total | H30: =SUM(H5:H29) -> 285 | I30: =SUM(I5:I29) -> 950 | J30: =J5+J6+J7+J8+J9+J10+J11+J12+J13+J14+J15+J16+J18+J19+J17+J20+J22+J23+J21+J24+J25+J26+J27+J28+J29 -> 0 | K30: =K5+K6+K7+K8+K9+K10+K11+K12+K13+K14+K15+K16+K18+K19+K17+K20+K22+K23+K21+K24+K25+K26+K27+K28+K29 -> 425 | L30: =SUM(L5:L29) -> 300 | M30: =SUM(M5:M29) -> 475 | N30: CASH | O30: CARD | P30: GV | Q30: RSL | X30: 4
A31: Daily Total | H31: =H30+H62+H94 -> 285 | I31: =I30+I62+I94 -> 950 | J31: =J30+J62+J94 -> 0 | K31: =K30+K62+K94 -> 425 | L31: =L30+L62+L94 -> 300 | M31: =M30+M62+M94 -> 475 | N31: =COUNT(H5:H29,H37:H61,H69:H93) -> 3 | O31: =COUNT(I5:I29,I37:I61,I69:I93) -> 12 | P31: =COUNTIF(G5:G29,"G*")+COUNTIF(G37:G61,"G*")+COUNTIF(G69:G93,"G*")+COUNTIF(G5:G29,"P*")+COUNTIF(G37:G61,"P*")+COUNTIF(G69:G93,"P*") -> 6 | Q31: =COUNTIF(G5:G29,"RSL")+COUNTIF(G37:G61,"RSL")+COUNTIF(G69:G93,"RSL") -> 0 | R31: CASH CLOSING | S31: =H31+L31-U28-U29-U30 -> 585 | T31: =H31+I31+L31+M31 -> 2010 | X31: Subtotal | Z31: =SUM(Z27:Z30) -> -2745
A32: TOTAL SALES | C32: =H31+I31+J31+K31 -> 1660 | F32: No of Cars | H32: =COUNT(B5:B29,B37:B61,B69:B93) -> 21 | I32: Average | K32: =C32/H32 -> 79.047619 | N32: =H31/C32 -> 0.17168675 | O32: =I31/C32 -> 0.57228916 | P32: =K31/C32 -> 0.2560241 | Q32: =J31/C32 -> 0 | R32: CARD CLOSING | S32: =I31+M31 -> 1425 | X32: B2 card | Z32: =I31 -> 950
A33: Daily Report | X33: Settlement | Z33: =SUM(Z31:Z32) -> -1795
A34: =A2 -> 44991 | H34: WEATHER | J34: =J2 -> SUNNY | L34: REPORT by | O34: =O2 -> HENDRA | R34: TOTAL STAFF | T34: =T2 -> 5
A36: No | B36: Docket No | C36: Reg No | D36: Mobile | E36: Gender | F36: TIME | G36: Service | H36: CASH | I36: CARD | J36: RSL | K36: GV | L36: GV CASH | M36: GV CARD | N36: O/Taker | O36: Comment | R36: NAME | S36: Time In | T36: Time out | U36: Total Hours
A37: =A29+1 -> 26 | J37: =IF(G37="RSL","55","0") -> 0 | K37: =IF(G37="GVS","37.5",IF(G37="GVM","41.5",IF(G37="GVL","50",IF(G37="PCS","45.8",IF(G37="PCM","50",IF(G37="PCL","58.3","0")))))) -> 0
A38: =A37+1 -> 27 | J38: =IF(G38="RSL","55","0") -> 0 | K38: =IF(G38="GVS","37.5",IF(G38="GVM","41.5",IF(G38="GVL","50",IF(G38="PCS","45.8",IF(G38="PCM","50",IF(G38="PCL","58.3","0")))))) -> 0
A39: =A38+1 -> 28 | J39: =IF(G39="RSL","55","0") -> 0 | K39: =IF(G39="GVS","37.5",IF(G39="GVM","41.5",IF(G39="GVL","50",IF(G39="PCS","45.8",IF(G39="PCM","50",IF(G39="PCL","58.3","0")))))) -> 0
A40: =A39+1 -> 29 | J40: =IF(G40="RSL","55","0") -> 0 | K40: =IF(G40="GVS","37.5",IF(G40="GVM","41.5",IF(G40="GVL","50",IF(G40="PCS","45.8",IF(G40="PCM","50",IF(G40="PCL","58.3","0")))))) -> 0
A41: =A40+1 -> 30 | J41: =IF(G41="RSL","55","0") -> 0 | K41: =IF(G41="GVS","37.5",IF(G41="GVM","41.5",IF(G41="GVL","50",IF(G41="PCS","45.8",IF(G41="PCM","50",IF(G41="PCL","58.3","0")))))) -> 0
A42: =A41+1 -> 31 | J42: =IF(G42="RSL","55","0") -> 0 | K42: =IF(G42="GVS","37.5",IF(G42="GVM","41.5",IF(G42="GVL","50",IF(G42="PCS","45.8",IF(G42="PCM","50",IF(G42="PCL","58.3","0")))))) -> 0
A43: =A42+1 -> 32 | J43: =IF(G43="RSL","55","0") -> 0 | K43: =IF(G43="GVS","37.5",IF(G43="GVM","41.5",IF(G43="GVL","50",IF(G43="PCS","45.8",IF(G43="PCM","50",IF(G43="PCL","58.3","0")))))) -> 0
A44: =A43+1 -> 33 | J44: =IF(G44="RSL","55","0") -> 0 | K44: =IF(G44="GVS","37.5",IF(G44="GVM","41.5",IF(G44="GVL","50",IF(G44="PCS","45.8",IF(G44="PCM","50",IF(G44="PCL","58.3","0")))))) -> 0
A45: =A44+1 -> 34 | J45: =IF(G45="RSL","55","0") -> 0 | K45: =IF(G45="GVS","37.5",IF(G45="GVM","41.5",IF(G45="GVL","50",IF(G45="PCS","45.8",IF(G45="PCM","50",IF(G45="PCL","58.3","0")))))) -> 0
A46: =A45+1 -> 35 | J46: =IF(G46="RSL","55","0") -> 0 | K46: =IF(G46="GVS","37.5",IF(G46="GVM","41.5",IF(G46="GVL","50",IF(G46="PCS","45.8",IF(G46="PCM","50",IF(G46="PCL","58.3","0")))))) -> 0
A47: =A46+1 -> 36 | J47: =IF(G47="RSL","55","0") -> 0 | K47: =IF(G47="GVS","37.5",IF(G47="GVM","41.5",IF(G47="GVL","50",IF(G47="PCS","45.8",IF(G47="PCM","50",IF(G47="PCL","58.3","0")))))) -> 0
A48: =A47+1 -> 37 | J48: =IF(G48="RSL","55","0") -> 0 | K48: =IF(G48="GVS","37.5",IF(G48="GVM","41.5",IF(G48="GVL","50",IF(G48="PCS","45.8",IF(G48="PCM","50",IF(G48="PCL","58.3","0")))))) -> 0
A49: =A48+1 -> 38 | J49: =IF(G49="RSL","55","0") -> 0 | K49: =IF(G49="GVS","37.5",IF(G49="GVM","41.5",IF(G49="GVL","50",IF(G49="PCS","45.8",IF(G49="PCM","50",IF(G49="PCL","58.3","0")))))) -> 0
... A61: =A60+1 -> 50 | J61: =IF(G61="RSL","55","0") -> 0 | K61: =IF(G61="GVS","37.5",IF(G61="GVM","41.5",IF(G61="GVL","50",IF(G61="PCS","45.8",IF(G61="PCM","50",IF(G61="PCL","58.3","0")))))) -> 0
A62: Page total | H62: =SUM(H37:H61) -> 0 | I62: =SUM(I37:I61) -> 0 | J62: =J61+J60+J59+J58+J57+J56+J55+J54+J53+J52+J51+J50+J49+J48+J47+J46+J45+J44+J43+J42+J41+J40+J39+J38+J37 -> 0 | K62: =K61+K60+K59+K58+K57+K56+K55+K54+K53+K52+K51+K50+K49+K48+K47+K46+K45+K44+K43+K42+K41+K40+K39+K38+K37 -> 0 | L62: =SUM(L37:L61) -> 0 | M62: =SUM(M37:M61) -> 0
R64: Page: 2
A65: Daily Report
A66: =A34 -> 44991 | H66: WEATHER | J66: =J34 -> SUNNY | L66: REPORT by | O66: =O34 -> HENDRA | R66: TOTAL STAFF | T66: =T34 -> 5
A68: No | B68: Docket No | C68: Reg No | D68: Mobile | E68: Gender | F68: TIME | G68: Service | H68: CASH | I68: CARD | J68: RSL | K68: GV | L68: GV CASH | M68: GV CARD | N68: O/Taker | O68: Comment | R68: NAME | S68: Time In | T68: Time out | U68: Total Hours
A69: =A61+1 -> 51 | J69: =IF(G69="RSL","55","0") -> 0 | K69: =IF(G69="GVS","37.5",IF(G69="GVM","41.5",IF(G69="GVL","50",IF(G69="PCS","45.8",IF(G69="PCM","50",IF(G69="PCL","58.3","0")))))) -> 0
A70: =A69+1 -> 52 | J70: =IF(G70="RSL","55","0") -> 0 | K70: =IF(G70="GVS","37.5",IF(G70="GVM","41.5",IF(G70="GVL","50",IF(G70="PCS","45.8",IF(G70="PCM","50",IF(G70="PCL","58.3","0")))))) -> 0
A71: =A70+1 -> 53 | J71: =IF(G71="RSL","55","0") -> 0 | K71: =IF(G71="GVS","37.5",IF(G71="GVM","41.5",IF(G71="GVL","50",IF(G71="PCS","45.8",IF(G71="PCM","50",IF(G71="PCL","58.3","0")))))) -> 0
A72: =A71+1 -> 54 | J72: =IF(G72="RSL","55","0") -> 0 | K72: =IF(G72="GVS","37.5",IF(G72="GVM","41.5",IF(G72="GVL","50",IF(G72="PCS","45.8",IF(G72="PCM","50",IF(G72="PCL","58.3","0")))))) -> 0
A73: =A72+1 -> 55 | J73: =IF(G73="RSL","55","0") -> 0 | K73: =IF(G73="GVS","37.5",IF(G73="GVM","41.5",IF(G73="GVL","50",IF(G73="PCS","45.8",IF(G73="PCM","50",IF(G73="PCL","58.3","0")))))) -> 0
A74: =A73+1 -> 56 | J74: =IF(G74="RSL","55","0") -> 0 | K74: =IF(G74="GVS","37.5",IF(G74="GVM","41.5",IF(G74="GVL","50",IF(G74="PCS","45.8",IF(G74="PCM","50",IF(G74="PCL","58.3","0")))))) -> 0
A75: =A74+1 -> 57 | J75: =IF(G75="RSL","55","0") -> 0 | K75: =IF(G75="GVS","37.5",IF(G75="GVM","41.5",IF(G75="GVL","50",IF(G75="PCS","45.8",IF(G75="PCM","50",IF(G75="PCL","58.3","0")))))) -> 0
A76: =A75+1 -> 58 | J76: =IF(G76="RSL","55","0") -> 0 | K76: =IF(G76="GVS","37.5",IF(G76="GVM","41.5",IF(G76="GVL","50",IF(G76="PCS","45.8",IF(G76="PCM","50",IF(G76="PCL","58.3","0")))))) -> 0
A77: =A76+1 -> 59 | J77: =IF(G77="RSL","55","0") -> 0 | K77: =IF(G77="GVS","37.5",IF(G77="GVM","41.5",IF(G77="GVL","50",IF(G77="PCS","45.8",IF(G77="PCM","50",IF(G77="PCL","58.3","0")))))) -> 0
A78: =A77+1 -> 60 | J78: =IF(G78="RSL","55","0") -> 0 | K78: =IF(G78="GVS","37.5",IF(G78="GVM","41.5",IF(G78="GVL","50",IF(G78="PCS","45.8",IF(G78="PCM","50",IF(G78="PCL","58.3","0")))))) -> 0
A79: =A78+1 -> 61 | J79: =IF(G79="RSL","55","0") -> 0 | K79: =IF(G79="GVS","37.5",IF(G79="GVM","41.5",IF(G79="GVL","50",IF(G79="PCS","45.8",IF(G79="PCM","50",IF(G79="PCL","58.3","0")))))) -> 0
A80: =A79+1 -> 62 | J80: =IF(G80="RSL","55","0") -> 0 | K80: =IF(G80="GVS","37.5",IF(G80="GVM","41.5",IF(G80="GVL","50",IF(G80="PCS","45.8",IF(G80="PCM","50",IF(G80="PCL","58.3","0")))))) -> 0
A81: =A80+1 -> 63 | J81: =IF(G81="RSL","55","0") -> 0 | K81: =IF(G81="GVS","37.5",IF(G81="GVM","41.5",IF(G81="GVL","50",IF(G81="PCS","45.8",IF(G81="PCM","50",IF(G81="PCL","58.3","0")))))) -> 0
... A93: =A92+1 -> 75 | J93: =IF(G93="RSL","55","0") -> 0 | K93: =IF(G93="GVS","37.5",IF(G93="GVM","41.5",IF(G93="GVL","50",IF(G93="PCS","45.8",IF(G93="PCM","50",IF(G93="PCL","58.3","0")))))) -> 0
A94: Page total | H94: =SUM(H69:H93) -> 0 | I94: =SUM(I69:I93) -> 0 | J94: =J93+J92+J91+J90+J89+J88+J87+J86+J85+J84+J83+J82+J81+J80+J79+J78+J77+J76+J75+J74+J73+J72+J71+J70+J69 -> 0 | K94: =K93+K92+K91+K90+K89+K88+K87+K86+K85+K84+K83+K82+K81+K80+K79+K78+K77+K76+K75+K74+K73+K72+K71+K70+K69 -> 0 | L94: =SUM(L69:L93) -> 0 | M94: =SUM(M69:M93) -> 0
R96: Page: 3

Sheet TUE
A1: B2 Daily Report
A2: 45110 | H2: WEATHER | J2: SUNNY | L2: REPORT BY | O2: HENDRA | R2: TOTAL STAFF | T2: 4 | X2: Merchant machine usage at B2 | AA2: Settle amount | AI2: Merchant machine usage at GA | AL2: Settle amount
A4: No | B4: Docket No | C4: Reg No | D4: Mobile | E4: Gender | F4: TIME | G4: Service | H4: CASH | I4: CARD | J4: RSL | K4: GV | L4: GV CASH | M4: GV CARD | N4: O/Taker | O4: Comment | R4: NAME | S4: Time In | T4: Time out | U4: Total Hours | Z4: B2 machine | AA4: BLH machine | AB4: Wongo | AE4: B2 machine | AF4: BLH machine | AG4: Wongo | AK4: GA machine | AL4: BLH machine | AM4: Wongo | AP4: GA machine | AQ4: BLH machine | AR4: Wongo
A5: 1 | B5: 14146 | C5: BZL35W | D5: 0466576221 | E5: F | F5: 915 | G5: D | I5: 55 | J5: =IF(G5="RSL","55","0") -> 0 | K5: =IF(G5="GVS","37.5",IF(G5="GVM","41.5",IF(G5="GVL","50",IF(G5="PCS","45.8",IF(G5="PCM","50",IF(G5="PCL","58.3","0")))))) -> 0 | N5: HENDRA | R5: HENDRA | S5: 0.33333333 | T5: 0.70833333 | U5: =(T5-S5)*24 -> 9 | X5: NOV | Y5: 1 | AD5: 16 | AI5: NOV | AJ5: 1 | AO5: 16
A6: 2 | B6: 14147 | C6: DAJ33N | D6: 0450070773 | E6: M | F6: 950 | G6: PCL | J6: =IF(G6="RSL","55","0") -> 0 | K6: 79.16 | N6: HENDRA | O6: 22194(2/6) | R6: ARIANTO | S6: 0.35416667 | T6: 0.48958333 | U6: =(T6-S6)*24 -> 3.25 | W6: M | Y6: 2 | AD6: 17 | AJ6: 2 | AO6: 17
A7: 3 | B7: 14148 | C7: NCB66C | D7: 0419696360 | E7: F | F7: 1000 | G7: X | H7: 75 | J7: =IF(G7="RSL","55","0") -> 0 | K7: =IF(G7="GVS","37.5",IF(G7="GVM","41.5",IF(G7="GVL","50",IF(G7="PCS","45.8",IF(G7="PCM","50",IF(G7="PCL","58.3","0")))))) -> 0 | N7: HENDRA | S7: 0.53125 | T7: 0.625 | U7: =(T7-S7)*24 -> 2.25 | W7: F | Y7: 3 | AD7: 18 | AJ7: 3 | AO7: 18
A8: 4 | B8: 14149 | C8: BXC81W | D8: 0407015117 | E8: F | F8: 1140 | G8: X | I8: 95 | J8: =IF(G8="RSL","55","0") -> 0 | K8: =IF(G8="GVS","37.5",IF(G8="GVM","41.5",IF(G8="GVL","50",IF(G8="PCS","45.8",IF(G8="PCM","50",IF(G8="PCL","58.3","0")))))) -> 0 | N8: HENDRA | R8: JAMES | S8: 0.375 | T8: 0.70833333 | U8: =(T8-S8)*24 -> 8 | Y8: 4 | AD8: 19 | AJ8: 4 | AO8: 19
A9: 5 | B9: 14150 | C9: LP127 | D9: 0408417669 | E9: M | F9: 1145 | G9: PCS | J9: =IF(G9="RSL","55","0") -> 0 | K9: 62.5 | N9: HENDRA | O9: 22090(1/6) | R9: VINNY | S9: 0.4375 | T9: 0.70833333 | U9: =(T9-S9)*24 -> 6.5 | X9: EXCL RSL | Y9: 5 | AD9: 20 | AJ9: 5 | AO9: 20
A10: 6 | B10: 14151 | C10: EEU68B | D10: 0422673942 | E10: M | F10: 1200 | G10: D | I10: 75 | J10: =IF(G10="RSL","55","0") -> 0 | K10: =IF(G10="GVS","37.5",IF(G10="GVM","41.5",IF(G10="GVL","50",IF(G10="PCS","45.8",IF(G10="PCM","50",IF(G10="PCL","58.3","0")))))) -> 0 | N10: HENDRA | R10: MONA | S10: 0.625 | T10: 0.70833333 | U10: =(T10-S10)*24 -> 2 | Y10: 6 | AD10: 21 | AJ10: 6 | AO10: 21
A11: 7 | B11: 14152 | C11: KLF723 | D11: 0425777003 | E11: M | F11: 1200 | G11: PCL | J11: =IF(G11="RSL","55","0") -> 0 | K11: 79.16 | N11: HENDRA | O11: 22006(4/6) | U11: =(T11-S11)*24 -> 0 | Y11: 7 | AD11: 22 | AJ11: 7 | AO11: 22
A12: 8 | B12: 14153 | C12: DQJ24H | D12: 0404076130 | E12: F | F12: 1235 | G12: D/CLAY | I12: 200 | J12: =IF(G12="RSL","55","0") -> 0 | K12: =IF(G12="GVS","37.5",IF(G12="GVM","41.5",IF(G12="GVL","50",IF(G12="PCS","45.8",IF(G12="PCM","50",IF(G12="PCL","58.3","0")))))) -> 0 | N12: HENDRA | U12: =(T12-S12)*24 -> 0 | Y12: 8 | AD12: 23 | AJ12: 8 | AO12: 23
A13: 9 | B13: 14154 | C13: RC8866 | D13: 0409709697 | E13: F | F13: 1240 | G13: PCL | J13: =IF(G13="RSL","55","0") -> 0 | K13: 79.16 | N13: HENDRA | O13: 22097(2/6) | U13: =(T13-S13)*24 -> 0 | Y13: 9 | AD13: 24 | AJ13: 9 | AO13: 24
A14: 10 | B14: 14155 | C14: 27KWH | D14: 0433612258 | E14: F | F14: 1245 | G14: X | I14: 75 | J14: =IF(G14="RSL","55","0") -> 0 | K14: =IF(G14="GVS","37.5",IF(G14="GVM","41.5",IF(G14="GVL","50",IF(G14="PCS","45.8",IF(G14="PCM","50",IF(G14="PCL","58.3","0")))))) -> 0 | N14: HENDRA | O14: BOOKING ONLINE | U14: =(T14-S14)*24 -> 0 | Y14: 10 | AD14: 25 | AJ14: 10 | AO14: 25
A15: 11 | B15: 14156 | C15: CNI28W | D15: 0425661609 | E15: M | F15: 1300 | G15: PCL | J15: =IF(G15="RSL","55","0") -> 0 | K15: 125 | N15: HENDRA | O15: 22118(2/6) H | U15: =(T15-S15)*24 -> 0 | Y15: 11 | AD15: 26 | AJ15: 11 | AO15: 26
A16: 12 | B16: 14157 | C16: EUH08U | D16: 0414158733 | E16: F | F16: 1300 | G16: X | I16: 75 | J16: =IF(G16="RSL","55","0") -> 0 | K16: =IF(G16="GVS","37.5",IF(G16="GVM","41.5",IF(G16="GVL","50",IF(G16="PCS","45.8",IF(G16="PCM","50",IF(G16="PCL","58.3","0")))))) -> 0 | N16: HENDRA | R16: =H32/U16 -> 0.51612903 | S16: =H32/(U16-U5) -> 0.72727273 | T16: =C32/U16 -> 45.644516 | U16: =SUM(U5:U15) -> 31 | Y16: 12 | AD16: 27 | AJ16: 12 | AO16: 27
A17: 13 | B17: 14158 | C17: DGA98Z | D17: 0413996557 | E17: F | F17: 1420 | G17: GV | J17: =IF(G17="RSL","55","0") -> 0 | K17: 0 | M17: 300 | N17: HENDRA | O17: XD-50-182-187 (D) | R17: Cars/T Hr ① | S17: Cars/T Hr ② | T17: Sales/T Hr | U17: Total Hours | Y17: 13 | AD17: 28 | AJ17: 13 | AO17: 28
A18: 14 | B18: 14159 | C18: DDC10C | D18: 0438775937 | E18: F | F18: 1445 | G18: X | I18: 95 | J18: =IF(G18="RSL","55","0") -> 0 | K18: =IF(G18="GVS","37.5",IF(G18="GVM","41.5",IF(G18="GVL","50",IF(G18="PCS","45.8",IF(G18="PCM","50",IF(G18="PCL","58.3","0")))))) -> 0 | N18: HENDRA | R18: ITEM | S18: QTY | T18: AMT | U18: RMKS | Y18: 14 | AD18: 29 | AJ18: 14 | AO18: 29
A19: 15 | B19: 14160 | C19: 522 | D19: 0430206670 | E19: M | F19: 1450 | G19: H | H19: 150 | J19: =IF(G19="RSL","55","0") -> 0 | K19: =IF(G19="GVS","37.5",IF(G19="GVM","41.5",IF(G19="GVL","50",IF(G19="PCS","45.8",IF(G19="PCM","50",IF(G19="PCL","58.3","0")))))) -> 0 | N19: HENDRA | R19: GV | S19: =COUNT(L5:M29,L37:M61,L69:M93) -> 1 | T19: =SUM(L5:M29,L37:M61,L69:M93) -> 300 | Y19: 15 | AD19: 30 | AJ19: 15 | AO19: 30
A20: 16 | B20: 14161 | C20: EHI64P | D20: 0431431944 | E20: F | F20: 1510 | G20: X | H20: 95 | J20: =IF(G20="RSL","55","0") -> 0 | K20: =IF(G20="GVS","37.5",IF(G20="GVM","41.5",IF(G20="GVL","50",IF(G20="PCS","45.8",IF(G20="PCM","50",IF(G20="PCL","58.3","0")))))) -> 0 | N20: HENDRA | AD20: 31 | AO20: 31
A21: 17 | J21: =IF(G21="RSL","55","0") -> 0 | K21: =IF(G21="GVS","37.5",IF(G21="GVM","41.5",IF(G21="GVL","50",IF(G21="PCS","45.8",IF(G21="PCM","50",IF(G21="PCL","58.3","0")))))) -> 0
A22: 18 | J22: =IF(G22="RSL","55","0") -> 0 | K22: =IF(G22="GVS","37.5",IF(G22="GVM","41.5",IF(G22="GVL","50",IF(G22="PCS","45.8",IF(G22="PCM","50",IF(G22="PCL","58.3","0")))))) -> 0 | AD22: Total | AE22: =SUM(Z5:Z19,AE5:AE20) -> 0 | AF22: =SUM(AA5:AA19,AF5:AF20,) -> 0 | AG22: =SUM(AB5:AB19,AG5:AG20) -> 0 | AO22: Total | AP22: =SUM(AK5:AK19,AP5:AP20) -> 0 | AQ22: =SUM(AL5:AL19,AQ5:AQ20,) -> 0 | AR22: =SUM(AM5:AM19,AR5:AR20) -> 0
A23: 19 | J23: =IF(G23="RSL","55","0") -> 0 | K23: =IF(G23="GVS","37.5",IF(G23="GVM","41.5",IF(G23="GVL","50",IF(G23="PCS","45.8",IF(G23="PCM","50",IF(G23="PCL","58.3","0")))))) -> 0
A24: 20 | J24: =IF(G24="RSL","55","0") -> 0 | K24: =IF(G24="GVS","37.5",IF(G24="GVM","41.5",IF(G24="GVL","50",IF(G24="PCS","45.8",IF(G24="PCM","50",IF(G24="PCL","58.3","0")))))) -> 0 | R24: SMALL | S24: MEDIUM | T24: LARGE | U24: TOTAL | AD24: B2/GA TOTAL | AE24: B2 machine | AF24: GA machine | AG24: BLH machine | AH24: Wongo machine | AI24: Sub total
A25: 21 | J25: =IF(G25="RSL","55","0") -> 0 | K25: =IF(G25="GVS","37.5",IF(G25="GVM","41.5",IF(G25="GVL","50",IF(G25="PCS","45.8",IF(G25="PCM","50",IF(G25="PCL","58.3","0")))))) -> 0 | R25: =COUNTIF(G5:G29,"GV1")+COUNTIF(G37:G61,"GV1")+COUNTIF(G69:G93,"GV1") -> 0 | S25: =COUNTIF(G5:G29,"GV2")+COUNTIF(G37:G61,"GV2")+COUNTIF(G69:G93,"GV2") -> 0 | T25: =COUNTIF(G5:G29,"GV3")+COUNTIF(G37:G61,"GV3")+COUNTIF(G69:G93,"GV3") -> 0 | U25: =((C32+(R26+S26+T26)*0.5)) -> 1414.98 | AD25: =SUM(AE25:AF25) -> 0 | AE25: =SUM(AE22) -> 0 | AF25: =SUM(AP22) -> 0 | AG25: =SUM(AF22+AQ22) -> 0 | AH25: =AG22+AR22 -> 0 | AI25: =SUM(AE25:AH25) -> 0
A26: 22 | J26: =IF(G26="RSL","55","0") -> 0 | K26: =IF(G26="GVS","37.5",IF(G26="GVM","41.5",IF(G26="GVL","50",IF(G26="PCS","45.8",IF(G26="PCM","50",IF(G26="PCL","58.3","0")))))) -> 0 | R26: =R25*37.5 -> 0 | S26: =S25*41.5 -> 0 | T26: =T25*50 -> 0 | X26: Branch cards
A27: 23 | J27: =IF(G27="RSL","55","0") -> 0 | K27: =IF(G27="GVS","37.5",IF(G27="GVM","41.5",IF(G27="GVL","50",IF(G27="PCS","45.8",IF(G27="PCM","50",IF(G27="PCL","58.3","0")))))) -> 0 | R27: Expense | X27: 1 | Z27: -2745
A28: 24 | J28: =IF(G28="RSL","55","0") -> 0 | K28: =IF(G28="GVS","37.5",IF(G28="GVM","41.5",IF(G28="GVL","50",IF(G28="PCS","45.8",IF(G28="PCM","50",IF(G28="PCL","58.3","0")))))) -> 0 | X28: 2
A29: 25 | J29: =IF(G29="RSL","55","0") -> 0 | K29: =IF(G29="GVS","37.5",IF(G29="GVM","41.5",IF(G29="GVL","50",IF(G29="PCS","45.8",IF(G29="PCM","50",IF(G29="PCL","58.3","0")))))) -> 0 | X29: 3
A30: Page total | H30: =SUM(H5:H29) -> 320 | I30: =SUM(I5:I29) -> 670 | J30: =J5+J6+J7+J8+J9+J10+J11+J12+J13+J14+J15+J16+J18+J19+J17+J20+J22+J23+J21+J24+J25+J26+J27+J28+J29 -> 0 | K30: =K5+K6+K7+K8+K9+K10+K11+K12+K13+K14+K15+K16+K18+K19+K17+K20+K22+K23+K21+K24+K25+K26+K27+K28+K29 -> 424.98 | L30: =SUM(L5:L29) -> 0 | M30: =SUM(M5:M29) -> 300 | N30: CASH | O30: CARD | P30: GV | Q30: RSL | X30: 4
A31: Daily Total | H31: =H30+H62+H94 -> 320 | I31: =I30+I62+I94 -> 670 | J31: =J30+J62+J94 -> 0 | K31: =K30+K62+K94 -> 424.98 | L31: =L30+L62+L94 -> 0 | M31: =M30+M62+M94 -> 300 | N31: =COUNT(H5:H29,H37:H61,H69:H93) -> 3 | O31: =COUNT(I5:I29,I37:I61,I69:I93) -> 7 | P31: =COUNTIF(G5:G29,"G*")+COUNTIF(G37:G61,"G*")+COUNTIF(G69:G93,"G*")+COUNTIF(G5:G29,"P*")+COUNTIF(G37:G61,"P*")+COUNTIF(G69:G93,"P*") -> 6 | Q31: =COUNTIF(G5:G29,"RSL")+COUNTIF(G37:G61,"RSL")+COUNTIF(G69:G93,"RSL") -> 0 | R31: CASH CLOSING | S31: =H31+L31-U28-U29-U30 -> 320 | T31: =H31+I31+L31+M31 -> 1290 | X31: Subtotal | Z31: =SUM(Z27:Z30) -> -2745
A32: TOTAL SALES | C32: =H31+I31+J31+K31 -> 1414.98 | F32: No of Cars | H32: =COUNT(B5:B29,B37:B61,B69:B93) -> 16 | I32: Average | K32: =C32/H32 -> 88.43625 | N32: =H31/C32 -> 0.22615161 | O32: =I31/C32 -> 0.47350493 | P32: =K31/C32 -> 0.30034347 | Q32: =J31/C32 -> 0 | R32: CARD CLOSING | S32: =I31+M31 -> 970 | X32: B2 card | Z32: =I31 -> 670
A33: Daily Report | X33: Settlement | Z33: =SUM(Z31:Z32) -> -2075
A34: =A2 -> 45110 | H34: WEATHER | J34: =J2 -> SUNNY | L34: REPORT by | O34: =O2 -> HENDRA | R34: TOTAL STAFF | T34: =T2 -> 4
A36: No | B36: Docket No | C36: Reg No | D36: Mobile | E36: Gender | F36: TIME | G36: Service | H36: CASH | I36: CARD | J36: RSL | K36: GV | L36: GV CASH | M36: GV CARD | N36: O/Taker | O36: Comment | R36: NAME | S36: Time In | T36: Time out | U36: Total Hours
A37: =A29+1 -> 26 | J37: =IF(G37="RSL","55","0") -> 0 | K37: =IF(G37="GVS","37.5",IF(G37="GVM","41.5",IF(G37="GVL","50",IF(G37="PCS","45.8",IF(G37="PCM","50",IF(G37="PCL","58.3","0")))))) -> 0
A38: =A37+1 -> 27 | J38: =IF(G38="RSL","55","0") -> 0 | K38: =IF(G38="GVS","37.5",IF(G38="GVM","41.5",IF(G38="GVL","50",IF(G38="PCS","45.8",IF(G38="PCM","50",IF(G38="PCL","58.3","0")))))) -> 0
A39: =A38+1 -> 28 | J39: =IF(G39="RSL","55","0") -> 0 | K39: =IF(G39="GVS","37.5",IF(G39="GVM","41.5",IF(G39="GVL","50",IF(G39="PCS","45.8",IF(G39="PCM","50",IF(G39="PCL","58.3","0")))))) -> 0
A40: =A39+1 -> 29 | J40: =IF(G40="RSL","55","0") -> 0 | K40: =IF(G40="GVS","37.5",IF(G40="GVM","41.5",IF(G40="GVL","50",IF(G40="PCS","45.8",IF(G40="PCM","50",IF(G40="PCL","58.3","0")))))) -> 0
A41: =A40+1 -> 30 | J41: =IF(G41="RSL","55","0") -> 0 | K41: =IF(G41="GVS","37.5",IF(G41="GVM","41.5",IF(G41="GVL","50",IF(G41="PCS","45.8",IF(G41="PCM","50",IF(G41="PCL","58.3","0")))))) -> 0
A42: =A41+1 -> 31 | J42: =IF(G42="RSL","55","0") -> 0 | K42: =IF(G42="GVS","37.5",IF(G42="GVM","41.5",IF(G42="GVL","50",IF(G42="PCS","45.8",IF(G42="PCM","50",IF(G42="PCL","58.3","0")))))) -> 0
A43: =A42+1 -> 32 | J43: =IF(G43="RSL","55","0") -> 0 | K43: =IF(G43="GVS","37.5",IF(G43="GVM","41.5",IF(G43="GVL","50",IF(G43="PCS","45.8",IF(G43="PCM","50",IF(G43="PCL","58.3","0")))))) -> 0
A44: =A43+1 -> 33 | J44: =IF(G44="RSL","55","0") -> 0 | K44: =IF(G44="GVS","37.5",IF(G44="GVM","41.5",IF(G44="GVL","50",IF(G44="PCS","45.8",IF(G44="PCM","50",IF(G44="PCL","58.3","0")))))) -> 0
A45: =A44+1 -> 34 | J45: =IF(G45="RSL","55","0") -> 0 | K45: =IF(G45="GVS","37.5",IF(G45="GVM","41.5",IF(G45="GVL","50",IF(G45="PCS","45.8",IF(G45="PCM","50",IF(G45="PCL","58.3","0")))))) -> 0
A46: =A45+1 -> 35 | J46: =IF(G46="RSL","55","0") -> 0 | K46: =IF(G46="GVS","37.5",IF(G46="GVM","41.5",IF(G46="GVL","50",IF(G46="PCS","45.8",IF(G46="PCM","50",IF(G46="PCL","58.3","0")))))) -> 0
A47: =A46+1 -> 36 | J47: =IF(G47="RSL","55","0") -> 0 | K47: =IF(G47="GVS","37.5",IF(G47="GVM","41.5",IF(G47="GVL","50",IF(G47="PCS","45.8",IF(G47="PCM","50",IF(G47="PCL","58.3","0")))))) -> 0
A48: =A47+1 -> 37 | J48: =IF(G48="RSL","55","0") -> 0 | K48: =IF(G48="GVS","37.5",IF(G48="GVM","41.5",IF(G48="GVL","50",IF(G48="PCS","45.8",IF(G48="PCM","50",IF(G48="PCL","58.3","0")))))) -> 0
A49: =A48+1 -> 38 | J49: =IF(G49="RSL","55","0") -> 0 | K49: =IF(G49="GVS","37.5",IF(G49="GVM","41.5",IF(G49="GVL","50",IF(G49="PCS","45.8",IF(G49="PCM","50",IF(G49="PCL","58.3","0")))))) -> 0
... A61: =A60+1 -> 50 | J61: =IF(G61="RSL","55","0") -> 0 | K61: =IF(G61="GVS","37.5",IF(G61="GVM","41.5",IF(G61="GVL","50",IF(G61="PCS","45.8",IF(G61="PCM","50",IF(G61="PCL","58.3","0")))))) -> 0
A62: Page total | H62: =SUM(H37:H61) -> 0 | I62: =SUM(I37:I61) -> 0 | J62: =J61+J60+J59+J58+J57+J56+J55+J54+J53+J52+J51+J50+J49+J48+J47+J46+J45+J44+J43+J42+J41+J40+J39+J38+J37 -> 0 | K62: =K61+K60+K59+K58+K57+K56+K55+K54+K53+K52+K51+K50+K49+K48+K47+K46+K45+K44+K43+K42+K41+K40+K39+K38+K37 -> 0 | L62: =SUM(L37:L61) -> 0 | M62: =SUM(M37:M61) -> 0
R64: Page: 2
A65: Daily Report
A66: =A34 -> 45110 | H66: WEATHER | J66: =J34 -> SUNNY | L66: REPORT by | O66: =O34 -> HENDRA | R66: TOTAL STAFF | T66: =T34 -> 4
A68: No | B68: Docket No | C68: Reg No | D68: Mobile | E68: Gender | F68: TIME | G68: Service | H68: CASH | I68: CARD | J68: RSL | K68: GV | L68: GV CASH | M68: GV CARD | N68: O/Taker | O68: Comment | R68: NAME | S68: Time In | T68: Time out | U68: Total Hours
A69: =A61+1 -> 51 | J69: =IF(G69="RSL","55","0") -> 0 | K69: =IF(G69="GVS","37.5",IF(G69="GVM","41.5",IF(G69="GVL","50",IF(G69="PCS","45.8",IF(G69="PCM","50",IF(G69="PCL","58.3","0")))))) -> 0
A70: =A69+1 -> 52 | J70: =IF(G70="RSL","55","0") -> 0 | K70: =IF(G70="GVS","37.5",IF(G70="GVM","41.5",IF(G70="GVL","50",IF(G70="PCS","45.8",IF(G70="PCM","50",IF(G70="PCL","58.3","0")))))) -> 0
A71: =A70+1 -> 53 | J71: =IF(G71="RSL","55","0") -> 0 | K71: =IF(G71="GVS","37.5",IF(G71="GVM","41.5",IF(G71="GVL","50",IF(G71="PCS","45.8",IF(G71="PCM","50",IF(G71="PCL","58.3","0")))))) -> 0
A72: =A71+1 -> 54 | J72: =IF(G72="RSL","55","0") -> 0 | K72: =IF(G72="GVS","37.5",IF(G72="GVM","41.5",IF(G72="GVL","50",IF(G72="PCS","45.8",IF(G72="PCM","50",IF(G72="PCL","58.3","0")))))) -> 0
A73: =A72+1 -> 55 | J73: =IF(G73="RSL","55","0") -> 0 | K73: =IF(G73="GVS","37.5",IF(G73="GVM","41.5",IF(G73="GVL","50",IF(G73="PCS","45.8",IF(G73="PCM","50",IF(G73="PCL","58.3","0")))))) -> 0
A74: =A73+1 -> 56 | J74: =IF(G74="RSL","55","0") -> 0 | K74: =IF(G74="GVS","37.5",IF(G74="GVM","41.5",IF(G74="GVL","50",IF(G74="PCS","45.8",IF(G74="PCM","50",IF(G74="PCL","58.3","0")))))) -> 0
A75: =A74+1 -> 57 | J75: =IF(G75="RSL","55","0") -> 0 | K75: =IF(G75="GVS","37.5",IF(G75="GVM","41.5",IF(G75="GVL","50",IF(G75="PCS","45.8",IF(G75="PCM","50",IF(G75="PCL","58.3","0")))))) -> 0
A76: =A75+1 -> 58 | J76: =IF(G76="RSL","55","0") -> 0 | K76: =IF(G76="GVS","37.5",IF(G76="GVM","41.5",IF(G76="GVL","50",IF(G76="PCS","45.8",IF(G76="PCM","50",IF(G76="PCL","58.3","0")))))) -> 0
A77: =A76+1 -> 59 | J77: =IF(G77="RSL","55","0") -> 0 | K77: =IF(G77="GVS","37.5",IF(G77="GVM","41.5",IF(G77="GVL","50",IF(G77="PCS","45.8",IF(G77="PCM","50",IF(G77="PCL","58.3","0")))))) -> 0
A78: =A77+1 -> 60 | J78: =IF(G78="RSL","55","0") -> 0 | K78: =IF(G78="GVS","37.5",IF(G78="GVM","41.5",IF(G78="GVL","50",IF(G78="PCS","45.8",IF(G78="PCM","50",IF(G78="PCL","58.3","0")))))) -> 0
A79: =A78+1 -> 61 | J79: =IF(G79="RSL","55","0") -> 0 | K79: =IF(G79="GVS","37.5",IF(G79="GVM","41.5",IF(G79="GVL","50",IF(G79="PCS","45.8",IF(G79="PCM","50",IF(G79="PCL","58.3","0")))))) -> 0
A80: =A79+1 -> 62 | J80: =IF(G80="RSL","55","0") -> 0 | K80: =IF(G80="GVS","37.5",IF(G80="GVM","41.5",IF(G80="GVL","50",IF(G80="PCS","45.8",IF(G80="PCM","50",IF(G80="PCL","58.3","0")))))) -> 0
A81: =A80+1 -> 63 | J81: =IF(G81="RSL","55","0") -> 0 | K81: =IF(G81="GVS","37.5",IF(G81="GVM","41.5",IF(G81="GVL","50",IF(G81="PCS","45.8",IF(G81="PCM","50",IF(G81="PCL","58.3","0")))))) -> 0
... A93: =A92+1 -> 75 | J93: =IF(G93="RSL","55","0") -> 0 | K93: =IF(G93="GVS","37.5",IF(G93="GVM","41.5",IF(G93="GVL","50",IF(G93="PCS","45.8",IF(G93="PCM","50",IF(G93="PCL","58.3","0")))))) -> 0
A94: Page total | H94: =SUM(H69:H93) -> 0 | I94: =SUM(I69:I93) -> 0 | J94: =J93+J92+J91+J90+J89+J88+J87+J86+J85+J84+J83+J82+J81+J80+J79+J78+J77+J76+J75+J74+J73+J72+J71+J70+J69 -> 0 | K94: =K93+K92+K91+K90+K89+K88+K87+K86+K85+K84+K83+K82+K81+K80+K79+K78+K77+K76+K75+K74+K73+K72+K71+K70+K69 -> 0 | L94: =SUM(L69:L93) -> 0 | M94: =SUM(M69:M93) -> 0
R96: Page: 3

Sheet WED
A1: B2 Daily Report
A2: 44993 | H2: WEATHER | J2: SUNNY | L2: REPORT BY | O2: HENDRA | R2: TOTAL STAFF | T2: 5 | X2: Merchant machine usage at B2 | AA2: Settle amount | AI2: Merchant machine usage at GA | AL2: Settle amount
A4: No | B4: Docket No | C4: Reg No | D4: Mobile | E4: Gender | F4: TIME | G4: Service | H4: CASH | I4: CARD | J4: RSL | K4: GV | L4: GV CASH | M4: GV CARD | N4: O/Taker | O4: Comment | R4: NAME | S4: Time In | T4: Time out | U4: Total Hours | Z4: B2 machine | AA4: BLH machine | AB4: Wongo | AE4: B2 machine | AF4: BLH machine | AG4: Wongo | AK4: GA machine | AL4: BLH machine | AM4: Wongo | AP4: GA machine | AQ4: BLH machine | AR4: Wongo
A5: 1 | B5: 14162 | C5: EPW65B | D5: 0432565750 | E5: M | F5: 800 | G5: PCS | J5: =IF(G5="RSL","55","0") -> 0 | K5: 125 | N5: HENDRA | O5: 22070(4-5/6) | R5: HENDRA | S5: 0.33333333 | T5: 0.70833333 | U5: =(T5-S5)*24 -> 9 | X5: NOV | Y5: 1 | AD5: 16 | AI5: NOV | AJ5: 1 | AO5: 16
A6: 2 | B6: 14163 | C6: EGQ53M | D6: 0433818333 | E6: F | F6: 915 | G6: X | H6: 70 | J6: =IF(G6="RSL","55","0") -> 0 | K6: =IF(G6="GVS","37.5",IF(G6="GVM","41.5",IF(G6="GVL","50",IF(G6="PCS","45.8",IF(G6="PCM","50",IF(G6="PCL","58.3","0")))))) -> 0 | N6: HENDRA | O6: $5 OFF | R6: ATET | S6: 0.33333333 | T6: 0.70833333 | U6: =(T6-S6)*24 -> 9 | W6: M | Y6: 2 | AD6: 17 | AJ6: 2 | AO6: 17
A7: 3 | B7: 14164 | C7: BXA63C | D7: 0450656856 | E7: F | F7: 930 | G7: GV | J7: =IF(G7="RSL","55","0") -> 0 | K7: 0 | M7: 350 | N7: ATET | O7: XD50-188-191/337-340 | R7: ARIANTO | S7: 0.35416667 | T7: 0.625 | U7: =(T7-S7)*24 -> 6.5 | W7: F | Y7: 3 | AD7: 18 | AJ7: 3 | AO7: 18
A8: 4 | B8: 14165 | C8: KING9 | D8: 0488891999 | E8: M | F8: 930 | G8: PCL | J8: =IF(G8="RSL","55","0") -> 0 | K8: 79.16 | M8: 475 | N8: HENDRA | O8: 22101(6/6) X, 23226(NEW) X | R8: VINNY | S8: 0.42708333 | T8: 0.70833333 | U8: =(T8-S8)*24 -> 6.75 | Y8: 4 | AD8: 19 | AJ8: 4 | AO8: 19
A9: 5 | B9: 14166 | C9: CAF83J | D9: 0410688507 | E9: M | F9: 930 | G9: X | I9: 95 | J9: =IF(G9="RSL","55","0") -> 0 | K9: =IF(G9="GVS","37.5",IF(G9="GVM","41.5",IF(G9="GVL","50",IF(G9="PCS","45.8",IF(G9="PCM","50",IF(G9="PCL","58.3","0")))))) -> 0 | N9: ATET | R9: KUROSH | S9: 0.41666667 | T9: 0.70833333 | U9: =(T9-S9)*24 -> 7 | X9: EXCL RSL | Y9: 5 | AD9: 20 | AJ9: 5 | AO9: 20
A10: 6 | B10: 14167 | C10: CRR97J | D10: 0410857808 | E10: M | F10: 930 | G10: GV | J10: =IF(G10="RSL","55","0") -> 0 | K10: 0 | M10: 350 | N10: ATET | O10: XD50-341-347 (TAX) | U10: =(T10-S10)*24 -> 0 | Y10: 6 | AD10: 21 | AJ10: 6 | AO10: 21
A11: 7 | B11: 14168 | C11: LAW885 | D11: 0423237896 | E11: M | F11: 1030 | G11: S/D | I11: 250 | J11: =IF(G11="RSL","55","0") -> 0 | K11: =IF(G11="GVS","37.5",IF(G11="GVM","41.5",IF(G11="GVL","50",IF(G11="PCS","45.8",IF(G11="PCM","50",IF(G11="PCL","58.3","0")))))) -> 0 | N11: ATET | U11: =(T11-S11)*24 -> 0 | Y11: 7 | AD11: 22 | AJ11: 7 | AO11: 22
A12: 8 | B12: 14169 | C12: EWU34D | D12: 0478966933 | E12: F | F12: 1030 | G12: F/D | H12: 295 | J12: =IF(G12="RSL","55","0") -> 0 | K12: =IF(G12="GVS","37.5",IF(G12="GVM","41.5",IF(G12="GVL","50",IF(G12="PCS","45.8",IF(G12="PCM","50",IF(G12="PCL","58.3","0")))))) -> 0 | N12: ATET | O12: TAX | U12: =(T12-S12)*24 -> 0 | Y12: 8 | AD12: 23 | AJ12: 8 | AO12: 23
A13: 9 | B13: 14170 | C13: CJL828 | D13: 0400127856 | E13: F | F13: 1045 | G13: PCL | J13: =IF(G13="RSL","55","0") -> 0 | K13: 79.16 | N13: ATET | O13: 22103(3/6) | U13: =(T13-S13)*24 -> 0 | Y13: 9 | AD13: 24 | AJ13: 9 | AO13: 24
A14: 10 | B14: 14171 | C14: DCB24N | D14: 0416026587 | E14: F | F14: 1045 | G14: W/O (GV) | H14: 15 | J14: =IF(G14="RSL","55","0") -> 0 | K14: 50 | N14: ATET | O14: XD50-137 | U14: =(T14-S14)*24 -> 0 | Y14: 10 | AD14: 25 | AJ14: 10 | AO14: 25
A15: 11 | B15: 14172 | C15: NCA15F | D15: 0411139378 | E15: M | F15: 1100 | G15: PCL | J15: =IF(G15="RSL","55","0") -> 0 | K15: 79.16 | N15: ATET | O15: 22126(1/6) | U15: =(T15-S15)*24 -> 0 | Y15: 11 | AD15: 26 | AJ15: 11 | AO15: 26
A16: 12 | B16: 14173 | C16: SBO212 | D16: 0401704628 | E16: F | F16: 1130 | G16: D | I16: 75 | J16: =IF(G16="RSL","55","0") -> 0 | K16: =IF(G16="GVS","37.5",IF(G16="GVM","41.5",IF(G16="GVL","50",IF(G16="PCS","45.8",IF(G16="PCM","50",IF(G16="PCL","58.3","0")))))) -> 0 | N16: ATET | R16: =H32/U16 -> 0.52287582 | S16: =H32/(U16-U5) -> 0.68376068 | T16: =C32/U16 -> 47.058301 | U16: =SUM(U5:U15) -> 38.25 | Y16: 12 | AD16: 27 | AJ16: 12 | AO16: 27
A17: 13 | B17: 14174 | C17: PAA333 | D17: 0414337333 | E17: F | F17: 1130 | G17: X | I17: 95 | J17: =IF(G17="RSL","55","0") -> 0 | K17: =IF(G17="GVS","37.5",IF(G17="GVM","41.5",IF(G17="GVL","50",IF(G17="PCS","45.8",IF(G17="PCM","50",IF(G17="PCL","58.3","0")))))) -> 0 | N17: ATET | R17: Cars/T Hr ① | S17: Cars/T Hr ② | T17: Sales/T Hr | U17: Total Hours | Y17: 13 | AD17: 28 | AJ17: 13 | AO17: 28
A18: 14 | B18: 14175 | C18: EKW89F | D18: 0434622861 | E18: F | F18: 1200 | G18: GV | J18: =IF(G18="RSL","55","0") -> 0 | K18: 0 | M18: 350 | N18: ATET | O18: XD50-348-354 | R18: ITEM | S18: QTY | T18: AMT | U18: RMKS | Y18: 14 | AD18: 29 | AJ18: 14 | AO18: 29
A19: 15 | B19: 14176 | C19: ERT75C | D19: 0411642270 | E19: F | F19: 1200 | G19: X | I19: 75 | J19: =IF(G19="RSL","55","0") -> 0 | K19: =IF(G19="GVS","37.5",IF(G19="GVM","41.5",IF(G19="GVL","50",IF(G19="PCS","45.8",IF(G19="PCM","50",IF(G19="PCL","58.3","0")))))) -> 0 | N19: ATET | R19: GV | S19: =COUNT(L5:M29,L37:M61,L69:M93) -> 4 | T19: =SUM(L5:M29,L37:M61,L69:M93) -> 1525 | Y19: 15 | AD19: 30 | AJ19: 15 | AO19: 30
A20: 16 | B20: 14177 | C20: NCZ87M | D20: 0402505402 | E20: F | F20: 1230 | G20: X | I20: 75 | J20: =IF(G20="RSL","55","0") -> 0 | K20: =IF(G20="GVS","37.5",IF(G20="GVM","41.5",IF(G20="GVL","50",IF(G20="PCS","45.8",IF(G20="PCM","50",IF(G20="PCL","58.3","0")))))) -> 0 | N20: ATET | AD20: 31 | AO20: 31
A21: 17 | B21: 14178 | C21: EKC89S | D21: 0438354090 | E21: F | F21: 1315 | G21: D | I21: 55 | J21: =IF(G21="RSL","55","0") -> 0 | K21: =IF(G21="GVS","37.5",IF(G21="GVM","41.5",IF(G21="GVL","50",IF(G21="PCS","45.8",IF(G21="PCM","50",IF(G21="PCL","58.3","0")))))) -> 0 | N21: ATET
A22: 18 | B22: 14179 | C22: ANZ53F | D22: 0419482011 | E22: F | F22: 1330 | G22: X | H22: 95 | J22: =IF(G22="RSL","55","0") -> 0 | K22: =IF(G22="GVS","37.5",IF(G22="GVM","41.5",IF(G22="GVL","50",IF(G22="PCS","45.8",IF(G22="PCM","50",IF(G22="PCL","58.3","0")))))) -> 0 | N22: ATET | AD22: Total | AE22: =SUM(Z5:Z19,AE5:AE20) -> 0 | AF22: =SUM(AA5:AA19,AF5:AF20,) -> 0 | AG22: =SUM(AB5:AB19,AG5:AG20) -> 0 | AO22: Total | AP22: =SUM(AK5:AK19,AP5:AP20) -> 0 | AQ22: =SUM(AL5:AL19,AQ5:AQ20,) -> 0 | AR22: =SUM(AM5:AM19,AR5:AR20) -> 0
A23: 19 | B23: 14180 | C23: EPO91D | D23: 0419460470 | E23: F | F23: 1400 | G23: PCS | J23: =IF(G23="RSL","55","0") -> 0 | K23: 62.5 | N23: ATET | O23: 22051(6/6)
A24: 20 | B24: 14181 | C24: EBQ17K | D24: 0422661161 | E24: F | F24: 1545 | G24: H | I24: 130 | J24: =IF(G24="RSL","55","0") -> 0 | K24: =IF(G24="GVS","37.5",IF(G24="GVM","41.5",IF(G24="GVL","50",IF(G24="PCS","45.8",IF(G24="PCM","50",IF(G24="PCL","58.3","0")))))) -> 0 | N24: ATET | R24: SMALL | S24: MEDIUM | T24: LARGE | U24: TOTAL | AD24: B2/GA TOTAL | AE24: B2 machine | AF24: GA machine | AG24: BLH machine | AH24: Wongo machine | AI24: Sub total
A25: 21 | J25: =IF(G25="RSL","55","0") -> 0 | K25: =IF(G25="GVS","37.5",IF(G25="GVM","41.5",IF(G25="GVL","50",IF(G25="PCS","45.8",IF(G25="PCM","50",IF(G25="PCL","58.3","0")))))) -> 0 | R25: =COUNTIF(G5:G29,"GV1")+COUNTIF(G37:G61,"GV1")+COUNTIF(G69:G93,"GV1") -> 0 | S25: =COUNTIF(G5:G29,"GV2")+COUNTIF(G37:G61,"GV2")+COUNTIF(G69:G93,"GV2") -> 0 | T25: =COUNTIF(G5:G29,"GV3")+COUNTIF(G37:G61,"GV3")+COUNTIF(G69:G93,"GV3") -> 0 | U25: =((C32+(R26+S26+T26)*0.5)) -> 1799.98 | AD25: =SUM(AE25:AF25) -> 0 | AE25: =SUM(AE22) -> 0 | AF25: =SUM(AP22) -> 0 | AG25: =SUM(AF22+AQ22) -> 0 | AH25: =AG22+AR22 -> 0 | AI25: =SUM(AE25:AH25) -> 0
A26: 22 | J26: =IF(G26="RSL","55","0") -> 0 | K26: =IF(G26="GVS","37.5",IF(G26="GVM","41.5",IF(G26="GVL","50",IF(G26="PCS","45.8",IF(G26="PCM","50",IF(G26="PCL","58.3","0")))))) -> 0 | R26: =R25*37.5 -> 0 | S26: =S25*41.5 -> 0 | T26: =T25*50 -> 0 | X26: Branch cards
A27: 23 | J27: =IF(G27="RSL","55","0") -> 0 | K27: =IF(G27="GVS","37.5",IF(G27="GVM","41.5",IF(G27="GVL","50",IF(G27="PCS","45.8",IF(G27="PCM","50",IF(G27="PCL","58.3","0")))))) -> 0 | R27: Expense | X27: 1 | Z27: -2745
A28: 24 | J28: =IF(G28="RSL","55","0") -> 0 | K28: =IF(G28="GVS","37.5",IF(G28="GVM","41.5",IF(G28="GVL","50",IF(G28="PCS","45.8",IF(G28="PCM","50",IF(G28="PCL","58.3","0")))))) -> 0 | R28: 14164 "NO WASH" | X28: 2
A29: 25 | J29: =IF(G29="RSL","55","0") -> 0 | K29: =IF(G29="GVS","37.5",IF(G29="GVM","41.5",IF(G29="GVL","50",IF(G29="PCS","45.8",IF(G29="PCM","50",IF(G29="PCL","58.3","0")))))) -> 0 | X29: 3
A30: Page total | H30: =SUM(H5:H29) -> 475 | I30: =SUM(I5:I29) -> 850 | J30: =J5+J6+J7+J8+J9+J10+J11+J12+J13+J14+J15+J16+J18+J19+J17+J20+J22+J23+J21+J24+J25+J26+J27+J28+J29 -> 0 | K30: =K5+K6+K7+K8+K9+K10+K11+K12+K13+K14+K15+K16+K18+K19+K17+K20+K22+K23+K21+K24+K25+K26+K27+K28+K29 -> 474.98 | L30: =SUM(L5:L29) -> 0 | M30: =SUM(M5:M29) -> 1525 | N30: CASH | O30: CARD | P30: GV | Q30: RSL | X30: 4
A31: Daily Total | H31: =H30+H62+H94 -> 475 | I31: =I30+I62+I94 -> 850 | J31: =J30+J62+J94 -> 0 | K31: =K30+K62+K94 -> 474.98 | L31: =L30+L62+L94 -> 0 | M31: =M30+M62+M94 -> 1525 | N31: =COUNT(H5:H29,H37:H61,H69:H93) -> 4 | O31: =COUNT(I5:I29,I37:I61,I69:I93) -> 8 | P31: =COUNTIF(G5:G29,"G*")+COUNTIF(G37:G61,"G*")+COUNTIF(G69:G93,"G*")+COUNTIF(G5:G29,"P*")+COUNTIF(G37:G61,"P*")+COUNTIF(G69:G93,"P*") -> 8 | Q31: =COUNTIF(G5:G29,"RSL")+COUNTIF(G37:G61,"RSL")+COUNTIF(G69:G93,"RSL") -> 0 | R31: CASH CLOSING | S31: =H31+L31-U28-U29-U30 -> 475 | T31: =H31+I31+L31+M31 -> 2850 | X31: Subtotal | Z31: =SUM(Z27:Z30) -> -2745
A32: TOTAL SALES | C32: =H31+I31+J31+K31 -> 1799.98 | F32: No of Cars | H32: =COUNT(B5:B29,B37:B61,B69:B93) -> 20 | I32: Average | K32: =C32/H32 -> 89.999 | N32: =H31/C32 -> 0.26389182 | O32: =I31/C32 -> 0.47222747 | P32: =K31/C32 -> 0.26388071 | Q32: =J31/C32 -> 0 | R32: CARD CLOSING | S32: =I31+M31 -> 2375 | X32: B2 card | Z32: =I31 -> 850
A33: Daily Report | X33: Settlement | Z33: =SUM(Z31:Z32) -> -1895
A34: =A2 -> 44993 | H34: WEATHER | J34: =J2 -> SUNNY | L34: REPORT by | O34: =O2 -> HENDRA | R34: TOTAL STAFF | T34: =T2 -> 5
A36: No | B36: Docket No | C36: Reg No | D36: Mobile | E36: Gender | F36: TIME | G36: Service | H36: CASH | I36: CARD | J36: RSL | K36: GV | L36: GV CASH | M36: GV CARD | N36: O/Taker | O36: Comment | R36: NAME | S36: Time In | T36: Time out | U36: Total Hours
A37: =A29+1 -> 26 | J37: =IF(G37="RSL","55","0") -> 0 | K37: =IF(G37="GVS","37.5",IF(G37="GVM","41.5",IF(G37="GVL","50",IF(G37="PCS","45.8",IF(G37="PCM","50",IF(G37="PCL","58.3","0")))))) -> 0
A38: =A37+1 -> 27 | J38: =IF(G38="RSL","55","0") -> 0 | K38: =IF(G38="GVS","37.5",IF(G38="GVM","41.5",IF(G38="GVL","50",IF(G38="PCS","45.8",IF(G38="PCM","50",IF(G38="PCL","58.3","0")))))) -> 0
A39: =A38+1 -> 28 | J39: =IF(G39="RSL","55","0") -> 0 | K39: =IF(G39="GVS","37.5",IF(G39="GVM","41.5",IF(G39="GVL","50",IF(G39="PCS","45.8",IF(G39="PCM","50",IF(G39="PCL","58.3","0")))))) -> 0
A40: =A39+1 -> 29 | J40: =IF(G40="RSL","55","0") -> 0 | K40: =IF(G40="GVS","37.5",IF(G40="GVM","41.5",IF(G40="GVL","50",IF(G40="PCS","45.8",IF(G40="PCM","50",IF(G40="PCL","58.3","0")))))) -> 0
A41: =A40+1 -> 30 | J41: =IF(G41="RSL","55","0") -> 0 | K41: =IF(G41="GVS","37.5",IF(G41="GVM","41.5",IF(G41="GVL","50",IF(G41="PCS","45.8",IF(G41="PCM","50",IF(G41="PCL","58.3","0")))))) -> 0
A42: =A41+1 -> 31 | J42: =IF(G42="RSL","55","0") -> 0 | K42: =IF(G42="GVS","37.5",IF(G42="GVM","41.5",IF(G42="GVL","50",IF(G42="PCS","45.8",IF(G42="PCM","50",IF(G42="PCL","58.3","0")))))) -> 0
A43: =A42+1 -> 32 | J43: =IF(G43="RSL","55","0") -> 0 | K43: =IF(G43="GVS","37.5",IF(G43="GVM","41.5",IF(G43="GVL","50",IF(G43="PCS","45.8",IF(G43="PCM","50",IF(G43="PCL","58.3","0")))))) -> 0
A44: =A43+1 -> 33 | J44: =IF(G44="RSL","55","0") -> 0 | K44: =IF(G44="GVS","37.5",IF(G44="GVM","41.5",IF(G44="GVL","50",IF(G44="PCS","45.8",IF(G44="PCM","50",IF(G44="PCL","58.3","0")))))) -> 0
A45: =A44+1 -> 34 | J45: =IF(G45="RSL","55","0") -> 0 | K45: =IF(G45="GVS","37.5",IF(G45="GVM","41.5",IF(G45="GVL","50",IF(G45="PCS","45.8",IF(G45="PCM","50",IF(G45="PCL","58.3","0")))))) -> 0
A46: =A45+1 -> 35 | J46: =IF(G46="RSL","55","0") -> 0 | K46: =IF(G46="GVS","37.5",IF(G46="GVM","41.5",IF(G46="GVL","50",IF(G46="PCS","45.8",IF(G46="PCM","50",IF(G46="PCL","58.3","0")))))) -> 0
A47: =A46+1 -> 36 | J47: =IF(G47="RSL","55","0") -> 0 | K47: =IF(G47="GVS","37.5",IF(G47="GVM","41.5",IF(G47="GVL","50",IF(G47="PCS","45.8",IF(G47="PCM","50",IF(G47="PCL","58.3","0")))))) -> 0
A48: =A47+1 -> 37 | J48: =IF(G48="RSL","55","0") -> 0 | K48: =IF(G48="GVS","37.5",IF(G48="GVM","41.5",IF(G48="GVL","50",IF(G48="PCS","45.8",IF(G48="PCM","50",IF(G48="PCL","58.3","0")))))) -> 0
A49: =A48+1 -> 38 | J49: =IF(G49="RSL","55","0") -> 0 | K49: =IF(G49="GVS","37.5",IF(G49="GVM","41.5",IF(G49="GVL","50",IF(G49="PCS","45.8",IF(G49="PCM","50",IF(G49="PCL","58.3","0")))))) -> 0
... A61: =A60+1 -> 50 | J61: =IF(G61="RSL","55","0") -> 0 | K61: =IF(G61="GVS","37.5",IF(G61="GVM","41.5",IF(G61="GVL","50",IF(G61="PCS","45.8",IF(G61="PCM","50",IF(G61="PCL","58.3","0")))))) -> 0
A62: Page total | H62: =SUM(H37:H61) -> 0 | I62: =SUM(I37:I61) -> 0 | J62: =J61+J60+J59+J58+J57+J56+J55+J54+J53+J52+J51+J50+J49+J48+J47+J46+J45+J44+J43+J42+J41+J40+J39+J38+J37 -> 0 | K62: =K61+K60+K59+K58+K57+K56+K55+K54+K53+K52+K51+K50+K49+K48+K47+K46+K45+K44+K43+K42+K41+K40+K39+K38+K37 -> 0 | L62: =SUM(L37:L61) -> 0 | M62: =SUM(M37:M61) -> 0
R64: Page: 2
A65: Daily Report
A66: =A34 -> 44993 | H66: WEATHER | J66: =J34 -> SUNNY | L66: REPORT by | O66: =O34 -> HENDRA | R66: TOTAL STAFF | T66: =T34 -> 5
A68: No | B68: Docket No | C68: Reg No | D68: Mobile | E68: Gender | F68: TIME | G68: Service | H68: CASH | I68: CARD | J68: RSL | K68: GV | L68: GV CASH | M68: GV CARD | N68: O/Taker | O68: Comment | R68: NAME | S68: Time In | T68: Time out | U68: Total Hours
A69: =A61+1 -> 51 | J69: =IF(G69="RSL","55","0") -> 0 | K69: =IF(G69="GVS","37.5",IF(G69="GVM","41.5",IF(G69="GVL","50",IF(G69="PCS","45.8",IF(G69="PCM","50",IF(G69="PCL","58.3","0")))))) -> 0
A70: =A69+1 -> 52 | J70: =IF(G70="RSL","55","0") -> 0 | K70: =IF(G70="GVS","37.5",IF(G70="GVM","41.5",IF(G70="GVL","50",IF(G70="PCS","45.8",IF(G70="PCM","50",IF(G70="PCL","58.3","0")))))) -> 0
A71: =A70+1 -> 53 | J71: =IF(G71="RSL","55","0") -> 0 | K71: =IF(G71="GVS","37.5",IF(G71="GVM","41.5",IF(G71="GVL","50",IF(G71="PCS","45.8",IF(G71="PCM","50",IF(G71="PCL","58.3","0")))))) -> 0
A72: =A71+1 -> 54 | J72: =IF(G72="RSL","55","0") -> 0 | K72: =IF(G72="GVS","37.5",IF(G72="GVM","41.5",IF(G72="GVL","50",IF(G72="PCS","45.8",IF(G72="PCM","50",IF(G72="PCL","58.3","0")))))) -> 0
A73: =A72+1 -> 55 | J73: =IF(G73="RSL","55","0") -> 0 | K73: =IF(G73="GVS","37.5",IF(G73="GVM","41.5",IF(G73="GVL","50",IF(G73="PCS","45.8",IF(G73="PCM","50",IF(G73="PCL","58.3","0")))))) -> 0
A74: =A73+1 -> 56 | J74: =IF(G74="RSL","55","0") -> 0 | K74: =IF(G74="GVS","37.5",IF(G74="GVM","41.5",IF(G74="GVL","50",IF(G74="PCS","45.8",IF(G74="PCM","50",IF(G74="PCL","58.3","0")))))) -> 0
A75: =A74+1 -> 57 | J75: =IF(G75="RSL","55","0") -> 0 | K75: =IF(G75="GVS","37.5",IF(G75="GVM","41.5",IF(G75="GVL","50",IF(G75="PCS","45.8",IF(G75="PCM","50",IF(G75="PCL","58.3","0")))))) -> 0
A76: =A75+1 -> 58 | J76: =IF(G76="RSL","55","0") -> 0 | K76: =IF(G76="GVS","37.5",IF(G76="GVM","41.5",IF(G76="GVL","50",IF(G76="PCS","45.8",IF(G76="PCM","50",IF(G76="PCL","58.3","0")))))) -> 0
A77: =A76+1 -> 59 | J77: =IF(G77="RSL","55","0") -> 0 | K77: =IF(G77="GVS","37.5",IF(G77="GVM","41.5",IF(G77="GVL","50",IF(G77="PCS","45.8",IF(G77="PCM","50",IF(G77="PCL","58.3","0")))))) -> 0
A78: =A77+1 -> 60 | J78: =IF(G78="RSL","55","0") -> 0 | K78: =IF(G78="GVS","37.5",IF(G78="GVM","41.5",IF(G78="GVL","50",IF(G78="PCS","45.8",IF(G78="PCM","50",IF(G78="PCL","58.3","0")))))) -> 0
A79: =A78+1 -> 61 | J79: =IF(G79="RSL","55","0") -> 0 | K79: =IF(G79="GVS","37.5",IF(G79="GVM","41.5",IF(G79="GVL","50",IF(G79="PCS","45.8",IF(G79="PCM","50",IF(G79="PCL","58.3","0")))))) -> 0
A80: =A79+1 -> 62 | J80: =IF(G80="RSL","55","0") -> 0 | K80: =IF(G80="GVS","37.5",IF(G80="GVM","41.5",IF(G80="GVL","50",IF(G80="PCS","45.8",IF(G80="PCM","50",IF(G80="PCL","58.3","0")))))) -> 0
A81: =A80+1 -> 63 | J81: =IF(G81="RSL","55","0") -> 0 | K81: =IF(G81="GVS","37.5",IF(G81="GVM","41.5",IF(G81="GVL","50",IF(G81="PCS","45.8",IF(G81="PCM","50",IF(G81="PCL","58.3","0")))))) -> 0
... A93: =A92+1 -> 75 | J93: =IF(G93="RSL","55","0") -> 0 | K93: =IF(G93="GVS","37.5",IF(G93="GVM","41.5",IF(G93="GVL","50",IF(G93="PCS","45.8",IF(G93="PCM","50",IF(G93="PCL","58.3","0")))))) -> 0
A94: Page total | H94: =SUM(H69:H93) -> 0 | I94: =SUM(I69:I93) -> 0 | J94: =J93+J92+J91+J90+J89+J88+J87+J86+J85+J84+J83+J82+J81+J80+J79+J78+J77+J76+J75+J74+J73+J72+J71+J70+J69 -> 0 | K94: =K93+K92+K91+K90+K89+K88+K87+K86+K85+K84+K83+K82+K81+K80+K79+K78+K77+K76+K75+K74+K73+K72+K71+K70+K69 -> 0 | L94: =SUM(L69:L93) -> 0 | M94: =SUM(M69:M93) -> 0
R96: Page: 3

Sheet THU
A1: B2 Daily Report
A2: 44994 | H2: WEATHER | J2: SUNNY | L2: REPORT BY | O2: HENDRA | R2: TOTAL STAFF | T2: 6 | X2: Merchant machine usage at B2 | AA2: Settle amount | AI2: Merchant machine usage at GA | AL2: Settle amount
A4: No | B4: Docket No | C4: Reg No | D4: Mobile | E4: Gender | F4: TIME | G4: Service | H4: CASH | I4: CARD | J4: RSL | K4: GV | L4: GV CASH | M4: GV CARD | N4: O/Taker | O4: Comment | R4: NAME | S4: Time In | T4: Time out | U4: Total Hours | Z4: B2 machine | AA4: BLH machine | AB4: Wongo | AE4: B2 machine | AF4: BLH machine | AG4: Wongo | AK4: GA machine | AL4: BLH machine | AM4: Wongo | AP4: GA machine | AQ4: BLH machine | AR4: Wongo
A5: 1 | B5: 14182 | C5: BE11EW | D5: 0410626003 | E5: F | F5: 900 | G5: PCS | J5: =IF(G5="RSL","55","0") -> 0 | K5: 62.5 | N5: HENDRA | O5: 22080(2/6) | R5: HENDRA | S5: 0.33333333 | T5: 0.77083333 | U5: =(T5-S5)*24 -> 10.5 | X5: NOV | Y5: 1 | AD5: 16 | AI5: NOV | AJ5: 1 | AO5: 16
A6: 2 | B6: 14183 | C6: GBI | D6: 0415888891 | E6: M | F6: 910 | G6: H | H6: 150 | J6: =IF(G6="RSL","55","0") -> 0 | K6: =IF(G6="GVS","37.5",IF(G6="GVM","41.5",IF(G6="GVL","50",IF(G6="PCS","45.8",IF(G6="PCM","50",IF(G6="PCL","58.3","0")))))) -> 0 | N6: HENDRA | O6: GEORGE CAR | R6: ATET | S6: 0.375 | T6: 0.70833333 | U6: =(T6-S6)*24 -> 8 | W6: M | Y6: 2 | AD6: 17 | AJ6: 2 | AO6: 17
A7: 3 | B7: 14184 | C7: CRQ96X | D7: 0408062082 | E7: F | F7: 920 | G7: D | H7: 75 | J7: =IF(G7="RSL","55","0") -> 0 | K7: =IF(G7="GVS","37.5",IF(G7="GVM","41.5",IF(G7="GVL","50",IF(G7="PCS","45.8",IF(G7="PCM","50",IF(G7="PCL","58.3","0")))))) -> 0 | N7: ATET | R7: ARIANTO | S7: 0.35416667 | T7: 0.66666667 | U7: =(T7-S7)*24 -> 7.5 | W7: F | Y7: 3 | AD7: 18 | AJ7: 3 | AO7: 18
A8: 4 | B8: 14185 | C8: 88 LIAM | D8: 0401795858 | E8: M | F8: 1000 | G8: GV | J8: =IF(G8="RSL","55","0") -> 0 | K8: 0 | L8: 350 | N8: ATET | O8: XD50-355 -361 | R8: MODI | S8: 0.41666667 | T8: 0.64583333 | U8: =(T8-S8)*24 -> 5.5 | Y8: 4 | AD8: 19 | AJ8: 4 | AO8: 19
A9: 5 | B9: 14186 | C9: EOK70F | D9: 0419236787 | E9: F | F9: 1015 | G9: X | I9: 95 | J9: =IF(G9="RSL","55","0") -> 0 | K9: =IF(G9="GVS","37.5",IF(G9="GVM","41.5",IF(G9="GVL","50",IF(G9="PCS","45.8",IF(G9="PCM","50",IF(G9="PCL","58.3","0")))))) -> 0 | N9: ATET | R9: TONY ENKHBAT | S9: 0.54166667 | T9: 0.70833333 | U9: =(T9-S9)*24 -> 4 | X9: EXCL RSL | Y9: 5 | AD9: 20 | AJ9: 5 | AO9: 20
A10: 6 | B10: 14187 | C10: EMJ32S | D10: 0478844282 | E10: F | F10: 1030 | G10: D | I10: 75 | J10: =IF(G10="RSL","55","0") -> 0 | K10: =IF(G10="GVS","37.5",IF(G10="GVM","41.5",IF(G10="GVL","50",IF(G10="PCS","45.8",IF(G10="PCM","50",IF(G10="PCL","58.3","0")))))) -> 0 | N10: ATET | R10: ANDREW OCTEC | S10: 0.5 | T10: 0.70833333 | U10: =(T10-S10)*24 -> 5 | Y10: 6 | AD10: 21 | AJ10: 6 | AO10: 21
A11: 7 | B11: 14188 | C11: 13013 | D11: 0433216826 | E11: F | F11: 1100 | G11: X | H11: 75 | J11: =IF(G11="RSL","55","0") -> 0 | K11: =IF(G11="GVS","37.5",IF(G11="GVM","41.5",IF(G11="GVL","50",IF(G11="PCS","45.8",IF(G11="PCM","50",IF(G11="PCL","58.3","0")))))) -> 0 | N11: ATET | U11: =(T11-S11)*24 -> 0 | Y11: 7 | AD11: 22 | AJ11: 7 | AO11: 22
A12: 8 | B12: 14189 | C12: NCA82M | D12: 0439988228 | E12: F | F12: 1115 | G12: PCL | J12: =IF(G12="RSL","55","0") -> 0 | K12: 108.33 | L12: 650 | N12: ATET | O12: 22079(6/6),23227(NEW) | U12: =(T12-S12)*24 -> 0 | Y12: 8 | AD12: 23 | AJ12: 8 | AO12: 23
A13: 9 | B13: 14190 | C13: TT3388 | D13: 0418679112 | E13: M | F13: 1130 | G13: PCS | J13: =IF(G13="RSL","55","0") -> 0 | K13: 62.5 | N13: ATET | O13: 22059(4/6) | U13: =(T13-S13)*24 -> 0 | Y13: 9 | AD13: 24 | AJ13: 9 | AO13: 24
A14: 10 | B14: 14191 | C14: BFY92W | D14: 0411464642 | E14: M | F14: 1130 | G14: D | I14: 75 | J14: =IF(G14="RSL","55","0") -> 0 | K14: =IF(G14="GVS","37.5",IF(G14="GVM","41.5",IF(G14="GVL","50",IF(G14="PCS","45.8",IF(G14="PCM","50",IF(G14="PCL","58.3","0")))))) -> 0 | N14: ATET | U14: =(T14-S14)*24 -> 0 | Y14: 10 | AD14: 25 | AJ14: 10 | AO14: 25
A15: 11 | B15: 14192 | C15: DZS82K | D15: 0411277388 | E15: M | F15: 1145 | G15: D | H15: 75 | J15: =IF(G15="RSL","55","0") -> 0 | K15: =IF(G15="GVS","37.5",IF(G15="GVM","41.5",IF(G15="GVL","50",IF(G15="PCS","45.8",IF(G15="PCM","50",IF(G15="PCL","58.3","0")))))) -> 0 | N15: ATET | U15: =(T15-S15)*24 -> 0 | Y15: 11 | AD15: 26 | AJ15: 11 | AO15: 26
A16: 12 | B16: 14193 | C16: SL6666 | D16: 0415190683 | E16: M | F16: 1230 | G16: PCL | J16: =IF(G16="RSL","55","0") -> 0 | K16: 79.16 | N16: ATET | O16: 22099(2/6) | R16: =H32/U16 -> 0.51851852 | S16: =H32/(U16-U5) -> 0.7 | T16: =C32/U16 -> 40.802222 | U16: =SUM(U5:U15) -> 40.5 | Y16: 12 | AD16: 27 | AJ16: 12 | AO16: 27
A17: 13 | B17: 14194 | C17: EPE21C | D17: 0438354090 | E17: F | F17: 1200 | G17: GV | J17: =IF(G17="RSL","55","0") -> 0 | K17: 0 | M17: 300 | N17: ATET | O17: XD50-362-367 | R17: Cars/T Hr ① | S17: Cars/T Hr ② | T17: Sales/T Hr | U17: Total Hours | Y17: 13 | AD17: 28 | AJ17: 13 | AO17: 28
A18: 14 | B18: 14195 | C18: ECV02N | D18: 0439645062 | E18: M | F18: 1300 | G18: S/D | I18: 250 | J18: =IF(G18="RSL","55","0") -> 0 | K18: =IF(G18="GVS","37.5",IF(G18="GVM","41.5",IF(G18="GVL","50",IF(G18="PCS","45.8",IF(G18="PCM","50",IF(G18="PCL","58.3","0")))))) -> 0 | N18: ATET | R18: ITEM | S18: QTY | T18: AMT | U18: RMKS | Y18: 14 | AD18: 29 | AJ18: 14 | AO18: 29
A19: 15 | B19: 14196 | C19: DTN05N | D19: 0404889042 | E19: F | F19: 1300 | G19: X | I19: 75 | J19: =IF(G19="RSL","55","0") -> 0 | K19: =IF(G19="GVS","37.5",IF(G19="GVM","41.5",IF(G19="GVL","50",IF(G19="PCS","45.8",IF(G19="PCM","50",IF(G19="PCL","58.3","0")))))) -> 0 | N19: ATET | R19: GV | S19: =COUNT(L5:M29,L37:M61,L69:M93) -> 5 | T19: =SUM(L5:M29,L37:M61,L69:M93) -> 1950 | Y19: 15 | AD19: 30 | AJ19: 15 | AO19: 30
A20: 16 | B20: 14197 | C20: CSQ63P | D20: 0415915465 | E20: F | F20: 1300 | G20: D | I20: 75 | J20: =IF(G20="RSL","55","0") -> 0 | K20: =IF(G20="GVS","37.5",IF(G20="GVM","41.5",IF(G20="GVL","50",IF(G20="PCS","45.8",IF(G20="PCM","50",IF(G20="PCL","58.3","0")))))) -> 0 | N20: ATET | AD20: 31 | AO20: 31
A21: 17 | B21: 14198 | C21: NRM058 | D21: 0448441099 | E21: F | F21: 1315 | G21: GV | J21: =IF(G21="RSL","55","0") -> 0 | K21: 125 | M21: 350 | N21: ATET | O21: XD50-368-374
A22: 18 | B22: 14199 | C22: BKO36F | D22: 0411757862 | E22: F | F22: 1330 | G22: D | I22: 55 | J22: =IF(G22="RSL","55","0") -> 0 | K22: =IF(G22="GVS","37.5",IF(G22="GVM","41.5",IF(G22="GVL","50",IF(G22="PCS","45.8",IF(G22="PCM","50",IF(G22="PCL","58.3","0")))))) -> 0 | N22: ATET | AD22: Total | AE22: =SUM(Z5:Z19,AE5:AE20) -> 0 | AF22: =SUM(AA5:AA19,AF5:AF20,) -> 0 | AG22: =SUM(AB5:AB19,AG5:AG20) -> 0 | AO22: Total | AP22: =SUM(AK5:AK19,AP5:AP20) -> 0 | AQ22: =SUM(AL5:AL19,AQ5:AQ20,) -> 0 | AR22: =SUM(AM5:AM19,AR5:AR20) -> 0
A23: 19 | B23: 14200 | C23: CDP596 | D23: 0408228252 | E23: F | F23: 1415 | G23: D | I23: 65 | J23: =IF(G23="RSL","55","0") -> 0 | K23: =IF(G23="GVS","37.5",IF(G23="GVM","41.5",IF(G23="GVL","50",IF(G23="PCS","45.8",IF(G23="PCM","50",IF(G23="PCL","58.3","0")))))) -> 0 | N23: ATET | O23: B2809-810 $10 OFF
A24: 20 | B24: 14201 | C24: CRV58P | D24: 0402018402 | E24: F | F24: 1415 | G24: GV | J24: =IF(G24="RSL","55","0") -> 0 | K24: 0 | M24: 300 | N24: ATET | O24: XD50-375-380 | R24: SMALL | S24: MEDIUM | T24: LARGE | U24: TOTAL | AD24: B2/GA TOTAL | AE24: B2 machine | AF24: GA machine | AG24: BLH machine | AH24: Wongo machine | AI24: Sub total
A25: 21 | B25: 14202 | C25: AY63UN | D25: 0431366591 | E25: M | F25: 1430 | G25: X | I25: 75 | J25: =IF(G25="RSL","55","0") -> 0 | K25: =IF(G25="GVS","37.5",IF(G25="GVM","41.5",IF(G25="GVL","50",IF(G25="PCS","45.8",IF(G25="PCM","50",IF(G25="PCL","58.3","0")))))) -> 0 | N25: ATET | O25: BOOKING ONLINE | R25: =COUNTIF(G5:G29,"GV1")+COUNTIF(G37:G61,"GV1")+COUNTIF(G69:G93,"GV1") -> 0 | S25: =COUNTIF(G5:G29,"GV2")+COUNTIF(G37:G61,"GV2")+COUNTIF(G69:G93,"GV2") -> 0 | T25: =COUNTIF(G5:G29,"GV3")+COUNTIF(G37:G61,"GV3")+COUNTIF(G69:G93,"GV3") -> 0 | U25: =((C32+(R26+S26+T26)*0.5)) -> 1652.49 | AD25: =SUM(AE25:AF25) -> 0 | AE25: =SUM(AE22) -> 0 | AF25: =SUM(AP22) -> 0 | AG25: =SUM(AF22+AQ22) -> 0 | AH25: =AG22+AR22 -> 0 | AI25: =SUM(AE25:AH25) -> 0
A26: 22 | J26: =IF(G26="RSL","55","0") -> 0 | K26: =IF(G26="GVS","37.5",IF(G26="GVM","41.5",IF(G26="GVL","50",IF(G26="PCS","45.8",IF(G26="PCM","50",IF(G26="PCL","58.3","0")))))) -> 0 | R26: =R25*37.5 -> 0 | S26: =S25*41.5 -> 0 | T26: =T25*50 -> 0 | X26: Branch cards
A27: 23 | J27: =IF(G27="RSL","55","0") -> 0 | K27: =IF(G27="GVS","37.5",IF(G27="GVM","41.5",IF(G27="GVL","50",IF(G27="PCS","45.8",IF(G27="PCM","50",IF(G27="PCL","58.3","0")))))) -> 0 | R27: Expense | X27: 1 | Z27: -2745
A28: 24 | J28: =IF(G28="RSL","55","0") -> 0 | K28: =IF(G28="GVS","37.5",IF(G28="GVM","41.5",IF(G28="GVL","50",IF(G28="PCS","45.8",IF(G28="PCM","50",IF(G28="PCL","58.3","0")))))) -> 0 | R28: 14198 : XD50-368 USE | X28: 2
A29: 25 | J29: =IF(G29="RSL","55","0") -> 0 | K29: =IF(G29="GVS","37.5",IF(G29="GVM","41.5",IF(G29="GVL","50",IF(G29="PCS","45.8",IF(G29="PCM","50",IF(G29="PCL","58.3","0")))))) -> 0 | X29: 3
A30: Page total | H30: =SUM(H5:H29) -> 375 | I30: =SUM(I5:I29) -> 840 | J30: =J5+J6+J7+J8+J9+J10+J11+J12+J13+J14+J15+J16+J18+J19+J17+J20+J22+J23+J21+J24+J25+J26+J27+J28+J29 -> 0 | K30: =K5+K6+K7+K8+K9+K10+K11+K12+K13+K14+K15+K16+K18+K19+K17+K20+K22+K23+K21+K24+K25+K26+K27+K28+K29 -> 437.49 | L30: =SUM(L5:L29) -> 1000 | M30: =SUM(M5:M29) -> 950 | N30: CASH | O30: CARD | P30: GV | Q30: RSL | X30: 4
A31: Daily Total | H31: =H30+H62+H94 -> 375 | I31: =I30+I62+I94 -> 840 | J31: =J30+J62+J94 -> 0 | K31: =K30+K62+K94 -> 437.49 | L31: =L30+L62+L94 -> 1000 | M31: =M30+M62+M94 -> 950 | N31: =COUNT(H5:H29,H37:H61,H69:H93) -> 4 | O31: =COUNT(I5:I29,I37:I61,I69:I93) -> 9 | P31: =COUNTIF(G5:G29,"G*")+COUNTIF(G37:G61,"G*")+COUNTIF(G69:G93,"G*")+COUNTIF(G5:G29,"P*")+COUNTIF(G37:G61,"P*")+COUNTIF(G69:G93,"P*") -> 8 | Q31: =COUNTIF(G5:G29,"RSL")+COUNTIF(G37:G61,"RSL")+COUNTIF(G69:G93,"RSL") -> 0 | R31: CASH CLOSING | S31: =H31+L31-U28-U29-U30 -> 1375 | T31: =H31+I31+L31+M31 -> 3165 | X31: Subtotal | Z31: =SUM(Z27:Z30) -> -2745
A32: TOTAL SALES | C32: =H31+I31+J31+K31 -> 1652.49 | F32: No of Cars | H32: =COUNT(B5:B29,B37:B61,B69:B93) -> 21 | I32: Average | K32: =C32/H32 -> 78.69 | N32: =H31/C32 -> 0.22693027 | O32: =I31/C32 -> 0.5083238 | P32: =K31/C32 -> 0.26474593 | Q32: =J31/C32 -> 0 | R32: CARD CLOSING | S32: =I31+M31 -> 1790 | X32: B2 card | Z32: =I31 -> 840
A33: Daily Report | X33: Settlement | Z33: =SUM(Z31:Z32) -> -1905
A34: =A2 -> 44994 | H34: WEATHER | J34: =J2 -> SUNNY | L34: REPORT by | O34: =O2 -> HENDRA | R34: TOTAL STAFF | T34: =T2 -> 6
A36: No | B36: Docket No | C36: Reg No | D36: Mobile | E36: Gender | F36: TIME | G36: Service | H36: CASH | I36: CARD | J36: RSL | K36: GV | L36: GV CASH | M36: GV CARD | N36: O/Taker | O36: Comment | R36: NAME | S36: Time In | T36: Time out | U36: Total Hours
A37: =A29+1 -> 26 | J37: =IF(G37="RSL","55","0") -> 0 | K37: =IF(G37="GVS","37.5",IF(G37="GVM","41.5",IF(G37="GVL","50",IF(G37="PCS","45.8",IF(G37="PCM","50",IF(G37="PCL","58.3","0")))))) -> 0
A38: =A37+1 -> 27 | J38: =IF(G38="RSL","55","0") -> 0 | K38: =IF(G38="GVS","37.5",IF(G38="GVM","41.5",IF(G38="GVL","50",IF(G38="PCS","45.8",IF(G38="PCM","50",IF(G38="PCL","58.3","0")))))) -> 0
A39: =A38+1 -> 28 | J39: =IF(G39="RSL","55","0") -> 0 | K39: =IF(G39="GVS","37.5",IF(G39="GVM","41.5",IF(G39="GVL","50",IF(G39="PCS","45.8",IF(G39="PCM","50",IF(G39="PCL","58.3","0")))))) -> 0
A40: =A39+1 -> 29 | J40: =IF(G40="RSL","55","0") -> 0 | K40: =IF(G40="GVS","37.5",IF(G40="GVM","41.5",IF(G40="GVL","50",IF(G40="PCS","45.8",IF(G40="PCM","50",IF(G40="PCL","58.3","0")))))) -> 0
A41: =A40+1 -> 30 | J41: =IF(G41="RSL","55","0") -> 0 | K41: =IF(G41="GVS","37.5",IF(G41="GVM","41.5",IF(G41="GVL","50",IF(G41="PCS","45.8",IF(G41="PCM","50",IF(G41="PCL","58.3","0")))))) -> 0
A42: =A41+1 -> 31 | J42: =IF(G42="RSL","55","0") -> 0 | K42: =IF(G42="GVS","37.5",IF(G42="GVM","41.5",IF(G42="GVL","50",IF(G42="PCS","45.8",IF(G42="PCM","50",IF(G42="PCL","58.3","0")))))) -> 0
A43: =A42+1 -> 32 | J43: =IF(G43="RSL","55","0") -> 0 | K43: =IF(G43="GVS","37.5",IF(G43="GVM","41.5",IF(G43="GVL","50",IF(G43="PCS","45.8",IF(G43="PCM","50",IF(G43="PCL","58.3","0")))))) -> 0
A44: =A43+1 -> 33 | J44: =IF(G44="RSL","55","0") -> 0 | K44: =IF(G44="GVS","37.5",IF(G44="GVM","41.5",IF(G44="GVL","50",IF(G44="PCS","45.8",IF(G44="PCM","50",IF(G44="PCL","58.3","0")))))) -> 0
A45: =A44+1 -> 34 | J45: =IF(G45="RSL","55","0") -> 0 | K45: =IF(G45="GVS","37.5",IF(G45="GVM","41.5",IF(G45="GVL","50",IF(G45="PCS","45.8",IF(G45="PCM","50",IF(G45="PCL","58.3","0")))))) -> 0
A46: =A45+1 -> 35 | J46: =IF(G46="RSL","55","0") -> 0 | K46: =IF(G46="GVS","37.5",IF(G46="GVM","41.5",IF(G46="GVL","50",IF(G46="PCS","45.8",IF(G46="PCM","50",IF(G46="PCL","58.3","0")))))) -> 0
A47: =A46+1 -> 36 | J47: =IF(G47="RSL","55","0") -> 0 | K47: =IF(G47="GVS","37.5",IF(G47="GVM","41.5",IF(G47="GVL","50",IF(G47="PCS","45.8",IF(G47="PCM","50",IF(G47="PCL","58.3","0")))))) -> 0
A48: =A47+1 -> 37 | J48: =IF(G48="RSL","55","0") -> 0 | K48: =IF(G48="GVS","37.5",IF(G48="GVM","41.5",IF(G48="GVL","50",IF(G48="PCS","45.8",IF(G48="PCM","50",IF(G48="PCL","58.3","0")))))) -> 0
A49: =A48+1 -> 38 | J49: =IF(G49="RSL","55","0") -> 0 | K49: =IF(G49="GVS","37.5",IF(G49="GVM","41.5",IF(G49="GVL","50",IF(G49="PCS","45.8",IF(G49="PCM","50",IF(G49="PCL","58.3","0")))))) -> 0
... A61: =A60+1 -> 50 | J61: =IF(G61="RSL","55","0") -> 0 | K61: =IF(G61="GVS","37.5",IF(G61="GVM","41.5",IF(G61="GVL","50",IF(G61="PCS","45.8",IF(G61="PCM","50",IF(G61="PCL","58.3","0")))))) -> 0
A62: Page total | H62: =SUM(H37:H61) -> 0 | I62: =SUM(I37:I61) -> 0 | J62: =J61+J60+J59+J58+J57+J56+J55+J54+J53+J52+J51+J50+J49+J48+J47+J46+J45+J44+J43+J42+J41+J40+J39+J38+J37 -> 0 | K62: =K61+K60+K59+K58+K57+K56+K55+K54+K53+K52+K51+K50+K49+K48+K47+K46+K45+K44+K43+K42+K41+K40+K39+K38+K37 -> 0 | L62: =SUM(L37:L61) -> 0 | M62: =SUM(M37:M61) -> 0
R64: Page: 2
A65: Daily Report
A66: =A34 -> 44994 | H66: WEATHER | J66: =J34 -> SUNNY | L66: REPORT by | O66: =O34 -> HENDRA | R66: TOTAL STAFF | T66: =T34 -> 6
A68: No | B68: Docket No | C68: Reg No | D68: Mobile | E68: Gender | F68: TIME | G68: Service | H68: CASH | I68: CARD | J68: RSL | K68: GV | L68: GV CASH | M68: GV CARD | N68: O/Taker | O68: Comment | R68: NAME | S68: Time In | T68: Time out | U68: Total Hours
A69: =A61+1 -> 51 | J69: =IF(G69="RSL","55","0") -> 0 | K69: =IF(G69="GVS","37.5",IF(G69="GVM","41.5",IF(G69="GVL","50",IF(G69="PCS","45.8",IF(G69="PCM","50",IF(G69="PCL","58.3","0")))))) -> 0
A70: =A69+1 -> 52 | J70: =IF(G70="RSL","55","0") -> 0 | K70: =IF(G70="GVS","37.5",IF(G70="GVM","41.5",IF(G70="GVL","50",IF(G70="PCS","45.8",IF(G70="PCM","50",IF(G70="PCL","58.3","0")))))) -> 0
A71: =A70+1 -> 53 | J71: =IF(G71="RSL","55","0") -> 0 | K71: =IF(G71="GVS","37.5",IF(G71="GVM","41.5",IF(G71="GVL","50",IF(G71="PCS","45.8",IF(G71="PCM","50",IF(G71="PCL","58.3","0")))))) -> 0
A72: =A71+1 -> 54 | J72: =IF(G72="RSL","55","0") -> 0 | K72: =IF(G72="GVS","37.5",IF(G72="GVM","41.5",IF(G72="GVL","50",IF(G72="PCS","45.8",IF(G72="PCM","50",IF(G72="PCL","58.3","0")))))) -> 0
A73: =A72+1 -> 55 | J73: =IF(G73="RSL","55","0") -> 0 | K73: =IF(G73="GVS","37.5",IF(G73="GVM","41.5",IF(G73="GVL","50",IF(G73="PCS","45.8",IF(G73="PCM","50",IF(G73="PCL","58.3","0")))))) -> 0
A74: =A73+1 -> 56 | J74: =IF(G74="RSL","55","0") -> 0 | K74: =IF(G74="GVS","37.5",IF(G74="GVM","41.5",IF(G74="GVL","50",IF(G74="PCS","45.8",IF(G74="PCM","50",IF(G74="PCL","58.3","0")))))) -> 0
A75: =A74+1 -> 57 | J75: =IF(G75="RSL","55","0") -> 0 | K75: =IF(G75="GVS","37.5",IF(G75="GVM","41.5",IF(G75="GVL","50",IF(G75="PCS","45.8",IF(G75="PCM","50",IF(G75="PCL","58.3","0")))))) -> 0
A76: =A75+1 -> 58 | J76: =IF(G76="RSL","55","0") -> 0 | K76: =IF(G76="GVS","37.5",IF(G76="GVM","41.5",IF(G76="GVL","50",IF(G76="PCS","45.8",IF(G76="PCM","50",IF(G76="PCL","58.3","0")))))) -> 0
A77: =A76+1 -> 59 | J77: =IF(G77="RSL","55","0") -> 0 | K77: =IF(G77="GVS","37.5",IF(G77="GVM","41.5",IF(G77="GVL","50",IF(G77="PCS","45.8",IF(G77="PCM","50",IF(G77="PCL","58.3","0")))))) -> 0
A78: =A77+1 -> 60 | J78: =IF(G78="RSL","55","0") -> 0 | K78: =IF(G78="GVS","37.5",IF(G78="GVM","41.5",IF(G78="GVL","50",IF(G78="PCS","45.8",IF(G78="PCM","50",IF(G78="PCL","58.3","0")))))) -> 0
A79: =A78+1 -> 61 | J79: =IF(G79="RSL","55","0") -> 0 | K79: =IF(G79="GVS","37.5",IF(G79="GVM","41.5",IF(G79="GVL","50",IF(G79="PCS","45.8",IF(G79="PCM","50",IF(G79="PCL","58.3","0")))))) -> 0
A80: =A79+1 -> 62 | J80: =IF(G80="RSL","55","0") -> 0 | K80: =IF(G80="GVS","37.5",IF(G80="GVM","41.5",IF(G80="GVL","50",IF(G80="PCS","45.8",IF(G80="PCM","50",IF(G80="PCL","58.3","0")))))) -> 0
A81: =A80+1 -> 63 | J81: =IF(G81="RSL","55","0") -> 0 | K81: =IF(G81="GVS","37.5",IF(G81="GVM","41.5",IF(G81="GVL","50",IF(G81="PCS","45.8",IF(G81="PCM","50",IF(G81="PCL","58.3","0")))))) -> 0
... A93: =A92+1 -> 75 | J93: =IF(G93="RSL","55","0") -> 0 | K93: =IF(G93="GVS","37.5",IF(G93="GVM","41.5",IF(G93="GVL","50",IF(G93="PCS","45.8",IF(G93="PCM","50",IF(G93="PCL","58.3","0")))))) -> 0
A94: Page total | H94: =SUM(H69:H93) -> 0 | I94: =SUM(I69:I93) -> 0 | J94: =J93+J92+J91+J90+J89+J88+J87+J86+J85+J84+J83+J82+J81+J80+J79+J78+J77+J76+J75+J74+J73+J72+J71+J70+J69 -> 0 | K94: =K93+K92+K91+K90+K89+K88+K87+K86+K85+K84+K83+K82+K81+K80+K79+K78+K77+K76+K75+K74+K73+K72+K71+K70+K69 -> 0 | L94: =SUM(L69:L93) -> 0 | M94: =SUM(M69:M93) -> 0
R96: Page: 3

Sheet FRI
A1: B2 Daily Report
A2: 45202 | H2: WEATHER | J2: SUNNY | L2: REPORT BY | O2: HENDRA | R2: TOTAL STAFF | T2: 5 | X2: Merchant machine usage at B2 | AA2: Settle amount | AI2: Merchant machine usage at GA | AL2: Settle amount
A4: No | B4: Docket No | C4: Reg No | D4: Mobile | E4: Gender | F4: TIME | G4: Service | H4: CASH | I4: CARD | J4: RSL | K4: GV | L4: GV CASH | M4: GV CARD | N4: O/Taker | O4: Comment | R4: NAME | S4: Time In | T4: Time out | U4: Total Hours | Z4: B2 machine | AA4: BLH machine | AB4: Wongo | AE4: B2 machine | AF4: BLH machine | AG4: Wongo | AK4: GA machine | AL4: BLH machine | AM4: Wongo | AP4: GA machine | AQ4: BLH machine | AR4: Wongo
A5: 1 | B5: 14203 | C5: EUH92M | D5: 0413723556 | E5: F | F5: 815 | G5: X | H5: 95 | J5: =IF(G5="RSL","55","0") -> 0 | K5: =IF(G5="GVS","37.5",IF(G5="GVM","41.5",IF(G5="GVL","50",IF(G5="PCS","45.8",IF(G5="PCM","50",IF(G5="PCL","58.3","0")))))) -> 0 | N5: HENDRA | R5: HENDRA | S5: 0.33333333 | T5: 0.70833333 | U5: =(T5-S5)*24 -> 9 | X5: NOV | Y5: 1 | AD5: 16 | AI5: NOV | AJ5: 1 | AO5: 16
A6: 2 | B6: 14204 | C6: YGH59W | D6: 0409714867 | E6: F | F6: 850 | G6: H | H6: 120 | J6: =IF(G6="RSL","55","0") -> 0 | K6: =IF(G6="GVS","37.5",IF(G6="GVM","41.5",IF(G6="GVL","50",IF(G6="PCS","45.8",IF(G6="PCM","50",IF(G6="PCL","58.3","0")))))) -> 0 | N6: HENDRA | R6: KUROSH | S6: 0.375 | T6: 0.70833333 | U6: =(T6-S6)*24 -> 8 | W6: M | Y6: 2 | AD6: 17 | AJ6: 2 | AO6: 17
A7: 3 | B7: 14205 | C7: DYM17V | D7: 0409246512 | E7: F | F7: 900 | G7: X | I7: 95 | J7: =IF(G7="RSL","55","0") -> 0 | K7: =IF(G7="GVS","37.5",IF(G7="GVM","41.5",IF(G7="GVL","50",IF(G7="PCS","45.8",IF(G7="PCM","50",IF(G7="PCL","58.3","0")))))) -> 0 | N7: HENDRA | R7: KADAM | S7: 0.375 | T7: 0.70833333 | U7: =(T7-S7)*24 -> 8 | W7: F | Y7: 3 | AD7: 18 | AJ7: 3 | AO7: 18
A8: 4 | B8: 14206 | C8: COM84M | D8: 0405232880 | E8: F | F8: 930 | G8: PCL | J8: =IF(G8="RSL","55","0") -> 0 | K8: 79.16 | M8: 475 | N8: HENDRA | O8: 22022(5/6), 23228(NEW) | R8: VINNY | S8: 0.41666667 | T8: 0.70833333 | U8: =(T8-S8)*24 -> 7 | Y8: 4 | AD8: 19 | AJ8: 4 | AO8: 19
A9: 5 | B9: 14207 | C9: EHV664 | D9: 0425774597 | E9: F | F9: 930 | G9: H | I9: 120 | J9: =IF(G9="RSL","55","0") -> 0 | K9: =IF(G9="GVS","37.5",IF(G9="GVM","41.5",IF(G9="GVL","50",IF(G9="PCS","45.8",IF(G9="PCM","50",IF(G9="PCL","58.3","0")))))) -> 0 | N9: HENDRA | R9: MODI | S9: 0.41666667 | T9: 0.70833333 | U9: =(T9-S9)*24 -> 7 | X9: EXCL RSL | Y9: 5 | AD9: 20 | AJ9: 5 | AO9: 20
A10: 6 | B10: 14208 | C10: ENI61G | D10: 0451513051 | E10: M | F10: 950 | G10: D | I10: 75 | J10: =IF(G10="RSL","55","0") -> 0 | K10: =IF(G10="GVS","37.5",IF(G10="GVM","41.5",IF(G10="GVL","50",IF(G10="PCS","45.8",IF(G10="PCM","50",IF(G10="PCL","58.3","0")))))) -> 0 | N10: HENDRA | O10: TAX | R10: ANDREW OCTEC | S10: 0.54166667 | T10: 0.70833333 | U10: =(T10-S10)*24 -> 4 | Y10: 6 | AD10: 21 | AJ10: 6 | AO10: 21
A11: 7 | B11: 14209 | C11: BZB84A | D11: 0408969223 | E11: F | F11: 1015 | G11: D | H11: 55 | J11: =IF(G11="RSL","55","0") -> 0 | K11: =IF(G11="GVS","37.5",IF(G11="GVM","41.5",IF(G11="GVL","50",IF(G11="PCS","45.8",IF(G11="PCM","50",IF(G11="PCL","58.3","0")))))) -> 0 | N11: HENDRA | U11: =(T11-S11)*24 -> 0 | Y11: 7 | AD11: 22 | AJ11: 7 | AO11: 22
A12: 8 | B12: 14210 | C12: NBU59C | D12: 0433818333 | E12: F | F12: 1030 | G12: X | H12: 90 | J12: =IF(G12="RSL","55","0") -> 0 | K12: =IF(G12="GVS","37.5",IF(G12="GVM","41.5",IF(G12="GVL","50",IF(G12="PCS","45.8",IF(G12="PCM","50",IF(G12="PCL","58.3","0")))))) -> 0 | N12: HENDRA | O12: $5 OFF | U12: =(T12-S12)*24 -> 0 | Y12: 8 | AD12: 23 | AJ12: 8 | AO12: 23
A13: 9 | B13: 14211 | C13: BVS27Y | D13: 0434979126 | E13: F | F13: 1100 | G13: H | H13: 120 | J13: =IF(G13="RSL","55","0") -> 0 | K13: =IF(G13="GVS","37.5",IF(G13="GVM","41.5",IF(G13="GVL","50",IF(G13="PCS","45.8",IF(G13="PCM","50",IF(G13="PCL","58.3","0")))))) -> 0 | N13: HENDRA | O13: TAX | U13: =(T13-S13)*24 -> 0 | Y13: 9 | AD13: 24 | AJ13: 9 | AO13: 24
A14: 10 | B14: 14212 | C14: DBF89P | D14: 0419694780 | E14: F | F14: 1115 | G14: X | I14: 75 | J14: =IF(G14="RSL","55","0") -> 0 | K14: =IF(G14="GVS","37.5",IF(G14="GVM","41.5",IF(G14="GVL","50",IF(G14="PCS","45.8",IF(G14="PCM","50",IF(G14="PCL","58.3","0")))))) -> 0 | N14: HENDRA | U14: =(T14-S14)*24 -> 0 | Y14: 10 | AD14: 25 | AJ14: 10 | AO14: 25
A15: 11 | B15: 14213 | C15: BGS53V | D15: ???? | E15: F | F15: 1115 | G15: GV | J15: =IF(G15="RSL","55","0") -> 0 | K15: 0 | L15: 350 | N15: VINNY | O15: XD50-381-387 | U15: =(T15-S15)*24 -> 0 | Y15: 11 | AD15: 26 | AJ15: 11 | AO15: 26
A16: 12 | B16: 14214 | C16: EOT07F | D16: 0425337813 | E16: F | F16: 1130 | G16: D | I16: 75 | J16: =IF(G16="RSL","55","0") -> 0 | K16: =IF(G16="GVS","37.5",IF(G16="GVM","41.5",IF(G16="GVL","50",IF(G16="PCS","45.8",IF(G16="PCM","50",IF(G16="PCL","58.3","0")))))) -> 0 | N16: HENDRA | R16: =H32/U16 -> 0.44186047 | S16: =H32/(U16-U5) -> 0.55882353 | T16: =C32/U16 -> 35.852558 | U16: =SUM(U5:U15) -> 43 | Y16: 12 | AD16: 27 | AJ16: 12 | AO16: 27
A17: 13 | B17: 14215 | C17: DDH59A | D17: 0403878036 | E17: F | F17: 1145 | G17: H | I17: 100 | J17: =IF(G17="RSL","55","0") -> 0 | K17: =IF(G17="GVS","37.5",IF(G17="GVM","41.5",IF(G17="GVL","50",IF(G17="PCS","45.8",IF(G17="PCM","50",IF(G17="PCL","58.3","0")))))) -> 0 | N17: HENDRA | R17: Cars/T Hr ① | S17: Cars/T Hr ② | T17: Sales/T Hr | U17: Total Hours | Y17: 13 | AD17: 28 | AJ17: 13 | AO17: 28
A18: 14 | B18: 14216 | C18: WSC44P | D18: 0414130777 | E18: F | F18: 1145 | G18: PCS | J18: =IF(G18="RSL","55","0") -> 0 | K18: 62.5 | N18: HENDRA | O18: 22063(2/6) | R18: ITEM | S18: QTY | T18: AMT | U18: RMKS | Y18: 14 | AD18: 29 | AJ18: 14 | AO18: 29
A19: 15 | B19: 14217 | C19: EIF04E | D19: 0406751366 | E19: F | F19: 1220 | G19: X | H19: 95 | J19: =IF(G19="RSL","55","0") -> 0 | K19: =IF(G19="GVS","37.5",IF(G19="GVM","41.5",IF(G19="GVL","50",IF(G19="PCS","45.8",IF(G19="PCM","50",IF(G19="PCL","58.3","0")))))) -> 0 | N19: VINNY | R19: GV | S19: =COUNT(L5:M29,L37:M61,L69:M93) -> 2 | T19: =SUM(L5:M29,L37:M61,L69:M93) -> 825 | Y19: 15 | AD19: 30 | AJ19: 15 | AO19: 30
A20: 16 | B20: 14218 | C20: DVF41S | D20: 0410742080 | E20: F | F20: 1235 | G20: RSL | J20: 60 | K20: =IF(G20="GVS","37.5",IF(G20="GVM","41.5",IF(G20="GVL","50",IF(G20="PCS","45.8",IF(G20="PCM","50",IF(G20="PCL","58.3","0")))))) -> 0 | N20: HENDRA | O20: CRSL20-011/016/039 (X) | AD20: 31 | AO20: 31
A21: 17 | B21: 14219 | C21: KBS888 | D21: 0431448778 | E21: M | F21: 1345 | G21: D | I21: 55 | J21: =IF(G21="RSL","55","0") -> 0 | K21: =IF(G21="GVS","37.5",IF(G21="GVM","41.5",IF(G21="GVL","50",IF(G21="PCS","45.8",IF(G21="PCM","50",IF(G21="PCL","58.3","0")))))) -> 0 | N21: HENDRA
A22: 18 | B22: 14220 | C22: EMB75G | D22: 0425973686 | E22: F | F22: 1510 | G22: X | I22: 95 | J22: =IF(G22="RSL","55","0") -> 0 | K22: =IF(G22="GVS","37.5",IF(G22="GVM","41.5",IF(G22="GVL","50",IF(G22="PCS","45.8",IF(G22="PCM","50",IF(G22="PCL","58.3","0")))))) -> 0 | N22: VINNY | AD22: Total | AE22: =SUM(Z5:Z19,AE5:AE20) -> 0 | AF22: =SUM(AA5:AA19,AF5:AF20,) -> 0 | AG22: =SUM(AB5:AB19,AG5:AG20) -> 0 | AO22: Total | AP22: =SUM(AK5:AK19,AP5:AP20) -> 0 | AQ22: =SUM(AL5:AL19,AQ5:AQ20,) -> 0 | AR22: =SUM(AM5:AM19,AR5:AR20) -> 0
A23: 19 | B23: 14221 | C23: CDF80J | D23: 0413809541 | E23: F | F23: 1515 | G23: X | I23: 75 | J23: =IF(G23="RSL","55","0") -> 0 | K23: =IF(G23="GVS","37.5",IF(G23="GVM","41.5",IF(G23="GVL","50",IF(G23="PCS","45.8",IF(G23="PCM","50",IF(G23="PCL","58.3","0")))))) -> 0 | N23: HENDRA
A24: 20 | J24: =IF(G24="RSL","55","0") -> 0 | K24: =IF(G24="GVS","37.5",IF(G24="GVM","41.5",IF(G24="GVL","50",IF(G24="PCS","45.8",IF(G24="PCM","50",IF(G24="PCL","58.3","0")))))) -> 0 | R24: SMALL | S24: MEDIUM | T24: LARGE | U24: TOTAL | AD24: B2/GA TOTAL | AE24: B2 machine | AF24: GA machine | AG24: BLH machine | AH24: Wongo machine | AI24: Sub total
A25: 21 | J25: =IF(G25="RSL","55","0") -> 0 | K25: =IF(G25="GVS","37.5",IF(G25="GVM","41.5",IF(G25="GVL","50",IF(G25="PCS","45.8",IF(G25="PCM","50",IF(G25="PCL","58.3","0")))))) -> 0 | R25: =COUNTIF(G5:G29,"GV1")+COUNTIF(G37:G61,"GV1")+COUNTIF(G69:G93,"GV1") -> 0 | S25: =COUNTIF(G5:G29,"GV2")+COUNTIF(G37:G61,"GV2")+COUNTIF(G69:G93,"GV2") -> 0 | T25: =COUNTIF(G5:G29,"GV3")+COUNTIF(G37:G61,"GV3")+COUNTIF(G69:G93,"GV3") -> 0 | U25: =((C32+(R26+S26+T26)*0.5)) -> 1541.66 | AD25: =SUM(AE25:AF25) -> 0 | AE25: =SUM(AE22) -> 0 | AF25: =SUM(AP22) -> 0 | AG25: =SUM(AF22+AQ22) -> 0 | AH25: =AG22+AR22 -> 0 | AI25: =SUM(AE25:AH25) -> 0
A26: 22 | J26: =IF(G26="RSL","55","0") -> 0 | K26: =IF(G26="GVS","37.5",IF(G26="GVM","41.5",IF(G26="GVL","50",IF(G26="PCS","45.8",IF(G26="PCM","50",IF(G26="PCL","58.3","0")))))) -> 0 | R26: =R25*37.5 -> 0 | S26: =S25*41.5 -> 0 | T26: =T25*50 -> 0 | X26: Branch cards
A27: 23 | J27: =IF(G27="RSL","55","0") -> 0 | K27: =IF(G27="GVS","37.5",IF(G27="GVM","41.5",IF(G27="GVL","50",IF(G27="PCS","45.8",IF(G27="PCM","50",IF(G27="PCL","58.3","0")))))) -> 0 | R27: Expense | X27: 1 | Z27: -2745
A28: 24 | J28: =IF(G28="RSL","55","0") -> 0 | K28: =IF(G28="GVS","37.5",IF(G28="GVM","41.5",IF(G28="GVL","50",IF(G28="PCS","45.8",IF(G28="PCM","50",IF(G28="PCL","58.3","0")))))) -> 0 | X28: 2
A29: 25 | J29: =IF(G29="RSL","55","0") -> 0 | K29: =IF(G29="GVS","37.5",IF(G29="GVM","41.5",IF(G29="GVL","50",IF(G29="PCS","45.8",IF(G29="PCM","50",IF(G29="PCL","58.3","0")))))) -> 0 | X29: 3
A30: Page total | H30: =SUM(H5:H29) -> 575 | I30: =SUM(I5:I29) -> 765 | J30: =J5+J6+J7+J8+J9+J10+J11+J12+J13+J14+J15+J16+J18+J19+J17+J20+J22+J23+J21+J24+J25+J26+J27+J28+J29 -> 60 | K30: =K5+K6+K7+K8+K9+K10+K11+K12+K13+K14+K15+K16+K18+K19+K17+K20+K22+K23+K21+K24+K25+K26+K27+K28+K29 -> 141.66 | L30: =SUM(L5:L29) -> 350 | M30: =SUM(M5:M29) -> 475 | N30: CASH | O30: CARD | P30: GV | Q30: RSL | X30: 4
A31: Daily Total | H31: =H30+H62+H94 -> 575 | I31: =I30+I62+I94 -> 765 | J31: =J30+J62+J94 -> 60 | K31: =K30+K62+K94 -> 141.66 | L31: =L30+L62+L94 -> 350 | M31: =M30+M62+M94 -> 475 | N31: =COUNT(H5:H29,H37:H61,H69:H93) -> 6 | O31: =COUNT(I5:I29,I37:I61,I69:I93) -> 9 | P31: =COUNTIF(G5:G29,"G*")+COUNTIF(G37:G61,"G*")+COUNTIF(G69:G93,"G*")+COUNTIF(G5:G29,"P*")+COUNTIF(G37:G61,"P*")+COUNTIF(G69:G93,"P*") -> 3 | Q31: =COUNTIF(G5:G29,"RSL")+COUNTIF(G37:G61,"RSL")+COUNTIF(G69:G93,"RSL") -> 1 | R31: CASH CLOSING | S31: =H31+L31-U28-U29-U30 -> 925 | T31: =H31+I31+L31+M31 -> 2165 | X31: Subtotal | Z31: =SUM(Z27:Z30) -> -2745
A32: TOTAL SALES | C32: =H31+I31+J31+K31 -> 1541.66 | F32: No of Cars | H32: =COUNT(B5:B29,B37:B61,B69:B93) -> 19 | I32: Average | K32: =C32/H32 -> 81.14 | N32: =H31/C32 -> 0.37297459 | O32: =I31/C32 -> 0.49621836 | P32: =K31/C32 -> 0.091887965 | Q32: =J31/C32 -> 0.038919087 | R32: CARD CLOSING | S32: =I31+M31 -> 1240 | X32: B2 card | Z32: =I31 -> 765
A33: Daily Report | X33: Settlement | Z33: =SUM(Z31:Z32) -> -1980
A34: =A2 -> 45202 | H34: WEATHER | J34: =J2 -> SUNNY | L34: REPORT by | O34: =O2 -> HENDRA | R34: TOTAL STAFF | T34: =T2 -> 5
A36: No | B36: Docket No | C36: Reg No | D36: Mobile | E36: Gender | F36: TIME | G36: Service | H36: CASH | I36: CARD | J36: RSL | K36: GV | L36: GV CASH | M36: GV CARD | N36: O/Taker | O36: Comment | R36: NAME | S36: Time In | T36: Time out | U36: Total Hours
A37: =A29+1 -> 26 | J37: =IF(G37="RSL","55","0") -> 0 | K37: =IF(G37="GVS","37.5",IF(G37="GVM","41.5",IF(G37="GVL","50",IF(G37="PCS","45.8",IF(G37="PCM","50",IF(G37="PCL","58.3","0")))))) -> 0
A38: =A37+1 -> 27 | J38: =IF(G38="RSL","55","0") -> 0 | K38: =IF(G38="GVS","37.5",IF(G38="GVM","41.5",IF(G38="GVL","50",IF(G38="PCS","45.8",IF(G38="PCM","50",IF(G38="PCL","58.3","0")))))) -> 0
A39: =A38+1 -> 28 | J39: =IF(G39="RSL","55","0") -> 0 | K39: =IF(G39="GVS","37.5",IF(G39="GVM","41.5",IF(G39="GVL","50",IF(G39="PCS","45.8",IF(G39="PCM","50",IF(G39="PCL","58.3","0")))))) -> 0
A40: =A39+1 -> 29 | J40: =IF(G40="RSL","55","0") -> 0 | K40: =IF(G40="GVS","37.5",IF(G40="GVM","41.5",IF(G40="GVL","50",IF(G40="PCS","45.8",IF(G40="PCM","50",IF(G40="PCL","58.3","0")))))) -> 0
A41: =A40+1 -> 30 | J41: =IF(G41="RSL","55","0") -> 0 | K41: =IF(G41="GVS","37.5",IF(G41="GVM","41.5",IF(G41="GVL","50",IF(G41="PCS","45.8",IF(G41="PCM","50",IF(G41="PCL","58.3","0")))))) -> 0
A42: =A41+1 -> 31 | J42: =IF(G42="RSL","55","0") -> 0 | K42: =IF(G42="GVS","37.5",IF(G42="GVM","41.5",IF(G42="GVL","50",IF(G42="PCS","45.8",IF(G42="PCM","50",IF(G42="PCL","58.3","0")))))) -> 0
A43: =A42+1 -> 32 | J43: =IF(G43="RSL","55","0") -> 0 | K43: =IF(G43="GVS","37.5",IF(G43="GVM","41.5",IF(G43="GVL","50",IF(G43="PCS","45.8",IF(G43="PCM","50",IF(G43="PCL","58.3","0")))))) -> 0
A44: =A43+1 -> 33 | J44: =IF(G44="RSL","55","0") -> 0 | K44: =IF(G44="GVS","37.5",IF(G44="GVM","41.5",IF(G44="GVL","50",IF(G44="PCS","45.8",IF(G44="PCM","50",IF(G44="PCL","58.3","0")))))) -> 0
A45: =A44+1 -> 34 | J45: =IF(G45="RSL","55","0") -> 0 | K45: =IF(G45="GVS","37.5",IF(G45="GVM","41.5",IF(G45="GVL","50",IF(G45="PCS","45.8",IF(G45="PCM","50",IF(G45="PCL","58.3","0")))))) -> 0
A46: =A45+1 -> 35 | J46: =IF(G46="RSL","55","0") -> 0 | K46: =IF(G46="GVS","37.5",IF(G46="GVM","41.5",IF(G46="GVL","50",IF(G46="PCS","45.8",IF(G46="PCM","50",IF(G46="PCL","58.3","0")))))) -> 0
A47: =A46+1 -> 36 | J47: =IF(G47="RSL","55","0") -> 0 | K47: =IF(G47="GVS","37.5",IF(G47="GVM","41.5",IF(G47="GVL","50",IF(G47="PCS","45.8",IF(G47="PCM","50",IF(G47="PCL","58.3","0")))))) -> 0
A48: =A47+1 -> 37 | J48: =IF(G48="RSL","55","0") -> 0 | K48: =IF(G48="GVS","37.5",IF(G48="GVM","41.5",IF(G48="GVL","50",IF(G48="PCS","45.8",IF(G48="PCM","50",IF(G48="PCL","58.3","0")))))) -> 0
A49: =A48+1 -> 38 | J49: =IF(G49="RSL","55","0") -> 0 | K49: =IF(G49="GVS","37.5",IF(G49="GVM","41.5",IF(G49="GVL","50",IF(G49="PCS","45.8",IF(G49="PCM","50",IF(G49="PCL","58.3","0")))))) -> 0
... A61: =A60+1 -> 50 | J61: =IF(G61="RSL","55","0") -> 0 | K61: =IF(G61="GVS","37.5",IF(G61="GVM","41.5",IF(G61="GVL","50",IF(G61="PCS","45.8",IF(G61="PCM","50",IF(G61="PCL","58.3","0")))))) -> 0
A62: Page total | H62: =SUM(H37:H61) -> 0 | I62: =SUM(I37:I61) -> 0 | J62: =J61+J60+J59+J58+J57+J56+J55+J54+J53+J52+J51+J50+J49+J48+J47+J46+J45+J44+J43+J42+J41+J40+J39+J38+J37 -> 0 | K62: =K61+K60+K59+K58+K57+K56+K55+K54+K53+K52+K51+K50+K49+K48+K47+K46+K45+K44+K43+K42+K41+K40+K39+K38+K37 -> 0 | L62: =SUM(L37:L61) -> 0 | M62: =SUM(M37:M61) -> 0
R64: Page: 2
A65: Daily Report
A66: =A34 -> 45202 | H66: WEATHER | J66: =J34 -> SUNNY | L66: REPORT by | O66: =O34 -> HENDRA | R66: TOTAL STAFF | T66: =T34 -> 5
A68: No | B68: Docket No | C68: Reg No | D68: Mobile | E68: Gender | F68: TIME | G68: Service | H68: CASH | I68: CARD | J68: RSL | K68: GV | L68: GV CASH | M68: GV CARD | N68: O/Taker | O68: Comment | R68: NAME | S68: Time In | T68: Time out | U68: Total Hours
A69: =A61+1 -> 51 | J69: =IF(G69="RSL","55","0") -> 0 | K69: =IF(G69="GVS","37.5",IF(G69="GVM","41.5",IF(G69="GVL","50",IF(G69="PCS","45.8",IF(G69="PCM","50",IF(G69="PCL","58.3","0")))))) -> 0
A70: =A69+1 -> 52 | J70: =IF(G70="RSL","55","0") -> 0 | K70: =IF(G70="GVS","37.5",IF(G70="GVM","41.5",IF(G70="GVL","50",IF(G70="PCS","45.8",IF(G70="PCM","50",IF(G70="PCL","58.3","0")))))) -> 0
A71: =A70+1 -> 53 | J71: =IF(G71="RSL","55","0") -> 0 | K71: =IF(G71="GVS","37.5",IF(G71="GVM","41.5",IF(G71="GVL","50",IF(G71="PCS","45.8",IF(G71="PCM","50",IF(G71="PCL","58.3","0")))))) -> 0
A72: =A71+1 -> 54 | J72: =IF(G72="RSL","55","0") -> 0 | K72: =IF(G72="GVS","37.5",IF(G72="GVM","41.5",IF(G72="GVL","50",IF(G72="PCS","45.8",IF(G72="PCM","50",IF(G72="PCL","58.3","0")))))) -> 0
A73: =A72+1 -> 55 | J73: =IF(G73="RSL","55","0") -> 0 | K73: =IF(G73="GVS","37.5",IF(G73="GVM","41.5",IF(G73="GVL","50",IF(G73="PCS","45.8",IF(G73="PCM","50",IF(G73="PCL","58.3","0")))))) -> 0
A74: =A73+1 -> 56 | J74: =IF(G74="RSL","55","0") -> 0 | K74: =IF(G74="GVS","37.5",IF(G74="GVM","41.5",IF(G74="GVL","50",IF(G74="PCS","45.8",IF(G74="PCM","50",IF(G74="PCL","58.3","0")))))) -> 0
A75: =A74+1 -> 57 | J75: =IF(G75="RSL","55","0") -> 0 | K75: =IF(G75="GVS","37.5",IF(G75="GVM","41.5",IF(G75="GVL","50",IF(G75="PCS","45.8",IF(G75="PCM","50",IF(G75="PCL","58.3","0")))))) -> 0
A76: =A75+1 -> 58 | J76: =IF(G76="RSL","55","0") -> 0 | K76: =IF(G76="GVS","37.5",IF(G76="GVM","41.5",IF(G76="GVL","50",IF(G76="PCS","45.8",IF(G76="PCM","50",IF(G76="PCL","58.3","0")))))) -> 0
A77: =A76+1 -> 59 | J77: =IF(G77="RSL","55","0") -> 0 | K77: =IF(G77="GVS","37.5",IF(G77="GVM","41.5",IF(G77="GVL","50",IF(G77="PCS","45.8",IF(G77="PCM","50",IF(G77="PCL","58.3","0")))))) -> 0
A78: =A77+1 -> 60 | J78: =IF(G78="RSL","55","0") -> 0 | K78: =IF(G78="GVS","37.5",IF(G78="GVM","41.5",IF(G78="GVL","50",IF(G78="PCS","45.8",IF(G78="PCM","50",IF(G78="PCL","58.3","0")))))) -> 0
A79: =A78+1 -> 61 | J79: =IF(G79="RSL","55","0") -> 0 | K79: =IF(G79="GVS","37.5",IF(G79="GVM","41.5",IF(G79="GVL","50",IF(G79="PCS","45.8",IF(G79="PCM","50",IF(G79="PCL","58.3","0")))))) -> 0
A80: =A79+1 -> 62 | J80: =IF(G80="RSL","55","0") -> 0 | K80: =IF(G80="GVS","37.5",IF(G80="GVM","41.5",IF(G80="GVL","50",IF(G80="PCS","45.8",IF(G80="PCM","50",IF(G80="PCL","58.3","0")))))) -> 0
A81: =A80+1 -> 63 | J81: =IF(G81="RSL","55","0") -> 0 | K81: =IF(G81="GVS","37.5",IF(G81="GVM","41.5",IF(G81="GVL","50",IF(G81="PCS","45.8",IF(G81="PCM","50",IF(G81="PCL","58.3","0")))))) -> 0
... A93: =A92+1 -> 75 | J93: =IF(G93="RSL","55","0") -> 0 | K93: =IF(G93="GVS","37.5",IF(G93="GVM","41.5",IF(G93="GVL","50",IF(G93="PCS","45.8",IF(G93="PCM","50",IF(G93="PCL","58.3","0")))))) -> 0
A94: Page total | H94: =SUM(H69:H93) -> 0 | I94: =SUM(I69:I93) -> 0 | J94: =J93+J92+J91+J90+J89+J88+J87+J86+J85+J84+J83+J82+J81+J80+J79+J78+J77+J76+J75+J74+J73+J72+J71+J70+J69 -> 0 | K94: =K93+K92+K91+K90+K89+K88+K87+K86+K85+K84+K83+K82+K81+K80+K79+K78+K77+K76+K75+K74+K73+K72+K71+K70+K69 -> 0 | L94: =SUM(L69:L93) -> 0 | M94: =SUM(M69:M93) -> 0
R96: Page: 3

Sheet SAT
A1: B2 Daily Report
A2: 45233 | H2: WEATHER | J2: SUNNY | L2: REPORT BY | O2: HENDRA | R2: TOTAL STAFF | T2: 7 | X2: Merchant machine usage at B2 | AA2: Settle amount | AI2: Merchant machine usage at GA | AL2: Settle amount
A4: No | B4: Docket No | C4: Reg No | D4: Mobile | E4: Gender | F4: TIME | G4: Service | H4: CASH | I4: CARD | J4: RSL | K4: GV | L4: GV CASH | M4: GV CARD | N4: O/Taker | O4: Comment | R4: NAME | S4: Time In | T4: Time out | U4: Total Hours | Z4: B2 machine | AA4: BLH machine | AB4: Wongo | AE4: B2 machine | AF4: BLH machine | AG4: Wongo | AK4: GA machine | AL4: BLH machine | AM4: Wongo | AP4: GA machine | AQ4: BLH machine | AR4: Wongo
A5: 1 | B5: 14222 | C5: CDD12P | D5: 0416934406 | E5: F | F5: 800 | G5: X | H5: 70 | J5: =IF(G5="RSL","55","0") -> 0 | K5: =IF(G5="GVS","37.5",IF(G5="GVM","41.5",IF(G5="GVL","50",IF(G5="PCS","45.8",IF(G5="PCM","50",IF(G5="PCL","58.3","0")))))) -> 0 | N5: HENDRA | R5: HENDRA | S5: 0.33333333 | T5: 0.70833333 | U5: =(T5-S5)*24 -> 9 | X5: NOV | Y5: 1 | AD5: 16 | AI5: NOV | AJ5: 1 | AO5: 16
A6: 2 | B6: 14223 | C6: BEK07W | D6: 0431384282 | E6: F | F6: 830 | G6: X | I6: 75 | J6: =IF(G6="RSL","55","0") -> 0 | K6: =IF(G6="GVS","37.5",IF(G6="GVM","41.5",IF(G6="GVL","50",IF(G6="PCS","45.8",IF(G6="PCM","50",IF(G6="PCL","58.3","0")))))) -> 0 | N6: ATET | R6: ATET | S6: 0.35416667 | T6: 0.70833333 | U6: =(T6-S6)*24 -> 8.5 | W6: M | Y6: 2 | AD6: 17 | AJ6: 2 | AO6: 17
A7: 3 | B7: 14224 | C7: EEI13E | D7: 0466577917 | E7: M | F7: 900 | G7: PCL | J7: =IF(G7="RSL","55","0") -> 0 | K7: 79.16 | N7: ATET | O7: 23210(2/6) | R7: ARIANTO | S7: 0.35416667 | T7: 0.625 | U7: =(T7-S7)*24 -> 6.5 | W7: F | Y7: 3 | AD7: 18 | AJ7: 3 | AO7: 18
A8: 4 | B8: 14225 | C8: EPZ98K | D8: 0402231090 | E8: F | F8: 910 | G8: D | I8: 75 | J8: =IF(G8="RSL","55","0") -> 0 | K8: =IF(G8="GVS","37.5",IF(G8="GVM","41.5",IF(G8="GVL","50",IF(G8="PCS","45.8",IF(G8="PCM","50",IF(G8="PCL","58.3","0")))))) -> 0 | N8: ATET | R8: JAMES | S8: 0.375 | T8: 0.70833333 | U8: =(T8-S8)*24 -> 8 | Y8: 4 | AD8: 19 | AJ8: 4 | AO8: 19
A9: 5 | B9: 14226 | C9: YDE96A | D9: 0433626429 | E9: M | F9: 1000 | G9: PCL | J9: =IF(G9="RSL","55","0") -> 0 | K9: 79.16 | N9: ATET | O9: 21056(3/6) | R9: VINNY | S9: 0.46875 | T9: 0.70833333 | U9: =(T9-S9)*24 -> 5.75 | X9: EXCL RSL | Y9: 5 | AD9: 20 | AJ9: 5 | AO9: 20
A10: 6 | B10: 14227 | C10: DGC99E | D10: 0406318751 | E10: M | F10: 1000 | G10: PCL | J10: =IF(G10="RSL","55","0") -> 0 | K10: 79.16 | N10: ATET | O10: 22129(3/6) | R10: KUROSH | S10: 0.38541667 | T10: 0.70833333 | U10: =(T10-S10)*24 -> 7.75 | Y10: 6 | AD10: 21 | AJ10: 6 | AO10: 21
A11: 7 | B11: 14228 | C11: CSC59Y | D11: 0401246909 | E11: F | F11: 1015 | G11: PCS | J11: =IF(G11="RSL","55","0") -> 0 | K11: 100 | N11: ATET | O11: 22081(3/6) H | R11: KADAM | S11: 0.4375 | T11: 0.70833333 | U11: =(T11-S11)*24 -> 6.5 | Y11: 7 | AD11: 22 | AJ11: 7 | AO11: 22
A12: 8 | B12: 14229 | C12: CTT06M | D12: 0408804880 | E12: F | F12: 1045 | G12: S/D | H12: 250 | J12: =IF(G12="RSL","55","0") -> 0 | K12: =IF(G12="GVS","37.5",IF(G12="GVM","41.5",IF(G12="GVL","50",IF(G12="PCS","45.8",IF(G12="PCM","50",IF(G12="PCL","58.3","0")))))) -> 0 | N12: ATET | U12: =(T12-S12)*24 -> 0 | Y12: 8 | AD12: 23 | AJ12: 8 | AO12: 23
A13: 9 | B13: 14230 | C13: EMI62K | D13: 0414031401 | E13: F | F13: 1045 | G13: X | I13: 95 | J13: =IF(G13="RSL","55","0") -> 0 | K13: =IF(G13="GVS","37.5",IF(G13="GVM","41.5",IF(G13="GVL","50",IF(G13="PCS","45.8",IF(G13="PCM","50",IF(G13="PCL","58.3","0")))))) -> 0 | N13: ATET | U13: =(T13-S13)*24 -> 0 | Y13: 9 | AD13: 24 | AJ13: 9 | AO13: 24
A14: 10 | B14: 14231 | C14: LGM111 | D14: 0418691153 | E14: F | F14: 1050 | G14: W/O | H14: 45 | J14: =IF(G14="RSL","55","0") -> 0 | K14: =IF(G14="GVS","37.5",IF(G14="GVM","41.5",IF(G14="GVL","50",IF(G14="PCS","45.8",IF(G14="PCM","50",IF(G14="PCL","58.3","0")))))) -> 0 | N14: ATET | U14: =(T14-S14)*24 -> 0 | Y14: 10 | AD14: 25 | AJ14: 10 | AO14: 25
A15: 11 | B15: 14232 | C15: EDT612 | D15: 0417117189 | E15: F | F15: 1100 | G15: GV | J15: =IF(G15="RSL","55","0") -> 0 | K15: 0 | M15: 350 | N15: ATET | O15: XD50-388-394 | U15: =(T15-S15)*24 -> 0 | Y15: 11 | AD15: 26 | AJ15: 11 | AO15: 26
A16: 12 | B16: 14233 | C16: EIW06T | D16: 0422641747 | E16: M | F16: 1115 | G16: GV | J16: =IF(G16="RSL","55","0") -> 0 | K16: 0 | M16: 350 | N16: ATET | O16: XD50-395-401 | R16: =H32/U16 -> 0.55769231 | S16: =H32/(U16-U5) -> 0.6744186 | T16: =C32/U16 -> 45.073077 | U16: =SUM(U5:U15) -> 52 | Y16: 12 | AD16: 27 | AJ16: 12 | AO16: 27
A17: 13 | B17: 14234 | C17: BSK111 | D17: 0403317903 | E17: F | F17: 1135 | G17: D | I17: 75 | J17: =IF(G17="RSL","55","0") -> 0 | K17: =IF(G17="GVS","37.5",IF(G17="GVM","41.5",IF(G17="GVL","50",IF(G17="PCS","45.8",IF(G17="PCM","50",IF(G17="PCL","58.3","0")))))) -> 0 | N17: ATET | R17: Cars/T Hr ① | S17: Cars/T Hr ② | T17: Sales/T Hr | U17: Total Hours | Y17: 13 | AD17: 28 | AJ17: 13 | AO17: 28
A18: 14 | B18: 14235 | C18: NCE76E | D18: 0451660650 | E18: M | F18: 1130 | G18: X | H18: 95 | J18: =IF(G18="RSL","55","0") -> 0 | K18: =IF(G18="GVS","37.5",IF(G18="GVM","41.5",IF(G18="GVL","50",IF(G18="PCS","45.8",IF(G18="PCM","50",IF(G18="PCL","58.3","0")))))) -> 0 | N18: ATET | R18: ITEM | S18: QTY | T18: AMT | U18: RMKS | Y18: 14 | AD18: 29 | AJ18: 14 | AO18: 29
A19: 15 | B19: 14236 | C19: ECO07V | D19: 0401717702 | E19: F | F19: 1230 | G19: X | I19: 75 | J19: =IF(G19="RSL","55","0") -> 0 | K19: =IF(G19="GVS","37.5",IF(G19="GVM","41.5",IF(G19="GVL","50",IF(G19="PCS","45.8",IF(G19="PCM","50",IF(G19="PCL","58.3","0")))))) -> 0 | N19: ATET | R19: GV | S19: =COUNT(L5:M29,L37:M61,L69:M93) -> 4 | T19: =SUM(L5:M29,L37:M61,L69:M93) -> 1553 | Y19: 15 | AD19: 30 | AJ19: 15 | AO19: 30
A20: 16 | B20: 14237 | C20: CST77V | D20: 0419168688 | E20: F | F20: 1245 | G20: X | I20: 75 | J20: =IF(G20="RSL","55","0") -> 0 | K20: =IF(G20="GVS","37.5",IF(G20="GVM","41.5",IF(G20="GVL","50",IF(G20="PCS","45.8",IF(G20="PCM","50",IF(G20="PCL","58.3","0")))))) -> 0 | N20: ATET | AD20: 31 | AO20: 31
A21: 17 | B21: 14238 | C21: BZZ80D | D21: 0414443866 | E21: M | F21: 1245 | G21: D | H21: 55 | J21: =IF(G21="RSL","55","0") -> 0 | K21: =IF(G21="GVS","37.5",IF(G21="GVM","41.5",IF(G21="GVL","50",IF(G21="PCS","45.8",IF(G21="PCM","50",IF(G21="PCL","58.3","0")))))) -> 0 | N21: ATET
A22: 18 | B22: 14239 | C22: CYO20F | D22: 0468848267 | E22: F | F22: 1300 | G22: PCS | J22: =IF(G22="RSL","55","0") -> 0 | K22: 63 | M22: 378 | N22: ATET | O22: 22098(1/6) | AD22: Total | AE22: =SUM(Z5:Z19,AE5:AE20) -> 0 | AF22: =SUM(AA5:AA19,AF5:AF20,) -> 0 | AG22: =SUM(AB5:AB19,AG5:AG20) -> 0 | AO22: Total | AP22: =SUM(AK5:AK19,AP5:AP20) -> 0 | AQ22: =SUM(AL5:AL19,AQ5:AQ20,) -> 0 | AR22: =SUM(AM5:AM19,AR5:AR20) -> 0
A23: 19 | B23: 14240 | C23: EWD81Y | D23: 0415122989 | E23: F | F23: 1315 | G23: W/O | I23: 65 | J23: =IF(G23="RSL","55","0") -> 0 | K23: =IF(G23="GVS","37.5",IF(G23="GVM","41.5",IF(G23="GVL","50",IF(G23="PCS","45.8",IF(G23="PCM","50",IF(G23="PCL","58.3","0")))))) -> 0 | N23: ATET
A24: 20 | B24: 14241 | C24: DMJ87F | D24: 0425373112 | E24: M | F24: 1315 | G24: PCL | J24: =IF(G24="RSL","55","0") -> 0 | K24: 79.16 | N24: ATET | O24: 22152(1/6) | R24: SMALL | S24: MEDIUM | T24: LARGE | U24: TOTAL | AD24: B2/GA TOTAL | AE24: B2 machine | AF24: GA machine | AG24: BLH machine | AH24: Wongo machine | AI24: Sub total
A25: 21 | B25: 14242 | C25: CEC69E | D25: 0434166888 | E25: M | F25: 1315 | G25: X | I25: 75 | J25: =IF(G25="RSL","55","0") -> 0 | K25: =IF(G25="GVS","37.5",IF(G25="GVM","41.5",IF(G25="GVL","50",IF(G25="PCS","45.8",IF(G25="PCM","50",IF(G25="PCL","58.3","0")))))) -> 0 | N25: ATET | O25: TAX | R25: =COUNTIF(G5:G29,"GV1")+COUNTIF(G37:G61,"GV1")+COUNTIF(G69:G93,"GV1") -> 0 | S25: =COUNTIF(G5:G29,"GV2")+COUNTIF(G37:G61,"GV2")+COUNTIF(G69:G93,"GV2") -> 0 | T25: =COUNTIF(G5:G29,"GV3")+COUNTIF(G37:G61,"GV3")+COUNTIF(G69:G93,"GV3") -> 0 | U25: =((C32+(R26+S26+T26)*0.5)) -> 2343.8 | AD25: =SUM(AE25:AF25) -> 0 | AE25: =SUM(AE22) -> 0 | AF25: =SUM(AP22) -> 0 | AG25: =SUM(AF22+AQ22) -> 0 | AH25: =AG22+AR22 -> 0 | AI25: =SUM(AE25:AH25) -> 0
A26: 22 | B26: 14243 | C26: CD42MJ | D26: 0402431006 | E26: F | F26: 1345 | G26: D | I26: 55 | J26: =IF(G26="RSL","55","0") -> 0 | K26: =IF(G26="GVS","37.5",IF(G26="GVM","41.5",IF(G26="GVL","50",IF(G26="PCS","45.8",IF(G26="PCM","50",IF(G26="PCL","58.3","0")))))) -> 0 | N26: ATET | R26: =R25*37.5 -> 0 | S26: =S25*41.5 -> 0 | T26: =T25*50 -> 0 | X26: Branch cards
A27: 23 | B27: 14244 | C27: EHU87A | D27: 0420694860 | E27: M | F27: 1345 | G27: PCL | J27: =IF(G27="RSL","55","0") -> 0 | K27: 125 | N27: ATET | O27: 22062(4/6) H | R27: Expense | X27: 1 | Z27: -2745
A28: 24 | B28: 14245 | C28: EKH52N | D28: 0420866899 | E28: M | F28: 1400 | G28: PCL | J28: =IF(G28="RSL","55","0") -> 0 | K28: 79.16 | L28: 475 | N28: HENDRA | O28: 22032(4/6) X, 23229(NEW) | X28: 2
A29: 25 | B29: 14246 | C29: DXT92E | D29: 0479137054 | E29: M | F29: 1445 | G29: H | I29: 130 | J29: =IF(G29="RSL","55","0") -> 0 | K29: =IF(G29="GVS","37.5",IF(G29="GVM","41.5",IF(G29="GVL","50",IF(G29="PCS","45.8",IF(G29="PCM","50",IF(G29="PCL","58.3","0")))))) -> 0 | N29: ATET | X29: 3
A30: Page total | H30: =SUM(H5:H29) -> 515 | I30: =SUM(I5:I29) -> 795 | J30: =J5+J6+J7+J8+J9+J10+J11+J12+J13+J14+J15+J16+J18+J19+J17+J20+J22+J23+J21+J24+J25+J26+J27+J28+J29 -> 0 | K30: =K5+K6+K7+K8+K9+K10+K11+K12+K13+K14+K15+K16+K18+K19+K17+K20+K22+K23+K21+K24+K25+K26+K27+K28+K29 -> 683.8 | L30: =SUM(L5:L29) -> 475 | M30: =SUM(M5:M29) -> 1078 | N30: CASH | O30: CARD | P30: GV | Q30: RSL | X30: 4
A31: Daily Total | H31: =H30+H62+H94 -> 515 | I31: =I30+I62+I94 -> 1020 | J31: =J30+J62+J94 -> 0 | K31: =K30+K62+K94 -> 808.8 | L31: =L30+L62+L94 -> 475 | M31: =M30+M62+M94 -> 1078 | N31: =COUNT(H5:H29,H37:H61,H69:H93) -> 5 | O31: =COUNT(I5:I29,I37:I61,I69:I93) -> 13 | P31: =COUNTIF(G5:G29,"G*")+COUNTIF(G37:G61,"G*")+COUNTIF(G69:G93,"G*")+COUNTIF(G5:G29,"P*")+COUNTIF(G37:G61,"P*")+COUNTIF(G69:G93,"P*") -> 11 | Q31: =COUNTIF(G5:G29,"RSL")+COUNTIF(G37:G61,"RSL")+COUNTIF(G69:G93,"RSL") -> 0 | R31: CASH CLOSING | S31: =H31+L31-U28-U29-U30 -> 990 | T31: =H31+I31+L31+M31 -> 3088 | X31: Subtotal | Z31: =SUM(Z27:Z30) -> -2745
A32: TOTAL SALES | C32: =H31+I31+J31+K31 -> 2343.8 | F32: No of Cars | H32: =COUNT(B5:B29,B37:B61,B69:B93) -> 29 | I32: Average | K32: =C32/H32 -> 80.82069 | N32: =H31/C32 -> 0.21972865 | O32: =I31/C32 -> 0.43519072 | P32: =K31/C32 -> 0.34508064 | Q32: =J31/C32 -> 0 | R32: CARD CLOSING | S32: =I31+M31 -> 2098 | X32: B2 card | Z32: =I31 -> 1020
A33: Daily Report | X33: Settlement | Z33: =SUM(Z31:Z32) -> -1725
A34: =A2 -> 45233 | H34: WEATHER | J34: =J2 -> SUNNY | L34: REPORT by | O34: =O2 -> HENDRA | R34: TOTAL STAFF | T34: =T2 -> 7
A36: No | B36: Docket No | C36: Reg No | D36: Mobile | E36: Gender | F36: TIME | G36: Service | H36: CASH | I36: CARD | J36: RSL | K36: GV | L36: GV CASH | M36: GV CARD | N36: O/Taker | O36: Comment | R36: NAME | S36: Time In | T36: Time out | U36: Total Hours
A37: =A29+1 -> 26 | B37: 14247 | C37: DBM56H | D37: 0404295312 | E37: M | F37: 1500 | G37: X | I37: 75 | J37: =IF(G37="RSL","55","0") -> 0 | K37: =IF(G37="GVS","37.5",IF(G37="GVM","41.5",IF(G37="GVL","50",IF(G37="PCS","45.8",IF(G37="PCM","50",IF(G37="PCL","58.3","0")))))) -> 0 | N37: ATET
A38: =A37+1 -> 27 | B38: 14248 | C38: MOSAUS | D38: 0401758007 | E38: F | F38: 1515 | G38: PCL | J38: =IF(G38="RSL","55","0") -> 0 | K38: 125 | N38: ATET | O38: 22194(4/6)H
A39: =A38+1 -> 28 | B39: 14249 | C39: EAQ24Y | D39: 0421937001 | E39: F | F39: 1515 | G39: X | I39: 75 | J39: =IF(G39="RSL","55","0") -> 0 | K39: =IF(G39="GVS","37.5",IF(G39="GVM","41.5",IF(G39="GVL","50",IF(G39="PCS","45.8",IF(G39="PCM","50",IF(G39="PCL","58.3","0")))))) -> 0 | N39: ATET
A40: =A39+1 -> 29 | B40: 14250 | C40: POJ000 | D40: 0416244569 | E40: F | F40: 1520 | G40: X | I40: 75 | J40: =IF(G40="RSL","55","0") -> 0 | K40: =IF(G40="GVS","37.5",IF(G40="GVM","41.5",IF(G40="GVL","50",IF(G40="PCS","45.8",IF(G40="PCM","50",IF(G40="PCL","58.3","0")))))) -> 0 | N40: ATET
A41: =A40+1 -> 30 | J41: =IF(G41="RSL","55","0") -> 0 | K41: =IF(G41="GVS","37.5",IF(G41="GVM","41.5",IF(G41="GVL","50",IF(G41="PCS","45.8",IF(G41="PCM","50",IF(G41="PCL","58.3","0")))))) -> 0
A42: =A41+1 -> 31 | J42: =IF(G42="RSL","55","0") -> 0 | K42: =IF(G42="GVS","37.5",IF(G42="GVM","41.5",IF(G42="GVL","50",IF(G42="PCS","45.8",IF(G42="PCM","50",IF(G42="PCL","58.3","0")))))) -> 0
A43: =A42+1 -> 32 | J43: =IF(G43="RSL","55","0") -> 0 | K43: =IF(G43="GVS","37.5",IF(G43="GVM","41.5",IF(G43="GVL","50",IF(G43="PCS","45.8",IF(G43="PCM","50",IF(G43="PCL","58.3","0")))))) -> 0
A44: =A43+1 -> 33 | J44: =IF(G44="RSL","55","0") -> 0 | K44: =IF(G44="GVS","37.5",IF(G44="GVM","41.5",IF(G44="GVL","50",IF(G44="PCS","45.8",IF(G44="PCM","50",IF(G44="PCL","58.3","0")))))) -> 0
A45: =A44+1 -> 34 | J45: =IF(G45="RSL","55","0") -> 0 | K45: =IF(G45="GVS","37.5",IF(G45="GVM","41.5",IF(G45="GVL","50",IF(G45="PCS","45.8",IF(G45="PCM","50",IF(G45="PCL","58.3","0")))))) -> 0
A46: =A45+1 -> 35 | J46: =IF(G46="RSL","55","0") -> 0 | K46: =IF(G46="GVS","37.5",IF(G46="GVM","41.5",IF(G46="GVL","50",IF(G46="PCS","45.8",IF(G46="PCM","50",IF(G46="PCL","58.3","0")))))) -> 0
A47: =A46+1 -> 36 | J47: =IF(G47="RSL","55","0") -> 0 | K47: =IF(G47="GVS","37.5",IF(G47="GVM","41.5",IF(G47="GVL","50",IF(G47="PCS","45.8",IF(G47="PCM","50",IF(G47="PCL","58.3","0")))))) -> 0
A48: =A47+1 -> 37 | J48: =IF(G48="RSL","55","0") -> 0 | K48: =IF(G48="GVS","37.5",IF(G48="GVM","41.5",IF(G48="GVL","50",IF(G48="PCS","45.8",IF(G48="PCM","50",IF(G48="PCL","58.3","0")))))) -> 0
A49: =A48+1 -> 38 | J49: =IF(G49="RSL","55","0") -> 0 | K49: =IF(G49="GVS","37.5",IF(G49="GVM","41.5",IF(G49="GVL","50",IF(G49="PCS","45.8",IF(G49="PCM","50",IF(G49="PCL","58.3","0")))))) -> 0
A50: =A49+1 -> 39 | J50: =IF(G50="RSL","55","0") -> 0 | K50: =IF(G50="GVS","37.5",IF(G50="GVM","41.5",IF(G50="GVL","50",IF(G50="PCS","45.8",IF(G50="PCM","50",IF(G50="PCL","58.3","0")))))) -> 0
A51: =A50+1 -> 40 | J51: =IF(G51="RSL","55","0") -> 0 | K51: =IF(G51="GVS","37.5",IF(G51="GVM","41.5",IF(G51="GVL","50",IF(G51="PCS","45.8",IF(G51="PCM","50",IF(G51="PCL","58.3","0")))))) -> 0
A52: =A51+1 -> 41 | J52: =IF(G52="RSL","55","0") -> 0 | K52: =IF(G52="GVS","37.5",IF(G52="GVM","41.5",IF(G52="GVL","50",IF(G52="PCS","45.8",IF(G52="PCM","50",IF(G52="PCL","58.3","0")))))) -> 0
... A61: =A60+1 -> 50 | J61: =IF(G61="RSL","55","0") -> 0 | K61: =IF(G61="GVS","37.5",IF(G61="GVM","41.5",IF(G61="GVL","50",IF(G61="PCS","45.8",IF(G61="PCM","50",IF(G61="PCL","58.3","0")))))) -> 0
A62: Page total | H62: =SUM(H37:H61) -> 0 | I62: =SUM(I37:I61) -> 225 | J62: =J61+J60+J59+J58+J57+J56+J55+J54+J53+J52+J51+J50+J49+J48+J47+J46+J45+J44+J43+J42+J41+J40+J39+J38+J37 -> 0 | K62: =K61+K60+K59+K58+K57+K56+K55+K54+K53+K52+K51+K50+K49+K48+K47+K46+K45+K44+K43+K42+K41+K40+K39+K38+K37 -> 125 | L62: =SUM(L37:L61) -> 0 | M62: =SUM(M37:M61) -> 0
R64: Page: 2
A65: Daily Report
A66: =A34 -> 45233 | H66: WEATHER | J66: =J34 -> SUNNY | L66: REPORT by | O66: =O34 -> HENDRA | R66: TOTAL STAFF | T66: =T34 -> 7
A68: No | B68: Docket No | C68: Reg No | D68: Mobile | E68: Gender | F68: TIME | G68: Service | H68: CASH | I68: CARD | J68: RSL | K68: GV | L68: GV CASH | M68: GV CARD | N68: O/Taker | O68: Comment | R68: NAME | S68: Time In | T68: Time out | U68: Total Hours
A69: =A61+1 -> 51 | J69: =IF(G69="RSL","55","0") -> 0 | K69: =IF(G69="GVS","37.5",IF(G69="GVM","41.5",IF(G69="GVL","50",IF(G69="PCS","45.8",IF(G69="PCM","50",IF(G69="PCL","58.3","0")))))) -> 0
A70: =A69+1 -> 52 | J70: =IF(G70="RSL","55","0") -> 0 | K70: =IF(G70="GVS","37.5",IF(G70="GVM","41.5",IF(G70="GVL","50",IF(G70="PCS","45.8",IF(G70="PCM","50",IF(G70="PCL","58.3","0")))))) -> 0
A71: =A70+1 -> 53 | J71: =IF(G71="RSL","55","0") -> 0 | K71: =IF(G71="GVS","37.5",IF(G71="GVM","41.5",IF(G71="GVL","50",IF(G71="PCS","45.8",IF(G71="PCM","50",IF(G71="PCL","58.3","0")))))) -> 0
A72: =A71+1 -> 54 | J72: =IF(G72="RSL","55","0") -> 0 | K72: =IF(G72="GVS","37.5",IF(G72="GVM","41.5",IF(G72="GVL","50",IF(G72="PCS","45.8",IF(G72="PCM","50",IF(G72="PCL","58.3","0")))))) -> 0
A73: =A72+1 -> 55 | J73: =IF(G73="RSL","55","0") -> 0 | K73: =IF(G73="GVS","37.5",IF(G73="GVM","41.5",IF(G73="GVL","50",IF(G73="PCS","45.8",IF(G73="PCM","50",IF(G73="PCL","58.3","0")))))) -> 0
A74: =A73+1 -> 56 | J74: =IF(G74="RSL","55","0") -> 0 | K74: =IF(G74="GVS","37.5",IF(G74="GVM","41.5",IF(G74="GVL","50",IF(G74="PCS","45.8",IF(G74="PCM","50",IF(G74="PCL","58.3","0")))))) -> 0
A75: =A74+1 -> 57 | J75: =IF(G75="RSL","55","0") -> 0 | K75: =IF(G75="GVS","37.5",IF(G75="GVM","41.5",IF(G75="GVL","50",IF(G75="PCS","45.8",IF(G75="PCM","50",IF(G75="PCL","58.3","0")))))) -> 0
A76: =A75+1 -> 58 | J76: =IF(G76="RSL","55","0") -> 0 | K76: =IF(G76="GVS","37.5",IF(G76="GVM","41.5",IF(G76="GVL","50",IF(G76="PCS","45.8",IF(G76="PCM","50",IF(G76="PCL","58.3","0")))))) -> 0
A77: =A76+1 -> 59 | J77: =IF(G77="RSL","55","0") -> 0 | K77: =IF(G77="GVS","37.5",IF(G77="GVM","41.5",IF(G77="GVL","50",IF(G77="PCS","45.8",IF(G77="PCM","50",IF(G77="PCL","58.3","0")))))) -> 0
A78: =A77+1 -> 60 | J78: =IF(G78="RSL","55","0") -> 0 | K78: =IF(G78="GVS","37.5",IF(G78="GVM","41.5",IF(G78="GVL","50",IF(G78="PCS","45.8",IF(G78="PCM","50",IF(G78="PCL","58.3","0")))))) -> 0
A79: =A78+1 -> 61 | J79: =IF(G79="RSL","55","0") -> 0 | K79: =IF(G79="GVS","37.5",IF(G79="GVM","41.5",IF(G79="GVL","50",IF(G79="PCS","45.8",IF(G79="PCM","50",IF(G79="PCL","58.3","0")))))) -> 0
A80: =A79+1 -> 62 | J80: =IF(G80="RSL","55","0") -> 0 | K80: =IF(G80="GVS","37.5",IF(G80="GVM","41.5",IF(G80="GVL","50",IF(G80="PCS","45.8",IF(G80="PCM","50",IF(G80="PCL","58.3","0")))))) -> 0
A81: =A80+1 -> 63 | J81: =IF(G81="RSL","55","0") -> 0 | K81: =IF(G81="GVS","37.5",IF(G81="GVM","41.5",IF(G81="GVL","50",IF(G81="PCS","45.8",IF(G81="PCM","50",IF(G81="PCL","58.3","0")))))) -> 0
... A93: =A92+1 -> 75 | J93: =IF(G93="RSL","55","0") -> 0 | K93: =IF(G93="GVS","37.5",IF(G93="GVM","41.5",IF(G93="GVL","50",IF(G93="PCS","45.8",IF(G93="PCM","50",IF(G93="PCL","58.3","0")))))) -> 0
A94: Page total | H94: =SUM(H69:H93) -> 0 | I94: =SUM(I69:I93) -> 0 | J94: =J93+J92+J91+J90+J89+J88+J87+J86+J85+J84+J83+J82+J81+J80+J79+J78+J77+J76+J75+J74+J73+J72+J71+J70+J69 -> 0 | K94: =K93+K92+K91+K90+K89+K88+K87+K86+K85+K84+K83+K82+K81+K80+K79+K78+K77+K76+K75+K74+K73+K72+K71+K70+K69 -> 0 | L94: =SUM(L69:L93) -> 0 | M94: =SUM(M69:M93) -> 0
R96: Page: 3

Sheet SUN
A1: B2 Daily Report
A2: 45263 | H2: WEATHER | J2: CLOUDY | L2: REPORT BY | O2: HENDRA | R2: TOTAL STAFF | T2: 4 | X2: Merchant machine usage at B2 | AA2: Settle amount | AI2: Merchant machine usage at GA | AL2: Settle amount
A4: No | B4: Docket No | C4: Reg No | D4: Mobile | E4: Gender | F4: TIME | G4: Service | H4: CASH | I4: CARD | J4: RSL | K4: GV | L4: GV CASH | M4: GV CARD | N4: O/Taker | O4: Comment | R4: NAME | S4: Time In | T4: Time out | U4: Total Hours | Z4: B2 machine | AA4: BLH machine | AB4: Wongo | AE4: B2 machine | AF4: BLH machine | AG4: Wongo | AK4: GA machine | AL4: BLH machine | AM4: Wongo | AP4: GA machine | AQ4: BLH machine | AR4: Wongo
A5: 1 | B5: 14251 | C5: EJS26H | D5: 0434321020 | E5: F | F5: 850 | G5: D | H5: 75 | J5: =IF(G5="RSL","55","0") -> 0 | K5: =IF(G5="GVS","37.5",IF(G5="GVM","41.5",IF(G5="GVL","50",IF(G5="PCS","45.8",IF(G5="PCM","50",IF(G5="PCL","58.3","0")))))) -> 0 | N5: HENDRA | R5: HENDRA | S5: 0.33333333 | T5: 0.71875 | U5: =(T5-S5)*24 -> 9.25 | X5: NOV | Y5: 1 | AD5: 16 | AI5: NOV | AJ5: 1 | AO5: 16
A6: 2 | B6: 14252 | C6: CS700 | D6: 0438997201 | E6: F | F6: 950 | G6: D | H6: 55 | J6: =IF(G6="RSL","55","0") -> 0 | K6: =IF(G6="GVS","37.5",IF(G6="GVM","41.5",IF(G6="GVL","50",IF(G6="PCS","45.8",IF(G6="PCM","50",IF(G6="PCL","58.3","0")))))) -> 0 | N6: HENDRA | R6: JAMES | S6: 0.35416667 | T6: 0.70833333 | U6: =(T6-S6)*24 -> 8.5 | W6: M | Y6: 2 | AD6: 17 | AJ6: 2 | AO6: 17
A7: 3 | B7: 14253 | C7: CNQ93A | D7: 0478160880 | E7: F | F7: 1100 | G7: D | H7: 55 | J7: =IF(G7="RSL","55","0") -> 0 | K7: =IF(G7="GVS","37.5",IF(G7="GVM","41.5",IF(G7="GVL","50",IF(G7="PCS","45.8",IF(G7="PCM","50",IF(G7="PCL","58.3","0")))))) -> 0 | N7: HENDRA | R7: VINNY | S7: 0.375 | T7: 0.71875 | U7: =(T7-S7)*24 -> 8.25 | W7: F | Y7: 3 | AD7: 18 | AJ7: 3 | AO7: 18
A8: 4 | B8: 14254 | C8: EHU87A | D8: 0420694860 | E8: M | F8: 1100 | G8: PCL | J8: =IF(G8="RSL","55","0") -> 0 | K8: 125 | L8: 750 | N8: HENDRA | O8: 23230(NEW) H | R8: KUROSH | S8: 0.38541667 | T8: 0.71875 | U8: =(T8-S8)*24 -> 8 | Y8: 4 | AD8: 19 | AJ8: 4 | AO8: 19
A9: 5 | B9: 14255 | C9: DSA73E | D9: 0408968692 | E9: M | F9: 1130 | G9: X | I9: 75 | J9: =IF(G9="RSL","55","0") -> 0 | K9: =IF(G9="GVS","37.5",IF(G9="GVM","41.5",IF(G9="GVL","50",IF(G9="PCS","45.8",IF(G9="PCM","50",IF(G9="PCL","58.3","0")))))) -> 0 | N9: HENDRA | U9: =(T9-S9)*24 -> 0 | X9: EXCL RSL | Y9: 5 | AD9: 20 | AJ9: 5 | AO9: 20
A10: 6 | B10: 14256 | C10: DTC67F | D10: 0403112344 | E10: M | F10: 1145 | G10: D | I10: 75 | J10: =IF(G10="RSL","55","0") -> 0 | K10: =IF(G10="GVS","37.5",IF(G10="GVM","41.5",IF(G10="GVL","50",IF(G10="PCS","45.8",IF(G10="PCM","50",IF(G10="PCL","58.3","0")))))) -> 0 | N10: HENDRA | O10: TAX | U10: =(T10-S10)*24 -> 0 | Y10: 6 | AD10: 21 | AJ10: 6 | AO10: 21
A11: 7 | B11: 14257 | C11: ESF85U | D11: 0434437231 | E11: F | F11: 1215 | G11: X | I11: 95 | J11: =IF(G11="RSL","55","0") -> 0 | K11: =IF(G11="GVS","37.5",IF(G11="GVM","41.5",IF(G11="GVL","50",IF(G11="PCS","45.8",IF(G11="PCM","50",IF(G11="PCL","58.3","0")))))) -> 0 | N11: HENDRA | U11: =(T11-S11)*24 -> 0 | Y11: 7 | AD11: 22 | AJ11: 7 | AO11: 22
A12: 8 | B12: 14258 | C12: NCB18X | D12: 0488357369 | E12: M | F12: 1230 | G12: D | I12: 75 | J12: =IF(G12="RSL","55","0") -> 0 | K12: =IF(G12="GVS","37.5",IF(G12="GVM","41.5",IF(G12="GVL","50",IF(G12="PCS","45.8",IF(G12="PCM","50",IF(G12="PCL","58.3","0")))))) -> 0 | N12: HENDRA | U12: =(T12-S12)*24 -> 0 | Y12: 8 | AD12: 23 | AJ12: 8 | AO12: 23
A13: 9 | B13: 14259 | C13: AIX070 | D13: 0413779278 | E13: F | F13: 1320 | G13: PCS | J13: =IF(G13="RSL","55","0") -> 0 | K13: 125 | N13: VINNY | O13: 22064(2-3/6) H | U13: =(T13-S13)*24 -> 0 | Y13: 9 | AD13: 24 | AJ13: 9 | AO13: 24
A14: 10 | B14: 14260 | C14: DZX36B | D14: 0478030894 | E14: F | F14: 1320 | G14: D | I14: 55 | J14: =IF(G14="RSL","55","0") -> 0 | K14: =IF(G14="GVS","37.5",IF(G14="GVM","41.5",IF(G14="GVL","50",IF(G14="PCS","45.8",IF(G14="PCM","50",IF(G14="PCL","58.3","0")))))) -> 0 | N14: VINNY | U14: =(T14-S14)*24 -> 0 | Y14: 10 | AD14: 25 | AJ14: 10 | AO14: 25
A15: 11 | B15: 14261 | C15: DNW70T | D15: 0449118109 | E15: M | F15: 1330 | G15: X | H15: 75 | J15: =IF(G15="RSL","55","0") -> 0 | K15: =IF(G15="GVS","37.5",IF(G15="GVM","41.5",IF(G15="GVL","50",IF(G15="PCS","45.8",IF(G15="PCM","50",IF(G15="PCL","58.3","0")))))) -> 0 | N15: HENDRA | O15: BOOKING ONLINE | U15: =(T15-S15)*24 -> 0 | Y15: 11 | AD15: 26 | AJ15: 11 | AO15: 26
A16: 12 | B16: 14262 | C16: DQR27A | D16: 0419487797 | E16: F | F16: 1345 | G16: X | I16: 95 | J16: =IF(G16="RSL","55","0") -> 0 | K16: =IF(G16="GVS","37.5",IF(G16="GVM","41.5",IF(G16="GVL","50",IF(G16="PCS","45.8",IF(G16="PCM","50",IF(G16="PCL","58.3","0")))))) -> 0 | N16: HENDRA | R16: =H32/U16 -> 0.47058824 | S16: =H32/(U16-U5) -> 0.64646465 | T16: =C32/U16 -> 38.235294 | U16: =SUM(U5:U15) -> 34 | Y16: 12 | AD16: 27 | AJ16: 12 | AO16: 27
A17: 13 | B17: 14263 | C17: ERX40P | D17: 0405232683 | E17: M | F17: 1400 | G17: X | I17: 75 | J17: =IF(G17="RSL","55","0") -> 0 | K17: =IF(G17="GVS","37.5",IF(G17="GVM","41.5",IF(G17="GVL","50",IF(G17="PCS","45.8",IF(G17="PCM","50",IF(G17="PCL","58.3","0")))))) -> 0 | N17: HENDRA | R17: Cars/T Hr ① | S17: Cars/T Hr ② | T17: Sales/T Hr | U17: Total Hours | Y17: 13 | AD17: 28 | AJ17: 13 | AO17: 28
A18: 14 | B18: 14264 | C18: EEN30S | D18: 0448544338 | E18: F | F18: 1415 | G18: D | I18: 75 | J18: =IF(G18="RSL","55","0") -> 0 | K18: =IF(G18="GVS","37.5",IF(G18="GVM","41.5",IF(G18="GVL","50",IF(G18="PCS","45.8",IF(G18="PCM","50",IF(G18="PCL","58.3","0")))))) -> 0 | N18: HENDRA | R18: ITEM | S18: QTY | T18: AMT | U18: RMKS | Y18: 14 | AD18: 29 | AJ18: 14 | AO18: 29
A19: 15 | B19: 14265 | C19: NBY11Q | D19: 0407197325 | E19: M | F19: 1420 | G19: X | I19: 95 | J19: =IF(G19="RSL","55","0") -> 0 | K19: =IF(G19="GVS","37.5",IF(G19="GVM","41.5",IF(G19="GVL","50",IF(G19="PCS","45.8",IF(G19="PCM","50",IF(G19="PCL","58.3","0")))))) -> 0 | N19: HENDRA | R19: GV | S19: =COUNT(L5:M29,L37:M61,L69:M93) -> 1 | T19: =SUM(L5:M29,L37:M61,L69:M93) -> 750 | Y19: 15 | AD19: 30 | AJ19: 15 | AO19: 30
A20: 16 | B20: 14266 | C20: NDW015 | D20: 0417650365 | E20: M | F20: 1530 | G20: D | I20: 75 | J20: =IF(G20="RSL","55","0") -> 0 | K20: =IF(G20="GVS","37.5",IF(G20="GVM","41.5",IF(G20="GVL","50",IF(G20="PCS","45.8",IF(G20="PCM","50",IF(G20="PCL","58.3","0")))))) -> 0 | N20: HENDRA | AD20: 31 | AO20: 31
A21: 17 | J21: =IF(G21="RSL","55","0") -> 0 | K21: =IF(G21="GVS","37.5",IF(G21="GVM","41.5",IF(G21="GVL","50",IF(G21="PCS","45.8",IF(G21="PCM","50",IF(G21="PCL","58.3","0")))))) -> 0
A22: 18 | J22: =IF(G22="RSL","55","0") -> 0 | K22: =IF(G22="GVS","37.5",IF(G22="GVM","41.5",IF(G22="GVL","50",IF(G22="PCS","45.8",IF(G22="PCM","50",IF(G22="PCL","58.3","0")))))) -> 0 | AD22: Total | AE22: =SUM(Z5:Z19,AE5:AE20) -> 0 | AF22: =SUM(AA5:AA19,AF5:AF20,) -> 0 | AG22: =SUM(AB5:AB19,AG5:AG20) -> 0 | AO22: Total | AP22: =SUM(AK5:AK19,AP5:AP20) -> 0 | AQ22: =SUM(AL5:AL19,AQ5:AQ20,) -> 0 | AR22: =SUM(AM5:AM19,AR5:AR20) -> 0
A23: 19 | J23: =IF(G23="RSL","55","0") -> 0 | K23: =IF(G23="GVS","37.5",IF(G23="GVM","41.5",IF(G23="GVL","50",IF(G23="PCS","45.8",IF(G23="PCM","50",IF(G23="PCL","58.3","0")))))) -> 0
A24: 20 | J24: =IF(G24="RSL","55","0") -> 0 | K24: =IF(G24="GVS","37.5",IF(G24="GVM","41.5",IF(G24="GVL","50",IF(G24="PCS","45.8",IF(G24="PCM","50",IF(G24="PCL","58.3","0")))))) -> 0 | R24: SMALL | S24: MEDIUM | T24: LARGE | U24: TOTAL | AD24: B2/GA TOTAL | AE24: B2 machine | AF24: GA machine | AG24: BLH machine | AH24: Wongo machine | AI24: Sub total
A25: 21 | J25: =IF(G25="RSL","55","0") -> 0 | K25: =IF(G25="GVS","37.5",IF(G25="GVM","41.5",IF(G25="GVL","50",IF(G25="PCS","45.8",IF(G25="PCM","50",IF(G25="PCL","58.3","0")))))) -> 0 | R25: =COUNTIF(G5:G29,"GV1")+COUNTIF(G37:G61,"GV1")+COUNTIF(G69:G93,"GV1") -> 0 | S25: =COUNTIF(G5:G29,"GV2")+COUNTIF(G37:G61,"GV2")+COUNTIF(G69:G93,"GV2") -> 0 | T25: =COUNTIF(G5:G29,"GV3")+COUNTIF(G37:G61,"GV3")+COUNTIF(G69:G93,"GV3") -> 0 | U25: =((C32+(R26+S26+T26)*0.5)) -> 1300 | AD25: =SUM(AE25:AF25) -> 0 | AE25: =SUM(AE22) -> 0 | AF25: =SUM(AP22) -> 0 | AG25: =SUM(AF22+AQ22) -> 0 | AH25: =AG22+AR22 -> 0 | AI25: =SUM(AE25:AH25) -> 0
A26: 22 | J26: =IF(G26="RSL","55","0") -> 0 | K26: =IF(G26="GVS","37.5",IF(G26="GVM","41.5",IF(G26="GVL","50",IF(G26="PCS","45.8",IF(G26="PCM","50",IF(G26="PCL","58.3","0")))))) -> 0 | R26: =R25*37.5 -> 0 | S26: =S25*41.5 -> 0 | T26: =T25*50 -> 0 | X26: Branch cards
A27: 23 | J27: =IF(G27="RSL","55","0") -> 0 | K27: =IF(G27="GVS","37.5",IF(G27="GVM","41.5",IF(G27="GVL","50",IF(G27="PCS","45.8",IF(G27="PCM","50",IF(G27="PCL","58.3","0")))))) -> 0 | R27: Expense | X27: 1 | Z27: -2745
A28: 24 | J28: =IF(G28="RSL","55","0") -> 0 | K28: =IF(G28="GVS","37.5",IF(G28="GVM","41.5",IF(G28="GVL","50",IF(G28="PCS","45.8",IF(G28="PCM","50",IF(G28="PCL","58.3","0")))))) -> 0 | X28: 2
A29: 25 | J29: =IF(G29="RSL","55","0") -> 0 | K29: =IF(G29="GVS","37.5",IF(G29="GVM","41.5",IF(G29="GVL","50",IF(G29="PCS","45.8",IF(G29="PCM","50",IF(G29="PCL","58.3","0")))))) -> 0 | X29: 3
A30: Page total | H30: =SUM(H5:H29) -> 260 | I30: =SUM(I5:I29) -> 790 | J30: =J5+J6+J7+J8+J9+J10+J11+J12+J13+J14+J15+J16+J18+J19+J17+J20+J22+J23+J21+J24+J25+J26+J27+J28+J29 -> 0 | K30: =K5+K6+K7+K8+K9+K10+K11+K12+K13+K14+K15+K16+K18+K19+K17+K20+K22+K23+K21+K24+K25+K26+K27+K28+K29 -> 250 | L30: =SUM(L5:L29) -> 750 | M30: =SUM(M5:M29) -> 0 | N30: CASH | O30: CARD | P30: GV | Q30: RSL | X30: 4
A31: Daily Total | H31: =H30+H62+H94 -> 260 | I31: =I30+I62+I94 -> 790 | J31: =J30+J62+J94 -> 0 | K31: =K30+K62+K94 -> 250 | L31: =L30+L62+L94 -> 750 | M31: =M30+M62+M94 -> 0 | N31: =COUNT(H5:H29,H37:H61,H69:H93) -> 4 | O31: =COUNT(I5:I29,I37:I61,I69:I93) -> 10 | P31: =COUNTIF(G5:G29,"G*")+COUNTIF(G37:G61,"G*")+COUNTIF(G69:G93,"G*")+COUNTIF(G5:G29,"P*")+COUNTIF(G37:G61,"P*")+COUNTIF(G69:G93,"P*") -> 2 | Q31: =COUNTIF(G5:G29,"RSL")+COUNTIF(G37:G61,"RSL")+COUNTIF(G69:G93,"RSL") -> 0 | R31: CASH CLOSING | S31: =H31+L31-U28-U29-U30 -> 1010 | T31: =H31+I31+L31+M31 -> 1800 | X31: Subtotal | Z31: =SUM(Z27:Z30) -> -2745
A32: TOTAL SALES | C32: =H31+I31+J31+K31 -> 1300 | F32: No of Cars | H32: =COUNT(B5:B29,B37:B61,B69:B93) -> 16 | I32: Average | K32: =C32/H32 -> 81.25 | N32: =H31/C32 -> 0.2 | O32: =I31/C32 -> 0.60769231 | P32: =K31/C32 -> 0.19230769 | Q32: =J31/C32 -> 0 | R32: CARD CLOSING | S32: =I31+M31 -> 790 | X32: B2 card | Z32: =I31 -> 790
A33: Daily Report | X33: Settlement | Z33: =SUM(Z31:Z32) -> -1955
A34: =A2 -> 45263 | H34: WEATHER | J34: =J2 -> CLOUDY | L34: REPORT by | O34: =O2 -> HENDRA | R34: TOTAL STAFF | T34: =T2 -> 4
A36: No | B36: Docket No | C36: Reg No | D36: Mobile | E36: Gender | F36: TIME | G36: Service | H36: CASH | I36: CARD | J36: RSL | K36: GV | L36: GV CASH | M36: GV CARD | N36: O/Taker | O36: Comment | R36: NAME | S36: Time In | T36: Time out | U36: Total Hours
A37: =A29+1 -> 26 | J37: =IF(G37="RSL","55","0") -> 0 | K37: =IF(G37="GVS","37.5",IF(G37="GVM","41.5",IF(G37="GVL","50",IF(G37="PCS","45.8",IF(G37="PCM","50",IF(G37="PCL","58.3","0")))))) -> 0
A38: =A37+1 -> 27 | J38: =IF(G38="RSL","55","0") -> 0 | K38: =IF(G38="GVS","37.5",IF(G38="GVM","41.5",IF(G38="GVL","50",IF(G38="PCS","45.8",IF(G38="PCM","50",IF(G38="PCL","58.3","0")))))) -> 0
A39: =A38+1 -> 28 | J39: =IF(G39="RSL","55","0") -> 0 | K39: =IF(G39="GVS","37.5",IF(G39="GVM","41.5",IF(G39="GVL","50",IF(G39="PCS","45.8",IF(G39="PCM","50",IF(G39="PCL","58.3","0")))))) -> 0
A40: =A39+1 -> 29 | J40: =IF(G40="RSL","55","0") -> 0 | K40: =IF(G40="GVS","37.5",IF(G40="GVM","41.5",IF(G40="GVL","50",IF(G40="PCS","45.8",IF(G40="PCM","50",IF(G40="PCL","58.3","0")))))) -> 0
A41: =A40+1 -> 30 | J41: =IF(G41="RSL","55","0") -> 0 | K41: =IF(G41="GVS","37.5",IF(G41="GVM","41.5",IF(G41="GVL","50",IF(G41="PCS","45.8",IF(G41="PCM","50",IF(G41="PCL","58.3","0")))))) -> 0
A42: =A41+1 -> 31 | J42: =IF(G42="RSL","55","0") -> 0 | K42: =IF(G42="GVS","37.5",IF(G42="GVM","41.5",IF(G42="GVL","50",IF(G42="PCS","45.8",IF(G42="PCM","50",IF(G42="PCL","58.3","0")))))) -> 0
A43: =A42+1 -> 32 | J43: =IF(G43="RSL","55","0") -> 0 | K43: =IF(G43="GVS","37.5",IF(G43="GVM","41.5",IF(G43="GVL","50",IF(G43="PCS","45.8",IF(G43="PCM","50",IF(G43="PCL","58.3","0")))))) -> 0
A44: =A43+1 -> 33 | J44: =IF(G44="RSL","55","0") -> 0 | K44: =IF(G44="GVS","37.5",IF(G44="GVM","41.5",IF(G44="GVL","50",IF(G44="PCS","45.8",IF(G44="PCM","50",IF(G44="PCL","58.3","0")))))) -> 0
A45: =A44+1 -> 34 | J45: =IF(G45="RSL","55","0") -> 0 | K45: =IF(G45="GVS","37.5",IF(G45="GVM","41.5",IF(G45="GVL","50",IF(G45="PCS","45.8",IF(G45="PCM","50",IF(G45="PCL","58.3","0")))))) -> 0
A46: =A45+1 -> 35 | J46: =IF(G46="RSL","55","0") -> 0 | K46: =IF(G46="GVS","37.5",IF(G46="GVM","41.5",IF(G46="GVL","50",IF(G46="PCS","45.8",IF(G46="PCM","50",IF(G46="PCL","58.3","0")))))) -> 0
A47: =A46+1 -> 36 | J47: =IF(G47="RSL","55","0") -> 0 | K47: =IF(G47="GVS","37.5",IF(G47="GVM","41.5",IF(G47="GVL","50",IF(G47="PCS","45.8",IF(G47="PCM","50",IF(G47="PCL","58.3","0")))))) -> 0
A48: =A47+1 -> 37 | J48: =IF(G48="RSL","55","0") -> 0 | K48: =IF(G48="GVS","37.5",IF(G48="GVM","41.5",IF(G48="GVL","50",IF(G48="PCS","45.8",IF(G48="PCM","50",IF(G48="PCL","58.3","0")))))) -> 0
A49: =A48+1 -> 38 | J49: =IF(G49="RSL","55","0") -> 0 | K49: =IF(G49="GVS","37.5",IF(G49="GVM","41.5",IF(G49="GVL","50",IF(G49="PCS","45.8",IF(G49="PCM","50",IF(G49="PCL","58.3","0")))))) -> 0
... A61: =A60+1 -> 50 | J61: =IF(G61="RSL","55","0") -> 0 | K61: =IF(G61="GVS","37.5",IF(G61="GVM","41.5",IF(G61="GVL","50",IF(G61="PCS","45.8",IF(G61="PCM","50",IF(G61="PCL","58.3","0")))))) -> 0
A62: Page total | H62: =SUM(H37:H61) -> 0 | I62: =SUM(I37:I61) -> 0 | J62: =J61+J60+J59+J58+J57+J56+J55+J54+J53+J52+J51+J50+J49+J48+J47+J46+J45+J44+J43+J42+J41+J40+J39+J38+J37 -> 0 | K62: =K61+K60+K59+K58+K57+K56+K55+K54+K53+K52+K51+K50+K49+K48+K47+K46+K45+K44+K43+K42+K41+K40+K39+K38+K37 -> 0 | L62: =SUM(L37:L61) -> 0 | M62: =SUM(M37:M61) -> 0
R64: Page: 2
A65: Daily Report
A66: =A34 -> 45263 | H66: WEATHER | J66: =J34 -> CLOUDY | L66: REPORT by | O66: =O34 -> HENDRA | R66: TOTAL STAFF | T66: =T34 -> 4
A68: No | B68: Docket No | C68: Reg No | D68: Mobile | E68: Gender | F68: TIME | G68: Service | H68: CASH | I68: CARD | J68: RSL | K68: GV | L68: GV CASH | M68: GV CARD | N68: O/Taker | O68: Comment | R68: NAME | S68: Time In | T68: Time out | U68: Total Hours
A69: =A61+1 -> 51 | J69: =IF(G69="RSL","55","0") -> 0 | K69: =IF(G69="GVS","37.5",IF(G69="GVM","41.5",IF(G69="GVL","50",IF(G69="PCS","45.8",IF(G69="PCM","50",IF(G69="PCL","58.3","0")))))) -> 0
A70: =A69+1 -> 52 | J70: =IF(G70="RSL","55","0") -> 0 | K70: =IF(G70="GVS","37.5",IF(G70="GVM","41.5",IF(G70="GVL","50",IF(G70="PCS","45.8",IF(G70="PCM","50",IF(G70="PCL","58.3","0")))))) -> 0
A71: =A70+1 -> 53 | J71: =IF(G71="RSL","55","0") -> 0 | K71: =IF(G71="GVS","37.5",IF(G71="GVM","41.5",IF(G71="GVL","50",IF(G71="PCS","45.8",IF(G71="PCM","50",IF(G71="PCL","58.3","0")))))) -> 0
A72: =A71+1 -> 54 | J72: =IF(G72="RSL","55","0") -> 0 | K72: =IF(G72="GVS","37.5",IF(G72="GVM","41.5",IF(G72="GVL","50",IF(G72="PCS","45.8",IF(G72="PCM","50",IF(G72="PCL","58.3","0")))))) -> 0
A73: =A72+1 -> 55 | J73: =IF(G73="RSL","55","0") -> 0 | K73: =IF(G73="GVS","37.5",IF(G73="GVM","41.5",IF(G73="GVL","50",IF(G73="PCS","45.8",IF(G73="PCM","50",IF(G73="PCL","58.3","0")))))) -> 0
A74: =A73+1 -> 56 | J74: =IF(G74="RSL","55","0") -> 0 | K74: =IF(G74="GVS","37.5",IF(G74="GVM","41.5",IF(G74="GVL","50",IF(G74="PCS","45.8",IF(G74="PCM","50",IF(G74="PCL","58.3","0")))))) -> 0
A75: =A74+1 -> 57 | J75: =IF(G75="RSL","55","0") -> 0 | K75: =IF(G75="GVS","37.5",IF(G75="GVM","41.5",IF(G75="GVL","50",IF(G75="PCS","45.8",IF(G75="PCM","50",IF(G75="PCL","58.3","0")))))) -> 0
A76: =A75+1 -> 58 | J76: =IF(G76="RSL","55","0") -> 0 | K76: =IF(G76="GVS","37.5",IF(G76="GVM","41.5",IF(G76="GVL","50",IF(G76="PCS","45.8",IF(G76="PCM","50",IF(G76="PCL","58.3","0")))))) -> 0
A77: =A76+1 -> 59 | J77: =IF(G77="RSL","55","0") -> 0 | K77: =IF(G77="GVS","37.5",IF(G77="GVM","41.5",IF(G77="GVL","50",IF(G77="PCS","45.8",IF(G77="PCM","50",IF(G77="PCL","58.3","0")))))) -> 0
A78: =A77+1 -> 60 | J78: =IF(G78="RSL","55","0") -> 0 | K78: =IF(G78="GVS","37.5",IF(G78="GVM","41.5",IF(G78="GVL","50",IF(G78="PCS","45.8",IF(G78="PCM","50",IF(G78="PCL","58.3","0")))))) -> 0
A79: =A78+1 -> 61 | J79: =IF(G79="RSL","55","0") -> 0 | K79: =IF(G79="GVS","37.5",IF(G79="GVM","41.5",IF(G79="GVL","50",IF(G79="PCS","45.8",IF(G79="PCM","50",IF(G79="PCL","58.3","0")))))) -> 0
A80: =A79+1 -> 62 | J80: =IF(G80="RSL","55","0") -> 0 | K80: =IF(G80="GVS","37.5",IF(G80="GVM","41.5",IF(G80="GVL","50",IF(G80="PCS","45.8",IF(G80="PCM","50",IF(G80="PCL","58.3","0")))))) -> 0
A81: =A80+1 -> 63 | J81: =IF(G81="RSL","55","0") -> 0 | K81: =IF(G81="GVS","37.5",IF(G81="GVM","41.5",IF(G81="GVL","50",IF(G81="PCS","45.8",IF(G81="PCM","50",IF(G81="PCL","58.3","0")))))) -> 0
... A93: =A92+1 -> 75 | J93: =IF(G93="RSL","55","0") -> 0 | K93: =IF(G93="GVS","37.5",IF(G93="GVM","41.5",IF(G93="GVL","50",IF(G93="PCS","45.8",IF(G93="PCM","50",IF(G93="PCL","58.3","0")))))) -> 0
A94: Page total | H94: =SUM(H69:H93) -> 0 | I94: =SUM(I69:I93) -> 0 | J94: =J93+J92+J91+J90+J89+J88+J87+J86+J85+J84+J83+J82+J81+J80+J79+J78+J77+J76+J75+J74+J73+J72+J71+J70+J69 -> 0 | K94: =K93+K92+K91+K90+K89+K88+K87+K86+K85+K84+K83+K82+K81+K80+K79+K78+K77+K76+K75+K74+K73+K72+K71+K70+K69 -> 0 | L94: =SUM(L69:L93) -> 0 | M94: =SUM(M69:M93) -> 0
R96: Page: 3

Sheet Sheet1

Sheet WEEKLY TOTAL
E1: CARS | H1: AMOUNT | L1: PERCENTAGE | Q1: TOTAL CARS | V1: TOTAL AMOUNT | AA1: AVERAGE
A2: MON | B2: Cash | E2: =MON!N31 -> 3 | H2: =MON!S31 -> 585 | L2: =MON!N32 -> 0.17168675 | Q2: =SUM(E2:G5) -> 21 | V2: =SUM(H2,H3,H5) -> 2010 | AA2: =V2/Q2 -> 95.714286
B3: Card | E3: =MON!O31 -> 12 | H3: =MON!S32 -> 1425 | L3: =MON!O32 -> 0.57228916
B4: GV | E4: =MON!P31 -> 6 | H4: =MON!K31 -> 425 | L4: =MON!P32 -> 0.2560241
B5: RSL | E5: =MON!Q31 -> 0 | H5: =MON!J31 -> 0 | L5: =MON!Q32 -> 0
B6: hrs | E6: =MON!U16 -> 38.5 | H6: no. staff | L6: =MON!T2 -> 5
A7: TUE | B7: Cash | E7: =TUE!N31 -> 3 | H7: =TUE!S31 -> 320 | L7: =TUE!N32 -> 0.22615161 | Q7: =SUM(E7:G10) -> 16 | V7: =SUM(H7,H8,H10) -> 1290 | AA7: =V7/Q7 -> 80.625
B8: Card | E8: =TUE!O31 -> 7 | H8: =TUE!S32 -> 970 | L8: =TUE!O32 -> 0.47350493
B9: GV | E9: =TUE!P31 -> 6 | H9: =TUE!K31 -> 424.98 | L9: =TUE!P32 -> 0.30034347
B10: RSL | E10: =TUE!Q31 -> 0 | H10: =TUE!J31 -> 0 | L10: =TUE!Q32 -> 0
B11: hrs | E11: =TUE!U16 -> 31 | H11: no. staff | L11: =TUE!T2 -> 4
A12: WED | B12: Cash | E12: =WED!N31 -> 4 | H12: =WED!S31 -> 475 | L12: =WED!N32 -> 0.26389182 | Q12: =SUM(E12:G15) -> 20 | V12: =SUM(H12,H13,H15) -> 2850 | AA12: =V12/Q12 -> 142.5
B13: Card | E13: =WED!O31 -> 8 | H13: =WED!S32 -> 2375 | L13: =WED!O32 -> 0.47222747
B14: GV | E14: =WED!P31 -> 8 | H14: =WED!K31 -> 474.98 | L14: =WED!P32 -> 0.26388071
B15: RSL | E15: =WED!Q31 -> 0 | H15: =WED!J31 -> 0 | L15: =WED!Q32 -> 0
B16: hrs | E16: =WED!U16 -> 38.25 | H16: no. staff | L16: =WED!T2 -> 5
A17: THU | B17: Cash | E17: =THU!N31 -> 4 | H17: =THU!S31 -> 1375 | L17: =THU!N32 -> 0.22693027 | Q17: =SUM(E17:G20) -> 21 | V17: =SUM(H17,H18,H20) -> 3165 | AA17: =V17/Q17 -> 150.71429
B18: Card | E18: =THU!O31 -> 9 | H18: =THU!S32 -> 1790 | L18: =THU!O32 -> 0.5083238
B19: GV | E19: =THU!P31 -> 8 | H19: =THU!K31 -> 437.49 | L19: =THU!P32 -> 0.26474593
B20: RSL | E20: =THU!Q31 -> 0 | H20: =THU!J31 -> 0 | L20: =THU!Q32 -> 0
B21: hrs | E21: =THU!U16 -> 40.5 | H21: no. staff | L21: =THU!T2 -> 6
A22: FR I | B22: Cash | E22: =FRI!N31 -> 6 | H22: =FRI!S31 -> 925 | L22: =FRI!N32 -> 0.37297459 | Q22: =SUM(E22:G25) -> 19 | V22: =SUM(H22,H23,H25) -> 2225 | AA22: =V22/Q22 -> 117.10526
B23: Card | E23: =FRI!O31 -> 9 | H23: =FRI!S32 -> 1240 | L23: =FRI!O32 -> 0.49621836
B24: GV | E24: =FRI!P31 -> 3 | H24: =FRI!K31 -> 141.66 | L24: =FRI!P32 -> 0.091887965
B25: RSL | E25: =FRI!Q31 -> 1 | H25: =FRI!J31 -> 60 | L25: =FRI!Q32 -> 0.038919087
B26: hrs | E26: =FRI!U16 -> 43 | H26: no. staff | L26: =FRI!T2 -> 5
A27: SAT | B27: Cash | E27: =SAT!N31 -> 5 | H27: =SAT!S31 -> 990 | L27: =SAT!N32 -> 0.21972865 | Q27: =SUM(E27:G30) -> 29 | V27: =SUM(H27,H28,H30) -> 3088 | AA27: =V27/Q27 -> 106.48276
B28: Card | E28: =SAT!O31 -> 13 | H28: =SAT!S32 -> 2098 | L28: =SAT!O32 -> 0.43519072
B29: GV | E29: =SAT!P31 -> 11 | H29: =SAT!K31 -> 808.8 | L29: =SAT!P32 -> 0.34508064
B30: RSL | E30: =SAT!Q31 -> 0 | H30: =SAT!J31 -> 0 | L30: =SAT!Q32 -> 0
B31: hrs | E31: =SAT!U16 -> 52 | H31: no. staff | L31: =SAT!T2 -> 7
A32: SUN | B32: Cash | E32: =SUN!N31 -> 4 | H32: =SUN!S31 -> 1010 | L32: =SUN!N32 -> 0.2 | Q32: =SUM(E32:G35) -> 16 | V32: =SUM(H32,H33,H35) -> 1800 | AA32: =V32/Q32 -> 112.5
B33: Card | E33: =SUN!O31 -> 10 | H33: =SUN!S32 -> 790 | L33: =SUN!O32 -> 0.60769231
B34: GV | E34: =SUN!P31 -> 2 | H34: =SUN!K31 -> 250 | L34: =SUN!P32 -> 0.19230769
B35: RSL | E35: =SUN!Q31 -> 0 | H35: =SUN!J31 -> 0 | L35: =SUN!Q32 -> 0
B36: hrs | E36: =SUN!U16 -> 34 | H36: no. staff | L36: =SUN!T2 -> 4
A37: TOTAL CARS | E37: TOTAL SALES | K37: AVERAGE | O37: RSL | T37: GV | Y37: GV SOLD
A39: =SUM(Q2:U35) -> 142 | E39: =SUM(V2:Z35) -> 16428 | K39: =E39/A39 -> 115.69014 | O39: =SUM(MON:SUN!Q31) -> 1 | T39: =SUM(MON:SUN!P31) -> 44 | Y39: =SUM(MON:SUN!S19) -> 19
O41: =SUM(MON:SUN!J31) -> 60 | T41: =SUM(MON:SUN!K31) -> 2962.91 | Y41: =SUM(MON:SUN!T19) -> 7678
A43: TOTAL CASH | F43: TOTAL CARD | K43: TOTAL RSL | P43: TOTAL GV | U43: STAFF HRS | Z43: no. staff
A45: =SUM(H2,H7,H12,H17,H22,H27,H32) -> 5680 | F45: =SUM(,H3,H8,H13,H18,H23,H28,H33) -> 10688 | K45: =SUM(H5,H10,H15,H20,H25,H30,H35) -> 60 | P45: =SUM(H4,H9,H14,H19,H24,H29,H34) -> 2962.91 | U45: =SUM(E6,E11,E16,E21,E26,E31,E36) -> 277.25 | Z45: =SUM(L6,L11,L16,L21,L26,L31,L36) -> 36
A49: =A45/E39 -> 0.34575116 | F49: =F45/E39 -> 0.65059654 | K49: =K45/E39 -> 0.0036523009 | P49: =P45/E39 -> 0.18035732 | U49: =U45/7 -> 39.607143 | Z49: =U45/Z45 -> 7.7013889
