Workbook

Sheet MON
A1: B2 Daily Report
A2: 7-02-2022 | H2: WEATHER | J2: MIX | L2: REPORT BY | O2: JOHN | R2: TOTAL STAFF | T2: 4 | X2: Merchant machine usage at B2 | AA2: Settle amount | AI2: Merchant machine usage at GA | AL2: Settle amount
A4: No | B4: Docket No | C4: Reg No | D4: Mobile | E4: Size | F4: TIME | G4: Service | H4: CASH | I4: CARD | J4: RSL | K4: GV | L4: GV CASH | M4: GV CARD | N4: O/Taker | O4: Comment | R4: NAME | S4: Time In | T4: Time out | U4: Total Hours | Z4: B2 machine | AA4: BLH machine | AB4: Wongo | AE4: B2 machine | AF4: BLH machine | AG4: Wongo | AK4: GA machine | AL4: BLH machine | AM4: Wongo | AP4: GA machine | AQ4: BLH machine | AR4: Wongo
A5: 1 | B5: 3108 | C5: CX10G8 | D5: 0402012082 | E5: L | F5: 800 | G5: D/ST | H5: 150 | J5: =IF(G5="RSL","50","0") -> 0 | K5: =IF(G5="GVS","37.5",IF(G5="GVM","41.5",IF(G5="GVL","50",IF(G5="PCS","45.8",IF(G5="PCM","50",IF(G5="PCL","58.3","0")))))) -> 0 | N5: PETER | R5: JOHN | S5: 0.33333333 | T5: 0.70833333 | U5: =(T5-S5)*24 -> 9 | X5: NOV | Y5: 1 | AD5: 16 | AI5: NOV | AJ5: 1 | AO5: 16
A6: 2 | B6: 3109 | C6: DZE76K | D6: 0428724704 | E6: L | F6: 930 | G6: IN | I6: 80 | J6: =IF(G6="RSL","50","0") -> 0 | K6: =IF(G6="GVS","37.5",IF(G6="GVM","41.5",IF(G6="GVL","50",IF(G6="PCS","45.8",IF(G6="PCM","50",IF(G6="PCL","58.3","0")))))) -> 0 | N6: JOHN | R6: HENDRA | S6: 0.33333333 | T6: 0.70833333 | U6: =(T6-S6)*24 -> 9 | W6: S | Y6: 2 | AD6: 17 | AJ6: 2 | AO6: 17
A7: 3 | B7: 3110 | C7: MI39KU | D7: 0403987772 | E7: S | F7: 940 | G7: X | I7: 60 | J7: =IF(G7="RSL","50","0") -> 0 | K7: =IF(G7="GVS","37.5",IF(G7="GVM","41.5",IF(G7="GVL","50",IF(G7="PCS","45.8",IF(G7="PCM","50",IF(G7="PCL","58.3","0")))))) -> 0 | N7: JOHN | R7: ARIANTO | S7: 0.41666667 | T7: 0.70833333 | U7: =(T7-S7)*24 -> 7 | W7: M | Y7: 3 | AD7: 18 | AJ7: 3 | AO7: 18
A8: 4 | B8: 3111 | C8: EQA93H | D8: 0401530380 | E8: S | F8: 1005 | G8: X | I8: 75 | J8: =IF(G8="RSL","50","0") -> 0 | K8: =IF(G8="GVS","37.5",IF(G8="GVM","41.5",IF(G8="GVL","50",IF(G8="PCS","45.8",IF(G8="PCM","50",IF(G8="PCL","58.3","0")))))) -> 0 | N8: JOHN | R8: KUROSH | S8: 0.41666667 | T8: 0.65625 | U8: =(T8-S8)*24 -> 5.75 | W8: L | Y8: 4 | AD8: 19 | AJ8: 4 | AO8: 19
A9: 5 | B9: 3112 | C9: EJX85L | D9: 0421085336 | E9: S | F9: 1010 | G9: D | I9: 55 | J9: =IF(G9="RSL","50","0") -> 0 | K9: =IF(G9="GVS","37.5",IF(G9="GVM","41.5",IF(G9="GVL","50",IF(G9="PCS","45.8",IF(G9="PCM","50",IF(G9="PCL","58.3","0")))))) -> 0 | N9: JOHN | U9: =(T9-S9)*24 -> 0 | X9: EXCL RSL | Y9: 5 | AD9: 20 | AJ9: 5 | AO9: 20
A10: 6 | B10: 3113 | C10: BKN48F | D10: 0413723556 | E10: L | F10: 1030 | G10: D | I10: 75 | J10: =IF(G10="RSL","50","0") -> 0 | K10: =IF(G10="GVS","37.5",IF(G10="GVM","41.5",IF(G10="GVL","50",IF(G10="PCS","45.8",IF(G10="PCM","50",IF(G10="PCL","58.3","0")))))) -> 0 | N10: JOHN | U10: =(T10-S10)*24 -> 0 | Y10: 6 | AD10: 21 | AJ10: 6 | AO10: 21
A11: 7 | B11: 3114 | C11: BJC14G | D11: 0467680536 | E11: S | F11: 1110 | G11: D | I11: 55 | J11: =IF(G11="RSL","50","0") -> 0 | K11: =IF(G11="GVS","37.5",IF(G11="GVM","41.5",IF(G11="GVL","50",IF(G11="PCS","45.8",IF(G11="PCM","50",IF(G11="PCL","58.3","0")))))) -> 0 | N11: JOHN | U11: =(T11-S11)*24 -> 0 | Y11: 7 | AD11: 22 | AJ11: 7 | AO11: 22
A12: 8 | B12: 3115 | C12: DVE92C | D12: 0415779552 | E12: L | F12: 1205 | G12: D | I12: 75 | J12: =IF(G12="RSL","50","0") -> 0 | K12: =IF(G12="GVS","37.5",IF(G12="GVM","41.5",IF(G12="GVL","50",IF(G12="PCS","45.8",IF(G12="PCM","50",IF(G12="PCL","58.3","0")))))) -> 0 | N12: JOHN | U12: =(T12-S12)*24 -> 0 | Y12: 8 | AD12: 23 | AJ12: 8 | AO12: 23
A13: 9 | B13: 3116 | C13: DPK65Y | D13: 0413884883 | E13: L | F13: 1305 | G13: X | I13: 95 | J13: =IF(G13="RSL","50","0") -> 0 | K13: =IF(G13="GVS","37.5",IF(G13="GVM","41.5",IF(G13="GVL","50",IF(G13="PCS","45.8",IF(G13="PCM","50",IF(G13="PCL","58.3","0")))))) -> 0 | N13: JOHN | U13: =(T13-S13)*24 -> 0 | Y13: 9 | AD13: 24 | AJ13: 9 | AO13: 24
A14: 10 | J14: =IF(G14="RSL","50","0") -> 0 | K14: =IF(G14="GVS","37.5",IF(G14="GVM","41.5",IF(G14="GVL","50",IF(G14="PCS","45.8",IF(G14="PCM","50",IF(G14="PCL","58.3","0")))))) -> 0 | U14: =(T14-S14)*24 -> 0 | Y14: 10 | AD14: 25 | AJ14: 10 | AO14: 25
A15: 11 | J15: =IF(G15="RSL","50","0") -> 0 | K15: =IF(G15="GVS","37.5",IF(G15="GVM","41.5",IF(G15="GVL","50",IF(G15="PCS","45.8",IF(G15="PCM","50",IF(G15="PCL","58.3","0")))))) -> 0 | U15: =(T15-S15)*24 -> 0 | Y15: 11 | AD15: 26 | AJ15: 11 | AO15: 26
A16: 12 | J16: =IF(G16="RSL","50","0") -> 0 | K16: =IF(G16="GVS","37.5",IF(G16="GVM","41.5",IF(G16="GVL","50",IF(G16="PCS","45.8",IF(G16="PCM","50",IF(G16="PCL","58.3","0")))))) -> 0 | R16: =H32/U16 -> 0.29268293 | S16: =H32/(U16-U5) -> 0.4137931 | T16: =C32/U16 -> 23.414634 | U16: =SUM(U5:U15) -> 30.75 | Y16: 12 | AD16: 27 | AJ16: 12 | AO16: 27
A17: 13 | J17: =IF(G17="RSL","50","0") -> 0 | K17: =IF(G17="GVS","37.5",IF(G17="GVM","41.5",IF(G17="GVL","50",IF(G17="PCS","45.8",IF(G17="PCM","50",IF(G17="PCL","58.3","0")))))) -> 0 | R17: Cars/T Hr ① | S17: Cars/T Hr ② | T17: Sales/T Hr | U17: Total Hours | Y17: 13 | AD17: 28 | AJ17: 13 | AO17: 28
A18: 14 | J18: =IF(G18="RSL","50","0") -> 0 | K18: =IF(G18="GVS","37.5",IF(G18="GVM","41.5",IF(G18="GVL","50",IF(G18="PCS","45.8",IF(G18="PCM","50",IF(G18="PCL","58.3","0")))))) -> 0 | R18: ITEM | S18: QTY | T18: AMT | U18: RMKS | Y18: 14 | AD18: 29 | AJ18: 14 | AO18: 29
A19: 15 | J19: =IF(G19="RSL","50","0") -> 0 | K19: =IF(G19="GVS","37.5",IF(G19="GVM","41.5",IF(G19="GVL","50",IF(G19="PCS","45.8",IF(G19="PCM","50",IF(G19="PCL","58.3","0")))))) -> 0 | R19: GV | S19: =COUNT(L5:M29,L37:M61,L69:M93) -> 0 | T19: =SUM(L5:M29,L37:M61,L69:M93) -> 0 | Y19: 15 | AD19: 30 | AJ19: 15 | AO19: 30
A20: 16 | J20: =IF(G20="RSL","50","0") -> 0 | K20: =IF(G20="GVS","37.5",IF(G20="GVM","41.5",IF(G20="GVL","50",IF(G20="PCS","45.8",IF(G20="PCM","50",IF(G20="PCL","58.3","0")))))) -> 0 | AD20: 31 | AO20: 31
A21: 17 | J21: =IF(G21="RSL","50","0") -> 0 | K21: =IF(G21="GVS","37.5",IF(G21="GVM","41.5",IF(G21="GVL","50",IF(G21="PCS","45.8",IF(G21="PCM","50",IF(G21="PCL","58.3","0")))))) -> 0
A22: 18 | J22: =IF(G22="RSL","50","0") -> 0 | K22: =IF(G22="GVS","37.5",IF(G22="GVM","41.5",IF(G22="GVL","50",IF(G22="PCS","45.8",IF(G22="PCM","50",IF(G22="PCL","58.3","0")))))) -> 0 | AD22: Total | AE22: =SUM(Z5:Z19,AE5:AE20) -> 0 | AF22: =SUM(AA5:AA19,AF5:AF20,) -> 0 | AG22: =SUM(AB5:AB19,AG5:AG20) -> 0 | AO22: Total | AP22: =SUM(AK5:AK19,AP5:AP20) -> 0 | AQ22: =SUM(AL5:AL19,AQ5:AQ20,) -> 0 | AR22: =SUM(AM5:AM19,AR5:AR20) -> 0
A23: 19 | J23: =IF(G23="RSL","50","0") -> 0 | K23: =IF(G23="GVS","37.5",IF(G23="GVM","41.5",IF(G23="GVL","50",IF(G23="PCS","45.8",IF(G23="PCM","50",IF(G23="PCL","58.3","0")))))) -> 0
A24: 20 | J24: =IF(G24="RSL","50","0") -> 0 | K24: =IF(G24="GVS","37.5",IF(G24="GVM","41.5",IF(G24="GVL","50",IF(G24="PCS","45.8",IF(G24="PCM","50",IF(G24="PCL","58.3","0")))))) -> 0 | R24: SMALL | S24: MEDIUM | T24: LARGE | U24: TOTAL | AD24: B2/GA TOTAL | AE24: B2 machine | AF24: GA machine | AG24: BLH machine | AH24: Wongo machine | AI24: Sub total
A25: 21 | J25: =IF(G25="RSL","50","0") -> 0 | K25: =IF(G25="GVS","37.5",IF(G25="GVM","41.5",IF(G25="GVL","50",IF(G25="PCS","45.8",IF(G25="PCM","50",IF(G25="PCL","58.3","0")))))) -> 0 | R25: =COUNTIF(G5:G29,"GV1")+COUNTIF(G37:G61,"GV1")+COUNTIF(G69:G93,"GV1") -> 0 | S25: =COUNTIF(G5:G29,"GV2")+COUNTIF(G37:G61,"GV2")+COUNTIF(G69:G93,"GV2") -> 0 | T25: =COUNTIF(G5:G29,"GV3")+COUNTIF(G37:G61,"GV3")+COUNTIF(G69:G93,"GV3") -> 0 | U25: =((C32+(R26+S26+T26)*0.5)) -> 720 | AD25: =SUM(AE25:AF25) -> 0 | AE25: =SUM(AE22) -> 0 | AF25: =SUM(AP22) -> 0 | AG25: =SUM(AF22+AQ22) -> 0 | AH25: =AG22+AR22 -> 0 | AI25: =SUM(AE25:AH25) -> 0
A26: 22 | J26: =IF(G26="RSL","50","0") -> 0 | K26: =IF(G26="GVS","37.5",IF(G26="GVM","41.5",IF(G26="GVL","50",IF(G26="PCS","45.8",IF(G26="PCM","50",IF(G26="PCL","58.3","0")))))) -> 0 | R26: =R25*37.5 -> 0 | S26: =S25*41.5 -> 0 | T26: =T25*50 -> 0 | X26: Branch cards
A27: 23 | J27: =IF(G27="RSL","50","0") -> 0 | K27: =IF(G27="GVS","37.5",IF(G27="GVM","41.5",IF(G27="GVL","50",IF(G27="PCS","45.8",IF(G27="PCM","50",IF(G27="PCL","58.3","0")))))) -> 0 | R27: Expense | X27: 1 | Z27: -2745
A28: 24 | J28: =IF(G28="RSL","50","0") -> 0 | K28: =IF(G28="GVS","37.5",IF(G28="GVM","41.5",IF(G28="GVL","50",IF(G28="PCS","45.8",IF(G28="PCM","50",IF(G28="PCL","58.3","0")))))) -> 0 | X28: 2
A29: 25 | J29: =IF(G29="RSL","50","0") -> 0 | K29: =IF(G29="GVS","37.5",IF(G29="GVM","41.5",IF(G29="GVL","50",IF(G29="PCS","45.8",IF(G29="PCM","50",IF(G29="PCL","58.3","0")))))) -> 0 | X29: 3
A30: Page total | H30: =SUM(H5:H29) -> 150 | I30: =SUM(I5:I29) -> 570 | J30: =J5+J6+J7+J8+J9+J10+J11+J12+J13+J14+J15+J16+J18+J19+J17+J20+J22+J23+J21+J24+J25+J26+J27+J28+J29 -> 0 | K30: =K5+K6+K7+K8+K9+K10+K11+K12+K13+K14+K15+K16+K18+K19+K17+K20+K22+K23+K21+K24+K25+K26+K27+K28+K29 -> 0 | L30: =SUM(L5:L29) -> 0 | M30: =SUM(M5:M29) -> 0 | N30: CASH | O30: CARD | P30: GV | Q30: RSL | X30: 4
A31: Daily Total | H31: =H30+H62+H94 -> 150 | I31: =I30+I62+I94 -> 570 | J31: =J30+J62+J94 -> 0 | K31: =K30+K62+K94 -> 0 | L31: =L30+L62+L94 -> 0 | M31: =M30+M62+M94 -> 0 | N31: =COUNT(H5:H29,H37:H61,H69:H93) -> 1 | O31: =COUNT(I5:I29,I37:I61,I69:I93) -> 8 | P31: =COUNTIF(G5:G29,"G*")+COUNTIF(G37:G61,"G*")+COUNTIF(G69:G93,"G*")+COUNTIF(G5:G29,"P*")+COUNTIF(G37:G61,"P*")+COUNTIF(G69:G93,"P*") -> 0 | Q31: =COUNTIF(G5:G29,"RSL")+COUNTIF(G37:G61,"RSL")+COUNTIF(G69:G93,"RSL") -> 0 | R31: CASH CLOSING | S31: =H31+L31-U28-U29-U30 -> 150 | T31: =H31+I31+L31+M31 -> 720 | X31: Subtotal | Z31: =SUM(Z27:Z30) -> -2745
A32: TOTAL SALES | C32: =H31+I31+J31+K31 -> 720 | F32: No of Cars | H32: =COUNT(B5:B29,B37:B61,B69:B93) -> 9 | I32: Average | K32: =C32/H32 -> 80 | N32: =H31/C32 -> 0.20833333 | O32: =I31/C32 -> 0.79166667 | P32: =K31/C32 -> 0 | Q32: =J31/C32 -> 0 | R32: CARD CLOSING | S32: =I31+M31 -> 570 | X32: B2 card | Z32: =I31 -> 570
A33: Daily Report | X33: Settlement | Z33: =SUM(Z31:Z32) -> -2175
A34: =A2 -> 7-02-2022 | H34: WEATHER | J34: =J2 -> MIX | L34: REPORT by | O34: =O2 -> JOHN | R34: TOTAL STAFF | T34: =T2 -> 4
A36: No | B36: Docket No | C36: Reg No | D36: Mobile | E36: Size | F36: TIME | G36: Service | H36: CASH | I36: CARD | J36: RSL | K36: GV | L36: GV CASH | M36: GV CARD | N36: O/Taker | O36: Comment | R36: NAME | S36: Time In | T36: Time out | U36: Total Hours
A37: =A29+1 -> 26 | J37: =IF(G37="RSL","50","0") -> 0 | K37: =IF(G37="GVS","37.5",IF(G37="GVM","41.5",IF(G37="GVL","50",IF(G37="PCS","45.8",IF(G37="PCM","50",IF(G37="PCL","58.3","0")))))) -> 0
A38: =A37+1 -> 27 | J38: =IF(G38="RSL","50","0") -> 0 | K38: =IF(G38="GVS","37.5",IF(G38="GVM","41.5",IF(G38="GVL","50",IF(G38="PCS","45.8",IF(G38="PCM","50",IF(G38="PCL","58.3","0")))))) -> 0
A39: =A38+1 -> 28 | J39: =IF(G39="RSL","50","0") -> 0 | K39: =IF(G39="GVS","37.5",IF(G39="GVM","41.5",IF(G39="GVL","50",IF(G39="PCS","45.8",IF(G39="PCM","50",IF(G39="PCL","58.3","0")))))) -> 0
A40: =A39+1 -> 29 | J40: =IF(G40="RSL","50","0") -> 0 | K40: =IF(G40="GVS","37.5",IF(G40="GVM","41.5",IF(G40="GVL","50",IF(G40="PCS","45.8",IF(G40="PCM","50",IF(G40="PCL","58.3","0")))))) -> 0
A41: =A40+1 -> 30 | J41: =IF(G41="RSL","50","0") -> 0 | K41: =IF(G41="GVS","37.5",IF(G41="GVM","41.5",IF(G41="GVL","50",IF(G41="PCS","45.8",IF(G41="PCM","50",IF(G41="PCL","58.3","0")))))) -> 0
A42: =A41+1 -> 31 | J42: =IF(G42="RSL","50","0") -> 0 | K42: =IF(G42="GVS","37.5",IF(G42="GVM","41.5",IF(G42="GVL","50",IF(G42="PCS","45.8",IF(G42="PCM","50",IF(G42="PCL","58.3","0")))))) -> 0
A43: =A42+1 -> 32 | J43: =IF(G43="RSL","50","0") -> 0 | K43: =IF(G43="GVS","37.5",IF(G43="GVM","41.5",IF(G43="GVL","50",IF(G43="PCS","45.8",IF(G43="PCM","50",IF(G43="PCL","58.3","0")))))) -> 0
A44: =A43+1 -> 33 | J44: =IF(G44="RSL","50","0") -> 0 | K44: =IF(G44="GVS","37.5",IF(G44="GVM","41.5",IF(G44="GVL","50",IF(G44="PCS","45.8",IF(G44="PCM","50",IF(G44="PCL","58.3","0")))))) -> 0
A45: =A44+1 -> 34 | J45: =IF(G45="RSL","50","0") -> 0 | K45: =IF(G45="GVS","37.5",IF(G45="GVM","41.5",IF(G45="GVL","50",IF(G45="PCS","45.8",IF(G45="PCM","50",IF(G45="PCL","58.3","0")))))) -> 0
A46: =A45+1 -> 35 | J46: =IF(G46="RSL","50","0") -> 0 | K46: =IF(G46="GVS","37.5",IF(G46="GVM","41.5",IF(G46="GVL","50",IF(G46="PCS","45.8",IF(G46="PCM","50",IF(G46="PCL","58.3","0")))))) -> 0
A47: =A46+1 -> 36 | J47: =IF(G47="RSL","50","0") -> 0 | K47: =IF(G47="GVS","37.5",IF(G47="GVM","41.5",IF(G47="GVL","50",IF(G47="PCS","45.8",IF(G47="PCM","50",IF(G47="PCL","58.3","0")))))) -> 0
A48: =A47+1 -> 37 | J48: =IF(G48="RSL","50","0") -> 0 | K48: =IF(G48="GVS","37.5",IF(G48="GVM","41.5",IF(G48="GVL","50",IF(G48="PCS","45.8",IF(G48="PCM","50",IF(G48="PCL","58.3","0")))))) -> 0
A49: =A48+1 -> 38 | J49: =IF(G49="RSL","50","0") -> 0 | K49: =IF(G49="GVS","37.5",IF(G49="GVM","41.5",IF(G49="GVL","50",IF(G49="PCS","45.8",IF(G49="PCM","50",IF(G49="PCL","58.3","0")))))) -> 0
... A61: =A60+1 -> 50 | J61: =IF(G61="RSL","50","0") -> 0 | K61: =IF(G61="GVS","37.5",IF(G61="GVM","41.5",IF(G61="GVL","50",IF(G61="PCS","45.8",IF(G61="PCM","50",IF(G61="PCL","58.3","0")))))) -> 0
A62: Page total | H62: =SUM(H37:H61) -> 0 | I62: =SUM(I37:I61) -> 0 | J62: =J61+J60+J59+J58+J57+J56+J55+J54+J53+J52+J51+J50+J49+J48+J47+J46+J45+J44+J43+J42+J41+J40+J39+J38+J37 -> 0 | K62: =K61+K60+K59+K58+K57+K56+K55+K54+K53+K52+K51+K50+K49+K48+K47+K46+K45+K44+K43+K42+K41+K40+K39+K38+K37 -> 0 | L62: =SUM(L37:L61) -> 0 | M62: =SUM(M37:M61) -> 0
R64: Page: 2
A65: Daily Report
A66: =A34 -> 7-02-2022 | H66: WEATHER | J66: =J34 -> MIX | L66: REPORT by | O66: =O34 -> JOHN | R66: TOTAL STAFF | T66: =T34 -> 4
A68: No | B68: Docket No | C68: Reg No | D68: Mobile | E68: Size | F68: TIME | G68: Service | H68: CASH | I68: CARD | J68: RSL | K68: GV | L68: GV CASH | M68: GV CARD | N68: O/Taker | O68: Comment | R68: NAME | S68: Time In | T68: Time out | U68: Total Hours
A69: =A61+1 -> 51 | J69: =IF(G69="RSL","50","0") -> 0 | K69: =IF(G69="GVS","37.5",IF(G69="GVM","41.5",IF(G69="GVL","50",IF(G69="PCS","45.8",IF(G69="PCM","50",IF(G69="PCL","58.3","0")))))) -> 0
A70: =A69+1 -> 52 | J70: =IF(G70="RSL","50","0") -> 0 | K70: =IF(G70="GVS","37.5",IF(G70="GVM","41.5",IF(G70="GVL","50",IF(G70="PCS","45.8",IF(G70="PCM","50",IF(G70="PCL","58.3","0")))))) -> 0
A71: =A70+1 -> 53 | J71: =IF(G71="RSL","50","0") -> 0 | K71: =IF(G71="GVS","37.5",IF(G71="GVM","41.5",IF(G71="GVL","50",IF(G71="PCS","45.8",IF(G71="PCM","50",IF(G71="PCL","58.3","0")))))) -> 0
A72: =A71+1 -> 54 | J72: =IF(G72="RSL","50","0") -> 0 | K72: =IF(G72="GVS","37.5",IF(G72="GVM","41.5",IF(G72="GVL","50",IF(G72="PCS","45.8",IF(G72="PCM","50",IF(G72="PCL","58.3","0")))))) -> 0
A73: =A72+1 -> 55 | J73: =IF(G73="RSL","50","0") -> 0 | K73: =IF(G73="GVS","37.5",IF(G73="GVM","41.5",IF(G73="GVL","50",IF(G73="PCS","45.8",IF(G73="PCM","50",IF(G73="PCL","58.3","0")))))) -> 0
A74: =A73+1 -> 56 | J74: =IF(G74="RSL","50","0") -> 0 | K74: =IF(G74="GVS","37.5",IF(G74="GVM","41.5",IF(G74="GVL","50",IF(G74="PCS","45.8",IF(G74="PCM","50",IF(G74="PCL","58.3","0")))))) -> 0
A75: =A74+1 -> 57 | J75: =IF(G75="RSL","50","0") -> 0 | K75: =IF(G75="GVS","37.5",IF(G75="GVM","41.5",IF(G75="GVL","50",IF(G75="PCS","45.8",IF(G75="PCM","50",IF(G75="PCL","58.3","0")))))) -> 0
A76: =A75+1 -> 58 | J76: =IF(G76="RSL","50","0") -> 0 | K76: =IF(G76="GVS","37.5",IF(G76="GVM","41.5",IF(G76="GVL","50",IF(G76="PCS","45.8",IF(G76="PCM","50",IF(G76="PCL","58.3","0")))))) -> 0
A77: =A76+1 -> 59 | J77: =IF(G77="RSL","50","0") -> 0 | K77: =IF(G77="GVS","37.5",IF(G77="GVM","41.5",IF(G77="GVL","50",IF(G77="PCS","45.8",IF(G77="PCM","50",IF(G77="PCL","58.3","0")))))) -> 0
A78: =A77+1 -> 60 | J78: =IF(G78="RSL","50","0") -> 0 | K78: =IF(G78="GVS","37.5",IF(G78="GVM","41.5",IF(G78="GVL","50",IF(G78="PCS","45.8",IF(G78="PCM","50",IF(G78="PCL","58.3","0")))))) -> 0
A79: =A78+1 -> 61 | J79: =IF(G79="RSL","50","0") -> 0 | K79: =IF(G79="GVS","37.5",IF(G79="GVM","41.5",IF(G79="GVL","50",IF(G79="PCS","45.8",IF(G79="PCM","50",IF(G79="PCL","58.3","0")))))) -> 0
A80: =A79+1 -> 62 | J80: =IF(G80="RSL","50","0") -> 0 | K80: =IF(G80="GVS","37.5",IF(G80="GVM","41.5",IF(G80="GVL","50",IF(G80="PCS","45.8",IF(G80="PCM","50",IF(G80="PCL","58.3","0")))))) -> 0
A81: =A80+1 -> 63 | J81: =IF(G81="RSL","50","0") -> 0 | K81: =IF(G81="GVS","37.5",IF(G81="GVM","41.5",IF(G81="GVL","50",IF(G81="PCS","45.8",IF(G81="PCM","50",IF(G81="PCL","58.3","0")))))) -> 0
... A93: =A92+1 -> 75 | J93: =IF(G93="RSL","50","0") -> 0 | K93: =IF(G93="GVS","37.5",IF(G93="GVM","41.5",IF(G93="GVL","50",IF(G93="PCS","45.8",IF(G93="PCM","50",IF(G93="PCL","58.3","0")))))) -> 0
A94: Page total | H94: =SUM(H69:H93) -> 0 | I94: =SUM(I69:I93) -> 0 | J94: =J93+J92+J91+J90+J89+J88+J87+J86+J85+J84+J83+J82+J81+J80+J79+J78+J77+J76+J75+J74+J73+J72+J71+J70+J69 -> 0 | K94: =K93+K92+K91+K90+K89+K88+K87+K86+K85+K84+K83+K82+K81+K80+K79+K78+K77+K76+K75+K74+K73+K72+K71+K70+K69 -> 0 | L94: =SUM(L69:L93) -> 0 | M94: =SUM(M69:M93) -> 0
R96: Page: 3

Sheet TUE
A1: B2 Daily Report
A2: 8-02-2022 | H2: WEATHER | J2: SUNNY | L2: REPORT BY | O2: JOHN | R2: TOTAL STAFF | T2: 5 | X2: Merchant machine usage at B2 | AA2: Settle amount | AI2: Merchant machine usage at GA | AL2: Settle amount
A4: No | B4: Docket No | C4: Reg No | D4: Mobile | E4: Size | F4: TIME | G4: Service | H4: CASH | I4: CARD | J4: RSL | K4: GV | L4: GV CASH | M4: GV CARD | N4: O/Taker | O4: Comment | R4: NAME | S4: Time In | T4: Time out | U4: Total Hours | Z4: B2 machine | AA4: BLH machine | AB4: Wongo | AE4: B2 machine | AF4: BLH machine | AG4: Wongo | AK4: GA machine | AL4: BLH machine | AM4: Wongo | AP4: GA machine | AQ4: BLH machine | AR4: Wongo
A5: 1 | B5: 3117 | C5: DFZ53M | D5: 0451185659 | E5: S | F5: 905 | G5: PCL | J5: =IF(G5="RSL","50","0") -> 0 | K5: 79.1 | N5: JOHN | O5: 21062(3/6) | R5: JOHN | S5: 0.33333333 | T5: 0.70833333 | U5: =(T5-S5)*24 -> 9 | X5: NOV | Y5: 1 | AD5: 16 | AI5: NOV | AJ5: 1 | AO5: 16
A6: 2 | B6: 3118 | C6: DBK20Y | D6: 0439402104 | E6: L | F6: 950 | G6: F/D | I6: 450 | J6: =IF(G6="RSL","50","0") -> 0 | K6: =IF(G6="GVS","37.5",IF(G6="GVM","41.5",IF(G6="GVL","50",IF(G6="PCS","45.8",IF(G6="PCM","50",IF(G6="PCL","58.3","0")))))) -> 0 | N6: JOHN | R6: HENDRA | S6: 0.33333333 | T6: 0.66666667 | U6: =(T6-S6)*24 -> 8 | W6: S | Y6: 2 | AD6: 17 | AJ6: 2 | AO6: 17
A7: 3 | B7: 3119 | C7: CI37CC | D7: 0412822385 | E7: S | F7: 1135 | G7: H | I7: 120 | J7: =IF(G7="RSL","50","0") -> 0 | K7: =IF(G7="GVS","37.5",IF(G7="GVM","41.5",IF(G7="GVL","50",IF(G7="PCS","45.8",IF(G7="PCM","50",IF(G7="PCL","58.3","0")))))) -> 0 | M7: 375 | N7: JOHN | O7: 22001(NEW) | R7: ARIANTO | S7: 0.41666667 | T7: 0.66666667 | U7: =(T7-S7)*24 -> 6 | W7: M | Y7: 3 | AD7: 18 | AJ7: 3 | AO7: 18
A8: 4 | B8: 3120 | C8: GABZ | D8: 0404444048 | E8: S | F8: 1240 | G8: X | I8: 75 | J8: =IF(G8="RSL","50","0") -> 0 | K8: =IF(G8="GVS","37.5",IF(G8="GVM","41.5",IF(G8="GVL","50",IF(G8="PCS","45.8",IF(G8="PCM","50",IF(G8="PCL","58.3","0")))))) -> 0 | N8: JOHN | R8: JUNIOR | S8: 0.34375 | T8: 0.70833333 | U8: =(T8-S8)*24 -> 8.75 | W8: L | Y8: 4 | AD8: 19 | AJ8: 4 | AO8: 19
A9: 5 | B9: 3121 | C9: EKH64Y | D9: 0479077655 | E9: L | F9: 1430 | G9: X | I9: 95 | J9: =IF(G9="RSL","50","0") -> 0 | K9: =IF(G9="GVS","37.5",IF(G9="GVM","41.5",IF(G9="GVL","50",IF(G9="PCS","45.8",IF(G9="PCM","50",IF(G9="PCL","58.3","0")))))) -> 0 | N9: JOHN | R9: HEATHER | S9: 0.41666667 | T9: 0.6875 | U9: =(T9-S9)*24 -> 6.5 | X9: EXCL RSL | Y9: 5 | AD9: 20 | AJ9: 5 | AO9: 20
A10: 6 | B10: 3122 | C10: EBF61F | D10: 0414858897 | E10: S | F10: 1430 | G10: PCL | J10: =IF(G10="RSL","50","0") -> 0 | K10: 100 | N10: JOHN | O10: 21053(5/6) | U10: =(T10-S10)*24 -> 0 | Y10: 6 | AD10: 21 | AJ10: 6 | AO10: 21
A11: 7 | B11: 3123 | C11: DLJ38W | D11: 0404340669 | E11: S | F11: 1640 | G11: X | I11: 75 | J11: =IF(G11="RSL","50","0") -> 0 | K11: =IF(G11="GVS","37.5",IF(G11="GVM","41.5",IF(G11="GVL","50",IF(G11="PCS","45.8",IF(G11="PCM","50",IF(G11="PCL","58.3","0")))))) -> 0 | U11: =(T11-S11)*24 -> 0 | Y11: 7 | AD11: 22 | AJ11: 7 | AO11: 22
A12: 8 | J12: =IF(G12="RSL","50","0") -> 0 | K12: =IF(G12="GVS","37.5",IF(G12="GVM","41.5",IF(G12="GVL","50",IF(G12="PCS","45.8",IF(G12="PCM","50",IF(G12="PCL","58.3","0")))))) -> 0 | U12: =(T12-S12)*24 -> 0 | Y12: 8 | AD12: 23 | AJ12: 8 | AO12: 23
A13: 9 | J13: =IF(G13="RSL","50","0") -> 0 | K13: =IF(G13="GVS","37.5",IF(G13="GVM","41.5",IF(G13="GVL","50",IF(G13="PCS","45.8",IF(G13="PCM","50",IF(G13="PCL","58.3","0")))))) -> 0 | U13: =(T13-S13)*24 -> 0 | Y13: 9 | AD13: 24 | AJ13: 9 | AO13: 24
A14: 10 | J14: =IF(G14="RSL","50","0") -> 0 | K14: =IF(G14="GVS","37.5",IF(G14="GVM","41.5",IF(G14="GVL","50",IF(G14="PCS","45.8",IF(G14="PCM","50",IF(G14="PCL","58.3","0")))))) -> 0 | U14: =(T14-S14)*24 -> 0 | Y14: 10 | AD14: 25 | AJ14: 10 | AO14: 25
A15: 11 | J15: =IF(G15="RSL","50","0") -> 0 | K15: =IF(G15="GVS","37.5",IF(G15="GVM","41.5",IF(G15="GVL","50",IF(G15="PCS","45.8",IF(G15="PCM","50",IF(G15="PCL","58.3","0")))))) -> 0 | U15: =(T15-S15)*24 -> 0 | Y15: 11 | AD15: 26 | AJ15: 11 | AO15: 26
A16: 12 | J16: =IF(G16="RSL","50","0") -> 0 | K16: =IF(G16="GVS","37.5",IF(G16="GVM","41.5",IF(G16="GVL","50",IF(G16="PCS","45.8",IF(G16="PCM","50",IF(G16="PCL","58.3","0")))))) -> 0 | R16: =H32/U16 -> 0.18300654 | S16: =H32/(U16-U5) -> 0.23931624 | T16: =C32/U16 -> 25.989542 | U16: =SUM(U5:U15) -> 38.25 | Y16: 12 | AD16: 27 | AJ16: 12 | AO16: 27
A17: 13 | J17: =IF(G17="RSL","50","0") -> 0 | K17: =IF(G17="GVS","37.5",IF(G17="GVM","41.5",IF(G17="GVL","50",IF(G17="PCS","45.8",IF(G17="PCM","50",IF(G17="PCL","58.3","0")))))) -> 0 | R17: Cars/T Hr ① | S17: Cars/T Hr ② | T17: Sales/T Hr | U17: Total Hours | Y17: 13 | AD17: 28 | AJ17: 13 | AO17: 28
A18: 14 | J18: =IF(G18="RSL","50","0") -> 0 | K18: =IF(G18="GVS","37.5",IF(G18="GVM","41.5",IF(G18="GVL","50",IF(G18="PCS","45.8",IF(G18="PCM","50",IF(G18="PCL","58.3","0")))))) -> 0 | R18: ITEM | S18: QTY | T18: AMT | U18: RMKS | Y18: 14 | AD18: 29 | AJ18: 14 | AO18: 29
A19: 15 | J19: =IF(G19="RSL","50","0") -> 0 | K19: =IF(G19="GVS","37.5",IF(G19="GVM","41.5",IF(G19="GVL","50",IF(G19="PCS","45.8",IF(G19="PCM","50",IF(G19="PCL","58.3","0")))))) -> 0 | R19: GV | S19: =COUNT(L5:M29,L37:M61,L69:M93) -> 1 | T19: =SUM(L5:M29,L37:M61,L69:M93) -> 375 | Y19: 15 | AD19: 30 | AJ19: 15 | AO19: 30
A20: 16 | J20: =IF(G20="RSL","50","0") -> 0 | K20: =IF(G20="GVS","37.5",IF(G20="GVM","41.5",IF(G20="GVL","50",IF(G20="PCS","45.8",IF(G20="PCM","50",IF(G20="PCL","58.3","0")))))) -> 0 | AD20: 31 | AO20: 31
A21: 17 | J21: =IF(G21="RSL","50","0") -> 0 | K21: =IF(G21="GVS","37.5",IF(G21="GVM","41.5",IF(G21="GVL","50",IF(G21="PCS","45.8",IF(G21="PCM","50",IF(G21="PCL","58.3","0")))))) -> 0
A22: 18 | J22: =IF(G22="RSL","50","0") -> 0 | K22: =IF(G22="GVS","37.5",IF(G22="GVM","41.5",IF(G22="GVL","50",IF(G22="PCS","45.8",IF(G22="PCM","50",IF(G22="PCL","58.3","0")))))) -> 0 | AD22: Total | AE22: =SUM(Z5:Z19,AE5:AE20) -> 0 | AF22: =SUM(AA5:AA19,AF5:AF20,) -> 0 | AG22: =SUM(AB5:AB19,AG5:AG20) -> 0 | AO22: Total | AP22: =SUM(AK5:AK19,AP5:AP20) -> 0 | AQ22: =SUM(AL5:AL19,AQ5:AQ20,) -> 0 | AR22: =SUM(AM5:AM19,AR5:AR20) -> 0
A23: 19 | J23: =IF(G23="RSL","50","0") -> 0 | K23: =IF(G23="GVS","37.5",IF(G23="GVM","41.5",IF(G23="GVL","50",IF(G23="PCS","45.8",IF(G23="PCM","50",IF(G23="PCL","58.3","0")))))) -> 0
A24: 20 | J24: =IF(G24="RSL","50","0") -> 0 | K24: =IF(G24="GVS","37.5",IF(G24="GVM","41.5",IF(G24="GVL","50",IF(G24="PCS","45.8",IF(G24="PCM","50",IF(G24="PCL","58.3","0")))))) -> 0 | R24: SMALL | S24: MEDIUM | T24: LARGE | U24: TOTAL | AD24: B2/GA TOTAL | AE24: B2 machine | AF24: GA machine | AG24: BLH machine | AH24: Wongo machine | AI24: Sub total
A25: 21 | J25: =IF(G25="RSL","50","0") -> 0 | K25: =IF(G25="GVS","37.5",IF(G25="GVM","41.5",IF(G25="GVL","50",IF(G25="PCS","45.8",IF(G25="PCM","50",IF(G25="PCL","58.3","0")))))) -> 0 | R25: =COUNTIF(G5:G29,"GV1")+COUNTIF(G37:G61,"GV1")+COUNTIF(G69:G93,"GV1") -> 0 | S25: =COUNTIF(G5:G29,"GV2")+COUNTIF(G37:G61,"GV2")+COUNTIF(G69:G93,"GV2") -> 0 | T25: =COUNTIF(G5:G29,"GV3")+COUNTIF(G37:G61,"GV3")+COUNTIF(G69:G93,"GV3") -> 0 | U25: =((C32+(R26+S26+T26)*0.5)) -> 994.1 | AD25: =SUM(AE25:AF25) -> 0 | AE25: =SUM(AE22) -> 0 | AF25: =SUM(AP22) -> 0 | AG25: =SUM(AF22+AQ22) -> 0 | AH25: =AG22+AR22 -> 0 | AI25: =SUM(AE25:AH25) -> 0
A26: 22 | J26: =IF(G26="RSL","50","0") -> 0 | K26: =IF(G26="GVS","37.5",IF(G26="GVM","41.5",IF(G26="GVL","50",IF(G26="PCS","45.8",IF(G26="PCM","50",IF(G26="PCL","58.3","0")))))) -> 0 | R26: =R25*37.5 -> 0 | S26: =S25*41.5 -> 0 | T26: =T25*50 -> 0 | X26: Branch cards
A27: 23 | J27: =IF(G27="RSL","50","0") -> 0 | K27: =IF(G27="GVS","37.5",IF(G27="GVM","41.5",IF(G27="GVL","50",IF(G27="PCS","45.8",IF(G27="PCM","50",IF(G27="PCL","58.3","0")))))) -> 0 | R27: Expense | X27: 1 | Z27: -2745
A28: 24 | J28: =IF(G28="RSL","50","0") -> 0 | K28: =IF(G28="GVS","37.5",IF(G28="GVM","41.5",IF(G28="GVL","50",IF(G28="PCS","45.8",IF(G28="PCM","50",IF(G28="PCL","58.3","0")))))) -> 0 | X28: 2
A29: 25 | J29: =IF(G29="RSL","50","0") -> 0 | K29: =IF(G29="GVS","37.5",IF(G29="GVM","41.5",IF(G29="GVL","50",IF(G29="PCS","45.8",IF(G29="PCM","50",IF(G29="PCL","58.3","0")))))) -> 0 | X29: 3
A30: Page total | H30: =SUM(H5:H29) -> 0 | I30: =SUM(I5:I29) -> 815 | J30: =J5+J6+J7+J8+J9+J10+J11+J12+J13+J14+J15+J16+J18+J19+J17+J20+J22+J23+J21+J24+J25+J26+J27+J28+J29 -> 0 | K30: =K5+K6+K7+K8+K9+K10+K11+K12+K13+K14+K15+K16+K18+K19+K17+K20+K22+K23+K21+K24+K25+K26+K27+K28+K29 -> 179.1 | L30: =SUM(L5:L29) -> 0 | M30: =SUM(M5:M29) -> 375 | N30: CASH | O30: CARD | P30: GV | Q30: RSL | X30: 4
A31: Daily Total | H31: =H30+H62+H94 -> 0 | I31: =I30+I62+I94 -> 815 | J31: =J30+J62+J94 -> 0 | K31: =K30+K62+K94 -> 179.1 | L31: =L30+L62+L94 -> 0 | M31: =M30+M62+M94 -> 375 | N31: =COUNT(H5:H29,H37:H61,H69:H93) -> 0 | O31: =COUNT(I5:I29,I37:I61,I69:I93) -> 5 | P31: =COUNTIF(G5:G29,"G*")+COUNTIF(G37:G61,"G*")+COUNTIF(G69:G93,"G*")+COUNTIF(G5:G29,"P*")+COUNTIF(G37:G61,"P*")+COUNTIF(G69:G93,"P*") -> 2 | Q31: =COUNTIF(G5:G29,"RSL")+COUNTIF(G37:G61,"RSL")+COUNTIF(G69:G93,"RSL") -> 0 | R31: CASH CLOSING | S31: =H31+L31-U28-U29-U30 -> 0 | T31: =H31+I31+L31+M31 -> 1190 | X31: Subtotal | Z31: =SUM(Z27:Z30) -> -2745
A32: TOTAL SALES | C32: =H31+I31+J31+K31 -> 994.1 | F32: No of Cars | H32: =COUNT(B5:B29,B37:B61,B69:B93) -> 7 | I32: Average | K32: =C32/H32 -> 142.01429 | N32: =H31/C32 -> 0 | O32: =I31/C32 -> 0.81983704 | P32: =K31/C32 -> 0.18016296 | Q32: =J31/C32 -> 0 | R32: CARD CLOSING | S32: =I31+M31 -> 1190 | X32: B2 card | Z32: =I31 -> 815
A33: Daily Report | X33: Settlement | Z33: =SUM(Z31:Z32) -> -1930
A34: =A2 -> 8-02-2022 | H34: WEATHER | J34: =J2 -> SUNNY | L34: REPORT by | O34: =O2 -> JOHN | R34: TOTAL STAFF | T34: =T2 -> 5
A36: No | B36: Docket No | C36: Reg No | D36: Mobile | E36: Size | F36: TIME | G36: Service | H36: CASH | I36: CARD | J36: RSL | K36: GV | L36: GV CASH | M36: GV CARD | N36: O/Taker | O36: Comment | R36: NAME | S36: Time In | T36: Time out | U36: Total Hours
A37: =A29+1 -> 26 | J37: =IF(G37="RSL","50","0") -> 0 | K37: =IF(G37="GVS","37.5",IF(G37="GVM","41.5",IF(G37="GVL","50",IF(G37="PCS","45.8",IF(G37="PCM","50",IF(G37="PCL","58.3","0")))))) -> 0
A38: =A37+1 -> 27 | J38: =IF(G38="RSL","50","0") -> 0 | K38: =IF(G38="GVS","37.5",IF(G38="GVM","41.5",IF(G38="GVL","50",IF(G38="PCS","45.8",IF(G38="PCM","50",IF(G38="PCL","58.3","0")))))) -> 0
A39: =A38+1 -> 28 | J39: =IF(G39="RSL","50","0") -> 0 | K39: =IF(G39="GVS","37.5",IF(G39="GVM","41.5",IF(G39="GVL","50",IF(G39="PCS","45.8",IF(G39="PCM","50",IF(G39="PCL","58.3","0")))))) -> 0
A40: =A39+1 -> 29 | J40: =IF(G40="RSL","50","0") -> 0 | K40: =IF(G40="GVS","37.5",IF(G40="GVM","41.5",IF(G40="GVL","50",IF(G40="PCS","45.8",IF(G40="PCM","50",IF(G40="PCL","58.3","0")))))) -> 0
A41: =A40+1 -> 30 | J41: =IF(G41="RSL","50","0") -> 0 | K41: =IF(G41="GVS","37.5",IF(G41="GVM","41.5",IF(G41="GVL","50",IF(G41="PCS","45.8",IF(G41="PCM","50",IF(G41="PCL","58.3","0")))))) -> 0
A42: =A41+1 -> 31 | J42: =IF(G42="RSL","50","0") -> 0 | K42: =IF(G42="GVS","37.5",IF(G42="GVM","41.5",IF(G42="GVL","50",IF(G42="PCS","45.8",IF(G42="PCM","50",IF(G42="PCL","58.3","0")))))) -> 0
A43: =A42+1 -> 32 | J43: =IF(G43="RSL","50","0") -> 0 | K43: =IF(G43="GVS","37.5",IF(G43="GVM","41.5",IF(G43="GVL","50",IF(G43="PCS","45.8",IF(G43="PCM","50",IF(G43="PCL","58.3","0")))))) -> 0
A44: =A43+1 -> 33 | J44: =IF(G44="RSL","50","0") -> 0 | K44: =IF(G44="GVS","37.5",IF(G44="GVM","41.5",IF(G44="GVL","50",IF(G44="PCS","45.8",IF(G44="PCM","50",IF(G44="PCL","58.3","0")))))) -> 0
A45: =A44+1 -> 34 | J45: =IF(G45="RSL","50","0") -> 0 | K45: =IF(G45="GVS","37.5",IF(G45="GVM","41.5",IF(G45="GVL","50",IF(G45="PCS","45.8",IF(G45="PCM","50",IF(G45="PCL","58.3","0")))))) -> 0
A46: =A45+1 -> 35 | J46: =IF(G46="RSL","50","0") -> 0 | K46: =IF(G46="GVS","37.5",IF(G46="GVM","41.5",IF(G46="GVL","50",IF(G46="PCS","45.8",IF(G46="PCM","50",IF(G46="PCL","58.3","0")))))) -> 0
A47: =A46+1 -> 36 | J47: =IF(G47="RSL","50","0") -> 0 | K47: =IF(G47="GVS","37.5",IF(G47="GVM","41.5",IF(G47="GVL","50",IF(G47="PCS","45.8",IF(G47="PCM","50",IF(G47="PCL","58.3","0")))))) -> 0
A48: =A47+1 -> 37 | J48: =IF(G48="RSL","50","0") -> 0 | K48: =IF(G48="GVS","37.5",IF(G48="GVM","41.5",IF(G48="GVL","50",IF(G48="PCS","45.8",IF(G48="PCM","50",IF(G48="PCL","58.3","0")))))) -> 0
A49: =A48+1 -> 38 | J49: =IF(G49="RSL","50","0") -> 0 | K49: =IF(G49="GVS","37.5",IF(G49="GVM","41.5",IF(G49="GVL","50",IF(G49="PCS","45.8",IF(G49="PCM","50",IF(G49="PCL","58.3","0")))))) -> 0
... A61: =A60+1 -> 50 | J61: =IF(G61="RSL","50","0") -> 0 | K61: =IF(G61="GVS","37.5",IF(G61="GVM","41.5",IF(G61="GVL","50",IF(G61="PCS","45.8",IF(G61="PCM","50",IF(G61="PCL","58.3","0")))))) -> 0
A62: Page total | H62: =SUM(H37:H61) -> 0 | I62: =SUM(I37:I61) -> 0 | J62: =J61+J60+J59+J58+J57+J56+J55+J54+J53+J52+J51+J50+J49+J48+J47+J46+J45+J44+J43+J42+J41+J40+J39+J38+J37 -> 0 | K62: =K61+K60+K59+K58+K57+K56+K55+K54+K53+K52+K51+K50+K49+K48+K47+K46+K45+K44+K43+K42+K41+K40+K39+K38+K37 -> 0 | L62: =SUM(L37:L61) -> 0 | M62: =SUM(M37:M61) -> 0
R64: Page: 2
A65: Daily Report
A66: =A34 -> 8-02-2022 | H66: WEATHER | J66: =J34 -> SUNNY | L66: REPORT by | O66: =O34 -> JOHN | R66: TOTAL STAFF | T66: =T34 -> 5
A68: No | B68: Docket No | C68: Reg No | D68: Mobile | E68: Size | F68: TIME | G68: Service | H68: CASH | I68: CARD | J68: RSL | K68: GV | L68: GV CASH | M68: GV CARD | N68: O/Taker | O68: Comment | R68: NAME | S68: Time In | T68: Time out | U68: Total Hours
A69: =A61+1 -> 51 | J69: =IF(G69="RSL","50","0") -> 0 | K69: =IF(G69="GVS","37.5",IF(G69="GVM","41.5",IF(G69="GVL","50",IF(G69="PCS","45.8",IF(G69="PCM","50",IF(G69="PCL","58.3","0")))))) -> 0
A70: =A69+1 -> 52 | J70: =IF(G70="RSL","50","0") -> 0 | K70: =IF(G70="GVS","37.5",IF(G70="GVM","41.5",IF(G70="GVL","50",IF(G70="PCS","45.8",IF(G70="PCM","50",IF(G70="PCL","58.3","0")))))) -> 0
A71: =A70+1 -> 53 | J71: =IF(G71="RSL","50","0") -> 0 | K71: =IF(G71="GVS","37.5",IF(G71="GVM","41.5",IF(G71="GVL","50",IF(G71="PCS","45.8",IF(G71="PCM","50",IF(G71="PCL","58.3","0")))))) -> 0
A72: =A71+1 -> 54 | J72: =IF(G72="RSL","50","0") -> 0 | K72: =IF(G72="GVS","37.5",IF(G72="GVM","41.5",IF(G72="GVL","50",IF(G72="PCS","45.8",IF(G72="PCM","50",IF(G72="PCL","58.3","0")))))) -> 0
A73: =A72+1 -> 55 | J73: =IF(G73="RSL","50","0") -> 0 | K73: =IF(G73="GVS","37.5",IF(G73="GVM","41.5",IF(G73="GVL","50",IF(G73="PCS","45.8",IF(G73="PCM","50",IF(G73="PCL","58.3","0")))))) -> 0
A74: =A73+1 -> 56 | J74: =IF(G74="RSL","50","0") -> 0 | K74: =IF(G74="GVS","37.5",IF(G74="GVM","41.5",IF(G74="GVL","50",IF(G74="PCS","45.8",IF(G74="PCM","50",IF(G74="PCL","58.3","0")))))) -> 0
A75: =A74+1 -> 57 | J75: =IF(G75="RSL","50","0") -> 0 | K75: =IF(G75="GVS","37.5",IF(G75="GVM","41.5",IF(G75="GVL","50",IF(G75="PCS","45.8",IF(G75="PCM","50",IF(G75="PCL","58.3","0")))))) -> 0
A76: =A75+1 -> 58 | J76: =IF(G76="RSL","50","0") -> 0 | K76: =IF(G76="GVS","37.5",IF(G76="GVM","41.5",IF(G76="GVL","50",IF(G76="PCS","45.8",IF(G76="PCM","50",IF(G76="PCL","58.3","0")))))) -> 0
A77: =A76+1 -> 59 | J77: =IF(G77="RSL","50","0") -> 0 | K77: =IF(G77="GVS","37.5",IF(G77="GVM","41.5",IF(G77="GVL","50",IF(G77="PCS","45.8",IF(G77="PCM","50",IF(G77="PCL","58.3","0")))))) -> 0
A78: =A77+1 -> 60 | J78: =IF(G78="RSL","50","0") -> 0 | K78: =IF(G78="GVS","37.5",IF(G78="GVM","41.5",IF(G78="GVL","50",IF(G78="PCS","45.8",IF(G78="PCM","50",IF(G78="PCL","58.3","0")))))) -> 0
A79: =A78+1 -> 61 | J79: =IF(G79="RSL","50","0") -> 0 | K79: =IF(G79="GVS","37.5",IF(G79="GVM","41.5",IF(G79="GVL","50",IF(G79="PCS","45.8",IF(G79="PCM","50",IF(G79="PCL","58.3","0")))))) -> 0
A80: =A79+1 -> 62 | J80: =IF(G80="RSL","50","0") -> 0 | K80: =IF(G80="GVS","37.5",IF(G80="GVM","41.5",IF(G80="GVL","50",IF(G80="PCS","45.8",IF(G80="PCM","50",IF(G80="PCL","58.3","0")))))) -> 0
A81: =A80+1 -> 63 | J81: =IF(G81="RSL","50","0") -> 0 | K81: =IF(G81="GVS","37.5",IF(G81="GVM","41.5",IF(G81="GVL","50",IF(G81="PCS","45.8",IF(G81="PCM","50",IF(G81="PCL","58.3","0")))))) -> 0
... A93: =A92+1 -> 75 | J93: =IF(G93="RSL","50","0") -> 0 | K93: =IF(G93="GVS","37.5",IF(G93="GVM","41.5",IF(G93="GVL","50",IF(G93="PCS","45.8",IF(G93="PCM","50",IF(G93="PCL","58.3","0")))))) -> 0
A94: Page total | H94: =SUM(H69:H93) -> 0 | I94: =SUM(I69:I93) -> 0 | J94: =J93+J92+J91+J90+J89+J88+J87+J86+J85+J84+J83+J82+J81+J80+J79+J78+J77+J76+J75+J74+J73+J72+J71+J70+J69 -> 0 | K94: =K93+K92+K91+K90+K89+K88+K87+K86+K85+K84+K83+K82+K81+K80+K79+K78+K77+K76+K75+K74+K73+K72+K71+K70+K69 -> 0 | L94: =SUM(L69:L93) -> 0 | M94: =SUM(M69:M93) -> 0
R96: Page: 3

Sheet WED
A1: B2 Daily Report
A2: 9-02-2022 | H2: WEATHER | J2: SUNNY | L2: REPORT BY | O2: JOHN | R2: TOTAL STAFF | T2: 6 | X2: Merchant machine usage at B2 | AA2: Settle amount | AI2: Merchant machine usage at GA | AL2: Settle amount
A4: No | B4: Docket No | C4: Reg No | D4: Mobile | E4: Size | F4: TIME | G4: Service | H4: CASH | I4: CARD | J4: RSL | K4: GV | L4: GV CASH | M4: GV CARD | N4: O/Taker | O4: Comment | R4: NAME | S4: Time In | T4: Time out | U4: Total Hours | Z4: B2 machine | AA4: BLH machine | AB4: Wongo | AE4: B2 machine | AF4: BLH machine | AG4: Wongo | AK4: GA machine | AL4: BLH machine | AM4: Wongo | AP4: GA machine | AQ4: BLH machine | AR4: Wongo
A5: 1 | B5: 3124 | C5: EOV94G | D5: 0408409070 | E5: L | F5: 910 | G5: X | I5: 95 | J5: =IF(G5="RSL","50","0") -> 0 | K5: =IF(G5="GVS","37.5",IF(G5="GVM","41.5",IF(G5="GVL","50",IF(G5="PCS","45.8",IF(G5="PCM","50",IF(G5="PCL","58.3","0")))))) -> 0 | N5: JOHN | R5: JOHN | S5: 0.33333333 | T5: 0.70833333 | U5: =(T5-S5)*24 -> 9 | X5: NOV | Y5: 1 | AD5: 16 | AI5: NOV | AJ5: 1 | AO5: 16
A6: 2 | B6: 3125 | C6: DVW72Q | D6: 0418881485 | E6: L | F6: 910 | G6: PCL | J6: =IF(G6="RSL","50","0") -> 0 | K6: 78.1 | N6: JOHN | O6: 21057(1/6) | R6: HENDRA | S6: 0.33333333 | T6: 0.70833333 | U6: =(T6-S6)*24 -> 9 | W6: S | Y6: 2 | AD6: 17 | AJ6: 2 | AO6: 17
A7: 3 | B7: 3126 | C7: NBZ17R | D7: 0414151185 | E7: L | F7: 915 | G7: PCL | I7: 100 | J7: =IF(G7="RSL","50","0") -> 0 | K7: 237.5 | N7: JOHN | O7: 21037(4,5,6/6),NEXT TIME | R7: ARIANTO | S7: 0.39583333 | T7: 0.66666667 | U7: =(T7-S7)*24 -> 6.5 | W7: M | Y7: 3 | AD7: 18 | AJ7: 3 | AO7: 18
A8: 4 | B8: 3127 | C8: DTJ82B | D8: 0416347269 | E8: S | F8: 920 | G8: H/ST | I8: 300 | J8: =IF(G8="RSL","50","0") -> 0 | K8: =IF(G8="GVS","37.5",IF(G8="GVM","41.5",IF(G8="GVL","50",IF(G8="PCS","45.8",IF(G8="PCM","50",IF(G8="PCL","58.3","0")))))) -> 0 | N8: JOHN | R8: JUNIOR | S8: 0.33333333 | T8: 0.70833333 | U8: =(T8-S8)*24 -> 9 | W8: L | Y8: 4 | AD8: 19 | AJ8: 4 | AO8: 19
A9: 5 | B9: 3128 | C9: DDD88L | D9: 0402555552 | E9: L | F9: 1000 | G9: GV3 | J9: =IF(G9="RSL","50","0") -> 0 | K9: =IF(G9="GVS","37.5",IF(G9="GVM","41.5",IF(G9="GVL","50",IF(G9="PCS","45.8",IF(G9="PCM","50",IF(G9="PCL","58.3","0")))))) -> 0 | N9: JOHN | O9: 202993(4/6) | R9: KUROSH | S9: 0.40625 | T9: 0.69791667 | U9: =(T9-S9)*24 -> 7 | X9: EXCL RSL | Y9: 5 | AD9: 20 | AJ9: 5 | AO9: 20
A10: 6 | B10: 3129 | C10: EHI70Q | D10: 0419860342 | E10: S | F10: 1000 | G10: X | I10: 75 | J10: =IF(G10="RSL","50","0") -> 0 | K10: =IF(G10="GVS","37.5",IF(G10="GVM","41.5",IF(G10="GVL","50",IF(G10="PCS","45.8",IF(G10="PCM","50",IF(G10="PCL","58.3","0")))))) -> 0 | N10: JOHN | R10: ANTHONY | S10: 0.45138889 | T10: 0.70833333 | U10: =(T10-S10)*24 -> 6.1666667 | Y10: 6 | AD10: 21 | AJ10: 6 | AO10: 21
A11: 7 | B11: 3130 | C11: CX076YM | D11: 0433797997 | E11: S | F11: 1010 | G11: D | I11: 55 | J11: =IF(G11="RSL","50","0") -> 0 | K11: =IF(G11="GVS","37.5",IF(G11="GVM","41.5",IF(G11="GVL","50",IF(G11="PCS","45.8",IF(G11="PCM","50",IF(G11="PCL","58.3","0")))))) -> 0 | N11: JOHN | U11: =(T11-S11)*24 -> 0 | Y11: 7 | AD11: 22 | AJ11: 7 | AO11: 22
A12: 8 | B12: 3131 | C12: EIO39K | D12: 0408095095 | E12: L | F12: 1010 | G12: X | I12: 95 | J12: =IF(G12="RSL","50","0") -> 0 | K12: =IF(G12="GVS","37.5",IF(G12="GVM","41.5",IF(G12="GVL","50",IF(G12="PCS","45.8",IF(G12="PCM","50",IF(G12="PCL","58.3","0")))))) -> 0 | N12: JOHN | U12: =(T12-S12)*24 -> 0 | Y12: 8 | AD12: 23 | AJ12: 8 | AO12: 23
A13: 9 | B13: 3132 | C13: DCS68B | D13: 0418677764 | E13: S | F13: 1050 | G13: PCS | J13: =IF(G13="RSL","50","0") -> 0 | K13: =IF(G13="GVS","37.5",IF(G13="GVM","41.5",IF(G13="GVL","50",IF(G13="PCS","45.8",IF(G13="PCM","50",IF(G13="PCL","58.3","0")))))) -> 45.8 | N13: JOHN | O13: 21044(5/6) | U13: =(T13-S13)*24 -> 0 | Y13: 9 | AD13: 24 | AJ13: 9 | AO13: 24
A14: 10 | B14: 3133 | C14: EEH85P | D14: 0478513380 | E14: S | F14: 1055 | G14: H | I14: 110 | J14: =IF(G14="RSL","50","0") -> 0 | K14: =IF(G14="GVS","37.5",IF(G14="GVM","41.5",IF(G14="GVL","50",IF(G14="PCS","45.8",IF(G14="PCM","50",IF(G14="PCL","58.3","0")))))) -> 0 | N14: JOHN | U14: =(T14-S14)*24 -> 0 | Y14: 10 | AD14: 25 | AJ14: 10 | AO14: 25
A15: 11 | B15: 3134 | C15: XWC148 | D15: 0433565707 | E15: S | F15: 1110 | G15: H/ID | I15: 380 | J15: =IF(G15="RSL","50","0") -> 0 | K15: =IF(G15="GVS","37.5",IF(G15="GVM","41.5",IF(G15="GVL","50",IF(G15="PCS","45.8",IF(G15="PCM","50",IF(G15="PCL","58.3","0")))))) -> 0 | N15: JOHN | U15: =(T15-S15)*24 -> 0 | Y15: 11 | AD15: 26 | AJ15: 11 | AO15: 26
A16: 12 | B16: 3135 | C16: ENM68N | D16: 0452118313 | E16: L | F16: 1130 | G16: X | I16: 95 | J16: =IF(G16="RSL","50","0") -> 0 | K16: =IF(G16="GVS","37.5",IF(G16="GVM","41.5",IF(G16="GVL","50",IF(G16="PCS","45.8",IF(G16="PCM","50",IF(G16="PCL","58.3","0")))))) -> 0 | N16: JOHN | R16: =H32/U16 -> 0.47142857 | S16: =H32/(U16-U5) -> 0.5840708 | T16: =C32/U16 -> 50.046429 | U16: =SUM(U5:U15) -> 46.666667 | Y16: 12 | AD16: 27 | AJ16: 12 | AO16: 27
A17: 13 | B17: 3136 | C17: DDP53S | D17: 0411014635 | E17: S | F17: 1155 | G17: D | I17: 55 | J17: =IF(G17="RSL","50","0") -> 0 | K17: =IF(G17="GVS","37.5",IF(G17="GVM","41.5",IF(G17="GVL","50",IF(G17="PCS","45.8",IF(G17="PCM","50",IF(G17="PCL","58.3","0")))))) -> 0 | N17: JOHN | R17: Cars/T Hr ① | S17: Cars/T Hr ② | T17: Sales/T Hr | U17: Total Hours | Y17: 13 | AD17: 28 | AJ17: 13 | AO17: 28
A18: 14 | B18: 3137 | C18: BPQ53P | D18: 0421075870 | E18: S | F18: 1205 | G18: X | I18: 75 | J18: =IF(G18="RSL","50","0") -> 0 | K18: =IF(G18="GVS","37.5",IF(G18="GVM","41.5",IF(G18="GVL","50",IF(G18="PCS","45.8",IF(G18="PCM","50",IF(G18="PCL","58.3","0")))))) -> 0 | N18: JOHN | R18: ITEM | S18: QTY | T18: AMT | U18: RMKS | Y18: 14 | AD18: 29 | AJ18: 14 | AO18: 29
A19: 15 | B19: 3138 | C19: 00SHA | D19: 0450928298 | E19: S | F19: 1220 | G19: D | I19: 55 | J19: =IF(G19="RSL","50","0") -> 0 | K19: =IF(G19="GVS","37.5",IF(G19="GVM","41.5",IF(G19="GVL","50",IF(G19="PCS","45.8",IF(G19="PCM","50",IF(G19="PCL","58.3","0")))))) -> 0 | N19: JOHN | R19: GV | S19: =COUNT(L5:M29,L37:M61,L69:M93) -> 1 | T19: =SUM(L5:M29,L37:M61,L69:M93) -> 375 | Y19: 15 | AD19: 30 | AJ19: 15 | AO19: 30
A20: 16 | B20: 3139 | C20: DKM62H | D20: 0404714158 | E20: S | F20: 1235 | G20: X | I20: 75 | J20: =IF(G20="RSL","50","0") -> 0 | K20: =IF(G20="GVS","37.5",IF(G20="GVM","41.5",IF(G20="GVL","50",IF(G20="PCS","45.8",IF(G20="PCM","50",IF(G20="PCL","58.3","0")))))) -> 0 | N20: JOHN | AD20: 31 | AO20: 31
A21: 17 | B21: 3140 | C21: TS6888 | D21: 0417880888 | E21: S | F21: 1235 | G21: PCS | J21: =IF(G21="RSL","50","0") -> 0 | K21: 58.3 | M21: 375 | N21: JOHN | O21: 21021(6/6),22002(NEW)
A22: 18 | B22: 3141 | C22: 88BMWM | D22: 0479077545 | E22: S | F22: 1315 | G22: X | I22: 75 | J22: =IF(G22="RSL","50","0") -> 0 | K22: =IF(G22="GVS","37.5",IF(G22="GVM","41.5",IF(G22="GVL","50",IF(G22="PCS","45.8",IF(G22="PCM","50",IF(G22="PCL","58.3","0")))))) -> 0 | N22: JOHN | AD22: Total | AE22: =SUM(Z5:Z19,AE5:AE20) -> 0 | AF22: =SUM(AA5:AA19,AF5:AF20,) -> 0 | AG22: =SUM(AB5:AB19,AG5:AG20) -> 0 | AO22: Total | AP22: =SUM(AK5:AK19,AP5:AP20) -> 0 | AQ22: =SUM(AL5:AL19,AQ5:AQ20,) -> 0 | AR22: =SUM(AM5:AM19,AR5:AR20) -> 0
A23: 19 | B23: 3142 | C23: ERD77U | D23: 0452102105 | E23: S | F23: 1340 | G23: GV1 | I23: 80 | J23: =IF(G23="RSL","50","0") -> 0 | K23: =IF(G23="GVS","37.5",IF(G23="GVM","41.5",IF(G23="GVL","50",IF(G23="PCS","45.8",IF(G23="PCM","50",IF(G23="PCL","58.3","0")))))) -> 0 | N23: JOHN | O23: 202799(6/6)
A24: 20 | B24: 3143 | C24: GCP573 | D24: 0413874273 | E24: S | F24: 1400 | G24: WO | H24: 50 | J24: =IF(G24="RSL","50","0") -> 0 | K24: =IF(G24="GVS","37.5",IF(G24="GVM","41.5",IF(G24="GVL","50",IF(G24="PCS","45.8",IF(G24="PCM","50",IF(G24="PCL","58.3","0")))))) -> 0 | N24: JOHN | R24: SMALL | S24: MEDIUM | T24: LARGE | U24: TOTAL | AD24: B2/GA TOTAL | AE24: B2 machine | AF24: GA machine | AG24: BLH machine | AH24: Wongo machine | AI24: Sub total
A25: 21 | B25: 3144 | C25: DQG86M | D25: 0411832570 | E25: S | F25: 1410 | G25: PCS | J25: =IF(G25="RSL","50","0") -> 0 | K25: =IF(G25="GVS","37.5",IF(G25="GVM","41.5",IF(G25="GVL","50",IF(G25="PCS","45.8",IF(G25="PCM","50",IF(G25="PCL","58.3","0")))))) -> 45.8 | N25: JOHN | O25: 21027(1/6) | R25: =COUNTIF(G5:G29,"GV1")+COUNTIF(G37:G61,"GV1")+COUNTIF(G69:G93,"GV1") -> 1 | S25: =COUNTIF(G5:G29,"GV2")+COUNTIF(G37:G61,"GV2")+COUNTIF(G69:G93,"GV2") -> 0 | T25: =COUNTIF(G5:G29,"GV3")+COUNTIF(G37:G61,"GV3")+COUNTIF(G69:G93,"GV3") -> 1 | U25: =((C32+(R26+S26+T26)*0.5)) -> 2379.25 | AD25: =SUM(AE25:AF25) -> 0 | AE25: =SUM(AE22) -> 0 | AF25: =SUM(AP22) -> 0 | AG25: =SUM(AF22+AQ22) -> 0 | AH25: =AG22+AR22 -> 0 | AI25: =SUM(AE25:AH25) -> 0
A26: 22 | B26: 3145 | C26: DB88ZA | D26: 0424576197 | E26: L | F26: 1530 | G26: W/H | I26: 100 | J26: =IF(G26="RSL","50","0") -> 0 | K26: =IF(G26="GVS","37.5",IF(G26="GVM","41.5",IF(G26="GVL","50",IF(G26="PCS","45.8",IF(G26="PCM","50",IF(G26="PCL","58.3","0")))))) -> 0 | N26: JOHN | R26: =R25*37.5 -> 37.5 | S26: =S25*41.5 -> 0 | T26: =T25*50 -> 50 | X26: Branch cards
A27: 23 | J27: =IF(G27="RSL","50","0") -> 0 | K27: =IF(G27="GVS","37.5",IF(G27="GVM","41.5",IF(G27="GVL","50",IF(G27="PCS","45.8",IF(G27="PCM","50",IF(G27="PCL","58.3","0")))))) -> 0 | R27: Expense | X27: 1 | Z27: -2745
A28: 24 | J28: =IF(G28="RSL","50","0") -> 0 | K28: =IF(G28="GVS","37.5",IF(G28="GVM","41.5",IF(G28="GVL","50",IF(G28="PCS","45.8",IF(G28="PCM","50",IF(G28="PCL","58.3","0")))))) -> 0 | X28: 2
A29: 25 | J29: =IF(G29="RSL","50","0") -> 0 | K29: =IF(G29="GVS","37.5",IF(G29="GVM","41.5",IF(G29="GVL","50",IF(G29="PCS","45.8",IF(G29="PCM","50",IF(G29="PCL","58.3","0")))))) -> 0 | X29: 3
A30: Page total | H30: =SUM(H5:H29) -> 50 | I30: =SUM(I5:I29) -> 1820 | J30: =J5+J6+J7+J8+J9+J10+J11+J12+J13+J14+J15+J16+J18+J19+J17+J20+J22+J23+J21+J24+J25+J26+J27+J28+J29 -> 0 | K30: =K5+K6+K7+K8+K9+K10+K11+K12+K13+K14+K15+K16+K18+K19+K17+K20+K22+K23+K21+K24+K25+K26+K27+K28+K29 -> 465.5 | L30: =SUM(L5:L29) -> 0 | M30: =SUM(M5:M29) -> 375 | N30: CASH | O30: CARD | P30: GV | Q30: RSL | X30: 4
A31: Daily Total | H31: =H30+H62+H94 -> 50 | I31: =I30+I62+I94 -> 1820 | J31: =J30+J62+J94 -> 0 | K31: =K30+K62+K94 -> 465.5 | L31: =L30+L62+L94 -> 0 | M31: =M30+M62+M94 -> 375 | N31: =COUNT(H5:H29,H37:H61,H69:H93) -> 1 | O31: =COUNT(I5:I29,I37:I61,I69:I93) -> 16 | P31: =COUNTIF(G5:G29,"G*")+COUNTIF(G37:G61,"G*")+COUNTIF(G69:G93,"G*")+COUNTIF(G5:G29,"P*")+COUNTIF(G37:G61,"P*")+COUNTIF(G69:G93,"P*") -> 7 | Q31: =COUNTIF(G5:G29,"RSL")+COUNTIF(G37:G61,"RSL")+COUNTIF(G69:G93,"RSL") -> 0 | R31: CASH CLOSING | S31: =H31+L31-U28-U29-U30 -> 50 | T31: =H31+I31+L31+M31 -> 2245 | X31: Subtotal | Z31: =SUM(Z27:Z30) -> -2745
A32: TOTAL SALES | C32: =H31+I31+J31+K31 -> 2335.5 | F32: No of Cars | H32: =COUNT(B5:B29,B37:B61,B69:B93) -> 22 | I32: Average | K32: =C32/H32 -> 106.15909 | N32: =H31/C32 -> 0.021408692 | O32: =I31/C32 -> 0.77927639 | P32: =K31/C32 -> 0.19931492 | Q32: =J31/C32 -> 0 | R32: CARD CLOSING | S32: =I31+M31 -> 2195 | X32: B2 card | Z32: =I31 -> 1820
A33: Daily Report | X33: Settlement | Z33: =SUM(Z31:Z32) -> -925
A34: =A2 -> 9-02-2022 | H34: WEATHER | J34: =J2 -> SUNNY | L34: REPORT by | O34: =O2 -> JOHN | R34: TOTAL STAFF | T34: =T2 -> 6
A36: No | B36: Docket No | C36: Reg No | D36: Mobile | E36: Size | F36: TIME | G36: Service | H36: CASH | I36: CARD | J36: RSL | K36: GV | L36: GV CASH | M36: GV CARD | N36: O/Taker | O36: Comment | R36: NAME | S36: Time In | T36: Time out | U36: Total Hours
A37: =A29+1 -> 26 | J37: =IF(G37="RSL","50","0") -> 0 | K37: =IF(G37="GVS","37.5",IF(G37="GVM","41.5",IF(G37="GVL","50",IF(G37="PCS","45.8",IF(G37="PCM","50",IF(G37="PCL","58.3","0")))))) -> 0
A38: =A37+1 -> 27 | J38: =IF(G38="RSL","50","0") -> 0 | K38: =IF(G38="GVS","37.5",IF(G38="GVM","41.5",IF(G38="GVL","50",IF(G38="PCS","45.8",IF(G38="PCM","50",IF(G38="PCL","58.3","0")))))) -> 0
A39: =A38+1 -> 28 | J39: =IF(G39="RSL","50","0") -> 0 | K39: =IF(G39="GVS","37.5",IF(G39="GVM","41.5",IF(G39="GVL","50",IF(G39="PCS","45.8",IF(G39="PCM","50",IF(G39="PCL","58.3","0")))))) -> 0
A40: =A39+1 -> 29 | J40: =IF(G40="RSL","50","0") -> 0 | K40: =IF(G40="GVS","37.5",IF(G40="GVM","41.5",IF(G40="GVL","50",IF(G40="PCS","45.8",IF(G40="PCM","50",IF(G40="PCL","58.3","0")))))) -> 0
A41: =A40+1 -> 30 | J41: =IF(G41="RSL","50","0") -> 0 | K41: =IF(G41="GVS","37.5",IF(G41="GVM","41.5",IF(G41="GVL","50",IF(G41="PCS","45.8",IF(G41="PCM","50",IF(G41="PCL","58.3","0")))))) -> 0
A42: =A41+1 -> 31 | J42: =IF(G42="RSL","50","0") -> 0 | K42: =IF(G42="GVS","37.5",IF(G42="GVM","41.5",IF(G42="GVL","50",IF(G42="PCS","45.8",IF(G42="PCM","50",IF(G42="PCL","58.3","0")))))) -> 0
A43: =A42+1 -> 32 | J43: =IF(G43="RSL","50","0") -> 0 | K43: =IF(G43="GVS","37.5",IF(G43="GVM","41.5",IF(G43="GVL","50",IF(G43="PCS","45.8",IF(G43="PCM","50",IF(G43="PCL","58.3","0")))))) -> 0
A44: =A43+1 -> 33 | J44: =IF(G44="RSL","50","0") -> 0 | K44: =IF(G44="GVS","37.5",IF(G44="GVM","41.5",IF(G44="GVL","50",IF(G44="PCS","45.8",IF(G44="PCM","50",IF(G44="PCL","58.3","0")))))) -> 0
A45: =A44+1 -> 34 | J45: =IF(G45="RSL","50","0") -> 0 | K45: =IF(G45="GVS","37.5",IF(G45="GVM","41.5",IF(G45="GVL","50",IF(G45="PCS","45.8",IF(G45="PCM","50",IF(G45="PCL","58.3","0")))))) -> 0
A46: =A45+1 -> 35 | J46: =IF(G46="RSL","50","0") -> 0 | K46: =IF(G46="GVS","37.5",IF(G46="GVM","41.5",IF(G46="GVL","50",IF(G46="PCS","45.8",IF(G46="PCM","50",IF(G46="PCL","58.3","0")))))) -> 0
A47: =A46+1 -> 36 | J47: =IF(G47="RSL","50","0") -> 0 | K47: =IF(G47="GVS","37.5",IF(G47="GVM","41.5",IF(G47="GVL","50",IF(G47="PCS","45.8",IF(G47="PCM","50",IF(G47="PCL","58.3","0")))))) -> 0
A48: =A47+1 -> 37 | J48: =IF(G48="RSL","50","0") -> 0 | K48: =IF(G48="GVS","37.5",IF(G48="GVM","41.5",IF(G48="GVL","50",IF(G48="PCS","45.8",IF(G48="PCM","50",IF(G48="PCL","58.3","0")))))) -> 0
A49: =A48+1 -> 38 | J49: =IF(G49="RSL","50","0") -> 0 | K49: =IF(G49="GVS","37.5",IF(G49="GVM","41.5",IF(G49="GVL","50",IF(G49="PCS","45.8",IF(G49="PCM","50",IF(G49="PCL","58.3","0")))))) -> 0
... A61: =A60+1 -> 50 | J61: =IF(G61="RSL","50","0") -> 0 | K61: =IF(G61="GVS","37.5",IF(G61="GVM","41.5",IF(G61="GVL","50",IF(G61="PCS","45.8",IF(G61="PCM","50",IF(G61="PCL","58.3","0")))))) -> 0
A62: Page total | H62: =SUM(H37:H61) -> 0 | I62: =SUM(I37:I61) -> 0 | J62: =J61+J60+J59+J58+J57+J56+J55+J54+J53+J52+J51+J50+J49+J48+J47+J46+J45+J44+J43+J42+J41+J40+J39+J38+J37 -> 0 | K62: =K61+K60+K59+K58+K57+K56+K55+K54+K53+K52+K51+K50+K49+K48+K47+K46+K45+K44+K43+K42+K41+K40+K39+K38+K37 -> 0 | L62: =SUM(L37:L61) -> 0 | M62: =SUM(M37:M61) -> 0
R64: Page: 2
A65: Daily Report
A66: =A34 -> 9-02-2022 | H66: WEATHER | J66: =J34 -> SUNNY | L66: REPORT by | O66: =O34 -> JOHN | R66: TOTAL STAFF | T66: =T34 -> 6
A68: No | B68: Docket No | C68: Reg No | D68: Mobile | E68: Size | F68: TIME | G68: Service | H68: CASH | I68: CARD | J68: RSL | K68: GV | L68: GV CASH | M68: GV CARD | N68: O/Taker | O68: Comment | R68: NAME | S68: Time In | T68: Time out | U68: Total Hours
A69: =A61+1 -> 51 | J69: =IF(G69="RSL","50","0") -> 0 | K69: =IF(G69="GVS","37.5",IF(G69="GVM","41.5",IF(G69="GVL","50",IF(G69="PCS","45.8",IF(G69="PCM","50",IF(G69="PCL","58.3","0")))))) -> 0
A70: =A69+1 -> 52 | J70: =IF(G70="RSL","50","0") -> 0 | K70: =IF(G70="GVS","37.5",IF(G70="GVM","41.5",IF(G70="GVL","50",IF(G70="PCS","45.8",IF(G70="PCM","50",IF(G70="PCL","58.3","0")))))) -> 0
A71: =A70+1 -> 53 | J71: =IF(G71="RSL","50","0") -> 0 | K71: =IF(G71="GVS","37.5",IF(G71="GVM","41.5",IF(G71="GVL","50",IF(G71="PCS","45.8",IF(G71="PCM","50",IF(G71="PCL","58.3","0")))))) -> 0
A72: =A71+1 -> 54 | J72: =IF(G72="RSL","50","0") -> 0 | K72: =IF(G72="GVS","37.5",IF(G72="GVM","41.5",IF(G72="GVL","50",IF(G72="PCS","45.8",IF(G72="PCM","50",IF(G72="PCL","58.3","0")))))) -> 0
A73: =A72+1 -> 55 | J73: =IF(G73="RSL","50","0") -> 0 | K73: =IF(G73="GVS","37.5",IF(G73="GVM","41.5",IF(G73="GVL","50",IF(G73="PCS","45.8",IF(G73="PCM","50",IF(G73="PCL","58.3","0")))))) -> 0
A74: =A73+1 -> 56 | J74: =IF(G74="RSL","50","0") -> 0 | K74: =IF(G74="GVS","37.5",IF(G74="GVM","41.5",IF(G74="GVL","50",IF(G74="PCS","45.8",IF(G74="PCM","50",IF(G74="PCL","58.3","0")))))) -> 0
A75: =A74+1 -> 57 | J75: =IF(G75="RSL","50","0") -> 0 | K75: =IF(G75="GVS","37.5",IF(G75="GVM","41.5",IF(G75="GVL","50",IF(G75="PCS","45.8",IF(G75="PCM","50",IF(G75="PCL","58.3","0")))))) -> 0
A76: =A75+1 -> 58 | J76: =IF(G76="RSL","50","0") -> 0 | K76: =IF(G76="GVS","37.5",IF(G76="GVM","41.5",IF(G76="GVL","50",IF(G76="PCS","45.8",IF(G76="PCM","50",IF(G76="PCL","58.3","0")))))) -> 0
A77: =A76+1 -> 59 | J77: =IF(G77="RSL","50","0") -> 0 | K77: =IF(G77="GVS","37.5",IF(G77="GVM","41.5",IF(G77="GVL","50",IF(G77="PCS","45.8",IF(G77="PCM","50",IF(G77="PCL","58.3","0")))))) -> 0
A78: =A77+1 -> 60 | J78: =IF(G78="RSL","50","0") -> 0 | K78: =IF(G78="GVS","37.5",IF(G78="GVM","41.5",IF(G78="GVL","50",IF(G78="PCS","45.8",IF(G78="PCM","50",IF(G78="PCL","58.3","0")))))) -> 0
A79: =A78+1 -> 61 | J79: =IF(G79="RSL","50","0") -> 0 | K79: =IF(G79="GVS","37.5",IF(G79="GVM","41.5",IF(G79="GVL","50",IF(G79="PCS","45.8",IF(G79="PCM","50",IF(G79="PCL","58.3","0")))))) -> 0
A80: =A79+1 -> 62 | J80: =IF(G80="RSL","50","0") -> 0 | K80: =IF(G80="GVS","37.5",IF(G80="GVM","41.5",IF(G80="GVL","50",IF(G80="PCS","45.8",IF(G80="PCM","50",IF(G80="PCL","58.3","0")))))) -> 0
A81: =A80+1 -> 63 | J81: =IF(G81="RSL","50","0") -> 0 | K81: =IF(G81="GVS","37.5",IF(G81="GVM","41.5",IF(G81="GVL","50",IF(G81="PCS","45.8",IF(G81="PCM","50",IF(G81="PCL","58.3","0")))))) -> 0
... A93: =A92+1 -> 75 | J93: =IF(G93="RSL","50","0") -> 0 | K93: =IF(G93="GVS","37.5",IF(G93="GVM","41.5",IF(G93="GVL","50",IF(G93="PCS","45.8",IF(G93="PCM","50",IF(G93="PCL","58.3","0")))))) -> 0
A94: Page total | H94: =SUM(H69:H93) -> 0 | I94: =SUM(I69:I93) -> 0 | J94: =J93+J92+J91+J90+J89+J88+J87+J86+J85+J84+J83+J82+J81+J80+J79+J78+J77+J76+J75+J74+J73+J72+J71+J70+J69 -> 0 | K94: =K93+K92+K91+K90+K89+K88+K87+K86+K85+K84+K83+K82+K81+K80+K79+K78+K77+K76+K75+K74+K73+K72+K71+K70+K69 -> 0 | L94: =SUM(L69:L93) -> 0 | M94: =SUM(M69:M93) -> 0
R96: Page: 3

Sheet THU
A1: B2 Daily Report
A2: 10-02-2022 | H2: WEATHER | J2: SUNNY | L2: REPORT BY | O2: JOHN | R2: TOTAL STAFF | T2: 7 | X2: Merchant machine usage at B2 | AA2: Settle amount | AI2: Merchant machine usage at GA | AL2: Settle amount
A4: No | B4: Docket No | C4: Reg No | D4: Mobile | E4: Size | F4: TIME | G4: Service | H4: CASH | I4: CARD | J4: RSL | K4: GV | L4: GV CASH | M4: GV CARD | N4: O/Taker | O4: Comment | R4: NAME | S4: Time In | T4: Time out | U4: Total Hours | Z4: B2 machine | AA4: BLH machine | AB4: Wongo | AE4: B2 machine | AF4: BLH machine | AG4: Wongo | AK4: GA machine | AL4: BLH machine | AM4: Wongo | AP4: GA machine | AQ4: BLH machine | AR4: Wongo
A5: 1 | B5: 3146 | C5: CLB30E | D5: 0434022609 | E5: L | F5: 910 | G5: PCS | I5: 70 | J5: =IF(G5="RSL","50","0") -> 0 | K5: =IF(G5="GVS","37.5",IF(G5="GVM","41.5",IF(G5="GVL","50",IF(G5="PCS","45.8",IF(G5="PCM","50",IF(G5="PCL","58.3","0")))))) -> 45.8 | N5: JOHN | O5: 21020(5/6) | R5: JOHN | S5: 0.33333333 | T5: 0.70833333 | U5: =(T5-S5)*24 -> 9 | X5: NOV | Y5: 1 | AD5: 16 | AI5: NOV | AJ5: 1 | AO5: 16
A6: 2 | B6: 3147 | C6: CSS96W | D6: 0414262262 | E6: L | F6: 910 | G6: D | I6: 75 | J6: =IF(G6="RSL","50","0") -> 0 | K6: =IF(G6="GVS","37.5",IF(G6="GVM","41.5",IF(G6="GVL","50",IF(G6="PCS","45.8",IF(G6="PCM","50",IF(G6="PCL","58.3","0")))))) -> 0 | N6: JOHN | R6: HENDRA | S6: 0.33333333 | T6: 0.70833333 | U6: =(T6-S6)*24 -> 9 | W6: S | Y6: 2 | AD6: 17 | AJ6: 2 | AO6: 17
A7: 3 | B7: 3148 | C7: OOOSAL | D7: 0414272218 | E7: S | F7: 925 | G7: X | I7: 75 | J7: =IF(G7="RSL","50","0") -> 0 | K7: =IF(G7="GVS","37.5",IF(G7="GVM","41.5",IF(G7="GVL","50",IF(G7="PCS","45.8",IF(G7="PCM","50",IF(G7="PCL","58.3","0")))))) -> 0 | N7: JOHN | R7: ARIANTO | S7: 0.39583333 | T7: 0.66666667 | U7: =(T7-S7)*24 -> 6.5 | W7: M | Y7: 3 | AD7: 18 | AJ7: 3 | AO7: 18
A8: 4 | B8: 3149 | C8: DCA98H | D8: 0410489985 | E8: S | F8: 935 | G8: X | I8: 75 | J8: =IF(G8="RSL","50","0") -> 0 | K8: =IF(G8="GVS","37.5",IF(G8="GVM","41.5",IF(G8="GVL","50",IF(G8="PCS","45.8",IF(G8="PCM","50",IF(G8="PCL","58.3","0")))))) -> 0 | N8: JOHN | R8: JUNIOR | S8: 0.35416667 | T8: 0.70833333 | U8: =(T8-S8)*24 -> 8.5 | W8: L | Y8: 4 | AD8: 19 | AJ8: 4 | AO8: 19
A9: 5 | B9: 3150 | C9: LP5569 | D9: 0410669160 | E9: M | F9: 940 | G9: D | I9: 60 | J9: =IF(G9="RSL","50","0") -> 0 | K9: =IF(G9="GVS","37.5",IF(G9="GVM","41.5",IF(G9="GVL","50",IF(G9="PCS","45.8",IF(G9="PCM","50",IF(G9="PCL","58.3","0")))))) -> 0 | N9: JOHN | R9: KUROSH | S9: 0.40625 | T9: 0.6875 | U9: =(T9-S9)*24 -> 6.75 | X9: EXCL RSL | Y9: 5 | AD9: 20 | AJ9: 5 | AO9: 20
A10: 6 | B10: 3151 | C10: EEC93Z | D10: 0481001446 | E10: S | F10: 950 | G10: X | I10: 75 | J10: =IF(G10="RSL","50","0") -> 0 | K10: =IF(G10="GVS","37.5",IF(G10="GVM","41.5",IF(G10="GVL","50",IF(G10="PCS","45.8",IF(G10="PCM","50",IF(G10="PCL","58.3","0")))))) -> 0 | N10: JOHN | R10: ANTHONY | S10: 0.41666667 | T10: 0.6875 | U10: =(T10-S10)*24 -> 6.5 | Y10: 6 | AD10: 21 | AJ10: 6 | AO10: 21
A11: 7 | B11: 3152 | C11: EEP11B | D11: 04155085787 | E11: L | F11: 1010 | G11: D | I11: 75 | J11: =IF(G11="RSL","50","0") -> 0 | K11: =IF(G11="GVS","37.5",IF(G11="GVM","41.5",IF(G11="GVL","50",IF(G11="PCS","45.8",IF(G11="PCM","50",IF(G11="PCL","58.3","0")))))) -> 0 | N11: JOHN | R11: HEATHER | S11: 0.42708333 | T11: 0.625 | U11: =(T11-S11)*24 -> 4.75 | Y11: 7 | AD11: 22 | AJ11: 7 | AO11: 22
A12: 8 | B12: 3153 | C12: TM123 | D12: 0419280680 | E12: S | F12: 1035 | G12: H | I12: 120 | J12: =IF(G12="RSL","50","0") -> 0 | K12: =IF(G12="GVS","37.5",IF(G12="GVM","41.5",IF(G12="GVL","50",IF(G12="PCS","45.8",IF(G12="PCM","50",IF(G12="PCL","58.3","0")))))) -> 0 | M12: 375 | N12: JOHN | O12: 22003(NEW) | U12: =(T12-S12)*24 -> 0 | Y12: 8 | AD12: 23 | AJ12: 8 | AO12: 23
A13: 9 | B13: 3154 | C13: AEQ39N | D13: 0403976363 | E13: S | F13: 1115 | G13: H | I13: 100 | J13: =IF(G13="RSL","50","0") -> 0 | K13: =IF(G13="GVS","37.5",IF(G13="GVM","41.5",IF(G13="GVL","50",IF(G13="PCS","45.8",IF(G13="PCM","50",IF(G13="PCL","58.3","0")))))) -> 0 | N13: JOHN | U13: =(T13-S13)*24 -> 0 | Y13: 9 | AD13: 24 | AJ13: 9 | AO13: 24
A14: 10 | B14: 3155 | C14: BTN15D | D14: 0403902656 | E14: S | F14: 1130 | G14: D/ST | I14: 150 | J14: =IF(G14="RSL","50","0") -> 0 | K14: =IF(G14="GVS","37.5",IF(G14="GVM","41.5",IF(G14="GVL","50",IF(G14="PCS","45.8",IF(G14="PCM","50",IF(G14="PCL","58.3","0")))))) -> 0 | N14: HENDRA | O14: BACK SEAT /ST | U14: =(T14-S14)*24 -> 0 | Y14: 10 | AD14: 25 | AJ14: 10 | AO14: 25
A15: 11 | B15: 3156 | C15: DNK08Z | D15: 0426828096 | E15: S | F15: 1200 | G15: PCS | J15: =IF(G15="RSL","50","0") -> 0 | K15: 58.3 | N15: JOHN | O15: 21036(4/6) | U15: =(T15-S15)*24 -> 0 | Y15: 11 | AD15: 26 | AJ15: 11 | AO15: 26
A16: 12 | B16: 3157 | C16: EPE21C | D16: 0438354090 | E16: S | F16: 1205 | G16: D | I16: 55 | J16: =IF(G16="RSL","50","0") -> 0 | K16: =IF(G16="GVS","37.5",IF(G16="GVM","41.5",IF(G16="GVL","50",IF(G16="PCS","45.8",IF(G16="PCM","50",IF(G16="PCL","58.3","0")))))) -> 0 | N16: JOHN | R16: =H32/U16 -> 0.35294118 | S16: =H32/(U16-U5) -> 0.42857143 | T16: =C32/U16 -> 29.884314 | U16: =SUM(U5:U15) -> 51 | Y16: 12 | AD16: 27 | AJ16: 12 | AO16: 27
A17: 13 | B17: 3158 | C17: BZV75U | D17: 0401629030 | E17: S | F17: 1205 | G17: W/O | H17: 60 | J17: =IF(G17="RSL","50","0") -> 0 | K17: =IF(G17="GVS","37.5",IF(G17="GVM","41.5",IF(G17="GVL","50",IF(G17="PCS","45.8",IF(G17="PCM","50",IF(G17="PCL","58.3","0")))))) -> 0 | N17: JOHN | R17: Cars/T Hr ① | S17: Cars/T Hr ② | T17: Sales/T Hr | U17: Total Hours | Y17: 13 | AD17: 28 | AJ17: 13 | AO17: 28
A18: 14 | B18: 3159 | C18: EQK74L | D18: 0449883204 | E18: M | F18: 1240 | G18: X | I18: 85 | J18: =IF(G18="RSL","50","0") -> 0 | K18: =IF(G18="GVS","37.5",IF(G18="GVM","41.5",IF(G18="GVL","50",IF(G18="PCS","45.8",IF(G18="PCM","50",IF(G18="PCL","58.3","0")))))) -> 0 | N18: JOHN | R18: ITEM | S18: QTY | T18: AMT | U18: RMKS | Y18: 14 | AD18: 29 | AJ18: 14 | AO18: 29
A19: 15 | B19: 3160 | C19: CY54ZA | D19: 0402090924 | E19: M | F19: 1400 | G19: X | I19: 85 | J19: =IF(G19="RSL","50","0") -> 0 | K19: =IF(G19="GVS","37.5",IF(G19="GVM","41.5",IF(G19="GVL","50",IF(G19="PCS","45.8",IF(G19="PCM","50",IF(G19="PCL","58.3","0")))))) -> 0 | N19: JOHN | O19: BOOKING | R19: GV | S19: =COUNT(L5:M29,L37:M61,L69:M93) -> 1 | T19: =SUM(L5:M29,L37:M61,L69:M93) -> 375 | Y19: 15 | AD19: 30 | AJ19: 15 | AO19: 30
A20: 16 | B20: 3161 | C20: 88SJ | D20: 0408510088 | E20: L | F20: 1430 | G20: H | I20: 150 | J20: =IF(G20="RSL","50","0") -> 0 | K20: =IF(G20="GVS","37.5",IF(G20="GVM","41.5",IF(G20="GVL","50",IF(G20="PCS","45.8",IF(G20="PCM","50",IF(G20="PCL","58.3","0")))))) -> 0 | N20: JOHN | AD20: 31 | AO20: 31
A21: 17 | B21: 3162 | C21: DYU77A | D21: 0488268777 | E21: S | F21: 1440 | G21: RSL | H21: 5 | J21: =IF(G21="RSL","50","0") -> 50 | K21: =IF(G21="GVS","37.5",IF(G21="GVM","41.5",IF(G21="GVL","50",IF(G21="PCS","45.8",IF(G21="PCM","50",IF(G21="PCL","58.3","0")))))) -> 0 | N21: JOHN | O21: 202201047(D)
A22: 18 | B22: 3163 | C22: ELM13V | D22: 0418620807 | E22: S | F22: 1445 | G22: D | I22: 55 | J22: =IF(G22="RSL","50","0") -> 0 | K22: =IF(G22="GVS","37.5",IF(G22="GVM","41.5",IF(G22="GVL","50",IF(G22="PCS","45.8",IF(G22="PCM","50",IF(G22="PCL","58.3","0")))))) -> 0 | N22: JOHN | AD22: Total | AE22: =SUM(Z5:Z19,AE5:AE20) -> 0 | AF22: =SUM(AA5:AA19,AF5:AF20,) -> 0 | AG22: =SUM(AB5:AB19,AG5:AG20) -> 0 | AO22: Total | AP22: =SUM(AK5:AK19,AP5:AP20) -> 0 | AQ22: =SUM(AL5:AL19,AQ5:AQ20,) -> 0 | AR22: =SUM(AM5:AM19,AR5:AR20) -> 0
A23: 19 | J23: =IF(G23="RSL","50","0") -> 0 | K23: =IF(G23="GVS","37.5",IF(G23="GVM","41.5",IF(G23="GVL","50",IF(G23="PCS","45.8",IF(G23="PCM","50",IF(G23="PCL","58.3","0")))))) -> 0
A24: 20 | J24: =IF(G24="RSL","50","0") -> 0 | K24: =IF(G24="GVS","37.5",IF(G24="GVM","41.5",IF(G24="GVL","50",IF(G24="PCS","45.8",IF(G24="PCM","50",IF(G24="PCL","58.3","0")))))) -> 0 | R24: SMALL | S24: MEDIUM | T24: LARGE | U24: TOTAL | AD24: B2/GA TOTAL | AE24: B2 machine | AF24: GA machine | AG24: BLH machine | AH24: Wongo machine | AI24: Sub total
A25: 21 | J25: =IF(G25="RSL","50","0") -> 0 | K25: =IF(G25="GVS","37.5",IF(G25="GVM","41.5",IF(G25="GVL","50",IF(G25="PCS","45.8",IF(G25="PCM","50",IF(G25="PCL","58.3","0")))))) -> 0 | R25: =COUNTIF(G5:G29,"GV1")+COUNTIF(G37:G61,"GV1")+COUNTIF(G69:G93,"GV1") -> 0 | S25: =COUNTIF(G5:G29,"GV2")+COUNTIF(G37:G61,"GV2")+COUNTIF(G69:G93,"GV2") -> 0 | T25: =COUNTIF(G5:G29,"GV3")+COUNTIF(G37:G61,"GV3")+COUNTIF(G69:G93,"GV3") -> 0 | U25: =((C32+(R26+S26+T26)*0.5)) -> 1524.1 | AD25: =SUM(AE25:AF25) -> 0 | AE25: =SUM(AE22) -> 0 | AF25: =SUM(AP22) -> 0 | AG25: =SUM(AF22+AQ22) -> 0 | AH25: =AG22+AR22 -> 0 | AI25: =SUM(AE25:AH25) -> 0
A26: 22 | J26: =IF(G26="RSL","50","0") -> 0 | K26: =IF(G26="GVS","37.5",IF(G26="GVM","41.5",IF(G26="GVL","50",IF(G26="PCS","45.8",IF(G26="PCM","50",IF(G26="PCL","58.3","0")))))) -> 0 | R26: =R25*37.5 -> 0 | S26: =S25*41.5 -> 0 | T26: =T25*50 -> 0 | X26: Branch cards
A27: 23 | J27: =IF(G27="RSL","50","0") -> 0 | K27: =IF(G27="GVS","37.5",IF(G27="GVM","41.5",IF(G27="GVL","50",IF(G27="PCS","45.8",IF(G27="PCM","50",IF(G27="PCL","58.3","0")))))) -> 0 | R27: Expense | X27: 1 | Z27: -2745
A28: 24 | J28: =IF(G28="RSL","50","0") -> 0 | K28: =IF(G28="GVS","37.5",IF(G28="GVM","41.5",IF(G28="GVL","50",IF(G28="PCS","45.8",IF(G28="PCM","50",IF(G28="PCL","58.3","0")))))) -> 0 | X28: 2
A29: 25 | J29: =IF(G29="RSL","50","0") -> 0 | K29: =IF(G29="GVS","37.5",IF(G29="GVM","41.5",IF(G29="GVL","50",IF(G29="PCS","45.8",IF(G29="PCM","50",IF(G29="PCL","58.3","0")))))) -> 0 | X29: 3
A30: Page total | H30: =SUM(H5:H29) -> 65 | I30: =SUM(I5:I29) -> 1305 | J30: =J5+J6+J7+J8+J9+J10+J11+J12+J13+J14+J15+J16+J18+J19+J17+J20+J22+J23+J21+J24+J25+J26+J27+J28+J29 -> 50 | K30: =K5+K6+K7+K8+K9+K10+K11+K12+K13+K14+K15+K16+K18+K19+K17+K20+K22+K23+K21+K24+K25+K26+K27+K28+K29 -> 104.1 | L30: =SUM(L5:L29) -> 0 | M30: =SUM(M5:M29) -> 375 | N30: CASH | O30: CARD | P30: GV | Q30: RSL | X30: 4
A31: Daily Total | H31: =H30+H62+H94 -> 65 | I31: =I30+I62+I94 -> 1305 | J31: =J30+J62+J94 -> 50 | K31: =K30+K62+K94 -> 104.1 | L31: =L30+L62+L94 -> 0 | M31: =M30+M62+M94 -> 375 | N31: =COUNT(H5:H29,H37:H61,H69:H93) -> 2 | O31: =COUNT(I5:I29,I37:I61,I69:I93) -> 15 | P31: =COUNTIF(G5:G29,"G*")+COUNTIF(G37:G61,"G*")+COUNTIF(G69:G93,"G*")+COUNTIF(G5:G29,"P*")+COUNTIF(G37:G61,"P*")+COUNTIF(G69:G93,"P*") -> 2 | Q31: =COUNTIF(G5:G29,"RSL")+COUNTIF(G37:G61,"RSL")+COUNTIF(G69:G93,"RSL") -> 1 | R31: CASH CLOSING | S31: =H31+L31-U28-U29-U30 -> 65 | T31: =H31+I31+L31+M31 -> 1745 | X31: Subtotal | Z31: =SUM(Z27:Z30) -> -2745
A32: TOTAL SALES | C32: =H31+I31+J31+K31 -> 1524.1 | F32: No of Cars | H32: =COUNT(B5:B29,B37:B61,B69:B93) -> 18 | I32: Average | K32: =C32/H32 -> 84.672222 | N32: =H31/C32 -> 0.04264812 | O32: =I31/C32 -> 0.85624303 | P32: =K31/C32 -> 0.068302605 | Q32: =J31/C32 -> 0.032806246 | R32: CARD CLOSING | S32: =I31+M31 -> 1680 | X32: B2 card | Z32: =I31 -> 1305
A33: Daily Report | X33: Settlement | Z33: =SUM(Z31:Z32) -> -1440
A34: =A2 -> 10-02-2022 | H34: WEATHER | J34: =J2 -> SUNNY | L34: REPORT by | O34: =O2 -> JOHN | R34: TOTAL STAFF | T34: =T2 -> 7
A36: No | B36: Docket No | C36: Reg No | D36: Mobile | E36: Size | F36: TIME | G36: Service | H36: CASH | I36: CARD | J36: RSL | K36: GV | L36: GV CASH | M36: GV CARD | N36: O/Taker | O36: Comment | R36: NAME | S36: Time In | T36: Time out | U36: Total Hours
A37: =A29+1 -> 26 | J37: =IF(G37="RSL","50","0") -> 0 | K37: =IF(G37="GVS","37.5",IF(G37="GVM","41.5",IF(G37="GVL","50",IF(G37="PCS","45.8",IF(G37="PCM","50",IF(G37="PCL","58.3","0")))))) -> 0
A38: =A37+1 -> 27 | J38: =IF(G38="RSL","50","0") -> 0 | K38: =IF(G38="GVS","37.5",IF(G38="GVM","41.5",IF(G38="GVL","50",IF(G38="PCS","45.8",IF(G38="PCM","50",IF(G38="PCL","58.3","0")))))) -> 0
A39: =A38+1 -> 28 | J39: =IF(G39="RSL","50","0") -> 0 | K39: =IF(G39="GVS","37.5",IF(G39="GVM","41.5",IF(G39="GVL","50",IF(G39="PCS","45.8",IF(G39="PCM","50",IF(G39="PCL","58.3","0")))))) -> 0
A40: =A39+1 -> 29 | J40: =IF(G40="RSL","50","0") -> 0 | K40: =IF(G40="GVS","37.5",IF(G40="GVM","41.5",IF(G40="GVL","50",IF(G40="PCS","45.8",IF(G40="PCM","50",IF(G40="PCL","58.3","0")))))) -> 0
A41: =A40+1 -> 30 | J41: =IF(G41="RSL","50","0") -> 0 | K41: =IF(G41="GVS","37.5",IF(G41="GVM","41.5",IF(G41="GVL","50",IF(G41="PCS","45.8",IF(G41="PCM","50",IF(G41="PCL","58.3","0")))))) -> 0
A42: =A41+1 -> 31 | J42: =IF(G42="RSL","50","0") -> 0 | K42: =IF(G42="GVS","37.5",IF(G42="GVM","41.5",IF(G42="GVL","50",IF(G42="PCS","45.8",IF(G42="PCM","50",IF(G42="PCL","58.3","0")))))) -> 0
A43: =A42+1 -> 32 | J43: =IF(G43="RSL","50","0") -> 0 | K43: =IF(G43="GVS","37.5",IF(G43="GVM","41.5",IF(G43="GVL","50",IF(G43="PCS","45.8",IF(G43="PCM","50",IF(G43="PCL","58.3","0")))))) -> 0
A44: =A43+1 -> 33 | J44: =IF(G44="RSL","50","0") -> 0 | K44: =IF(G44="GVS","37.5",IF(G44="GVM","41.5",IF(G44="GVL","50",IF(G44="PCS","45.8",IF(G44="PCM","50",IF(G44="PCL","58.3","0")))))) -> 0
A45: =A44+1 -> 34 | J45: =IF(G45="RSL","50","0") -> 0 | K45: =IF(G45="GVS","37.5",IF(G45="GVM","41.5",IF(G45="GVL","50",IF(G45="PCS","45.8",IF(G45="PCM","50",IF(G45="PCL","58.3","0")))))) -> 0
A46: =A45+1 -> 35 | J46: =IF(G46="RSL","50","0") -> 0 | K46: =IF(G46="GVS","37.5",IF(G46="GVM","41.5",IF(G46="GVL","50",IF(G46="PCS","45.8",IF(G46="PCM","50",IF(G46="PCL","58.3","0")))))) -> 0
A47: =A46+1 -> 36 | J47: =IF(G47="RSL","50","0") -> 0 | K47: =IF(G47="GVS","37.5",IF(G47="GVM","41.5",IF(G47="GVL","50",IF(G47="PCS","45.8",IF(G47="PCM","50",IF(G47="PCL","58.3","0")))))) -> 0
A48: =A47+1 -> 37 | J48: =IF(G48="RSL","50","0") -> 0 | K48: =IF(G48="GVS","37.5",IF(G48="GVM","41.5",IF(G48="GVL","50",IF(G48="PCS","45.8",IF(G48="PCM","50",IF(G48="PCL","58.3","0")))))) -> 0
A49: =A48+1 -> 38 | J49: =IF(G49="RSL","50","0") -> 0 | K49: =IF(G49="GVS","37.5",IF(G49="GVM","41.5",IF(G49="GVL","50",IF(G49="PCS","45.8",IF(G49="PCM","50",IF(G49="PCL","58.3","0")))))) -> 0
... A61: =A60+1 -> 50 | J61: =IF(G61="RSL","50","0") -> 0 | K61: =IF(G61="GVS","37.5",IF(G61="GVM","41.5",IF(G61="GVL","50",IF(G61="PCS","45.8",IF(G61="PCM","50",IF(G61="PCL","58.3","0")))))) -> 0
A62: Page total | H62: =SUM(H37:H61) -> 0 | I62: =SUM(I37:I61) -> 0 | J62: =J61+J60+J59+J58+J57+J56+J55+J54+J53+J52+J51+J50+J49+J48+J47+J46+J45+J44+J43+J42+J41+J40+J39+J38+J37 -> 0 | K62: =K61+K60+K59+K58+K57+K56+K55+K54+K53+K52+K51+K50+K49+K48+K47+K46+K45+K44+K43+K42+K41+K40+K39+K38+K37 -> 0 | L62: =SUM(L37:L61) -> 0 | M62: =SUM(M37:M61) -> 0
R64: Page: 2
A65: Daily Report
A66: =A34 -> 10-02-2022 | H66: WEATHER | J66: =J34 -> SUNNY | L66: REPORT by | O66: =O34 -> JOHN | R66: TOTAL STAFF | T66: =T34 -> 7
A68: No | B68: Docket No | C68: Reg No | D68: Mobile | E68: Size | F68: TIME | G68: Service | H68: CASH | I68: CARD | J68: RSL | K68: GV | L68: GV CASH | M68: GV CARD | N68: O/Taker | O68: Comment | R68: NAME | S68: Time In | T68: Time out | U68: Total Hours
A69: =A61+1 -> 51 | J69: =IF(G69="RSL","50","0") -> 0 | K69: =IF(G69="GVS","37.5",IF(G69="GVM","41.5",IF(G69="GVL","50",IF(G69="PCS","45.8",IF(G69="PCM","50",IF(G69="PCL","58.3","0")))))) -> 0
A70: =A69+1 -> 52 | J70: =IF(G70="RSL","50","0") -> 0 | K70: =IF(G70="GVS","37.5",IF(G70="GVM","41.5",IF(G70="GVL","50",IF(G70="PCS","45.8",IF(G70="PCM","50",IF(G70="PCL","58.3","0")))))) -> 0
A71: =A70+1 -> 53 | J71: =IF(G71="RSL","50","0") -> 0 | K71: =IF(G71="GVS","37.5",IF(G71="GVM","41.5",IF(G71="GVL","50",IF(G71="PCS","45.8",IF(G71="PCM","50",IF(G71="PCL","58.3","0")))))) -> 0
A72: =A71+1 -> 54 | J72: =IF(G72="RSL","50","0") -> 0 | K72: =IF(G72="GVS","37.5",IF(G72="GVM","41.5",IF(G72="GVL","50",IF(G72="PCS","45.8",IF(G72="PCM","50",IF(G72="PCL","58.3","0")))))) -> 0
A73: =A72+1 -> 55 | J73: =IF(G73="RSL","50","0") -> 0 | K73: =IF(G73="GVS","37.5",IF(G73="GVM","41.5",IF(G73="GVL","50",IF(G73="PCS","45.8",IF(G73="PCM","50",IF(G73="PCL","58.3","0")))))) -> 0
A74: =A73+1 -> 56 | J74: =IF(G74="RSL","50","0") -> 0 | K74: =IF(G74="GVS","37.5",IF(G74="GVM","41.5",IF(G74="GVL","50",IF(G74="PCS","45.8",IF(G74="PCM","50",IF(G74="PCL","58.3","0")))))) -> 0
A75: =A74+1 -> 57 | J75: =IF(G75="RSL","50","0") -> 0 | K75: =IF(G75="GVS","37.5",IF(G75="GVM","41.5",IF(G75="GVL","50",IF(G75="PCS","45.8",IF(G75="PCM","50",IF(G75="PCL","58.3","0")))))) -> 0
A76: =A75+1 -> 58 | J76: =IF(G76="RSL","50","0") -> 0 | K76: =IF(G76="GVS","37.5",IF(G76="GVM","41.5",IF(G76="GVL","50",IF(G76="PCS","45.8",IF(G76="PCM","50",IF(G76="PCL","58.3","0")))))) -> 0
A77: =A76+1 -> 59 | J77: =IF(G77="RSL","50","0") -> 0 | K77: =IF(G77="GVS","37.5",IF(G77="GVM","41.5",IF(G77="GVL","50",IF(G77="PCS","45.8",IF(G77="PCM","50",IF(G77="PCL","58.3","0")))))) -> 0
A78: =A77+1 -> 60 | J78: =IF(G78="RSL","50","0") -> 0 | K78: =IF(G78="GVS","37.5",IF(G78="GVM","41.5",IF(G78="GVL","50",IF(G78="PCS","45.8",IF(G78="PCM","50",IF(G78="PCL","58.3","0")))))) -> 0
A79: =A78+1 -> 61 | J79: =IF(G79="RSL","50","0") -> 0 | K79: =IF(G79="GVS","37.5",IF(G79="GVM","41.5",IF(G79="GVL","50",IF(G79="PCS","45.8",IF(G79="PCM","50",IF(G79="PCL","58.3","0")))))) -> 0
A80: =A79+1 -> 62 | J80: =IF(G80="RSL","50","0") -> 0 | K80: =IF(G80="GVS","37.5",IF(G80="GVM","41.5",IF(G80="GVL","50",IF(G80="PCS","45.8",IF(G80="PCM","50",IF(G80="PCL","58.3","0")))))) -> 0
A81: =A80+1 -> 63 | J81: =IF(G81="RSL","50","0") -> 0 | K81: =IF(G81="GVS","37.5",IF(G81="GVM","41.5",IF(G81="GVL","50",IF(G81="PCS","45.8",IF(G81="PCM","50",IF(G81="PCL","58.3","0")))))) -> 0
... A93: =A92+1 -> 75 | J93: =IF(G93="RSL","50","0") -> 0 | K93: =IF(G93="GVS","37.5",IF(G93="GVM","41.5",IF(G93="GVL","50",IF(G93="PCS","45.8",IF(G93="PCM","50",IF(G93="PCL","58.3","0")))))) -> 0
A94: Page total | H94: =SUM(H69:H93) -> 0 | I94: =SUM(I69:I93) -> 0 | J94: =J93+J92+J91+J90+J89+J88+J87+J86+J85+J84+J83+J82+J81+J80+J79+J78+J77+J76+J75+J74+J73+J72+J71+J70+J69 -> 0 | K94: =K93+K92+K91+K90+K89+K88+K87+K86+K85+K84+K83+K82+K81+K80+K79+K78+K77+K76+K75+K74+K73+K72+K71+K70+K69 -> 0 | L94: =SUM(L69:L93) -> 0 | M94: =SUM(M69:M93) -> 0
R96: Page: 3

Sheet FRI
A1: B2 Daily Report
A2: 11-02-2022 | H2: WEATHER | J2: RAIN | L2: REPORT BY | O2: JOHN | R2: TOTAL STAFF | T2: 4 | X2: Merchant machine usage at B2 | AA2: Settle amount | AI2: Merchant machine usage at GA | AL2: Settle amount
A4: No | B4: Docket No | C4: Reg No | D4: Mobile | E4: Size | F4: TIME | G4: Service | H4: CASH | I4: CARD | J4: RSL | K4: GV | L4: GV CASH | M4: GV CARD | N4: O/Taker | O4: Comment | R4: NAME | S4: Time In | T4: Time out | U4: Total Hours | Z4: B2 machine | AA4: BLH machine | AB4: Wongo | AE4: B2 machine | AF4: BLH machine | AG4: Wongo | AK4: GA machine | AL4: BLH machine | AM4: Wongo | AP4: GA machine | AQ4: BLH machine | AR4: Wongo
A5: 1 | B5: 3164 | C5: ANT90S | D5: 0407416907 | E5: S | F5: 920 | G5: X | H5: 75 | J5: =IF(G5="RSL","55","0") -> 0 | K5: =IF(G5="GVS","37.5",IF(G5="GVM","41.5",IF(G5="GVL","50",IF(G5="PCS","45.8",IF(G5="PCM","50",IF(G5="PCL","58.3","0")))))) -> 0 | N5: JOHN | R5: JOHN | S5: 0.33333333 | T5: 0.73958333 | U5: =(T5-S5)*24 -> 9.75 | X5: NOV | Y5: 1 | AD5: 16 | AI5: NOV | AJ5: 1 | AO5: 16
A6: 2 | B6: 3165 | C6: DBB68G | D6: 0438406642 | E6: L | F6: 920 | G6: D | I6: 75 | J6: =IF(G6="RSL","55","0") -> 0 | K6: =IF(G6="GVS","37.5",IF(G6="GVM","41.5",IF(G6="GVL","50",IF(G6="PCS","45.8",IF(G6="PCM","50",IF(G6="PCL","58.3","0")))))) -> 0 | N6: JOHN | R6: HENDRA | S6: 0.35416667 | T6: 0.375 | U6: =(T6-S6)*24 -> 0.5 | W6: S | Y6: 2 | AD6: 17 | AJ6: 2 | AO6: 17
A7: 3 | B7: 3166 | C7: BW68PO | D7: 0425830228 | E7: L | F7: 1005 | G7: W/O | H7: 150 | J7: =IF(G7="RSL","55","0") -> 0 | K7: =IF(G7="GVS","37.5",IF(G7="GVM","41.5",IF(G7="GVL","50",IF(G7="PCS","45.8",IF(G7="PCM","50",IF(G7="PCL","58.3","0")))))) -> 0 | N7: JOHN | S7: 0.70833333 | T7: 0.73958333 | U7: =(T7-S7)*24 -> 0.75 | W7: M | Y7: 3 | AD7: 18 | AJ7: 3 | AO7: 18
A8: 4 | B8: 3167 | C8: DGG97Z | D8: 0402519751 | E8: S | F8: 1045 | G8: D/ST | I8: 300 | J8: =IF(G8="RSL","55","0") -> 0 | K8: =IF(G8="GVS","37.5",IF(G8="GVM","41.5",IF(G8="GVL","50",IF(G8="PCS","45.8",IF(G8="PCM","50",IF(G8="PCL","58.3","0")))))) -> 0 | N8: JOHN | R8: JUNIOR | S8: 0.33333333 | T8: 0.73958333 | U8: =(T8-S8)*24 -> 9.75 | W8: L | Y8: 4 | AD8: 19 | AJ8: 4 | AO8: 19
A9: 5 | B9: 3168 | C9: DGM111 | D9: 0418691153 | E9: S | F9: 1050 | G9: D | H9: 55 | J9: =IF(G9="RSL","55","0") -> 0 | K9: =IF(G9="GVS","37.5",IF(G9="GVM","41.5",IF(G9="GVL","50",IF(G9="PCS","45.8",IF(G9="PCM","50",IF(G9="PCL","58.3","0")))))) -> 0 | N9: JOHN | R9: HEATHER | S9: 0.41666667 | T9: 0.73958333 | U9: =(T9-S9)*24 -> 7.75 | X9: EXCL RSL | Y9: 5 | AD9: 20 | AJ9: 5 | AO9: 20
A10: 6 | B10: 3169 | C10: BWD40C | D10: 0410580486 | E10: L | F10: 1140 | G10: D/ID | H10: 300 | J10: =IF(G10="RSL","55","0") -> 0 | K10: =IF(G10="GVS","37.5",IF(G10="GVM","41.5",IF(G10="GVL","50",IF(G10="PCS","45.8",IF(G10="PCM","50",IF(G10="PCL","58.3","0")))))) -> 0 | N10: JOHN | O10: TAX,KOREAN | U10: =(T10-S10)*24 -> 0 | Y10: 6 | AD10: 21 | AJ10: 6 | AO10: 21
A11: 7 | B11: 3170 | C11: EGR64D | D11: 0408885895 | E11: S | F11: 1150 | G11: W/O | H11: 50 | J11: =IF(G11="RSL","55","0") -> 0 | K11: =IF(G11="GVS","37.5",IF(G11="GVM","41.5",IF(G11="GVL","50",IF(G11="PCS","45.8",IF(G11="PCM","50",IF(G11="PCL","58.3","0")))))) -> 0 | N11: JOHN | U11: =(T11-S11)*24 -> 0 | Y11: 7 | AD11: 22 | AJ11: 7 | AO11: 22
A12: 8 | B12: 3171 | C12: EHG87N | D12: 0410448101 | E12: L | F12: 1230 | G12: X | I12: 95 | J12: =IF(G12="RSL","55","0") -> 0 | K12: =IF(G12="GVS","37.5",IF(G12="GVM","41.5",IF(G12="GVL","50",IF(G12="PCS","45.8",IF(G12="PCM","50",IF(G12="PCL","58.3","0")))))) -> 0 | N12: JOHN | U12: =(T12-S12)*24 -> 0 | Y12: 8 | AD12: 23 | AJ12: 8 | AO12: 23
A13: 9 | B13: 3172 | C13: CDD62Z | D13: 0412688789 | E13: L | F13: 1330 | G13: D/ST | H13: 300 | J13: =IF(G13="RSL","55","0") -> 0 | K13: =IF(G13="GVS","37.5",IF(G13="GVM","41.5",IF(G13="GVL","50",IF(G13="PCS","45.8",IF(G13="PCM","50",IF(G13="PCL","58.3","0")))))) -> 0 | N13: JOHN | U13: =(T13-S13)*24 -> 0 | Y13: 9 | AD13: 24 | AJ13: 9 | AO13: 24
A14: 10 | B14: 3173 | C14: DYA55U | D14: 0432212280 | E14: S | F14: 1625 | G14: D/ST | I14: 280 | J14: =IF(G14="RSL","55","0") -> 0 | K14: =IF(G14="GVS","37.5",IF(G14="GVM","41.5",IF(G14="GVL","50",IF(G14="PCS","45.8",IF(G14="PCM","50",IF(G14="PCL","58.3","0")))))) -> 0 | N14: JOHN | U14: =(T14-S14)*24 -> 0 | Y14: 10 | AD14: 25 | AJ14: 10 | AO14: 25
A15: 11 | B15: 3174 | C15: NLP77A | D15: 0458977226 | E15: L | F15: 1630 | G15: F/D | I15: 480 | J15: =IF(G15="RSL","55","0") -> 0 | K15: =IF(G15="GVS","37.5",IF(G15="GVM","41.5",IF(G15="GVL","50",IF(G15="PCS","45.8",IF(G15="PCM","50",IF(G15="PCL","58.3","0")))))) -> 0 | N15: JOHN | U15: =(T15-S15)*24 -> 0 | Y15: 11 | AD15: 26 | AJ15: 11 | AO15: 26
A16: 12 | J16: =IF(G16="RSL","55","0") -> 0 | K16: =IF(G16="GVS","37.5",IF(G16="GVM","41.5",IF(G16="GVL","50",IF(G16="PCS","45.8",IF(G16="PCM","50",IF(G16="PCL","58.3","0")))))) -> 0 | R16: =H32/U16 -> 0.38596491 | S16: =H32/(U16-U5) -> 0.58666667 | T16: =C32/U16 -> 75.789474 | U16: =SUM(U5:U15) -> 28.5 | Y16: 12 | AD16: 27 | AJ16: 12 | AO16: 27
A17: 13 | J17: =IF(G17="RSL","55","0") -> 0 | K17: =IF(G17="GVS","37.5",IF(G17="GVM","41.5",IF(G17="GVL","50",IF(G17="PCS","45.8",IF(G17="PCM","50",IF(G17="PCL","58.3","0")))))) -> 0 | R17: Cars/T Hr ① | S17: Cars/T Hr ② | T17: Sales/T Hr | U17: Total Hours | Y17: 13 | AD17: 28 | AJ17: 13 | AO17: 28
A18: 14 | J18: =IF(G18="RSL","55","0") -> 0 | K18: =IF(G18="GVS","37.5",IF(G18="GVM","41.5",IF(G18="GVL","50",IF(G18="PCS","45.8",IF(G18="PCM","50",IF(G18="PCL","58.3","0")))))) -> 0 | R18: ITEM | S18: QTY | T18: AMT | U18: RMKS | Y18: 14 | AD18: 29 | AJ18: 14 | AO18: 29
A19: 15 | J19: =IF(G19="RSL","55","0") -> 0 | K19: =IF(G19="GVS","37.5",IF(G19="GVM","41.5",IF(G19="GVL","50",IF(G19="PCS","45.8",IF(G19="PCM","50",IF(G19="PCL","58.3","0")))))) -> 0 | R19: GV | S19: =COUNT(L5:M29,L37:M61,L69:M93) -> 0 | T19: =SUM(L5:M29,L37:M61,L69:M93) -> 0 | Y19: 15 | AD19: 30 | AJ19: 15 | AO19: 30
A20: 16 | J20: =IF(G20="RSL","55","0") -> 0 | K20: =IF(G20="GVS","37.5",IF(G20="GVM","41.5",IF(G20="GVL","50",IF(G20="PCS","45.8",IF(G20="PCM","50",IF(G20="PCL","58.3","0")))))) -> 0 | AD20: 31 | AO20: 31
A21: 17 | J21: =IF(G21="RSL","55","0") -> 0 | K21: =IF(G21="GVS","37.5",IF(G21="GVM","41.5",IF(G21="GVL","50",IF(G21="PCS","45.8",IF(G21="PCM","50",IF(G21="PCL","58.3","0")))))) -> 0
A22: 18 | J22: =IF(G22="RSL","55","0") -> 0 | K22: =IF(G22="GVS","37.5",IF(G22="GVM","41.5",IF(G22="GVL","50",IF(G22="PCS","45.8",IF(G22="PCM","50",IF(G22="PCL","58.3","0")))))) -> 0 | AD22: Total | AE22: =SUM(Z5:Z19,AE5:AE20) -> 0 | AF22: =SUM(AA5:AA19,AF5:AF20,) -> 0 | AG22: =SUM(AB5:AB19,AG5:AG20) -> 0 | AO22: Total | AP22: =SUM(AK5:AK19,AP5:AP20) -> 0 | AQ22: =SUM(AL5:AL19,AQ5:AQ20,) -> 0 | AR22: =SUM(AM5:AM19,AR5:AR20) -> 0
A23: 19 | J23: =IF(G23="RSL","55","0") -> 0 | K23: =IF(G23="GVS","37.5",IF(G23="GVM","41.5",IF(G23="GVL","50",IF(G23="PCS","45.8",IF(G23="PCM","50",IF(G23="PCL","58.3","0")))))) -> 0
A24: 20 | J24: =IF(G24="RSL","55","0") -> 0 | K24: =IF(G24="GVS","37.5",IF(G24="GVM","41.5",IF(G24="GVL","50",IF(G24="PCS","45.8",IF(G24="PCM","50",IF(G24="PCL","58.3","0")))))) -> 0 | R24: SMALL | S24: MEDIUM | T24: LARGE | U24: TOTAL | AD24: B2/GA TOTAL | AE24: B2 machine | AF24: GA machine | AG24: BLH machine | AH24: Wongo machine | AI24: Sub total
A25: 21 | J25: =IF(G25="RSL","55","0") -> 0 | K25: =IF(G25="GVS","37.5",IF(G25="GVM","41.5",IF(G25="GVL","50",IF(G25="PCS","45.8",IF(G25="PCM","50",IF(G25="PCL","58.3","0")))))) -> 0 | R25: =COUNTIF(G5:G29,"GV1")+COUNTIF(G37:G61,"GV1")+COUNTIF(G69:G93,"GV1") -> 0 | S25: =COUNTIF(G5:G29,"GV2")+COUNTIF(G37:G61,"GV2")+COUNTIF(G69:G93,"GV2") -> 0 | T25: =COUNTIF(G5:G29,"GV3")+COUNTIF(G37:G61,"GV3")+COUNTIF(G69:G93,"GV3") -> 0 | U25: =((C32+(R26+S26+T26)*0.5)) -> 2160 | AD25: =SUM(AE25:AF25) -> 0 | AE25: =SUM(AE22) -> 0 | AF25: =SUM(AP22) -> 0 | AG25: =SUM(AF22+AQ22) -> 0 | AH25: =AG22+AR22 -> 0 | AI25: =SUM(AE25:AH25) -> 0
A26: 22 | J26: =IF(G26="RSL","55","0") -> 0 | K26: =IF(G26="GVS","37.5",IF(G26="GVM","41.5",IF(G26="GVL","50",IF(G26="PCS","45.8",IF(G26="PCM","50",IF(G26="PCL","58.3","0")))))) -> 0 | R26: =R25*37.5 -> 0 | S26: =S25*41.5 -> 0 | T26: =T25*50 -> 0 | X26: Branch cards
A27: 23 | J27: =IF(G27="RSL","55","0") -> 0 | K27: =IF(G27="GVS","37.5",IF(G27="GVM","41.5",IF(G27="GVL","50",IF(G27="PCS","45.8",IF(G27="PCM","50",IF(G27="PCL","58.3","0")))))) -> 0 | R27: Expense | X27: 1 | Z27: -2745
A28: 24 | J28: =IF(G28="RSL","55","0") -> 0 | K28: =IF(G28="GVS","37.5",IF(G28="GVM","41.5",IF(G28="GVL","50",IF(G28="PCS","45.8",IF(G28="PCM","50",IF(G28="PCL","58.3","0")))))) -> 0 | X28: 2
A29: 25 | J29: =IF(G29="RSL","55","0") -> 0 | K29: =IF(G29="GVS","37.5",IF(G29="GVM","41.5",IF(G29="GVL","50",IF(G29="PCS","45.8",IF(G29="PCM","50",IF(G29="PCL","58.3","0")))))) -> 0 | X29: 3
A30: Page total | H30: =SUM(H5:H29) -> 930 | I30: =SUM(I5:I29) -> 1230 | J30: =J5+J6+J7+J8+J9+J10+J11+J12+J13+J14+J15+J16+J18+J19+J17+J20+J22+J23+J21+J24+J25+J26+J27+J28+J29 -> 0 | K30: =K5+K6+K7+K8+K9+K10+K11+K12+K13+K14+K15+K16+K18+K19+K17+K20+K22+K23+K21+K24+K25+K26+K27+K28+K29 -> 0 | L30: =SUM(L5:L29) -> 0 | M30: =SUM(M5:M29) -> 0 | N30: CASH | O30: CARD | P30: GV | Q30: RSL | X30: 4
A31: Daily Total | H31: =H30+H62+H94 -> 930 | I31: =I30+I62+I94 -> 1230 | J31: =J30+J62+J94 -> 0 | K31: =K30+K62+K94 -> 0 | L31: =L30+L62+L94 -> 0 | M31: =M30+M62+M94 -> 0 | N31: =COUNT(H5:H29,H37:H61,H69:H93) -> 6 | O31: =COUNT(I5:I29,I37:I61,I69:I93) -> 5 | P31: =COUNTIF(G5:G29,"G*")+COUNTIF(G37:G61,"G*")+COUNTIF(G69:G93,"G*")+COUNTIF(G5:G29,"P*")+COUNTIF(G37:G61,"P*")+COUNTIF(G69:G93,"P*") -> 0 | Q31: =COUNTIF(G5:G29,"RSL")+COUNTIF(G37:G61,"RSL")+COUNTIF(G69:G93,"RSL") -> 0 | R31: CASH CLOSING | S31: =H31+L31-U28-U29-U30 -> 930 | T31: =H31+I31+L31+M31 -> 2160 | X31: Subtotal | Z31: =SUM(Z27:Z30) -> -2745
A32: TOTAL SALES | C32: =H31+I31+J31+K31 -> 2160 | F32: No of Cars | H32: =COUNT(B5:B29,B37:B61,B69:B93) -> 11 | I32: Average | K32: =C32/H32 -> 196.36364 | N32: =H31/C32 -> 0.43055556 | O32: =I31/C32 -> 0.56944444 | P32: =K31/C32 -> 0 | Q32: =J31/C32 -> 0 | R32: CARD CLOSING | S32: =I31+M31 -> 1230 | X32: B2 card | Z32: =I31 -> 1230
A33: Daily Report | X33: Settlement | Z33: =SUM(Z31:Z32) -> -1515
A34: =A2 -> 11-02-2022 | H34: WEATHER | J34: =J2 -> RAIN | L34: REPORT by | O34: =O2 -> JOHN | R34: TOTAL STAFF | T34: =T2 -> 4
A36: No | B36: Docket No | C36: Reg No | D36: Mobile | E36: Size | F36: TIME | G36: Service | H36: CASH | I36: CARD | J36: RSL | K36: GV | L36: GV CASH | M36: GV CARD | N36: O/Taker | O36: Comment | R36: NAME | S36: Time In | T36: Time out | U36: Total Hours
A37: =A29+1 -> 26 | J37: =IF(G37="RSL","55","0") -> 0 | K37: =IF(G37="GVS","37.5",IF(G37="GVM","41.5",IF(G37="GVL","50",IF(G37="PCS","45.8",IF(G37="PCM","50",IF(G37="PCL","58.3","0")))))) -> 0
A38: =A37+1 -> 27 | J38: =IF(G38="RSL","55","0") -> 0 | K38: =IF(G38="GVS","37.5",IF(G38="GVM","41.5",IF(G38="GVL","50",IF(G38="PCS","45.8",IF(G38="PCM","50",IF(G38="PCL","58.3","0")))))) -> 0
A39: =A38+1 -> 28 | J39: =IF(G39="RSL","55","0") -> 0 | K39: =IF(G39="GVS","37.5",IF(G39="GVM","41.5",IF(G39="GVL","50",IF(G39="PCS","45.8",IF(G39="PCM","50",IF(G39="PCL","58.3","0")))))) -> 0
A40: =A39+1 -> 29 | J40: =IF(G40="RSL","55","0") -> 0 | K40: =IF(G40="GVS","37.5",IF(G40="GVM","41.5",IF(G40="GVL","50",IF(G40="PCS","45.8",IF(G40="PCM","50",IF(G40="PCL","58.3","0")))))) -> 0
A41: =A40+1 -> 30 | J41: =IF(G41="RSL","55","0") -> 0 | K41: =IF(G41="GVS","37.5",IF(G41="GVM","41.5",IF(G41="GVL","50",IF(G41="PCS","45.8",IF(G41="PCM","50",IF(G41="PCL","58.3","0")))))) -> 0
A42: =A41+1 -> 31 | J42: =IF(G42="RSL","55","0") -> 0 | K42: =IF(G42="GVS","37.5",IF(G42="GVM","41.5",IF(G42="GVL","50",IF(G42="PCS","45.8",IF(G42="PCM","50",IF(G42="PCL","58.3","0")))))) -> 0
A43: =A42+1 -> 32 | J43: =IF(G43="RSL","55","0") -> 0 | K43: =IF(G43="GVS","37.5",IF(G43="GVM","41.5",IF(G43="GVL","50",IF(G43="PCS","45.8",IF(G43="PCM","50",IF(G43="PCL","58.3","0")))))) -> 0
A44: =A43+1 -> 33 | J44: =IF(G44="RSL","55","0") -> 0 | K44: =IF(G44="GVS","37.5",IF(G44="GVM","41.5",IF(G44="GVL","50",IF(G44="PCS","45.8",IF(G44="PCM","50",IF(G44="PCL","58.3","0")))))) -> 0
A45: =A44+1 -> 34 | J45: =IF(G45="RSL","55","0") -> 0 | K45: =IF(G45="GVS","37.5",IF(G45="GVM","41.5",IF(G45="GVL","50",IF(G45="PCS","45.8",IF(G45="PCM","50",IF(G45="PCL","58.3","0")))))) -> 0
A46: =A45+1 -> 35 | J46: =IF(G46="RSL","55","0") -> 0 | K46: =IF(G46="GVS","37.5",IF(G46="GVM","41.5",IF(G46="GVL","50",IF(G46="PCS","45.8",IF(G46="PCM","50",IF(G46="PCL","58.3","0")))))) -> 0
A47: =A46+1 -> 36 | J47: =IF(G47="RSL","55","0") -> 0 | K47: =IF(G47="GVS","37.5",IF(G47="GVM","41.5",IF(G47="GVL","50",IF(G47="PCS","45.8",IF(G47="PCM","50",IF(G47="PCL","58.3","0")))))) -> 0
A48: =A47+1 -> 37 | J48: =IF(G48="RSL","55","0") -> 0 | K48: =IF(G48="GVS","37.5",IF(G48="GVM","41.5",IF(G48="GVL","50",IF(G48="PCS","45.8",IF(G48="PCM","50",IF(G48="PCL","58.3","0")))))) -> 0
A49: =A48+1 -> 38 | J49: =IF(G49="RSL","55","0") -> 0 | K49: =IF(G49="GVS","37.5",IF(G49="GVM","41.5",IF(G49="GVL","50",IF(G49="PCS","45.8",IF(G49="PCM","50",IF(G49="PCL","58.3","0")))))) -> 0
... A61: =A60+1 -> 50 | J61: =IF(G61="RSL","55","0") -> 0 | K61: =IF(G61="GVS","37.5",IF(G61="GVM","41.5",IF(G61="GVL","50",IF(G61="PCS","45.8",IF(G61="PCM","50",IF(G61="PCL","58.3","0")))))) -> 0
A62: Page total | H62: =SUM(H37:H61) -> 0 | I62: =SUM(I37:I61) -> 0 | J62: =J61+J60+J59+J58+J57+J56+J55+J54+J53+J52+J51+J50+J49+J48+J47+J46+J45+J44+J43+J42+J41+J40+J39+J38+J37 -> 0 | K62: =K61+K60+K59+K58+K57+K56+K55+K54+K53+K52+K51+K50+K49+K48+K47+K46+K45+K44+K43+K42+K41+K40+K39+K38+K37 -> 0 | L62: =SUM(L37:L61) -> 0 | M62: =SUM(M37:M61) -> 0
R64: Page: 2
A65: Daily Report
A66: =A34 -> 11-02-2022 | H66: WEATHER | J66: =J34 -> RAIN | L66: REPORT by | O66: =O34 -> JOHN | R66: TOTAL STAFF | T66: =T34 -> 4
A68: No | B68: Docket No | C68: Reg No | D68: Mobile | E68: Size | F68: TIME | G68: Service | H68: CASH | I68: CARD | J68: RSL | K68: GV | L68: GV CASH | M68: GV CARD | N68: O/Taker | O68: Comment | R68: NAME | S68: Time In | T68: Time out | U68: Total Hours
A69: =A61+1 -> 51 | J69: =IF(G69="RSL","50","0") -> 0 | K69: =IF(G69="GVS","37.5",IF(G69="GVM","41.5",IF(G69="GVL","50",IF(G69="PCS","45.8",IF(G69="PCM","50",IF(G69="PCL","58.3","0")))))) -> 0
A70: =A69+1 -> 52 | J70: =IF(G70="RSL","50","0") -> 0 | K70: =IF(G70="GVS","37.5",IF(G70="GVM","41.5",IF(G70="GVL","50",IF(G70="PCS","45.8",IF(G70="PCM","50",IF(G70="PCL","58.3","0")))))) -> 0
A71: =A70+1 -> 53 | J71: =IF(G71="RSL","50","0") -> 0 | K71: =IF(G71="GVS","37.5",IF(G71="GVM","41.5",IF(G71="GVL","50",IF(G71="PCS","45.8",IF(G71="PCM","50",IF(G71="PCL","58.3","0")))))) -> 0
A72: =A71+1 -> 54 | J72: =IF(G72="RSL","50","0") -> 0 | K72: =IF(G72="GVS","37.5",IF(G72="GVM","41.5",IF(G72="GVL","50",IF(G72="PCS","45.8",IF(G72="PCM","50",IF(G72="PCL","58.3","0")))))) -> 0
A73: =A72+1 -> 55 | J73: =IF(G73="RSL","50","0") -> 0 | K73: =IF(G73="GVS","37.5",IF(G73="GVM","41.5",IF(G73="GVL","50",IF(G73="PCS","45.8",IF(G73="PCM","50",IF(G73="PCL","58.3","0")))))) -> 0
A74: =A73+1 -> 56 | J74: =IF(G74="RSL","50","0") -> 0 | K74: =IF(G74="GVS","37.5",IF(G74="GVM","41.5",IF(G74="GVL","50",IF(G74="PCS","45.8",IF(G74="PCM","50",IF(G74="PCL","58.3","0")))))) -> 0
A75: =A74+1 -> 57 | J75: =IF(G75="RSL","50","0") -> 0 | K75: =IF(G75="GVS","37.5",IF(G75="GVM","41.5",IF(G75="GVL","50",IF(G75="PCS","45.8",IF(G75="PCM","50",IF(G75="PCL","58.3","0")))))) -> 0
A76: =A75+1 -> 58 | J76: =IF(G76="RSL","50","0") -> 0 | K76: =IF(G76="GVS","37.5",IF(G76="GVM","41.5",IF(G76="GVL","50",IF(G76="PCS","45.8",IF(G76="PCM","50",IF(G76="PCL","58.3","0")))))) -> 0
A77: =A76+1 -> 59 | J77: =IF(G77="RSL","50","0") -> 0 | K77: =IF(G77="GVS","37.5",IF(G77="GVM","41.5",IF(G77="GVL","50",IF(G77="PCS","45.8",IF(G77="PCM","50",IF(G77="PCL","58.3","0")))))) -> 0
A78: =A77+1 -> 60 | J78: =IF(G78="RSL","50","0") -> 0 | K78: =IF(G78="GVS","37.5",IF(G78="GVM","41.5",IF(G78="GVL","50",IF(G78="PCS","45.8",IF(G78="PCM","50",IF(G78="PCL","58.3","0")))))) -> 0
A79: =A78+1 -> 61 | J79: =IF(G79="RSL","50","0") -> 0 | K79: =IF(G79="GVS","37.5",IF(G79="GVM","41.5",IF(G79="GVL","50",IF(G79="PCS","45.8",IF(G79="PCM","50",IF(G79="PCL","58.3","0")))))) -> 0
A80: =A79+1 -> 62 | J80: =IF(G80="RSL","50","0") -> 0 | K80: =IF(G80="GVS","37.5",IF(G80="GVM","41.5",IF(G80="GVL","50",IF(G80="PCS","45.8",IF(G80="PCM","50",IF(G80="PCL","58.3","0")))))) -> 0
A81: =A80+1 -> 63 | J81: =IF(G81="RSL","50","0") -> 0 | K81: =IF(G81="GVS","37.5",IF(G81="GVM","41.5",IF(G81="GVL","50",IF(G81="PCS","45.8",IF(G81="PCM","50",IF(G81="PCL","58.3","0")))))) -> 0
... A93: =A92+1 -> 75 | J93: =IF(G93="RSL","50","0") -> 0 | K93: =IF(G93="GVS","37.5",IF(G93="GVM","41.5",IF(G93="GVL","50",IF(G93="PCS","45.8",IF(G93="PCM","50",IF(G93="PCL","58.3","0")))))) -> 0
A94: Page total | H94: =SUM(H69:H93) -> 0 | I94: =SUM(I69:I93) -> 0 | J94: =J93+J92+J91+J90+J89+J88+J87+J86+J85+J84+J83+J82+J81+J80+J79+J78+J77+J76+J75+J74+J73+J72+J71+J70+J69 -> 0 | K94: =K93+K92+K91+K90+K89+K88+K87+K86+K85+K84+K83+K82+K81+K80+K79+K78+K77+K76+K75+K74+K73+K72+K71+K70+K69 -> 0 | L94: =SUM(L69:L93) -> 0 | M94: =SUM(M69:M93) -> 0
R96: Page: 3

Sheet SAT
A1: B2 Daily Report
A2: 12-02-2022 | H2: WEATHER | J2: MIX | L2: REPORT BY | O2: JOHN | R2: TOTAL STAFF | T2: 7 | X2: Merchant machine usage at B2 | AA2: Settle amount | AI2: Merchant machine usage at GA | AL2: Settle amount
A4: No | B4: Docket No | C4: Reg No | D4: Mobile | E4: Size | F4: TIME | G4: Service | H4: CASH | I4: CARD | J4: RSL | K4: GV | L4: GV CASH | M4: GV CARD | N4: O/Taker | O4: Comment | R4: NAME | S4: Time In | T4: Time out | U4: Total Hours | Z4: B2 machine | AA4: BLH machine | AB4: Wongo | AE4: B2 machine | AF4: BLH machine | AG4: Wongo | AK4: GA machine | AL4: BLH machine | AM4: Wongo | AP4: GA machine | AQ4: BLH machine | AR4: Wongo
A5: 1 | B5: 3175 | C5: CNU72Q | D5: 0408577729 | E5: S | F5: 1000 | G5: W/O | I5: 50 | J5: =IF(G5="RSL","55","0") -> 0 | K5: =IF(G5="GVS","37.5",IF(G5="GVM","41.5",IF(G5="GVL","50",IF(G5="PCS","45.8",IF(G5="PCM","50",IF(G5="PCL","58.3","0")))))) -> 0 | N5: JOHN | R5: JOHN | S5: 0.33333333 | T5: 0.69791667 | U5: =(T5-S5)*24 -> 8.75 | X5: NOV | Y5: 1 | AD5: 16 | AI5: NOV | AJ5: 1 | AO5: 16
A6: 2 | B6: 3176 | C6: DQX92X | D6: 0407065929 | E6: M | F6: 1015 | G6: D | H6: 60 | J6: =IF(G6="RSL","55","0") -> 0 | K6: =IF(G6="GVS","37.5",IF(G6="GVM","41.5",IF(G6="GVL","50",IF(G6="PCS","45.8",IF(G6="PCM","50",IF(G6="PCL","58.3","0")))))) -> 0 | N6: JOHN | R6: HENDRA | S6: 0.33333333 | T6: 0.6875 | U6: =(T6-S6)*24 -> 8.5 | W6: S | Y6: 2 | AD6: 17 | AJ6: 2 | AO6: 17
A7: 3 | B7: 3177 | C7: BDH43W | D7: 0416192892 | E7: L | F7: 1030 | G7: H | I7: 160 | J7: =IF(G7="RSL","55","0") -> 0 | K7: =IF(G7="GVS","37.5",IF(G7="GVM","41.5",IF(G7="GVL","50",IF(G7="PCS","45.8",IF(G7="PCM","50",IF(G7="PCL","58.3","0")))))) -> 0 | N7: JOHN | R7: ARIANTO | S7: 0.39583333 | T7: 0.64583333 | U7: =(T7-S7)*24 -> 6 | W7: M | Y7: 3 | AD7: 18 | AJ7: 3 | AO7: 18
A8: 4 | B8: 3178 | C8: CWQ66M | D8: 0414943453 | E8: M | F8: 1040 | G8: D | I8: 60 | J8: =IF(G8="RSL","55","0") -> 0 | K8: =IF(G8="GVS","37.5",IF(G8="GVM","41.5",IF(G8="GVL","50",IF(G8="PCS","45.8",IF(G8="PCM","50",IF(G8="PCL","58.3","0")))))) -> 0 | N8: JOHN | R8: JUNIOR | S8: 0.33333333 | T8: 0.69791667 | U8: =(T8-S8)*24 -> 8.75 | W8: L | Y8: 4 | AD8: 19 | AJ8: 4 | AO8: 19
A9: 5 | B9: 3179 | C9: CW23ZE | D9: 0438275390 | E9: L | F9: 1110 | G9: H | I9: 150 | J9: =IF(G9="RSL","55","0") -> 0 | K9: =IF(G9="GVS","37.5",IF(G9="GVM","41.5",IF(G9="GVL","50",IF(G9="PCS","45.8",IF(G9="PCM","50",IF(G9="PCL","58.3","0")))))) -> 0 | N9: JOHN | R9: KUROSH | S9: 0.41666667 | T9: 0.64583333 | U9: =(T9-S9)*24 -> 5.5 | X9: EXCL RSL | Y9: 5 | AD9: 20 | AJ9: 5 | AO9: 20
A10: 6 | B10: 3180 | C10: EEU56J | D10: 0430527449 | E10: L | F10: 1210 | G10: H/ARMOR | I10: 180 | J10: =IF(G10="RSL","55","0") -> 0 | K10: =IF(G10="GVS","37.5",IF(G10="GVM","41.5",IF(G10="GVL","50",IF(G10="PCS","45.8",IF(G10="PCM","50",IF(G10="PCL","58.3","0")))))) -> 0 | N10: JOHN | R10: ANTHONY | S10: 0.41666667 | T10: 0.64583333 | U10: =(T10-S10)*24 -> 5.5 | Y10: 6 | AD10: 21 | AJ10: 6 | AO10: 21
A11: 7 | B11: 3181 | C11: PIENAR | D11: 0437722310 | E11: S | F11: 1215 | G11: X | I11: 75 | J11: =IF(G11="RSL","55","0") -> 0 | K11: =IF(G11="GVS","37.5",IF(G11="GVM","41.5",IF(G11="GVL","50",IF(G11="PCS","45.8",IF(G11="PCM","50",IF(G11="PCL","58.3","0")))))) -> 0 | N11: JOHN | R11: HEATHER | S11: 0.41666667 | T11: 0.57291667 | U11: =(T11-S11)*24 -> 3.75 | Y11: 7 | AD11: 22 | AJ11: 7 | AO11: 22
A12: 8 | B12: 3182 | C12: HMC168 | D12: 0416235397 | E12: L | F12: 1240 | G12: PCL | J12: =IF(G12="RSL","50","0") -> 0 | K12: 79.1 | M12: 475 | N12: JOHN | O12: 22004(1/6) | S12: 0.61458333 | T12: 0.64583333 | U12: =(T12-S12)*24 -> 0.75 | Y12: 8 | AD12: 23 | AJ12: 8 | AO12: 23
A13: 9 | B13: 3183 | C13: CWB93E | D13: 0479167486 | E13: L | F13: 1245 | G13: D | H13: 50 | I13: 25 | J13: =IF(G13="RSL","55","0") -> 0 | K13: =IF(G13="GVS","37.5",IF(G13="GVM","41.5",IF(G13="GVL","50",IF(G13="PCS","45.8",IF(G13="PCM","50",IF(G13="PCL","58.3","0")))))) -> 0 | N13: JOHN | U13: =(T13-S13)*24 -> 0 | Y13: 9 | AD13: 24 | AJ13: 9 | AO13: 24
A14: 10 | B14: 3184 | C14: 2088 | D14: 0400167996 | E14: S | F14: 1250 | G14: PCS | J14: =IF(G14="RSL","50","0") -> 0 | K14: 62.5 | M14: 375 | N14: JOHN | O14: 22004(1/6) | U14: =(T14-S14)*24 -> 0 | Y14: 10 | AD14: 25 | AJ14: 10 | AO14: 25
A15: 11 | B15: 3185 | C15: EMB31D | D15: 0439642395 | E15: S | F15: 1250 | G15: X | I15: 75 | J15: =IF(G15="RSL","55","0") -> 0 | K15: =IF(G15="GVS","37.5",IF(G15="GVM","41.5",IF(G15="GVL","50",IF(G15="PCS","45.8",IF(G15="PCM","50",IF(G15="PCL","58.3","0")))))) -> 0 | N15: JOHN | U15: =(T15-S15)*24 -> 0 | Y15: 11 | AD15: 26 | AJ15: 11 | AO15: 26
A16: 12 | B16: 3186 | C16: ECG68Q | D16: 0417230580 | E16: S | F16: 1300 | G16: X | I16: 100 | J16: =IF(G16="RSL","55","0") -> 0 | K16: =IF(G16="GVS","37.5",IF(G16="GVM","41.5",IF(G16="GVL","50",IF(G16="PCS","45.8",IF(G16="PCM","50",IF(G16="PCL","58.3","0")))))) -> 0 | N16: JOHN | R16: =H32/U16 -> 0.27368421 | S16: =H32/(U16-U5) -> 0.33548387 | T16: =C32/U16 -> 25.402105 | U16: =SUM(U5:U15) -> 47.5 | Y16: 12 | AD16: 27 | AJ16: 12 | AO16: 27
A17: 13 | B17: 3187 | C17: EII82R | D17: 0451374668 | E17: L | F17: 1410 | G17: IN | I17: 80 | J17: =IF(G17="RSL","55","0") -> 0 | K17: =IF(G17="GVS","37.5",IF(G17="GVM","41.5",IF(G17="GVL","50",IF(G17="PCS","45.8",IF(G17="PCM","50",IF(G17="PCL","58.3","0")))))) -> 0 | N17: JOHN | R17: Cars/T Hr ① | S17: Cars/T Hr ② | T17: Sales/T Hr | U17: Total Hours | Y17: 13 | AD17: 28 | AJ17: 13 | AO17: 28
A18: 14 | J18: =IF(G18="RSL","55","0") -> 0 | K18: =IF(G18="GVS","37.5",IF(G18="GVM","41.5",IF(G18="GVL","50",IF(G18="PCS","45.8",IF(G18="PCM","50",IF(G18="PCL","58.3","0")))))) -> 0 | R18: ITEM | S18: QTY | T18: AMT | U18: RMKS | Y18: 14 | AD18: 29 | AJ18: 14 | AO18: 29
A19: 15 | J19: =IF(G19="RSL","55","0") -> 0 | K19: =IF(G19="GVS","37.5",IF(G19="GVM","41.5",IF(G19="GVL","50",IF(G19="PCS","45.8",IF(G19="PCM","50",IF(G19="PCL","58.3","0")))))) -> 0 | R19: GV | S19: =COUNT(L5:M29,L37:M61,L69:M93) -> 2 | T19: =SUM(L5:M29,L37:M61,L69:M93) -> 850 | Y19: 15 | AD19: 30 | AJ19: 15 | AO19: 30
A20: 16 | J20: =IF(G20="RSL","55","0") -> 0 | K20: =IF(G20="GVS","37.5",IF(G20="GVM","41.5",IF(G20="GVL","50",IF(G20="PCS","45.8",IF(G20="PCM","50",IF(G20="PCL","58.3","0")))))) -> 0 | AD20: 31 | AO20: 31
A21: 17 | J21: =IF(G21="RSL","55","0") -> 0 | K21: =IF(G21="GVS","37.5",IF(G21="GVM","41.5",IF(G21="GVL","50",IF(G21="PCS","45.8",IF(G21="PCM","50",IF(G21="PCL","58.3","0")))))) -> 0
A22: 18 | J22: =IF(G22="RSL","55","0") -> 0 | K22: =IF(G22="GVS","37.5",IF(G22="GVM","41.5",IF(G22="GVL","50",IF(G22="PCS","45.8",IF(G22="PCM","50",IF(G22="PCL","58.3","0")))))) -> 0 | AD22: Total | AE22: =SUM(Z5:Z19,AE5:AE20) -> 0 | AF22: =SUM(AA5:AA19,AF5:AF20,) -> 0 | AG22: =SUM(AB5:AB19,AG5:AG20) -> 0 | AO22: Total | AP22: =SUM(AK5:AK19,AP5:AP20) -> 0 | AQ22: =SUM(AL5:AL19,AQ5:AQ20,) -> 0 | AR22: =SUM(AM5:AM19,AR5:AR20) -> 0
A23: 19 | J23: =IF(G23="RSL","55","0") -> 0 | K23: =IF(G23="GVS","37.5",IF(G23="GVM","41.5",IF(G23="GVL","50",IF(G23="PCS","45.8",IF(G23="PCM","50",IF(G23="PCL","58.3","0")))))) -> 0
A24: 20 | J24: =IF(G24="RSL","55","0") -> 0 | K24: =IF(G24="GVS","37.5",IF(G24="GVM","41.5",IF(G24="GVL","50",IF(G24="PCS","45.8",IF(G24="PCM","50",IF(G24="PCL","58.3","0")))))) -> 0 | R24: SMALL | S24: MEDIUM | T24: LARGE | U24: TOTAL | AD24: B2/GA TOTAL | AE24: B2 machine | AF24: GA machine | AG24: BLH machine | AH24: Wongo machine | AI24: Sub total
A25: 21 | J25: =IF(G25="RSL","55","0") -> 0 | K25: =IF(G25="GVS","37.5",IF(G25="GVM","41.5",IF(G25="GVL","50",IF(G25="PCS","45.8",IF(G25="PCM","50",IF(G25="PCL","58.3","0")))))) -> 0 | R25: =COUNTIF(G5:G29,"GV1")+COUNTIF(G37:G61,"GV1")+COUNTIF(G69:G93,"GV1") -> 0 | S25: =COUNTIF(G5:G29,"GV2")+COUNTIF(G37:G61,"GV2")+COUNTIF(G69:G93,"GV2") -> 0 | T25: =COUNTIF(G5:G29,"GV3")+COUNTIF(G37:G61,"GV3")+COUNTIF(G69:G93,"GV3") -> 0 | U25: =((C32+(R26+S26+T26)*0.5)) -> 1206.6 | AD25: =SUM(AE25:AF25) -> 0 | AE25: =SUM(AE22) -> 0 | AF25: =SUM(AP22) -> 0 | AG25: =SUM(AF22+AQ22) -> 0 | AH25: =AG22+AR22 -> 0 | AI25: =SUM(AE25:AH25) -> 0
A26: 22 | J26: =IF(G26="RSL","55","0") -> 0 | K26: =IF(G26="GVS","37.5",IF(G26="GVM","41.5",IF(G26="GVL","50",IF(G26="PCS","45.8",IF(G26="PCM","50",IF(G26="PCL","58.3","0")))))) -> 0 | R26: =R25*37.5 -> 0 | S26: =S25*41.5 -> 0 | T26: =T25*50 -> 0 | X26: Branch cards
A27: 23 | J27: =IF(G27="RSL","55","0") -> 0 | K27: =IF(G27="GVS","37.5",IF(G27="GVM","41.5",IF(G27="GVL","50",IF(G27="PCS","45.8",IF(G27="PCM","50",IF(G27="PCL","58.3","0")))))) -> 0 | R27: Expense | X27: 1 | Z27: -2745
A28: 24 | J28: =IF(G28="RSL","55","0") -> 0 | K28: =IF(G28="GVS","37.5",IF(G28="GVM","41.5",IF(G28="GVL","50",IF(G28="PCS","45.8",IF(G28="PCM","50",IF(G28="PCL","58.3","0")))))) -> 0 | X28: 2
A29: 25 | J29: =IF(G29="RSL","55","0") -> 0 | K29: =IF(G29="GVS","37.5",IF(G29="GVM","41.5",IF(G29="GVL","50",IF(G29="PCS","45.8",IF(G29="PCM","50",IF(G29="PCL","58.3","0")))))) -> 0 | X29: 3
A30: Page total | H30: =SUM(H5:H29) -> 110 | I30: =SUM(I5:I29) -> 955 | J30: =J5+J6+J7+J8+J9+J10+J11+J12+J13+J14+J15+J16+J18+J19+J17+J20+J22+J23+J21+J24+J25+J26+J27+J28+J29 -> 0 | K30: =K5+K6+K7+K8+K9+K10+K11+K12+K13+K14+K15+K16+K18+K19+K17+K20+K22+K23+K21+K24+K25+K26+K27+K28+K29 -> 141.6 | L30: =SUM(L5:L29) -> 0 | M30: =SUM(M5:M29) -> 850 | N30: CASH | O30: CARD | P30: GV | Q30: RSL | X30: 4
A31: Daily Total | H31: =H30+H62+H94 -> 110 | I31: =I30+I62+I94 -> 955 | J31: =J30+J62+J94 -> 0 | K31: =K30+K62+K94 -> 141.6 | L31: =L30+L62+L94 -> 0 | M31: =M30+M62+M94 -> 850 | N31: =COUNT(H5:H29,H37:H61,H69:H93) -> 2 | O31: =COUNT(I5:I29,I37:I61,I69:I93) -> 10 | P31: =COUNTIF(G5:G29,"G*")+COUNTIF(G37:G61,"G*")+COUNTIF(G69:G93,"G*")+COUNTIF(G5:G29,"P*")+COUNTIF(G37:G61,"P*")+COUNTIF(G69:G93,"P*") -> 2 | Q31: =COUNTIF(G5:G29,"RSL")+COUNTIF(G37:G61,"RSL")+COUNTIF(G69:G93,"RSL") -> 0 | R31: CASH CLOSING | S31: =H31+L31-U28-U29-U30 -> 110 | T31: =H31+I31+L31+M31 -> 1915 | X31: Subtotal | Z31: =SUM(Z27:Z30) -> -2745
A32: TOTAL SALES | C32: =H31+I31+J31+K31 -> 1206.6 | F32: No of Cars | H32: =COUNT(B5:B29,B37:B61,B69:B93) -> 13 | I32: Average | K32: =C32/H32 -> 92.815385 | N32: =H31/C32 -> 0.091165258 | O32: =I31/C32 -> 0.79148019 | P32: =K31/C32 -> 0.11735455 | Q32: =J31/C32 -> 0 | R32: CARD CLOSING | S32: =I31+M31 -> 1805 | X32: B2 card | Z32: =I31 -> 955
A33: Daily Report | X33: Settlement | Z33: =SUM(Z31:Z32) -> -1790
A34: =A2 -> 12-02-2022 | H34: WEATHER | J34: =J2 -> MIX | L34: REPORT by | O34: =O2 -> JOHN | R34: TOTAL STAFF | T34: =T2 -> 7
A36: No | B36: Docket No | C36: Reg No | D36: Mobile | E36: Size | F36: TIME | G36: Service | H36: CASH | I36: CARD | J36: RSL | K36: GV | L36: GV CASH | M36: GV CARD | N36: O/Taker | O36: Comment | R36: NAME | S36: Time In | T36: Time out | U36: Total Hours
A37: =A29+1 -> 26 | J37: =IF(G37="RSL","50","0") -> 0 | K37: =IF(G37="GVS","37.5",IF(G37="GVM","41.5",IF(G37="GVL","50",IF(G37="PCS","45.8",IF(G37="PCM","50",IF(G37="PCL","58.3","0")))))) -> 0
A38: =A37+1 -> 27 | J38: =IF(G38="RSL","50","0") -> 0 | K38: =IF(G38="GVS","37.5",IF(G38="GVM","41.5",IF(G38="GVL","50",IF(G38="PCS","45.8",IF(G38="PCM","50",IF(G38="PCL","58.3","0")))))) -> 0
A39: =A38+1 -> 28 | J39: =IF(G39="RSL","50","0") -> 0 | K39: =IF(G39="GVS","37.5",IF(G39="GVM","41.5",IF(G39="GVL","50",IF(G39="PCS","45.8",IF(G39="PCM","50",IF(G39="PCL","58.3","0")))))) -> 0
A40: =A39+1 -> 29 | J40: =IF(G40="RSL","50","0") -> 0 | K40: =IF(G40="GVS","37.5",IF(G40="GVM","41.5",IF(G40="GVL","50",IF(G40="PCS","45.8",IF(G40="PCM","50",IF(G40="PCL","58.3","0")))))) -> 0
A41: =A40+1 -> 30 | J41: =IF(G41="RSL","50","0") -> 0 | K41: =IF(G41="GVS","37.5",IF(G41="GVM","41.5",IF(G41="GVL","50",IF(G41="PCS","45.8",IF(G41="PCM","50",IF(G41="PCL","58.3","0")))))) -> 0
A42: =A41+1 -> 31 | J42: =IF(G42="RSL","50","0") -> 0 | K42: =IF(G42="GVS","37.5",IF(G42="GVM","41.5",IF(G42="GVL","50",IF(G42="PCS","45.8",IF(G42="PCM","50",IF(G42="PCL","58.3","0")))))) -> 0
A43: =A42+1 -> 32 | J43: =IF(G43="RSL","50","0") -> 0 | K43: =IF(G43="GVS","37.5",IF(G43="GVM","41.5",IF(G43="GVL","50",IF(G43="PCS","45.8",IF(G43="PCM","50",IF(G43="PCL","58.3","0")))))) -> 0
A44: =A43+1 -> 33 | J44: =IF(G44="RSL","50","0") -> 0 | K44: =IF(G44="GVS","37.5",IF(G44="GVM","41.5",IF(G44="GVL","50",IF(G44="PCS","45.8",IF(G44="PCM","50",IF(G44="PCL","58.3","0")))))) -> 0
A45: =A44+1 -> 34 | J45: =IF(G45="RSL","50","0") -> 0 | K45: =IF(G45="GVS","37.5",IF(G45="GVM","41.5",IF(G45="GVL","50",IF(G45="PCS","45.8",IF(G45="PCM","50",IF(G45="PCL","58.3","0")))))) -> 0
A46: =A45+1 -> 35 | J46: =IF(G46="RSL","50","0") -> 0 | K46: =IF(G46="GVS","37.5",IF(G46="GVM","41.5",IF(G46="GVL","50",IF(G46="PCS","45.8",IF(G46="PCM","50",IF(G46="PCL","58.3","0")))))) -> 0
A47: =A46+1 -> 36 | J47: =IF(G47="RSL","50","0") -> 0 | K47: =IF(G47="GVS","37.5",IF(G47="GVM","41.5",IF(G47="GVL","50",IF(G47="PCS","45.8",IF(G47="PCM","50",IF(G47="PCL","58.3","0")))))) -> 0
A48: =A47+1 -> 37 | J48: =IF(G48="RSL","50","0") -> 0 | K48: =IF(G48="GVS","37.5",IF(G48="GVM","41.5",IF(G48="GVL","50",IF(G48="PCS","45.8",IF(G48="PCM","50",IF(G48="PCL","58.3","0")))))) -> 0
A49: =A48+1 -> 38 | J49: =IF(G49="RSL","50","0") -> 0 | K49: =IF(G49="GVS","37.5",IF(G49="GVM","41.5",IF(G49="GVL","50",IF(G49="PCS","45.8",IF(G49="PCM","50",IF(G49="PCL","58.3","0")))))) -> 0
... A61: =A60+1 -> 50 | J61: =IF(G61="RSL","50","0") -> 0 | K61: =IF(G61="GVS","37.5",IF(G61="GVM","41.5",IF(G61="GVL","50",IF(G61="PCS","45.8",IF(G61="PCM","50",IF(G61="PCL","58.3","0")))))) -> 0
A62: Page total | H62: =SUM(H37:H61) -> 0 | I62: =SUM(I37:I61) -> 0 | J62: =J61+J60+J59+J58+J57+J56+J55+J54+J53+J52+J51+J50+J49+J48+J47+J46+J45+J44+J43+J42+J41+J40+J39+J38+J37 -> 0 | K62: =K61+K60+K59+K58+K57+K56+K55+K54+K53+K52+K51+K50+K49+K48+K47+K46+K45+K44+K43+K42+K41+K40+K39+K38+K37 -> 0 | L62: =SUM(L37:L61) -> 0 | M62: =SUM(M37:M61) -> 0
R64: Page: 2
A65: Daily Report
A66: =A34 -> 12-02-2022 | H66: WEATHER | J66: =J34 -> MIX | L66: REPORT by | O66: =O34 -> JOHN | R66: TOTAL STAFF | T66: =T34 -> 7
A68: No | B68: Docket No | C68: Reg No | D68: Mobile | E68: Size | F68: TIME | G68: Service | H68: CASH | I68: CARD | J68: RSL | K68: GV | L68: GV CASH | M68: GV CARD | N68: O/Taker | O68: Comment | R68: NAME | S68: Time In | T68: Time out | U68: Total Hours
A69: =A61+1 -> 51 | J69: =IF(G69="RSL","50","0") -> 0 | K69: =IF(G69="GVS","37.5",IF(G69="GVM","41.5",IF(G69="GVL","50",IF(G69="PCS","45.8",IF(G69="PCM","50",IF(G69="PCL","58.3","0")))))) -> 0
A70: =A69+1 -> 52 | J70: =IF(G70="RSL","50","0") -> 0 | K70: =IF(G70="GVS","37.5",IF(G70="GVM","41.5",IF(G70="GVL","50",IF(G70="PCS","45.8",IF(G70="PCM","50",IF(G70="PCL","58.3","0")))))) -> 0
A71: =A70+1 -> 53 | J71: =IF(G71="RSL","50","0") -> 0 | K71: =IF(G71="GVS","37.5",IF(G71="GVM","41.5",IF(G71="GVL","50",IF(G71="PCS","45.8",IF(G71="PCM","50",IF(G71="PCL","58.3","0")))))) -> 0
A72: =A71+1 -> 54 | J72: =IF(G72="RSL","50","0") -> 0 | K72: =IF(G72="GVS","37.5",IF(G72="GVM","41.5",IF(G72="GVL","50",IF(G72="PCS","45.8",IF(G72="PCM","50",IF(G72="PCL","58.3","0")))))) -> 0
A73: =A72+1 -> 55 | J73: =IF(G73="RSL","50","0") -> 0 | K73: =IF(G73="GVS","37.5",IF(G73="GVM","41.5",IF(G73="GVL","50",IF(G73="PCS","45.8",IF(G73="PCM","50",IF(G73="PCL","58.3","0")))))) -> 0
A74: =A73+1 -> 56 | J74: =IF(G74="RSL","50","0") -> 0 | K74: =IF(G74="GVS","37.5",IF(G74="GVM","41.5",IF(G74="GVL","50",IF(G74="PCS","45.8",IF(G74="PCM","50",IF(G74="PCL","58.3","0")))))) -> 0
A75: =A74+1 -> 57 | J75: =IF(G75="RSL","50","0") -> 0 | K75: =IF(G75="GVS","37.5",IF(G75="GVM","41.5",IF(G75="GVL","50",IF(G75="PCS","45.8",IF(G75="PCM","50",IF(G75="PCL","58.3","0")))))) -> 0
A76: =A75+1 -> 58 | J76: =IF(G76="RSL","50","0") -> 0 | K76: =IF(G76="GVS","37.5",IF(G76="GVM","41.5",IF(G76="GVL","50",IF(G76="PCS","45.8",IF(G76="PCM","50",IF(G76="PCL","58.3","0")))))) -> 0
A77: =A76+1 -> 59 | J77: =IF(G77="RSL","50","0") -> 0 | K77: =IF(G77="GVS","37.5",IF(G77="GVM","41.5",IF(G77="GVL","50",IF(G77="PCS","45.8",IF(G77="PCM","50",IF(G77="PCL","58.3","0")))))) -> 0
A78: =A77+1 -> 60 | J78: =IF(G78="RSL","50","0") -> 0 | K78: =IF(G78="GVS","37.5",IF(G78="GVM","41.5",IF(G78="GVL","50",IF(G78="PCS","45.8",IF(G78="PCM","50",IF(G78="PCL","58.3","0")))))) -> 0
A79: =A78+1 -> 61 | J79: =IF(G79="RSL","50","0") -> 0 | K79: =IF(G79="GVS","37.5",IF(G79="GVM","41.5",IF(G79="GVL","50",IF(G79="PCS","45.8",IF(G79="PCM","50",IF(G79="PCL","58.3","0")))))) -> 0
A80: =A79+1 -> 62 | J80: =IF(G80="RSL","50","0") -> 0 | K80: =IF(G80="GVS","37.5",IF(G80="GVM","41.5",IF(G80="GVL","50",IF(G80="PCS","45.8",IF(G80="PCM","50",IF(G80="PCL","58.3","0")))))) -> 0
A81: =A80+1 -> 63 | J81: =IF(G81="RSL","50","0") -> 0 | K81: =IF(G81="GVS","37.5",IF(G81="GVM","41.5",IF(G81="GVL","50",IF(G81="PCS","45.8",IF(G81="PCM","50",IF(G81="PCL","58.3","0")))))) -> 0
... A93: =A92+1 -> 75 | J93: =IF(G93="RSL","50","0") -> 0 | K93: =IF(G93="GVS","37.5",IF(G93="GVM","41.5",IF(G93="GVL","50",IF(G93="PCS","45.8",IF(G93="PCM","50",IF(G93="PCL","58.3","0")))))) -> 0
A94: Page total | H94: =SUM(H69:H93) -> 0 | I94: =SUM(I69:I93) -> 0 | J94: =J93+J92+J91+J90+J89+J88+J87+J86+J85+J84+J83+J82+J81+J80+J79+J78+J77+J76+J75+J74+J73+J72+J71+J70+J69 -> 0 | K94: =K93+K92+K91+K90+K89+K88+K87+K86+K85+K84+K83+K82+K81+K80+K79+K78+K77+K76+K75+K74+K73+K72+K71+K70+K69 -> 0 | L94: =SUM(L69:L93) -> 0 | M94: =SUM(M69:M93) -> 0
R96: Page: 3

Sheet SUN
A1: B2 Daily Report
A2: 13-02-2022 | H2: WEATHER | J2: SUNNY | L2: REPORT BY | O2: HENDRA | R2: TOTAL STAFF | T2: 7 | X2: Merchant machine usage at B2 | AA2: Settle amount | AI2: Merchant machine usage at GA | AL2: Settle amount
A4: No | B4: Docket No | C4: Reg No | D4: Mobile | E4: Size | F4: TIME | G4: Service | H4: CASH | I4: CARD | J4: RSL | K4: GV | L4: GV CASH | M4: GV CARD | N4: O/Taker | O4: Comment | R4: NAME | S4: Time In | T4: Time out | U4: Total Hours | Z4: B2 machine | AA4: BLH machine | AB4: Wongo | AE4: B2 machine | AF4: BLH machine | AG4: Wongo | AK4: GA machine | AL4: BLH machine | AM4: Wongo | AP4: GA machine | AQ4: BLH machine | AR4: Wongo
A5: 1 | B5: 3188 | C5: CGB33Z | D5: 0413002322 | E5: S | F5: 810 | G5: RSL | J5: =IF(G5="RSL","55","0") -> 55 | K5: =IF(G5="GVS","37.5",IF(G5="GVM","41.5",IF(G5="GVL","50",IF(G5="PCS","45.8",IF(G5="PCM","50",IF(G5="PCL","58.3","0")))))) -> 0 | N5: HENDRA | O5: 202112014 | R5: HENDRA | S5: 0.33333333 | T5: 0.72916667 | U5: =(T5-S5)*24 -> 9.5 | X5: NOV | Y5: 1 | AD5: 16 | AI5: NOV | AJ5: 1 | AO5: 16
A6: 2 | B6: 3189 | C6: BJ69RS | D6: 0432638117 | E6: S | F6: 925 | G6: D | I6: 55 | J6: =IF(G6="RSL","55","0") -> 0 | K6: =IF(G6="GVS","37.5",IF(G6="GVM","41.5",IF(G6="GVL","50",IF(G6="PCS","45.8",IF(G6="PCM","50",IF(G6="PCL","58.3","0")))))) -> 0 | N6: HENDRA | R6: JUNIOR | S6: 0.33333333 | T6: 0.72916667 | U6: =(T6-S6)*24 -> 9.5 | W6: S | Y6: 2 | AD6: 17 | AJ6: 2 | AO6: 17
A7: 3 | B7: 3190 | C7: DBG98Q | D7: 0420566060 | E7: S | F7: 1005 | G7: RSL | J7: 110 | K7: =IF(G7="GVS","37.5",IF(G7="GVM","41.5",IF(G7="GVL","50",IF(G7="PCS","45.8",IF(G7="PCM","50",IF(G7="PCL","58.3","0")))))) -> 0 | N7: HENDRA | O7: 202201042, 202201043(x) | R7: KUROSH | S7: 0.39583333 | T7: 0.71875 | U7: =(T7-S7)*24 -> 7.75 | W7: M | Y7: 3 | AD7: 18 | AJ7: 3 | AO7: 18
A8: 4 | B8: 3191 | C8: ECE78G | D8: 0402031217 | E8: M | F8: 1005 | G8: D | I8: 60 | J8: =IF(G8="RSL","55","0") -> 0 | K8: =IF(G8="GVS","37.5",IF(G8="GVM","41.5",IF(G8="GVL","50",IF(G8="PCS","45.8",IF(G8="PCM","50",IF(G8="PCL","58.3","0")))))) -> 0 | N8: HENDRA | R8: ANTHONY | S8: 0.41666667 | T8: 0.71875 | U8: =(T8-S8)*24 -> 7.25 | W8: L | Y8: 4 | AD8: 19 | AJ8: 4 | AO8: 19
A9: 5 | B9: 3192 | C9: DHN23B | D9: 0423471070 | E9: L | F9: 1005 | G9: GV3 | J9: =IF(G9="RSL","55","0") -> 0 | K9: =IF(G9="GVS","37.5",IF(G9="GVM","41.5",IF(G9="GVL","50",IF(G9="PCS","45.8",IF(G9="PCM","50",IF(G9="PCL","58.3","0")))))) -> 0 | N9: HENDRA | O9: 192649(4/6) | R9: HEATHER | S9: 0.39583333 | T9: 0.72916667 | U9: =(T9-S9)*24 -> 8 | X9: EXCL RSL | Y9: 5 | AD9: 20 | AJ9: 5 | AO9: 20
A10: 6 | B10: 3193 | C10: DPH25M | D10: 0413128074 | E10: L | F10: 1010 | G10: PCL | J10: =IF(G10="RSL","55","0") -> 0 | K10: 79.1 | N10: HENDRA | O10: 21027 (5/6) | R10: JAIKE | S10: 0.41666667 | T10: 0.70833333 | U10: =(T10-S10)*24 -> 7 | Y10: 6 | AD10: 21 | AJ10: 6 | AO10: 21
A11: 7 | B11: 3194 | C11: DHG63Z | D11: 0413693536 | E11: S | F11: 1050 | G11: D/ST | I11: 145 | J11: =IF(G11="RSL","55","0") -> 0 | K11: =IF(G11="GVS","37.5",IF(G11="GVM","41.5",IF(G11="GVL","50",IF(G11="PCS","45.8",IF(G11="PCM","50",IF(G11="PCL","58.3","0")))))) -> 0 | N11: HENDRA | O11: TAX | R11: PETER | S11: 0.375 | T11: 0.70833333 | U11: =(T11-S11)*24 -> 8 | Y11: 7 | AD11: 22 | AJ11: 7 | AO11: 22
A12: 8 | B12: 3195 | C12: CKA59X | D12: 0424138064 | E12: S | F12: 1100 | G12: D | I12: 55 | J12: =IF(G12="RSL","55","0") -> 0 | K12: =IF(G12="GVS","37.5",IF(G12="GVM","41.5",IF(G12="GVL","50",IF(G12="PCS","45.8",IF(G12="PCM","50",IF(G12="PCL","58.3","0")))))) -> 0 | N12: HENDRA | U12: =(T12-S12)*24 -> 0 | Y12: 8 | AD12: 23 | AJ12: 8 | AO12: 23
A13: 9 | B13: 3196 | C13: CMK487 | D13: 0422997980 | E13: L | F13: 1135 | G13: X | I13: 95 | J13: =IF(G13="RSL","55","0") -> 0 | K13: =IF(G13="GVS","37.5",IF(G13="GVM","41.5",IF(G13="GVL","50",IF(G13="PCS","45.8",IF(G13="PCM","50",IF(G13="PCL","58.3","0")))))) -> 0 | N13: HENDRA | O13: TAX | U13: =(T13-S13)*24 -> 0 | Y13: 9 | AD13: 24 | AJ13: 9 | AO13: 24
A14: 10 | B14: 3197 | C14: YDX79Q | D14: 0418230539 | E14: L | F14: 1145 | G14: W/H | I14: 100 | J14: =IF(G14="RSL","55","0") -> 0 | K14: =IF(G14="GVS","37.5",IF(G14="GVM","41.5",IF(G14="GVL","50",IF(G14="PCS","45.8",IF(G14="PCM","50",IF(G14="PCL","58.3","0")))))) -> 0 | N14: HENDRA | U14: =(T14-S14)*24 -> 0 | Y14: 10 | AD14: 25 | AJ14: 10 | AO14: 25
A15: 11 | B15: 3198 | C15: EMJ32U | D15: 0466711171 | E15: L | F15: 1225 | G15: X | I15: 95 | J15: =IF(G15="RSL","55","0") -> 0 | K15: =IF(G15="GVS","37.5",IF(G15="GVM","41.5",IF(G15="GVL","50",IF(G15="PCS","45.8",IF(G15="PCM","50",IF(G15="PCL","58.3","0")))))) -> 0 | N15: HENDRA | U15: =(T15-S15)*24 -> 0 | Y15: 11 | AD15: 26 | AJ15: 11 | AO15: 26
A16: 12 | B16: 3199 | C16: CWP52Y | D16: 0403215490 | E16: L | F16: 1230 | G16: PCL | J16: =IF(G16="RSL","55","0") -> 0 | K16: 79.1 | N16: HENDRA | O16: 21059 (1/6) | R16: =H32/U16 -> 0.42105263 | S16: =H32/(U16-U5) -> 0.50526316 | T16: =C32/U16 -> 38.403509 | U16: =SUM(U5:U15) -> 57 | Y16: 12 | AD16: 27 | AJ16: 12 | AO16: 27
A17: 13 | B17: 3200 | C17: DGE07L | D17: 0422286731 | E17: L | F17: 1235 | G17: H | H17: 150 | J17: =IF(G17="RSL","55","0") -> 0 | K17: =IF(G17="GVS","37.5",IF(G17="GVM","41.5",IF(G17="GVL","50",IF(G17="PCS","45.8",IF(G17="PCM","50",IF(G17="PCL","58.3","0")))))) -> 0 | N17: HENDRA | R17: Cars/T Hr ① | S17: Cars/T Hr ② | T17: Sales/T Hr | U17: Total Hours | Y17: 13 | AD17: 28 | AJ17: 13 | AO17: 28
A18: 14 | B18: 3201 | C18: cJKJ75E | D18: 0413328510 | E18: L | F18: 1300 | G18: X | I18: 95 | J18: =IF(G18="RSL","55","0") -> 0 | K18: =IF(G18="GVS","37.5",IF(G18="GVM","41.5",IF(G18="GVL","50",IF(G18="PCS","45.8",IF(G18="PCM","50",IF(G18="PCL","58.3","0")))))) -> 0 | N18: HENDRA | R18: ITEM | S18: QTY | T18: AMT | U18: RMKS | Y18: 14 | AD18: 29 | AJ18: 14 | AO18: 29
A19: 15 | B19: 3202 | C19: COD81L | D19: 0410888824 | E19: S | F19: 1310 | G19: GV1 | J19: =IF(G19="RSL","55","0") -> 0 | K19: =IF(G19="GVS","37.5",IF(G19="GVM","41.5",IF(G19="GVL","50",IF(G19="PCS","45.8",IF(G19="PCM","50",IF(G19="PCL","58.3","0")))))) -> 0 | N19: HENDRA | O19: 202788 (6/6) | R19: GV | S19: =COUNT(L5:M29,L37:M61,L69:M93) -> 1 | T19: =SUM(L5:M29,L37:M61,L69:M93) -> 375 | Y19: 15 | AD19: 30 | AJ19: 15 | AO19: 30
A20: 16 | B20: 3203 | C20: DXB70P | D20: 0439931560 | E20: S | F20: 1330 | G20: D/ST | I20: 150 | J20: =IF(G20="RSL","55","0") -> 0 | K20: =IF(G20="GVS","37.5",IF(G20="GVM","41.5",IF(G20="GVL","50",IF(G20="PCS","45.8",IF(G20="PCM","50",IF(G20="PCL","58.3","0")))))) -> 0 | N20: HENDRA | AD20: 31 | AO20: 31
A21: 17 | B21: 3204 | C21: DWR91R | D21: 0403419794 | E21: S | F21: 1400 | G21: PCS | J21: =IF(G21="RSL","55","0") -> 0 | K21: 62.5 | M21: 375 | N21: HENDRA | O21: 22005 (1/6)
A22: 18 | B22: 3205 | C22: CYS78B | D22: 0405128331 | E22: S | F22: 1405 | G22: X | I22: 100 | J22: =IF(G22="RSL","55","0") -> 0 | K22: =IF(G22="GVS","37.5",IF(G22="GVM","41.5",IF(G22="GVL","50",IF(G22="PCS","45.8",IF(G22="PCM","50",IF(G22="PCL","58.3","0")))))) -> 0 | N22: HENDRA | AD22: Total | AE22: =SUM(Z5:Z19,AE5:AE20) -> 0 | AF22: =SUM(AA5:AA19,AF5:AF20,) -> 0 | AG22: =SUM(AB5:AB19,AG5:AG20) -> 0 | AO22: Total | AP22: =SUM(AK5:AK19,AP5:AP20) -> 0 | AQ22: =SUM(AL5:AL19,AQ5:AQ20,) -> 0 | AR22: =SUM(AM5:AM19,AR5:AR20) -> 0
A23: 19 | B23: 3206 | C23: EKY86R | D23: 0408763516 | E23: S | F23: 1415 | G23: H/ST | I23: 200 | J23: =IF(G23="RSL","55","0") -> 0 | K23: =IF(G23="GVS","37.5",IF(G23="GVM","41.5",IF(G23="GVL","50",IF(G23="PCS","45.8",IF(G23="PCM","50",IF(G23="PCL","58.3","0")))))) -> 0 | N23: HENDRA
A24: 20 | B24: 3207 | C24: DPL50C | D24: 0430380802 | E24: L | F24: 1420 | G24: H | I24: 150 | J24: =IF(G24="RSL","55","0") -> 0 | K24: =IF(G24="GVS","37.5",IF(G24="GVM","41.5",IF(G24="GVL","50",IF(G24="PCS","45.8",IF(G24="PCM","50",IF(G24="PCL","58.3","0")))))) -> 0 | N24: HENDRA | R24: SMALL | S24: MEDIUM | T24: LARGE | U24: TOTAL | AD24: B2/GA TOTAL | AE24: B2 machine | AF24: GA machine | AG24: BLH machine | AH24: Wongo machine | AI24: Sub total
A25: 21 | B25: 3208 | C25: CAH21V | D25: 0437737553 | E25: L | F25: 1445 | G25: H | I25: 150 | J25: =IF(G25="RSL","55","0") -> 0 | K25: =IF(G25="GVS","37.5",IF(G25="GVM","41.5",IF(G25="GVL","50",IF(G25="PCS","45.8",IF(G25="PCM","50",IF(G25="PCL","58.3","0")))))) -> 0 | N25: HENDRA | R25: =COUNTIF(G5:G29,"GV1")+COUNTIF(G37:G61,"GV1")+COUNTIF(G69:G93,"GV1") -> 1 | S25: =COUNTIF(G5:G29,"GV2")+COUNTIF(G37:G61,"GV2")+COUNTIF(G69:G93,"GV2") -> 0 | T25: =COUNTIF(G5:G29,"GV3")+COUNTIF(G37:G61,"GV3")+COUNTIF(G69:G93,"GV3") -> 1 | U25: =((C32+(R26+S26+T26)*0.5)) -> 2232.75 | AD25: =SUM(AE25:AF25) -> 0 | AE25: =SUM(AE22) -> 0 | AF25: =SUM(AP22) -> 0 | AG25: =SUM(AF22+AQ22) -> 0 | AH25: =AG22+AR22 -> 0 | AI25: =SUM(AE25:AH25) -> 0
A26: 22 | B26: 3209 | C26: AWS04Q | D26: 0413318376 | E26: S | F26: 1456 | G26: D | I26: 70 | J26: =IF(G26="RSL","55","0") -> 0 | K26: =IF(G26="GVS","37.5",IF(G26="GVM","41.5",IF(G26="GVL","50",IF(G26="PCS","45.8",IF(G26="PCM","50",IF(G26="PCL","58.3","0")))))) -> 0 | N26: HENDRA | R26: =R25*37.5 -> 37.5 | S26: =S25*41.5 -> 0 | T26: =T25*50 -> 50 | X26: Branch cards
A27: 23 | B27: 3210 | C27: DJL54R | D27: 0408752956 | E27: L | F27: 1500 | G27: PCL | J27: =IF(G27="RSL","55","0") -> 0 | K27: =IF(G27="GVS","37.5",IF(G27="GVM","41.5",IF(G27="GVL","50",IF(G27="PCS","45.8",IF(G27="PCM","50",IF(G27="PCL","58.3","0")))))) -> 58.3 | N27: HENDRA | O27: 2112062.3 | R27: Expense | X27: 1 | Z27: -2745
A28: 24 | B28: 3211 | C28: ECK37C | D28: 0410471717 | E28: L | F28: 1550 | G28: D | I28: 75 | J28: =IF(G28="RSL","55","0") -> 0 | K28: =IF(G28="GVS","37.5",IF(G28="GVM","41.5",IF(G28="GVL","50",IF(G28="PCS","45.8",IF(G28="PCM","50",IF(G28="PCL","58.3","0")))))) -> 0 | N28: HENDRA | X28: 2
A29: 25 | J29: =IF(G29="RSL","55","0") -> 0 | K29: =IF(G29="GVS","37.5",IF(G29="GVM","41.5",IF(G29="GVL","50",IF(G29="PCS","45.8",IF(G29="PCM","50",IF(G29="PCL","58.3","0")))))) -> 0 | X29: 3
A30: Page total | H30: =SUM(H5:H29) -> 150 | I30: =SUM(I5:I29) -> 1595 | J30: =J5+J6+J7+J8+J9+J10+J11+J12+J13+J14+J15+J16+J18+J19+J17+J20+J22+J23+J21+J24+J25+J26+J27+J28+J29 -> 165 | K30: =K5+K6+K7+K8+K9+K10+K11+K12+K13+K14+K15+K16+K18+K19+K17+K20+K22+K23+K21+K24+K25+K26+K27+K28+K29 -> 279 | L30: =SUM(L5:L29) -> 0 | M30: =SUM(M5:M29) -> 375 | N30: CASH | O30: CARD | P30: GV | Q30: RSL | X30: 4
A31: Daily Total | H31: =H30+H62+H94 -> 150 | I31: =I30+I62+I94 -> 1595 | J31: =J30+J62+J94 -> 165 | K31: =K30+K62+K94 -> 279 | L31: =L30+L62+L94 -> 0 | M31: =M30+M62+M94 -> 375 | N31: =COUNT(H5:H29,H37:H61,H69:H93) -> 1 | O31: =COUNT(I5:I29,I37:I61,I69:I93) -> 15 | P31: =COUNTIF(G5:G29,"G*")+COUNTIF(G37:G61,"G*")+COUNTIF(G69:G93,"G*")+COUNTIF(G5:G29,"P*")+COUNTIF(G37:G61,"P*")+COUNTIF(G69:G93,"P*") -> 6 | Q31: =COUNTIF(G5:G29,"RSL")+COUNTIF(G37:G61,"RSL")+COUNTIF(G69:G93,"RSL") -> 2 | R31: CASH CLOSING | S31: =H31+L31-U28-U29-U30 -> 150 | T31: =H31+I31+L31+M31 -> 2120 | X31: Subtotal | Z31: =SUM(Z27:Z30) -> -2745
A32: TOTAL SALES | C32: =H31+I31+J31+K31 -> 2189 | F32: No of Cars | H32: =COUNT(B5:B29,B37:B61,B69:B93) -> 24 | I32: Average | K32: =C32/H32 -> 91.208333 | N32: =H31/C32 -> 0.06852444 | O32: =I31/C32 -> 0.72864322 | P32: =K31/C32 -> 0.12745546 | Q32: =J31/C32 -> 0.075376884 | R32: CARD CLOSING | S32: =I31+M31 -> 1970 | X32: B2 card | Z32: =I31 -> 1595
A33: Daily Report | X33: Settlement | Z33: =SUM(Z31:Z32) -> -1150
A34: =A2 -> 13-02-2022 | H34: WEATHER | J34: =J2 -> SUNNY | L34: REPORT by | O34: =O2 -> HENDRA | R34: TOTAL STAFF | T34: =T2 -> 7
A36: No | B36: Docket No | C36: Reg No | D36: Mobile | E36: Size | F36: TIME | G36: Service | H36: CASH | I36: CARD | J36: RSL | K36: GV | L36: GV CASH | M36: GV CARD | N36: O/Taker | O36: Comment | R36: NAME | S36: Time In | T36: Time out | U36: Total Hours
A37: =A29+1 -> 26 | J37: =IF(G37="RSL","55","0") -> 0 | K37: =IF(G37="GVS","37.5",IF(G37="GVM","41.5",IF(G37="GVL","50",IF(G37="PCS","45.8",IF(G37="PCM","50",IF(G37="PCL","58.3","0")))))) -> 0
A38: =A37+1 -> 27 | J38: =IF(G38="RSL","55","0") -> 0 | K38: =IF(G38="GVS","37.5",IF(G38="GVM","41.5",IF(G38="GVL","50",IF(G38="PCS","45.8",IF(G38="PCM","50",IF(G38="PCL","58.3","0")))))) -> 0
A39: =A38+1 -> 28 | J39: =IF(G39="RSL","55","0") -> 0 | K39: =IF(G39="GVS","37.5",IF(G39="GVM","41.5",IF(G39="GVL","50",IF(G39="PCS","45.8",IF(G39="PCM","50",IF(G39="PCL","58.3","0")))))) -> 0
A40: =A39+1 -> 29 | J40: =IF(G40="RSL","55","0") -> 0 | K40: =IF(G40="GVS","37.5",IF(G40="GVM","41.5",IF(G40="GVL","50",IF(G40="PCS","45.8",IF(G40="PCM","50",IF(G40="PCL","58.3","0")))))) -> 0
A41: =A40+1 -> 30 | J41: =IF(G41="RSL","55","0") -> 0 | K41: =IF(G41="GVS","37.5",IF(G41="GVM","41.5",IF(G41="GVL","50",IF(G41="PCS","45.8",IF(G41="PCM","50",IF(G41="PCL","58.3","0")))))) -> 0
A42: =A41+1 -> 31 | J42: =IF(G42="RSL","55","0") -> 0 | K42: =IF(G42="GVS","37.5",IF(G42="GVM","41.5",IF(G42="GVL","50",IF(G42="PCS","45.8",IF(G42="PCM","50",IF(G42="PCL","58.3","0")))))) -> 0
A43: =A42+1 -> 32 | J43: =IF(G43="RSL","55","0") -> 0 | K43: =IF(G43="GVS","37.5",IF(G43="GVM","41.5",IF(G43="GVL","50",IF(G43="PCS","45.8",IF(G43="PCM","50",IF(G43="PCL","58.3","0")))))) -> 0
A44: =A43+1 -> 33 | J44: =IF(G44="RSL","55","0") -> 0 | K44: =IF(G44="GVS","37.5",IF(G44="GVM","41.5",IF(G44="GVL","50",IF(G44="PCS","45.8",IF(G44="PCM","50",IF(G44="PCL","58.3","0")))))) -> 0
A45: =A44+1 -> 34 | J45: =IF(G45="RSL","55","0") -> 0 | K45: =IF(G45="GVS","37.5",IF(G45="GVM","41.5",IF(G45="GVL","50",IF(G45="PCS","45.8",IF(G45="PCM","50",IF(G45="PCL","58.3","0")))))) -> 0
A46: =A45+1 -> 35 | J46: =IF(G46="RSL","55","0") -> 0 | K46: =IF(G46="GVS","37.5",IF(G46="GVM","41.5",IF(G46="GVL","50",IF(G46="PCS","45.8",IF(G46="PCM","50",IF(G46="PCL","58.3","0")))))) -> 0
A47: =A46+1 -> 36 | J47: =IF(G47="RSL","55","0") -> 0 | K47: =IF(G47="GVS","37.5",IF(G47="GVM","41.5",IF(G47="GVL","50",IF(G47="PCS","45.8",IF(G47="PCM","50",IF(G47="PCL","58.3","0")))))) -> 0
A48: =A47+1 -> 37 | J48: =IF(G48="RSL","55","0") -> 0 | K48: =IF(G48="GVS","37.5",IF(G48="GVM","41.5",IF(G48="GVL","50",IF(G48="PCS","45.8",IF(G48="PCM","50",IF(G48="PCL","58.3","0")))))) -> 0
A49: =A48+1 -> 38 | J49: =IF(G49="RSL","55","0") -> 0 | K49: =IF(G49="GVS","37.5",IF(G49="GVM","41.5",IF(G49="GVL","50",IF(G49="PCS","45.8",IF(G49="PCM","50",IF(G49="PCL","58.3","0")))))) -> 0
... A61: =A60+1 -> 50 | J61: =IF(G61="RSL","55","0") -> 0 | K61: =IF(G61="GVS","37.5",IF(G61="GVM","41.5",IF(G61="GVL","50",IF(G61="PCS","45.8",IF(G61="PCM","50",IF(G61="PCL","58.3","0")))))) -> 0
A62: Page total | H62: =SUM(H37:H61) -> 0 | I62: =SUM(I37:I61) -> 0 | J62: =J61+J60+J59+J58+J57+J56+J55+J54+J53+J52+J51+J50+J49+J48+J47+J46+J45+J44+J43+J42+J41+J40+J39+J38+J37 -> 0 | K62: =K61+K60+K59+K58+K57+K56+K55+K54+K53+K52+K51+K50+K49+K48+K47+K46+K45+K44+K43+K42+K41+K40+K39+K38+K37 -> 0 | L62: =SUM(L37:L61) -> 0 | M62: =SUM(M37:M61) -> 0
R64: Page: 2
A65: Daily Report
A66: =A34 -> 13-02-2022 | H66: WEATHER | J66: =J34 -> SUNNY | L66: REPORT by | O66: =O34 -> HENDRA | R66: TOTAL STAFF | T66: =T34 -> 7
A68: No | B68: Docket No | C68: Reg No | D68: Mobile | E68: Size | F68: TIME | G68: Service | H68: CASH | I68: CARD | J68: RSL | K68: GV | L68: GV CASH | M68: GV CARD | N68: O/Taker | O68: Comment | R68: NAME | S68: Time In | T68: Time out | U68: Total Hours
A69: =A61+1 -> 51 | J69: =IF(G69="RSL","55","0") -> 0 | K69: =IF(G69="GVS","37.5",IF(G69="GVM","41.5",IF(G69="GVL","50",IF(G69="PCS","45.8",IF(G69="PCM","50",IF(G69="PCL","58.3","0")))))) -> 0
A70: =A69+1 -> 52 | J70: =IF(G70="RSL","55","0") -> 0 | K70: =IF(G70="GVS","37.5",IF(G70="GVM","41.5",IF(G70="GVL","50",IF(G70="PCS","45.8",IF(G70="PCM","50",IF(G70="PCL","58.3","0")))))) -> 0
A71: =A70+1 -> 53 | J71: =IF(G71="RSL","55","0") -> 0 | K71: =IF(G71="GVS","37.5",IF(G71="GVM","41.5",IF(G71="GVL","50",IF(G71="PCS","45.8",IF(G71="PCM","50",IF(G71="PCL","58.3","0")))))) -> 0
A72: =A71+1 -> 54 | J72: =IF(G72="RSL","55","0") -> 0 | K72: =IF(G72="GVS","37.5",IF(G72="GVM","41.5",IF(G72="GVL","50",IF(G72="PCS","45.8",IF(G72="PCM","50",IF(G72="PCL","58.3","0")))))) -> 0
A73: =A72+1 -> 55 | J73: =IF(G73="RSL","55","0") -> 0 | K73: =IF(G73="GVS","37.5",IF(G73="GVM","41.5",IF(G73="GVL","50",IF(G73="PCS","45.8",IF(G73="PCM","50",IF(G73="PCL","58.3","0")))))) -> 0
A74: =A73+1 -> 56 | J74: =IF(G74="RSL","55","0") -> 0 | K74: =IF(G74="GVS","37.5",IF(G74="GVM","41.5",IF(G74="GVL","50",IF(G74="PCS","45.8",IF(G74="PCM","50",IF(G74="PCL","58.3","0")))))) -> 0
A75: =A74+1 -> 57 | J75: =IF(G75="RSL","55","0") -> 0 | K75: =IF(G75="GVS","37.5",IF(G75="GVM","41.5",IF(G75="GVL","50",IF(G75="PCS","45.8",IF(G75="PCM","50",IF(G75="PCL","58.3","0")))))) -> 0
A76: =A75+1 -> 58 | J76: =IF(G76="RSL","55","0") -> 0 | K76: =IF(G76="GVS","37.5",IF(G76="GVM","41.5",IF(G76="GVL","50",IF(G76="PCS","45.8",IF(G76="PCM","50",IF(G76="PCL","58.3","0")))))) -> 0
A77: =A76+1 -> 59 | J77: =IF(G77="RSL","55","0") -> 0 | K77: =IF(G77="GVS","37.5",IF(G77="GVM","41.5",IF(G77="GVL","50",IF(G77="PCS","45.8",IF(G77="PCM","50",IF(G77="PCL","58.3","0")))))) -> 0
A78: =A77+1 -> 60 | J78: =IF(G78="RSL","55","0") -> 0 | K78: =IF(G78="GVS","37.5",IF(G78="GVM","41.5",IF(G78="GVL","50",IF(G78="PCS","45.8",IF(G78="PCM","50",IF(G78="PCL","58.3","0")))))) -> 0
A79: =A78+1 -> 61 | J79: =IF(G79="RSL","55","0") -> 0 | K79: =IF(G79="GVS","37.5",IF(G79="GVM","41.5",IF(G79="GVL","50",IF(G79="PCS","45.8",IF(G79="PCM","50",IF(G79="PCL","58.3","0")))))) -> 0
A80: =A79+1 -> 62 | J80: =IF(G80="RSL","55","0") -> 0 | K80: =IF(G80="GVS","37.5",IF(G80="GVM","41.5",IF(G80="GVL","50",IF(G80="PCS","45.8",IF(G80="PCM","50",IF(G80="PCL","58.3","0")))))) -> 0
A81: =A80+1 -> 63 | J81: =IF(G81="RSL","55","0") -> 0 | K81: =IF(G81="GVS","37.5",IF(G81="GVM","41.5",IF(G81="GVL","50",IF(G81="PCS","45.8",IF(G81="PCM","50",IF(G81="PCL","58.3","0")))))) -> 0
... A93: =A92+1 -> 75 | J93: =IF(G93="RSL","55","0") -> 0 | K93: =IF(G93="GVS","37.5",IF(G93="GVM","41.5",IF(G93="GVL","50",IF(G93="PCS","45.8",IF(G93="PCM","50",IF(G93="PCL","58.3","0")))))) -> 0
A94: Page total | H94: =SUM(H69:H93) -> 0 | I94: =SUM(I69:I93) -> 0 | J94: =J93+J92+J91+J90+J89+J88+J87+J86+J85+J84+J83+J82+J81+J80+J79+J78+J77+J76+J75+J74+J73+J72+J71+J70+J69 -> 0 | K94: =K93+K92+K91+K90+K89+K88+K87+K86+K85+K84+K83+K82+K81+K80+K79+K78+K77+K76+K75+K74+K73+K72+K71+K70+K69 -> 0 | L94: =SUM(L69:L93) -> 0 | M94: =SUM(M69:M93) -> 0
R96: Page: 3

Sheet WEEKLY TOTAL
E1: CARS | H1: AMOUNT | L1: PERCENTAGE | Q1: TOTAL CARS | V1: TOTAL AMOUNT | AA1: AVERAGE
A2: MON | B2: Cash | E2: =MON!N31 -> 1 | H2: =MON!S31 -> 150 | L2: =MON!N32 -> 0.20833333 | Q2: =SUM(E2:G5) -> 9 | V2: =SUM(H2,H3,H5) -> 720 | AA2: =V2/Q2 -> 80
B3: Card | E3: =MON!O31 -> 8 | H3: =MON!S32 -> 570 | L3: =MON!O32 -> 0.79166667
B4: GV | E4: =MON!P31 -> 0 | H4: =MON!K31 -> 0 | L4: =MON!P32 -> 0
B5: RSL | E5: =MON!Q31 -> 0 | H5: =MON!J31 -> 0 | L5: =MON!Q32 -> 0
B6: hrs | E6: =MON!U16 -> 30.75 | H6: no. staff | L6: =MON!T2 -> 4
A7: TUE | B7: Cash | E7: =TUE!N31 -> 0 | H7: =TUE!S31 -> 0 | L7: =TUE!N32 -> 0 | Q7: =SUM(E7:G10) -> 7 | V7: =SUM(H7,H8,H10) -> 1190 | AA7: =V7/Q7 -> 170
B8: Card | E8: =TUE!O31 -> 5 | H8: =TUE!S32 -> 1190 | L8: =TUE!O32 -> 0.81983704
B9: GV | E9: =TUE!P31 -> 2 | H9: =TUE!K31 -> 179.1 | L9: =TUE!P32 -> 0.18016296
B10: RSL | E10: =TUE!Q31 -> 0 | H10: =TUE!J31 -> 0 | L10: =TUE!Q32 -> 0
B11: hrs | E11: =TUE!U16 -> 38.25 | H11: no. staff | L11: =TUE!T2 -> 5
A12: WED | B12: Cash | E12: =WED!N31 -> 1 | H12: =WED!S31 -> 50 | L12: =WED!N32 -> 0.021408692 | Q12: =SUM(E12:G15) -> 24 | V12: =SUM(H12,H13,H15) -> 2245 | AA12: =V12/Q12 -> 93.541667
B13: Card | E13: =WED!O31 -> 16 | H13: =WED!S32 -> 2195 | L13: =WED!O32 -> 0.77927639
B14: GV | E14: =WED!P31 -> 7 | H14: =WED!K31 -> 465.5 | L14: =WED!P32 -> 0.19931492
B15: RSL | E15: =WED!Q31 -> 0 | H15: =WED!J31 -> 0 | L15: =WED!Q32 -> 0
B16: hrs | E16: =WED!U16 -> 46.666667 | H16: no. staff | L16: =WED!T2 -> 6
A17: THU | B17: Cash | E17: =THU!N31 -> 2 | H17: =THU!S31 -> 65 | L17: =THU!N32 -> 0.04264812 | Q17: =SUM(E17:G20) -> 20 | V17: =SUM(H17,H18,H20) -> 1795 | AA17: =V17/Q17 -> 89.75
B18: Card | E18: =THU!O31 -> 15 | H18: =THU!S32 -> 1680 | L18: =THU!O32 -> 0.85624303
B19: GV | E19: =THU!P31 -> 2 | H19: =THU!K31 -> 104.1 | L19: =THU!P32 -> 0.068302605
B20: RSL | E20: =THU!Q31 -> 1 | H20: =THU!J31 -> 50 | L20: =THU!Q32 -> 0.032806246
B21: hrs | E21: =THU!U16 -> 51 | H21: no. staff | L21: =THU!T2 -> 7
A22: FR I | B22: Cash | E22: =FRI!N31 -> 6 | H22: =FRI!S31 -> 930 | L22: =FRI!N32 -> 0.43055556 | Q22: =SUM(E22:G25) -> 11 | V22: =SUM(H22,H23,H25) -> 2160 | AA22: =V22/Q22 -> 196.36364
B23: Card | E23: =FRI!O31 -> 5 | H23: =FRI!S32 -> 1230 | L23: =FRI!O32 -> 0.56944444
B24: GV | E24: =FRI!P31 -> 0 | H24: =FRI!K31 -> 0 | L24: =FRI!P32 -> 0
B25: RSL | E25: =FRI!Q31 -> 0 | H25: =FRI!J31 -> 0 | L25: =FRI!Q32 -> 0
B26: hrs | E26: =FRI!U16 -> 28.5 | H26: no. staff | L26: =FRI!T2 -> 4
A27: SAT | B27: Cash | E27: =SAT!N31 -> 2 | H27: =SAT!S31 -> 110 | L27: =SAT!N32 -> 0.091165258 | Q27: =SUM(E27:G30) -> 14 | V27: =SUM(H27,H28,H30) -> 1915 | AA27: =V27/Q27 -> 136.78571
B28: Card | E28: =SAT!O31 -> 10 | H28: =SAT!S32 -> 1805 | L28: =SAT!O32 -> 0.79148019
B29: GV | E29: =SAT!P31 -> 2 | H29: =SAT!K31 -> 141.6 | L29: =SAT!P32 -> 0.11735455
B30: RSL | E30: =SAT!Q31 -> 0 | H30: =SAT!J31 -> 0 | L30: =SAT!Q32 -> 0
B31: hrs | E31: =SAT!U16 -> 47.5 | H31: no. staff | L31: =SAT!T2 -> 7
A32: SUN | B32: Cash | E32: =SUN!N31 -> 1 | H32: =SUN!S31 -> 150 | L32: =SUN!N32 -> 0.06852444 | Q32: =SUM(E32:G35) -> 24 | V32: =SUM(H32,H33,H35) -> 2285 | AA32: =V32/Q32 -> 95.208333
B33: Card | E33: =SUN!O31 -> 15 | H33: =SUN!S32 -> 1970 | L33: =SUN!O32 -> 0.72864322
B34: GV | E34: =SUN!P31 -> 6 | H34: =SUN!K31 -> 279 | L34: =SUN!P32 -> 0.12745546
B35: RSL | E35: =SUN!Q31 -> 2 | H35: =SUN!J31 -> 165 | L35: =SUN!Q32 -> 0.075376884
B36: hrs | E36: =SUN!U16 -> 57 | H36: no. staff | L36: =SUN!T2 -> 7
A37: TOTAL CARS | E37: TOTAL SALES | K37: AVERAGE | O37: RSL | T37: GV | Y37: GV SOLD
A39: =SUM(Q2:U35) -> 109 | E39: =SUM(V2:Z35) -> 12310 | K39: =E39/A39 -> 112.93578 | O39: =SUM(MON:SUN!Q31) -> 3 | T39: =SUM(MON:SUN!P31) -> 19 | Y39: =SUM(MON:SUN!S19) -> 6
O41: =SUM(MON:SUN!J31) -> 215 | T41: =SUM(MON:SUN!K31) -> 1169.3 | Y41: =SUM(MON:SUN!T19) -> 2350
A43: TOTAL CASH | F43: TOTAL CARD | K43: TOTAL RSL | P43: TOTAL GV | U43: STAFF HRS | Z43: no. staff
A45: =SUM(H2,H7,H12,H17,H22,H27,H32) -> 1455 | F45: =SUM(,H3,H8,H13,H18,H23,H28,H33) -> 10640 | K45: =SUM(H5,H10,H15,H20,H25,H30,H35) -> 215 | P45: =SUM(H4,H9,H14,H19,H24,H29,H34) -> 1169.3 | U45: =SUM(E6,E11,E16,E21,E26,E31,E36) -> 299.66667 | Z45: =SUM(L6,L11,L16,L21,L26,L31,L36) -> 40
A49: =A45/E39 -> 0.11819659 | F49: =F45/E39 -> 0.86433794 | K49: =K45/E39 -> 0.017465475 | P49: =P45/E39 -> 0.094987815 | U49: =U45/7 -> 42.809524 | Z49: =U45/Z45 -> 7.4916667

Sheet Sheet2
A1: Reg No | B1: Mobile
A2: EOL27E | B2: 404113366
A3: CDS89H | B3: 447514956
A5: 88FATE | B5: 449988448
A6: DP469 | B6: 408417669
